Workbook

Sheet READ ME
B1: Ashok Leyland model — clean-up READ ME
B2: Structure, formatting and audit conventions. No number in this workbook was changed.
B4: COLOUR CODE
B5: 1,234 | C5: Blue — Hardcoded input. Typed number. Change these freely.
B6: 1,234 | C6: Blue on amber — Formula built only from hardcoded numbers, e.g. =8835+8903+12146. An input in disguise.
B7: 1,234 | C7: Black — Formula referencing cells on the same sheet. Do not overtype.
B8: 1,234 | C8: Black on amber — Formula with a hardcoded plug inside it, e.g. =+C41-1722.094 or =+AH20*0.21. Undocumented assumption — audit these first.
B9: 1,234 | C9: Green — Link to another sheet in this workbook.
B10: 1,234 | C10: Red on amber — Broken formula returning #REF!. Source has been deleted.
B12: CELL COUNTS BY TYPE
B13: Sheet | C13: Main Model | D13: New Qrtrly - Ind AS | E13: New Qrtrly | F13: DCF | G13: Comments
B14: Hardcoded inputs | C14: 2833 | D14: 870 | E14: 564 | F14: 19 | G14: 401
B15: Formulas made only of hardcodes | C15: 592 | D15: 137 | E15: 136 | F15: 8 | G15: 8
B16: Clean formulas | C16: 15502 | D16: 2806 | E16: 1576 | F16: 91 | G16: 108
B17: Formulas with a hardcoded plug | C17: 535 | D17: 173 | E17: 37 | F17: 0 | G17: 10
B18: Cross-sheet links | C18: 0 | D18: 91 | E18: 3 | F18: 23 | G18: 0
B19: Broken (#REF!) | C19: 318 | D19: 0 | E19: 0 | F19: 0 | G19: 3
B20: Text | C20: 995 | D20: 416 | E20: 165 | F20: 55 | G20: 692
B22: WHAT CHANGED
B23: Quarters vs years | C23: On "New Qrtrly - Ind AS" the annual columns (FY16, FY17, FY26E) no longer sit inside the run of quarters. They are in their own ANNUAL block to the right.
B24: Estimates vs actuals | C24: The interleaved E / A pairs are split into two blocks: QUARTERLY — ACTUALS (49 columns) and QUARTERLY — BSe ESTIMATES (30 columns), each in date order. The side-by-side comparison you lose is rebuilt live on the "Est vs Act" tab.
B25: Workings | C25: Unheaded scratch columns (old CE, CF, CH, CI, CJ, CK) are parked in a WORKINGS / CHECKS block at the far right instead of trailing the estimates.
B26: Blank rows | C26: All blank rows removed. Content is now grouped under 15 titled section bands.
B27: Duplicate labels | C27: 8 empty legacy label rows deleted (pre-Ind-AS margin and cost-ratio lines that were superseded by the rows below them). Listed on the Issues tab.
B28: Orphan rows | C28: Four unlabelled rows that carried live formulas are grouped under ORPHAN CALC ROWS. Nothing references them.
B29: Headers | C29: Two-row header: fiscal year over period, frozen. A small grey row records each column's original letter, so anything can be traced back to the source file.
B30: Number formats | C30: One consistent format per row, derived from the values in that row. Rows formatted as % but holding non-percentage values were reformatted — flagged on the Issues tab.
B31: Formulas | C31: All 3,207 formulas on the restructured sheet were re-pointed to the new addresses. Every one of the 9,416 data cells was checked against the original: zero differences. The other sheets were not moved at all — 277,641 cells checked, zero differences.
B32: Not changed | C32: No value, no formula logic, no estimate. The 738 pre-existing formula errors were left exactly as they were rather than silently patched — they are itemised on the Issues tab.
B34: TABS
B35: READ ME | C35: This page.
B36: Issues | C36: Everything found that needs your judgement, not mine.
B37: New Qrtrly - Ind AS | C37: Restructured quarterly model. The live sheet.
B38: Est vs Act | C38: Reported vs BSe by quarter. All links, no typed numbers.
B39: Main Model | C39: Annual model FY1993-FY2029E. Colour-coded only; nothing moved.
B40: New Qrtrly | C40: Legacy pre-Ind-AS quarterly sheet, FY07 onward. Colour-coded only.
B41: DCF, Comments, Industry launches and cap | C41: Untouched apart from colour coding.

Sheet Issues
B1: Issues found — for your call, not mine
B2: Nothing below was changed in the workbook. Each is preserved exactly as it was in the source file.
B4: Sheet | C4: Where | D4: What
B5: New Qrtrly - Ind AS (restructured) | C5: row 4: "H / MCVs" | D5: Row mixes magnitudes — it holds both sub-1 ratios and figures in the thousands, so it is carrying two different quantities on one line. Shown to 2dp so both are readable; values unchanged.
B6: New Qrtrly - Ind AS (restructured) | C6: row 5: "LCVs" | D6: Row mixes magnitudes — it holds both sub-1 ratios and figures in the thousands, so it is carrying two different quantities on one line. Shown to 2dp so both are readable; values unchanged.
B7: New Qrtrly - Ind AS (restructured) | C7: row 6: "Total CVs" | D7: Row mixes magnitudes — it holds both sub-1 ratios and figures in the thousands, so it is carrying two different quantities on one line. Shown to 2dp so both are readable; values unchanged.
B8: New Qrtrly - Ind AS (restructured) | C8: row 7: "Product mix (%)" | D8: Row mixes magnitudes — it holds both sub-1 ratios and figures in the thousands, so it is carrying two different quantities on one line. Shown to 2dp so both are readable; values unchanged.
B9: New Qrtrly - Ind AS (restructured) | C9: row 11: "H / MCVs" | D9: Row mixes magnitudes — it holds both sub-1 ratios and figures in the thousands, so it is carrying two different quantities on one line. Shown to 2dp so both are readable; values unchanged.
B10: New Qrtrly - Ind AS (restructured) | C10: row 17: "Discounts" | D10: Row mixes magnitudes — it holds both sub-1 ratios and figures in the thousands, so it is carrying two different quantities on one line. Shown to 2dp so both are readable; values unchanged.
B11: New Qrtrly - Ind AS (restructured) | C11: row 22: "Net sales" | D11: Row mixes magnitudes — it holds both sub-1 ratios and figures in the thousands, so it is carrying two different quantities on one line. Shown to 2dp so both are readable; values unchanged.
B12: New Qrtrly - Ind AS (restructured) | C12: row 31: "EBITDA" | D12: Row mixes magnitudes — it holds both sub-1 ratios and figures in the thousands, so it is carrying two different quantities on one line. Shown to 2dp so both are readable; values unchanged.
B13: New Qrtrly - Ind AS (restructured) | C13: row 38: "Exceptional income" | D13: Row mixes magnitudes — it holds both sub-1 ratios and figures in the thousands, so it is carrying two different quantities on one line. Shown to 2dp so both are readable; values unchanged.
B14: New Qrtrly - Ind AS (restructured) | C14: row 42: "PAT (pre exceptionals)" | D14: Row mixes magnitudes — it holds both sub-1 ratios and figures in the thousands, so it is carrying two different quantities on one line. Shown to 2dp so both are readable; values unchanged.
B15: New Qrtrly - Ind AS (restructured) | C15: row 46: "" | D15: Row mixes magnitudes — it holds both sub-1 ratios and figures in the thousands, so it is carrying two different quantities on one line. Shown to 2dp so both are readable; values unchanged.
... B41: All sheets | C41: Amber-shaded cells | D41: Formula contains a hardcoded number that is not a unit conversion — e.g. =+C41-1722.094, =+AH20*0.21, =H22*91%*88%/H6*1000000. Each is an undocumented assumption or plug. Count in this workbook: see the READ ME tab.

Sheet Industry launches and cap
A2: 41401
A3: Daimler Trucks -
A4: Still a niche player – BUT – has strong market shares in certain segments – eg – 30% market share in the Kerala construction market (small). Has 8-9% market share in Mumbai – which accounts for around 8-9% of overall CV sales.
A5: 40% of all trucks bought are through Bharat Benz Financial services
A6: Daimler trucks – launched 3 new models – 914 Rigid, 1214 construction and 1217 tipper. Will launch 6 more models end of 2013 – taking its overall tally to 12. Will launch overall 17 trucks – will have 110 dealers by that time

Sheet Est vs Act
A1: Ashok Leyland — reported vs BSe estimate
A2: Rebuilt from the restructured quarterly sheet. Every figure is a live link — nothing is typed. This replaces the side-by-side E/A columns that used to be interleaved.
A4: Quarter | B4: Total CVs (nos.) | E4: Net sales (INR m) | H4: EBITDA (INR m) | K4: EBITDA margin (%) | N4: PAT pre-except. (INR m)
B5: BSe | C5: Act | D5: Var | E5: BSe | F5: Act | G5: Var | H5: BSe | I5: Act | J5: Var | K5: BSe | L5: Act | M5: Var | N5: BSe | O5: Act | P5: Var
A6: 4QFY19 | B6: ='New Qrtrly - Ind AS'!AZ11 -> 59521 | C6: ='New Qrtrly - Ind AS'!U11 -> 59521 | D6: =IFERROR('New Qrtrly - Ind AS'!U11/'New Qrtrly - Ind AS'!AZ11-1,"") -> 0 | E6: ='New Qrtrly - Ind AS'!AZ33 -> 85167.782 | F6: ='New Qrtrly - Ind AS'!U33 -> 88459.3 | G6: =IFERROR('New Qrtrly - Ind AS'!U33/'New Qrtrly - Ind AS'!AZ33-1,"") -> 0.038647456 | H6: ='New Qrtrly - Ind AS'!AZ40 -> 9096.9789 | I6: ='New Qrtrly - Ind AS'!U40 -> 9854.4 | J6: =IFERROR('New Qrtrly - Ind AS'!U40/'New Qrtrly - Ind AS'!AZ40-1,"") -> 0.083260726 | K6: ='New Qrtrly - Ind AS'!AZ61 -> 10.681244 | L6: ='New Qrtrly - Ind AS'!U61 -> 11.140038 | M6: =IFERROR(('New Qrtrly - Ind AS'!U61-'New Qrtrly - Ind AS'!AZ61)*100,"") -> 45.879402 | N6: ='New Qrtrly - Ind AS'!AZ51 -> 5618.9842 | O6: ='New Qrtrly - Ind AS'!U51 -> 6611.66 | P6: =IFERROR('New Qrtrly - Ind AS'!U51/'New Qrtrly - Ind AS'!AZ51-1,"") -> 0.17666464
A7: 1QFY20 | B7: ='New Qrtrly - Ind AS'!BA11 -> 39608 | C7: ='New Qrtrly - Ind AS'!V11 -> 39608 | D7: =IFERROR('New Qrtrly - Ind AS'!V11/'New Qrtrly - Ind AS'!BA11-1,"") -> 0 | E7: ='New Qrtrly - Ind AS'!BA33 -> 58864.87 | F7: ='New Qrtrly - Ind AS'!V33 -> 56838.6 | G7: =IFERROR('New Qrtrly - Ind AS'!V33/'New Qrtrly - Ind AS'!BA33-1,"") -> -0.034422406 | H7: ='New Qrtrly - Ind AS'!BA40 -> 4482.1637 | I7: ='New Qrtrly - Ind AS'!V40 -> 5369.7 | J7: =IFERROR('New Qrtrly - Ind AS'!V40/'New Qrtrly - Ind AS'!BA40-1,"") -> 0.19801514 | K7: ='New Qrtrly - Ind AS'!BA61 -> 7.614327 | L7: ='New Qrtrly - Ind AS'!V61 -> 9.447277 | M7: =IFERROR(('New Qrtrly - Ind AS'!V61-'New Qrtrly - Ind AS'!BA61)*100,"") -> 183.295 | N7: ='New Qrtrly - Ind AS'!BA51 -> 2529.1228 | O7: ='New Qrtrly - Ind AS'!V51 -> 2442.97 | P7: =IFERROR('New Qrtrly - Ind AS'!V51/'New Qrtrly - Ind AS'!BA51-1,"") -> -0.034064299
A8: 2QFY20 | B8: ='New Qrtrly - Ind AS'!BB11 -> 28938 | C8: ='New Qrtrly - Ind AS'!W11 -> 28938 | D8: =IFERROR('New Qrtrly - Ind AS'!W11/'New Qrtrly - Ind AS'!BB11-1,"") -> 0 | E8: ='New Qrtrly - Ind AS'!BB33 -> 40696.311 | F8: ='New Qrtrly - Ind AS'!W33 -> 39295 | G8: =IFERROR('New Qrtrly - Ind AS'!W33/'New Qrtrly - Ind AS'!BB33-1,"") -> -0.034433374 | H8: ='New Qrtrly - Ind AS'!BB40 -> 1812.375 | I8: ='New Qrtrly - Ind AS'!W40 -> 2285.8 | J8: =IFERROR('New Qrtrly - Ind AS'!W40/'New Qrtrly - Ind AS'!BB40-1,"") -> 0.26121805 | K8: ='New Qrtrly - Ind AS'!BB61 -> 4.4534133 | L8: ='New Qrtrly - Ind AS'!W61 -> 5.8170251 | M8: =IFERROR(('New Qrtrly - Ind AS'!W61-'New Qrtrly - Ind AS'!BB61)*100,"") -> 136.36117 | N8: ='New Qrtrly - Ind AS'!BB51 -> 203.20496 | O8: ='New Qrtrly - Ind AS'!W51 -> 874.775 | P8: =IFERROR('New Qrtrly - Ind AS'!W51/'New Qrtrly - Ind AS'!BB51-1,"") -> 3.3048899
A9: 3QFY20 | B9: ='New Qrtrly - Ind AS'!BC11 -> 31200 | C9: ='New Qrtrly - Ind AS'!X11 -> 31200 | D9: =IFERROR('New Qrtrly - Ind AS'!X11/'New Qrtrly - Ind AS'!BC11-1,"") -> 0 | E9: ='New Qrtrly - Ind AS'!BC33 -> 41307.412 | F9: ='New Qrtrly - Ind AS'!X33 -> 40156.5 | G9: =IFERROR('New Qrtrly - Ind AS'!X33/'New Qrtrly - Ind AS'!BC33-1,"") -> -0.027862128 | H9: ='New Qrtrly - Ind AS'!BC40 -> 2490.0682 | I9: ='New Qrtrly - Ind AS'!X40 -> 2251.5 | J9: =IFERROR('New Qrtrly - Ind AS'!X40/'New Qrtrly - Ind AS'!BC40-1,"") -> -0.095807896 | K9: ='New Qrtrly - Ind AS'!BC61 -> 6.0281389 | L9: ='New Qrtrly - Ind AS'!X61 -> 5.6068133 | M9: =IFERROR(('New Qrtrly - Ind AS'!X61-'New Qrtrly - Ind AS'!BC61)*100,"") -> -42.132555 | N9: ='New Qrtrly - Ind AS'!BC51 -> 832.05456 | O9: ='New Qrtrly - Ind AS'!X51 -> 292.69 | P9: =IFERROR('New Qrtrly - Ind AS'!X51/'New Qrtrly - Ind AS'!BC51-1,"") -> -0.6482322
A10: 4QFY20 | B10: ='New Qrtrly - Ind AS'!BD11 -> 25507 | C10: ='New Qrtrly - Ind AS'!Y11 -> 25507 | D10: =IFERROR('New Qrtrly - Ind AS'!Y11/'New Qrtrly - Ind AS'!BD11-1,"") -> 0 | E10: ='New Qrtrly - Ind AS'!BD33 -> 32829.226 | F10: ='New Qrtrly - Ind AS'!Y33 -> 38384.6 | G10: =IFERROR('New Qrtrly - Ind AS'!Y33/'New Qrtrly - Ind AS'!BD33-1,"") -> 0.16922038 | H10: ='New Qrtrly - Ind AS'!BD40 -> 634.08639 | I10: ='New Qrtrly - Ind AS'!Y40 -> 1829.5 | J10: =IFERROR('New Qrtrly - Ind AS'!Y40/'New Qrtrly - Ind AS'!BD40-1,"") -> 1.8852535 | K10: ='New Qrtrly - Ind AS'!BD61 -> 1.9314692 | L10: ='New Qrtrly - Ind AS'!Y61 -> 4.7662344 | M10: =IFERROR(('New Qrtrly - Ind AS'!Y61-'New Qrtrly - Ind AS'!BD61)*100,"") -> 283.47652 | N10: ='New Qrtrly - Ind AS'!BD51 -> -704.13953 | O10: ='New Qrtrly - Ind AS'!Y51 -> -57.725 | P10: =IFERROR('New Qrtrly - Ind AS'!Y51/'New Qrtrly - Ind AS'!BD51-1,"") -> -0.91802051
A11: 1QFY21 | B11: ='New Qrtrly - Ind AS'!BE11 -> 3814 | C11: ='New Qrtrly - Ind AS'!Z11 -> 3814 | D11: =IFERROR('New Qrtrly - Ind AS'!Z11/'New Qrtrly - Ind AS'!BE11-1,"") -> 0 | E11: ='New Qrtrly - Ind AS'!BE33 -> 6313.512 | F11: ='New Qrtrly - Ind AS'!Z33 -> 6508.7 | G11: =IFERROR('New Qrtrly - Ind AS'!Z33/'New Qrtrly - Ind AS'!BE33-1,"") -> 0.030915913 | H11: ='New Qrtrly - Ind AS'!BE40 -> -3069.0815 | I11: ='New Qrtrly - Ind AS'!Z40 -> -3332.4 | J11: =IFERROR('New Qrtrly - Ind AS'!Z40/'New Qrtrly - Ind AS'!BE40-1,"") -> 0.085797162 | K11: ='New Qrtrly - Ind AS'!BE61 -> -48.61132 | L11: ='New Qrtrly - Ind AS'!Z61 -> -51.199164 | M11: =IFERROR(('New Qrtrly - Ind AS'!Z61-'New Qrtrly - Ind AS'!BE61)*100,"") -> -258.78443 | N11: ='New Qrtrly - Ind AS'!BE51 -> -3527.3571 | O11: ='New Qrtrly - Ind AS'!Z51 -> -3875.475 | P11: =IFERROR('New Qrtrly - Ind AS'!Z51/'New Qrtrly - Ind AS'!BE51-1,"") -> 0.09869087
A12: 2QFY21 | B12: ='New Qrtrly - Ind AS'!BF11 -> 19444 | C12: ='New Qrtrly - Ind AS'!AA11 -> 19444 | D12: =IFERROR('New Qrtrly - Ind AS'!AA11/'New Qrtrly - Ind AS'!BF11-1,"") -> 0 | E12: ='New Qrtrly - Ind AS'!BF33 -> 31522.655 | F12: ='New Qrtrly - Ind AS'!AA33 -> 28365.8 | G12: =IFERROR('New Qrtrly - Ind AS'!AA33/'New Qrtrly - Ind AS'!BF33-1,"") -> -0.10014558 | H12: ='New Qrtrly - Ind AS'!BF40 -> 1087.2495 | I12: ='New Qrtrly - Ind AS'!AA40 -> 804.3 | J12: =IFERROR('New Qrtrly - Ind AS'!AA40/'New Qrtrly - Ind AS'!BF40-1,"") -> -0.26024338 | K12: ='New Qrtrly - Ind AS'!BF61 -> 3.4491051 | L12: ='New Qrtrly - Ind AS'!AA61 -> 2.8354568 | M12: =IFERROR(('New Qrtrly - Ind AS'!AA61-'New Qrtrly - Ind AS'!BF61)*100,"") -> -61.364827 | N12: ='New Qrtrly - Ind AS'!BF51 -> -561.92537 | O12: ='New Qrtrly - Ind AS'!AA51 -> -1453.95 | P12: =IFERROR('New Qrtrly - Ind AS'!AA51/'New Qrtrly - Ind AS'!BF51-1,"") -> 1.5874432
A13: 3QFY21 | B13: ='New Qrtrly - Ind AS'!BG11 -> 33410 | C13: ='New Qrtrly - Ind AS'!AB11 -> 33410 | D13: =IFERROR('New Qrtrly - Ind AS'!AB11/'New Qrtrly - Ind AS'!BG11-1,"") -> 0 | E13: ='New Qrtrly - Ind AS'!BG33 -> 50689.644 | F13: ='New Qrtrly - Ind AS'!AB33 -> 48135.1 | G13: =IFERROR('New Qrtrly - Ind AS'!AB33/'New Qrtrly - Ind AS'!BG33-1,"") -> -0.050395772 | H13: ='New Qrtrly - Ind AS'!BG40 -> 4246.5485 | I13: ='New Qrtrly - Ind AS'!AB40 -> 2537.9 | J13: =IFERROR('New Qrtrly - Ind AS'!AB40/'New Qrtrly - Ind AS'!BG40-1,"") -> -0.4023617 | K13: ='New Qrtrly - Ind AS'!BG61 -> 8.3775465 | L13: ='New Qrtrly - Ind AS'!AB61 -> 5.2724519 | M13: =IFERROR(('New Qrtrly - Ind AS'!AB61-'New Qrtrly - Ind AS'!BG61)*100,"") -> -310.50946 | N13: ='New Qrtrly - Ind AS'!BG51 -> 1467.5839 | O13: ='New Qrtrly - Ind AS'!AB51 -> 151.425 | P13: =IFERROR('New Qrtrly - Ind AS'!AB51/'New Qrtrly - Ind AS'!BG51-1,"") -> -0.89682021
A14: 4QFY21 | B14: ='New Qrtrly - Ind AS'!BH11 -> 44060 | C14: ='New Qrtrly - Ind AS'!AC11 -> 44060 | D14: =IFERROR('New Qrtrly - Ind AS'!AC11/'New Qrtrly - Ind AS'!BH11-1,"") -> 0 | E14: ='New Qrtrly - Ind AS'!BH33 -> 65065.948 | F14: ='New Qrtrly - Ind AS'!AC33 -> 70004.9 | G14: =IFERROR('New Qrtrly - Ind AS'!AC33/'New Qrtrly - Ind AS'!BH33-1,"") -> 0.075906865 | H14: ='New Qrtrly - Ind AS'!BH40 -> 4845.9594 | I14: ='New Qrtrly - Ind AS'!AC40 -> 5341.6 | J14: =IFERROR('New Qrtrly - Ind AS'!AC40/'New Qrtrly - Ind AS'!BH40-1,"") -> 0.10227915 | K14: ='New Qrtrly - Ind AS'!BH61 -> 7.4477658 | L14: ='New Qrtrly - Ind AS'!AC61 -> 7.630323 | M14: =IFERROR(('New Qrtrly - Ind AS'!AC61-'New Qrtrly - Ind AS'!BH61)*100,"") -> 18.255726 | N14: ='New Qrtrly - Ind AS'!BH51 -> 1747.1716 | O14: ='New Qrtrly - Ind AS'!AC51 -> 2131.575 | P14: =IFERROR('New Qrtrly - Ind AS'!AC51/'New Qrtrly - Ind AS'!BH51-1,"") -> 0.2200147
A15: 1QFY22 | B15: ='New Qrtrly - Ind AS'!BI11 -> 17987 | C15: ='New Qrtrly - Ind AS'!AD11 -> 17987 | D15: =IFERROR('New Qrtrly - Ind AS'!AD11/'New Qrtrly - Ind AS'!BI11-1,"") -> 0 | E15: ='New Qrtrly - Ind AS'!BI33 -> 27149.778 | F15: ='New Qrtrly - Ind AS'!AD33 -> 29509.9 | G15: =IFERROR('New Qrtrly - Ind AS'!AD33/'New Qrtrly - Ind AS'!BI33-1,"") -> 0.086929688 | H15: ='New Qrtrly - Ind AS'!BI40 -> -1019.8021 | I15: ='New Qrtrly - Ind AS'!AD40 -> -1401 | J15: =IFERROR('New Qrtrly - Ind AS'!AD40/'New Qrtrly - Ind AS'!BI40-1,"") -> 0.37379594 | K15: ='New Qrtrly - Ind AS'!BI61 -> -3.7562079 | L15: ='New Qrtrly - Ind AS'!AD61 -> -4.7475593 | M15: =IFERROR(('New Qrtrly - Ind AS'!AD61-'New Qrtrly - Ind AS'!BI61)*100,"") -> -99.13514 | N15: ='New Qrtrly - Ind AS'!BI51 -> -2463.8615 | O15: ='New Qrtrly - Ind AS'!AD51 -> -2810.3 | P15: =IFERROR('New Qrtrly - Ind AS'!AD51/'New Qrtrly - Ind AS'!BI51-1,"") -> 0.14060795
A16: 2QFY22 | B16: ='New Qrtrly - Ind AS'!BJ11 -> 27543 | C16: ='New Qrtrly - Ind AS'!AE11 -> 27543 | D16: =IFERROR('New Qrtrly - Ind AS'!AE11/'New Qrtrly - Ind AS'!BJ11-1,"") -> 0 | E16: ='New Qrtrly - Ind AS'!BJ33 -> 46091.455 | F16: ='New Qrtrly - Ind AS'!AE33 -> 44578.5 | G16: =IFERROR('New Qrtrly - Ind AS'!AE33/'New Qrtrly - Ind AS'!BJ33-1,"") -> -0.032825063 | H16: ='New Qrtrly - Ind AS'!BJ40 -> 1799.4125 | I16: ='New Qrtrly - Ind AS'!AE40 -> 1346.9 | J16: =IFERROR('New Qrtrly - Ind AS'!AE40/'New Qrtrly - Ind AS'!BJ40-1,"") -> -0.25147789 | K16: ='New Qrtrly - Ind AS'!BJ61 -> 3.9040045 | L16: ='New Qrtrly - Ind AS'!AE61 -> 3.0214117 | M16: =IFERROR(('New Qrtrly - Ind AS'!AE61-'New Qrtrly - Ind AS'!BJ61)*100,"") -> -88.259279 | N16: ='New Qrtrly - Ind AS'!BJ51 -> -420.41128 | O16: ='New Qrtrly - Ind AS'!AE51 -> -831.825 | P16: =IFERROR('New Qrtrly - Ind AS'!AE51/'New Qrtrly - Ind AS'!BJ51-1,"") -> 0.97859818
A17: 3QFY22 | B17: ='New Qrtrly - Ind AS'!BK11 -> 34077 | C17: ='New Qrtrly - Ind AS'!AF11 -> 34077 | D17: =IFERROR('New Qrtrly - Ind AS'!AF11/'New Qrtrly - Ind AS'!BK11-1,"") -> 0 | E17: ='New Qrtrly - Ind AS'!BK33 -> 56808.43 | F17: ='New Qrtrly - Ind AS'!AF33 -> 55351.6 | G17: =IFERROR('New Qrtrly - Ind AS'!AF33/'New Qrtrly - Ind AS'!BK33-1,"") -> -0.025644612 | H17: ='New Qrtrly - Ind AS'!BK40 -> 2952.3221 | I17: ='New Qrtrly - Ind AS'!AF40 -> 2238.9 | J17: =IFERROR('New Qrtrly - Ind AS'!AF40/'New Qrtrly - Ind AS'!BK40-1,"") -> -0.24164778 | K17: ='New Qrtrly - Ind AS'!BK61 -> 5.1969788 | L17: ='New Qrtrly - Ind AS'!AF61 -> 4.0448695 | M17: =IFERROR(('New Qrtrly - Ind AS'!AF61-'New Qrtrly - Ind AS'!BK61)*100,"") -> -115.21093 | N17: ='New Qrtrly - Ind AS'!BK51 -> 337.62545 | O17: ='New Qrtrly - Ind AS'!AF51 -> -257.55 | P17: =IFERROR('New Qrtrly - Ind AS'!AF51/'New Qrtrly - Ind AS'!BK51-1,"") -> -1.7628276
A18: 4QFY22 | B18: ='New Qrtrly - Ind AS'!BL11 -> 48719 | C18: ='New Qrtrly - Ind AS'!AG11 -> 48719 | D18: =IFERROR('New Qrtrly - Ind AS'!AG11/'New Qrtrly - Ind AS'!BL11-1,"") -> 0 | E18: ='New Qrtrly - Ind AS'!BL33 -> 81508.784 | F18: ='New Qrtrly - Ind AS'!AG33 -> 87442.9 | G18: =IFERROR('New Qrtrly - Ind AS'!AG33/'New Qrtrly - Ind AS'!BL33-1,"") -> 0.07280339 | H18: ='New Qrtrly - Ind AS'!BL40 -> 5809.3008 | I18: ='New Qrtrly - Ind AS'!AG40 -> 7760.4 | J18: =IFERROR('New Qrtrly - Ind AS'!AG40/'New Qrtrly - Ind AS'!BL40-1,"") -> 0.33585785 | K18: ='New Qrtrly - Ind AS'!BL61 -> 7.1272082 | L18: ='New Qrtrly - Ind AS'!AG61 -> 8.87482 | M18: =IFERROR(('New Qrtrly - Ind AS'!AG61-'New Qrtrly - Ind AS'!BL61)*100,"") -> 174.76118 | N18: ='New Qrtrly - Ind AS'!BL51 -> 2372.5105 | O18: ='New Qrtrly - Ind AS'!AG51 -> 5486.75 | P18: =IFERROR('New Qrtrly - Ind AS'!AG51/'New Qrtrly - Ind AS'!BL51-1,"") -> 1.3126346
A19: 1QFY23 | B19: ='New Qrtrly - Ind AS'!BM11 -> 39651 | C19: ='New Qrtrly - Ind AS'!AH11 -> 39651 | D19: =IFERROR('New Qrtrly - Ind AS'!AH11/'New Qrtrly - Ind AS'!BM11-1,"") -> 0 | E19: ='New Qrtrly - Ind AS'!BM33 -> 71167.274 | F19: ='New Qrtrly - Ind AS'!AH33 -> 72228.5 | G19: =IFERROR('New Qrtrly - Ind AS'!AH33/'New Qrtrly - Ind AS'!BM33-1,"") -> 0.014911712 | H19: ='New Qrtrly - Ind AS'!BM40 -> 4545.1276 | I19: ='New Qrtrly - Ind AS'!AH40 -> 3202.8 | J19: =IFERROR('New Qrtrly - Ind AS'!AH40/'New Qrtrly - Ind AS'!BM40-1,"") -> -0.29533331 | K19: ='New Qrtrly - Ind AS'!BM61 -> 6.3865416 | L19: ='New Qrtrly - Ind AS'!AH61 -> 4.4342607 | M19: =IFERROR(('New Qrtrly - Ind AS'!AH61-'New Qrtrly - Ind AS'!BM61)*100,"") -> -195.22809 | N19: ='New Qrtrly - Ind AS'!BM51 -> 1424.5893 | O19: ='New Qrtrly - Ind AS'!AH51 -> 582.925 | P19: =IFERROR('New Qrtrly - Ind AS'!AH51/'New Qrtrly - Ind AS'!BM51-1,"") -> -0.59081189
A20: 2QFY23 | B20: ='New Qrtrly - Ind AS'!BN11 -> 45295 | C20: ='New Qrtrly - Ind AS'!AI11 -> 45295 | D20: =IFERROR('New Qrtrly - Ind AS'!AI11/'New Qrtrly - Ind AS'!BN11-1,"") -> 0 | E20: ='New Qrtrly - Ind AS'!BN33 -> 82922.193 | F20: ='New Qrtrly - Ind AS'!AI33 -> 82659.5 | G20: =IFERROR('New Qrtrly - Ind AS'!AI33/'New Qrtrly - Ind AS'!BN33-1,"") -> -0.0031679403 | H20: ='New Qrtrly - Ind AS'!BN40 -> 4956.3502 | I20: ='New Qrtrly - Ind AS'!AI40 -> 5373.4 | J20: =IFERROR('New Qrtrly - Ind AS'!AI40/'New Qrtrly - Ind AS'!BN40-1,"") -> 0.084144529 | K20: ='New Qrtrly - Ind AS'!BN61 -> 5.9771095 | L20: ='New Qrtrly - Ind AS'!AI61 -> 6.5006442 | M20: =IFERROR(('New Qrtrly - Ind AS'!AI61-'New Qrtrly - Ind AS'!BN61)*100,"") -> 52.353471 | N20: ='New Qrtrly - Ind AS'!BN51 -> 1866.4452 | O20: ='New Qrtrly - Ind AS'!AI51 -> 1931.375 | P20: =IFERROR('New Qrtrly - Ind AS'!AI51/'New Qrtrly - Ind AS'!BN51-1,"") -> 0.034787965
A21: 3QFY23 | B21: ='New Qrtrly - Ind AS'!BO11 -> 47562 | C21: ='New Qrtrly - Ind AS'!AJ11 -> 47562 | D21: =IFERROR('New Qrtrly - Ind AS'!AJ11/'New Qrtrly - Ind AS'!BO11-1,"") -> 0 | E21: ='New Qrtrly - Ind AS'!BO33 -> 87924.937 | F21: ='New Qrtrly - Ind AS'!AJ33 -> 90296.7 | G21: =IFERROR('New Qrtrly - Ind AS'!AJ33/'New Qrtrly - Ind AS'!BO33-1,"") -> 0.026974866 | H21: ='New Qrtrly - Ind AS'!BO40 -> 6631.3187 | I21: ='New Qrtrly - Ind AS'!AJ40 -> 7973.4 | J21: =IFERROR('New Qrtrly - Ind AS'!AJ40/'New Qrtrly - Ind AS'!BO40-1,"") -> 0.20238527 | K21: ='New Qrtrly - Ind AS'!BO61 -> 7.5420228 | L21: ='New Qrtrly - Ind AS'!AJ61 -> 8.830223 | M21: =IFERROR(('New Qrtrly - Ind AS'!AJ61-'New Qrtrly - Ind AS'!BO61)*100,"") -> 128.82003 | N21: ='New Qrtrly - Ind AS'!BO51 -> 2989.9231 | O21: ='New Qrtrly - Ind AS'!AJ51 -> 3561.35 | P21: =IFERROR('New Qrtrly - Ind AS'!AJ51/'New Qrtrly - Ind AS'!BO51-1,"") -> 0.19111758
A22: 4QFY23 | B22: ='New Qrtrly - Ind AS'!BP11 -> 59697 | C22: ='New Qrtrly - Ind AS'!AK11 -> 59697 | D22: =IFERROR('New Qrtrly - Ind AS'!AK11/'New Qrtrly - Ind AS'!BP11-1,"") -> 0 | E22: ='New Qrtrly - Ind AS'!BP33 -> 114695.08 | F22: ='New Qrtrly - Ind AS'!AK33 -> 116256.7 | G22: =IFERROR('New Qrtrly - Ind AS'!AK33/'New Qrtrly - Ind AS'!BP33-1,"") -> 0.013615403 | H22: ='New Qrtrly - Ind AS'!BP40 -> 12264.194 | I22: ='New Qrtrly - Ind AS'!AK40 -> 12757.4 | J22: =IFERROR('New Qrtrly - Ind AS'!AK40/'New Qrtrly - Ind AS'!BP40-1,"") -> 0.040215096 | K22: ='New Qrtrly - Ind AS'!BP61 -> 10.692869 | L22: ='New Qrtrly - Ind AS'!AK61 -> 10.973475 | M22: =IFERROR(('New Qrtrly - Ind AS'!AK61-'New Qrtrly - Ind AS'!BP61)*100,"") -> 28.060645 | N22: ='New Qrtrly - Ind AS'!BP51 -> 6904.936 | O22: ='New Qrtrly - Ind AS'!AK51 -> 7090.875 | P22: =IFERROR('New Qrtrly - Ind AS'!AK51/'New Qrtrly - Ind AS'!BP51-1,"") -> 0.026928421
A23: 1QFY24 | B23: ='New Qrtrly - Ind AS'!BQ11 -> 41329 | C23: ='New Qrtrly - Ind AS'!AL11 -> 41329 | D23: =IFERROR('New Qrtrly - Ind AS'!AL11/'New Qrtrly - Ind AS'!BQ11-1,"") -> 0 | E23: ='New Qrtrly - Ind AS'!BQ33 -> 80486.007 | F23: ='New Qrtrly - Ind AS'!AL33 -> 81892.9 | G23: =IFERROR('New Qrtrly - Ind AS'!AL33/'New Qrtrly - Ind AS'!BQ33-1,"") -> 0.017479971 | H23: ='New Qrtrly - Ind AS'!BQ40 -> 6140.5297 | I23: ='New Qrtrly - Ind AS'!AL40 -> 8207.5 | J23: =IFERROR('New Qrtrly - Ind AS'!AL40/'New Qrtrly - Ind AS'!BQ40-1,"") -> 0.33661107 | K23: ='New Qrtrly - Ind AS'!BQ61 -> 7.6293134 | L23: ='New Qrtrly - Ind AS'!AL61 -> 10.022236 | M23: =IFERROR(('New Qrtrly - Ind AS'!AL61-'New Qrtrly - Ind AS'!BQ61)*100,"") -> 239.2923 | N23: ='New Qrtrly - Ind AS'!BQ51 -> 2618.3708 | O23: ='New Qrtrly - Ind AS'!AL51 -> 5768.625 | P23: =IFERROR('New Qrtrly - Ind AS'!AL51/'New Qrtrly - Ind AS'!BQ51-1,"") -> 1.2031352
A24: 2QFY24 | B24: ='New Qrtrly - Ind AS'!BR11 -> 49846 | C24: ='New Qrtrly - Ind AS'!AM11 -> 49846 | D24: =IFERROR('New Qrtrly - Ind AS'!AM11/'New Qrtrly - Ind AS'!BR11-1,"") -> 0 | E24: ='New Qrtrly - Ind AS'!BR33 -> 96793.845 | F24: ='New Qrtrly - Ind AS'!AM33 -> 96380.4 | G24: =IFERROR('New Qrtrly - Ind AS'!AM33/'New Qrtrly - Ind AS'!BR33-1,"") -> -0.0042713985 | H24: ='New Qrtrly - Ind AS'!BR40 -> 10466.4 | I24: ='New Qrtrly - Ind AS'!AM40 -> 10797.9 | J24: =IFERROR('New Qrtrly - Ind AS'!AM40/'New Qrtrly - Ind AS'!BR40-1,"") -> 0.031672809 | K24: ='New Qrtrly - Ind AS'!BR61 -> 10.813084 | L24: ='New Qrtrly - Ind AS'!AM61 -> 11.203419 | M24: =IFERROR(('New Qrtrly - Ind AS'!AM61-'New Qrtrly - Ind AS'!BR61)*100,"") -> 39.033501 | N24: ='New Qrtrly - Ind AS'!BR51 -> 5821.4798 | O24: ='New Qrtrly - Ind AS'!AM51 -> 5781.7 | P24: =IFERROR('New Qrtrly - Ind AS'!AM51/'New Qrtrly - Ind AS'!BR51-1,"") -> -0.0068332807
A25: 3QFY24 | B25: ='New Qrtrly - Ind AS'!BS11 -> 47241 | C25: ='New Qrtrly - Ind AS'!AN11 -> 47241 | D25: =IFERROR('New Qrtrly - Ind AS'!AN11/'New Qrtrly - Ind AS'!BS11-1,"") -> 0 | E25: ='New Qrtrly - Ind AS'!BS33 -> 89516.598 | F25: ='New Qrtrly - Ind AS'!AN33 -> 92730.1 | G25: =IFERROR('New Qrtrly - Ind AS'!AN33/'New Qrtrly - Ind AS'!BS33-1,"") -> 0.035898392 | H25: ='New Qrtrly - Ind AS'!BS40 -> 9211.4151 | I25: ='New Qrtrly - Ind AS'!AN40 -> 11139.3 | J25: =IFERROR('New Qrtrly - Ind AS'!AN40/'New Qrtrly - Ind AS'!BS40-1,"") -> 0.20929302 | K25: ='New Qrtrly - Ind AS'!BS61 -> 10.290176 | L25: ='New Qrtrly - Ind AS'!AN61 -> 12.012604 | M25: =IFERROR(('New Qrtrly - Ind AS'!AN61-'New Qrtrly - Ind AS'!BS61)*100,"") -> 172.24288 | N25: ='New Qrtrly - Ind AS'!BS51 -> 5082.9906 | O25: ='New Qrtrly - Ind AS'!AN51 -> 5804.725 | P25: =IFERROR('New Qrtrly - Ind AS'!AN51/'New Qrtrly - Ind AS'!BS51-1,"") -> 0.14199012
A26: 4QFY24 | B26: ='New Qrtrly - Ind AS'!BT11 -> 56269 | C26: ='New Qrtrly - Ind AS'!AO11 -> 56269 | D26: =IFERROR('New Qrtrly - Ind AS'!AO11/'New Qrtrly - Ind AS'!BT11-1,"") -> 0 | E26: ='New Qrtrly - Ind AS'!BT33 -> 111003.56 | F26: ='New Qrtrly - Ind AS'!AO33 -> 112666.9 | G26: =IFERROR('New Qrtrly - Ind AS'!AO33/'New Qrtrly - Ind AS'!BT33-1,"") -> 0.01498457 | H26: ='New Qrtrly - Ind AS'!BT40 -> 13735.965 | I26: ='New Qrtrly - Ind AS'!AO40 -> 15921.1 | J26: =IFERROR('New Qrtrly - Ind AS'!AO40/'New Qrtrly - Ind AS'!BT40-1,"") -> 0.15908129 | K26: ='New Qrtrly - Ind AS'!BT61 -> 12.374346 | L26: ='New Qrtrly - Ind AS'!AO61 -> 14.131125 | M26: =IFERROR(('New Qrtrly - Ind AS'!AO61-'New Qrtrly - Ind AS'!BT61)*100,"") -> 175.67781 | N26: ='New Qrtrly - Ind AS'!BT51 -> 8131.1755 | O26: ='New Qrtrly - Ind AS'!AO51 -> 9526.55 | P26: =IFERROR('New Qrtrly - Ind AS'!AO51/'New Qrtrly - Ind AS'!BT51-1,"") -> 0.17160797
A27: 1QFY25 | B27: ='New Qrtrly - Ind AS'!BU11 -> 43893 | C27: ='New Qrtrly - Ind AS'!AP11 -> 43893 | D27: =IFERROR('New Qrtrly - Ind AS'!AP11/'New Qrtrly - Ind AS'!BU11-1,"") -> 0 | E27: ='New Qrtrly - Ind AS'!BU33 -> 86128.818 | F27: ='New Qrtrly - Ind AS'!AP33 -> 85985.3 | G27: =IFERROR('New Qrtrly - Ind AS'!AP33/'New Qrtrly - Ind AS'!BU33-1,"") -> -0.0016663215 | H27: ='New Qrtrly - Ind AS'!BU40 -> 8971.5539 | I27: ='New Qrtrly - Ind AS'!AP40 -> 9108.7 | J27: =IFERROR('New Qrtrly - Ind AS'!AP40/'New Qrtrly - Ind AS'!BU40-1,"") -> 0.015286778 | K27: ='New Qrtrly - Ind AS'!BU61 -> 10.416437 | L27: ='New Qrtrly - Ind AS'!AP61 -> 10.593322 | M27: =IFERROR(('New Qrtrly - Ind AS'!AP61-'New Qrtrly - Ind AS'!BU61)*100,"") -> 17.688563 | N27: ='New Qrtrly - Ind AS'!BU51 -> 5286.0877 | O27: ='New Qrtrly - Ind AS'!AP51 -> 5255.8 | P27: =IFERROR('New Qrtrly - Ind AS'!AP51/'New Qrtrly - Ind AS'!BU51-1,"") -> -0.0057296998
A28: 2QFY25 | B28: ='New Qrtrly - Ind AS'!BV11 -> 45624 | C28: ='New Qrtrly - Ind AS'!AQ11 -> 45624 | D28: =IFERROR('New Qrtrly - Ind AS'!AQ11/'New Qrtrly - Ind AS'!BV11-1,"") -> 0 | E28: ='New Qrtrly - Ind AS'!BV33 -> 87588.76 | F28: ='New Qrtrly - Ind AS'!AQ33 -> 87688.3 | G28: =IFERROR('New Qrtrly - Ind AS'!AQ33/'New Qrtrly - Ind AS'!BV33-1,"") -> 0.0011364425 | H28: ='New Qrtrly - Ind AS'!BV40 -> 9349.6754 | I28: ='New Qrtrly - Ind AS'!AQ40 -> 10173 | J28: =IFERROR('New Qrtrly - Ind AS'!AQ40/'New Qrtrly - Ind AS'!BV40-1,"") -> 0.088059165 | K28: ='New Qrtrly - Ind AS'!BV61 -> 10.674515 | L28: ='New Qrtrly - Ind AS'!AQ61 -> 11.60132 | M28: =IFERROR(('New Qrtrly - Ind AS'!AQ61-'New Qrtrly - Ind AS'!BV61)*100,"") -> 92.680465 | N28: ='New Qrtrly - Ind AS'!BV51 -> 5074.7728 | O28: ='New Qrtrly - Ind AS'!AQ51 -> 6820.65 | P28: =IFERROR('New Qrtrly - Ind AS'!AQ51/'New Qrtrly - Ind AS'!BV51-1,"") -> 0.34403062
A29: 3QFY25 | B29: ='New Qrtrly - Ind AS'!BW11 -> 46404 | C29: ='New Qrtrly - Ind AS'!AR11 -> 46404 | D29: =IFERROR('New Qrtrly - Ind AS'!AR11/'New Qrtrly - Ind AS'!BW11-1,"") -> 0 | E29: ='New Qrtrly - Ind AS'!BW33 -> 90525.254 | F29: ='New Qrtrly - Ind AS'!AR33 -> 94786.7 | G29: =IFERROR('New Qrtrly - Ind AS'!AR33/'New Qrtrly - Ind AS'!BW33-1,"") -> 0.047074664 | H29: ='New Qrtrly - Ind AS'!BW40 -> 10680.942 | I29: ='New Qrtrly - Ind AS'!AR40 -> 12114.3 | J29: =IFERROR('New Qrtrly - Ind AS'!AR40/'New Qrtrly - Ind AS'!BW40-1,"") -> 0.13419775 | K29: ='New Qrtrly - Ind AS'!BW61 -> 11.798853 | L29: ='New Qrtrly - Ind AS'!AR61 -> 12.780591 | M29: =IFERROR(('New Qrtrly - Ind AS'!AR61-'New Qrtrly - Ind AS'!BW61)*100,"") -> 98.173752 | N29: ='New Qrtrly - Ind AS'!BW51 -> 6069.6592 | O29: ='New Qrtrly - Ind AS'!AR51 -> 7617.4 | P29: =IFERROR('New Qrtrly - Ind AS'!AR51/'New Qrtrly - Ind AS'!BW51-1,"") -> 0.25499633
A30: 4QFY25 | B30: ='New Qrtrly - Ind AS'!BX11 -> 59176 | C30: ='New Qrtrly - Ind AS'!AS11 -> 59176 | D30: =IFERROR('New Qrtrly - Ind AS'!AS11/'New Qrtrly - Ind AS'!BX11-1,"") -> 0 | E30: ='New Qrtrly - Ind AS'!BX33 -> 122688.44 | F30: ='New Qrtrly - Ind AS'!AS33 -> 119067.1 | G30: =IFERROR('New Qrtrly - Ind AS'!AS33/'New Qrtrly - Ind AS'!BX33-1,"") -> -0.02951653 | H30: ='New Qrtrly - Ind AS'!BX40 -> 17366.205 | I30: ='New Qrtrly - Ind AS'!AS40 -> 17909.6 | J30: =IFERROR('New Qrtrly - Ind AS'!AS40/'New Qrtrly - Ind AS'!BX40-1,"") -> 0.0312904 | K30: ='New Qrtrly - Ind AS'!BX61 -> 14.15472 | L30: ='New Qrtrly - Ind AS'!AS61 -> 15.041603 | M30: =IFERROR(('New Qrtrly - Ind AS'!AS61-'New Qrtrly - Ind AS'!BX61)*100,"") -> 88.688276 | N30: ='New Qrtrly - Ind AS'!BX51 -> 11322.153 | O30: ='New Qrtrly - Ind AS'!AS51 -> 12561.075 | P30: =IFERROR('New Qrtrly - Ind AS'!AS51/'New Qrtrly - Ind AS'!BX51-1,"") -> 0.10942456
A31: 1QFY26 | B31: ='New Qrtrly - Ind AS'!BY11 -> 44238 | C31: ='New Qrtrly - Ind AS'!AT11 -> 44238 | D31: =IFERROR('New Qrtrly - Ind AS'!AT11/'New Qrtrly - Ind AS'!BY11-1,"") -> 0 | E31: ='New Qrtrly - Ind AS'!BY33 -> 87230.373 | F31: ='New Qrtrly - Ind AS'!AT33 -> 87245.1 | G31: =IFERROR('New Qrtrly - Ind AS'!AT33/'New Qrtrly - Ind AS'!BY33-1,"") -> 0.00016882692 | H31: ='New Qrtrly - Ind AS'!BY40 -> 9685.1171 | I31: ='New Qrtrly - Ind AS'!AT40 -> 9695.5 | J31: =IFERROR('New Qrtrly - Ind AS'!AT40/'New Qrtrly - Ind AS'!BY40-1,"") -> 0.0010720471 | K31: ='New Qrtrly - Ind AS'!BY61 -> 11.102918 | L31: ='New Qrtrly - Ind AS'!AT61 -> 11.112945 | M31: =IFERROR(('New Qrtrly - Ind AS'!AT61-'New Qrtrly - Ind AS'!BY61)*100,"") -> 1.0026687 | N31: ='New Qrtrly - Ind AS'!BY51 -> 5883.582 | O31: ='New Qrtrly - Ind AS'!AT51 -> 5937.3 | P31: =IFERROR('New Qrtrly - Ind AS'!AT51/'New Qrtrly - Ind AS'!BY51-1,"") -> 0.0091301577
A32: 2QFY26 | B32: ='New Qrtrly - Ind AS'!BZ11 -> 49116 | C32: ='New Qrtrly - Ind AS'!AU11 -> 49116 | D32: =IFERROR('New Qrtrly - Ind AS'!AU11/'New Qrtrly - Ind AS'!BZ11-1,"") -> 0 | E32: ='New Qrtrly - Ind AS'!BZ33 -> 96381.045 | F32: ='New Qrtrly - Ind AS'!AU33 -> 95881.8 | G32: =IFERROR('New Qrtrly - Ind AS'!AU33/'New Qrtrly - Ind AS'!BZ33-1,"") -> -0.0051799112 | H32: ='New Qrtrly - Ind AS'!BZ40 -> 11004.122 | I32: ='New Qrtrly - Ind AS'!AU40 -> 11621.6 | J32: =IFERROR('New Qrtrly - Ind AS'!AU40/'New Qrtrly - Ind AS'!BZ40-1,"") -> 0.056113329 | K32: ='New Qrtrly - Ind AS'!BZ61 -> 11.417309 | L32: ='New Qrtrly - Ind AS'!AU61 -> 12.120757 | M32: =IFERROR(('New Qrtrly - Ind AS'!AU61-'New Qrtrly - Ind AS'!BZ61)*100,"") -> 70.344768 | N32: ='New Qrtrly - Ind AS'!BZ51 -> 6449.8855 | O32: ='New Qrtrly - Ind AS'!AU51 -> 8010.6 | P32: =IFERROR('New Qrtrly - Ind AS'!AU51/'New Qrtrly - Ind AS'!BZ51-1,"") -> 0.24197554
A33: 3QFY26 | B33: ='New Qrtrly - Ind AS'!CA11 -> 57625 | C33: ='New Qrtrly - Ind AS'!AV11 -> 57625 | D33: =IFERROR('New Qrtrly - Ind AS'!AV11/'New Qrtrly - Ind AS'!CA11-1,"") -> 0 | E33: ='New Qrtrly - Ind AS'!CA33 -> 114180.03 | F33: ='New Qrtrly - Ind AS'!AV33 -> 115338.5 | G33: =IFERROR('New Qrtrly - Ind AS'!AV33/'New Qrtrly - Ind AS'!CA33-1,"") -> 0.010145958 | H33: ='New Qrtrly - Ind AS'!CA40 -> 14798.77 | I33: ='New Qrtrly - Ind AS'!AV40 -> 15350.2 | J33: =IFERROR('New Qrtrly - Ind AS'!AV40/'New Qrtrly - Ind AS'!CA40-1,"") -> 0.037261907 | K33: ='New Qrtrly - Ind AS'!CA61 -> 12.960908 | L33: ='New Qrtrly - Ind AS'!AV61 -> 13.308826 | M33: =IFERROR(('New Qrtrly - Ind AS'!AV61-'New Qrtrly - Ind AS'!CA61)*100,"") -> 34.791737 | N33: ='New Qrtrly - Ind AS'!CA51 -> 9996.5772 | O33: ='New Qrtrly - Ind AS'!AV51 -> 10273.8 | P33: =IFERROR('New Qrtrly - Ind AS'!AV51/'New Qrtrly - Ind AS'!CA51-1,"") -> 0.02773177
A34: 4QFY26 | B34: ='New Qrtrly - Ind AS'!CB11 -> 69458 | C34: ='New Qrtrly - Ind AS'!AW11 -> 69458 | D34: =IFERROR('New Qrtrly - Ind AS'!AW11/'New Qrtrly - Ind AS'!CB11-1,"") -> 0 | E34: ='New Qrtrly - Ind AS'!CB33 -> 140899.48 | F34: ='New Qrtrly - Ind AS'!AW33 -> 141604.9 | G34: =IFERROR('New Qrtrly - Ind AS'!AW33/'New Qrtrly - Ind AS'!CB33-1,"") -> 0.0050065543 | H34: ='New Qrtrly - Ind AS'!CB40 -> 19806.457 | I34: ='New Qrtrly - Ind AS'!AW40 -> 20655.2 | J34: =IFERROR('New Qrtrly - Ind AS'!AW40/'New Qrtrly - Ind AS'!CB40-1,"") -> 0.042851819 | K34: ='New Qrtrly - Ind AS'!CB61 -> 14.057154 | L34: ='New Qrtrly - Ind AS'!AW61 -> 14.586501 | M34: =IFERROR(('New Qrtrly - Ind AS'!AW61-'New Qrtrly - Ind AS'!CB61)*100,"") -> 52.934653 | N34: ='New Qrtrly - Ind AS'!CB51 -> 13774.843 | O34: ='New Qrtrly - Ind AS'!AW51 -> 14047.2 | P34: =IFERROR('New Qrtrly - Ind AS'!AW51/'New Qrtrly - Ind AS'!CB51-1,"") -> 0.019772062
A35: 1QFY27 | B35: ='New Qrtrly - Ind AS'!CC11 -> 48763 | C35: ='New Qrtrly - Ind AS'!AX11 -> 48763 | D35: =IFERROR('New Qrtrly - Ind AS'!AX11/'New Qrtrly - Ind AS'!CC11-1,"") -> 0 | E35: ='New Qrtrly - Ind AS'!CC33 -> 98419.605 | F35: ='New Qrtrly - Ind AS'!AX33 -> 96343.5 | G35: =IFERROR('New Qrtrly - Ind AS'!AX33/'New Qrtrly - Ind AS'!CC33-1,"") -> -0.021094428 | H35: ='New Qrtrly - Ind AS'!CC40 -> 9576.4542 | I35: ='New Qrtrly - Ind AS'!AX40 -> 9695.3 | J35: =IFERROR('New Qrtrly - Ind AS'!AX40/'New Qrtrly - Ind AS'!CC40-1,"") -> 0.012410209 | K35: ='New Qrtrly - Ind AS'!CC61 -> 9.7302303 | L35: ='New Qrtrly - Ind AS'!AX61 -> 10.063263 | M35: =IFERROR(('New Qrtrly - Ind AS'!AX61-'New Qrtrly - Ind AS'!CC61)*100,"") -> 33.303296 | N35: ='New Qrtrly - Ind AS'!CC51 -> 6004.8407 | O35: ='New Qrtrly - Ind AS'!AX51 -> 6091.1 | P35: =IFERROR('New Qrtrly - Ind AS'!AX51/'New Qrtrly - Ind AS'!CC51-1,"") -> 0.014364968

Sheet Main Model
Y1: =+Y61 -> 1.6825652e-11 | Z1: =+Z35+Z38-Z41-(23279.2) -> 0 | AA1: =+AA35+AA38-AA41-30757.301 -> 0 | AC1: =+AC35+AC38-AC41-23096.1 -> 0 | AD1: =+AD35+AD38-AD41 -> 17791.1 | AE1: =+AE35+AE38-AE41-22381 -> 0 | AF1: =+AF35+AF38-AF41-32504.3 -> 0 | AH1: =+AH21 -> 1986372.7 | AI1: =+AI21 -> 1996354.1 | AJ1: =+AJ21 -> 2021180.7 | AK1: =+AK21 -> 2039068.7 | AL1: =+AL21 -> 2061411.2 | AM1: Multiple | AN1: EBITDA | AO1: Debt | AP1: TP
Z2: =+Z294 -> 113296 | AD2: =+AD38+AD35-AD41 -> 17791.1 | AE2: =+AE38+AE35-AE41 -> 22381 | AF2: =+AF38+AF35-AF41 -> 32504.3 | AG2: =+AG35+AG38-AG41-36150.6 -> 0 | AH2: =+AH35+AH38-AH41-37931.3 -> 0 | AM2: 18 | AN2: =+AVERAGE(AJ47:AK47) -> 60694.811 | AO2: =AVERAGE(AJ115:AK115) -> -81674.808 | AP2: =+ROUND(((AM2*AN2-AO2)/AH84)/5,0)*5 -> 200 | AQ2: =+AP2/AP3-1+AJ137/AP3 -> 0.121498 | AR2: =+ROUND(((AM2*AN2-AO2)/AH84)/1,0)*1 -> 200
B3: FY 1993 | C3: FY 1994 | D3: FY 1995 | E3: FY 1996 | F3: FY 1997 | G3: FY 1998 | H3: FY 1999 | I3: FY2000 | J3: FY2001 | K3: FY2002 | L3: FY2003 | M3: FY2004 | N3: FY2005 | O3: FY2006 | P3: FY2007 | Q3: FY2008 | R3: FY2009 | S3: FY2010 | T3: FY2011 | U3: FY2012 | V3: FY2013 | W3: FY2014 | X3: FY2015 | Y3: FY2016 | Z3: FY2017 | AA3: FY2018 | AB3: FY2019 | AC3: FY2020 | AD3: FY2021 | AE3: FY2022 | AF3: FY2023 | AG3: FY2024 | AH3: FY2025 | AI3: FY2026 | AJ3: FY2027E | AK3: FY2028E | AL3: FY2029E | AO3: CMP | AP3: 181.3
A4: Summary | AO4: Old TP | AP4: 165 | AQ4: =+AP2/AP4-1 -> 0.21212121
AP5: =145/130-1 -> 0.11538462
A6: Income Statement | AE6: =+AE10/12 -> 10693.833 | AF6: =+AF10/12 -> 16017.083 | AG6: =+AG10/12 -> 16223.583 | AH6: =+AH10/12 -> 16257.75 | AI6: =+AI10/12 -> 18369.75 | AJ6: =+AJ10/12 -> 19782.97 | AK6: =+AK10/12 -> 21182.658 | AL6: =+AL10/12 -> 22525.657
A8: (Rs m) | B8: FY 1993 | C8: FY 1994 | D8: FY 1995 | E8: FY 1996 | F8: FY 1997 | G8: FY 1998 | H8: FY 1999 | I8: FY2000 | J8: FY2001 | K8: FY2002 | L8: FY 2003 | M8: FY2004 | N8: FY 2005 | O8: FY 2006 | P8: FY 2007 | Q8: FY2008 | R8: FY2009 | S8: FY2010 | T8: FY2011 | U8: FY2012 | V8: =+V3 -> FY2013 | W8: =+W3 -> FY2014 | X8: =+X3 -> FY2015 | Y8: =+Y3 -> FY2016 | Z8: =+Z3 -> FY2017 | AA8: =+AA3 -> FY2018 | AB8: =+AB3 -> FY2019 | AC8: =+AC3 -> FY2020 | ... AL8: =+AL3 -> FY2029E
A10: Volumes (Nos) | B10: =+B378 -> 20571 | C10: =+C378 -> 24226 | D10: =+D378 -> 30410 | E10: =+E378 -> 37399 | F10: =+F378 -> 43352 | G10: =+G378 -> 31547 | H10: =+H378 -> 29741 | I10: =+I378 -> 37859 | ... T10: =+T378 -> 94106 | U10: =+U378+U386 -> 101990 | V10: =+V378+V386 -> 114611 | W10: =+W378+W386 -> 89337 | X10: =+X378+X386 -> 104902 | Y10: =+Y378+Y386 -> 140457 | Z10: =+Z378+Z386 -> 145066 | AA10: =+AA378+AA386 -> 174873 | AB10: =+AB378+AB386 -> 197366 | ... AL10: =+AL378+AL386 -> 270307.88
A11: % change YoY | C11: =C10/B10*100-100 -> 17.767731 | D11: =D10/C10*100-100 -> 25.526294 | E11: =E10/D10*100-100 -> 22.982572 | F11: =F10/E10*100-100 -> 15.917538 | G11: =G10/F10*100-100 -> -27.230578 | H11: =H10/G10*100-100 -> -5.7247916 | I11: =I10/H10*100-100 -> 27.295652 | J11: =J10/I10*100-100 -> -14.221189 | ... AL11: =AL10/AK10*100-100 -> 6.3400895
A13: Sales & operational income | B13: =+B436 -> 9544.37 | C13: =+C436 -> 11812.94 | D13: =+D436 -> 15132.92 | E13: =+E436 -> 20097.02 | F13: =+F436 -> 24824.51 | G13: =+G436 -> 20142.802 | H13: =+H436 -> 20450.478 | I13: =+I436 -> 25987.18 | ... AL13: =+AL436 -> 557215.7 | AO13: 33236
A14: % change YoY | C14: =C13/B13*100-100 -> 23.768672 | D14: =D13/C13*100-100 -> 28.104604 | E14: =E13/D13*100-100 -> 32.803319 | F14: =F13/E13*100-100 -> 23.523338 | G14: =G13/F13*100-100 -> -18.859218 | H14: =H13/G13*100-100 -> 1.5274777 | I14: =I13/H13*100-100 -> 27.073702 | J14: =J13/I13*100-100 -> 0.30572767 | ... AL14: =AL13/AK13*100-100 -> 7.5052785 | AO14: =+AO13-AD10 -> -67479
AC15: =174674.7-AC13 -> 0 | AE15: =+AE10/AC10-1 -> 0.024534342 | AO15: =+AO14/5 -> -13495.8
A16: Excise | B16: =+B572 -> 1330.6 | C16: =+C572 -> 1223.45 | D16: =+D572 -> 1791.33 | E16: =+E572 -> 2199.23 | F16: =+F572 -> 3011.55 | G16: =+G572 -> 2454.9 | H16: =+H572 -> 2263.75 | I16: =+I572 -> 3454.64 | ... AL16: =+AL572 -> 0
A17: % of sales | B17: =+B574 -> 13.941203 | C17: =+C574 -> 10.356863 | D17: =+D574 -> 11.837306 | E17: =+E574 -> 10.943065 | F17: =+F574 -> 12.131357 | G17: =+G574 -> 12.18748 | H17: =+H574 -> 11.069423 | I17: =+I574 -> 13.293632 | ... AA17: =+AA574 -> 1.0428241
AN18: Base | AO18: FY19 | AP18: FY20 | AQ18: FY21 | AR18: FY22 | AS18: FY23 | AT18: FY24 | AU18: FY25 | AV18: FY26 | AW18: FY27 | AX18: FY28
A19: Net revenue | B19: =B13-B16 -> 8213.77 | C19: =C13-C16 -> 10589.49 | D19: =D13-D16 -> 13341.59 | E19: =E13-E16 -> 17897.79 | F19: =F13-F16 -> 21812.96 | G19: =G13-G16 -> 17687.902 | H19: =H13-H16 -> 18186.728 | I19: =I13-I16 -> 22532.54 | ... AL19: =AL13-AL16 -> 557215.7 | AN19: Volumes | AO19: =+AB10 -> 197366 | AP19: =+AC10 -> 125253 | AQ19: =+AD10 -> 100715 | AR19: =+AE10 -> 128326 | AS19: =+AF10 -> 192205 | AT19: =+AG10 -> 194683 | AU19: =+AH10 -> 195093 | AV19: =+AI10 -> 220437 | ... AX19: =+AK10 -> 254191.89 | AY19: =+SQRT(AX19/AV19)-1 -> 0.073837584
A20: % change YoY | C20: =C19/B19*100-100 -> 28.923625 | D20: =D19/C19*100-100 -> 25.988976 | E20: =E19/D19*100-100 -> 34.150352 | F20: =F19/E19*100-100 -> 21.875159 | G20: =G19/F19*100-100 -> -18.911044 | H20: =H19/G19*100-100 -> 2.8201582 | I20: =I19/H19*100-100 -> 23.895511 | J20: =J19/I19*100-100 -> -0.055120284 | ... AL20: =AL19/AK19*100-100 -> 7.5052785 | AN20: % Chg YoY | AO20: =+AO19/AA10-1 -> 0.12862477 | AP20: =+AP19/AO19-1 -> -0.36537702 | AQ20: =+AQ19/AP19-1 -> -0.19590748 | AR20: =+AR19/AQ19-1 -> 0.27414983 | AS20: =+AS19/AR19-1 -> 0.49778689 | AT20: =+AT19/AS19-1 -> 0.012892485 | AU20: =+AU19/AT19-1 -> 0.0021059877 | AV20: =+AV19/AU19-1 -> 0.12990727 | AW20: =+AW19/AV19-1 -> 0.076931913 | AX20: =+AX19/AW19-1 -> 0.070752147
A21: ASP | X21: =+X19-135621.836 -> 0 | AC21: =+AC19*1000000/AC10 -> 1394575 | AD21: =+AD19*1000000/AD10 -> 1519282.1 | AE21: =+AE19*1000000/AE10 -> 1690093.2 | AF21: =+AF19*1000000/AF10 -> 1880499.5 | AG21: =+AG19*1000000/AG10 -> 1970743.7 | AH21: =+AH19*1000000/AH10 -> 1986372.7 | AI21: =+AI19*1000000/AI10 -> 1996354.1 | AJ21: =+AJ19*1000000/AJ10 -> 2021180.7 | ... AL21: =+AL19*1000000/AL10 -> 2061411.2 | AN21: ASP | AO21: =+AB22 -> 1472135.5 | AP21: =+AC22 -> 1394575 | AQ21: =+AD22 -> 1519282.1 | AR21: =+AE22 -> 1690093.2 | AS21: =+AF22 -> 1880499.5 | AT21: =+AG22 -> 1970743.7 | AU21: =+AH22 -> 1986372.7 | AV21: =+AI22 -> 1996354.1 | ... AX21: =+AK22 -> 2039068.7 | AY21: =+SQRT(AX21/AV21)-1 -> 0.01064155
A22: Revenue / vehicle | B22: =+B19/B10*1000000 -> 399288.8 | C22: =+C19/C10*1000000 -> 437112.61 | D22: =+D19/D10*1000000 -> 438723.78 | E22: =+E19/E10*1000000 -> 478563.33 | F22: =+F19/F10*1000000 -> 503159.25 | G22: =+G19/G10*1000000 -> 560684.11 | H22: =+H19/H10*1000000 -> 611503.59 | I22: =+I19/I10*1000000 -> 595169.97 | ... R22: =+R19/R10*1000000 -> 1098835.9 | S22: =S19/S10*1000000 -> 1133296.4 | T22: =T19/T10*1000000 -> 1181402.8 | U22: =U19/U10*1000000 -> 1258008.9 | V22: =V19/V10*1000000 -> 1089005.4 | W22: =W19/W10*1000000 -> 1113024.5 | X22: =X19/X10*1000000 -> 1292843.2 | Y22: =Y19/Y10*1000000 -> 1348263.5 | Z22: =Z19/Z10*1000000 -> 1379968.9 | ... AL22: =AL19/AL10*1000000 -> 2061411.2 | AN22: % Chg YoY | AO22: =+AO21/AA22-1 -> -0.019210382 | AP22: =+AP21/AO21-1 -> -0.052685737 | AQ22: =+AQ21/AP21-1 -> 0.089423053 | AR22: =+AR21/AQ21-1 -> 0.1124288 | AS22: =+AS21/AR21-1 -> 0.11266022 | AT22: =+AT21/AS21-1 -> 0.047989514 | AU22: =+AU21/AT21-1 -> 0.0079304737 | AV22: =+AV21/AU21-1 -> 0.005024942 | AW22: =+AW21/AV21-1 -> 0.012435992 | AX22: =+AX21/AW21-1 -> 0.0088502883
X23: =86266.352+13911.872-526.126-X25 -> 0 | Y23: =122521.706+15312.255-5214.366-Y25 -> 670.991 | AA23: =+AA22/Z22-1 -> 0.087683737 | AB23: =+AB22/AA22-1 -> -0.019210382 | AC23: =+AC22/AB22-1 -> -0.052685737 | AD23: =+AD22/AC22-1 -> 0.089423053 | AE23: =+AE22/AD22-1 -> 0.1124288 | AF23: =+AF22/AE22-1 -> 0.11266022 | AG23: =+AG22/AF22-1 -> 0.047989514 | AH23: =+AH22/AG22-1 -> 0.0079304737 | ... AL23: =+AL22/AK22-1 -> 0.010957194 | AN23: Revenue | AO23: =+AO21*AO19/1000000 -> 290549.5 | AP23: =+AP21*AP19/1000000 -> 174674.7 | AQ23: =+AQ21*AQ19/1000000 -> 153014.5 | AR23: =+AR21*AR19/1000000 -> 216882.9 | AS23: =+AS21*AS19/1000000 -> 361441.4 | AT23: =+AT21*AT19/1000000 -> 383670.3 | AU23: =+AU21*AU19/1000000 -> 387527.4 | AV23: =+AV21*AV19/1000000 -> 440070.3 | ... AX23: =+AX21*AX19/1000000 -> 518314.74
AG24: =+AG21/AF21-1 -> 0.047989514 | AH24: =+AH21/AG21-1 -> 0.0079304737 | AI24: =+AI21/AH21-1 -> 0.005024942 | AJ24: =+AJ21/AI21-1 -> 0.012435992 | AQ24: =+AQ21/AP21-1 -> 0.089423053 | AR24: =+AR21/AQ21-1 -> 0.1124288 | AS24: =+AS21/AR21-1 -> 0.11266022 | AT24: =+AT21/AS21-1 -> 0.047989514 | AU24: =+AU21/AT21-1 -> 0.0079304737 | AV24: =+AV21/AU21-1 -> 0.005024942 | AW24: =+AW21/AV21-1 -> 0.012435992 | AX24: =+AX21/AW21-1 -> 0.0088502883
A25: Raw material expenses | B25: =+B565 -> 5960.34 | C25: =+C565 -> 7619.16 | D25: =+D565 -> 9785.26 | E25: =+E565 -> 13034.08 | F25: =+F565 -> 15709.15 | G25: =+G565 -> 12432.96 | H25: =+H565 -> 12799.48 | I25: =+I565 -> 15614.33 | ... AL25: =+AL565 -> 401195.31 | AN25: EBITDA | AO25: =+AO23*AO26 -> 31357.4 | AP25: =+AP23*AP26 -> 11736.5 | AQ25: =+AQ23*AQ26 -> 5351.4 | AR25: =+AR23*AR26 -> 9945.2 | AS25: =+AS23*AS26 -> 29307 | AT25: =+AT23*AT26 -> 46065.8 | AU25: =+AU23*AU26 -> 49305.6 | AV25: =+AV23*AV26 -> 57322.5 | ... AX25: =+AX23*AX26 -> 63844.138 | AY25: =+SQRT(AX25/AV25)-1 -> 0.055353491
A26: % of sales | B26: =B25/B19*100 -> 72.565217 | C26: =C25/C19*100 -> 71.950207 | D26: =D25/D19*100 -> 73.344032 | E26: =E25/E19*100 -> 72.825081 | F26: =F25/F19*100 -> 72.017507 | G26: =G25/G19*100 -> 70.290757 | H26: =H25/H19*100 -> 70.378134 | I26: =I25/I19*100 -> 69.296804 | ... AL26: =AL25/AL19*100 -> 72 | AN26: EBITDA Margin | AO26: =+AB48 -> 0.10792447 | AP26: =+AC48 -> 0.067190612 | AQ26: =+AD48 -> 0.034973156 | AR26: =+AE48 -> 0.04585516 | AS26: =+AF48 -> 0.081083683 | AT26: =+AG48 -> 0.12006611 | AU26: =+AH48 -> 0.12723126 | AV26: =+AI48 -> 0.1302576 | ... AX26: =+AK48 -> 0.12317639
AN27: Non operating items | AO27: =+AB50-AB49-AB53 -> -5814.5 | AP27: =+AC50-AC49-AC53 -> -6559.1 | AQ27: =+AD50-AD49-AD53 -> -9350 | AR27: =+AE50-AE49-AE53 -> -9777.4 | AS27: =+AF50-AF49-AF53+AF54 -> -8203 | AT27: =+AG50-AG49-AG53 -> -7206.8 | AU27: =+AH50-AH49-AH53 -> -6860 | AV27: =+AI50-AI49-AI53 -> -5697.5 | AW27: =+AJ50-AJ49-AJ53 -> -5423.0348 | AX27: =+AK50-AK49-AK53 -> -5383.3649
A28: Mat cost / vehicle | B28: =B25/B10*1000000 -> 289744.79 | C28: =C25/C10*1000000 -> 314503.43 | D28: =D25/D10*1000000 -> 321777.7 | E28: =E25/E10*1000000 -> 348514.13 | F28: =F25/F10*1000000 -> 362362.75 | G28: =G25/G10*1000000 -> 394109.11 | H28: =H25/H10*1000000 -> 430364.82 | I28: =I25/I10*1000000 -> 412433.77 | ... AL28: =AL25/AL10*1000000 -> 1484216.1 | AN28: PBT | AO28: =+AO25+AO27 -> 25542.9 | AP28: =+AP25+AP27 -> 5177.4 | AQ28: =+AQ25+AQ27 -> -3998.6 | AR28: =+AR25+AR27 -> 167.8 | AS28: =+AS25+AS27 -> 21104 | AT28: =+AT25+AT27 -> 38859 | AU28: =+AU25+AU27 -> 42445.6 | AV28: =+AV25+AV27 -> 51625 | ... AX28: =+AX25+AX27 -> 58460.773
AN29: Tax | AO29: =+AB56 -> 5136 | AP29: =+AC56 -> 1224 | AQ29: =+AD56 -> -982.3 | AR29: =+AE56 -> -142.2 | AS29: =+AF56 -> 7302.9 | AT29: =+AG56 -> 11743.1 | AU29: =+AH56 -> 10450 | AV29: =+AI56 -> 12484.9 | ... AX29: =+AK56 -> 14615.193
A30: Gross profit / unit | B30: =(B19-B25)/B10*1000000 -> 109544.02 | C30: =(C19-C25)/C10*1000000 -> 122609.18 | D30: =(D19-D25)/D10*1000000 -> 116946.07 | E30: =(E19-E25)/E10*1000000 -> 130049.2 | F30: =(F19-F25)/F10*1000000 -> 140796.5 | G30: =(G19-G25)/G10*1000000 -> 166575 | H30: =(H19-H25)/H10*1000000 -> 181138.78 | I30: =(I19-I25)/I10*1000000 -> 182736.21 | ... AL30: =(AL19-AL25)/AL10*1000000 -> 577195.14 | AN30: PAT | AO30: =+AO28-AO29 -> 20406.9 | AP30: =+AP28-AP29 -> 3953.4 | AQ30: =+AQ28-AQ29 -> -3016.3 | AR30: =+AR28-AR29 -> 310 | AS30: =+AS28-AS29 -> 13801.1 | AT30: =+AT28-AT29 -> 27115.9 | AU30: =+AU28-AU29+AH59-AH57+AH54 -> 32254.925 | AV30: =+AV28-AV29 -> 39140.1 | AW30: =+AW28-AW29 -> 39091.838 | AX30: =+AX28-AX29 -> 43845.58
AN31: Net debt | AO31: =+AB115 -> -7412.3 | AP31: =+AC115 -> 19588.9 | AQ31: =+AD115 -> 30183 | AR31: =+AE115 -> 12088.7 | AS31: =+AF115 -> -478.8 | AT31: =+AG115 -> -13878.4 | AU31: =+AH115 -> -42429.3 | AV31: =+AI115 -> -59017.2 | ... AX31: =+AK115 -> -93625.428
A32: Manpower costs | B32: =+B607 -> 718.28 | C32: =+C607 -> 934.41 | D32: =+D607 -> 1138.95 | E32: =+E607 -> 1571.62 | F32: =+F607 -> 1864.34 | G32: =+G607 -> 1846.74 | H32: =+H607 -> 2083.88 | I32: =+I607 -> 2286.04 | ... AL32: =+AL607 -> 33444.875 | AN32: Multiple | AP32: =+AM2 -> 18
A33: % of sales | B33: =B32/B19*100 -> 8.7448273 | C33: =C32/C19*100 -> 8.8239377 | D33: =D32/D19*100 -> 8.5368386 | E33: =E32/E19*100 -> 8.7810841 | F33: =F32/F19*100 -> 8.5469372 | G33: =G32/G19*100 -> 10.440696 | H33: =H32/H19*100 -> 11.458246 | I33: =I32/I19*100 -> 10.145505 | ... AL33: =AL32/AL19*100 -> 6.0021416 | AN33: TP | AP33: =+ROUND((AP32*AVERAGE(AW25:AX25)-AVERAGE(AW31:AX31))/$AH$84/5,0)*5 -> 200 | AQ33: =+AP33-AP2 -> 0 | AR33: =+AQ33-AQ2 -> -0.121498 | AS33: =+AR33-AR2 -> -200.1215 | AT33: =+AS33-AS2 -> -200.1215 | AU33: =+AT33-AT2 -> -200.1215 | AV33: =+AU33-AU2 -> -200.1215 | AW33: =+AV33-AV2 -> -200.1215 | AX33: =+AW33-AW2 -> -200.1215
A35: Other variable expenses | B35: =+B584 -> 82.84 | C35: =+C584 -> 132.1 | D35: =+D584 -> 123.6 | E35: =+E584 -> 237.2 | F35: =+F584 -> 295.4 | G35: =+G584 -> 217.18 | H35: =+H584 -> 163.68 | I35: =+I584 -> 230.14 | ... AL35: =+AL584 -> 3900.5099 | AN35: Bull | AO35: =+AO18 -> FY19 | AP35: =+AP18 -> FY20 | AQ35: =+AQ18 -> FY21 | AR35: =+AR18 -> FY22 | AS35: =+AS18 -> FY23 | AT35: =+AT18 -> FY24 | AU35: =+AU18 -> FY25 | AV35: =+AV18 -> FY26 | ... AX35: =+AX18 -> FY28
A36: % of sales | B36: =B35/B19*100 -> 1.0085503 | C36: =C35/C19*100 -> 1.2474633 | D36: =D35/D19*100 -> 0.92642631 | E36: =E35/E19*100 -> 1.3253033 | F36: =F35/F19*100 -> 1.3542408 | G36: =G35/G19*100 -> 1.2278449 | H36: =H35/H19*100 -> 0.89999695 | I36: =I35/I19*100 -> 1.0213673 | ... AL36: =AL35/AL19*100 -> 0.7 | AN36: Volumes | AO36: =+AO19 -> 197366 | AP36: =+AP19 -> 125253 | AQ36: =+AQ19 -> 100715 | AR36: =+AR19 -> 128326 | AS36: =+AS19 -> 192205 | AT36: =+AT19 -> 194683 | AU36: =+AU19 -> 195093 | AV36: =+AV19 -> 220437 | AW36: =+AV36*(1+AW37) -> 242480.7 | AX36: =+AW36*(1+AX37) -> 266728.77 | AY36: =+SQRT(AX36/AV36)-1 -> 0.1
AN37: % Chg YoY | AW37: 0.1 | AX37: 0.1
A38: Other fixed expenses | B38: =B632-B32 -> 827.29 | C38: =C632-C32 -> 1027.32 | D38: =D632-D32 -> 1212.78 | E38: =E632-E32 -> 1643 | F38: =F632-F32 -> 1731.23 | G38: =G632-G32 -> 1647.68 | H38: =H632-H32 -> 1483.97 | I38: =I632-I32 -> 1796.29 | ... AL38: =AL632-AL32 -> 51306.698 | AN38: ASP | AO38: =+AO21 -> 1472135.5 | AP38: =+AP21 -> 1394575 | AQ38: =+AQ21 -> 1519282.1 | AR38: =+AR21 -> 1690093.2 | AS38: =+AS21 -> 1880499.5 | AT38: =+AT21 -> 1970743.7 | AU38: =+AU21 -> 1986372.7 | AV38: =+AV21 -> 1996354.1 | AW38: =+AV38*(1+AW39) -> 2116135.3 | AX38: =+AW38*(1+AX39) -> 2158458 | AY38: =+SQRT(AX38/AV38)-1 -> 0.039807675
A39: % of sales | B39: =B38/B19*100 -> 10.071989 | C39: =C38/C19*100 -> 9.7013171 | D39: =D38/D19*100 -> 9.0902209 | E39: =E38/E19*100 -> 9.1799043 | F39: =F38/F19*100 -> 7.9367037 | G39: =G38/G19*100 -> 9.3152938 | H39: =H38/H19*100 -> 8.1596314 | I39: =I38/I19*100 -> 7.9719819 | ... AL39: =AL38/AL19*100 -> 9.2076906 | AN39: % Chg YoY | AW39: 0.06 | AX39: 0.02
AN40: Revenue | AO40: =+AO38*AO36/1000000 -> 290549.5 | AP40: =+AP38*AP36/1000000 -> 174674.7 | AQ40: =+AQ38*AQ36/1000000 -> 153014.5 | AR40: =+AR38*AR36/1000000 -> 216882.9 | AS40: =+AS38*AS36/1000000 -> 361441.4 | AT40: =+AT38*AT36/1000000 -> 383670.3 | AU40: =+AU38*AU36/1000000 -> 387527.4 | AV40: =+AV38*AV36/1000000 -> 440070.3 | ... AX40: =+AX38*AX36/1000000 -> 575722.85
A41: Expenses capitalised | B41: =+B643 -> 1.3 | C41: =+C643 -> 0.83 | D41: =+D643 -> -0.4 | E41: =+E643 -> 42.29 | F41: =+F643 -> 77.21 | G41: =+G643 -> 4.28 | H41: =+H643 -> 0 | I41: =+I643 -> 2.47 | ... AL41: =+AL643 -> 900 | AN41: EBITDA | AO41: =+AO25 -> 31357.4 | AP41: =+AP25 -> 11736.5 | AQ41: =+AQ25 -> 5351.4 | AR41: =+AR25 -> 9945.2 | AS41: =+AS25 -> 29307 | AT41: =+AT25 -> 46065.8 | AU41: =+AU25 -> 49305.6 | AV41: =+AV25 -> 57322.5 | AW41: =+AW40*AW42 -> 66705.856 | AX41: =+AX40*AX42 -> 77722.585 | AY41: =+SQRT(AX41/AV41)-1 -> 0.16442375
A42: % of sales | B42: =B41/B19*100 -> 0.015827081 | C42: =C41/C19*100 -> 0.0078379601 | D42: =D41/D19*100 -> -0.0029981434 | E42: =E41/E19*100 -> 0.23628616 | F42: =F41/F19*100 -> 0.35396388 | G42: =G41/G19*100 -> 0.02419733 | H42: =H41/H19*100 -> 0 | I42: =I41/I19*100 -> 0.010961924 | ... AL42: =AL41/AL19*100 -> 0.16151734 | AN42: EBITDA Margin | AO42: =+AO41/AO40 -> 0.10792447 | AP42: =+AP41/AP40 -> 0.067190612 | AQ42: =+AQ41/AQ40 -> 0.034973156 | AR42: =+AR41/AR40 -> 0.04585516 | AS42: =+AS41/AS40 -> 0.081083683 | AT42: =+AT41/AT40 -> 0.12006611 | AU42: =+AU41/AU40 -> 0.12723126 | AV42: =+AV41/AV40 -> 0.1302576 | AW42: 0.13 | AX42: 0.135
AN43: Non operating items | AO43: =+AO27 -> -5814.5 | AP43: =+AP27 -> -6559.1 | AQ43: =+AQ27 -> -9350 | AR43: =+AR27 -> -9777.4 | AS43: =+AS27 -> -8203 | AT43: =+AT27 -> -7206.8 | AU43: =+AU27 -> -6860 | AV43: =+AV27 -> -5697.5 | ... AX43: =+AX27 -> -5383.3649
A44: Cost of sales | B44: =+B25+B32+B35+B38-B41 -> 7587.45 | C44: =+C25+C32+C35+C38-C41 -> 9712.16 | D44: =+D25+D32+D35+D38-D41 -> 12260.99 | E44: =+E25+E32+E35+E38-E41 -> 16443.61 | F44: =+F25+F32+F35+F38-F41 -> 19522.91 | G44: =+G25+G32+G35+G38-G41 -> 16140.28 | H44: =+H25+H32+H35+H38-H41 -> 16531.01 | I44: =+I25+I32+I35+I38-I41 -> 19924.33 | ... AL44: =+AL25+AL32+AL35+AL38-AL41 -> 488947.39 | AN44: PBT | AO44: =+AO41+AO43 -> 25542.9 | AP44: =+AP41+AP43 -> 5177.4 | AQ44: =+AQ41+AQ43 -> -3998.6 | AR44: =+AR41+AR43 -> 167.8 | AS44: =+AS41+AS43 -> 21104 | AT44: =+AT41+AT43 -> 38859 | AU44: =+AU41+AU43 -> 42445.6 | AV44: =+AV41+AV43 -> 51625 | ... AX44: =+AX41+AX43 -> 72339.22
A45: % of sales | B45: =B44/B19*100 -> 92.374756 | C45: =C44/C19*100 -> 91.715087 | D45: =D44/D19*100 -> 91.900516 | E45: =E44/E19*100 -> 91.875086 | F45: =F44/F19*100 -> 89.501425 | G45: =G44/G19*100 -> 91.250395 | H45: =H44/H19*100 -> 90.896008 | I45: =I44/I19*100 -> 88.424696 | ... AL45: =AL44/AL19*100 -> 87.748315 | AN45: Tax | AO45: =+AO29/AO28*AO44 -> 5136 | AP45: =+AP29/AP28*AP44 -> 1224 | AQ45: =+AQ29/AQ28*AQ44 -> -982.3 | AR45: =+AR29/AR28*AR44 -> -142.2 | AS45: =+AS29/AS28*AS44 -> 7302.9 | AT45: =+AT29/AT28*AT44 -> 11743.1 | AU45: =+AU29/AU28*AU44 -> 10450 | AV45: =+AV29/AV28*AV44 -> 12484.9 | ... AX45: =+AX29/AX28*AX44 -> 18084.805
AB46: =+(AB47/W47)^0.2-1 -> 0.79867487 | AC46: =+(AC47/Z47)^0.33333-1 -> -0.18927662 | AE46: =42000/AE47 -> 4.2231428 | AF46: =+AF47/Z47-1 -> 0.33060182 | AG46: =+AG47/AA47-1 -> 0.68185924 | AH46: =+AH47/AB47-1 -> 0.57237526 | AI46: =+AI47/AC47-1 -> 3.8841222 | AJ46: =+AJ47/AD47-1 -> 9.7533515 | AK46: =+AK47/AE47-1 -> 5.4195931 | AL46: =+AL47/AF47-1 -> 1.3294201 | AN46: PAT | AO46: =+AO44-AO45 -> 20406.9 | AP46: =+AP44-AP45 -> 3953.4 | AQ46: =+AQ44-AQ45 -> -3016.3 | AR46: =+AR44-AR45 -> 310 | AS46: =+AS44-AS45 -> 13801.1 | AT46: =+AT44-AT45 -> 27115.9 | AU46: =+AU30 -> 32254.925 | AV46: =+AV30 -> 39140.1 | AW46: =+AW44-AW45 -> 45962.116 | AX46: =+AX44-AX45 -> 54254.415
A47: EBITDA | B47: =+B19-B44 -> 626.32 | C47: =+C19-C44 -> 877.33 | D47: =+D19-D44 -> 1080.6 | E47: =+E19-E44 -> 1454.18 | F47: =+F19-F44 -> 2290.05 | G47: =+G19-G44 -> 1547.6216 | H47: =+H19-H44 -> 1655.7184 | I47: =+I19-I44 -> 2608.21 | ... AL47: =+AL19-AL44 -> 68268.314 | AM47: =+AJ47/AI47-1 -> 0.0038900097 | AN47: Net debt | AO47: =+AO31 -> -7412.3 | AP47: =+AP31 -> 19588.9 | AQ47: =+AQ31 -> 30183 | AR47: =+AR31 -> 12088.7 | AS47: =+AS31 -> -478.8 | AT47: =+AT31 -> -13878.4 | AU47: =+AU31 -> -42429.3 | AV47: =+AV31 -> -59017.2 | AW47: =+AW31-(AW41-AW25)*(1-AJ702/100) -> -76594.467 | AX47: =+AX31-(AX41-AX25)*(1-AK702/100) -> -104034.26
A48: EBITDA Margin | F48: =+F47/F19 -> 0.10498575 | G48: =+G47/G19 -> 0.087496053 | H48: =+H47/H19 -> 0.091039924 | I48: =+I47/I19 -> 0.11575304 | J48: =+J47/J19 -> 0.12754195 | K48: =+K47/K19 -> 0.13097767 | L48: =+L47/L19 -> 0.12200867 | M48: =+M47/M19 -> 0.11626915 | ... AL48: =+AL47/AL19 -> 0.12251685 | AN48: Multiple | AO48: =+AP32 -> 18 | AP48: 20
A49: Interest | B49: =+B683 -> 835.55 | C49: =+C683 -> 671.57 | D49: =+D683 -> 751.67 | E49: =+E683 -> 990.46 | F49: =+F683 -> 1369.45 | G49: =+G683 -> 1724.3 | H49: =+H683 -> 1534.57 | I49: =+I683 -> 1400.67 | ... AL49: =+AL683 -> 764.544 | AN49: TP | AO49: =+ROUND((AO48*AVERAGE(AU41)-AVERAGE(AU47))/$AB$84/5,0)*5 -> 160 | AP49: =+ROUND((AP48*AVERAGE(AW41:AX41)-AVERAGE(AW47:AX47))/$AH$84/5,0)*5 -> 260
A50: Other income | B50: =+B474 -> 569.31 | C50: =+C474 -> 475.64 | D50: =+D474 -> 768.76 | E50: =+E474 -> 1418.16 | F50: =+F474 -> 1305.73 | G50: =+G474 -> 1088.93 | H50: =+H474 -> 877.44 | I50: =+I474 -> 549.76 | ... AL50: =+AL474 -> 4299.4121
A51: EBDT | B51: =+B47-B49+B50 -> 360.08 | C51: =+C47-C49+C50 -> 681.4 | D51: =+D47-D49+D50 -> 1097.69 | E51: =+E47-E49+E50 -> 1881.88 | F51: =+F47-F49+F50 -> 2226.33 | G51: =+G47-G49+G50 -> 912.25158 | H51: =+H47-H49+H50 -> 998.58838 | I51: =+I47-I49+I50 -> 1757.3 | ... AL51: =+AL47-AL49+AL50 -> 71803.182 | AN51: Bear | AO51: FY19 | AP51: =+AP35 -> FY20 | AQ51: =+AQ35 -> FY21 | AR51: =+AR35 -> FY22 | AS51: =+AS35 -> FY23 | AT51: =+AT35 -> FY24 | AU51: =+AU35 -> FY25 | AV51: =+AV35 -> FY26 | AW51: =+AW35 -> FY27 | AX51: =+AX35 -> FY28
A52: Forex gains/(losses) on swap contracts | Y52: =+Y688 -> 50.48 | Z52: =+Z688 -> 153.974 | AA52: =+AA688 -> 3.913 | AB52: =+AB688 -> -26.3 | AC52: =+AC688 -> 0.1 | AD52: =+AD688 -> 0 | AE52: =+AE688 -> 0 | AF52: =+AF688 -> 0 | ... AL52: =+AL688 -> 0 | AN52: Volumes | AO52: =+AO19 -> 197366 | AP52: =+AP19 -> 125253 | AQ52: =+AQ19 -> 100715 | AR52: =+AR19 -> 128326 | AS52: =+AS19 -> 192205 | AT52: =+AT19 -> 194683 | AU52: =+AU19 -> 195093 | AV52: =+AV19 -> 220437 | AW52: =+AV52*(1+AW53) -> 227050.11 | AX52: =+AW52*(1+AX53) -> 233861.61 | AY52: =+SQRT(AX52/AV52)-1 -> 0.03
A53: Depreciation | B53: =+B689 -> 315.83 | C53: =+C689 -> 328.1 | D53: =+D689 -> 391.79 | E53: =+E689 -> 546.05 | F53: =+F689 -> 655.98 | G53: =+G689 -> 705.57 | H53: =+H689 -> 761.9 | I53: =+I689 -> 824.43 | ... AL53: =+AL689 -> 8467.4548 | AN53: % Chg YoY | AW53: 0.03 | AX53: 0.03
A54: Exceptionals (losses)/gains | B54: =+B692 -> 0 | C54: =+C692 -> 0 | D54: =+D692 -> 0 | E54: =+E692 -> 0 | F54: =+F692 -> 0 | G54: =+G692 -> 0 | H54: =+H692 -> 0 | I54: =+I692 -> 0 | ... AL54: =+AL692 -> 0 | AN54: ASP | AO54: =+AO21 -> 1472135.5 | AP54: =+AP21 -> 1394575 | AQ54: =+AQ21 -> 1519282.1 | AR54: =+AR21 -> 1690093.2 | AS54: =+AS21 -> 1880499.5 | AT54: =+AT21 -> 1970743.7 | AU54: =+AU21 -> 1986372.7 | AV54: =+AV21 -> 1996354.1 | AW54: =+AV54*(1+AW55) -> 1996354.1 | AX54: =+AW54*(1+AX55) -> 2016317.6 | AY54: =+SQRT(AX54/AV54)-1 -> 0.0049875621
A55: PBT | B55: =+B51-B53+B54 -> 44.25 | C55: =+C51-C53+C54 -> 353.3 | D55: =+D51-D53+D54 -> 705.9 | E55: =+E51-E53+E54 -> 1335.83 | F55: =+F51-F53+F54 -> 1570.35 | G55: =+G51-G53+G54 -> 206.68158 | H55: =+H51-H53+H54 -> 236.68838 | I55: =+I51-I53+I54 -> 932.87 | ... X55: =+X51-X53+X54 -> 4421.967 | Y55: =+Y51-Y53+Y54+Y52 -> 8265.367 | Z55: =+Z51-Z53+Z54+Z52 -> 16540.862 | AA55: =+AA51-AA53+AA54+AA52 -> 22307.154 | AB55: =+AB51-AB53+AB54+AB52 -> 24968 | AC55: =+AC51-AC53+AC54+AC52 -> 3619.2 | AD55: =+AD51-AD53+AD54 -> -4119.1 | AE55: =+AE51-AE53+AE54 -> 5276.1 | AF55: =+AF51-AF53+AF54 -> 21104 | AG55: =+AG51-AG53+AG54 -> 37921.8 | AH55: =+AH51-AH53+AH54 -> 43482.9 | AI55: =+AI51-AI53+AI54 -> 48140.2 | AJ55: =+AJ51-AJ53+AJ54 -> 52122.45 | AK55: =+AK51-AK53+AK54 -> 58460.773 | AL55: =+AL51-AL53+AL54 -> 63335.727 | AN55: % Chg YoY | AW55: 0 | AX55: 0.01
A56: Tax | B56: =+B701 -> 0 | C56: =+C701 -> 0 | D56: =+D701 -> 0 | E56: =+E701 -> 205 | F56: =+F701 -> 321 | G56: =+G701 -> 22.5 | H56: =+H701 -> 29.5 | I56: =+I701 -> 148 | ... AL56: =+AL701 -> 15833.932 | AN56: Revenue | AO56: =+AO54*AO52/1000000 -> 290549.5 | AP56: =+AP54*AP52/1000000 -> 174674.7 | AQ56: =+AQ54*AQ52/1000000 -> 153014.5 | AR56: =+AR54*AR52/1000000 -> 216882.9 | AS56: =+AS54*AS52/1000000 -> 361441.4 | AT56: =+AT54*AT52/1000000 -> 383670.3 | AU56: =+AU54*AU52/1000000 -> 387527.4 | AV56: =+AV54*AV52/1000000 -> 440070.3 | ... AX56: =+AX54*AX52/1000000 -> 471539.29
A57: PAT | B57: =+B55-B56 -> 44.25 | C57: =+C55-C56 -> 353.3 | D57: =+D55-D56 -> 705.9 | E57: =+E55-E56 -> 1130.83 | F57: =+F55-F56 -> 1249.35 | G57: =+G55-G56 -> 184.18158 | H57: =+H55-H56 -> 207.18838 | I57: =+I55-I56 -> 784.87 | ... AL57: =+AL55-AL56 -> 47501.795 | AN57: EBITDA | AO57: =+AO25 -> 31357.4 | AP57: =+AP25 -> 11736.5 | AQ57: =+AQ25 -> 5351.4 | AR57: =+AR25 -> 9945.2 | AS57: =+AS25 -> 29307 | AT57: =+AT25 -> 46065.8 | AU57: =+AU25 -> 49305.6 | AV57: =+AV25 -> 57322.5 | AW57: =+AW56*AW58 -> 50766.51 | AX57: =+AX56*AX58 -> 54227.018 | AY57: =+SQRT(AX57/AV57)-1 -> -0.027375287
B58: =+B57-B704 -> 0 | C58: =+C57-C704 -> -1.7053026e-12 | D58: =+D57-D704 -> 0 | E58: =+E57-E704 -> 0 | F58: =+F57-F704 -> 0 | G58: =+G57-G704 -> -1.8189894e-12 | H58: =+H57-H704 -> -3.4106051e-12 | I58: =+I57-I704 -> 3.4106051e-12 | ... AL58: =+AL57-AL704 -> 0 | AN58: EBITDA Margin | AO58: =+AO57/AO56 -> 0.10792447 | AP58: =+AP57/AP56 -> 0.067190612 | AQ58: =+AQ57/AQ56 -> 0.034973156 | AR58: =+AR57/AR56 -> 0.04585516 | AS58: =+AS57/AS56 -> 0.081083683 | AT58: =+AT57/AT56 -> 0.12006611 | AU58: =+AU57/AU56 -> 0.12723126 | AV58: =+AV57/AV56 -> 0.1302576 | AW58: 0.112 | AX58: 0.115
A59: PAT (pre exceptionals) | B59: =+B707 -> 44.25 | C59: =+C707 -> 353.3 | D59: =+D707 -> 705.9 | E59: =+E707 -> 1130.83 | F59: =+F707 -> 1249.35 | G59: =+G707 -> 184.18158 | H59: =+H707 -> 207.18838 | I59: =+I707 -> 784.87 | ... Q59: =+Q707 -> 4820.47 | R59: =+R57-R52-R54 -> 2489.85 | S59: =+S57-S52-S54 -> 4269.462 | T59: =+T57-T52-T54 -> 6812.993 | U59: =+U57-U52-U54 -> 5643.788 | V59: =+V57-V52-V54 -> 1441.506 | W59: =+W57-W52-W54 -> -4762.778 | X59: =+X57-X52-X54 -> 2338.701 | Y59: =+Y707 -> 9878.5835 | Z59: =+Z707 -> 12430.395 | AA59: =+AA57-AA52-AA54 -> 15747.643 | AB59: =+AB57-(AB52+AB54)*0.8 -> 20291.92 | AC59: =+AC57-(AC52+AC54)*0.75 -> 3563.85 | AD59: =+AD57-(AD52+AD54)*0.75 -> -3046.425 | AE59: =+AE57-(AE52+AE54)*0.75 -> 1587.075 | AF59: =+AF57-(AF52+AF54)*0.75 -> 13166.525 | AG59: =+AG57-(AG52+AG54)*0.75 -> 26881.6 | AH59: =+AH57-(AH52+AH54)*0.75 -> 32254.925 | AI59: =+AI57-(AI52+AI54)*1 -> 39140.1 | AJ59: =+AJ57-(AJ52+AJ54)*0.75 -> 39091.838 | AK59: =+AK57-(AK52+AK54)*0.75 -> 43845.58 | AL59: =+AL57-(AL52+AL54)*0.75 -> 47501.795 | AN59: Non operating items | AO59: =+AO27 -> -5814.5 | AP59: =+AP27 -> -6559.1 | AQ59: =+AQ27 -> -9350 | AR59: =+AR27 -> -9777.4 | AS59: =+AS27 -> -8203 | AT59: =+AT27 -> -7206.8 | AU59: =+AU27 -> -6860 | AV59: =+AV27 -> -5697.5 | ... AX59: =+AX27 -> -5383.3649
H60: 207.18838 | I60: 784.87 | J60: 916.81 | K60: 922.56 | L60: 1202.12 | M60: 1935.8 | N60: 2714.1 | O60: 3273.2 | P60: 4412.86 | Q60: 4693.1 | R60: 1899.963 | S60: 4236.747 | T60: 6312.993 | U60: 5659.766 | V60: 4337.067 | W60: 293.811 | X60: 3348.06 | Y60: 7217.758 | Z60: 12230.772 | AA60: 15625.896 | AB60: 19832 | AC60: 2395.2 | AD60: -3136.8 | AE60: 5418.3 | AF60: 13801.1 | AG60: 26178.7 | AH60: 33032.9 | AI60: 35655.3 | AN60: PBT | AO60: =+AO57+AO59 -> 25542.9 | AP60: =+AP57+AP59 -> 5177.4 | AQ60: =+AQ57+AQ59 -> -3998.6 | AR60: =+AR57+AR59 -> 167.8 | AS60: =+AS57+AS59 -> 21104 | AT60: =+AT57+AT59 -> 38859 | AU60: =+AU57+AU59 -> 42445.6 | AV60: =+AV57+AV59 -> 51625 | ... AX60: =+AX57+AX59 -> 48843.653
H61: =+H60-H57 -> 3.4674486e-12 | I61: =+I60-I57 -> -3.7516656e-12 | J61: =+J60-J57 -> 0 | K61: =+K60-K57 -> 0 | L61: =+L60-L57 -> -4.5474735e-12 | M61: =+M60-M57 -> 0 | N61: =+N60-N57 -> 0 | O61: =+O60-O57 -> 0 | ... X61: =+X60-X57 -> -1.4097168e-11 | Y61: =+Y57-3895.985 -> 1.6825652e-11 | Z61: =+Z57-12230.772 -> 0 | AA61: =+AA60-AA57 -> 0 | AB61: =+AB60-AB57 -> 9.094947e-11 | AC61: =+AC60-AC57 -> 0 | AD61: =+AD60-AD57 -> 0 | AE61: =+AE60-AE57 -> 0 | AF61: =+AF60-AF57 -> 0 | AG61: =+AG60-AG57 -> 0 | AH61: =+AH60-AH57 -> 0 | AI61: =+AI60-AI57 -> -1.6007107e-10 | AN61: Tax | AO61: =+AO29/AO28*AO60 -> 5136 | AP61: =+AP29/AP28*AP60 -> 1224 | AQ61: =+AQ29/AQ28*AQ60 -> -982.3 | AR61: =+AR29/AR28*AR60 -> -142.2 | AS61: =+AS29/AS28*AS60 -> 7302.9 | AT61: =+AT29/AT28*AT60 -> 11743.1 | AU61: =+AU29/AU28*AU60 -> 10450 | AV61: =+AV29/AV28*AV60 -> 12484.9 | ... AX61: =+AX29/AX28*AX60 -> 12210.913
AA62: =+AA59-AA707 -> 0 | AB62: =+AB59-AB707 -> 0 | AC62: =+AC59-AC707 -> 0 | AD62: =+AD59-AD707 -> 0 | AE62: =+AE59-AE707 -> 0 | AF62: =+AF59-AF707 -> 0 | AG62: =+AG59-AG707 -> 0 | AH62: =+AH59-AH707 -> 0 | ... AL62: =+AL59-AL707 -> 0 | AN62: PAT | AO62: =+AO60-AO61 -> 20406.9 | AP62: =+AP60-AP61 -> 3953.4 | AQ62: =+AQ60-AQ61 -> -3016.3 | AR62: =+AR60-AR61 -> 310 | AS62: =+AS60-AS61 -> 13801.1 | AT62: =+AT60-AT61 -> 27115.9 | AU62: =+AU46 -> 32254.925 | AV62: =+AV46 -> 39140.1 | AW62: =+AW60-AW61 -> 34007.606 | AX62: =+AX60-AX61 -> 36632.74
A63: EBDIT | B63: =+B47+B50 -> 1195.63 | C63: =+C47+C50 -> 1352.97 | D63: =+D47+D50 -> 1849.36 | E63: =+E47+E50 -> 2872.34 | F63: =+F47+F50 -> 3595.78 | G63: =+G47+G50 -> 2636.5516 | H63: =+H47+H50 -> 2533.1584 | I63: =+I47+I50 -> 3157.97 | ... AL63: =+AL47+AL50 -> 72567.726 | AN63: Net debt | AO63: =+AO31 -> -7412.3 | AP63: =+AP31 -> 19588.9 | AQ63: =+AQ31 -> 30183 | AR63: =+AR31 -> 12088.7 | AS63: =+AS31 -> -478.8 | AT63: =+AT31 -> -13878.4 | AU63: =+AU31 -> -42429.3 | AV63: =+AV31 -> -59017.2 | AW63: =+AW31-(AW57-AW25)*(1-AJ702/100) -> -64639.957 | AX63: =+AX31-(AX57-AX25)*(1-AK702/100) -> -86412.588
A64: EBIT | B64: =+B63-B53 -> 879.8 | C64: =+C63-C53 -> 1024.87 | D64: =+D63-D53 -> 1457.57 | E64: =+E63-E53 -> 2326.29 | F64: =+F63-F53 -> 2939.8 | G64: =+G63-G53 -> 1930.9816 | H64: =+H63-H53 -> 1771.2584 | I64: =+I63-I53 -> 2333.54 | ... AL64: =+AL63-AL53 -> 64100.271 | AN64: Multiple | AO64: =+AP32 -> 18 | AP64: 14
A65: EBITwOI | B65: =+B47-B53 -> 310.49 | C65: =+C47-C53 -> 549.23 | D65: =+D47-D53 -> 688.81 | E65: =+E47-E53 -> 908.13 | F65: =+F47-F53 -> 1634.07 | G65: =+G47-G53 -> 842.05158 | H65: =+H47-H53 -> 893.81838 | I65: =+I47-I53 -> 1783.78 | ... AL65: =+AL47-AL53 -> 59800.859 | AN65: TP | AO65: =+ROUND((AO64*AVERAGE(AU57)-AVERAGE(AU63))/$AB$84/5,0)*5 -> 160 | AP65: =+ROUND((AP64*AVERAGE(AW57:AX57)-AVERAGE(AW63:AX63))/$AH$84/5,0)*5 -> 140
A66: Cash profit | B66: =+B59+B53 -> 360.08 | C66: =+C59+C53 -> 681.4 | D66: =+D59+D53 -> 1097.69 | E66: =+E59+E53 -> 1676.88 | F66: =+F59+F53 -> 1905.33 | G66: =+G59+G53 -> 889.75158 | H66: =+H59+H53 -> 969.08838 | I66: =+I59+I53 -> 1609.3 | ... AL66: =+AL59+AL53 -> 55969.25
B67: FY 1993 | C67: FY 1994 | D67: FY 1995 | E67: FY 1996 | F67: FY 1997 | G67: FY 1998 | H67: FY 1999 | I67: FY2000 | J67: FY2001 | K67: FY2002 | L67: FY2003 | M67: FY2004 | N67: FY2005 | O67: FY2006 | P67: FY2007 | Q67: FY2008 | R67: FY2009 | S67: FY2010 | T67: FY2011 | U67: FY2012 | V67: FY2013E | W67: FY2014E | X67: FY2015E | Y67: =+Y3 -> FY2016 | Z67: =+Z3 -> FY2017 | AA67: =+AA3 -> FY2018 | AB67: =+AB3 -> FY2019 | AC67: =+AC3 -> FY2020 | AD67: =+AD3 -> FY2021 | AE67: =+AE3 -> FY2022 | AF67: =+AF3 -> FY2023 | ... AL67: =+AL3 -> FY2029E
A68: Profit Margins | AN68: Bull | AO68: =+AP49 -> 260
A69: OPM (%) | B69: =+B47/B13*100 -> 6.5621932 | C69: =+C47/C13*100 -> 7.4268556 | D69: =+D47/D13*100 -> 7.1407237 | E69: =+E47/E13*100 -> 7.2357991 | F69: =+F47/F13*100 -> 9.2249555 | G69: =+G47/G13*100 -> 7.6832489 | H69: =+H47/H13*100 -> 8.096233 | I69: =+I47/I13*100 -> 10.036526 | ... AL69: =+AL47/AL13*100 -> 12.251685 | AN69: Higher volumes and ASPs drive stronger EBITDA growth | AO69: =+AO68-AO70-AP2 -> -40
A70: EBITDA Margins (%) | B70: =B47/B19*100 -> 7.625244 | C70: =C47/C19*100 -> 8.2849127 | D70: =D47/D19*100 -> 8.0994844 | E70: =E47/E19*100 -> 8.1249137 | F70: =F47/F19*100 -> 10.498575 | G70: =G47/G19*100 -> 8.7496053 | H70: =H47/H19*100 -> 9.1039924 | I70: =I47/I19*100 -> 11.575304 | ... AL70: =AL47/AL19*100 -> 12.251685 | AN70: Higher target multiple | AO70: =+AP49-AO49 -> 100
AN71: Base | AO71: =+AO68-AO69-AO70 -> 200 | AP71: =+AO71-AP33 -> 0
A72: Other income / EBDIT (%) | B72: =+B50/B63*100 -> 47.615901 | C72: =+C50/C63*100 -> 35.155251 | D72: =+D50/D63*100 -> 41.568975 | E72: =+E50/E63*100 -> 49.372985 | F72: =+F50/F63*100 -> 36.312845 | G72: =+G50/G63*100 -> 41.301297 | H72: =+H50/H63*100 -> 34.638182 | I72: =+I50/I63*100 -> 17.408652 | ... AL72: =+AL50/AL63*100 -> 5.9246891 | AN72: Lower target multiple | AO72: =+AO65-AP65 -> 20
A73: Other income / PAT (%) | B73: =+B50/B59*100 -> 1286.5763 | C73: =+C50/C59*100 -> 134.6278 | D73: =+D50/D59*100 -> 108.90494 | E73: =+E50/E59*100 -> 125.40877 | F73: =+F50/F59*100 -> 104.51275 | G73: =+G50/G59*100 -> 591.22635 | H73: =+H50/H59*100 -> 423.49866 | I73: =+I50/I59*100 -> 70.044721 | ... AL73: =+AL50/AL59*100 -> 9.0510519 | AN73: Lower volumes and ASPs result in weaker EBITDA growth | AO73: =+AO71-AP65-AO72 -> 40
AN74: Bear | AO74: =+AO71-AO73-AO72 -> 140
A75: EBITwOI/Sales | B75: =+B65/B13*100 -> 3.253122 | C75: =+C65/C13*100 -> 4.649393 | D75: =+D65/D13*100 -> 4.5517322 | E75: =+E65/E13*100 -> 4.5187296 | F75: =+F65/F13*100 -> 6.5824864 | G75: =+G65/G13*100 -> 4.1804094 | H75: =+H65/H13*100 -> 4.3706478 | I75: =+I65/I13*100 -> 6.8640768 | ... AL75: =+AL65/AL13*100 -> 10.732084
A76: EBITwOI/ Net Sales | B76: =B65/B19*100 -> 3.7801156 | C76: =C65/C19*100 -> 5.1865576 | D76: =D65/D19*100 -> 5.1628779 | E76: =E65/E19*100 -> 5.0739784 | F76: =F65/F19*100 -> 7.4912804 | G76: =G65/G19*100 -> 4.7606075 | H76: =H65/H19*100 -> 4.9146738 | I76: =I65/I19*100 -> 7.9164621 | ... AL76: =AL65/AL19*100 -> 10.732084
A77: Interest cover (X) | B77: =+B63/B49 -> 1.4309497 | C77: =+C63/C49 -> 2.0146373 | D77: =+D63/D49 -> 2.460335 | E77: =+E63/E49 -> 2.9000061 | F77: =+F63/F49 -> 2.6257111 | G77: =+G63/G49 -> 1.5290562 | H77: =+H63/H49 -> 1.6507285 | I77: =+I63/I49 -> 2.2546139 | ... AL77: =+AL63/AL49 -> 94.91635
A79: EBDT (%) | B79: =+B51/B13*100 -> 3.7726953 | C79: =+C51/C13*100 -> 5.7682507 | D79: =+D51/D13*100 -> 7.2536563 | E79: =+E51/E13*100 -> 9.3639754 | F79: =+F51/F13*100 -> 8.9682737 | G79: =+G51/G13*100 -> 4.528921 | H79: =+H51/H13*100 -> 4.8829585 | I79: =+I51/I13*100 -> 6.7621804 | ... Q79: =+Q51/Q13*100 -> 9.2710627 | R79: =+R51/R19*100 -> 7.4543338 | S79: =+S51/S19*100 -> 10.382114 | T79: =+T51/T19*100 -> 10.067095 | U79: =+U51/U19*100 -> 8.1150183 | V79: =+V51/V19*100 -> 4.5022442 | W79: =+W51/W19*100 -> -2.2109259 | X79: =+X51/X19*100 -> 5.5861027 | Y79: =+Y51/Y19*100 -> 11.219193 | ... AL79: =+AL51/AL19*100 -> 12.886066
A80: Pre tax margins (%) | B80: =+B55/B13*100 -> 0.46362411 | C80: =+C55/C13*100 -> 2.9907881 | D80: =+D55/D13*100 -> 4.6646648 | E80: =+E55/E13*100 -> 6.6469059 | F80: =+F55/F13*100 -> 6.3258046 | G80: =+G55/G13*100 -> 1.0260816 | H80: =+H55/H13*100 -> 1.1573733 | I80: =+I55/I13*100 -> 3.5897316 | ... Q80: =+Q55/Q13*100 -> 7.143185 | R80: =+R55/R19*100 -> 3.4850983 | S80: =+S55/S19*100 -> 7.51962 | T80: =+T55/T19*100 -> 7.2119112 | U80: =+U55/U19*100 -> 5.3776563 | V80: =+V55/V19*100 -> 3.7713257 | W80: =+W55/W19*100 -> -0.91737892 | X80: =+X55/X19*100 -> 3.2605126 | Y80: =+Y55/Y19*100 -> 4.3645954 | ... AL80: =+AL55/AL19*100 -> 11.366465
A81: Tax / PBT (%) | B81: =+B56/B55*100 -> 0 | C81: =+C56/C55*100 -> 0 | D81: =+D56/D55*100 -> 0 | E81: =+E56/E55*100 -> 15.346264 | F81: =+F56/F55*100 -> 20.441303 | G81: =+G56/G55*100 -> 10.886311 | H81: =+H56/H55*100 -> 12.463645 | I81: =+I56/I55*100 -> 15.865019 | ... AL81: =+AL56/AL55*100 -> 25
A82: Net profit margins (%) | B82: =+B59/B19*100 -> 0.53872948 | C82: =+C59/C19*100 -> 3.3363269 | D82: =+D59/D19*100 -> 5.2909736 | E82: =+E59/E19*100 -> 6.3182661 | F82: =+F59/F19*100 -> 5.7275583 | G82: =+G59/G19*100 -> 1.0412856 | H82: =+H59/H19*100 -> 1.1392284 | I82: =+I59/I19*100 -> 3.4832735 | ... AL82: =+AL59/AL19*100 -> 8.5248486
A84: Equity (m shares) | B84: =(+B773)*2*2 -> 2774.48 | C84: =(+C773)*2*2 -> 3119.92 | D84: =(+D773)*2*2 -> 4757 | E84: =(+E773)*2*2 -> 4757.16 | F84: =(+F773)*2*2 -> 4757.16 | G84: =(+G773)*2*2 -> 4757.16 | H84: =(+H773)*2*2 -> 4757.16 | I84: =(+I773)*2*2 -> 4757.16 | ... T84: =(+T773)*2*2 -> 5321.368 | U84: =+U773*2 -> 5321.36 | V84: =+V773*2 -> 5321.36 | W84: =+W773*2 -> 5321.36 | X84: =+X773*2 -> 5691.76 | Y84: =+Y773*2 -> 5691.76 | Z84: =+Z773*2 -> 5691.76 | AA84: =+AA773*2 -> 5854.216 | AB84: =+AB773*2 -> 5871 | ... AH84: =+AH773*2 -> 5873 | AI84: =+AI773 -> 5873.9 | AJ84: =+AJ773 -> 5873.9 | AK84: =+AK773 -> 5873.9 | AL84: =+AL773 -> 5873.9
AM85: =95/AD86 -> -183.08181
A86: EPS (Rs) | B86: =+B59/B84 -> 0.015948935 | C86: =+C59/C84 -> 0.11324008 | D86: =+D59/D84 -> 0.14839184 | E86: =+E59/E84 -> 0.23771116 | F86: =+F59/F84 -> 0.26262518 | G86: =+G59/G84 -> 0.038716708 | H86: =+H59/H84 -> 0.043552956 | I86: =+I59/I84 -> 0.16498709 | ... AL86: =+AL59/AL84 -> 8.0869261
A87: CEPS (Rs) | B87: =+B66/B84 -> 0.12978288 | C87: =+C66/C84 -> 0.21840304 | D87: =+D66/D84 -> 0.23075258 | E87: =+E66/E84 -> 0.35249603 | F87: =+F66/F84 -> 0.40051838 | G87: =+G66/G84 -> 0.18703419 | H87: =+H66/H84 -> 0.20371154 | I87: =+I66/I84 -> 0.33829007 | ... AL87: =+AL66/AL84 -> 9.5284649
A89: Equity FD (m shares) | B89: =B84 -> 2774.48 | C89: =C84 -> 3119.92 | D89: =+$G$84 -> 4757.16 | E89: =+$G$84 -> 4757.16 | F89: =+$G$84 -> 4757.16 | G89: =+$G$84 -> 4757.16 | H89: =+$G$84 -> 4757.16 | I89: =+$G$84 -> 4757.16 | J89: =+$G$84 -> 4757.16 | K89: =+$G$84 -> 4757.16 | ... M89: =+$G$84 -> 4757.16 | N89: =+$G$84+131.6418*2 -> 5020.4436 | O89: =+O84 -> 4886.36 | P89: =+P84 -> 5295.48 | Q89: =+Q84 -> 5321.36 | R89: =+R84 -> 5321.368 | S89: =+S84 -> 5321.368 | T89: =+T84 -> 5321.368 | U89: =+U84 -> 5321.36 | V89: =+V84 -> 5321.36 | ... AL89: =+AL84 -> 5873.9
A91: EPS FD (Rs) | B91: =+B59/B89 -> 0.015948935 | C91: =+C59/C89 -> 0.11324008 | D91: =+D59/D89 -> 0.14838685 | E91: =+E59/E89 -> 0.23771116 | F91: =+F59/F89 -> 0.26262518 | G91: =+G59/G89 -> 0.038716708 | H91: =+H59/H89 -> 0.043552956 | I91: =+I59/I89 -> 0.16498709 | ... AL91: =+AL59/AL89 -> 8.0869261
A92: CEPS FD (Rs) | B92: =+B66/B89 -> 0.12978288 | C92: =+C66/C89 -> 0.21840304 | D92: =+D66/D89 -> 0.23074481 | E92: =+E66/E89 -> 0.35249603 | F92: =+F66/F89 -> 0.40051838 | G92: =+G66/G89 -> 0.18703419 | H92: =+H66/H89 -> 0.20371154 | I92: =+I66/I89 -> 0.33829007 | ... AL92: =+AL66/AL89 -> 9.5284649
A93: Book value FD (Rs) | B93: =(B789-B777)/B89 -> 1.3622012 | C93: =(C789-C777)/C89 -> 1.4009269 | D93: =(D789-D777)/D89 -> 1.979925 | E93: =(E789-E777)/E89 -> 2.1182933 | F93: =(F789-F777)/F89 -> 2.2434183 | G93: =(G789-G777)/G89 -> 2.2546162 | H93: =(H789-H777)/H89 -> 2.2703777 | I93: =(I789-I777)/I89 -> 2.3382375 | ... AL93: =(AL789-AL777)/AL89 -> 34.895036
A95: Market price (Rs) | B95: 127 | C95: =B95 -> 127 | D95: =C95 -> 127 | E95: =D95 -> 127 | F95: =E95 -> 127 | G95: =F95 -> 127 | H95: =G95 -> 127 | I95: =H95 -> 127 | J95: =I95 -> 127 | ... AL95: =AK95 -> 127
A97: Valuation
A99: P / E (x) | B99: =+B95/B91 -> 7962.9144 | C99: =+C95/C91 -> 1121.511 | D99: =+D95/D91 -> 855.87097 | E99: =+E95/E91 -> 534.26184 | F99: =+F95/F91 -> 483.57892 | G99: =+G95/G91 -> 3280.2375 | H99: =+H95/H91 -> 2915.9904 | I99: =+I95/I91 -> 769.75718 | ... AL99: =+AL95/AL91 -> 15.70436
A100: Earnings growth (%) | C100: =+C91/B91*100-100 -> 610.0166 | D100: =+D91/C91*100-100 -> 31.037393 | E100: =+E91/D91*100-100 -> 60.196912 | F100: =+F91/E91*100-100 -> 10.480797 | G100: =+G91/F91*100-100 -> -85.257808 | H100: =+H91/G91*100-100 -> 12.49137 | I100: =+I91/H91*100-100 -> 278.81951 | J100: =+J91/I91*100-100 -> 23.777186 | ... AL100: =+AL91/AK91*100-100 -> 8.3388465
A101: Earnings growth / P/E (x) | B101: =+B100/B99 -> 0 | C101: =+C100/C99 -> 0.54392386 | D101: =+D100/D99 -> 0.036264103 | E101: =+E100/E99 -> 0.11267305 | F101: =+F100/F99 -> 0.021673396 | G101: =+G100/G99 -> -0.025991352 | H101: =+H100/H99 -> 0.0042837487 | I101: =+I100/I99 -> 0.36221748 | ... AL101: =+AL100/AL99 -> 0.53098926
A103: Earnings yield | B103: =100/B99 -> 0.012558216 | C103: =100/C99 -> 0.08916542 | D103: =100/D99 -> 0.11684004 | E103: =100/E99 -> 0.18717414 | F103: =100/F99 -> 0.20679148 | G103: =100/G99 -> 0.030485597 | H103: =100/H99 -> 0.034293666 | I103: =100/I99 -> 0.1299111 | ... AL103: =100/AL99 -> 6.3676583
A105: Price / cash flow / share (x) | B105: =+B95/B92 -> 978.55743 | C105: =+C95/C92 -> 581.49375 | D105: =+D95/D92 -> 550.39157 | E105: =+E95/E92 -> 360.28775 | F105: =+F95/F92 -> 317.08907 | G105: =+G95/G92 -> 679.02023 | H105: =+H95/H92 -> 623.43057 | I105: =+I95/I92 -> 375.41746 | ... AL105: =+AL95/AL92 -> 13.328485
A106: Cash earnings growth (%) | C106: =+C92/B92*100-100 -> 68.283397 | D106: =+D92/C92*100-100 -> 5.6509188 | E106: =+E92/D92*100-100 -> 52.764442 | F106: =+F92/E92*100-100 -> 13.623515 | G106: =+G92/F92*100-100 -> -53.30197 | H106: =+H92/G92*100-100 -> 8.9167364 | I106: =+I92/H92*100-100 -> 66.063285 | J106: =+J92/I92*100-100 -> 15.266886 | ... AL106: =+AL92/AK92*100-100 -> 7.7211626
A107: CEPS growth / CEPS | C107: =+C106/C105 -> 0.11742757 | D107: =+D106/D105 -> 0.010267088 | E107: =+E106/E105 -> 0.14645084 | F107: =+F106/F105 -> 0.042964316 | G107: =+G106/G105 -> -0.078498353 | H107: =+H106/H105 -> 0.014302694 | I107: =+I106/I105 -> 0.17597286 | J107: =+J106/J105 -> 0.046874922 | ... AL107: =+AL106/AL105 -> 0.57929785
A109: Price / book value / share (x) | B109: =+B95/+B93 -> 93.231455 | C109: =+C95/+C93 -> 90.654263 | D109: =+D95/+D93 -> 64.143844 | E109: =+E95/+E93 -> 59.953927 | F109: =+F95/+F93 -> 56.610039 | G109: =+G95/+G93 -> 56.328878 | H109: =+H95/+H93 -> 55.937829 | I109: =+I95/+I93 -> 54.314414 | ... AL109: =+AL95/+AL93 -> 3.6394861
A110: Mcap | B110: =B95*X84 -> 722853.52
A111: Mkt cap / sales (x) | B111: =+$B$110/B13 -> 75.736117 | C111: =+$B$110/C13 -> 61.191669 | D111: =+$B$110/D13 -> 47.766956 | E111: =+$B$110/E13 -> 35.968194 | F111: =+$B$110/F13 -> 29.118541 | G111: =+$B$110/G13 -> 35.886444 | H111: =+$B$110/H13 -> 35.346534 | I111: =+$B$110/I13 -> 27.815774 | ... AL111: =+$B$110/AL13 -> 1.2972598
A112: MKt cap / net sales (x) | B112: =+$B$110/B19 -> 88.005084 | C112: =+$B$110/C19 -> 68.26141 | D112: =+$B$110/D19 -> 54.180463 | E112: =+$B$110/E19 -> 40.387865 | F112: =+$B$110/F19 -> 33.138718 | G112: =+$B$110/G19 -> 40.867116 | H112: =+$B$110/H19 -> 39.74621 | I112: =+$B$110/I19 -> 32.080428 | ... AL112: =+$B$110/AL19 -> 1.2972598
A113: Sales / share (x) | B113: =+B13/B89 -> 3.4400572 | C113: =+C13/C89 -> 3.7862958 | D113: =+D13/D89 -> 3.1810828 | E113: =+E13/E89 -> 4.2245836 | F113: =+F13/F89 -> 5.2183467 | G113: =+G13/G89 -> 4.2342073 | H113: =+H13/H89 -> 4.2988839 | I113: =+I13/I89 -> 5.4627509 | ... AL113: =+AL13/AL89 -> 94.862988
B114: FY 1993 | C114: FY 1994 | D114: FY 1995 | E114: FY 1996 | F114: FY 1997 | G114: FY 1998 | H114: FY 1999 | I114: FY2000 | J114: FY2001 | K114: FY2002 | L114: FY2003 | M114: FY2004 | N114: FY2005 | O114: FY2006 | P114: FY2007 | Q114: FY2008 | R114: FY2009 | S114: FY2010 | T114: FY2011 | U114: FY2012 | V114: FY2013E | W114: FY2014E | X114: FY2015E | Y114: FY2016E | Z114: FY2017E | AA114: =+AA3 -> FY2018 | AB114: =+AB3 -> FY2019 | AC114: =+AC3 -> FY2020 | AD114: =+AD3 -> FY2021 | AE114: =+AE3 -> FY2022 | AF114: =+AF3 -> FY2023 | AG114: =+AG3 -> FY2024 | AH114: =+AH3 -> FY2025 | ... AL114: =+AL3 -> FY2029E
...

Sheet New Qrtrly - Ind AS
A1: Ashok Leyland (AL IN) — Quarterly model, Ind AS
A2: Note: Have used our Q database for volumes | Restructured: actuals, estimates and annual columns separated; blank rows removed; colour coding applied. No values changed — see README.
B3: QUARTERLY — ACTUALS (reported) | AZ3: QUARTERLY — BSe ESTIMATES | CE3: ANNUAL | CI3: WORKINGS / CHECKS
A4: Fiscal year | B4: FY16 | C4: FY16 | D4: FY16 | E4: FY16 | F4: FY17 | G4: FY17 | H4: FY17 | I4: FY17 | J4: FY18 | K4: FY18 | L4: FY18 | M4: FY18 | N4: FY18 | O4: FY18 | P4: FY19 | Q4: FY19 | R4: FY19 | S4: FY19 | T4: FY19 | U4: FY19 | V4: FY20 | W4: FY20 | X4: FY20 | Y4: FY20 | Z4: FY21 | AA4: FY21 | AB4: FY21 | AC4: FY21 | AD4: FY22 | AE4: FY22 | AF4: FY22 | AG4: FY22 | AH4: FY23 | AI4: FY23 | AJ4: FY23 | AK4: FY23 | AL4: FY24 | AM4: FY24 | AN4: FY24 | AO4: FY24 | AP4: FY25 | AQ4: FY25 | AR4: FY25 | AS4: FY25 | AT4: FY26 | AU4: FY26 | AV4: FY26 | AW4: FY26 | AX4: FY27 | AZ4: FY19 | BA4: FY20 | BB4: FY20 | BC4: FY20 | BD4: FY20 | BE4: FY21 | BF4: FY21 | BG4: FY21 | BH4: FY21 | BI4: FY22 | BJ4: FY22 | BK4: FY22 | BL4: FY22 | BM4: FY23 | BN4: FY23 | BO4: FY23 | BP4: FY23 | BQ4: FY24 | BR4: FY24 | BS4: FY24 | BT4: FY24 | BU4: FY25 | BV4: FY25 | BW4: FY25 | BX4: FY25 | BY4: FY26 | BZ4: FY26 | CA4: FY26 | CB4: FY26 | CC4: FY27 | CE4: FY16 | CF4: FY17 | CG4: FY26E | CJ4: FY26
A5: Period | B5: 1Q | C5: 2Q | D5: 3Q | E5: 4Q | F5: 1Q | G5: 2Q | H5: 3Q | I5: 4Q | J5: 1Q | K5: 2Q | L5: 3Q | M5: 3Q rest. | N5: 4Q | O5: 4Q rest. | P5: 1Q | Q5: 1Q rest. | R5: 2Q | S5: 2Q rest. | T5: 3Q | U5: 4Q | V5: 1Q | W5: 2Q | X5: 3Q | Y5: 4Q | Z5: 1Q | AA5: 2Q | AB5: 3Q | AC5: 4Q | AD5: 1Q | AE5: 2Q | AF5: 3Q | AG5: 4Q | AH5: 1Q | AI5: 2Q | AJ5: 3Q | AK5: 4Q | AL5: 1Q | AM5: 2Q | AN5: 3Q | AO5: 4Q | AP5: 1Q | AQ5: 2Q | AR5: 3Q | AS5: 4Q | AT5: 1Q | AU5: 2Q | AV5: 3Q | AW5: 4Q | AX5: 1Q | AZ5: 4Q | BA5: 1Q | BB5: 2Q | BC5: 3Q | BD5: 4Q | BE5: 1Q | BF5: 2Q | BG5: 3Q | BH5: 4Q | BI5: 1Q | BJ5: 2Q | BK5: 3Q | BL5: 4Q | BM5: 1Q | BN5: 2Q | BO5: 3Q | BP5: 4Q | BQ5: 1Q | BR5: 2Q | BS5: 3Q | BT5: 4Q | BU5: 1Q | BV5: 2Q | BW5: 3Q | BX5: 4Q | BY5: 1Q | BZ5: 2Q | CA5: 3Q | CB5: 4Q | CC5: 1Q | CE5: FY16 | CF5: FY17 | CG5: FY26E | CI5: (CE) | CJ5: 4Q | CK5: (CH) | CL5: (CI) | CM5: (CJ) | CN5: (CK)
A6: Source column | B6: src B | C6: src C | D6: src D | E6: src E | F6: src G | G6: src H | H6: src I | I6: src J | J6: src L | K6: src M | L6: src N | M6: src O | N6: src P | O6: src Q | P6: src R | Q6: src S | R6: src T | S6: src U | T6: src V | U6: src X | V6: src Z | W6: src AB | X6: src AD | Y6: src AF | Z6: src AH | AA6: src AJ | AB6: src AL | AC6: src AN | AD6: src AP | AE6: src AR | AF6: src AT | AG6: src AV | AH6: src AX | AI6: src AZ | AJ6: src BB | AK6: src BD | AL6: src BF | AM6: src BH | AN6: src BJ | AO6: src BL | AP6: src BN | AQ6: src BP | AR6: src BR | AS6: src BT | AT6: src BV | AU6: src BX | AV6: src BZ | AW6: src CB | AX6: src CD | AZ6: src W | BA6: src Y | BB6: src AA | BC6: src AC | BD6: src AE | BE6: src AG | BF6: src AI | BG6: src AK | BH6: src AM | BI6: src AO | BJ6: src AQ | BK6: src AS | BL6: src AU | BM6: src AW | BN6: src AY | BO6: src BA | BP6: src BC | BQ6: src BE | BR6: src BG | BS6: src BI | BT6: src BK | BU6: src BM | BV6: src BO | BW6: src BQ | BX6: src BS | BY6: src BU | BZ6: src BW | CA6: src BY | CB6: src CA | CC6: src CC | CE6: src F | CF6: src K | CG6: src CG | CI6: src CE | CJ6: src CF | CK6: src CH | CL6: src CI | CM6: src CJ | CN6: src CK
A8: VOLUMES (Nos.)
A9: H / MCVs | B9: 21485 | C9: =8835+8903+12146 -> 29884 | D9: =7177+6296+9703 -> 23176 | E9: =11208+10801+13240 -> 35249 | F9: =7873+7469+8685 -> 24027 | G9: =8182+8201+8958 -> 25341 | H9: =9575+6928+8782 -> 25285 | I9: 38643 | J9: 19877 | K9: 31397 | L9: =9140+10638+15950 -> 35728 | M9: =9140+10638+15950 -> 35728 | N9: =13726+13643+17057 -> 44426 | O9: =13726+13643+17057 -> 44426 | P9: 30646 | Q9: 30646 | R9: 38387 | S9: 38387 | T9: =9797+8718+11295 -> 29810 | U9: =14694+13291+16034 -> 44019 | V9: 26719 | W9: 16815 | X9: =5126+5966+7025 -> 18117 | Y9: 16956 | Z9: 1021 | AA9: =1705+2589+3642 -> 7936 | AB9: =4588+5114+6884 -> 16586 | AC9: 26277 | AD9: 9050 | AE9: 13514 | AF9: 19305 | AG9: 32016 | AH9: 24987 | AI9: =8148+8379+11314 -> 27841 | AJ9: 30790 | AK9: 40491 | AL9: 26165 | AM9: 32086 | AN9: 29485 | AO9: 37149 | AP9: 27885 | AQ9: 28180 | AR9: 30058 | AS9: 39908 | AT9: 28071 | AU9: 30718 | AV9: 37376 | AW9: 46493 | AX9: 29424 | AZ9: =14694+13291+16034 -> 44019 | BA9: 26719 | BB9: 16815 | BC9: =5126+5966+7025 -> 18117 | BD9: =78607-X9-W9-V9 -> 16956 | BE9: 1021 | BF9: =1705+2589+3642 -> 7936 | BG9: =4588+5114+6884 -> 16586 | BH9: 26277 | BI9: 9050 | BJ9: 13514 | BK9: 19305 | BL9: 32016 | BM9: 24987 | BN9: =8148+8379+11314 -> 27841 | BO9: 30790 | BP9: 40491 | BQ9: 26165 | BR9: 32086 | BS9: =87736-AM9-AL9 -> 29485 | BT9: 37149 | BU9: 27885 | BV9: 28180 | BW9: 30058 | BX9: 39908 | BY9: 28071 | BZ9: 30718 | CA9: 37376 | CB9: 46493 | CC9: 29424 | CG9: ='Main Model'!AI294 -> 142658 | CI9: =+CC9/AW9-1 -> -0.36713054 | CJ9: =CG9-AV9-AU9-AT9 -> 46493 | CL9: =+CA9/AU9-1 -> 0.21674588
A10: LCVs | B10: 6701 | C10: =2219+2641+2637 -> 7497 | D10: =2627+2674+2451 -> 7752 | E10: =2678+2605+3462 -> 8745 | F10: =2309+2406+2423 -> 7138 | G10: =2310+2696+3094 -> 8100 | H10: =2959+2646+1949 -> 7554 | I10: 8978 | J10: 8618 | K10: 9588 | L10: =3804+3819+3303 -> 10926 | M10: =3804+3819+3303 -> 10926 | N10: =4455+4458+5396 -> 14309 | O10: =4455+4458+5396 -> 14309 | P10: 11481 | Q10: 11481 | R10: 13572 | S10: 13572 | T10: =5352+4403+4198 -> 13953 | U10: =4954+5047+5501 -> 15502 | V10: 12889 | W10: 12123 | X10: =4731+4209+4143 -> 13083 | Y10: 8551 | Z10: 2793 | AA10: =3070+3736+4702 -> 11508 | AB10: =5401+5545+5878 -> 16824 | AC10: 17783 | AD10: 8937 | AE10: 14029 | AF10: 14772 | AG10: 16703 | AH10: 14664 | AI10: =5477+5742+6235 -> 17454 | AJ10: 16772 | AK10: 19206 | AL10: 15164 | AM10: 17760 | AN10: 17756 | AO10: 19120 | AP10: 16008 | AQ10: 17444 | AR10: 16346 | AS10: 19268 | AT10: 16167 | AU10: 18398 | AV10: 20249 | AW10: 22965 | AX10: 19339 | AZ10: =4954+5047+5501 -> 15502 | BA10: 12889 | BB10: 12123 | BC10: =4731+4209+4143 -> 13083 | BD10: =46646-X10-W10-V10 -> 8551 | BE10: 2793 | BF10: =3070+3736+4702 -> 11508 | BG10: =5401+5545+5878 -> 16824 | BH10: 17783 | BI10: 8937 | BJ10: 14029 | BK10: 14772 | BL10: 16703 | BM10: 14664 | BN10: =5477+5742+6235 -> 17454 | BO10: 16772 | BP10: 19206 | BQ10: 15164 | BR10: 17760 | BS10: =50680-AM10-AL10 -> 17756 | BT10: 19120 | BU10: 16008 | BV10: 17444 | BW10: 16346 | BX10: 19268 | BY10: 16167 | BZ10: 18398 | CA10: 20249 | CB10: 22965 | CC10: 19339 | CG10: ='Main Model'!AI296 -> 77779 | CI10: =+CC10/AW10-1 -> -0.15789245 | CJ10: =CG10-AV10-AU10-AT10 -> 22965 | CL10: =+CA10/AU10-1 -> 0.10060876
A11: Total CVs | B11: =+B10+B9 -> 28186 | C11: =+C10+C9 -> 37381 | D11: =+D10+D9 -> 30928 | E11: =+E10+E9 -> 43994 | F11: =+F10+F9 -> 31165 | G11: =+G10+G9 -> 33441 | H11: =+H10+H9 -> 32839 | I11: =+I10+I9 -> 47621 | J11: =+J10+J9 -> 28495 | K11: 40985 | L11: =+L10+L9 -> 46654 | M11: =+M10+M9 -> 46654 | N11: =+N10+N9 -> 58735 | O11: =+O10+O9 -> 58735 | P11: =+P10+P9 -> 42127 | Q11: =+Q10+Q9 -> 42127 | R11: =+R10+R9 -> 51959 | S11: =+S10+S9 -> 51959 | ... AX11: =+AX10+AX9 -> 48763 | AZ11: =+AZ10+AZ9 -> 59521 | BA11: =+BA10+BA9 -> 39608 | BB11: =+BB10+BB9 -> 28938 | BC11: =+BC10+BC9 -> 31200 | BD11: =+BD10+BD9 -> 25507 | BE11: =+BE10+BE9 -> 3814 | BF11: =+BF10+BF9 -> 19444 | BG11: =+BG10+BG9 -> 33410 | ... CC11: =+CC10+CC9 -> 48763 | CE11: =+E11+D11+B11+C11 -> 140489 | CG11: =+CG10+CG9 -> 220437 | CJ11: =CG11-AV11-AU11-AT11 -> 69458 | CK11: =+CJ11/AS11-1 -> 0.17375287 | CL11: =+CM11-CA11-AU11-AT11 -> 69458 | CM11: =+'Main Model'!AI10 -> 220437 | CN11: =+CL11/BX11-1 -> 0.17375287
A13: MIX & GROWTH RATIOS
A14: Product mix (%) | B14: =+B10/B11 -> 0.23774214 | C14: =+C10/C11 -> 0.20055643 | D14: =+D10/D11 -> 0.25064666 | E14: =+E10/E11 -> 0.19877711 | F14: =+F10/F11 -> 0.22903899 | G14: =+G10/G11 -> 0.24221764 | H14: =+H10/H11 -> 0.23003137 | I14: =+I10/I11 -> 0.18853027 | J14: =+J11/'New Qrtrly'!AV6-1 -> 269606.27 | K14: =+K11/'New Qrtrly'!AX6-1 -> #DIV/0! | L14: =+L11/'New Qrtrly'!AZ6-1 -> #DIV/0! | M14: =+M11/'New Qrtrly'!BA6-1 -> #DIV/0! | N14: =+N11/'New Qrtrly'!BB6-1 -> #DIV/0! | O14: =+O11/'New Qrtrly'!BA6-1 -> #DIV/0! | P14: =+P11/'New Qrtrly'!BD6-1 -> #DIV/0! | Q14: =+Q11/'New Qrtrly'!BE6-1 -> #DIV/0! | R14: =+R11/'New Qrtrly'!BF6-1 -> #DIV/0! | S14: =+S11/'New Qrtrly'!BH6-1 -> #DIV/0! | T14: =+T11/'New Qrtrly'!BH6-1 -> #DIV/0! | U14: =+U11/'New Qrtrly'!BJ6-1 -> #DIV/0! | V14: =+V11/'New Qrtrly'!BL6-1 -> #DIV/0! | W14: =+W11/'New Qrtrly'!BN6-1 -> #DIV/0! | X14: =+X11/'New Qrtrly'!BP6-1 -> #DIV/0! | Y14: =+Y11/'New Qrtrly'!BR6-1 -> #DIV/0! | Z14: =+Z11/'New Qrtrly'!BT6-1 -> #DIV/0! | AA14: =+AA11/'New Qrtrly'!BV6-1 -> #DIV/0! | AB14: =+AB11/'New Qrtrly'!BX6-1 -> #DIV/0! | AC14: =+AC11/'New Qrtrly'!BZ6-1 -> #DIV/0! | AD14: =+AD11/'New Qrtrly'!CB6-1 -> #DIV/0! | AE14: =+AE11/'New Qrtrly'!CD6-1 -> #DIV/0! | AF14: =+AF11/'New Qrtrly'!CF6-1 -> #DIV/0! | AG14: =+AG11/'New Qrtrly'!CH6-1 -> #DIV/0! | AH14: =+AH11/'New Qrtrly'!CJ6-1 -> #DIV/0! | AI14: =+AI11/'New Qrtrly'!CL6-1 -> #DIV/0! | AJ14: =+AJ11/'New Qrtrly'!CN6-1 -> #DIV/0! | AK14: =+AK11/'New Qrtrly'!CP6-1 -> #DIV/0! | AL14: =+AL11/'New Qrtrly'!CR6-1 -> #DIV/0! | AM14: =+AM11/'New Qrtrly'!CT6-1 -> #DIV/0! | AN14: =+AN11/'New Qrtrly'!CV6-1 -> #DIV/0! | AO14: =+AO11/'New Qrtrly'!CX6-1 -> #DIV/0! | AP14: =+AP11/'New Qrtrly'!CZ6-1 -> #DIV/0! | AQ14: =+AQ11/'New Qrtrly'!DB6-1 -> #DIV/0! | AR14: =+AR11/'New Qrtrly'!DD6-1 -> #DIV/0! | AS14: =+AS11/'New Qrtrly'!DF6-1 -> #DIV/0! | AT14: =+AT11/'New Qrtrly'!DH6-1 -> #DIV/0! | AU14: =+AU11/'New Qrtrly'!DJ6-1 -> #DIV/0! | AV14: =+AV11/'New Qrtrly'!DL6-1 -> #DIV/0! | AW14: =+AW11/'New Qrtrly'!DN6-1 -> #DIV/0! | AX14: =+AX11/'New Qrtrly'!DP6-1 -> #DIV/0! | AZ14: =+AZ11/'New Qrtrly'!BI6-1 -> #DIV/0! | BA14: =+BA11/'New Qrtrly'!BK6-1 -> #DIV/0! | BB14: =+BB11/'New Qrtrly'!BM6-1 -> #DIV/0! | BC14: =+BC11/'New Qrtrly'!BO6-1 -> #DIV/0! | BD14: =+BD11/'New Qrtrly'!BQ6-1 -> #DIV/0! | BE14: =+BE11/'New Qrtrly'!BS6-1 -> #DIV/0! | BF14: =+BF11/'New Qrtrly'!BU6-1 -> #DIV/0! | BG14: =+BG11/'New Qrtrly'!BW6-1 -> #DIV/0! | BH14: =+BH11/'New Qrtrly'!BY6-1 -> #DIV/0! | BI14: =+BI11/'New Qrtrly'!CA6-1 -> #DIV/0! | BJ14: =+BJ11/'New Qrtrly'!CC6-1 -> #DIV/0! | BK14: =+BK11/'New Qrtrly'!CE6-1 -> #DIV/0! | BL14: =+BL11/'New Qrtrly'!CG6-1 -> #DIV/0! | BM14: =+BM11/'New Qrtrly'!CI6-1 -> #DIV/0! | BN14: =+BN11/'New Qrtrly'!CK6-1 -> #DIV/0! | BO14: =+BO11/'New Qrtrly'!CM6-1 -> #DIV/0! | BP14: =+BP11/'New Qrtrly'!CO6-1 -> #DIV/0! | BQ14: =+BQ11/'New Qrtrly'!CQ6-1 -> #DIV/0! | BR14: =+BR11/'New Qrtrly'!CS6-1 -> #DIV/0! | BS14: =+BS11/'New Qrtrly'!CU6-1 -> #DIV/0! | BT14: =+BT11/'New Qrtrly'!CW6-1 -> #DIV/0! | BU14: =+BU11/'New Qrtrly'!CY6-1 -> #DIV/0! | BV14: =+BV11/'New Qrtrly'!DA6-1 -> #DIV/0! | BW14: =+BW11/'New Qrtrly'!DC6-1 -> #DIV/0! | BX14: =+BX11/'New Qrtrly'!DE6-1 -> #DIV/0! | BY14: =+BY11/'New Qrtrly'!DG6-1 -> #DIV/0! | BZ14: =+BZ11/'New Qrtrly'!DI6-1 -> #DIV/0! | CA14: =+CA11/'New Qrtrly'!DK6-1 -> #DIV/0! | CB14: =+CB11/'New Qrtrly'!DM6-1 -> #DIV/0! | CC14: =+CC11/'New Qrtrly'!DO6-1 -> #DIV/0!
A15: H / MCVs | J15: =+J10/J11 -> 0.30243902 | K15: =+K10/K11 -> 0.23393925 | L15: =+L10/L11 -> 0.23419214 | M15: =+M10/M11 -> 0.23419214 | N15: =+N10/N11 -> 0.24361965 | O15: =+O10/O11 -> 0.24361965 | P15: =+P10/P11 -> 0.27253305 | Q15: =+Q10/Q11 -> 0.27253305 | ... AX15: =+AX10/AX11 -> 0.39659168 | AZ15: =+AZ10/AZ11 -> 0.26044589 | BA15: =+BA10/BA11 -> 0.32541406 | BB15: =+BB10/BB11 -> 0.41893013 | BC15: =+BC10/BC11 -> 0.41932692 | BD15: =+BD10/BD11 -> 0.33524131 | BE15: =+BE10/BE11 -> 0.73230205 | BF15: =+BF10/BF11 -> 0.59185353 | BG15: =+BG10/BG11 -> 0.50356181 | ... CC15: =+CC10/CC11 -> 0.39659168
A16: LCVs | J16: =J11+K11 -> 69480 | K16: =157000/J16*(J35+J34+K35+K34) -> 163722.56 | L16: =157000/K16*(K35+K34+L35+L34) -> 90003.743 | M16: =157000/L16*(L35+L34+M35+M34) -> 176050.22 | N16: =157000/L16*(L35+L34+N35+N34) -> 198646.35 | O16: =157000/M16*(M35+M34+O35+O34) -> 100402.47 | P16: =157000/N16*(N35+N34+P35+P34) -> 84229.067 | Q16: =157000/O16*(O35+O34+Q35+Q34) -> 165203.26 | R16: =157000/P16*(P35+P34+R35+R34) -> 184158.46 | S16: =157000/R16*(R35+R34+S35+S34) -> 94003.183 | T16: =157000/R16*(R35+R34+T35+T34) -> 84950.117 | Z16: =+Z33*0.2 -> 1301.74 | AA16: =0.45*AA33 -> 12764.61 | AB16: =0.56*AB33 -> 26955.656 | BF16: =+Z16/Z9*BF9*1.05 -> 10624.034
A17: Market share (%) | Z17: =+Z31*0.21 -> 1366.827 | AA17: =+AA31*0.21 -> 5956.818 | AB17: =+AB9*2+AB10*0.7 -> 44948.8 | BF17: =+Z17/Z10*BF10 -> 5631.7383
A18: H / MCVs | P18: =+P11/J11-1 -> 0.47839972 | R18: =+R11/K11-1 -> 0.2677565 | T18: =+T11/M11-1 -> -0.06196682 | U18: =+U11/O11-1 -> 0.01338214 | Z18: =0.25*Z31 -> 1627.175 | AA18: =0.25*AA31 -> 7091.45 | AC18: =0.65*AC31 -> 45503.185 | AD18: =0.52*AD33 -> 15345.148 | AE18: =0.52*AE33 -> 23180.82 | AF18: =0.52*AF33 -> 28782.832 | AG18: =0.52*AG33 -> 45470.308 | AH18: =0.52*AH33 -> 37558.82 | AI18: =0.52*AI33 -> 42982.94 | AJ18: =0.52*AJ33 -> 46954.284 | AK18: =0.52*AK33 -> 60453.484 | ... AS18: =0.52*AS33 -> 61914.892 | BF18: =+Z18*2 -> 3254.35 | BX18: =0.52*BX33 -> 63797.987
A19: LCVs and others | Z19: =+Z31-Z18-Z17-Z16 -> 2212.958 | AA19: =+AA31-AA18-AA17-AA16 -> 2552.922 | AC19: =+AC31-AC18 -> 24501.715 | AD19: =+AD31-AD18 -> 14164.752 | AE19: =+AE31-AE18 -> 21397.68 | AF19: =+AF31-AF18 -> 26568.768 | AG19: =+AG31-AG18 -> 41972.592 | AH19: =+AH31-AH18 -> 34669.68 | AI19: =+AI31-AI18 -> 39676.56 | AJ19: =+AJ31-AJ18 -> 43342.416 | ... AS19: =+AS31-AS18 -> 57152.208 | BF19: =+Z19*1.2 -> 2655.5496 | BX19: =+BX31-BX18 -> -63797.987
A20: Volumes (Nos.) | AA20: =+AA10/AA11 -> 0.59185353 | AB20: =+AB10/AB11 -> 0.50356181 | AC20: =+AC10/AC11 -> 0.40360872 | AD20: =+AD10/AD11 -> 0.49685884 | AE20: =+AE10/AE11 -> 0.50934902 | AF20: =+AF10/AF11 -> 0.43348886 | AG20: =+AG10/AG11 -> 0.34284365 | AH20: =+AH10/AH11 -> 0.36982674 | ... AX20: =+AX10/AX11 -> 0.39659168 | BI20: =+BI10/BI11 -> 0.49685884 | BJ20: =+BJ10/BJ11 -> 0.50934902 | BK20: =+BK10/BK11 -> 0.43348886 | BL20: =+BL10/BL11 -> 0.34284365 | BM20: =+BM10/BM11 -> 0.36982674 | BN20: =+BN10/BN11 -> 0.38534055 | BO20: =+BO10/BO11 -> 0.35263446 | BP20: =+BP10/BP11 -> 0.32172471 | ... CC20: =+CC10/CC11 -> 0.39659168
A22: REVENUE BUILD
A23: Engine Sales (Rs m)
A24: Spare parts+Kits (Rs m) | X24: =+(X35+X34)/X11*1000000 -> 946548.08 | Y24: =+(Y35+Y34)/Y11*1000000 -> 1069886.7 | Z24: =+(Z35+Z34)/Z11*1000000 -> 1094520.2 | AA24: =+(AA35+AA34)/AA11*1000000 -> 1038911.7 | AB24: =+(AB35+AB34)/AB11*1000000 -> 1072256.8 | AC24: =+(AC35+AC34)/AC11*1000000 -> 1221831.6 | AD24: =+(AD35+AD34)/AD11*1000000 -> 1216017.1 | AE24: =+(AE35+AE34)/AE11*1000000 -> 1241164.7 | ... AX24: =+(AX35+AX34)/AX11*1000000 -> 1413446.7 | BX24: =+(BX35+BX34)/BX11*1000000 -> 1482395.4
A25: Defence (kits)
A26: Discounts | P26: 375000 | Q26: 375000 | S26: 405000 | Y26: =+Y27/X27-1 -> 0.16922038 | Z26: =+Z27/Y27-1 -> 0.1340075 | AA26: =+AA27/Z27-1 -> -0.1451383 | AB26: =+AB27/AA27-1 -> -0.012411603 | AC26: =+AC27/AB27-1 -> 0.10280454 | AD26: =+AD27/AC27-1 -> 0.032583204 | AE26: =+AE27/AD27-1 -> -0.013481564 | AF26: =+AF27/AE27-1 -> 0.0035860501 | ... AX26: =+AX27/AW27-1 -> -0.030883483 | BX26: =+BX27/BW27-1 -> 0.062780784
A27: Average Realisations (Rs m) | B27: =B33/B11*1000000 -> 1377680.7 | C27: =C33/C11*1000000 -> 1328797.9 | D27: =D33/D11*1000000 -> 1330133.8 | E27: =E33/E11*1000000 -> 1357720.5 | F27: =F33/F11*1000000 -> 1366545.7 | G27: =G33/G11*1000000 -> 1382257.1 | H27: =H33/H11*1000000 -> 1375281.2 | I27: =I33/I11*1000000 -> 1389698.9 | ... AX27: =AX33/AX11*1000000 -> 1975750.1 | AZ27: =T27*0.99 -> 1430886.3 | BA27: =U27 -> 1486186.4 | BB27: =+V27*0.98 -> 1406327.7 | BC27: =+W27*0.975 -> 1323955.5 | BD27: =+X27 -> 1287067.3 | BE27: =+Y27*1.1 -> 1655351.9 | BF27: =+Z27*0.95 -> 1621202.1 | BG27: =+AA27*1.04 -> 1517199.8 | BH27: =+AB27*1.025 -> 1476757.8 | BI27: =+AC27*0.95 -> 1509411.1 | BJ27: =+AD27*1.02 -> 1673436.3 | BK27: =+AE27*1.03 -> 1667060.8 | BL27: =+AF27*1.03 -> 1673038.9 | BM27: =+AG27 -> 1794841.8 | BN27: =+AH27*1.005 -> 1830714 | BO27: =+AI27*1.013 -> 1848638.3 | BP27: =+AJ27*1.012 -> 1921287.2 | BQ27: =+AK27*1 -> 1947446.3 | BR27: =+AL27*0.98 -> 1941857.8 | BS27: =+AM27*0.98 -> 1894892.1 | BT27: =+AN27*1.005 -> 1972730.3 | BU27: =+AO27*0.98 -> 1962245 | BV27: =+AP27*0.98 -> 1919795.7 | BW27: =+AQ27*1.015 -> 1950807.1 | BX27: =+AR27*1.015 -> 2073280.3 | BY27: =+AS27*0.98 -> 1971842.6 | BZ27: =+AT27*0.995 -> 1962314.6 | CA27: =+AU27*1.015 -> 1981432.3 | CB27: =+AV27*1.0135 -> 2028556.5 | CC27: =+AW27*0.99 -> 2018325.5
A28: (INR m) | BC28: =+BC27-W27 -> -33947.578 | BD28: =+BD27-X27 -> 0 | BE28: =+BE27-Y27 -> 150486.53 | BF28: =+BF27-Z27 -> -85326.429
A30: INCOME STATEMENT (INR m)
A31: Gross Sales | B31: =40076.081+1078.347 -> 41154.428 | C31: =51859.991+883.674 -> 52743.665 | D31: =42819.741+843.781 -> 43663.522 | E31: 62368.127 | F31: =44482.826+830.465 -> 45313.291 | G31: =47923.842+1192.4 -> 49116.242 | H31: 48282.549 | I31: 70572.209 | J31: 45344.621 | K31: 60763.825 | L31: 71131.62 | M31: 71906.6 | N31: 87724.91 | O31: 87800.9 | P31: 62501.254 | Q31: 62627.2 | R31: 76079.801 | S31: 76210.6 | T31: 63252.4 | U31: 88459.3 | V31: 56838.6 | W31: 39295 | X31: 40156.5 | Y31: 38384.6 | Z31: 6508.7 | AA31: 28365.8 | AB31: 48135.1 | AC31: 70004.9 | AD31: =29345.9+164 -> 29509.9 | AE31: 44578.5 | AF31: 55351.6 | AG31: 87442.9 | AH31: 72228.5 | AI31: 82659.5 | AJ31: 90296.7 | AK31: 116256.7 | AL31: 81892.9 | AM31: 96380.4 | AN31: 92730.1 | AO31: 112666.9 | AP31: 85985.3 | AQ31: 87688.3 | AR31: 94786.7 | AS31: 119067.1 | AT31: 87245.1 | AU31: 95881.8 | AV31: 115338.5 | AW31: 141604.9 | AX31: 96343.5
A32: Less: Excise duty | B32: 2323.12 | C32: 3071.869 | D32: 2525.143 | E32: 2636.57 | F32: 2724.894 | G32: 2892.181 | H32: 3119.691 | I32: 4393.357 | J32: 2766.04
A33: Net sales | B33: =+B31-B32 -> 38831.308 | C33: =+C31-C32 -> 49671.796 | D33: =+D31-D32 -> 41138.379 | E33: =+E31-E32 -> 59731.557 | F33: =+F31-F32 -> 42588.397 | G33: =+G31-G32 -> 46224.061 | H33: =+H31-H32 -> 45162.858 | I33: =+I31-I32 -> 66178.852 | J33: =J31-J32 -> 42578.581 | K33: =K31-K32 -> 60763.825 | L33: =L31-L32 -> 71131.62 | M33: =M31-M32 -> 71906.6 | N33: =N31-N32 -> 87724.91 | O33: =O31-O32 -> 87800.9 | P33: =P31-P32 -> 62501.254 | Q33: =Q31-Q32 -> 62627.2 | ... AX33: =AX31-AX32 -> 96343.5 | AZ33: =AZ27*AZ11/10^6 -> 85167.782 | BA33: =BA27*BA11/10^6 -> 58864.87 | BB33: =BB27*BB11/10^6 -> 40696.311 | BC33: =BC27*BC11/10^6 -> 41307.412 | BD33: =BD27*BD11/10^6 -> 32829.226 | BE33: =BE27*BE11/10^6 -> 6313.512 | BF33: =BF27*BF11/10^6 -> 31522.655 | BG33: =BG27*BG11/10^6 -> 50689.644 | ... CC33: =CC27*CC11/10^6 -> 98419.605 | CE33: =+E33+D33+B33+C33 -> 189373.04 | CG33: ='Main Model'!AI19 -> 440070.3 | CJ33: =CG33-AV33-AU33-AT33 -> 141604.9 | CL33: =+CM33-CA33-AU33-AT33 -> 142763.37 | CM33: =+'Main Model'!AI19 -> 440070.3 | CN33: =+CL33/BX33-1 -> 0.16362527
A34: Decrease/(Increase) in Stocks | B34: -2469.627 | C34: -2430.844 | D34: -2487.722 | E34: 3097.979 | F34: -1548.179 | G34: 1557.41 | H34: -6592.28 | I34: -507.764 | J34: -2847.014 | K34: 6081.489 | L34: -8731.179 | M34: -10095.8 | N34: 20905.657 | O34: 19662.6 | P34: -9276.384 | Q34: -9350.9 | R34: -10.775 | S34: -88.9 | T34: -10940.7 | U34: 10792.5 | V34: -7138.3 | W34: 3663 | X34: 9655.9 | Y34: 5734.1 | Z34: 180.1 | AA34: -1022.3 | AB34: -2304.3 | AC34: -1476.6 | AD34: -2578.9 | AE34: 1560.3 | AF34: -918.1 | AG34: 1446.8 | AH34: -6622.6 | AI34: 3407 | AJ34: -6100.1 | AK34: 3730.8 | AL34: -1975 | AM34: -2609 | AN34: -2261.1 | AO34: 1735.7 | AP34: -4108.9 | AQ34: 605.4 | AR34: 134.9 | AS34: 5674.4 | AT34: -6509.3 | AU34: 1640.8 | AV34: 2912.1 | AW34: 847.1 | AX34: -5051.9 | CE34: =+E34+D34+B34+C34 -> -4290.214
A35: Raw Materials | B35: =25492.433+3549.388 -> 29041.821 | C35: =32585.377+4458.318 -> 37043.695 | D35: =26126.584+5116.026 -> 31242.61 | E35: =36775.559+2188.523 -> 38964.082 | F35: =27226.302+3569.379 -> 30795.681 | G35: =25667.731+4111.572 -> 29779.303 | H35: =34094.779+3850.037 -> 37944.816 | I35: =43565.808+4545.451 -> 48111.259 | J35: =28211.092+4051.282 -> 32262.374 | K35: =32590.943+4367.261 -> 36958.204 | L35: =54064.829+5484.256 -> 59549.085 | M35: =58278.7+1923.9 -> 60202.6 | N35: =35925.396+6229.478 -> 42154.874 | O35: =40923+1892.8 -> 42815.8 | P35: =47530.8+5257.004 -> 52787.804 | Q35: =50476+2045 -> 52521 | R35: =49685.064+5613.624 -> 55298.688 | S35: =53466.7+1598.5 -> 55065.2 | T35: =53192+2105.9 -> 55297.9 | U35: =51588+1911.6 -> 53499.6 | V35: =44963.4+1911.5 -> 46874.9 | W35: =21726.1+1743.9 -> 23470 | X35: =17602.6+2273.8 -> 19876.4 | Y35: =19552.5+2003 -> 21555.5 | Z35: =3250.2+744.2 -> 3994.4 | AA35: =19223.7+1999.2 -> 21222.9 | AB35: =35981.2+2147.2 -> 38128.4 | AC35: =2576+52734.5 -> 55310.5 | AD35: =22334+2117.4 -> 24451.4 | AE35: =30925.4+1699.7 -> 32625.1 | AF35: =41573.6+2475.6 -> 44049.2 | AG35: =64298.6+2676.3 -> 66974.9 | AH35: =61313.6+2589.5 -> 63903.1 | AI35: =58320.3+2738.5 -> 61058.8 | AJ35: =2925.3+72033.3 -> 74958.6 | AK35: =80802.3+3353.6 -> 84155.9 | AL35: =58764.2+3582.3 -> 62346.5 | AM35: =3551.7+69922.8 -> 73474.5 | AN35: =65553.6+3684.9 -> 69238.5 | AO35: =74924.8+4245.2 -> 79170 | AP35: =61988+4167.3 -> 66155.3 | AQ35: =57735.4+4069.6 -> 61805 | AR35: =63674+3933.9 -> 67607.9 | AS35: =73720+4633.8 -> 78353.8 | AT35: =63866.3+4271.3 -> 68137.6 | AU35: =62103.5+4492.6 -> 66596.1 | AV35: =75901.7+4439.2 -> 80340.9 | AW35: =95355.3+4850.8 -> 100206.1 | AX35: =69206.4+4769.4 -> 73975.8 | AZ35: =AZ71/100*AZ33 -> 61320.803 | BA35: =BA71/100*BA33 -> 42382.707 | BB35: =BB71/100*BB33 -> 28283.936 | BC35: =BC71/100*BC33 -> 28667.344 | BD35: =BD71/100*BD33 -> 24195.139 | BE35: =BE71/100*BE33 -> 4482.5935 | BF35: =BF71/100*BF33 -> 21435.405 | BG35: =BG71/100*BG33 -> 36243.095 | ... CC35: =CC71/100*CC33 -> 72043.151 | CE35: =+E35+D35+B35+C35 -> 136292.21 | CG35: ='Main Model'!AI25 -> 314171.4 | CJ35: =CG35-AV35-AV34-AU35-AU34-AT35-AT34 -> 101053.2
A36: Staff costs | B36: 3287.136 | C36: 3763.162 | D36: 3474.789 | E36: 3325.541 | F36: 3581.296 | G36: 3692.046 | H36: 3917.767 | I36: 4118.241 | J36: 4217.456 | K36: 4660.319 | L36: 4917.685 | M36: 4766.4 | N36: 4549.2 | O36: 4588 | P36: 4929.916 | Q36: 5001.4 | R36: 5173.61 | S36: 5250.8 | T36: 5000.7 | U36: 5734.8 | V36: 5004.3 | W36: 4321.2 | X36: 2727.9 | Y36: 4097.2 | Z36: 3541.9 | AA36: 3736.2 | AB36: 4544.8 | AC36: 4016 | AD36: 4243.1 | AE36: 4003 | AF36: 4324.1 | AG36: 4375.8 | AH36: 4454.1 | AI36: 5270.5 | AJ36: 5494.7 | AK36: 5919.3 | AL36: 5375.6 | AM36: 5728.3 | AN36: 5694.6 | AO36: 5535.3 | AP36: 5497.5 | AQ36: 5986.8 | AR36: 6063.5 | AS36: 6514.9 | AT36: 6121.9 | AU36: 6477.8 | AV36: 6251.6 | AW36: 7215.6 | AX36: 6927.1 | AZ36: 5000 | BA36: 4700 | BB36: 4800 | BC36: 4350 | BD36: 2800 | BE36: 2400 | BF36: 4000 | BG36: 4000 | BH36: 4600 | BI36: 3900 | BJ36: 4500 | BK36: 4400 | BL36: 4400 | BM36: 4400 | BN36: 4500 | BO36: 5300 | BP36: 5300 | BQ36: 5920 | BR36: 5400 | BS36: 5800 | BT36: 5800 | BU36: 5600 | BV36: 5550 | BW36: 6000 | BX36: 6200 | BY36: 6450 | BZ36: 6350 | CA36: 6600 | CB36: 6400 | CC36: 6800 | CE36: =+E36+D36+B36+C36 -> 13850.628 | CG36: ='Main Model'!AI32 -> 26066.9 | CJ36: =CG36-AV36-AU36-AT36 -> 7215.6
A37: Other Expenses | B37: 5046.968 | C37: 5055.557 | D37: 4416.103 | E37: 6508.869 | F37: 4939.273 | G37: 5830.432 | H37: 5351.395 | I37: 7158.1 | J37: 5885.039 | K37: 6945.844 | L37: 7511.752 | M37: 8640.3 | N37: 9788.344 | O37: 9478.1 | P37: 7584.45 | Q37: 7739.3 | R37: 7558.964 | S37: 7693.2 | T37: 7398.2 | U37: 8578 | V37: 6728 | W37: 5555 | X37: 5644.8 | Y37: 5168.3 | Z37: 2124.7 | AA37: 3624.7 | AB37: 5228.3 | AC37: 6813.4 | AD37: 4795.3 | AE37: 5043.2 | AF37: 5657.5 | AG37: 6885 | AH37: 7291.1 | AI37: 7549.8 | AJ37: 7970.1 | AK37: 9693.3 | AL37: 7938.3 | AM37: 8988.7 | AN37: 8918.8 | AO37: 10304.8 | AP37: 9332.7 | AQ37: 9118.1 | AR37: 8866.1 | AS37: 10614.4 | AT37: 9799.4 | AU37: 9545.5 | AV37: 10483.7 | AW37: 12680.9 | AX37: 10797.2 | AZ37: 9750 | BA37: 7300 | BB37: 5800 | BC37: 5800 | BD37: 5200 | BE37: 2500 | BF37: 5000 | BG37: 6200 | BH37: 6300 | BI37: 3500 | BJ37: 5500 | BK37: 5600 | BL37: 6500 | BM37: 6000 | BN37: =+AH37*1.08 -> 7874.388 | BO37: =+AI37*1.04 -> 7851.792 | BP37: =+AJ37*1.25 -> 9962.625 | BQ37: 7900 | BR37: 9300 | BS37: 8800 | BT37: =+AN37*1.17 -> 10434.996 | BU37: 9200 | BV37: 9450 | BW37: =+AQ37*1.01 -> 9209.281 | BX37: 11400 | BY37: 8900 | BZ37: 10500 | CA37: 10800 | CB37: 12400 | CC37: 10000 | CE37: =+E37+D37+B37+C37 -> 21027.497 | CG37: ='Main Model'!AI38+'Main Model'!AI35+'Main Model'!AI41 -> 44309.5 | CJ37: =CG37-AV37-AU37-AT37 -> 14480.9
A38: Provision for contingencies | CE38: =+E38+D38+B38+C38 -> 0
A39: Total Expenditure | B39: =SUM(B34:B38) -> 34906.298 | C39: =SUM(C34:C38) -> 43431.57 | D39: =SUM(D34:D38) -> 36645.78 | E39: =SUM(E34:E38) -> 51896.471 | F39: =SUM(F34:F38) -> 37768.071 | G39: =SUM(G34:G38) -> 40859.191 | H39: =SUM(H34:H38) -> 40621.698 | I39: =SUM(I34:I38) -> 58879.836 | ... AX39: =SUM(AX34:AX38) -> 86648.2 | AZ39: =SUM(AZ34:AZ38) -> 76070.803 | BA39: =SUM(BA34:BA38) -> 54382.707 | BB39: =SUM(BB34:BB38) -> 38883.936 | BC39: =SUM(BC34:BC38) -> 38817.344 | BD39: =SUM(BD34:BD38) -> 32195.139 | BE39: =SUM(BE34:BE38) -> 9382.5935 | BF39: =SUM(BF34:BF38) -> 30435.405 | BG39: =SUM(BG34:BG38) -> 46443.095 | ... CC39: =SUM(CC34:CC38) -> 88843.151 | CE39: =SUM(CE34:CE38) -> 166880.12
A40: EBITDA | B40: =B33-B39 -> 3925.01 | C40: =C33-C39 -> 6240.226 | D40: =D33-D39 -> 4492.599 | E40: =E33-E39 -> 7835.086 | F40: =F33-F39 -> 4820.326 | G40: =G33-G39 -> 5364.87 | H40: =H33-H39 -> 4541.16 | I40: =I33-I39 -> 7299.016 | ... AX40: =AX33-AX39 -> 9695.3 | AZ40: =AZ33-AZ39 -> 9096.9789 | BA40: =BA33-BA39 -> 4482.1637 | BB40: =BB33-BB39 -> 1812.375 | BC40: =BC33-BC39 -> 2490.0682 | BD40: =BD33-BD39 -> 634.08639 | BE40: =BE33-BE39 -> -3069.0815 | BF40: =BF33-BF39 -> 1087.2495 | BG40: =BG33-BG39 -> 4246.5485 | ... CC40: =CC33-CC39 -> 9576.4542 | CE40: =CE33-CE39 -> 22492.921 | CG40: ='Main Model'!AI47 -> 57322.5 | CJ40: =CG40-AV40-AU40-AT40 -> 20655.2 | CL40: =+CM40-CA40-AU40-AT40 -> 21206.63 | CM40: =+'Main Model'!AI47 -> 57322.5 | CN40: =+CL40/BX40-1 -> 0.22114365
A41: Forex gain / (losses) | B41: -180.481 | C41: -79.465 | D41: -17.185 | E41: 327.611 | F41: 496.708 | G41: 65.683 | H41: -637.1 | I41: 228.683 | J41: -26.73 | K41: -26.428 | L41: -1.942 | M41: -26.1 | N41: 59.013 | O41: 68.1 | P41: -62.748 | Q41: -36.9 | S41: 19.7 | T41: -9.4 | U41: 0.3 | V41: 0.1
A42: Interest | B42: 701.188 | C42: 630.543 | D42: 603.181 | E42: 541.475 | F42: 338.239 | G42: 339.242 | H42: 453.315 | I42: 422.991 | J42: 366.312 | K42: 410.243 | L42: 335.257 | M42: 367.8 | N42: 200.647 | O42: 243.8 | P42: 115.925 | Q42: 141.9 | R42: 173.715 | S42: 204.1 | T42: 191.7 | U42: 166.1 | V42: 125.5 | W42: 301.2 | X42: 336.8 | Y42: 331 | Z42: 768.4 | AA42: 872.4 | AB42: 656.4 | AC42: 770.7 | AD42: 707.4 | AE42: 870.8 | AF42: 668.3 | AG42: 764.6 | AH42: 688.8 | AI42: 770.5 | AJ42: 804 | AK42: 627.6 | AL42: 698.7 | AM42: 587.1 | AN42: 616.3 | AO42: 592.3 | AP42: 590.5 | AQ42: 606.8 | AR42: 500.6 | AS42: 471.2 | AT42: 418.6 | AU42: 419.8 | AV42: 438.3 | AW42: 420.6 | AX42: 415.3 | AZ42: 185 | BA42: 130 | BB42: 125 | BC42: 250 | BD42: 340 | BE42: 340 | BF42: 340 | BG42: 600 | BH42: 600 | BI42: 650 | BJ42: 750 | BK42: 820 | BL42: 700 | BM42: 750 | BN42: 680 | BO42: 780 | BP42: 800 | BQ42: 800 | BR42: 750 | BS42: 580 | BT42: 600 | BU42: 600 | BV42: 600 | BW42: 600 | BX42: 520 | BY42: 480 | BZ42: 410 | CA42: 420 | CB42: 450 | CC42: 400 | CG42: ='Main Model'!AI49 -> 1697.3 | CJ42: =CG42-AV42-AU42-AT42 -> 420.6
A43: Other income | B43: 258.814 | C43: 454.412 | D43: 297.941 | E43: 218.425 | F43: 385.174 | G43: 316.144 | H43: 257.816 | I43: 403.567 | J43: 384.089 | K43: 556.604 | L43: 379.657 | M43: 417.3 | N43: 577.297 | O43: 594.1 | P43: 499.85 | Q43: 524.7 | R43: 281.452 | S43: 275.9 | T43: 208 | U43: 90.8 | V43: 210.7 | W43: 455 | X43: 223.3 | Y43: 344.4 | Z43: 256.2 | AA43: 218.7 | AB43: 340.6 | AC43: 379.5 | AD43: 134 | AE43: 209.3 | AF43: 176.4 | AG43: 241.6 | AH43: 256.4 | AI43: 199.9 | AJ43: 315.9 | AK43: 389.2 | AL43: 511.8 | AM43: 474.6 | AN43: 300.3 | AO43: 1179 | AP43: 223.4 | AQ43: 972.7 | AR43: 247.1 | AS43: 1059.3 | AT43: 528.5 | AU43: 1347.8 | AV43: 592.5 | AW43: 682.9 | AX43: 851 | AZ43: 200 | BA43: 600 | BB43: 200 | BC43: 400 | BD43: 250 | BE43: 250 | BF43: 250 | BG43: 200 | BH43: 250 | BI43: 350 | BJ43: 200 | BK43: 200 | BL43: 180 | BM43: 200 | BN43: 240 | BO43: 220 | BP43: 300 | BQ43: 300 | BR43: 450 | BS43: 450 | BT43: 300 | BU43: 1000 | BV43: 250 | BW43: 350 | BX43: 250 | BY43: 1050 | BZ43: 500 | CA43: 700 | CB43: 800 | CC43: 670 | CG43: ='Main Model'!AI50 -> 3151.7 | CJ43: =CG43-AV43-AU43-AT43 -> 682.9
A44: EBDT | B44: =B40-B42+B43+B41 -> 3302.155 | C44: =C40-C42+C43+C41 -> 5984.63 | D44: =D40-D42+D43+D41 -> 4170.174 | E44: =E40-E42+E43+E41 -> 7839.647 | F44: =F40-F42+F43+F41 -> 5363.969 | G44: =G40-G42+G43+G41 -> 5407.455 | H44: =H40-H42+H43+H41 -> 3708.561 | I44: =I40-I42+I43+I41 -> 7508.275 | ... AX44: =AX40-AX42+AX43+AX41 -> 10131 | AZ44: =AZ40-AZ42+AZ43+AZ41 -> 9111.9789 | BA44: =BA40-BA42+BA43+BA41 -> 4952.1637 | BB44: =BB40-BB42+BB43+BB41 -> 1887.375 | BC44: =BC40-BC42+BC43+BC41 -> 2640.0682 | BD44: =BD40-BD42+BD43+BD41 -> 544.08639 | BE44: =BE40-BE42+BE43+BE41 -> -3159.0815 | BF44: =BF40-BF42+BF43+BF41 -> 997.24947 | BG44: =BG40-BG42+BG43+BG41 -> 3846.5485 | ... CC44: =CC40-CC42+CC43+CC41 -> 9846.4542 | CE44: =CE40-CE42+CE43-CE41 -> 22492.921 | CG44: ='Main Model'!AI51 -> 58776.9 | CJ44: =CG44-AV44-AU44-AT44 -> 20917.5
A45: Depreciation & Amortization | B45: 1137.683 | C45: 1231.124 | D45: 1194.226 | E45: 1315.971 | F45: 1209.725 | G45: 1261.107 | H45: 1313.35 | I45: 1394.757 | J45: 1321.32 | K45: 1411.354 | L45: 1350.371 | M45: 1459.5 | N45: 1463.049 | O45: 1574.2 | P45: 1430.462 | Q45: 1524.8 | R45: 1401.846 | S45: 1481.1 | T45: 1606.6 | U45: 1597.6 | V45: 1646.4 | W45: 1600.4 | X45: 1574.6 | Y45: 1876.6 | Z45: 1636.7 | AA45: 1711.6 | AB45: 1944.3 | AC45: 2184.5 | AD45: 1834.9 | AE45: 1842.7 | AF45: 1896.5 | AG45: 1953.5 | AH45: 1824 | AI45: 1767.9 | AJ45: 1889.5 | AK45: 1838.2 | AL45: 1793.6 | AM45: 1802.9 | AN45: 1784.7 | AO45: 1796.9 | AP45: 1727.2 | AQ45: 1754.4 | AR45: 1923.3 | AS45: 1788.5 | AT45: 1828.1 | AU45: 1723 | AV45: 1774.6 | AW45: 1826.2 | AX45: 1829.2 | AZ45: 1620 | BA45: 1580 | BB45: 1620 | BC45: 1600 | BD45: 1550 | BE45: 1880 | BF45: 1800 | BG45: 1750 | BH45: 2000 | BI45: 2200 | BJ45: 1850 | BK45: 1850 | BL45: 1900 | BM45: 1960 | BN45: 1850 | BO45: 1800 | BP45: 1900 | BQ45: 1900 | BR45: 1850 | BS45: 1820 | BT45: 1820 | BU45: 1820 | BV45: 1750 | BW45: 1760 | BX45: 2000 | BY45: 1850 | BZ45: 1880 | CA45: 1750 | CB45: 1790 | CC45: 1840 | CE45: =+E45+D45+B45+C45 -> 4879.004 | CG45: ='Main Model'!AI53 -> 7151.9 | CJ45: =CG45-AV45-AU45-AT45 -> 1826.2
A46: PBT | B46: =+B44-B45 -> 2164.472 | C46: =+C44-C45 -> 4753.506 | D46: =+D44-D45 -> 2975.948 | E46: =+E44-E45 -> 6523.676 | F46: =+F44-F45 -> 4154.244 | G46: =+G44-G45 -> 4146.348 | H46: =+H44-H45 -> 2395.211 | I46: =+I44-I45 -> 6113.518 | ... AX46: =+AX44-AX45 -> 8301.8 | AZ46: =+AZ44-AZ45 -> 7491.9789 | BA46: =+BA44-BA45 -> 3372.1637 | BB46: =+BB44-BB45 -> 267.37495 | BC46: =+BC44-BC45 -> 1040.0682 | BD46: =+BD44-BD45 -> -1005.9136 | BE46: =+BE44-BE45 -> -5039.0815 | BF46: =+BF44-BF45 -> -802.75053 | BG46: =+BG44-BG45 -> 2096.5485 | ... CC46: =+CC44-CC45 -> 8006.4542 | CE46: =+CE44-CE45 -> 17613.917 | CG46: ='Main Model'!AI55 -> 48140.2 | CJ46: =CG46-AV46-AU46-AT46 -> 15606.5
A47: Exceptional income | I47: 3240 | N47: 0.032 | CE47: =+E47+D47+B47+C47 -> 0
A48: Exceptional expenditure | C48: 1570 | D48: 50 | E48: 6532.235 | I48: 3508.459 | J48: 125.692 | M48: 29.1 | O48: 44.1 | P48: 146.593 | Q48: 177.9 | R48: 159.431 | S48: 192.7 | T48: 60.9 | U48: 117.1 | V48: 201.2 | W48: 648.1 | X48: 21.7 | Y48: 687.3 | Z48: 16.7 | AA48: 17 | AB48: 460.3 | AC48: -373.5 | AD48: 16.8 | AE48: -2.3 | AF48: -420.2 | AG48: -4702.6 | AH48: -130.1 | AI48: -82.3 | AJ48: -69.4 | AK48: -564.3 | AL48: 5.9 | AM48: 228.8 | AN48: 5.9 | AO48: 696.6 | AQ48: -1173.8 | AS48: 136.5 | AU48: 400 | AV48: 3084.8 | BD48: 29 | CE48: =+E48+D48+B48+C48 -> 8152.235 | CG48: =-'Main Model'!AI54 -> 3484.8 | CJ48: =CG48-AV48-AU48-AT48 -> 0
A49: Tax | B49: 719.511 | C49: 1461.412 | D49: 788.903 | E49: =1217.458+182.098 -> 1399.556 | F49: 1246.4 | G49: 1202.248 | H49: =729.644+48.407 -> 778.051 | I49: =-369.505-1787.105+3240 -> 1083.39 | J49: =662.146-169.739 -> 492.407 | K49: =1795.998-312.047 -> 1483.951 | L49: =2383.724-304.458 -> 2079.266 | M49: =2383.8-304.5 -> 2079.3 | N49: =1930.853+694.781 -> 2625.634 | O49: =1930.6+694.7 -> 2625.3 | P49: =1566.12-47.541 -> 1518.579 | Q49: =1179.3-36 -> 1143.3 | R49: =2060.561-50.579 -> 2009.982 | S49: =1475.7-45.1 -> 1430.6 | T49: =1059.6-32.3 -> 1027.3 | U49: =67.4+1467.4 -> 1534.8 | V49: =1416.1-110.9 -> 1305.2 | W49: =-665.9+468.3 -> -197.6 | X49: =411.7-147.5 -> 264.2 | Y49: =296.7-444.5 -> -147.8 | Z49: =-1610.1+0.1 -> -1610 | AA49: =-111.4+0.1 -> -111.3 | AB49: 11.3 | AC49: 727.7 | AD49: -1003.2 | AE49: -324.9 | AF49: 213.1 | AG49: =101.1+871.7 -> 972.8 | AH49: =415.1-19.1 -> 396 | AI49: =1167.6-43.5 -> 1124.1 | AJ49: =2213.4-161.6 -> 2051.8 | AK49: =4003.9-272.9 -> 3731 | AL49: =2131.9-1675 -> 456.9 | AM49: =3021.6+22 -> 3043.6 | AN49: =2847.3+385.1 -> 3232.4 | AO49: =4853.6+156.6 -> 5010.2 | AP49: =2497-738.4 -> 1758.6 | AQ49: =3085.6-828.3 -> 2257.3 | AR49: =3545.6-1225.5 -> 2320.1 | AS49: =5845.8-1731.8 -> 4114 | AT49: =1940+100 -> 2040 | AU49: =2626+90 -> 2716 | AV49: =2706.5-21.7 -> 2684.8 | AW49: =4998.1+46 -> 5044.1 | AX49: =2117.9+92.8 -> 2210.7 | AZ49: =+AZ46*0.25 -> 1872.9947 | BA49: =+BA46*0.25 -> 843.04093 | BB49: =+BB46*0.24 -> 64.169988 | BC49: =+BC46*0.2 -> 208.01364 | BD49: =+BD46*0.3 -> -301.77408 | BE49: =+BE46*0.3 -> -1511.7245 | BF49: =+BF46*0.3 -> -240.82516 | BG49: =+BG46*0.3 -> 628.96454 | BH49: =+BH46*0.3 -> 748.78782 | BI49: =+BI46*0.3 -> -1055.9406 | BJ49: =+BJ46*0.3 -> -180.17626 | BK49: =+BK46*0.3 -> 144.69662 | ... BW49: =+BW46*0.3 -> 2601.2825 | BX49: =+BX46*0.25 -> 3774.0511 | BY49: =+BY46*0.3 -> 2521.5351 | BZ49: =+BZ46*0.3 -> 2764.2366 | CA49: =+CA46*0.25 -> 3332.1924 | CB49: =+CB46*0.25 -> 4591.6143 | CC49: =+CC46*0.25 -> 2001.6136 | CE49: =+E49+D49+B49+C49 -> 4369.382 | CG49: ='Main Model'!AI56 -> 12484.9 | CJ49: =CG49-AV49-AU49-AT49 -> 5044.1
A50: PAT | B50: =B46+B47-B49-B48 -> 1444.961 | C50: =C46+C47-C49-C48 -> 1722.094 | D50: =D46+D47-D49-D48 -> 2137.045 | E50: =E46+E47-E49-E48 -> -1408.115 | F50: =F46+F47-F49-F48 -> 2907.844 | G50: =G46+G47-G49-G48 -> 2944.1 | H50: =H46+H47-H49-H48 -> 1617.16 | I50: =I46+I47-I49-I48 -> 4761.669 | ... AX50: =AX46+AX47-AX49-AX48 -> 6091.1 | AZ50: =AZ46+AZ47-AZ49-AZ48 -> 5618.9842 | BA50: =BA46+BA47-BA49-BA48 -> 2529.1228 | BB50: =BB46+BB47-BB49-BB48 -> 203.20496 | BC50: =BC46+BC47-BC49-BC48 -> 832.05456 | BD50: =BD46+BD47-BD49-BD48 -> -733.13953 | BE50: =BE46+BE47-BE49-BE48 -> -3527.3571 | BF50: =BF46+BF47-BF49-BF48 -> -561.92537 | BG50: =BG46+BG47-BG49-BG48 -> 1467.5839 | ... CC50: =CC46+CC47-CC49-CC48 -> 6004.8407 | CE50: =CE46+CE47-CE49-CE48 -> 5092.3 | CG50: ='Main Model'!AI57 -> 35655.3 | CJ50: =CG50-AV50-AU50-AT50 -> 14047.2
A51: PAT (pre exceptionals) | B51: =B50+B48-B47-B41*(1-B66/100) -> 1565.4467 | C51: =C50-C47+(+C48-C41)*(1-C66/100) -> 2990.3547 | D51: =D50+D48-D47 -> 2187.045 | E51: =E50-E47+(+E48-E41) -> 4796.509 | F51: =F50-F47+(+F48-F41) -> 2411.136 | G51: =G50-G47+(+G48-G41) -> 2878.417 | H51: =H50-H47+(+H48-H41) -> 2254.26 | I51: =I50-I47+(+I48-I41) -> 4801.445 | J51: =J50-J47+(+J48-J41)*0.7 -> 1219.0494 | K51: =K50-K47+(+K48-K41)*0.7 -> 3361.0966 | L51: =L50-L47+(+L48-L41)*0.7 -> 4498.4574 | M51: =M50-M47+(+M48-M41)*0.7 -> 4887.24 | N51: =N50-N47+(+N48-N41) -> 6614.802 | O51: =O50-O47+(+O48-O41)*0.7 -> 7414.4 | P51: =P50-P47+(+P48-P41)*0.7 -> 3847.5497 | Q51: =Q50-Q47+(+Q48-Q41)*0.7 -> 4366.66 | R51: =R50-R47+(+R48-R41) -> 4755.223 | S51: =S50-S47+(+S48-S41)*0.7 -> 5398.5 | T51: =T50-T47+(+T48-T41)*0.7 -> 3857.61 | U51: =U50-U47+(+U48-U41)*0.7 -> 6611.66 | V51: =V50+(+V48-V47-V41)*0.7 -> 2442.97 | W51: =W50-W47+(+W48-W41)*0.75 -> 874.775 | X51: =X50-X47+(+X48-X41)*0.7 -> 292.69 | Y51: =Y50-Y47+(+Y48-Y41)*0.75 -> -57.725 | Z51: =Z50-Z47+(+Z48-Z41)*0.75 -> -3875.475 | AA51: =AA50-AA47+(+AA48-AA41)*0.75 -> -1453.95 | AB51: =AB50-AB47+(+AB48-AB41)*0.75 -> 151.425 | AC51: =AC50-AC47+(+AC48-AC41)*0.75 -> 2131.575 | AD51: =AD50-AD47+(+AD48-AD41)*0.75 -> -2810.3 | AE51: =AE50-AE47+(+AE48-AE41)*0.75 -> -831.825 | AF51: =AF50-AF47+(+AF48-AF41)*0.75 -> -257.55 | ... AX51: =AX50-AX47+(+AX48-AX41)*0.75 -> 6091.1 | AZ51: =AZ50-AZ47+(+AZ48-AZ41) -> 5618.9842 | BA51: =BA50-BA47+(+BA48-BA41) -> 2529.1228 | BB51: =BB50-BB47+(+BB48-BB41) -> 203.20496 | BC51: =BC50-BC47+(+BC48-BC41) -> 832.05456 | BD51: =BD50-BD47+(+BD48-BD41) -> -704.13953 | BE51: =BE50-BE47+(+BE48-BE41) -> -3527.3571 | BF51: =BF50-BF47+(+BF48-BF41) -> -561.92537 | BG51: =BG50-BG47+(+BG48-BG41) -> 1467.5839 | ... CC51: =CC50-CC47+(+CC48-CC41) -> 6004.8407 | CE51: =CE50+CE48-CE47 -> 13244.535 | CG51: ='Main Model'!AI59 -> 39140.1 | CJ51: =CG51-AV51-AU51-AT51 -> 14918.4 | CL51: =+CM51-CA51-AU51-AT51 -> 15195.623 | CM51: =+'Main Model'!AI59 -> 39140.1 | CN51: =+CL51/BX51-1 -> 0.3421142
A52: Other comprehensive income | B52: -23.951 | C52: -49.387 | D52: 30.372 | E52: 14.29 | F52: -90.624 | G52: 30.827 | H52: -45.804 | I52: 190.777 | J52: -35.031 | K52: -174.085 | L52: 127.366 | N52: -272.89 | P52: -245.185 | Q52: -245.185 | R52: -343.341 | AR52: 7.8 | AS52: 57.5 | AT52: -128.1 | AU52: -576.4 | AW52: -288.7 | AX52: -92.5
A53: Total reported comprehensive income | B53: =+B50+B52 -> 1421.01 | C53: =+C50+C52 -> 1672.707 | D53: =+D50+D52 -> 2167.417 | E53: =+E50+E52 -> -1393.825 | F53: =+F50+F52 -> 2817.22 | G53: =+G50+G52 -> 2974.927 | H53: =+H50+H52 -> 1571.356 | I53: =+I50+I52 -> 4952.446 | ... AX53: =+AX50+AX52 -> 5998.6
A55: DERIVED P&L LINES
A56: EBDIT | B56: =B40+B43 -> 4183.824 | C56: =C40+C43 -> 6694.638 | D56: =D40+D43 -> 4790.54 | E56: =E40+E43 -> 8053.511 | F56: =F40+F43 -> 5205.5 | G56: =G40+G43 -> 5681.014 | H56: =H40+H43 -> 4798.976 | I56: =I40+I43 -> 7702.583 | ... AX56: =AX40+AX43 -> 10546.3 | CE56: =CE40+CE43 -> 22492.921
A57: EBIT (ex other income) | B57: =B40-B45 -> 2787.327 | C57: =C40-C45 -> 5009.102 | D57: =D40-D45 -> 3298.373 | E57: =E40-E45 -> 6519.115 | F57: =F40-F45 -> 3610.601 | G57: =G40-G45 -> 4103.763 | H57: =H40-H45 -> 3227.81 | I57: =I40-I45 -> 5904.259 | ... AX57: =AX40-AX45 -> 7866.1 | CE57: =CE40-CE45 -> 17613.917
A58: Cash profit | B58: =B51+B45 -> 2703.1297 | C58: =C51+C45 -> 4221.4787 | D58: =D51+D45 -> 3381.271 | E58: =E51+E45 -> 6112.48 | F58: =F51+F45 -> 3620.861 | G58: =G51+G45 -> 4139.524 | H58: =H51+H45 -> 3567.61 | I58: =I51+I45 -> 6196.202 | ... AX58: =AX51+AX45 -> 7920.3 | CE58: =CE51+CE45 -> 18123.539
A60: PROFIT MARGINS
A61: EBITDA (%) net sales | B61: =B40/B33*100 -> 10.107849 | C61: =C40/C33*100 -> 12.562916 | D61: =D40/D33*100 -> 10.9207 | E61: =E40/E33*100 -> 13.117164 | F61: =F40/F33*100 -> 11.318402 | G61: =G40/G33*100 -> 11.606228 | H61: =H40/H33*100 -> 10.055077 | I61: =I40/I33*100 -> 11.029227 | ... AX61: =AX40/AX33*100 -> 10.063263 | AZ61: =AZ40/AZ33*100 -> 10.681244 | BA61: =BA40/BA33*100 -> 7.614327 | BB61: =BB40/BB33*100 -> 4.4534133 | BC61: =BC40/BC33*100 -> 6.0281389 | BD61: =BD40/BD33*100 -> 1.9314692 | BE61: =BE40/BE33*100 -> -48.61132 | BF61: =BF40/BF33*100 -> 3.4491051 | BG61: =BG40/BG33*100 -> 8.3775465 | ... CC61: =CC40/CC33*100 -> 9.7302303 | CE61: =CE40/CE33*100 -> 11.877573 | CG61: =CG40/CG33*100 -> 13.02576 | CJ61: =CJ40/CJ33*100 -> 14.586501 | CL61: =CL40/CL33*100 -> 14.854392
A62: Interest cover (x) | B62: =B56/B42 -> 5.966765 | C62: =C56/C42 -> 10.617258 | D62: =D56/D42 -> 7.9421268 | E62: =E56/E42 -> 14.873283 | F62: =F56/F42 -> 15.390005 | G62: =G56/G42 -> 16.746199 | H62: =H56/H42 -> 10.586405 | I62: =I56/I42 -> 18.209804 | ... AX62: =AX56/AX42 -> 25.394414 | AZ62: =AZ56/AZ42 -> 0 | BA62: =BA56/BA42 -> 0 | BB62: =BB56/BB42 -> 0 | BC62: =BC56/BC42 -> 0 | BD62: =BD56/BD42 -> 0 | BE62: =BE56/BE42 -> 0 | BF62: =BF56/BF42 -> 0 | BG62: =BG56/BG42 -> 0 | ... CC62: =CC56/CC42 -> 0 | CE62: =CE56/CE42 -> #DIV/0! | CG62: =CG56/CG42 -> 0 | CJ62: =CJ56/CJ42 -> 0
A63: Other income / EBDIT (%) | B63: =B43/B56*100 -> 6.1860633 | C63: =C43/C56*100 -> 6.7877008 | D63: =D43/D56*100 -> 6.2193615 | E63: =E43/E56*100 -> 2.7121711 | F63: =F43/F56*100 -> 7.3993661 | G63: =G43/G56*100 -> 5.564922 | H63: =H43/H56*100 -> 5.3723128 | I63: =I43/I56*100 -> 5.2393723 | ... AX63: =AX43/AX56*100 -> 8.0691807 | AZ63: =AZ43/AZ56*100 -> #DIV/0! | BA63: =BA43/BA56*100 -> #DIV/0! | BB63: =BB43/BB56*100 -> #DIV/0! | BC63: =BC43/BC56*100 -> #DIV/0! | BD63: =BD43/BD56*100 -> #DIV/0! | BE63: =BE43/BE56*100 -> #DIV/0! | BF63: =BF43/BF56*100 -> #DIV/0! | BG63: =BG43/BG56*100 -> #DIV/0! | ... CC63: =CC43/CC56*100 -> #DIV/0! | CE63: =CE43/CE56*100 -> 0 | CG63: =CG43/CG56*100 -> #DIV/0! | CJ63: =CJ43/CJ56*100 -> #DIV/0!
A64: Other income / PAT (%) | B64: =B43/B51*100 -> 16.532916 | C64: =C43/C51*100 -> 15.195923 | D64: =D43/D51*100 -> 13.622994 | E64: =E43/E51*100 -> 4.5538328 | F64: =F43/F51*100 -> 15.974794 | G64: =G43/G51*100 -> 10.983259 | H64: =H43/H51*100 -> 11.436835 | I64: =I43/I51*100 -> 8.4051155 | ... AX64: =AX43/AX51*100 -> 13.971204 | AZ64: =AZ43/AZ51*100 -> 3.5593622 | BA64: =BA43/BA51*100 -> 23.723641 | BB64: =BB43/BB51*100 -> 98.422793 | BC64: =BC43/BC51*100 -> 48.073771 | BD64: =BD43/BD51*100 -> -35.504327 | BE64: =BE43/BE51*100 -> -7.0874594 | BF64: =BF43/BF51*100 -> -44.489894 | BG64: =BG43/BG51*100 -> 13.627841 | ... CC64: =CC43/CC51*100 -> 11.157665 | CE64: =CE43/CE51*100 -> 0 | CG64: =CG43/CG51*100 -> 8.0523555 | CJ64: =CJ43/CJ51*100 -> 4.5775686
A65: Pre tax margins (%) | B65: =B46/B33*100 -> 5.5740384 | C65: =C46/C33*100 -> 9.5698291 | D65: =D46/D33*100 -> 7.2339943 | E65: =E46/E33*100 -> 10.921657 | F65: =F46/F33*100 -> 9.7544033 | G65: =G46/G33*100 -> 8.9701076 | H65: =H46/H33*100 -> 5.3034974 | I65: =I46/I33*100 -> 9.2378725 | ... AX65: =AX46/AX33*100 -> 8.6168761 | CE65: =CE46/CE33*100 -> 9.3011745
A66: Tax / PBT (%) | B66: =B49/(B46+B47+B48)*100 -> 33.241871 | C66: =C49/(C46+C47+C48)*100 -> 23.110787 | D66: =D49/(D46+D47+D48)*100 -> 26.071268 | E66: =E49/(E46+E47+E48)*100 -> 10.719712 | F66: =F49/(F46+F47+F48)*100 -> 30.003052 | G66: =G49/(G46+G47+G48)*100 -> 28.995347 | H66: =H49/(H46+H47+H48)*100 -> 32.48361 | I66: =I49/(I46+I47+I48)*100 -> 8.4231996 | J66: =J49/(J46+J47-J48)*100 -> 30.684133 | K66: =K49/(K46+K47-K48)*100 -> 30.745597 | L66: =L49/(L46+L47-L48)*100 -> 31.617258 | M66: =M49/(M46+M47-M48)*100 -> 30.013424 | N66: =N49/(N46+N47-N48)*100 -> 28.234199 | O66: =O49/(O46+O47-O48)*100 -> 26.105504 | P66: =P49/(P46+P47-P48)*100 -> 29.093837 | Q66: =Q49/(Q46+Q47-Q48)*100 -> 21.331816 | ... V66: =V49/(V46+V47-V48)*100 -> 36.181183 | W66: =W49/(W46+W47+W48)*100 -> -13.28582 | X66: =X49/(X46+X47+X48)*100 -> 45.154674 | Y66: =Y49/(Y46+Y47+Y48)*100 -> -22.613219 | Z66: =Z49/(Z46+Z47+Z48)*100 -> 29.462358 | AA66: =AA49/(AA46+AA47+AA48)*100 -> 7.2085492 | AB66: =AB49/(AB46+AB47+AB48)*100 -> 1.5309579 | AC66: =AC49/(AC46+AC47+AC48)*100 -> 30.417154 | AD66: =AD49/(AD46+AD47+AD48)*100 -> 26.452208 | ... AX66: =AX49/(AX46+AX47+AX48)*100 -> 26.629165 | AZ66: =AZ49/(AZ46+AZ47+AZ48)*100 -> 25 | BA66: =BA49/(BA46+BA47+BA48)*100 -> 25 | BB66: =BB49/(BB46+BB47+BB48)*100 -> 24 | BC66: =BC49/(BC46+BC47+BC48)*100 -> 20 | BD66: =BD49/(BD46+BD47+BD48)*100 -> 30.89056 | BE66: =BE49/(BE46+BE47+BE48)*100 -> 30 | BF66: =BF49/(BF46+BF47+BF48)*100 -> 30 | BG66: =BG49/(BG46+BG47+BG48)*100 -> 30 | ... CC66: =CC49/(CC46+CC47+CC48)*100 -> 25 | CE66: =CE49/(CE46+CE47+CE48)*100 -> 16.957837
A67: Net profit margins (%) Net Sales | B67: =B51/B33*100 -> 4.0314036 | C67: =C51/C33*100 -> 6.0202266 | D67: =D51/D33*100 -> 5.316313 | E67: =E51/E33*100 -> 8.0301088 | F67: =F51/F33*100 -> 5.6614857 | G67: =G51/G33*100 -> 6.2270967 | H67: =H51/H33*100 -> 4.9914024 | I67: =I51/I33*100 -> 7.2552558 | ... AX67: =AX51/AX33*100 -> 6.3222739 | CE67: =CE51/CE33*100 -> 6.9938862
A69: COST RATIOS
A70: Cost ratios | V70: =+(V34+V35)/V11*1000000 -> 1003246.8 | W70: =+(W34+W35)/W11*1000000 -> 937625.27 | X70: =+(X34+X35)/X11*1000000 -> 946548.08 | Y70: =+(Y34+Y35)/Y11*1000000 -> 1069886.7 | Z70: =+(Z34+Z35)/Z11*1000000 -> 1094520.2 | AA70: =+(AA34+AA35)/AA11*1000000 -> 1038911.7 | AB70: =+(AB34+AB35)/AB11*1000000 -> 1072256.8 | AC70: =+(AC34+AC35)/AC11*1000000 -> 1221831.6 | ... AX70: =+(AX34+AX35)/AX11*1000000 -> 1413446.7 | BC70: =+(BC34+BC35)/BC11*1000000 -> 918825.13 | BD70: =+(BD34+BD35)/BD11*1000000 -> 948568.61 | BE70: =+(BE34+BE35)/BE11*1000000 -> 1175299.8 | BF70: =+(BF34+BF35)/BF11*1000000 -> 1102417.5 | BG70: =+(BG34+BG35)/BG11*1000000 -> 1084797.8 | BH70: =+(BH34+BH35)/BH11*1000000 -> 1119382.4 | BI70: =+(BI34+BI35)/BI11*1000000 -> 1154699.5 | BJ70: =+(BJ34+BJ35)/BJ11*1000000 -> 1245036.6 | ... CC70: =+(CC34+CC35)/CC11*1000000 -> 1477414.2 | CG70: =+(CG34+CG35)/CG11*1000000 -> 1425220.8 | CJ70: =+(CJ34+CJ35)/CJ11*1000000 -> 1454882.1
A71: Raw materials / sales | B71: =(B34+B35)/B33*100 -> 68.42982 | C71: =(C34+C35)/C33*100 -> 69.683107 | D71: =(D34+D35)/D33*100 -> 69.897961 | E71: =(E34+E35)/E33*100 -> 70.418491 | F71: =(F34+F35)/F33*100 -> 68.674813 | G71: =(G34+G35)/G33*100 -> 67.793076 | H71: =(H34+H35)/H33*100 -> 69.421063 | I71: =(I34+I35)/I33*100 -> 71.931582 | ... AX71: =(AX34+AX35)/AX33*100 -> 71.539751 | AZ71: 72 | BA71: 72 | BB71: 69.5 | BC71: 69.4 | BD71: 73.7 | BE71: 71 | BF71: 68 | BG71: 71.5 | BH71: 75.8 | BI71: 76.5 | BJ71: 74.4 | BK71: 77.2 | BL71: 79.5 | BM71: 79 | BN71: 79.1 | BO71: 77.5 | BP71: 76 | BQ71: 75.2 | BR71: 74 | BS71: 73.4 | BT71: 73 | BU71: 72.4 | BV71: 72.2 | BW71: 71.4 | BX71: 71.5 | BY71: 71.3 | BZ71: 71.1 | CA71: 71.8 | CB71: 72.6 | CC71: 73.2 | CE71: =(CE34+CE35)/CE33*100 -> 69.704745 | CG71: =(CG34+CG35)/CG33*100 -> 71.391185 | CJ71: =(CJ34+CJ35)/CJ33*100 -> 71.362785
A72: Staff costs / sales | B72: =B36/B33*100 -> 8.4651694 | C72: =C36/C33*100 -> 7.5760538 | D72: =D36/D33*100 -> 8.4465871 | E72: =E36/E33*100 -> 5.5674775 | F72: =F36/F33*100 -> 8.4090885 | G72: =G36/G33*100 -> 7.9872818 | H72: =H36/H33*100 -> 8.6747544 | I72: =I36/I33*100 -> 6.2228958 | ... AX72: =AX36/AX33*100 -> 7.1900024 | AZ72: =AZ36/AZ33*100 -> 5.8707646 | BA72: =BA36/BA33*100 -> 7.9843886 | BB72: =BB36/BB33*100 -> 11.794681 | BC72: =BC36/BC33*100 -> 10.530798 | BD72: =BD36/BD33*100 -> 8.5289858 | BE72: =BE36/BE33*100 -> 38.013708 | BF72: =BF36/BF33*100 -> 12.689287 | BG72: =BG36/BG33*100 -> 7.8911582 | ... CC72: =CC36/CC33*100 -> 6.9091925 | CE72: =CE36/CE33*100 -> 7.3139387 | CG72: =CG36/CG33*100 -> 5.9233491 | CJ72: =CJ36/CJ33*100 -> 5.0955864
A73: Other expenses / sales | B73: =B37/B33*100 -> 12.997162 | C73: =C37/C33*100 -> 10.177923 | D73: =D37/D33*100 -> 10.734752 | E73: =E37/E33*100 -> 10.896868 | F73: =F37/F33*100 -> 11.597696 | G73: =G37/G33*100 -> 12.613414 | H73: =H37/H33*100 -> 11.849106 | I73: =I37/I33*100 -> 10.816295 | ... AX73: =AX37/AX33*100 -> 11.206983 | AZ73: =AZ37/AZ33*100 -> 11.447991 | BA73: =BA37/BA33*100 -> 12.401284 | BB73: =BB37/BB33*100 -> 14.251906 | BC73: =BC37/BC33*100 -> 14.041063 | BD73: =BD37/BD33*100 -> 15.839545 | BE73: =BE37/BE33*100 -> 39.597612 | BF73: =BF37/BF33*100 -> 15.861608 | BG73: =BG37/BG33*100 -> 12.231295 | ... CC73: =CC37/CC33*100 -> 10.160577 | CE73: =CE37/CE33*100 -> 11.103744 | CG73: =CG37/CG33*100 -> 10.068732 | CJ73: =CJ37/CJ33*100 -> 10.22627
A75: PER SHARE
A76: Equity (m shares) | B76: 2845.88 | C76: 2845.88 | D76: 2845.88 | E76: 2845.88 | F76: 2845.88 | G76: 2845.88 | H76: 2845.88 | I76: 2845.88 | J76: 2926.538 | K76: 2926.538 | L76: 2927.108 | M76: 2927.1 | N76: 2927.108 | O76: 2935.5 | P76: 2927.108 | Q76: 2927.108 | R76: 2927.108 | S76: 2935.5 | T76: 2935.5 | U76: 2935.5 | V76: 2935.5 | W76: 2935.5 | X76: 2935.5 | Y76: 2935.5 | Z76: 2935.5 | AA76: 2935.5 | AB76: 2935.5 | AC76: 2935.5 | AD76: 2935.5 | AE76: 2935.5 | AF76: 2935.5 | AG76: 2935.5 | AH76: 2935.5 | AI76: 2935.5 | AJ76: 2935.5 | AK76: 2936.1 | AL76: 2936.1 | AM76: 2936.1 | AN76: 2936.1 | AO76: 2936.3 | AP76: 5872.6 | AQ76: =+BV76 -> 5872.6 | AR76: =2936.3*2 -> 5872.6 | AS76: 5872.6 | AT76: 5872.6 | AU76: 5872.6 | AV76: 5872.6 | AW76: 5873.9 | AX76: 5873.9 | AZ76: =+T76 -> 2935.5 | BA76: =+U76 -> 2935.5 | BB76: =+V76 -> 2935.5 | BC76: =+W76 -> 2935.5 | BD76: =+X76 -> 2935.5 | BE76: =+Y76 -> 2935.5 | BF76: =+Z76 -> 2935.5 | BG76: =+AA76 -> 2935.5 | ... CC76: =+AW76 -> 5873.9 | CG76: 5872.6 | CJ76: 5872.6
A77: EPS (Rs) | B77: =B51/B76 -> 0.55007475 | C77: =C51/C76 -> 1.0507663 | D77: =D51/D76 -> 0.76849516 | E77: =E51/E76 -> 1.6854221 | F77: =F51/F76 -> 0.84723741 | G77: =G51/G76 -> 1.011433 | H77: =H51/H76 -> 0.79211351 | I77: =I51/I76 -> 1.6871565 | ... AX77: =AX51/AX76 -> 1.0369771 | AZ77: =AZ51/AZ76 -> 1.9141489 | BA77: =BA51/BA76 -> 0.86156457 | BB77: =BB51/BB76 -> 0.069223289 | BC77: =BC51/BC76 -> 0.2834456 | BD77: =BD51/BD76 -> -0.23987039 | BE77: =BE51/BE76 -> -1.2016205 | BF77: =BF51/BF76 -> -0.19142407 | BG77: =BG51/BG76 -> 0.49994343 | ... CC77: =CC51/CC76 -> 1.0222919 | CG77: =CG51/CG76 -> 6.6648674 | CJ77: =CJ51/CJ76 -> 2.5403399
A78: CEPS (Rs) | B78: =B58/B76 -> 0.94983968 | C78: =C58/C76 -> 1.483365 | D78: =D58/D76 -> 1.1881285 | E78: =E58/E76 -> 2.1478348 | F78: =F58/F76 -> 1.2723168 | G78: =G58/G76 -> 1.4545673 | H78: =H58/H76 -> 1.2536052 | I78: =I58/I76 -> 2.1772534 | ... AX78: =AX58/AX76 -> 1.3483886 | CG78: =CG58/CG76 -> 0 | CJ78: =CJ58/CJ76 -> 0
A79: EPS (Rs) reported PAT | B79: =B50/B76 -> 0.50773785 | C79: =C50/C76 -> 0.60511828 | D79: =D50/D76 -> 0.7509259 | E79: =E50/E76 -> -0.49479071 | F79: =F50/F76 -> 1.0217732 | G79: =G50/G76 -> 1.0345131 | H79: =H50/H76 -> 0.56824603 | I79: =I50/I76 -> 1.6731798 | ... AX79: =AX50/AX76 -> 1.0369771 | CG79: =CG50/CG76 -> 6.0714675 | CJ79: =CJ50/CJ76 -> 2.3919899
A81: PER VEHICLE (INR)
A82: Average Realizations | B82: =+B33/B11*1000000 -> 1377680.7 | C82: =+C33/C11*1000000 -> 1328797.9 | D82: =+D33/D11*1000000 -> 1330133.8 | E82: =+E33/E11*1000000 -> 1357720.5 | F82: =+F33/F11*1000000 -> 1366545.7 | G82: =+G33/G11*1000000 -> 1382257.1 | H82: =+H33/H11*1000000 -> 1375281.2 | I82: =+I33/I11*1000000 -> 1389698.9 | ... AX82: =+AX33/AX11*1000000 -> 1975750.1 | BQ82: =+BQ33/BQ11*1000000 -> 1947446.3 | BR82: =+BR33/BR11*1000000 -> 1941857.8 | BS82: =+BS33/BS11*1000000 -> 1894892.1 | BT82: =+BT33/BT11*1000000 -> 1972730.3 | BU82: =+BU33/BU11*1000000 -> 1962245 | BV82: =+BV33/BV11*1000000 -> 1919795.7 | BW82: =+BW33/BW11*1000000 -> 1950807.1 | BX82: =+BX33/BX11*1000000 -> 2073280.3 | ... CC82: =+CC33/CC11*1000000 -> 2018325.5
A83: Material Cost / Vehicle | B83: =+(B34+B35)/B11*1000000 -> 942744.41 | C83: =+(C34+C35)/C11*1000000 -> 925947.7 | D83: =+(D34+D35)/D11*1000000 -> 929736.42 | E83: =+(E34+E35)/E11*1000000 -> 956086.31 | F83: =+(F34+F35)/F11*1000000 -> 938472.71 | G83: =+(G34+G35)/G11*1000000 -> 937074.64 | H83: =+(H34+H35)/H11*1000000 -> 954734.8 | I83: =+(I34+I35)/I11*1000000 -> 999632.41 | ... AX83: =+(AX34+AX35)/AX11*1000000 -> 1413446.7 | BQ83: =+(BQ34+BQ35)/BQ11*1000000 -> 1464479.6 | BR83: =+(BR34+BR35)/BR11*1000000 -> 1436974.8 | BS83: =+(BS34+BS35)/BS11*1000000 -> 1390850.8 | BT83: =+(BT34+BT35)/BT11*1000000 -> 1440093.1 | BU83: =+(BU34+BU35)/BU11*1000000 -> 1420665.4 | BV83: =+(BV34+BV35)/BV11*1000000 -> 1386092.5 | BW83: =+(BW34+BW35)/BW11*1000000 -> 1392876.3 | BX83: =+(BX34+BX35)/BX11*1000000 -> 1482395.4 | ... CC83: =+(CC34+CC35)/CC11*1000000 -> 1477414.2
A84: Gross Contribution / Vehicle | B84: =+(B33-B34-B35)/B11*1000000 -> 434936.28 | C84: =+(C33-C34-C35)/C11*1000000 -> 402850.24 | D84: =+(D33-D34-D35)/D11*1000000 -> 400397.41 | E84: =+(E33-E34-E35)/E11*1000000 -> 401634.22 | F84: =+(F33-F34-F35)/F11*1000000 -> 428073 | G84: =+(G33-G34-G35)/G11*1000000 -> 445182.5 | H84: =+(H33-H34-H35)/H11*1000000 -> 420546.36 | I84: =+(I33-I34-I35)/I11*1000000 -> 390066.5 | ... AX84: =+(AX33-AX34-AX35)/AX11*1000000 -> 562303.39 | BQ84: =+(BQ33-BQ34-BQ35)/BQ11*1000000 -> 482966.68 | BR84: =+(BR33-BR34-BR35)/BR11*1000000 -> 504883.03 | BS84: =+(BS33-BS34-BS35)/BS11*1000000 -> 504041.3 | BT84: =+(BT33-BT34-BT35)/BT11*1000000 -> 532637.17 | BU84: =+(BU33-BU34-BU35)/BU11*1000000 -> 541579.61 | BV84: =+(BV33-BV34-BV35)/BV11*1000000 -> 533703.21 | BW84: =+(BW33-BW34-BW35)/BW11*1000000 -> 557930.84 | BX84: =+(BX33-BX34-BX35)/BX11*1000000 -> 590884.89 | ... CC84: =+(CC33-CC34-CC35)/CC11*1000000 -> 540911.23
A85: EBITDA / Vehicle | B85: =+B40/B11*1000000 -> 139253.88 | C85: =+C40/C11*1000000 -> 166935.77 | D85: =+D40/D11*1000000 -> 145259.93 | E85: =+E40/E11*1000000 -> 178094.42 | F85: =+F40/F11*1000000 -> 154671.14 | G85: =+G40/G11*1000000 -> 160427.92 | H85: =+H40/H11*1000000 -> 138285.58 | I85: =+I40/I11*1000000 -> 153273.05 | ... AX85: =+AX40/AX11*1000000 -> 198824.93 | BQ85: =+BQ40/BQ11*1000000 -> 148576.78 | BR85: =+BR40/BR11*1000000 -> 209974.72 | BS85: =+BS40/BS11*1000000 -> 194987.72 | BT85: =+BT40/BT11*1000000 -> 244112.48 | BU85: =+BU40/BU11*1000000 -> 204396.01 | BV85: =+BV40/BV11*1000000 -> 204928.88 | BW85: =+BW40/BW11*1000000 -> 230172.87 | BX85: =+BX40/BX11*1000000 -> 293467.02 | ... CC85: =+CC40/CC11*1000000 -> 196387.72
A87: BALANCE SHEET ITEMS (INR m)
A88: Debt | AM88: 11390 | AN88: 17470 | AO88: 17470 | AP88: 17470 | AQ88: 17470 | AR88: 17470 | AS88: 17470 | AT88: 17470
A89: Investment in Optare/Switch | AN89: 6620 | AO89: 6620 | AP89: 6620 | AQ89: 6620 | AR89: 6620 | AS89: 6620 | AT89: 6620
A91: RESULT vs BSe — COMMENTARY
G92: 2% ahead | H92: 1% ahead | I92: 1% ahead | J92: 5% ahead | K92: 1% ahead | L92: 4% ahead | N92: 2% behind
G93: 4.8% ahead | H93: 7.9% behind | I93: 2.5% ahead | J93: 17.2% behind | K93: 1.6% behind | L93: 17% ahead | N93: 2% ahead
G94: 30 bps ahead | H94: 90 bps behind | I94: 10 bps ahead | J94: 190 bps behind | K94: 25 bps behind | L94: 120 bps ahead | N94: 44 bps ahead
G95: 3.6% ahead | H95: 13.3% behind | I95: 27.1% ahead | J95: 28.6% behind | K95: 2.3% behind | L95: 19.3% ahead | N95: 9.5% ahead
G96: 100 bps lower | H96: 325bps higher | I96: Vitiated by impairments, tax write backs | J96: 250 bps lower | K96: 170bps higher | L96: 160bps higher | N96: 280bps lower
A98: SEGMENT MIX — GOODS CVs, DOMESTIC (Nos.)
A99: 7.5-12 MT | B99: 1342 | C99: 2034 | D99: 1744 | E99: 2652 | F99: 2019 | G99: 2275 | H99: 2302 | I99: 2954 | J99: 2042 | K99: 3560 | L99: 3540 | M99: 3540 | N99: 4376
A100: 12-16.2 MT | B100: 4057 | C100: 5025 | D100: 3750 | E100: 5938 | F100: 4474 | G100: 5530 | H100: 5070 | I100: 6549 | J100: 2884 | K100: 4511 | L100: 3650 | M100: 3650 | N100: 4895
A101: 16.2-25 MT | B101: 3053 | C101: 4495 | D101: 3859 | E101: 6067 | F101: 4505 | G101: 4608 | H101: 4853 | I101: 7175 | J101: 2379 | K101: 4610 | L101: 7192 | M101: 7192 | N101: 6795
A102: > 25 MT | B102: 4095 | C102: 5646 | D102: 4108 | E102: 5888 | F102: 3219 | G102: 2852 | H102: 2440 | I102: 5636 | J102: 2092 | K102: 3537 | L102: 4299 | M102: 4299 | N102: 6026
A103: 26.4-35.2 TT | B103: 641 | C103: 895 | D103: 527 | E103: 1046 | F103: 574 | G103: 717 | H103: 1827 | I103: 3373 | J103: 1505 | K103: 1021 | L103: 981 | M103: 981 | N103: 1690
A104: >35.2 TT | B104: 3126 | C104: 4705 | D104: 3902 | E104: 5439 | F104: 3837 | G104: 3113 | H104: 3793 | I104: 6995 | J104: 4193 | K104: 9113 | L104: 11585 | M104: 11585 | N104: 14736
A105: Total | B105: =SUM(B99:B104) -> 16314 | C105: =SUM(C99:C104) -> 22800 | D105: =SUM(D99:D104) -> 17890 | E105: =SUM(E99:E104) -> 27030 | F105: =SUM(F99:F104) -> 18628 | G105: =SUM(G99:G104) -> 19095 | H105: =SUM(H99:H104) -> 20285 | I105: =SUM(I99:I104) -> 32682 | ... AX105: =SUM(AX99:AX104) -> 0
A107: SEGMENT MIX — GOODS CVs, DOMESTIC (%)
A108: 7.5-12 MT | B108: =B99/B$105 -> 0.082260635 | C108: =C99/C$105 -> 0.089210526 | D108: =D99/D$105 -> 0.097484628 | E108: =E99/E$105 -> 0.098113208 | F108: =F99/F$105 -> 0.10838523 | G108: =G99/G$105 -> 0.11914114 | H108: =H99/H$105 -> 0.11348287 | I108: =I99/I$105 -> 0.090386145 | ... AX108: =AX99/AX$105 -> #DIV/0!
A109: 12-16.2 MT | B109: =B100/B$105 -> 0.24868211 | C109: =C100/C$105 -> 0.22039474 | D109: =D100/D$105 -> 0.20961431 | E109: =E100/E$105 -> 0.21968183 | F109: =F100/F$105 -> 0.24017608 | G109: =G100/G$105 -> 0.28960461 | H109: =H100/H$105 -> 0.24993838 | I109: =I100/I$105 -> 0.20038553 | ... AX109: =AX100/AX$105 -> #DIV/0!
A110: 16.2-25 MT | B110: =B101/B$105 -> 0.18713988 | C110: =C101/C$105 -> 0.19714912 | D110: =D101/D$105 -> 0.2157071 | E110: =E101/E$105 -> 0.22445431 | F110: =F101/F$105 -> 0.24184024 | G110: =G101/G$105 -> 0.24131972 | H110: =H101/H$105 -> 0.23924082 | I110: =I101/I$105 -> 0.21953981 | ... AX110: =AX101/AX$105 -> #DIV/0!
A111: > 25 MT | B111: =B102/B$105 -> 0.2510114 | C111: =C102/C$105 -> 0.24763158 | D111: =D102/D$105 -> 0.22962549 | E111: =E102/E$105 -> 0.21783204 | F111: =F102/F$105 -> 0.17280438 | G111: =G102/G$105 -> 0.14935847 | H111: =H102/H$105 -> 0.12028593 | I111: =I102/I$105 -> 0.17244967 | ... AX111: =AX102/AX$105 -> #DIV/0!
A112: 26.4-35.2 TT | B112: =B103/B$105 -> 0.039291406 | C112: =C103/C$105 -> 0.039254386 | D112: =D103/D$105 -> 0.029457798 | E112: =E103/E$105 -> 0.038697743 | F112: =F103/F$105 -> 0.030813829 | G112: =G103/G$105 -> 0.037549097 | H112: =H103/H$105 -> 0.090066552 | I112: =I103/I$105 -> 0.10320666 | ... AX112: =AX103/AX$105 -> #DIV/0!
A113: >35.2 TT | B113: =B104/B$105 -> 0.19161456 | C113: =C104/C$105 -> 0.20635965 | D113: =D104/D$105 -> 0.21811068 | E113: =E104/E$105 -> 0.20122087 | F113: =F104/F$105 -> 0.20598024 | G113: =G104/G$105 -> 0.16302697 | H113: =H104/H$105 -> 0.18698546 | I113: =I104/I$105 -> 0.21403219 | ... AX113: =AX104/AX$105 -> #DIV/0!
...

Sheet New Qrtrly
A1: Ashok Leyland | B1: 1QFY07 | C1: 2QFY07 | D1: 3QFY07 | E1: 4QFY07 | F1: 1QFY08 | G1: 2QFY08 | H1: 3QFY08 | I1: 4QFY08 | J1: 1QFY09 | K1: 2QFY09 | L1: 3QFY09 | M1: 4QFY09 | N1: 1QFY10 | O1: 2QFY10 | P1: 3QFY10 | Q1: 4QFY10A | R1: 1QFY11A | S1: 2QFY11A | T1: 3QFY11A | U1: 4QFY11A | V1: FY11 | W1: 1QFY12A | X1: 2QFY12A | Y1: 3QFY12A | Z1: 4QFY12A | AA1: 1QFY13A | AB1: 2QFY13A | AC1: 3QFY13A | AD1: 4QFY13A | AE1: 1QFY14A | AF1: 2QFY14A | AG1: 3QFY14A | AH1: 4QFY14A | AI1: 1QFY15A | AJ1: 2QFY15A | AK1: 3QFY15A | AL1: 4QFY15A | AM1: FY15 | AN1: 1QFY16A | AO1: 2QFY16A | AP1: 3QFY16E | AQ1: 3QFY16A | AR1: 4QFY16E | AS1: 4QFY16A | AT1: FY16 | AU1: 1QFY17E
A2: Note: Have used our Q database for volumes | AH2: =+SUM(AE22:AH22)/SUM(AE6:AH6)*1000000 -> 1113086.8
A3: Volumes (Nos.)
A4: H / MCVs | B4: 16943 | C4: 19781 | D4: 19997 | E4: 26084 | F4: =18163-F5 -> 18004 | G4: 18745 | H4: 18814 | I4: 26941 | J4: 18180 | K4: 16979 | L4: 7914 | M4: 10051 | N4: 7467 | O4: =5858+819+13194+1614-N4 -> 14018 | P4: 15838 | Q4: 25484 | R4: 21127 | S4: =6504+17926 -> 24430 | T4: 18258 | U4: 29421 | V4: =+SUM(R4:U4) -> 93236 | W4: 19083 | X4: =17225+6125 -> 23350 | Y4: =+Y6-Y5 -> 20756 | Z4: =9200+9521+12074 -> 30795 | AA4: 20337 | AB4: =7596+6982+6597 -> 21175 | AC4: =4964+4487+5230 -> 14681 | AD4: =7045+6863+9695 -> 23603 | AE4: 14897 | AF4: =4715+4939+6259 -> 15913 | AG4: =3890+2715+4093 -> 10698 | AH4: =7723+5576+5530 -> 18829 | AI4: 14949 | AJ4: =5832+5750+6625 -> 18207 | AK4: =5865+5204+7210 -> 18279 | AL4: =8009+8230+10027 -> 26266 | AN4: 21485 | AO4: =8803+8903+12134 -> 29840 | AP4: =7177+6296+9758 -> 23231 | AQ4: =7177+6296+9703 -> 23176 | AR4: 33000 | AS4: =11208+10801+13240 -> 35249 | AU4: =7873+7469+8685 -> 24027
A5: LCVs | B5: 97 | C5: 88 | D5: 71 | E5: 46 | F5: =142+17 -> 159 | G5: 147 | H5: 151 | I5: 368 | J5: 245 | K5: 228 | L5: 127 | M5: 750 | N5: 231 | O5: =344+165-N5 -> 278 | P5: 289 | Q5: 323 | R5: 275 | S5: 160 | T5: 179 | U5: 258 | V5: =+SUM(R5:U5) -> 872 | W5: 194 | X5: 278 | Y5: =7593-4893 -> 2700 | Z5: =1100+1582+2211 -> 4893 | AA5: 7248 | AB5: =3027+2803+2835 -> 8665 | AC5: =3033+2883+2069 -> 7985 | AD5: =3001+3698+4325 -> 11024 | AE5: 6824 | AF5: =2517+2200+2480 -> 7197 | AG5: =2385+2660+2710 -> 7755 | AH5: =2563+2339+2317 -> 7219 | AI5: 5032 | AJ5: =2501+2111+2560 -> 7172 | AK5: =2537+2528+2080 -> 7145 | AL5: =2634+2532+2727 -> 7893 | AN5: 6701 | AO5: =2219+2641+2637 -> 7497 | AP5: =2451+2674+3627 -> 8752 | AQ5: =2627+2674+2451 -> 7752 | AR5: 7500 | AS5: =2678+2605+3462 -> 8745 | AU5: =2309+2406+2423 -> 7138
A6: Total CVs | B6: =B4+B5 -> 17040 | C6: =C4+C5 -> 19869 | D6: =D4+D5 -> 20068 | E6: =E4+E5 -> 26130 | F6: =F4+F5 -> 18163 | G6: =G4+G5 -> 18892 | H6: =H4+H5 -> 18965 | I6: =I4+I5 -> 27309 | ... L6: =L4+L5 -> 8041 | M6: =M5+M4 -> 10801 | N6: =N5+N4 -> 7698 | O6: =O4+O5 -> 14296 | P6: =P4+P5 -> 16127 | Q6: =Q4+Q5 -> 25807 | R6: =R4+R5 -> 21402 | S6: =+S5+S4 -> 24590 | T6: =+T5+T4 -> 18437 | U6: =+U5+U4 -> 29679 | V6: =+SUM(R6:U6) -> 94108 | W6: =+W5+W4 -> 19277 | X6: =+X5+X4 -> 23628 | Y6: 23456 | Z6: =14285+11103+10300 -> 35688 | AA6: =+AA5+AA4 -> 27585 | AB6: =+AB5+AB4 -> 29840 | AC6: =+AC5+AC4 -> 22666 | AD6: =+AD5+AD4 -> 34627 | AE6: =+AE5+AE4 -> 21721 | AF6: =+AF5+AF4 -> 23110 | AG6: =+AG5+AG4 -> 18453 | AH6: =+AH5+AH4 -> 26048 | ... AL6: =+AL5+AL4 -> 34159 | AM6: =+AL6+AK6+AI6+AJ6 -> 104943 | AN6: =+AN5+AN4 -> 28186 | AO6: =+AO5+AO4 -> 37337 | AP6: =+AP5+AP4 -> 31983 | AQ6: =+AQ5+AQ4 -> 30928 | AR6: =+AR5+AR4 -> 40500 | AS6: =+AS5+AS4 -> 43994 | AT6: =+AS6+AQ6+AN6+AO6 -> 140445 | AU6: =+AU5+AU4 -> 31165 | AV6: =+AU6/AN6-1 -> 0.10569077
A7: Product mix (%) | F7: =(F25+F24)*10^6/F6 -> 642505.09 | G7: =(G25+G24)*10^6/G6 -> 693352.74 | H7: =(H25+H24)*10^6/H6 -> 716566.31 | I7: =(I25+I24)*10^6/I6 -> 692977.04 | J7: =(J25+J24)*10^6/J6 -> 780238.26 | K7: =(K25+K24)*10^6/K6 -> 810809.32 | L7: =(L25+L24)*10^6/L6 -> 914929.49 | M7: =(M25+M24)*10^6/M6 -> 818263.12 | N7: =(N25+N24)*10^6/N6 -> 860836.58 | P7: =(P25+P24)*10^6/P6 -> 803614.93 | AE7: =+AE5/AE6 -> 0.31416601 | AF7: =+AF5/AF6 -> 0.31142363 | AG7: =+AG5/AG6 -> 0.42025687 | AH7: =+AH5/AH6 -> 0.2771422 | AI7: =+AI5/AI6 -> 0.25183925 | AJ7: =+AJ5/AJ6 -> 0.28259585 | AK7: =+AK5/AK6 -> 0.28103367 | AL7: =+AL5/AL6 -> 0.23106648 | AN7: =+AN5/AN6 -> 0.23774214 | AO7: =+AO5/AO6 -> 0.20079278 | AP7: =+AP5/AP6 -> 0.27364537 | AQ7: =+AQ5/AQ6 -> 0.25064666 | AS7: =+AS5/AS6 -> 0.19877711 | AU7: =+AU5/AU6 -> 0.22903899
A8: H / MCVs | B8: =B4/B6*100 -> 99.430751 | C8: =C4/C6*100 -> 99.557099 | D8: =D4/D6*100 -> 99.646203 | E8: =E4/E6*100 -> 99.823957 | F8: =F4/F6*100 -> 99.124594 | G8: =G4/G6*100 -> 99.221893 | H8: =H4/H6*100 -> 99.203796 | I8: =I4/I6*100 -> 98.652459 | ... N8: =N4/N6*100 -> 96.999221 | P8: =P4/P6*100 -> 98.207974
A9: LCVs | B9: =B5/B6*100 -> 0.56924883 | C9: =C5/C6*100 -> 0.442901 | D9: =D5/D6*100 -> 0.35379709 | E9: =E5/E6*100 -> 0.17604286 | F9: =F5/F6*100 -> 0.87540605 | G9: =G5/G6*100 -> 0.77810714 | H9: =H5/H6*100 -> 0.79620353 | I9: =I5/I6*100 -> 1.3475411 | ... N9: =N5/N6*100 -> 3.0007794 | P9: =P5/P6*100 -> 1.7920258
A10: Market share (%) | F10: =F27*10^6/F6 -> 88336.729 | G10: =G27*10^6/G6 -> 58345.331 | H10: =H27*10^6/H6 -> 69150.54 | I10: =I27*10^6/I6 -> 72035.959 | J10: =J27*10^6/J6 -> 71951.208 | K10: =K27*10^6/K6 -> 93147.847 | L10: =L27*10^6/L6 -> 117213.9 | M10: =M27*10^6/M6 -> 110641.61 | N10: =N27*10^6/N6 -> 121484.8
A11: H / MCVs | B11: 28.1 | C11: 30.7 | D11: 28.7 | E11: 29.3 | F11: 29.9 | G11: 28.14 | H11: 25.5 | I11: 29.1 | J11: 28.8 | K11: 28.1 | L11: 25.5
A12: LCVs | B12: 0.2 | C12: 0.2 | D12: 0.1 | E12: 0.1 | F12: 0.3 | G12: 0.2 | H12: 0.2 | I12: 0.5 | K12: 0.4 | L12: 0.3 | Q12: =+(Q22-Q14-Q15)/Q6*1000000 -> 1055155.7 | R12: =+(R22-R14-R15)/R6*1000000 -> 998494.58 | S12: =+(S22-S14-S15)/S6*1000000 -> 1004454.9 | T12: =+(T22-T14-T15)/T6*1000000 -> 1079484.2
A14: Engine Sales (Rs m) | F14: =190000*2659/10^6 -> 505.21 | J14: =190000*1.05*4860/10^6 -> 969.57 | K14: 800 | R14: 740 | S14: 690 | T14: =2000-S14-R14 -> 570 | X14: 648 | AA14: 690 | AB14: 705
A15: Spare parts+Kits (Rs m) | B15: 487.8 | C15: =1630-B15 -> 1142.2 | F15: 840 | G15: =2200-F15 -> 1360 | J15: 1440 | K15: 1200 | L15: =L27*10^6/L6 -> 117213.9 | M15: =M27*10^6/M6 -> 110641.61 | N15: =2670-O15 -> 1220 | O15: 1450 | P15: 1600 | Q15: =6430-P15-O15-N15 -> 2160 | R15: 1370 | S15: 1750 | T15: =1600+200 -> 1800
A16: Defence (kits) | AA16: 880 | AB16: 800
A18: Average Realisations (Rs m) | B18: =B22/B6*1000000 -> 835605.63 | C18: =C22/C6*1000000 -> 843384.67 | D18: =D22/D6*1000000 -> 885783.83 | E18: =E20/E6*1000000 -> 1019801.4 | F18: =F22/F6*1000000 -> 892551.89 | G18: =G22/G6*1000000 -> 924144.61 | H18: =H22*91%*88%/H6*1000000 -> 760087.35 | I18: =I22/I6*1000000 -> 938154.09 | J18: =J22/J6*1000000 -> 1022449.4 | K18: =(K22-3200)/K6*1000000 -> 898705.82 | L18: =L22/L6*1000000 -> 1244681.4 | M18: =M22/M6*1000000 -> 1127786.3 | N18: =N22/N6*1000000 -> 1185309.2 | O18: =O22/O6*1000000 -> 1103584.6 | P18: =P22/P6*1000000 -> 1125773.2 | Q18: =Q22/Q6*1000000 -> 1138853.9 | R18: =R22/R6*1000000 -> 1097083.5 | S18: =S22/S6*1000000 -> 1103682.2 | ... U18: =U22/U6*1000000 -> 1289979.9 | W18: =W22/W6*1000000 -> 1294551 | X18: =X22/X6*1000000 -> 1309704.9 | Y18: =Y22/Y6*1000000 -> 1227744.3 | Z18: =Z22/Z6*1000000 -> 1207974.7 | AA18: =AA22/AA6*1000000 -> 1090211.1 | AB18: =AB22/AB6*1000000 -> 1104572.9 | AC18: =AC22/AC6*1000000 -> 1050255.8 | AD18: =AD22/AD6*1000000 -> 1076749.9 | ... AJ18: =AJ22/AJ6*1000000 -> 1267850.8 | AL18: =AL22/AL6*1000000 -> 1319038.8 | AN18: =AN22/AN6*1000000 -> 1362810 | AO18: =AO22/AO6*1000000 -> 1323014.2 | AP18: =AP22/AP6*1000000 -> 1230927.1 | AQ18: =AQ22/AQ6*1000000 -> 1320921 | AS18: =AS22/AS6*1000000 -> 1353658 | AU18: =AU22/AU6*1000000 -> 1316694.4
A19: (INR m) | B19: 1QFY07 | C19: 2QFY07 | D19: 3QFY07 | E19: =E1 -> 4QFY07 | F19: 1QFY08 | G19: 2QFY08 | H19: 3QFY08 | I19: =I1 -> 4QFY08 | J19: 1QFY09 | K19: =K1 -> 2QFY09 | L19: 3QFY09 | M19: 4QFY09 | N19: 1QFY10 | R19: =+R18/N18-1 -> -0.074432626 | S19: =+S18/O18-1 -> 8.8392696e-05 | T19: =+T18/P18-1 -> 0.073067052 | U19: =+U18/Q18-1 -> 0.13270009 | AI19: =+AI18/AH18-1 -> 0.049851827 | AJ19: =+AJ18/AI18-1 -> 0.022394481 | AP19: =+AP18/AM18-1 -> #DIV/0! | AU19: =+AU18/AR18-1 -> #DIV/0!
A20: Gross Sales | B20: 16413.77 | C20: 19286.2 | D20: 20699.79 | E20: 26647.41 | F20: 18831.9 | H20: =H22/0.86 -> 20931.186 | I20: =I22/0.86 -> 29790.756
A21: Less: Excise duty | B21: 2175.05 | C21: 2528.99 | D21: 2923.88 | E21: 3737.49 | F21: 2620.48 | H21: =H20-H22 -> 2930.366 | I21: =I20-I22 -> 4170.7058
A22: Net sales | B22: =B20-B21 -> 14238.72 | C22: =C20-C21 -> 16757.21 | D22: =D20-D21 -> 17775.91 | E22: =E20-E21 -> 22909.92 | F22: =F20-F21 -> 16211.42 | G22: =17458.94 -> 17458.94 | H22: 18000.82 | I22: 25620.05 | J22: 18838.63 | K22: 18664.031 | L22: 10008.483 | M22: 12181.22 | N22: 9124.51 | O22: 15776.846 | P22: =18155.344 -> 18155.344 | Q22: 29390.402 | R22: 23479.781 | S22: 27139.545 | T22: 22272.451 | U22: 38285.313 | V22: =+SUM(R22:U22) -> 111177.09 | W22: 24955.06 | X22: 30945.708 | Y22: 28797.97 | Z22: =42358.201+752 -> 43110.201 | AA22: =29409.8+663.672 -> 30073.472 | AB22: =32224.393+736.062 -> 32960.455 | AC22: =23225.049+580.05 -> 23805.099 | AD22: =36484.115+800.503 -> 37284.618 | AE22: =23132.128+505.992 -> 23638.12 | AF22: =24982.828+513.403 -> 25496.231 | AG22: =19032.828+499.317 -> 19532.145 | AH22: =30209.552+558.219 -> 30767.771 | AI22: =24346.199+431.837 -> 24778.036 | AJ22: =31503.691+673.095 -> 32176.786 | AK22: =32906.227+703.742 -> 33609.969 | AL22: =44355.331+701.714 -> 45057.045 | AM22: =+AL22+AK22+AI22+AJ22 -> 135621.84 | AN22: =37752.961+659.203 -> 38412.164 | AO22: =48788.121+609.262 -> 49397.383 | AP22: =0.375*AP5+(AO22-0.375*AO5)*(AP4/AO4)*0.995 -> 39368.741 | AQ22: =40294.5979999999+558.847 -> 40853.445 | AR22: =AR6/AQ6*AP22 -> 51553.092 | AS22: =58934.885+617.944 -> 59552.829 | AT22: =+AS22+AQ22+AN22+AO22 -> 188215.82 | AU22: =0.375*AU5+(AS22-0.375*AS5)*(AU4/AS4)*1 -> 41034.782
I23: =(I22-I25-I24)*10^6/I6 -> 245177.05 | J23: =(J22-J25-J24)*10^6/J6 -> 242211.13 | K23: =(K22-K25-K24)*10^6/K6 -> 273867.32 | L23: =(L22-L25-L24)*10^6/L6 -> 329751.9 | M23: =(M22-M25-M24)*10^6/M6 -> 309523.19 | N23: =(N22-N25-N24)*10^6/N6 -> 324472.59 | O23: =(O22-O25-O24)*10^6/O6 -> 328595.27 | P23: =(P22-P25-P24)*10^6/P6 -> 322158.24 | Q23: =(Q22-Q25-Q24)*10^6/Q6 -> 305384.24 | R23: =(R25+R24)*10^6/R6 -> 810484.67 | AD23: =SUM(AA22:AD22)/SUM(AA6:AD6) -> 1.0819893
A24: Decrease/(Increase) in Stocks | B24: -821.36 | C24: -554.36 | D24: -951.64 | E24: 1680.43 | F24: -1267.14 | G24: -876.49 | H24: -557.14 | I24: 1788.72 | K24: -1759.269 | L24: 1279.131 | M24: 2601.6 | N24: 374.44 | O24: 421.013 | P24: -2636.084 | Q24: 1905.741 | R24: -1136.017 | S24: -924.936 | T24: -1493.953 | U24: 1065.243 | V24: =+SUM(R24:U24) -> -2489.663 | W24: -2376.723 | X24: 1629.392 | Y24: -1033.842 | Z24: 111.043 | AA24: -1132.23 | AB24: 2157.625 | AC24: -2447.446 | AD24: 4141.82 | AE24: -384.441 | AF24: 1772.155 | AG24: 1309.357 | AH24: 1541.639 | AI24: -1720.916 | AJ24: -892.269 | AK24: 2005.436 | AL24: 81.623 | AM24: =+AL24+AK24+AI24+AJ24 -> -526.126 | AN24: -2469.627 | AO24: -2430.844 | AQ24: -2487.722 | AS24: 2173.827 | AT24: =+AS24+AQ24+AN24+AO24 -> -5214.366
A25: Raw Materials | B25: 11266.69 | C25: 13215.6 | D25: =14177.19+328.2 -> 14505.39 | E25: 15378.79 | F25: 12936.96 | G25: =13584.7+390.61 -> 13975.31 | H25: 14146.82 | I25: =16666.84+468.95 -> 17135.79 | J25: =16518.34+467-2609.45 -> 14375.89 | K25: =15015.97+694.895 -> 15710.865 | L25: =5674.65+403.167 -> 6077.817 | M25: =5779.6+456.86 -> 6236.46 | N25: =5743.31+508.97 -> 6252.28 | O25: 10658.235 | P25: =14849.922+746.06 -> 15595.982 | Q25: =19059.262+544.348 -> 19603.61 | R25: =17787.928+694.082 -> 18482.01 | S25: =20107.221+786.815 -> 20894.036 | T25: =17178.599+609.011 -> 17787.61 | U25: =25893.94+643.789 -> 26537.729 | V25: =+SUM(R25:U25) -> 83701.385 | W25: =19606.331+751.454 -> 20357.785 | X25: =20203.269+924.694 -> 21127.963 | Y25: =20756.678+1564.745 -> 22321.423 | Z25: =1832.844+30147.39 -> 31980.234 | AA25: =20486.898+2532.018 -> 23018.916 | AB25: =18809.779+3025.853 -> 21835.632 | AC25: =16464.181+3089.407 -> 19553.588 | AD25: =19633.306+4470.116 -> 24103.422 | AE25: =15398.46+2822.809 -> 18221.269 | AF25: =14566.981+3118.049 -> 17685.03 | AG25: =10556.513+3702.419 -> 14258.932 | AH25: =18574.993+3046.999 -> 21621.992 | AI25: =17148.371+2731.375 -> 19879.746 | AJ25: =20574.231+4000 -> 24574.231 | AK25: =20364.151+2662.246 -> 23026.397 | AL25: =28179.599+4518.251 -> 32697.85 | AM25: =+AL25+AK25+AI25+AJ25 -> 100178.22 | AN25: =25591.924+3549.388 -> 29141.312 | AO25: =32746.865+4458.318 -> 37205.183 | AP25: =+AP22*AP66/100 -> 27636.856 | AQ25: =26289.917+5116.026 -> 31405.943 | AS25: =37893+2188.523 -> 40081.523 | AT25: =+AS25+AQ25+AN25+AO25 -> 137833.96 | AU25: =+AU22*AU66/100 -> 29216.765
A26: Staff costs | B26: 1291.24 | C26: 1203.48 | D26: 1149.04 | E26: 1163.19 | F26: 1391.1 | G26: 1619.17 | H26: 1477.87 | I26: 1673.58 | J26: 1626.44 | K26: 1570.217 | L26: 1225.269 | M26: 1239.85 | N26: 1440.93 | O26: 1675.036 | P26: 1736.174 | Q26: 1807.117 | R26: 2024.952 | S26: 2114.877 | T26: =2439.233-260 -> 2179.233 | U26: 3018.101 | V26: =+SUM(R26:U26) -> 9337.163 | W26: 2497.391 | X26: 2515.135 | Y26: 2723.22 | Z26: 2468.196 | AA26: 2678.56 | AB26: 2638.047 | AC26: 2617.086 | AD26: 2821.441 | AE26: 2581.889 | AF26: 2545.724 | AG26: 2396.223 | AH26: 2472.887 | AI26: 2831.366 | AJ26: 2914.986 | AK26: 2770.383 | AL26: 3323.303 | AM26: =+AL26+AK26+AI26+AJ26 -> 11840.038 | AN26: 3304.142 | AO26: 3783.532 | AP26: 3300 | AQ26: 3491.794 | AS26: 3407.999 | AT26: =+AS26+AQ26+AN26+AO26 -> 13987.467 | AU26: 3450
A27: Other Expenses | B27: =1315.59 -> 1315.59 | C27: =1542.05+30.48 -> 1572.53 | D27: =1232.58-28.11 -> 1204.47 | E27: =2038.19+53.79 -> 2091.98 | F27: =1407.52+196.94 -> 1604.46 | G27: =1446.71+46.16-390.61 -> 1102.26 | H27: =1278.49+32.95 -> 1311.44 | I27: =2064.68-97.45 -> 1967.23 | J27: =1664.8-339.099 -> 1325.701 | K27: 1602.795 | L27: =594.865+347.652 -> 942.517 | M27: =955.04+180+60 -> 1195.04 | N27: 935.19 | O27: 1362.064 | P27: 1396.976 | Q27: =2290.006+3.936-380 -> 1913.942 | R27: 1754.828 | S27: 1992.975 | T27: 1879.295 | U27: 2565.533 | V27: =+SUM(R27:U27) -> 8192.631 | W27: =2030.412+94.603 -> 2125.015 | X27: 2361.667 | Y27: 2683.451 | Z27: 3851.243 | AA27: 3101.239 | AB27: =2988.261 -> 2988.261 | AC27: 3058.694 | AD27: 4234.932 | AE27: 2986.832 | AF27: 2930.615 | AG27: 2536.67 | AH27: 3291.871 | AI27: 2626.973 | AJ27: 3235.942 | AK27: 3426.273 | AL27: 4383.308 | AM27: =+AL27+AK27+AI27+AJ27 -> 13672.496 | AN27: 4549.35 | AO27: 4895.008 | AP27: 4400 | AQ27: 4146.279 | AS27: 6358.4 | AT27: =+AS27+AQ27+AN27+AO27 -> 19949.037 | AU27: 4150
A28: Provision for contingencies | AM28: =+AL28+AK28+AI28+AJ28 -> 0 | AT28: =+AS28+AQ28+AN28+AO28 -> 0
A29: Total Expenditure | B29: =SUM(B24:B28) -> 13052.16 | C29: =SUM(C24:C28) -> 15437.25 | D29: =SUM(D24:D28) -> 15907.26 | E29: =SUM(E24:E28) -> 20314.39 | F29: =SUM(F24:F28) -> 14665.38 | G29: =SUM(G24:G28) -> 15820.25 | H29: =SUM(H24:H28) -> 16378.99 | I29: =SUM(I24:I28) -> 22565.32 | ... U29: =SUM(U24:U28) -> 33186.606 | V29: =+SUM(R29:U29) -> 98741.516 | W29: =SUM(W24:W28) -> 22603.468 | X29: =SUM(X24:X28) -> 27634.157 | Y29: =SUM(Y24:Y28) -> 26694.252 | Z29: =SUM(Z24:Z28) -> 38410.716 | AA29: =SUM(AA23:AA28) -> 27666.485 | AB29: =SUM(AB23:AB28) -> 29619.565 | AC29: =SUM(AC23:AC28) -> 22781.922 | AD29: =SUM(AD23:AD28) -> 35302.697 | AE29: =SUM(AE23:AE28) -> 23405.549 | AF29: =SUM(AF23:AF28) -> 24933.524 | AG29: =SUM(AG23:AG28) -> 20501.182 | AH29: =SUM(AH23:AH28) -> 28928.389 | ... AQ29: =SUM(AQ23:AQ28) -> 36556.294 | AS29: =SUM(AS23:AS28) -> 52021.749 | AT29: =SUM(AT23:AT28) -> 166556.1 | AU29: =SUM(AU23:AU28) -> 36816.765
A31: EBITDA | B31: =B22-B29 -> 1186.56 | C31: =C22-C29 -> 1319.96 | D31: =D22-D29 -> 1868.65 | E31: =E22-E29 -> 2595.53 | F31: =F22-F29 -> 1546.04 | G31: =G22-G29 -> 1638.69 | H31: =H22-H29 -> 1621.83 | I31: =I22-I29 -> 3054.73 | ... U31: =U22-U29 -> 5098.707 | V31: =+SUM(R31:U31) -> 12435.574 | W31: =W22-W29 -> 2351.592 | X31: =X22-X29 -> 3311.551 | Y31: =Y22-Y29 -> 2103.718 | Z31: =Z22-Z29 -> 4699.485 | AA31: =AA22-AA29 -> 2406.987 | AB31: =AB22-AB29 -> 3340.89 | AC31: =AC22-AC29 -> 1023.177 | AD31: =AD22-AD29 -> 1981.921 | ... AQ31: =AQ22-AQ29 -> 4297.151 | AR31: =AR49/100*AR22 -> 5773.9462 | AS31: =AS22-AS29 -> 7531.08 | AT31: =AT22-AT29 -> 21659.722 | AU31: =AU22-AU29 -> 4218.0173
A32: Forex | C32: 30.48 | D32: -28.11 | F32: 196.94 | G32: 46.16 | H32: 32.95 | J32: -339.099 | K32: -143.508 | L32: -347.652 | AM32: =+AL32+AK32+AI32+AJ32 -> 0 | AT32: =+AS32+AR32+AP32+AQ32 -> 0
A33: Interest | B33: 5.17 | C33: 3.71 | D33: 25.65 | E33: 18.79 | F33: 127.58 | G33: 126.25 | H33: 152.48 | I33: 91.09 | J33: 106.94 | K33: 245.753 | L33: 394.086 | M33: 440.31 | N33: 258.03 | O33: 170.04 | P33: 162.129 | Q33: 221.106 | R33: 316.179 | S33: 394.85 | T33: 474.81 | U33: 450.775 | V33: =+SUM(R33:U33) -> 1636.614 | W33: 533.454 | X33: 626.978 | Y33: 550.123 | Z33: 724.008 | AA33: 833.764 | AB33: 1036.382 | AC33: 1071.055 | AD33: 827.656 | AE33: 1006.794 | AF33: 1244.135 | AG33: 1152.59 | AH33: 1125.729 | AI33: 1063.398 | AJ33: 1007.455 | AK33: 982.159 | AL33: 882.063 | AM33: =+AL33+AK33+AI33+AJ33 -> 3935.075 | AN33: 765.689 | AO33: 701.817 | AP33: 690 | AQ33: 665.712 | AR33: 660 | AS33: 602.228 | AT33: =+AS33+AQ33+AN33+AO33 -> 2735.446 | AU33: 605
A34: Other income | B34: 138.84 | C34: =336.62-235.8 -> 100.82 | D34: 63.51 | E34: 169.06 | F34: 75.5 | G34: 111.4 | H34: =437.02-330 -> 107.02 | I34: 116.07 | J34: 121.66 | K34: =284.945-155 -> 129.945 | L34: 105.836 | M34: =131.05-60 -> 71.05 | N34: =606.24-515 -> 91.24 | O34: 55.596 | P34: 19.522 | Q34: 23.093 | R34: 47.298 | S34: 48.141 | T34: 16.733 | U34: 41.171 | V34: =+SUM(R34:U34) -> 153.343 | W34: 41.177 | X34: 103.27 | Y34: 32.325 | Z34: 108.762 | AA34: 128.659 | AB34: 238.667 | AC34: 140.952 | AD34: 115.237 | AE34: 122.567 | AF34: 231.15 | AG34: 154.086 | AH34: 157.404 | AI34: 231.166 | AJ34: 256.985 | AK34: 193.237 | AL34: 372.458 | AM34: =+AL34+AK34+AI34+AJ34 -> 1053.846 | AN34: 270.95 | AO34: 264.638 | AP34: 250 | AQ34: 258.714 | AR34: 250 | AS34: 319.558 | AT34: =+AS34+AQ34+AN34+AO34 -> 1113.86 | AU34: 250
A35: EBDT | B35: =B31-B33+B34 -> 1320.23 | C35: =C31-C33+C34+C32 -> 1447.55 | D35: =D31-D33+D34+D32 -> 1878.4 | E35: =E31-E33+E34-E32 -> 2745.8 | F35: =F31-F33+F34+F32 -> 1690.9 | G35: =G31-G33+G34+G32 -> 1670 | H35: =H31-H33+H34+H32 -> 1609.32 | I35: =I31-I33+I34-I32 -> 3079.71 | J35: =J31-J33+J34+J32 -> 1186.22 | K35: =K31-K33+K34+K32 -> 1280.107 | L35: =L31-L33+L34-L32 -> 543.151 | M35: =M31-M33+M34-M32 -> 539.01 | N35: =N31-N33+N34+N32 -> -45.12 | O35: =O31-O33+O34+O32 -> 1546.054 | P35: =P31-P33+P34-P32 -> 1919.689 | Q35: =Q31-Q33+Q34-Q32 -> 3961.979 | R35: =R31-R33+R34-R32 -> 2085.127 | S35: =S31-S33+S34-S32 -> 2715.884 | T35: =T31-T33+T34-T32 -> 1462.189 | U35: =U31-U33+U34-U32 -> 4689.103 | V35: =+SUM(R35:U35) -> 10952.303 | W35: =W31-W33+W34-W32 -> 1859.315 | X35: =X31-X33+X34-X32 -> 2787.843 | Y35: =Y31-Y33+Y34-Y32 -> 1585.92 | Z35: =Z31-Z33+Z34-Z32 -> 4084.239 | AA35: =AA31-AA33+AA34-AA32 -> 1701.882 | AB35: =AB31-AB33+AB34-AB32 -> 2543.175 | AC35: =AC31-AC33+AC34-AC32 -> 93.074 | AD35: =AD31-AD33+AD34-AD32 -> 1269.502 | ... AU35: =AU31-AU33+AU34-AU32 -> 3863.0173
A36: Depreciation & Amortization | B36: 327.7 | C36: 364.5 | D36: 332.28 | E36: 481.26 | F36: 412.9 | G36: 466.2 | H36: 408.31 | I36: 486.2 | J36: 441.07 | K36: 505.37 | L36: 357.803 | M36: 479.9 | N36: 435.01 | O36: 505.823 | P36: 512.717 | Q36: 587.533 | R36: 614.688 | S36: 640.593 | T36: 646.908 | U36: 772.121 | V36: =+SUM(R36:U36) -> 2674.31 | W36: 846.588 | X36: 859.325 | Y36: 866.286 | Z36: 955.933 | AA36: 892.523 | AB36: 984.109 | AC36: 931.13 | AD36: 1000.073 | AE36: 951.735 | AF36: 900.843 | AG36: 883.314 | AH36: 1034.468 | AI36: 1033.151 | AJ36: 1030.797 | AK36: 998.61 | AL36: 1100.809 | AM36: =+AL36+AK36+AI36+AJ36 -> 4163.367 | AN36: 1043.17 | AO36: 1129.407 | AP36: 1100 | AQ36: 1086.932 | AR36: 1086.932 | AS36: 1177.159 | AT36: =+AS36+AQ36+AN36+AO36 -> 4436.668 | AU36: 1200
A37: PBT | B37: =B35-B36 -> 992.53 | C37: =C35-C36 -> 1083.05 | D37: =D35-D36 -> 1546.12 | E37: =E35-E36 -> 2264.54 | F37: =F35-F36 -> 1278 | G37: =G35-G36 -> 1203.8 | H37: =H35-H36 -> 1201.01 | I37: =I35-I36 -> 2593.51 | ... T37: =T35-T36 -> 815.281 | U37: =+U35-U36 -> 3916.982 | V37: =+SUM(R37:U37) -> 8277.993 | W37: =+W35-W36 -> 1012.727 | X37: =+X35-X36 -> 1928.518 | Y37: =+Y35-Y36 -> 719.634 | Z37: =+Z35-Z36 -> 3128.306 | AA37: =+AA35-AA36 -> 809.359 | AB37: =+AB35-AB36 -> 1559.066 | AC37: =+AC35-AC36 -> -838.056 | AD37: =+AD35-AD36 -> 269.42901 | ... AU37: =+AU35-AU36 -> 2663.0173
A38: Exceptional income | C38: 235.8 | E38: 53.79 | H38: 330 | I38: -97.45 | K38: 155 | M38: 300 | N38: 515 | W38: 94.603 | Z38: 15.978 | AC38: 1562.569 | AD38: 1343.618 | AF38: 483.193 | AG38: =1002.903+15+341.152 -> 1359.055 | AH38: 3760.941 | AJ38: 1089.728 | AM38: =+AL38+AK38+AI38+AJ38 -> 1089.728 | AO38: 1518.293 | AS38: 416.804 | AT38: =+AS38+AQ38+AN38+AO38 -> 1935.097
A39: Exceptional expenditure | B39: -38.43 | C39: =-30.84 -> -30.84 | D39: 20.6 | E39: -30.44 | F39: -34.92 | G39: -26.5 | H39: =12.77 -> 12.77 | I39: -21.77 | J39: =-21.63 -> -21.63 | K39: -21.708 | L39: =22.289 -> 22.289 | M39: -35.47 | N39: -10.36 | O39: -8.676 | P39: 9.744 | Q39: 380 | T39: 260 | AE39: 65.116 | AF39: 45.616 | AG39: 435.868 | AL39: 80.369 | AM39: =+AL39+AK39+AI39+AJ39 -> 80.369 | AO39: 1570 | AQ39: 65.168 | AS39: 4209.379 | AT39: =+AS39+AQ39+AN39+AO39 -> 5844.547
A40: Tax | B40: 262.3 | C40: 334.38 | D40: =460.45+12.5 -> 472.95 | E40: 572.7 | F40: 361.2 | G40: 373.94 | H40: =20+296.07 -> 316.07 | I40: 668.6 | J40: 217.82 | K40: =207.288+28.304 -> 235.592 | L40: =-26.523+0.9 -> -25.623 | M40: -209.5 | N40: -53.2 | O40: 145.5 | P40: 350.9 | Q40: 767.8 | R40: 244 | S40: 404.7 | T40: 121.6 | U40: =885.8+48.9 -> 934.7 | V40: =+SUM(R40:U40) -> 1705 | W40: =167.9+76.9 -> 244.8 | X40: 387.7 | Y40: 50.6 | Z40: =327.4+229.5 -> 556.9 | AA40: =100+40 -> 140 | AB40: 133.1 | AC40: -16.9 | AD40: 113.8 | AE40: -251 | AF40: -663 | AG40: -255.6 | AH40: -36.4 | AI40: -225 | AJ40: 445.47 | AK40: 273 | AL40: 580.437 | AM40: =+AL40+AK40+AI40+AJ40 -> 1073.907 | AN40: 755.889 | AO40: 1458.111 | AP40: =+AP37*0.3 -> 747.56545 | AQ40: 751.8 | AR40: =AR56/100*AR37 -> 1197.564 | AS40: 1508.46 | AT40: =+AS40+AQ40+AN40+AO40 -> 4474.26 | AU40: =+AU37*0.28 -> 745.64484
A41: PAT | B41: =B37+B38+B39-B40 -> 691.8 | C41: =C37+C38+C39-C40 -> 953.63 | D41: =D37+D38-D40-D39 -> 1052.57 | E41: =E37+E38+E39-E40 -> 1715.19 | F41: =F37+F38+F39-F40 -> 881.88 | G41: =G37+G38+G39-G40 -> 803.36 | H41: =H37+H38-H40-H39 -> 1202.17 | I41: =I37+I38+I39-I40 -> 1805.69 | J41: =J37+J38+J39-J40 -> 505.7 | K41: =K37+K38+K39-K40 -> 672.437 | L41: =L37+L38-L40-L39 -> 188.682 | M41: =M37+M38+M39-M40 -> 533.14 | N41: =N37-N40+N39+N38 -> 77.71 | O41: =O37-O40+O39+O38 -> 886.055 | P41: =P37+P38-P40-P39 -> 1046.328 | Q41: =Q37+Q38-Q40-Q39 -> 2226.646 | R41: =R37+R38-R40-R39 -> 1226.439 | S41: =S37+S38-S40-S39 -> 1670.591 | T41: =T37+T38-T40-T39 -> 433.681 | U41: =U37+U38-U40-U39 -> 2982.282 | V41: =+SUM(R41:U41) -> 6312.993 | W41: =W37+W38-W40-W39 -> 862.53 | X41: =X37+X38-X40-X39 -> 1540.818 | Y41: =Y37+Y38-Y40-Y39 -> 669.034 | Z41: =Z37+Z38-Z40-Z39 -> 2587.384 | AA41: =AA37+AA38-AA40-AA39 -> 669.359 | AB41: =AB37+AB38-AB40-AB39 -> 1425.966 | AC41: =AC37+AC38-AC40-AC39 -> 741.413 | AD41: =AD37+AD38-AD40-AD39 -> 1499.247 | ... AU41: =AU37+AU38-AU40-AU39 -> 1917.3725
A42: PAT (pre exceptionals) | B42: =B41-B39 -> 730.23 | C42: =C41-((C39)*(1-C56/100))-C38 -> 740.66363 | D42: =D41-D39 -> 1031.97 | E42: =E41-E39-E38*(1-E56/100) -> 1705.3046 | F42: =F41-F39 -> 916.8 | G42: =G41-((G39)*(1-G56/100))-G38+G32*(1-0.3) -> 853.75494 | H42: =H41-H38+H39 -> 884.94 | I42: =I41-I39-I38*(1-I56/100) -> 1898.5772 | J42: =J41-J39-J32*0.7 -> 764.6993 | K42: =K41-K39-K32*0.7-K38*0.9 -> 655.1006 | L42: =L41+((L39)*(1-0.3))-L38+L32*(1-0.3) -> -39.0721 | M42: =M41-M39-M38*(1-30/100) -> 358.61 | N42: =N41-N38-N39 -> -426.93 | O42: =O41-O38-O39 -> 894.731 | P42: =P41+P39-P38+P32*(1-0.3) -> 1056.072 | Q42: =Q41+Q39*(1-Q40/Q37)-Q38+Q32*(1-0.3) -> 2520.1832 | R42: =R41+R39-R38+R32*(1-0.3) -> 1226.439 | S42: =S41+S39-S38+S32*(1-0.3) -> 1670.591 | T42: =T41+T39-T38+T32*(1-0.3) -> 693.681 | U42: =U41+U39-U38+U32*(1-0.3) -> 2982.282 | V42: =+SUM(R42:U42) -> 6572.993 | W42: =W41+W39-W38*(1-W56/100) -> 788.8411 | X42: =X41+X39-X38*(1-X56/100) -> 1540.818 | Y42: =Y41+Y39-Y38*(1-Y56/100) -> 669.034 | Z42: =Z41+Z39-Z38*(1-Z56/100) -> 2574.2359 | AA42: =AA41+AA39-AA38*(1-AA56/100) -> 669.359 | AB42: =AB41+AB39-AB38*(1-AB56/100) -> 1425.966 | AC42: =AC41+AC39-AC38 -> -821.156 | AD42: =AD41+AD39-AD38 -> 155.62901 | AE42: =AE41+AE39-AE38 -> -1352.391 | AF42: =AF41+AF39-AF38 -> -688.121 | AG42: =AG41+AG39-AG38 -> -2595.255 | AH42: =AH41+AH39-AH38 -> -127.011 | AI42: =AI41+AI39-AI38 -> -479.516 | AJ42: =AJ41+AJ39-AJ38 -> 117.159 | ... AO42: =AO41+AO39-AO38 -> 2919.807 | AP42: =AP41+AP39-AP38+AP32*(1-0.3) -> 1744.3194 | AQ42: =AQ41+AQ39-AQ38 -> 2051.421 | AR42: =AR41+AR39-AR38 -> 3079.4503 | AS42: =AS41+AS39-AS38 -> 4562.791 | AT42: =AT41+AT39-AT38 -> 11127.208 | AU42: =AU41+AU39-AU38+AU32*(1-0.3) -> 1917.3725
AI43: =+AI42+479.516 -> 1.9895197e-12 | AJ43: =+AJ41-1206.887 -> 0 | AK43: =+AK42-320.948 -> -4.0927262e-12 | AL43: =+AL41-22997.41/10 -> 0 | AN43: =+AN42-1593.189 -> 7.9580786e-12 | AO43: =+AO41-2868.1 -> 0 | AQ43: =+AQ41-1986.253 -> -8.9812602e-11 | AS43: =+AS41-770.216 -> 9.4360075e-12
A44: EBDIT | B44: =B31+B34 -> 1325.4 | C44: =C31+C34 -> 1420.78 | D44: =D31+D34 -> 1932.16 | E44: =E31+E34 -> 2764.59 | F44: =F31+F34 -> 1621.54 | G44: =G31+G34 -> 1750.09 | H44: =H31+H34 -> 1728.85 | I44: =I31+I34 -> 3170.8 | ... U44: =U31+U34 -> 5139.878 | V44: =+SUM(R44:U44) -> 12588.917 | W44: =W31+W34 -> 2392.769 | X44: =X31+X34 -> 3414.821 | Y44: =Y31+Y34 -> 2136.043 | Z44: =Z31+Z34 -> 4808.247 | AA44: =AA31+AA34 -> 2535.646 | AB44: =AB31+AB34 -> 3579.557 | AC44: =AC31+AC34 -> 1164.129 | AD44: =AD31+AD34 -> 2097.158 | ... AL44: =AL31+AL34 -> 4943.419 | AN44: =AN31+AN34 -> 4157.937 | AO44: =AO31+AO34 -> 6209.142 | AP44: =AP31+AP34 -> 4281.8848 | AQ44: =AQ31+AQ34 -> 4555.865 | AS44: =AS31+AS34 -> 7850.638 | AT44: =AT31+AT34 -> 22773.582 | AU44: =AU31+AU34 -> 4468.0173
A45: EBIT (ex other income) | B45: =B31-B36 -> 858.86 | C45: =C31-C36 -> 955.46 | D45: =D31-D36 -> 1536.37 | E45: =E31-E36 -> 2114.27 | F45: =F31-F36 -> 1133.14 | G45: =G31-G36 -> 1172.49 | H45: =H31-H36 -> 1213.52 | I45: =I31-I36 -> 2568.53 | ... U45: =U31-U36 -> 4326.586 | V45: =+SUM(R45:U45) -> 9761.264 | W45: =W31-W36 -> 1505.004 | X45: =X31-X36 -> 2452.226 | Y45: =Y31-Y36 -> 1237.432 | Z45: =Z31-Z36 -> 3743.552 | AA45: =AA31-AA36 -> 1514.464 | AB45: =AB31-AB36 -> 2356.781 | AC45: =AC31-AC36 -> 92.047 | AD45: =AD31-AD36 -> 981.84801 | ... AL45: =AL31-AL36 -> 3470.152 | AN45: =AN31-AN36 -> 2843.817 | AO45: =AO31-AO36 -> 4815.097 | AP45: =AP31-AP36 -> 2931.8848 | AQ45: =AQ31-AQ36 -> 3210.219 | AS45: =AS31-AS36 -> 6353.921 | AT45: =AT31-AT36 -> 17223.054 | AU45: =AU31-AU36 -> 3018.0173
A46: Cash profit | B46: =B42+B36 -> 1057.93 | C46: =C42+C36 -> 1105.1636 | D46: =D42+D36 -> 1364.25 | E46: =E42+E36 -> 2186.5646 | F46: =F42+F36 -> 1329.7 | G46: =G42+G36 -> 1319.9549 | H46: =H42+H36 -> 1293.25 | I46: =I42+I36 -> 2384.7772 | ... U46: =U42+U36 -> 3754.403 | V46: =+SUM(R46:U46) -> 9247.303 | W46: =W42+W36 -> 1635.4291 | X46: =X42+X36 -> 2400.143 | Y46: =Y42+Y36 -> 1535.32 | Z46: =Z42+Z36 -> 3530.1689 | AA46: =AA42+AA36 -> 1561.882 | AB46: =AB42+AB36 -> 2410.075 | AC46: =AC42+AC36 -> 109.974 | AD46: =AD42+AD36 -> 1155.702 | ... AL46: =AL42+AL36 -> 3480.919 | AN46: =AN42+AN36 -> 2636.359 | AO46: =AO42+AO36 -> 4049.214 | AP46: =AP42+AP36 -> 2844.3194 | AQ46: =AQ42+AQ36 -> 3138.353 | AS46: =AS42+AS36 -> 5739.95 | AT46: =AT42+AT36 -> 15563.876 | AU46: =AU42+AU36 -> 3117.3725
A47: Profit Margins
A48: EBITDA (%) | B48: =B31/B20*100 -> 7.2290522 | C48: =C31/C20*100 -> 6.8440647 | D48: =D31/D20*100 -> 9.0273863 | E48: =E31/E20*100 -> 9.7402712 | F48: =F31/F20*100 -> 8.2096868 | G48: =G31/G20*100 -> #DIV/0! | H48: =H31/H20*100 -> 7.7483904 | I48: =I31/I20*100 -> 10.253953 | ... K48: =K31/K20*100 -> #DIV/0! | M48: =M31/M20*100 -> #DIV/0! | N48: =N31/N20*100 -> #DIV/0! | O48: =O31/O20*100 -> #DIV/0!
A49: EBITDA (%) net sales | B49: =B31/B22*100 -> 8.3333333 | C49: =C31/C22*100 -> 7.8769676 | D49: =D31/D22*100 -> 10.512261 | E49: =E31/E22*100 -> 11.329284 | F49: =F31/F22*100 -> 9.536734 | G49: =G31/G22*100 -> 9.385965 | H49: =H31/H22*100 -> 9.0097562 | I49: =I31/I22*100 -> 11.923201 | ... AL49: =AL31/AL22*100 -> 10.144831 | AN49: =AN31/AN22*100 -> 10.119157 | AO49: =AO31/AO22*100 -> 12.034046 | AP49: =AP31/AP22*100 -> 10.241335 | AQ49: =AQ31/AQ22*100 -> 10.518454 | AR49: 11.2 | AS49: =AS31/AS22*100 -> 12.646049 | AT49: =AT31/AT22*100 -> 11.507918 | AU49: =AU31/AU22*100 -> 10.279127
A50: Interest cover (x) | B50: =B44/B33 -> 256.36364 | C50: =C44/C33 -> 382.95957 | D50: =D44/D33 -> 75.327875 | E50: =E44/E33 -> 147.13092 | F50: =F44/F33 -> 12.709986 | G50: =G44/G33 -> 13.862099 | H50: =H44/H33 -> 11.338208 | I50: =I44/I33 -> 34.809529 | ... AL50: =AL44/AL33 -> 5.6043831 | AN50: =AN44/AN33 -> 5.4303209 | AO50: =AO44/AO33 -> 8.847238 | AP50: =AP44/AP33 -> 6.2056302 | AQ50: =AQ44/AQ33 -> 6.8435975 | AS50: =AS44/AS33 -> 13.03599 | AT50: =AT44/AT33 -> 8.3253634 | AU50: =AU44/AU33 -> 7.3851525
A51: Other income / EBDIT (%) | B51: =B34/B44*100 -> 10.475328 | C51: =C34/C44*100 -> 7.0961021 | D51: =D34/D44*100 -> 3.2869949 | E51: =E34/E44*100 -> 6.1151925 | F51: =F34/F44*100 -> 4.6560677 | G51: =G34/G44*100 -> 6.3653869 | H51: =H34/H44*100 -> 6.1902421 | I51: =I34/I44*100 -> 3.6605904 | ... AL51: =AL34/AL44*100 -> 7.534421 | AN51: =AN34/AN44*100 -> 6.5164528 | AO51: =AO34/AO44*100 -> 4.2620703 | AP51: =AP34/AP44*100 -> 5.8385503 | AQ51: =AQ34/AQ44*100 -> 5.6787021 | AS51: =AS34/AS44*100 -> 4.0704717 | AT51: =AT34/AT44*100 -> 4.891018 | AU51: =AU34/AU44*100 -> 5.595323
A52: Other income / PAT (%) | B52: =B34/B42*100 -> 19.013188 | C52: =C34/C42*100 -> 13.612117 | D52: =D34/D42*100 -> 6.1542487 | E52: =E34/E42*100 -> 9.9137714 | F52: =F34/F42*100 -> 8.2351658 | G52: =G34/G42*100 -> 13.048241 | H52: =H34/H42*100 -> 12.093475 | I52: =I34/I42*100 -> 6.1135255 | ... AL52: =AL34/AL42*100 -> 15.648773 | AN52: =AN34/AN42*100 -> 17.006771 | AO52: =AO34/AO42*100 -> 9.0635443 | AP52: =AP34/AP42*100 -> 14.332238 | AQ52: =AQ34/AQ42*100 -> 12.611453 | AS52: =AS34/AS42*100 -> 7.0035643 | AT52: =AT34/AT42*100 -> 10.010238 | AU52: =AU34/AU42*100 -> 13.038677
A53: EBIT (%) | B53: =B45/B20*100 -> 5.2325578 | C53: =C45/C20*100 -> 4.9541123 | D53: =D45/D20*100 -> 7.4221526 | E53: =E45/E20*100 -> 7.934242 | F53: =F45/F20*100 -> 6.0171305 | G53: =G45/G20*100 -> #DIV/0! | H53: =H45/H20*100 -> 5.7976648 | I53: =I45/I20*100 -> 8.6219028 | ... O53: =O45/O20*100 -> #DIV/0!
A54: EBDT (%) | B54: =B35/B20*100 -> 8.0434294 | C54: =C35/C20*100 -> 7.5056258 | D54: =D35/D20*100 -> 9.0744882 | E54: =E35/E20*100 -> 10.304191 | F54: =F35/F20*100 -> 8.9789134 | G54: =G35/G20*100 -> #DIV/0! | H54: =H35/H20*100 -> 7.6886231 | I54: =I35/I20*100 -> 10.337804 | ... O54: =O35/O20*100 -> #DIV/0!
A55: Pre tax margins (%) | B55: =B37/B20*100 -> 6.046935 | C55: =C37/C20*100 -> 5.6156734 | D55: =D37/D20*100 -> 7.4692545 | E55: =E37/E20*100 -> 8.4981617 | F55: =F37/F20*100 -> 6.7863572 | G55: =G37/G20*100 -> #DIV/0! | H55: =H37/H20*100 -> 5.7378975 | I55: =I37/I20*100 -> 8.7057543 | ... K55: =K37/K20*100 -> #DIV/0! | L55: =L37/L22*100 -> 1.851909 | M55: =M37/M22*100 -> 0.48525517 | N55: =N37/N22*100 -> -5.2619812 | O55: =O37/O22*100 -> 6.5934028 | P55: =P37/P22*100 -> 7.7496301 | Q55: =Q37/Q22*100 -> 11.481456 | R55: =R37/R22*100 -> 6.2625754 | S55: =S37/S22*100 -> 7.6467421 | ... AL55: =AL37/AL22*100 -> 6.5706639 | AN55: =AN37/AN22*100 -> 6.1154534 | AO55: =AO37/AO22*100 -> 8.8626517 | AP55: =AP37/AP22*100 -> 6.3296026 | AQ55: =AQ37/AQ22*100 -> 6.8616514 | AS55: =AS37/AS22*100 -> 10.194731 | AT55: =AT37/AT22*100 -> 8.2891374 | AU55: =AU37/AU22*100 -> 6.4896586
A56: Tax / PBT (%) | B56: =B40/(B37+B38+B39)*100 -> 27.491877 | C56: =C40/(C37+C38+C39)*100 -> 25.960979 | D56: =D40/(D37+D38+D39)*100 -> 30.18727 | E56: =E40/(E37+E38+E39)*100 -> 25.031798 | F56: =F40/(F37+F38+F39)*100 -> 29.056859 | G56: =G40/(G37+G38+G39)*100 -> 31.762507 | H56: =H40/(H37+H38+H39)*100 -> 20.473772 | I56: =I40/(I37+I38+I39)*100 -> 27.021893 | ... AL56: =AL40/(AL37+AL38+AL39)*100 -> 19.087571 | AN56: =AN40/(AN37+AN38+AN39)*100 -> 32.178114 | AO56: =AO40/(AO37+AO38+AO39)*100 -> 19.529464 | AP56: =AP40/(AP37+AP38+AP39)*100 -> 30 | AQ56: =AQ40/(AQ37+AQ38+AQ39)*100 -> 26.209834 | AR56: 28 | AS56: =AS40/(AS37+AS38+AS39)*100 -> 14.101139 | AT56: =AT40/(AT37+AT38+AT39)*100 -> 19.136216 | AU56: =AU40/(AU37+AU38+AU39)*100 -> 28
A57: Net profit margins (%) | B57: =B42/B20*100 -> 4.4488865 | C57: =C42/C20*100 -> 3.8403814 | D57: =D42/D20*100 -> 4.9854129 | E57: =E42/E20*100 -> 6.3995135 | F57: =F42/F20*100 -> 4.8683351 | G57: =G42/G20*100 -> #DIV/0! | H57: =H42/H20*100 -> 4.2278541 | I57: =I42/I20*100 -> 6.3730413 | ... K57: =K42/K20*100 -> #DIV/0! | M57: =M42/M20*100 -> #DIV/0! | N57: =N42/N20*100 -> #DIV/0! | O57: =O42/O20*100 -> #DIV/0!
A58: Net profit margins (%) Net Sales | B58: =B42/B22*100 -> 5.1284806 | C58: =C42/C22*100 -> 4.4199699 | D58: =D42/D22*100 -> 5.8054412 | E58: =E42/E22*100 -> 7.4435206 | F58: =F42/F22*100 -> 5.6552726 | G58: =G42/G22*100 -> 4.8900731 | H58: =H42/H22*100 -> 4.9161094 | I58: =I42/I22*100 -> 7.4105131 | ... AL58: =AL42/AL22*100 -> 5.282437 | AN58: =AN42/AN22*100 -> 4.1476158 | AO58: =AO42/AO22*100 -> 5.9108536 | AP58: =AP42/AP22*100 -> 4.4307218 | AQ58: =AQ42/AQ22*100 -> 5.021415 | AS58: =AS42/AS22*100 -> 7.6617536 | AT58: =AT42/AT22*100 -> 5.9119408 | AU58: =AU42/AU22*100 -> 4.6725542
A60: Cost ratios
A61: Excise / sales | B61: =B21/B20*100 -> 13.251374 | C61: =C21/C20*100 -> 13.112951 | D61: 13.11 | E61: =E21/E20*100 -> 14.025716 | F61: =F21/F20*100 -> 13.915112 | G61: =G21/G20*100 -> #DIV/0! | H61: 14.11 | I61: =I21/I20*100 -> 14 | J61: =J21/J20*100 -> #DIV/0! | K61: =K21/K20*100 -> #DIV/0! | M61: =M21/M20*100 -> #DIV/0! | N61: =N21/N20*100 -> #DIV/0!
A62: Raw materials / sales | B62: =(B24+B25)/B20*100 -> 63.637604 | C62: =(C24+C25)/C20*100 -> 65.649221 | D62: =(D24+D25)/D20*100 -> 65.477717 | E62: =(E24+E25)/E20*100 -> 64.018304 | F62: =(F24+F25)/F20*100 -> 61.968362 | G62: =(G24+G25)/G20*100 -> #DIV/0! | H62: =(H24+H25)/H20*100 -> 64.925513 | I62: =(I24+I25)/I20*100 -> 63.524773 | ... N62: =(N24+N25)/N20*100 -> #DIV/0!
A63: Staff costs / sales | B63: =B26/B20*100 -> 7.8668094 | C63: =C26/C20*100 -> 6.2401095 | D63: =D26/D20*100 -> 5.5509742 | E63: =E26/E20*100 -> 4.3651147 | F63: =F26/F20*100 -> 7.3869339 | G63: =G26/G20*100 -> #DIV/0! | H63: =H26/H20*100 -> 7.0606128 | I63: =I26/I20*100 -> 5.6177829 | ... N63: =N26/N20*100 -> #DIV/0!
A64: Other expenses / sales | B64: =B27/B20*100 -> 8.0151604 | C64: =C27/C20*100 -> 8.1536539 | D64: =D27/D20*100 -> 5.8187547 | E64: =E27/E20*100 -> 7.8505941 | F64: =F27/F20*100 -> 8.5199051 | G64: =G27/G20*100 -> #DIV/0! | H64: =H27/H20*100 -> 6.2654835 | I64: =I27/I20*100 -> 6.6034914 | ... N64: =N27/N20*100 -> #DIV/0!
A65: Cost ratios
A66: Raw materials / sales | B66: =(B24+B25)/B22*100 -> 73.358631 | C66: =(C24+C25)/C22*100 -> 75.556969 | D66: =(D24+D25)/D22*100 -> 76.247855 | E66: =(E24+E25)/E22*100 -> 74.462154 | F66: =(F24+F25)/F22*100 -> 71.985181 | G66: =(G24+G25)/G22*100 -> 75.026433 | H66: =(H24+H25)/H22*100 -> 75.494783 | I66: =(I24+I25)/I22*100 -> 73.866015 | ... AL66: =(AL24+AL25)/AL22*100 -> 72.751049 | AN66: =(AN24+AN25)/AN22*100 -> 69.435518 | AO66: =(AO24+AO25)/AO22*100 -> 70.397128 | AP66: 70.2 | AQ66: =(AQ24+AQ25)/AQ22*100 -> 70.785269 | AS66: =(AS24+AS25)/AS22*100 -> 70.954396 | AT66: =(AT24+AT25)/AT22*100 -> 70.461449 | AU66: 71.2
A67: Staff costs / sales | B67: =B26/B22*100 -> 9.0685118 | C67: =C26/C22*100 -> 7.1818638 | D67: =D26/D22*100 -> 6.4640291 | E67: =E26/E22*100 -> 5.0772329 | F67: =F26/F22*100 -> 8.580988 | G67: =G26/G22*100 -> 9.2741598 | H67: =H26/H22*100 -> 8.2100149 | I67: =I26/I22*100 -> 6.5323058 | ... AL67: =AL26/AL22*100 -> 7.3757678 | AN67: =AN26/AN22*100 -> 8.6018117 | AO67: =AO26/AO22*100 -> 7.6593774 | AP67: =AP26/AP22*100 -> 8.3822848 | AQ67: =AQ26/AQ22*100 -> 8.5471225 | AS67: =AS26/AS22*100 -> 5.7226484 | AT67: =AT26/AT22*100 -> 7.4316107 | AU67: =AU26/AU22*100 -> 8.4075017
A68: Other expenses / sales | B68: =B27/B22*100 -> 9.2395243 | C68: =C27/C22*100 -> 9.3841994 | D68: =D27/D22*100 -> 6.7758556 | E68: =E27/E22*100 -> 9.1313283 | F68: =F27/F22*100 -> 9.8970972 | G68: =G27/G22*100 -> 6.3134417 | H68: =H27/H22*100 -> 7.2854459 | I68: =I27/I22*100 -> 7.6784784 | ... AL68: =AL27/AL22*100 -> 9.7283521 | AN68: =AN27/AN22*100 -> 11.843514 | AO68: =AO27/AO22*100 -> 9.909448 | AP68: =AP27/AP22*100 -> 11.17638 | AQ68: =AQ27/AQ22*100 -> 10.149154 | AS68: =AS27/AS22*100 -> 10.676907 | AT68: =AT27/AT22*100 -> 10.599022 | AU68: =AU27/AU22*100 -> 10.113372
A70: Equity (m shares) | B70: 1309.9 | C70: 1309.9 | D70: 1323.3 | E70: 1323.3 | F70: 1330.34 | G70: 1331.34 | H70: 1330.34 | I70: 1330.34 | J70: 1330.34 | K70: 1330.34 | L70: 1330.34 | M70: 1330.34 | N70: 1330.34 | O70: 1330.34 | P70: 1330.34 | Q70: 1330.34 | R70: 1330.34 | S70: 1330.34 | T70: 1330.34 | U70: 1330.34 | V70: 1330.34 | W70: 1330.34 | X70: =1330.34*2 -> 2660.68 | Y70: =1330.34*2 -> 2660.68 | Z70: =1330.34*2 -> 2660.68 | AA70: =1330.34*2 -> 2660.68 | AB70: =1330.34*2 -> 2660.68 | AC70: =1330.34*2 -> 2660.68 | AD70: =1330.34*2 -> 2660.68 | AE70: =1330.34*2 -> 2660.68 | ... AI70: =1330.34*2 -> 2660.68 | AJ70: =+'Main Model'!X84 -> 5691.76 | AK70: =+'Main Model'!Y84 -> 5691.76 | AL70: =+'Main Model'!Z84 -> 5691.76 | AN70: 2845.88 | AO70: 2845.88 | AP70: 2845.88 | AQ70: 2845.88 | AS70: 2845.88 | AU70: 2845.88
A72: EPS (Rs) | B72: =B42/B70 -> 0.55747004 | C72: =C42/C70 -> 0.56543525 | D72: =D42/D70 -> 0.77984584 | E72: =E42/E70 -> 1.2886757 | F72: =F42/F70 -> 0.68914714 | G72: =G42/G70 -> 0.64127491 | H72: =H42/H70 -> 0.66519837 | I72: =I42/I70 -> 1.4271368 | ... AL72: =AL42/AL70 -> 0.41816767 | AN72: =AN42/AN70 -> 0.55982297 | AO72: =AO42/AO70 -> 1.0259769 | AP72: =AP42/AP70 -> 0.61292795 | AQ72: =AQ42/AQ70 -> 0.7208389 | AS72: =AS42/AS70 -> 1.603297 | AU72: =AU42/AU70 -> 0.67373623
A73: CEPS (Rs) | B73: =B46/B70 -> 0.8076418 | C73: =C46/C70 -> 0.84370077 | D73: =D46/D70 -> 1.0309454 | E73: =E46/E70 -> 1.6523574 | F73: =F46/F70 -> 0.99951892 | G73: =G46/G70 -> 0.99144842 | H73: =H46/H70 -> 0.97211991 | I73: =I46/I70 -> 1.7926073 | ... AL73: =AL46/AL70 -> 0.61157164 | AN73: =AN46/AN70 -> 0.92637743 | AO73: =AO46/AO70 -> 1.4228337 | AP73: =AP46/AP70 -> 0.99945163 | AQ73: =AQ46/AQ70 -> 1.1027707 | AS73: =AS46/AS70 -> 2.0169333 | AU73: =AU46/AU70 -> 1.0953984
A75: EPS (Rs) reported PAT | B75: =B41/B70 -> 0.52813192 | C75: =C41/C70 -> 0.72801741 | D75: =D41/D70 -> 0.79541298 | E75: =E41/E70 -> 1.296146 | F75: =F41/F70 -> 0.66289821 | G75: =G41/G70 -> 0.60342212 | H75: =H41/H70 -> 0.90365621 | I75: =I41/I70 -> 1.3573147 | ... AL75: =AL41/AL70 -> 0.40404743 | AN75: =AN41/AN70 -> 0.55982297 | AO75: =AO41/AO70 -> 1.0078078 | AP75: =AP41/AP70 -> 0.61292795 | AQ75: =AQ41/AQ70 -> 0.69793983 | AS75: =AS41/AS70 -> 0.27064247 | AU75: =AU41/AU70 -> 0.67373623
F77: =F22-F15-F14 -> 14866.21 | G77: 1) Why interest cost has increased? Debt repayment schedule? | N77: =+N1 -> 1QFY10 | O77: =+O1 -> 2QFY10 | P77: =+P1 -> 3QFY10 | Q77: =+Q1 -> 4QFY10A | R77: =+R1 -> 1QFY11A | S77: =+S1 -> 2QFY11A | T77: =+T1 -> 3QFY11A | U77: =+U1 -> 4QFY11A | ... AL77: =+AL1 -> 4QFY15A | AN77: =+AN1 -> 1QFY16A | AO77: =+AO1 -> 2QFY16A | AP77: =+AP1 -> 3QFY16E | AQ77: =+AQ1 -> 3QFY16A | AS77: =+AS1 -> 4QFY16A | AU77: =+AU1 -> 1QFY17E
A78: Average Realizations | N78: =+N22/N6*1000000 -> 1185309.2 | O78: =+O22/O6*1000000 -> 1103584.6 | P78: =+P22/P6*1000000 -> 1125773.2 | Q78: =+Q22/Q6*1000000 -> 1138853.9 | R78: =+R22/R6*1000000 -> 1097083.5 | S78: =+S22/S6*1000000 -> 1103682.2 | T78: =+T22/T6*1000000 -> 1208030.1 | U78: =+U22/U6*1000000 -> 1289979.9 | ... AL78: =+AL22/AL6*1000000 -> 1319038.8 | AN78: =+AN22/AN6*1000000 -> 1362810 | AO78: =+AO22/AO6*1000000 -> 1323014.2 | AP78: =+AP22/AP6*1000000 -> 1230927.1 | AQ78: =+AQ22/AQ6*1000000 -> 1320921 | AS78: =+AS22/AS6*1000000 -> 1353658 | AU78: =+AU22/AU6*1000000 -> 1316694.4
A79: Material Cost / Vehicle | N79: =+(N24+N25)/N6*1000000 -> 860836.58 | O79: =+(O24+O25)/O6*1000000 -> 774989.37 | P79: =+(P24+P25)/P6*1000000 -> 803614.93 | Q79: =+(Q24+Q25)/Q6*1000000 -> 833469.64 | R79: =+(R24+R25)/R6*1000000 -> 810484.67 | S79: =+(S24+S25)/S6*1000000 -> 812082.15 | T79: =+(T24+T25)/T6*1000000 -> 883747.74 | U79: =+(U24+U25)/U6*1000000 -> 930050.61 | ... AL79: =+(AL24+AL25)/AL6*1000000 -> 959614.54 | AN79: =+(AN24+AN25)/AN6*1000000 -> 946274.21 | AO79: =+(AO24+AO25)/AO6*1000000 -> 931364.04 | AP79: =+(AP23+AP25)/AP6*1000000 -> 864110.82 | AQ79: =+(AQ24+AQ25)/AQ6*1000000 -> 935017.49 | AS79: =+(AS24+AS25)/AS6*1000000 -> 960479.84 | AU79: =+(AU23+AU25)/AU6*1000000 -> 937486.44
A80: Gross Contribution / Vehicle | N80: =+(N22-N24-N25)/N6*1000000 -> 324472.59 | O80: =+(O22-O24-O25)/O6*1000000 -> 328595.27 | P80: =+(P22-P24-P25)/P6*1000000 -> 322158.24 | Q80: =+(Q22-Q24-Q25)/Q6*1000000 -> 305384.24 | R80: =+(R22-R24-R25)/R6*1000000 -> 286598.82 | S80: =+(S22-S24-S25)/S6*1000000 -> 291600.04 | T80: =+(T22-T24-T25)/T6*1000000 -> 324282.37 | U80: =+(U22-U24-U25)/U6*1000000 -> 359929.28 | ... AL80: =+(AL22-AL24-AL25)/AL6*1000000 -> 359424.22 | AN80: =+(AN22-AN24-AN25)/AN6*1000000 -> 416535.83 | AO80: =+(AO22-AO24-AO25)/AO6*1000000 -> 391650.21 | AP80: =+(AP22-AP23-AP25)/AP6*1000000 -> 366816.27 | AQ80: =+(AQ22-AQ24-AQ25)/AQ6*1000000 -> 385903.52 | AS80: =+(AS22-AS24-AS25)/AS6*1000000 -> 393178.14 | AU80: =+(AU22-AU23-AU25)/AU6*1000000 -> 379208
A81: EBITDA / Vehicle | N81: =+N31/N6*1000000 -> 15805.404 | O81: =+O31/O6*1000000 -> 116151.23 | P81: =+P31/P6*1000000 -> 127878.46 | Q81: =+Q31/Q6*1000000 -> 161196.26 | R81: =+R31/R6*1000000 -> 109990.09 | S81: =+S31/S6*1000000 -> 124546.28 | T81: =+T31/T6*1000000 -> 104152.84 | U81: =+U31/U6*1000000 -> 171795.11 | ... AL81: =+AL31/AL6*1000000 -> 133814.25 | AN81: =+AN31/AN6*1000000 -> 137904.88 | AO81: =+AO31/AO6*1000000 -> 159212.15 | AP81: =+AP31/AP6*1000000 -> 126063.37 | AQ81: =+AQ31/AQ6*1000000 -> 138940.47 | AS81: =+AS31/AS6*1000000 -> 171184.25 | AU81: =+AU31/AU6*1000000 -> 135344.69
A85: To understand mix shift better
A86: Goods CVs (domestic)
A87: 7.5-12 MT | AE87: 1 | AF87: 1363 | AG87: 946 | AH87: 1529 | AI87: 1062 | AJ87: 1205 | AK87: 1171 | AL87: 1171
A88: 12-16.2 MT | AE88: 1.25 | AF88: 2291 | AG88: 2307 | AH88: 3295 | AI88: 2286 | AJ88: 2242 | AK88: 2530 | AL88: 2530
A89: 16.2-25 MT | AE89: 1.5 | AF89: 2547 | AG89: 1897 | AH89: 2709 | AI89: 2516 | AJ89: 2894 | AK89: 3234 | AL89: 3234
A90: > 25 MT | AE90: 1.75 | AF90: 1986 | AG90: 1071 | AH90: 3080 | AI90: 2348 | AJ90: 3544 | AK90: 3186 | AL90: 3186
A91: 26.4-35.2 TT | AE91: 1.75 | AF91: 314 | AG91: 208 | AH91: 972 | AI91: 725 | AJ91: 479 | AK91: 381 | AL91: 381
A92: >35.2 TT | AE92: 2 | AF92: 622 | AG92: 428 | AH92: 968 | AI92: 1070 | AJ92: 1717 | AK92: 1878 | AL92: 1878
A93: Total | AF93: =SUM(AF87:AF92) -> 9123 | AG93: =SUM(AG87:AG92) -> 6857 | AH93: =SUM(AH87:AH92) -> 12553 | AI93: =SUM(AI87:AI92) -> 10007 | AJ93: =SUM(AJ87:AJ92) -> 12081 | AK93: =SUM(AK87:AK92) -> 12380 | AL93: =SUM(AL87:AL92) -> 12380
A94: %
A95: 7.5-12 MT | AF95: =AF87/AF$93 -> 0.14940261 | AG95: =AG87/AG$93 -> 0.13796121 | AH95: =AH87/AH$93 -> 0.12180355 | AI95: =AI87/AI$93 -> 0.10612571 | AJ95: =AJ87/AJ$93 -> 0.099743399 | AK95: =AK87/AK$93 -> 0.094588045 | AL95: =AL87/AL$93 -> 0.094588045
A96: 12-16.2 MT | AF96: =AF88/AF$93 -> 0.25112353 | AG96: =AG88/AG$93 -> 0.33644451 | AH96: =AH88/AH$93 -> 0.26248705 | AI96: =AI88/AI$93 -> 0.22844009 | AJ96: =AJ88/AJ$93 -> 0.18558066 | AK96: =AK88/AK$93 -> 0.20436187 | AL96: =AL88/AL$93 -> 0.20436187
A97: 16.2-25 MT | AF97: =AF89/AF$93 -> 0.27918448 | AG97: =AG89/AG$93 -> 0.2766516 | AH97: =AH89/AH$93 -> 0.21580499 | AI97: =AI89/AI$93 -> 0.251424 | AJ97: =AJ89/AJ$93 -> 0.23954971 | AK97: =AK89/AK$93 -> 0.26122779 | AL97: =AL89/AL$93 -> 0.26122779
A98: > 25 MT | AF98: =AF90/AF$93 -> 0.21769155 | AG98: =AG90/AG$93 -> 0.15619075 | AH98: =AH90/AH$93 -> 0.24535967 | AI98: =AI90/AI$93 -> 0.23463575 | AJ98: =AJ90/AJ$93 -> 0.2933532 | AK98: =AK90/AK$93 -> 0.25735057 | AL98: =AL90/AL$93 -> 0.25735057
A99: 26.4-35.2 TT | AF99: =AF91/AF$93 -> 0.034418503 | AG99: =AG91/AG$93 -> 0.030333965 | AH99: =AH91/AH$93 -> 0.07743169 | AI99: =AI91/AI$93 -> 0.072449286 | AJ99: =AJ91/AJ$93 -> 0.039649036 | AK99: =AK91/AK$93 -> 0.030775444 | AL99: =AL91/AL$93 -> 0.030775444
A100: >35.2 TT | AF100: =AF92/AF$93 -> 0.068179327 | AG100: =AG92/AG$93 -> 0.062417967 | AH100: =AH92/AH$93 -> 0.077113041 | AI100: =AI92/AI$93 -> 0.10692515 | AJ100: =AJ92/AJ$93 -> 0.142124 | AK100: =AK92/AK$93 -> 0.15169628 | AL100: =AL92/AL$93 -> 0.15169628
AF101: =SUMPRODUCT(AF87:AF92,AE87:AE92)/AF93 -> 1.459635 | AG101: =SUMPRODUCT(AG87:AG92,AE87:AE92)/AG93 -> 1.4247484 | AH101: =SUMPRODUCT(AH87:AH92,AE87:AE92)/AH93 -> 1.4927308 | AI101: =SUMPRODUCT(AI87:AI92,AE87:AE92)/AI93 -> 1.520061 | AJ101: =SUMPRODUCT(AJ87:AJ92,AE87:AE92)/AJ93 -> 1.5580457 | AK101: =SUMPRODUCT(AK87:AK92,AE87:AE92)/AK93 -> 1.5494952 | AL101: =SUMPRODUCT(AL87:AL92,AG87:AG92)/AL93 -> 1403.442
A105: Pax (domestic)
A106: 7.5-12 | AF106: 1131 | AG106: 540 | AH106: 784 | AI106: 946 | AJ106: 725 | AK106: 473 | AL106: 473
A107: 12-16.2 | AF107: 3706 | AG107: 1582 | AH107: 2584 | AI107: 1906 | AJ107: 2625 | AK107: 2022 | AL107: 2022
A108: % | AF108: =AF107+AF106 -> 4837 | AG108: =AG107+AG106 -> 2122 | AH108: =AH107+AH106 -> 3368 | AI108: =AI107+AI106 -> 2852 | AJ108: =AJ107+AJ106 -> 3350 | AK108: =AK107+AK106 -> 2495 | AL108: =AL107+AL106 -> 2495
A109: 7.5-12 | AF109: =AF106/AF108 -> 0.23382262 | AG109: =AG106/AG108 -> 0.25447691 | AH109: =AH106/AH108 -> 0.2327791 | AI109: =AI106/AI108 -> 0.33169705 | AJ109: =AJ106/AJ108 -> 0.21641791 | AK109: =AK106/AK108 -> 0.18957916 | AL109: =AL106/AL108 -> 0.18957916
A110: 12-16.2 | AF110: =AF107/AF108 -> 0.76617738 | AG110: =AG107/AG108 -> 0.74552309 | AH110: =AH107/AH108 -> 0.7672209 | AI110: =AI107/AI108 -> 0.66830295 | AJ110: =AJ107/AJ108 -> 0.78358209 | AK110: =AK107/AK108 -> 0.81042084 | AL110: =AL107/AL108 -> 0.81042084
A114: Industry vols in domestic goods
A115: 7.5-12 MT | AF115: 10260 | AG115: 8703 | AH115: 9614 | AI115: 8177 | AJ115: 9075 | AK115: 9704 | AL115: 9704
A116: 12-16.2 MT | AF116: 7647 | AG116: 7653 | AH116: 9494 | AI116: 7270 | AJ116: 7371 | AK116: 8342 | AL116: 8342
A117: 16.2-25 MT | AF117: 10491 | AG117: 9753 | AH117: 11884 | AI117: 11356 | AJ117: 11428 | AK117: 13352 | AL117: 13352
...

Sheet mcTempChartDataSheet
I8: E6XYB6412478

Sheet DCF
B1: From Company Annual Report | F1: From Citi model | I1: Estimates | S1: Terminal
B2: FY14 | C2: FY15 | D2: FY16 | E2: FY17 | F2: FY18 | G2: FY19 | H2: FY20 | I2: FY21 | J2: FY22 | K2: FY23 | L2: FY24 | M2: FY25 | N2: FY26 | O2: FY27 | P2: FY28 | Q2: FY29 | R2: FY30
A3: Sales | B3: =+'Main Model'!W19 -> 99434.267 | C3: =+'Main Model'!X19 -> 135621.84 | D3: =+'Main Model'!Y19 -> 189373.04 | E3: =+'Main Model'!Z19 -> 200186.57 | F3: =+'Main Model'!AA19 -> 262479.08 | G3: =+'Main Model'!AB19 -> 290549.5 | H3: =+'Main Model'!AC19 -> 174674.7
A4: EBITDA | B4: =+'Main Model'!W47 -> 1665.623 | C4: =+'Main Model'!X47 -> 10266.337 | D4: =+'Main Model'!Y47 -> 22546.311 | E4: =+'Main Model'!Z47 -> 22025.372 | F4: =+'Main Model'!AA47 -> 27389.807 | G4: =+'Main Model'!AB47 -> 31357.4 | H4: =+'Main Model'!AC47 -> 11736.5
A5: Margin | B5: =+B4/B3 -> 0.016750996 | C5: =+C4/C3 -> 0.07569826 | D5: =+D4/D3 -> 0.11905766 | E5: =+E4/E3 -> 0.11002423 | F5: =+F4/F3 -> 0.10435044 | G5: =+G4/G3 -> 0.10792447 | H5: =+H4/H3 -> 0.067190612 | I5: 0.12 | J5: 0.12 | K5: 0.12 | L5: 0.12 | M5: 0.12 | N5: 0.12 | O5: 0.12 | P5: 0.12 | Q5: 0.12 | R5: 0.12
A6: Less tax | B6: -297.407 | C6: -501.89 | D6: -4408.76 | E6: -3476.196 | F6: =-'Main Model'!AA56 -> -6681.258 | G6: =-'Main Model'!AB56 -> -5136 | H6: =-'Main Model'!AC56 -> -1224
A7: (inc)/dec in working capital | B7: =5861.708+467.494-2161.247 -> 4167.955 | C7: =18167.409-11219.837 -> 6947.572 | D7: =21238.534-23033.142 -> -1794.608 | E7: =25023.908-23120.801 -> 1903.107 | F7: =+'Main Model'!AA1018 -> 26149.909 | G7: =+'Main Model'!AB1018 -> -22078.294 | H7: =+'Main Model'!AC1018 -> -6718.4
A8: CFO | B8: =+B7+B6+B4 -> 5536.171 | C8: =+C7+C6+C4 -> 16712.019 | D8: =+D7+D6+D4 -> 16342.943 | E8: =+E7+E6+E4 -> 20452.283 | F8: =+F7+F6+F4 -> 46858.458 | G8: =+G7+G6+G4 -> 4143.106 | H8: =+H7+H6+H4 -> 3794.1 | I8: =+I7+I6+I4 -> 0 | ... R8: =+R7+R6+R4 -> 0
A9: Capex (purchase of tangible and intangible assets, netted) | B9: =-2197.54+126.965 -> -2070.575 | C9: =-2112.39+53.639 -> -2058.751 | D9: =-1702.233+43.068 -> -1659.165 | E9: =-3782.729+122.917 -> -3659.812 | F9: =+'Main Model'!AA1021 -> -7534.029 | G9: =+'Main Model'!AB1021 -> -15176.776 | H9: =+'Main Model'!AC1021 -> -17953.8
A10: FCF | B10: =+B9+B8 -> 3465.596 | C10: =+C9+C8 -> 14653.268 | D10: =+D9+D8 -> 14683.778 | E10: =+E9+E8 -> 16792.471 | F10: =+F9+F8 -> 39324.429 | G10: =+G9+G8 -> -11033.67 | H10: =+H9+H8 -> -14159.7 | I10: =+I9+I8 -> 0 | ... R10: =+R9+R8 -> 0
A11: t= | B11: 0 | C11: 0 | D11: 0 | E11: =+D11+1 -> 1 | F11: =+E11+1 -> 2 | G11: =+F11+1 -> 3 | H11: =+G11+1 -> 4 | I11: =+H11+1 -> 5 | J11: =+I11+1 -> 6 | K11: =+J11+1 -> 7 | L11: =+K11+1 -> 8 | ... N11: =+M11+1 -> 10 | O11: 10
A12: Discount rate | B12: =1/(1+$B$15)^B11 -> 1 | C12: =1/(1+$B$15)^C11 -> 1 | D12: =1/(1+$B$15)^D11 -> 1 | E12: =1/(1+$B$15)^E11 -> 1 | F12: =1/(1+$B$15)^F11 -> 1 | G12: =1/(1+$B$15)^G11 -> 1 | H12: =1/(1+$B$15)^H11 -> 1 | I12: =1/(1+$B$15)^I11 -> 1 | ... N12: =1/(1+$B$15)^N11 -> 1 | O12: =N12 -> 1
A13: PV of CF | B13: =+B12*B10 -> 3465.596 | C13: =+C12*C10 -> 14653.268 | D13: =+D12*D10 -> 14683.778 | E13: =+E12*E10 -> 16792.471 | F13: =+F12*F10 -> 39324.429 | G13: =+G12*G10 -> -11033.67 | H13: =+H12*H10 -> -14159.7 | I13: =+I12*I10 -> 0 | ... O13: =+O12*O10 -> 0
A15: WACC | B15: =+B36 -> 0
A16: Terminal growth rate
A17: Terminal multiple | B17: =1/(B36-B16) -> #DIV/0!
A18: NPV of terminal value | B18: =+O13 -> 0
A19: NPV of cash flows | B19: =+SUM(E13:N13) -> 30923.53
A20: Enterprise value | B20: =+B19+B18 -> 30923.53
A21: Less: Net debt/(net cash)
A22: Equity value | B22: =+B20-B21 -> 30923.53
A23: No of shares
A24: Value per share (Rs) | B24: =+B22/B23 -> #DIV/0!
A26: Weighted Average Cost of Capital (%)
A27: Rf
A28: MRP
A29: Beta (Equity)
A30: Cost of Equity | B30: =+B29*B28+B27 -> 0
A31: Cost of Debt
A32: Tax Rate
A33: After-Tax Cost of Debt | B33: =+(1-B32)*B31 -> 0
A34: Debt/EV | B34: 0
A35: Equity/EV | B35: =100%-B34 -> 1
A36: WACC | B36: =+B30 -> 0
A38: Others
A39: TP | B39: =+B38+B24 -> #DIV/0!

Sheet Comments
A1: Ashok Leyland Ltd
A3: Why the poor ROE and ROCE - ALL does not cover its cost of capital and is a shareholder value destroyer ?
A4: Is this because of lack of economies fo scale due to multiple locations and small capacities or has capacity been set up at very high costs !
A5: What steps to change this ? any internal targets ?
A7: 66% of reserves from share premium - even the book value is built up on shareholders inflows
A10: Debenture repayment schedule
G11: 2005 | H11: 2006 | I11: 2007 | J11: 2008 | K11: 2009 | L11: 2010 | M11: 2011
E12: 29 | G12: 50 | H12: 50
E13: 1 | G13: 83.3333 | H13: 83.3333 | I13: 83.3333
E14: 2 | G14: 33.33333 | H14: 33.3333 | I14: 33.3333
E15: 3 | G15: 16.66667 | H15: 16.666667 | I15: 16.66667
E16: 4 | I16: 133.33333 | J16: 133.3333 | K16: 133.3333
E17: 5 | G17: 6.66667 | H17: 6.6667 | I17: 6.6667
E18: 6 | I18: 16.66667 | J18: 16.66667 | K18: 16.66667
E19: 7 | G19: 166.66667 | H19: 83.3333
E20: 9A | J20: 50
E21: 10 | I21: 250
E22: 11 | K22: 166.66667 | L22: 166.6667 | M22: 166.6667
G23: =SUM(G12:G22) -> 356.66664 | H23: =SUM(H12:H22) -> 273.33327 | I23: =SUM(I12:I22) -> 539.99997 | J23: =SUM(J12:J22) -> 199.99997 | K23: =SUM(K12:K22) -> 316.66664 | L23: =SUM(L12:L22) -> 166.6667 | M23: =SUM(M12:M22) -> 166.6667
A26: Sale of stake in Indus Ind
A27: Book value / SH | C27: =(512.38+165.02)/(9.362442+29.070185) -> 17.625649
A28: Total shares (mn) | C28: 44.382627
A29: Total shares o/s (I Ind) mn | C29: =290.702 -> 290.702
A30: Max stake ALL can hold | C30: =0.1*C29 -> 29.0702
A31: shares to be sold | C31: =C28-C30 -> 15.312427
A32: share actually sold | C32: 8.25
A33: avg sale price / sh | C33: =414/8.25 -> 50.181818
A35: profit / sh | C35: =C33-C27 -> 32.556169
A36: gain on sale | C36: =C35*C32 -> 268.58839
A37: further shares to be sold | C37: =C31-C32 -> 7.062427
A39: book vale of residual stake (mn) | C39: =C27*C30 -> 512.38115
A42: average realisations up by almost 6.6% because of more MAVs sold
A44: total FCCNs of USD 1000 each | B44: =100000000/1000 -> 100000 | F44: NEW: | G44: Conversion at Rs31 / sh
A45: each FCCN is | B45: 131.6418 | C45: shares of Rs10 each | G45: =100*44.1/31 -> 142.25806 | H45: m shares additional
A46: which is | B46: 1316.418 | C46: shares of Rs1 each | G46: =#REF!+Comments!G45 -> #REF!
A47: into 100,000 notes | B47: =B46*B44 -> 131641800 | C47: total shares | G47: =G45*30 -> 4267.7419 | H47: share premium
A48: or | B48: =B47/1000000 -> 131.6418 | C48: mn shares
H51: MKT SHARE
A52: FY06 sales expectations | D52: FY05 | E52: FY06 | F52: YOY GR (%) | G52: YTD | H52: fy05 | I52: fY06ytd
A53: Total | D53: 54740 | E53: 70000 | F53: =E53/D53*100-100 -> 27.877238 | G53: 13202 | H53: 0.256 | I53: =F60/41386 -> 0.31899676
A54: domestic | D54: =#REF! -> #REF! | E54: 65500 | F54: =E54/D54*100-100 -> #REF!
A55: exports | D55: =#REF! -> #REF! | E55: 4500 | F55: =E55/D55*100-100 -> #REF!
A57: Total mkt | B57: FY05 | C57: FY06 | F57: apr - June 05 | G57: growth YTD | H57: rest of year | I57: growth rest of year
A58: MHCV | B58: 212110 | C58: 230000 | D58: =C58/B58*100-100 -> 8.434303 | F58: 41386 | G58: =F58/43425*100-100 -> -4.6954519 | H58: =C58-F58 -> 188614 | I58: =H58/168685 -> 1.1181433 | L58: =B58*1.1 -> 233321
A59: TAMO | B59: 135349 | C59: 143469.94 | D59: =C59/B59*100-100 -> 6 | L59: 70000
A60: ALL | B60: 54321 | C60: 64768 | D60: =C60/B60*100-100 -> 19.231973 | F60: 13202 | G60: 19.4 | H60: =C60-F60 -> 51566 | I60: =H60/43321 -> 1.1903234 | L60: =L59/L58*100 -> 30.001586
A61: Eicher | B61: 15678
A62: Tatra | B62: 171
A63: Volvo | B63: 946
A64: swaraj | B64: 5580
A65: Hind Motors | B65: 12
A67: Mkt sh
A68: TAMO | B68: =B59/B$58*100 -> 63.810759 | C68: =C59/C$58*100 -> 62.378235
A69: ALL | B69: =B60/B$58*100 -> 25.609825 | C69: =C60/C$58*100 -> 28.16
A70: Eicher | B70: =B61/B$58*100 -> 7.3914478 | C70: =C61/C$58*100 -> 0
A71: Tatra | B71: =B62/B$58*100 -> 0.080618547 | C71: =C62/C$58*100 -> 0
A72: Volvo | B72: =B63/B$58*100 -> 0.445995 | C72: =C63/C$58*100 -> 0
A73: swaraj | B73: =B64/B$58*100 -> 2.6307105 | C73: =C64/C$58*100 -> 0
A74: Hind Motors | B74: =B65/B$58*100 -> 0.0056574419 | C74: =C65/C$58*100 -> 0
B78: From the ALL FY06 presentation
B79: Segment | D79: 2003-04 | G79: 2004-05 | J79: 2005-06
C80: TIV | D80: AL | E80: MS % | F80: TIV | G80: AL | H80: MS % | I80: TIV | J80: AL | K80: MS %
B81: Haulage | C81: 45790 | D81: 7039 | E81: =+D81/C81*100 -> 15.372352 | F81: 48241 | G81: 6096 | H81: =+G81/F81*100 -> 12.636554 | I81: 37659 | J81: 4949 | K81: =+J81/I81*100 -> 13.141613
B82: MAV | C82: 46313 | D82: 17500 | E82: =+D82/C82*100 -> 37.786367 | F82: 57596 | G82: 16641 | H82: =+G82/F82*100 -> 28.892631 | I82: 60522 | J82: 18828 | K82: =+J82/I82*100 -> 31.109349
B83: Tractor | C83: 7729 | D83: 3853 | E83: =+D83/C83*100 -> 49.85121 | F83: 11842 | G83: 5617 | H83: =+G83/F83*100 -> 47.432866 | I83: 12162 | J83: 5643 | K83: =+J83/I83*100 -> 46.398619
B84: Tipper | C84: 16742 | D84: 4555 | E84: =+D84/C84*100 -> 27.207024 | F84: 24717 | G84: 7590 | H84: =+G84/F84*100 -> 30.70761 | I84: 31762 | J84: 10933 | K84: =+J84/I84*100 -> 34.421636
B85: Goods | C85: =SUM(C81:C84) -> 116574 | D85: =SUM(D81:D84) -> 32947 | E85: =+D85/C85*100 -> 28.262734 | F85: =SUM(F81:F84) -> 142396 | G85: =SUM(G81:G84) -> 35944 | H85: =+G85/F85*100 -> 25.242282 | I85: =SUM(I81:I84) -> 142105 | J85: =SUM(J81:J84) -> 40353 | K85: =+J85/I85*100 -> 28.396608
B86: Pass Pvt | C86: 13825 | D86: 5769 | E86: =+D86/C86*100 -> 41.728752 | F86: 13052 | G86: 4956 | H86: =+G86/F86*100 -> 37.971192 | I86: 12534 | J86: 5582 | K86: =+J86/I86*100 -> 44.534865
B87: Pass STU | C87: 9796 | D87: 5258 | E87: =+D87/C87*100 -> 53.674969 | F87: 10640 | G87: 5445 | H87: =+G87/F87*100 -> 51.174812 | I87: 12526 | J87: 6901 | K87: =+J87/I87*100 -> 55.093406
B88: Pass Total | C88: =SUM(C86:C87) -> 23621 | D88: =SUM(D86:D87) -> 11027 | E88: =+D88/C88*100 -> 46.683036 | F88: =SUM(F86:F87) -> 23692 | G88: =SUM(G86:G87) -> 10401 | H88: =+G88/F88*100 -> 43.900895 | I88: =SUM(I86:I87) -> 25060 | J88: =SUM(J86:J87) -> 12483 | K88: =+J88/I88*100 -> 49.81245
B89: MDV | C89: =+C85+C88 -> 140195 | D89: =+D85+D88 -> 43974 | E89: =+D89/C89*100 -> 31.366311 | F89: =+F85+F88 -> 166088 | G89: =+G85+G88 -> 46345 | H89: =+G89/F89*100 -> 27.903882 | I89: =+I85+I88 -> 167165 | J89: =+J85+J88 -> 52836 | K89: =+J89/I89*100 -> 31.607095
B92: From the ALL FY06 presentation
B93: New product launches
B94: •ICV - 1512 with H Series engine
B95: •Semi Forward Control in Tipper and Haulage segments
B96: •Tractor range - 6x2 / 6x4 with 210-350 hp engine and GTW up to 49T
B97: •Tipper 8x4 with 350 hp engine
B98: •InterCentury Luxura bus
B99: •Branded Buses
B100: •Defence sector - HMV and other logistics vehicles
B102: From the ALL FY06 presentation
B103: Efficiency improvements
B104: •Material cost reduction
... B110: tgt 300 bps improvement in 2 yrs
D113: 38808 | E113: 38838 | F113: 38869 | G113: 38899 | H113: YTD
B114: MDV Passenger | C114: Production | D114: 713 | E114: 708 | F114: 819 | G114: 1182 | H114: 3422
C115: Sales Domestic | D115: 398 | E115: 550 | F115: 425 | G115: 745 | H115: 2118 | J115: =SUM(D115:F115)+SUM(D116:F116) -> 2181
C116: Sales Exports | D116: 187 | E116: 214 | F116: 407 | G116: 162 | H116: 970
B117: MDV Goods | C117: Production | D117: 4708 | E117: 5120 | F117: 5804 | G117: 5612 | H117: 21244 | I117: YTD growth | L117: computations for fy07 - mdv goods domestic
C118: Sales Domestic | D118: 4335 | E118: 4732 | F118: 5261 | G118: 4208 | H118: 18536 | I118: =H118/12508 -> 1.4819316 | J118: =SUM(D118:F118)+SUM(D119:F119) -> 14762 | L118: =42613-12508 -> 30105 | M118: rest of fy06 (aug - mar)
C119: Sales Exports | D119: 102 | E119: 95 | F119: 237 | G119: 99 | H119: 533
B120: LCV | C120: Production | D120: 95 | E120: 58 | F120: 49 | G120: 10 | H120: 212 | L120: =47727-H118 -> 29191 | M120: rest of fy07
C121: Sales Domestic | D121: 17 | E121: 40 | F121: 38 | G121: 17 | H121: 112 | J121: =SUM(D121:F121)+SUM(D122:F122) -> 97 | L121: =L120/L118 -> 0.96963959 | M121: rest of the year it is -3% growth in HCVs - on my assumption
C122: Sales Exports | D122: 0 | E122: 0 | F122: 2 | G122: 0 | H122: 2
B123: Total | C123: Production | D123: 5516 | E123: 5886 | F123: 6672 | G123: 6804 | H123: 24878 | L123: =L120+5299+3000 -> 37490 | M123: 5299 is the addition that will take the overall vehicle sales to 75k
C124: Sales Domestic | D124: 4750 | E124: 5322 | F124: 5724 | G124: 4970 | H124: 20766 | J124: =SUM(D124:F124)+SUM(D125:F125) -> 17040 | L124: =L123/L118 -> 1.2453081 | M124: on that new basis, rest of the fiscal growth is
C125: Sales Exports | D125: 289 | E125: 309 | F125: 646 | G125: 261 | H125: 1505
L126: =L123+H118 -> 56026 | M126: total estimated for fy07
L128: =L123/8 -> 4686.25 | M128: mthly average for rest of fiscal 2007
B129: to do for ALL / queries
...
