Workbook

Sheet README
A1: INDIA ELECTRIC TWO-WHEELER — MODEL LANDSCAPE DATABASE
A2: Built for Bernstein India Autos. All data as of 25 August 2026 unless a cell states otherwise.
A5: PURPOSE | B5: A continuously usable model-level database of every meaningful electric two-wheeler on sale in India, plus the credible pipeline. Scooters and motorcycles are held on separate sheets because they are structurally different markets.
A7: SHEET GUIDE
A8: Scooters_Current | B8: Variant-level master for every e-scooter on sale. 58 variants across 26 brands. Filter-ready.
A9: Motorcycles_Current | B9: Variant-level master for every e-motorcycle on sale. 29 variants across 14 brands.
A10: Pipeline | B10: 24 upcoming products with an explicit CONFIRMATION LEVEL on each. Read this column before modelling anything.
A11: Price_Band_Map | B11: Live COUNTIF map of how many products sit in each price band, scooters vs motorcycles. Shows crowded bands and white space.
A12: Company_Profiles | B12: Ownership, funding, financials, capacity, network, cell strategy and the identified moat for 18 players.
A13: Volumes_MarketShare | B13: Vahan registrations FY22-FY26 plus Jul-26, with live share and YoY formulas.
A14: Industry_Penetration | B14: Total e-2W volumes, total 2W volumes and EV penetration by year, with live formulas.
A15: Supply_Chain_Barriers | B15: Component-by-component assessment of what is outsourceable and what is not. This is the analytical core of the entry-barrier thesis.
A16: Regulatory_Subsidy | B16: PM E-DRIVE, GST 2.0, FAME-II clawback, AIS-156, PLI, rare-earth magnet scheme, state policies.
A17: BOM_Economics | B17: Cell and pack cost benchmarks with live INR conversion driven by one editable FX cell.
A18: Sources | B18: Master source list with as-of dates.
A20: CONFIRMATION / CONFIDENCE CODES
A21: HIGH | B21: Sourced from an OEM website, official press release, regulatory filing or Vahan. Use directly.
A22: MEDIUM | B22: Credible auto media or a specification aggregator, cross-checked where possible. Verify before publishing a number.
A23: LOW | B23: Single-source, aggregator-only, or a category where disclosure is poor. Treat as indicative only.
A25: PIPELINE CONFIRMATION LEVELS
A26: COMPANY-CONFIRMED | B26: Officially announced by the company with a product commitment.
A27: COMPANY-GUIDED WINDOW | B27: Company has stated a quarter or window but not a date.
A28: COMPANY-SIGNALLED | B28: Management commentary or investor material implies it; no formal launch commitment.
A29: MEDIA-REPORTED | B29: Credible media or a patent filing. Not a company commitment.
A30: SPECULATIVE | B30: Industry chatter or inference. Model zero volume.
A32: CRITICAL DATA CAVEATS — READ BEFORE USING
A33: 1. Prices are in flux | B33: The PM E-DRIVE e-2W demand incentive (Rs2,500/kWh, cap Rs5,000) LAPSED on 31 July 2026. Ex-showroom prices observed in August 2026 are not comparable to launch prices quoted before that date. Both are captured in separate columns.
A34: 2. Vahan is retail, not wholesale | B34: All volume data is Vahan retail registration. It differs from OEM dispatch. An MHI inquiry specifically probed discrepancies between Ola's reported sales and Vahan. Anchor to Vahan.
A35: 3. Low-speed EVs are invisible | B35: Vehicles under 250W and 25 km/h need no registration and do NOT appear in Vahan. All industry volume figures therefore understate the true market.
A36: 4. Range claims are certification figures | B36: IDC and ARAI numbers are test-cycle results. Real-world range is typically 60-75 per cent of claimed. A separate real-world estimate column is provided and is clearly marked as an estimate.
A37: 5. Private-company financials | B37: River, Matter, Raptee, Simple and Ultraviolette figures are media-reported and largely unaudited.
A38: 6. Aggregator price conflicts | B38: Where sources disagree materially (Suzuki e-Access, TVS iQube variant naming, Bajaj Chetak top speeds), the conflict is flagged in the Analyst notes column rather than silently resolved.
A40: HOW TO KEEP THIS CURRENT
A41: Monthly | B41: Update Volumes_MarketShare with the latest Vahan month. Share and YoY columns recalculate automatically.
A42: On launch | B42: Add a new row to the relevant Current sheet and delete the corresponding Pipeline row. Copy the calculated columns down.
A43: Quarterly | B43: Refresh Company_Profiles financials and BOM_Economics FX (cell C13 on that sheet, shown in blue).
A45: COLOUR CONVENTION | B45: Blue text = an editable input assumption. Yellow fill = a cell you should review and update. Everything else is either sourced data or a formula.

Sheet Scooters_Current
A1: ELECTRIC SCOOTERS — INDIA MODEL MASTER (VARIANT LEVEL)
A2: 58 variants, 26 brands. Prices ex-showroom Delhi. PM E-DRIVE e-2W incentive lapsed 31-Jul-2026 — compare 'price at launch' and 'price latest' with care. Data as of 25-Aug-2026.
A3: ID | B3: OEM / parent | C3: Brand | D3: Model | E3: Variant | F3: Status | G3: Launch (M-Y) | H3: Positioning tier | I3: Price at launch (Rs, ex-shwr) | J3: Price latest (Rs, ex-shwr Delhi) | K3: Price as-of | L3: BaaS / subscription price | M3: Battery (kWh) | N3: Battery type | O3: Chemistry | P3: Cell sourcing | Q3: Motor type / drive | R3: Peak power (kW) | S3: Torque (Nm) | T3: Top speed (km/h) | U3: 0-40 km/h (s) | V3: Claimed range (km) | W3: Range cycle | X3: Real-world range est. (km) | Y3: Charger (W) | Z3: Charge time 0-80% | AA3: Fast charge / network | AB3: Kerb weight (kg) | AC3: Length (mm) | AD3: Width (mm) | AE3: Height (mm) | AF3: Wheelbase (mm) | AG3: Ground clearance (mm) | AH3: Seat height (mm) | AI3: Boot space (litres) | AJ3: Wheels / tyres | AK3: Brakes (F/R) | AL3: ABS / CBS | AM3: Display | AN3: Connectivity | AO3: Ride modes | AP3: Reverse | AQ3: OTA updates | AR3: Other key features | AS3: IP rating | AT3: Vehicle warranty | AU3: Battery warranty | AV3: Platform | AW3: Manufacturing / localisation | AX3: Key differentiator | AY3: Rs per kWh (calc) | AZ3: km per kWh (calc) | BA3: Price band (calc) | BB3: Data confidence | BC3: Source 1 | BD3: Source 2 | BE3: Analyst notes
A4: S001 | B4: Ather Energy (listed: ATHERENERG) | C4: Ather | D4: Rizta | E4: S 2.9 kWh | F4: On sale | G4: Apr-2024 | H4: Mass / family | I4: 109999 | J4: 114999 | K4: Aug-2026 | L4: n/a | M4: 2.9 | N4: Fixed | O4: Li-ion NMC | P4: Imported cells (LG/Samsung SDI class) — pack assembled in-house | Q4: PMSM, belt drive | R4: 4.3 | S4: 22 | T4: 80 | U4: n/a | V4: 123 | W4: IDC | X4: 85 | Y4: 350 | Z4: ~4h30m (Duo charger) | AA4: Ather Grid fast charging (6,100+ points) | AB4: 119 | AC4: 1850 | AD4: 750 | AE4: 1140 | AF4: 1285 | AG4: 150 | AH4: 780 | AI4: 34 | AJ4: 12-inch alloy, tubeless | AK4: Disc front / Drum rear | AL4: CBS | AM4: 7-inch LCD DeepView | AN4: 4G LTE + Bluetooth; AtherStack 7.0 | AO4: 2 | AP4: Yes | AQ4: Yes | AR4: Auto-hold, reverse, Alexa skill, crash/fall alert, pillion backrest optional | AS4: IP67 (pack) / IP65 (dash) | AT4: 3 yr / 30,000 km | AU4: 3 yr std; 5 yr/60,000 km with Pro Pack (8 yr extended optional) | AV4: Rizta / 450 shared architecture | AW4: PLI-certified; high stated localisation | AX4: Family-scooter pivot from performance brand; largest boot + AtherStack software | AY4: =IF(AND(ISNUMBER($J4),ISNUMBER($M4)),$J4/$M4,"n/a") -> 39654.828 | AZ4: =IF(AND(ISNUMBER($V4),ISNUMBER($M4)),$V4/$M4,"n/a") -> 42.413793 | BA4: =IF(NOT(ISNUMBER($J4)),"n/a",IF($J4<70000,"1. <Rs70k",IF($J4<100000,"2. Rs70k-1L",IF($J4<150000,"3. Rs1-1.5L",IF($J4<200000,"4. Rs1.5-2L",IF($J4<300000,"5. Rs2-3L","6. >Rs3L")))))) -> 3. Rs1-1.5L | BB4: HIGH | BC4: atherenergy.com/rizta (Aug-2026) | BD4: 91wheels / ZigWheels specs (Aug-2026) | BE4: ~70% of Ather volume. 3 lakh+ Rizta cumulative units reported by FADA/press Apr-2026.
A5: S002 | B5: Ather Energy | C5: Ather | D5: Rizta | E5: Z 2.9 kWh | F5: On sale | G5: Apr-2024 | H5: Mass / family | I5: n/a | J5: 132000 | K5: Aug-2026 | L5: n/a | M5: 2.9 | N5: Fixed | O5: Li-ion NMC | P5: In-house pack | Q5: PMSM, belt drive | R5: 4.3 | S5: 22 | T5: 80 | U5: n/a | V5: 126 | W5: IDC | X5: 88 | Y5: 350 | Z5: ~4h30m | AA5: Ather Grid | AB5: 125 | AC5: 1850 | AD5: 750 | AE5: 1140 | AF5: 1285 | AG5: 150 | AH5: 780 | AI5: 34 | AJ5: 12-inch alloy, tubeless | AK5: Disc front / Drum rear | AL5: CBS | AM5: 7-inch TFT DeepView touchscreen | AN5: 4G LTE, navigation, voice alerts | AO5: 2 | AP5: Yes | AQ5: Yes | AR5: Magic Twist regen, pillion backrest, Alexa | AS5: IP67 / IP65 | AT5: 3 yr / 30,000 km | AU5: 3 yr std; 5 yr/60,000 km w/ Pro Pack | AV5: Rizta | AW5: PLI-certified | AX5: Touchscreen + connected feature ladder over S | AY5: =IF(AND(ISNUMBER($J5),ISNUMBER($M5)),$J5/$M5,"n/a") -> 45517.241 | AZ5: =IF(AND(ISNUMBER($V5),ISNUMBER($M5)),$V5/$M5,"n/a") -> 43.448276 | BA5: =IF(NOT(ISNUMBER($J5)),"n/a",IF($J5<70000,"1. <Rs70k",IF($J5<100000,"2. Rs70k-1L",IF($J5<150000,"3. Rs1-1.5L",IF($J5<200000,"4. Rs1.5-2L",IF($J5<300000,"5. Rs2-3L","6. >Rs3L")))))) -> 3. Rs1-1.5L | BB5: MEDIUM | BC5: Autocar India variant page (Apr-2026) | BD5: Ather spec sheet | BE5: Autocar lists on-road Delhi Rs1.48L for Z 2.9; ex-showroom estimated.
A6: S003 | B6: Ather Energy | C6: Ather | D6: Rizta | E6: S 3.7 kWh | F6: On sale | G6: 2025 | H6: Mass / family | I6: n/a | J6: 138000 | K6: Aug-2026 | L6: n/a | M6: 3.7 | N6: Fixed | O6: Li-ion NMC | P6: In-house pack | Q6: PMSM, belt drive | R6: 4.3 | S6: 22 | T6: 80 | U6: n/a | V6: 159 | W6: IDC | X6: 110 | Y6: 350 | Z6: ~5h15m | AA6: Ather Grid | AB6: 125 | AC6: 1850 | AD6: 750 | AE6: 1140 | AF6: 1285 | AG6: 150 | AH6: 780 | AI6: 34 | AJ6: 12-inch alloy | AK6: Disc front / Drum rear | AL6: CBS | AM6: 7-inch LCD DeepView | AN6: 4G LTE + Bluetooth | AO6: 2 | AP6: Yes | AQ6: Yes | AR6: Auto-hold, reverse | AS6: IP67 / IP65 | AT6: 3 yr / 30,000 km | AU6: 3 yr std; 5 yr/60,000 km w/ Pro Pack | AV6: Rizta | AW6: PLI-certified | AX6: Long-range family variant | AY6: =IF(AND(ISNUMBER($J6),ISNUMBER($M6)),$J6/$M6,"n/a") -> 37297.297 | AZ6: =IF(AND(ISNUMBER($V6),ISNUMBER($M6)),$V6/$M6,"n/a") -> 42.972973 | BA6: =IF(NOT(ISNUMBER($J6)),"n/a",IF($J6<70000,"1. <Rs70k",IF($J6<100000,"2. Rs70k-1L",IF($J6<150000,"3. Rs1-1.5L",IF($J6<200000,"4. Rs1.5-2L",IF($J6<300000,"5. Rs2-3L","6. >Rs3L")))))) -> 3. Rs1-1.5L | BB6: MEDIUM | BC6: Autocar India (Apr-2026) | BD6: ZigWheels (Aug-2026) | BE6: On-road Delhi Rs1.52L per Autocar.
A7: S004 | B7: Ather Energy | C7: Ather | D7: Rizta | E7: Z 3.7 kWh | F7: On sale | G7: 2025 | H7: Mass / family | I7: n/a | J7: 152000 | K7: Aug-2026 | L7: n/a | M7: 3.7 | N7: Fixed | O7: Li-ion NMC | P7: In-house pack | Q7: PMSM, belt drive | R7: 4.3 | S7: 22 | T7: 80 | U7: n/a | V7: 159 | W7: IDC | X7: 112 | Y7: 350 | Z7: ~5h15m | AA7: Ather Grid | AB7: 125 | AC7: 1850 | AD7: 750 | AE7: 1140 | AF7: 1285 | AG7: 150 | AH7: 780 | AI7: 34 | AJ7: 12-inch alloy | AK7: Disc front / Drum rear | AL7: CBS | AM7: 7-inch TFT touchscreen | AN7: 4G LTE, nav, voice | AO7: 2 | AP7: Yes | AQ7: Yes | AR7: Magic Twist, Alexa, crash alert; Stack Pro pack option | AS7: IP67 / IP65 | AT7: 3 yr / 30,000 km | AU7: 3 yr std; 5 yr/60,000 km w/ Pro Pack (8 yr optional) | AV7: Rizta | AW7: PLI-certified | AX7: Top family variant; Stack Pro software bundle | AY7: =IF(AND(ISNUMBER($J7),ISNUMBER($M7)),$J7/$M7,"n/a") -> 41081.081 | AZ7: =IF(AND(ISNUMBER($V7),ISNUMBER($M7)),$V7/$M7,"n/a") -> 42.972973 | BA7: =IF(NOT(ISNUMBER($J7)),"n/a",IF($J7<70000,"1. <Rs70k",IF($J7<100000,"2. Rs70k-1L",IF($J7<150000,"3. Rs1-1.5L",IF($J7<200000,"4. Rs1.5-2L",IF($J7<300000,"5. Rs2-3L","6. >Rs3L")))))) -> 4. Rs1.5-2L | BB7: MEDIUM | BC7: Autocar India (Apr-2026) | BD7: ZigWheels lists Z Stack Pro at Rs1.80-1.84L | BE7: Software subscription (Pro/Stack Pro) is a recurring-revenue lever — watch attach rate.
A8: S005 | B8: Ather Energy | C8: Ather | D8: 450S | E8: 2.9 kWh | F8: On sale | G8: 2023 | H8: Premium performance | I8: n/a | J8: 130311 | K8: Aug-2026 | L8: n/a | M8: 2.9 | N8: Fixed | O8: Li-ion NMC | P8: In-house pack | Q8: PMSM, belt drive | R8: 5.4 | S8: 22 | T8: 90 | U8: 3.3 | V8: 115 | W8: IDC | X8: 80 | Y8: 350 | Z8: ~5h30m | AA8: Ather Grid | AB8: 111 | AC8: n/a | AD8: n/a | AE8: n/a | AF8: 1278 | AG8: 165 | AH8: 780 | AI8: 22 | AJ8: 12-inch alloy | AK8: Disc front / Disc rear | AL8: CBS | AM8: 7-inch LCD | AN8: Bluetooth + 4G | AO8: 3 | AP8: Yes | AQ8: Yes | AR8: Regen, auto-hold | AS8: IP67 | AT8: 3 yr / 30,000 km | AU8: 3 yr std | AV8: 450 platform | AW8: PLI-certified | AX8: Entry into the 450 performance line | AY8: =IF(AND(ISNUMBER($J8),ISNUMBER($M8)),$J8/$M8,"n/a") -> 44934.828 | AZ8: =IF(AND(ISNUMBER($V8),ISNUMBER($M8)),$V8/$M8,"n/a") -> 39.655172 | BA8: =IF(NOT(ISNUMBER($J8)),"n/a",IF($J8<70000,"1. <Rs70k",IF($J8<100000,"2. Rs70k-1L",IF($J8<150000,"3. Rs1-1.5L",IF($J8<200000,"4. Rs1.5-2L",IF($J8<300000,"5. Rs2-3L","6. >Rs3L")))))) -> 3. Rs1-1.5L | BB8: MEDIUM | BC8: BikeWale price list (Aug-2026) | BD8: Ather spec sheet | BE8: n/a
A9: S006 | B9: Ather Energy | C9: Ather | D9: 450X | E9: 2.9 / 3.7 kWh | F9: On sale | G9: 2020 (gen updates to 2025) | H9: Premium performance | I9: n/a | J9: 153902 | K9: Aug-2026 | L9: n/a | M9: 3.7 | N9: Fixed | O9: Li-ion NMC | P9: In-house pack | Q9: PMSM, belt drive | R9: 6.4 | S9: 26 | T9: 90 | U9: 2.9 | V9: 161 | W9: IDC | X9: 115 | Y9: 350 | Z9: ~4h30m (fast charge to 80%) | AA9: Ather Grid DC fast charge | AB9: 111 | AC9: n/a | AD9: n/a | AE9: n/a | AF9: 1278 | AG9: 165 | AH9: 780 | AI9: 22 | AJ9: 12-inch alloy | AK9: Disc / Disc | AL9: CBS | AM9: 7-inch TFT touchscreen | AN9: 4G, nav, AtherStack | AO9: 4 | AP9: Yes | AQ9: Yes | AR9: Warp mode, traction control, Magic Twist, Alexa | AS9: IP67 | AT9: 3 yr / 30,000 km | AU9: 3 yr std; extended options | AV9: 450 platform | AW9: PLI-certified | AX9: Original premium-performance halo product; deepest software stack in segment | AY9: =IF(AND(ISNUMBER($J9),ISNUMBER($M9)),$J9/$M9,"n/a") -> 41595.135 | AZ9: =IF(AND(ISNUMBER($V9),ISNUMBER($M9)),$V9/$M9,"n/a") -> 43.513514 | BA9: =IF(NOT(ISNUMBER($J9)),"n/a",IF($J9<70000,"1. <Rs70k",IF($J9<100000,"2. Rs70k-1L",IF($J9<150000,"3. Rs1-1.5L",IF($J9<200000,"4. Rs1.5-2L",IF($J9<300000,"5. Rs2-3L","6. >Rs3L")))))) -> 4. Rs1.5-2L | BB9: MEDIUM | BC9: BikeWale (Aug-2026) | BD9: ZigWheels (Aug-2026) | BE9: Cited by ZigWheels as one of India's 3 most popular e-scooters.
A10: S007 | B10: Ather Energy | C10: Ather | D10: 450 Apex | E10: 3.7 kWh | F10: On sale | G10: Jan-2024 | H10: Halo performance | I10: 189000 | J10: 195000 | K10: Aug-2026 | L10: n/a | M10: 3.7 | N10: Fixed | O10: Li-ion NMC | P10: In-house pack | Q10: PMSM, belt drive | R10: 7 | S10: 26 | T10: 100 | U10: 2.7 | V10: 157 | W10: IDC | X10: 110 | Y10: 350 | Z10: ~4h30m | AA10: Ather Grid | AB10: 112 | AC10: n/a | AD10: n/a | AE10: n/a | AF10: 1278 | AG10: 165 | AH10: 780 | AI10: 22 | AJ10: 12-inch alloy | AK10: Disc / Disc | AL10: CBS | AM10: 7-inch TFT touchscreen | AN10: 4G, nav, full AtherStack | AO10: 4 | AP10: Yes | AQ10: Yes | AR10: Warp+ mode, magnesium parts, translucent bodywork | AS10: IP67 | AT10: 3 yr / 30,000 km | AU10: 3 yr std | AV10: 450 platform | AW10: PLI-certified | AX10: Halo / brand-building variant; limited volume | AY10: =IF(AND(ISNUMBER($J10),ISNUMBER($M10)),$J10/$M10,"n/a") -> 52702.703 | AZ10: =IF(AND(ISNUMBER($V10),ISNUMBER($M10)),$V10/$M10,"n/a") -> 42.432432 | BA10: =IF(NOT(ISNUMBER($J10)),"n/a",IF($J10<70000,"1. <Rs70k",IF($J10<100000,"2. Rs70k-1L",IF($J10<150000,"3. Rs1-1.5L",IF($J10<200000,"4. Rs1.5-2L",IF($J10<300000,"5. Rs2-3L","6. >Rs3L")))))) -> 4. Rs1.5-2L | BB10: MEDIUM | BC10: Ather press release (Jan-2024) | BD10: Autocar India | BE10: Low-volume halo; matters for brand pricing power, not for volume forecasting.
A11: S008 | B11: TVS Motor Company (listed: TVSMOTOR) | C11: TVS | D11: iQube | E11: 2.2 kWh | F11: On sale | G11: 2022 (variant) | H11: Entry mass | I11: 94999 | J11: 119236 | K11: Aug-2026 | L11: BaaS option from Mar-2026 | M11: 2.2 | N11: Fixed | O11: Li-ion | P11: Imported cells; pack assembled in-house | Q11: BLDC hub | R11: 4.4 | S11: 33 | T11: 75 | U11: 4.2 | V11: 94 | W11: IDC | X11: 70 | Y11: 950 | Z11: 2h45m-2h50m (0-80%) | AA11: No DC fast charge | AB11: 110 | AC11: 1805 | AD11: 645 | AE11: 1140 | AF11: 1301 | AG11: 157 | AH11: 770 | AI11: 30 | AJ11: 12-inch alloy | AK11: Drum / Drum | AL11: CBS | AM11: 5-inch TFT | AN11: Bluetooth, SmartXonnect, OTA, geofencing | AO11: 2 | AP11: Yes | AQ11: Yes | AR11: Regen braking, Q-Park reverse, 118 connected features (higher trims) | AS11: IP67 (AIS-156 certified) | AT11: 3 yr / 50,000 km | AU11: 3 yr (2 yr extended optional) | AV11: iQube platform | AW11: High localisation; PLI-linked | AX11: Cheapest route into India's largest 2W service network (TVS) | AY11: =IF(AND(ISNUMBER($J11),ISNUMBER($M11)),$J11/$M11,"n/a") -> 54198.182 | AZ11: =IF(AND(ISNUMBER($V11),ISNUMBER($M11)),$V11/$M11,"n/a") -> 42.727273 | BA11: =IF(NOT(ISNUMBER($J11)),"n/a",IF($J11<70000,"1. <Rs70k",IF($J11<100000,"2. Rs70k-1L",IF($J11<150000,"3. Rs1-1.5L",IF($J11<200000,"4. Rs1.5-2L",IF($J11<300000,"5. Rs2-3L","6. >Rs3L")))))) -> 3. Rs1-1.5L | BB11: MEDIUM | BC11: BikeWale price list (Aug-2026) | BD11: tvsmotor.com spec pages | BE11: TVS = FY26 e-2W market leader, 341,513 units. Sources differ on 2.2 vs 2.3 kWh nameplate.
A12: S009 | B12: TVS Motor Company | C12: TVS | D12: iQube | E12: 3.1 kWh | F12: On sale | G12: 2025 | H12: Mass | I12: n/a | J12: 138495 | K12: Aug-2026 | L12: n/a | M12: 3.1 | N12: Fixed | O12: Li-ion | P12: n/a | Q12: BLDC hub | R12: 4.4 | S12: 33 | T12: 82 | U12: n/a | V12: 123 | W12: IDC | X12: 90 | Y12: 950 | Z12: ~4h00m (0-80%) | AA12: No | AB12: 118 | AC12: 1805 | AD12: 645 | AE12: 1140 | AF12: 1301 | AG12: 157 | AH12: 770 | AI12: 32 | AJ12: 12-inch alloy | AK12: Disc / Drum | AL12: CBS | AM12: 5-inch TFT | AN12: SmartXonnect, OTA, Alexa skill | AO12: 2 | AP12: Yes | AQ12: Yes | AR12: Q-Park reverse, crash/fall/anti-theft alert | AS12: IP67 / AIS-156 | AT12: 3 yr / 50,000 km | AU12: 3 yr | AV12: iQube | AW12: High localisation | AX12: Volume sweet spot of the iQube ladder | AY12: =IF(AND(ISNUMBER($J12),ISNUMBER($M12)),$J12/$M12,"n/a") -> 44675.806 | AZ12: =IF(AND(ISNUMBER($V12),ISNUMBER($M12)),$V12/$M12,"n/a") -> 39.677419 | BA12: =IF(NOT(ISNUMBER($J12)),"n/a",IF($J12<70000,"1. <Rs70k",IF($J12<100000,"2. Rs70k-1L",IF($J12<150000,"3. Rs1-1.5L",IF($J12<200000,"4. Rs1.5-2L",IF($J12<300000,"5. Rs2-3L","6. >Rs3L")))))) -> 3. Rs1-1.5L | BB12: MEDIUM | BC12: BikeWale (Aug-2026) | BD12: 91wheels (Aug-2026) | BE12: n/a
A13: S010 | B13: TVS Motor Company | C13: TVS | D13: iQube | E13: 3.5 kWh | F13: On sale | G13: 2024 | H13: Mass | I13: n/a | J13: 145640 | K13: Aug-2026 | L13: n/a | M13: 3.5 | N13: Fixed | O13: Li-ion | P13: n/a | Q13: BLDC hub | R13: 4.4 | S13: 33 | T13: 78 | U13: n/a | V13: 145 | W13: IDC | X13: 105 | Y13: 950 | Z13: ~4h30m-4h40m (0-80%) | AA13: No | AB13: 118 | AC13: 1805 | AD13: 645 | AE13: 1140 | AF13: 1301 | AG13: 157 | AH13: 770 | AI13: 32 | AJ13: 12-inch alloy | AK13: Disc / Drum | AL13: CBS | AM13: 5-inch TFT | AN13: SmartXonnect, 118 connected features, Alexa | AO13: 2 | AP13: Yes | AQ13: Yes | AR13: Fits 2 helmets, USB port, crash/fall alert | AS13: IP67 / AIS-156 | AT13: 3 yr / 50,000 km | AU13: 3 yr | AV13: iQube | AW13: High localisation | AX13: Long-range mass variant | AY13: =IF(AND(ISNUMBER($J13),ISNUMBER($M13)),$J13/$M13,"n/a") -> 41611.429 | AZ13: =IF(AND(ISNUMBER($V13),ISNUMBER($M13)),$V13/$M13,"n/a") -> 41.428571 | BA13: =IF(NOT(ISNUMBER($J13)),"n/a",IF($J13<70000,"1. <Rs70k",IF($J13<100000,"2. Rs70k-1L",IF($J13<150000,"3. Rs1-1.5L",IF($J13<200000,"4. Rs1.5-2L",IF($J13<300000,"5. Rs2-3L","6. >Rs3L")))))) -> 3. Rs1-1.5L | BB13: HIGH | BC13: tvsmotor.com iQube 3.5 kWh page | BD13: Autocar India (Aug-2026) | BE13: Autocar reader Q&A flags no fast-charge support as a purchase objection.
A14: S011 | B14: TVS Motor Company | C14: TVS | D14: iQube | E14: MillionR Special Edition | F14: On sale | G14: 2025 | H14: Mass | I14: n/a | J14: 140138 | K14: Aug-2026 | L14: n/a | M14: 3.1 | N14: Fixed | O14: Li-ion | P14: n/a | Q14: BLDC hub | R14: 4.4 | S14: 33 | T14: 82 | U14: n/a | V14: 123 | W14: IDC | X14: 90 | Y14: 950 | Z14: ~4h | AA14: No | AB14: 118 | AC14: n/a | AD14: n/a | AE14: n/a | AF14: 1301 | AG14: 157 | AH14: 770 | AI14: 32 | AJ14: 12-inch alloy | AK14: Disc / Drum | AL14: CBS | AM14: 5-inch TFT | AN14: SmartXonnect | AO14: 2 | AP14: Yes | AQ14: Yes | AR14: Commemorative 1-million-EV edition trim | AS14: IP67 | AT14: 3 yr / 50,000 km | AU14: 3 yr | AV14: iQube | AW14: High localisation | AX14: Milestone edition — marketing-led differentiation | AY14: =IF(AND(ISNUMBER($J14),ISNUMBER($M14)),$J14/$M14,"n/a") -> 45205.806 | AZ14: =IF(AND(ISNUMBER($V14),ISNUMBER($M14)),$V14/$M14,"n/a") -> 39.677419 | BA14: =IF(NOT(ISNUMBER($J14)),"n/a",IF($J14<70000,"1. <Rs70k",IF($J14<100000,"2. Rs70k-1L",IF($J14<150000,"3. Rs1-1.5L",IF($J14<200000,"4. Rs1.5-2L",IF($J14<300000,"5. Rs2-3L","6. >Rs3L")))))) -> 3. Rs1-1.5L | BB14: MEDIUM | BC14: BikeWale price list (Aug-2026) | BD14: n/a | BE14: n/a
A15: S012 | B15: TVS Motor Company | C15: TVS | D15: iQube | E15: S 4.7 kWh | F15: On sale | G15: 2025 | H15: Upper-mass | I15: n/a | J15: 165353 | K15: Aug-2026 | L15: n/a | M15: 4.7 | N15: Fixed | O15: Li-ion | P15: n/a | Q15: BLDC hub | R15: 4.4 | S15: 33 | T15: 82 | U15: n/a | V15: n/a | W15: IDC | X15: n/a | Y15: 950 | Z15: ~3h00m (0-80%) | AA15: No | AB15: n/a | AC15: n/a | AD15: n/a | AE15: n/a | AF15: 1301 | AG15: 157 | AH15: 770 | AI15: 32 | AJ15: 12-inch alloy | AK15: Disc / Drum | AL15: CBS | AM15: 12.7 cm (5-inch) TFT | AN15: SmartXonnect, OTA | AO15: 3 | AP15: Yes | AQ15: Yes | AR15: Q-Park, regen | AS15: IP67 | AT15: 3 yr / 50,000 km | AU15: 3 yr | AV15: iQube | AW15: High localisation | AX15: Bridges mass iQube to flagship ST | AY15: =IF(AND(ISNUMBER($J15),ISNUMBER($M15)),$J15/$M15,"n/a") -> 35181.489 | AZ15: =IF(AND(ISNUMBER($V15),ISNUMBER($M15)),$V15/$M15,"n/a") -> n/a | BA15: =IF(NOT(ISNUMBER($J15)),"n/a",IF($J15<70000,"1. <Rs70k",IF($J15<100000,"2. Rs70k-1L",IF($J15<150000,"3. Rs1-1.5L",IF($J15<200000,"4. Rs1.5-2L",IF($J15<300000,"5. Rs2-3L","6. >Rs3L")))))) -> 4. Rs1.5-2L | BB15: MEDIUM | BC15: BikeWale (Aug-2026) | BD15: 91wheels (Aug-2026) | BE15: Claimed range not consistently disclosed across sources.
A16: S013 | B16: TVS Motor Company | C16: TVS | D16: iQube | E16: ST 5.3 kWh | F16: On sale | G16: 2024 | H16: Flagship | I16: n/a | J16: 175582 | K16: Aug-2026 | L16: n/a | M16: 5.3 | N16: Fixed | O16: Li-ion | P16: n/a | Q16: BLDC hub | R16: 4.4 | S16: 33 | T16: 82 | U16: 4.3 | V16: 175 | W16: IDC (older 212 km claim withdrawn) | X16: 130 | Y16: 950 | Z16: 4h18m (0-80%) | AA16: No DC fast charge | AB16: n/a | AC16: n/a | AD16: n/a | AE16: n/a | AF16: 1301 | AG16: 157 | AH16: 770 | AI16: 32 | AJ16: 12-inch alloy | AK16: Disc / Drum | AL16: CBS | AM16: 17.78 cm (7-inch) touchscreen | AN16: SmartXonnect, nav, Alexa, OTA | AO16: 3 | AP16: Yes | AQ16: Yes | AR16: Largest pack in TVS range; TPMS on some trims | AS16: IP67 / AIS-156 | AT16: 3 yr / 50,000 km | AU16: 3 yr | AV16: iQube | AW16: High localisation | AX16: TVS's long-range flagship; competes with Ather 450X / Ola S1 Pro | AY16: =IF(AND(ISNUMBER($J16),ISNUMBER($M16)),$J16/$M16,"n/a") -> 33128.679 | AZ16: =IF(AND(ISNUMBER($V16),ISNUMBER($M16)),$V16/$M16,"n/a") -> 33.018868 | BA16: =IF(NOT(ISNUMBER($J16)),"n/a",IF($J16<70000,"1. <Rs70k",IF($J16<100000,"2. Rs70k-1L",IF($J16<150000,"3. Rs1-1.5L",IF($J16<200000,"4. Rs1.5-2L",IF($J16<300000,"5. Rs2-3L","6. >Rs3L")))))) -> 4. Rs1.5-2L | BB16: MEDIUM | BC16: 91wheels (Aug-2026) | BD16: BikeWale (Aug-2026) | BE16: Range claim revised: 212 km (launch marketing) vs ~175 km IDC now cited. Treat 175 km as the working figure.
A17: S014 | B17: TVS Motor Company | C17: TVS | D17: Orbiter | E17: V1 / V2 | F17: On sale | G17: Mar-2026 | H17: Entry urban | I17: 99900 | J17: 102459 | K17: Aug-2026 | L17: From Rs49,999 on BaaS | M17: 3.1 | N17: Fixed | O17: Li-ion | P17: n/a | Q17: BLDC hub | R17: 2.5 | S17: n/a | T17: 68 | U17: n/a | V17: 158 | W17: IDC | X17: 110 | Y17: n/a | Z17: n/a | AA17: No | AB17: n/a | AC17: n/a | AD17: n/a | AE17: n/a | AF17: n/a | AG17: n/a | AH17: n/a | AI17: 33 | AJ17: 12-inch | AK17: Drum / Drum | AL17: CBS | AM17: LCD | AN17: Bluetooth, basic connectivity | AO17: 2 | AP17: Yes | AQ17: n/a | AR17: 33L storage; BaaS-led pricing to undercut ICE | AS17: IP67 | AT17: 3 yr | AU17: 3 yr | AV17: New entry platform | AW17: High localisation | AX17: TVS's sub-Rs1L volume weapon; BaaS pricing attacks the ICE price gap directly | AY17: =IF(AND(ISNUMBER($J17),ISNUMBER($M17)),$J17/$M17,"n/a") -> 33051.29 | AZ17: =IF(AND(ISNUMBER($V17),ISNUMBER($M17)),$V17/$M17,"n/a") -> 50.967742 | BA17: =IF(NOT(ISNUMBER($J17)),"n/a",IF($J17<70000,"1. <Rs70k",IF($J17<100000,"2. Rs70k-1L",IF($J17<150000,"3. Rs1-1.5L",IF($J17<200000,"4. Rs1.5-2L",IF($J17<300000,"5. Rs2-3L","6. >Rs3L")))))) -> 3. Rs1-1.5L | BB17: MEDIUM | BC17: BikeWale (Aug-2026) | BD17: ZigWheels Orbiter V1 vs V2 (Mar-2026) | BE17: Key competitive datapoint: first credible sub-Rs50k effective entry price from a top-4 OEM.
A18: S015 | B18: TVS Motor Company | C18: TVS | D18: X | E18: 4.4 kWh | F18: On sale | G18: 2023 | H18: Premium crossover | I18: 249000 | J18: n/a | K18: Aug-2026 | L18: n/a | M18: 4.4 | N18: Fixed | O18: Li-ion | P18: n/a | Q18: PMSM | R18: 11 | S18: n/a | T18: 105 | U18: 2.6 | V18: 140 | W18: IDC | X18: 100 | Y18: n/a | Z18: ~3h (0-80%) | AA18: Yes | AB18: n/a | AC18: n/a | AD18: n/a | AE18: n/a | AF18: n/a | AG18: n/a | AH18: n/a | AI18: n/a | AJ18: 14/12-inch | AK18: Disc / Disc | AL18: Dual-channel | AM18: 10.2-inch TFT touchscreen | AN18: 4G, nav, OTA | AO18: 4 | AP18: Yes | AQ18: Yes | AR18: Largest display in segment; premium crossover positioning | AS18: IP67 | AT18: 3 yr | AU18: 3 yr | AV18: TVS X platform | AW18: High localisation | AX18: TVS's differentiated premium niche play — low volume, high ASP | AY18: =IF(AND(ISNUMBER($J18),ISNUMBER($M18)),$J18/$M18,"n/a") -> n/a | AZ18: =IF(AND(ISNUMBER($V18),ISNUMBER($M18)),$V18/$M18,"n/a") -> 31.818182 | BA18: =IF(NOT(ISNUMBER($J18)),"n/a",IF($J18<70000,"1. <Rs70k",IF($J18<100000,"2. Rs70k-1L",IF($J18<150000,"3. Rs1-1.5L",IF($J18<200000,"4. Rs1.5-2L",IF($J18<300000,"5. Rs2-3L","6. >Rs3L")))))) -> n/a | BB18: MEDIUM | BC18: TVS press material / Autocar India | BD18: n/a | BE18: Niche-thesis exhibit: differentiated premium positioning has NOT scaled volumes.
A19: S016 | B19: Bajaj Auto (listed: BAJAJ-AUTO) | C19: Bajaj | D19: Chetak | E19: 2501 | F19: On sale | G19: Jan-2026 | H19: Entry | I19: 87100 | J19: 99000 | K19: Aug-2026 | L19: n/a | M19: 2.5 | N19: Fixed | O19: Li-ion | P19: n/a | Q19: PMSM | R19: n/a | S19: n/a | T19: 55 | U19: n/a | V19: 113 | W19: IDC | X19: 80 | Y19: 750 | Z19: n/a | AA19: No | AB19: n/a | AC19: n/a | AD19: n/a | AE19: n/a | AF19: n/a | AG19: n/a | AH19: n/a | AI19: n/a | AJ19: 12-inch | AK19: Drum / Drum | AL19: CBS | AM19: Negative LCD | AN19: Bluetooth (TecPac optional) | AO19: 2 | AP19: n/a | AQ19: n/a | AR19: All-metal body; IP67; TecPac add-on from Rs4,000 + data pack | AS19: IP67 | AT19: 3 yr | AU19: 5 yr / 70,000 km (35-series claim) | AV19: Chetak 25/30 series | AW19: High localisation | AX19: Cheapest entry into an all-metal, dealer-backed Chetak | AY19: =IF(AND(ISNUMBER($J19),ISNUMBER($M19)),$J19/$M19,"n/a") -> 39600 | AZ19: =IF(AND(ISNUMBER($V19),ISNUMBER($M19)),$V19/$M19,"n/a") -> 45.2 | BA19: =IF(NOT(ISNUMBER($J19)),"n/a",IF($J19<70000,"1. <Rs70k",IF($J19<100000,"2. Rs70k-1L",IF($J19<150000,"3. Rs1-1.5L",IF($J19<200000,"4. Rs1.5-2L",IF($J19<300000,"5. Rs2-3L","6. >Rs3L")))))) -> 2. Rs70k-1L | BB19: MEDIUM | BC19: carhp.in variant explainer (Sep-2025) | BD19: Bajaj Chetak.com | BE19: Price flagged MEDIUM: PM E-DRIVE incentive lapsed 31-Jul-2026, prices in flux.
A20: S017 | B20: Bajaj Auto | C20: Bajaj | D20: Chetak | E20: 3001 | F20: On sale | G20: 2025 | H20: Entry-mid | I20: 99900 | J20: 109000 | K20: Aug-2026 | L20: n/a | M20: 3 | N20: Fixed | O20: Li-ion | P20: n/a | Q20: PMSM | R20: 3.1 | S20: n/a | T20: 63 | U20: n/a | V20: 127 | W20: IDC | X20: 90 | Y20: 750 | Z20: 3h50m (0-80%) | AA20: No | AB20: n/a | AC20: n/a | AD20: n/a | AE20: n/a | AF20: n/a | AG20: n/a | AH20: n/a | AI20: 35 | AJ20: 12-inch | AK20: Drum / Drum | AL20: CBS | AM20: Negative LCD | AN20: Bluetooth phone connectivity | AO20: 2 | AP20: n/a | AQ20: n/a | AR20: All-metal body, best-in-class 35L boot | AS20: IP67 | AT20: 3 yr | AU20: 5 yr / 70,000 km | AV20: Chetak 30 series | AW20: High localisation | AX20: Metal-body durability pitch at the Rs1L price point | AY20: =IF(AND(ISNUMBER($J20),ISNUMBER($M20)),$J20/$M20,"n/a") -> 36333.333 | AZ20: =IF(AND(ISNUMBER($V20),ISNUMBER($M20)),$V20/$M20,"n/a") -> 42.333333 | BA20: =IF(NOT(ISNUMBER($J20)),"n/a",IF($J20<70000,"1. <Rs70k",IF($J20<100000,"2. Rs70k-1L",IF($J20<150000,"3. Rs1-1.5L",IF($J20<200000,"4. Rs1.5-2L",IF($J20<300000,"5. Rs2-3L","6. >Rs3L")))))) -> 3. Rs1-1.5L | BB20: HIGH | BC20: Autocar India variant explainer | BD20: chetak.com | BE20: n/a
A21: S018 | B21: Bajaj Auto | C21: Bajaj | D21: Chetak | E21: 3503 | F21: On sale | G21: 2025 | H21: Mass | I21: 102000 | J21: 109000 | K21: Aug-2026 | L21: n/a | M21: 3.5 | N21: Fixed | O21: Li-ion | P21: n/a | Q21: PMSM | R21: 4 | S21: n/a | T21: 63 | U21: n/a | V21: 151 | W21: IDC | X21: 105 | Y21: 900 | Z21: 3h25m (0-80%) | AA21: No | AB21: n/a | AC21: n/a | AD21: n/a | AE21: n/a | AF21: n/a | AG21: n/a | AH21: n/a | AI21: 35 | AJ21: 12-inch | AK21: Drum / Drum | AL21: CBS | AM21: Negative LCD | AN21: Bluetooth, handlebar music control, call/SMS alerts | AO21: 2 | AP21: n/a | AQ21: n/a | AR21: Hill-hold, all-metal body, 35L boot | AS21: IP67 | AT21: 3 yr | AU21: 5 yr / 70,000 km | AV21: Chetak 35 series | AW21: High localisation | AX21: Best range-per-rupee in the Chetak ladder | AY21: =IF(AND(ISNUMBER($J21),ISNUMBER($M21)),$J21/$M21,"n/a") -> 31142.857 | AZ21: =IF(AND(ISNUMBER($V21),ISNUMBER($M21)),$V21/$M21,"n/a") -> 43.142857 | BA21: =IF(NOT(ISNUMBER($J21)),"n/a",IF($J21<70000,"1. <Rs70k",IF($J21<100000,"2. Rs70k-1L",IF($J21<150000,"3. Rs1-1.5L",IF($J21<200000,"4. Rs1.5-2L",IF($J21<300000,"5. Rs2-3L","6. >Rs3L")))))) -> 3. Rs1-1.5L | BB21: HIGH | BC21: chetak.com/series-35/chetak-c3503 | BD21: Autocar India (Jul-2026) | BE21: Top speed cited variously as 63 and 70 km/h — Bajaj site says 70 km/h.
A22: S019 | B22: Bajaj Auto | C22: Bajaj | D22: Chetak | E22: 3502 | F22: On sale | G22: 2025 | H22: Mass | I22: n/a | J22: 130306 | K22: Aug-2026 | L22: n/a | M22: 3.5 | N22: Fixed | O22: Li-ion | P22: n/a | Q22: PMSM | R22: 4 | S22: n/a | T22: 73 | U22: n/a | V22: 153 | W22: IDC | X22: 107 | Y22: 900 | Z22: 3h25m (0-80%) | AA22: No | AB22: n/a | AC22: n/a | AD22: n/a | AE22: n/a | AF22: n/a | AG22: n/a | AH22: n/a | AI22: 35 | AJ22: 12-inch | AK22: Disc / Drum | AL22: CBS | AM22: TFT with app connectivity | AN22: Bluetooth + TecPac (overspeed alert, guide-me-home, immobiliser, music) | AO22: 3 | AP22: n/a | AQ22: n/a | AR22: Front disc; TFT dash | AS22: IP67 | AT22: 3 yr | AU22: 5 yr / 70,000 km | AV22: Chetak 35 series | AW22: High localisation | AX22: Feature step-up variant | AY22: =IF(AND(ISNUMBER($J22),ISNUMBER($M22)),$J22/$M22,"n/a") -> 37230.286 | AZ22: =IF(AND(ISNUMBER($V22),ISNUMBER($M22)),$V22/$M22,"n/a") -> 43.714286 | BA22: =IF(NOT(ISNUMBER($J22)),"n/a",IF($J22<70000,"1. <Rs70k",IF($J22<100000,"2. Rs70k-1L",IF($J22<150000,"3. Rs1-1.5L",IF($J22<200000,"4. Rs1.5-2L",IF($J22<300000,"5. Rs2-3L","6. >Rs3L")))))) -> 3. Rs1-1.5L | BB22: HIGH | BC22: chetak.com/series-35/chetak-c3502 | BD22: Autocar India | BE22: Chetak.com quotes 80 km/h top speed for 3502 vs Autocar's 73 km/h — verify.
A23: S020 | B23: Bajaj Auto | C23: Bajaj | D23: Chetak | E23: 3501 | F23: On sale | G23: 2025 | H23: Upper-mass flagship | I23: 122500 | J23: 134000 | K23: Aug-2026 | L23: n/a | M23: 3.5 | N23: Fixed | O23: Li-ion | P23: n/a | Q23: PMSM | R23: 4 | S23: n/a | T23: 73 | U23: n/a | V23: 153 | W23: IDC | X23: 107 | Y23: 950 | Z23: 3h00m (0-80%) | AA23: No | AB23: n/a | AC23: n/a | AD23: n/a | AE23: n/a | AF23: n/a | AG23: n/a | AH23: n/a | AI23: 35 | AJ23: 12-inch | AK23: Disc / Drum | AL23: CBS | AM23: TFT touchscreen | AN23: Bluetooth, TecPac, sequential indicators | AO23: 3 | AP23: n/a | AQ23: n/a | AR23: Keyless ignition, sequential indicators, fastest-charging Chetak | AS23: IP67 | AT23: 3 yr | AU23: 5 yr / 70,000 km | AV23: Chetak 35 series | AW23: High localisation | AX23: Chetak flagship; all-metal body remains the brand's structural differentiator | AY23: =IF(AND(ISNUMBER($J23),ISNUMBER($M23)),$J23/$M23,"n/a") -> 38285.714 | AZ23: =IF(AND(ISNUMBER($V23),ISNUMBER($M23)),$V23/$M23,"n/a") -> 43.714286 | BA23: =IF(NOT(ISNUMBER($J23)),"n/a",IF($J23<70000,"1. <Rs70k",IF($J23<100000,"2. Rs70k-1L",IF($J23<150000,"3. Rs1-1.5L",IF($J23<200000,"4. Rs1.5-2L",IF($J23<300000,"5. Rs2-3L","6. >Rs3L")))))) -> 3. Rs1-1.5L | BB23: HIGH | BC23: Autocar India variant explainer | BD23: chetak.com | BE23: Bajaj FY26: 289,349 units, #2 in India.
A24: S021 | B24: Ola Electric (listed: OLAELEC) | C24: Ola Electric | D24: S1 X | E24: 2 kWh Gen 3 | F24: On sale | G24: 2025 | H24: Entry | I24: 79999 | J24: 84999 | K24: Aug-2026 | L24: n/a | M24: 2 | N24: Fixed | O24: Li-ion (4680 cylindrical on select trims) | P24: Ola in-house 4680 Bharat Cell (Krishnagiri) + imported | Q24: Mid-drive IPM | R24: n/a | S24: n/a | T24: n/a | U24: n/a | V24: n/a | W24: IDC | X24: n/a | Y24: n/a | Z24: n/a | AA24: Ola Hypercharger network | AB24: n/a | AC24: n/a | AD24: n/a | AE24: n/a | AF24: n/a | AG24: n/a | AH24: n/a | AI24: 34 | AJ24: 12-inch | AK24: Drum / Drum | AL24: CBS | AM24: LCD | AN24: MoveOS, Bluetooth | AO24: 3 | AP24: Yes | AQ24: Yes | AR24: MoveOS OTA platform | AS24: IP67 | AT24: 3 yr | AU24: 3 yr | AV24: Gen 3 | AW24: In-house cell + motor (ferrite, rare-earth-free on newer trims) | AX24: Lowest sticker price among the top-5 OEMs | AY24: =IF(AND(ISNUMBER($J24),ISNUMBER($M24)),$J24/$M24,"n/a") -> 42499.5 | AZ24: =IF(AND(ISNUMBER($V24),ISNUMBER($M24)),$V24/$M24,"n/a") -> n/a | BA24: =IF(NOT(ISNUMBER($J24)),"n/a",IF($J24<70000,"1. <Rs70k",IF($J24<100000,"2. Rs70k-1L",IF($J24<150000,"3. Rs1-1.5L",IF($J24<200000,"4. Rs1.5-2L",IF($J24<300000,"5. Rs2-3L","6. >Rs3L")))))) -> 2. Rs70k-1L | BB24: MEDIUM | BC24: Ola Electric price list / BikeDekho (Aug-2026) | BD24: n/a | BE24: Ola FY26 volumes fell 52% to 164,295. Treat all Ola pricing as promotional and volatile.
A25: S022 | B25: Ola Electric | C25: Ola Electric | D25: S1 X | E25: 3 kWh Gen 3 | F25: On sale | G25: 2025 | H25: Entry-mid | I25: n/a | J25: 99999 | K25: Aug-2026 | L25: n/a | M25: 3 | N25: Fixed | O25: Li-ion | P25: n/a | Q25: Mid-drive IPM | R25: n/a | S25: n/a | T25: n/a | U25: n/a | V25: n/a | W25: IDC | X25: n/a | Y25: n/a | Z25: n/a | AA25: Ola Hypercharger | AB25: n/a | AC25: n/a | AD25: n/a | AE25: n/a | AF25: n/a | AG25: n/a | AH25: n/a | AI25: 34 | AJ25: 12-inch | AK25: Drum / Drum | AL25: CBS | AM25: LCD | AN25: MoveOS | AO25: 3 | AP25: Yes | AQ25: Yes | AR25: n/a | AS25: IP67 | AT25: 3 yr | AU25: 3 yr | AV25: Gen 3 | AW25: n/a | AX25: Volume entry variant | AY25: =IF(AND(ISNUMBER($J25),ISNUMBER($M25)),$J25/$M25,"n/a") -> 33333 | AZ25: =IF(AND(ISNUMBER($V25),ISNUMBER($M25)),$V25/$M25,"n/a") -> n/a | BA25: =IF(NOT(ISNUMBER($J25)),"n/a",IF($J25<70000,"1. <Rs70k",IF($J25<100000,"2. Rs70k-1L",IF($J25<150000,"3. Rs1-1.5L",IF($J25<200000,"4. Rs1.5-2L",IF($J25<300000,"5. Rs2-3L","6. >Rs3L")))))) -> 2. Rs70k-1L | BB25: LOW | BC25: BikeDekho / aggregator listings (Aug-2026) | BD25: n/a | BE25: Spec disclosure inconsistent across sources.
A26: S023 | B26: Ola Electric | C26: Ola Electric | D26: S1 X | E26: 4 kWh Gen 3 | F26: On sale | G26: 2025 | H26: Mid | I26: n/a | J26: 114000 | K26: Aug-2026 | L26: n/a | M26: 4 | N26: Fixed | O26: Li-ion | P26: n/a | Q26: Mid-drive IPM | R26: n/a | S26: n/a | T26: n/a | U26: n/a | V26: 242 | W26: IDC | X26: 150 | Y26: n/a | Z26: n/a | AA26: Ola Hypercharger | AB26: n/a | AC26: n/a | AD26: n/a | AE26: n/a | AF26: n/a | AG26: n/a | AH26: n/a | AI26: 34 | AJ26: 12-inch | AK26: Disc / Drum | AL26: CBS | AM26: LCD | AN26: MoveOS | AO26: 3 | AP26: Yes | AQ26: Yes | AR26: n/a | AS26: IP67 | AT26: 3 yr | AU26: 3 yr | AV26: Gen 3 | AW26: n/a | AX26: Longest range at the sub-Rs1.2L price point on claimed figures | AY26: =IF(AND(ISNUMBER($J26),ISNUMBER($M26)),$J26/$M26,"n/a") -> 28500 | AZ26: =IF(AND(ISNUMBER($V26),ISNUMBER($M26)),$V26/$M26,"n/a") -> 60.5 | BA26: =IF(NOT(ISNUMBER($J26)),"n/a",IF($J26<70000,"1. <Rs70k",IF($J26<100000,"2. Rs70k-1L",IF($J26<150000,"3. Rs1-1.5L",IF($J26<200000,"4. Rs1.5-2L",IF($J26<300000,"5. Rs2-3L","6. >Rs3L")))))) -> 3. Rs1-1.5L | BB26: LOW | BC26: Aggregator listings (Aug-2026) | BD26: n/a | BE26: 242 km IDC claim is an outlier; real-world expected c.55-60% of claim.
A27: S024 | B27: Ola Electric | C27: Ola Electric | D27: S1 Pro | E27: 3 kWh Gen 3 | F27: On sale | G27: Jan-2025 | H27: Premium | I27: 115000 | J27: 125000 | K27: Aug-2026 | L27: n/a | M27: 3 | N27: Fixed | O27: Li-ion | P27: n/a | Q27: Mid-drive IPM | R27: 5.5 | S27: n/a | T27: 117 | U27: 4.3 | V27: 176 | W27: IDC | X27: 105 | Y27: n/a | Z27: 7h15m (0-80%, std charger) | AA27: Ola Hypercharger | AB27: 109 | AC27: 1900 | AD27: 850 | AE27: 1288 | AF27: 1359 | AG27: 160 | AH27: 791 | AI27: 34 | AJ27: 12-inch (90/90-12) | AK27: Disc / Disc | AL27: CBS | AM27: 7-inch TFT touchscreen | AN27: MoveOS, 4G, nav, OTA | AO27: 3 | AP27: Yes | AQ27: Yes | AR27: Cruise control, traction control, reverse, hill hold | AS27: IP67 | AT27: 3 yr | AU27: 3 yr | AV27: Gen 3 | AW27: In-house motor and (on some trims) 4680 cell | AX27: Highest claimed top speed among mass e-scooters | AY27: =IF(AND(ISNUMBER($J27),ISNUMBER($M27)),$J27/$M27,"n/a") -> 41666.667 | AZ27: =IF(AND(ISNUMBER($V27),ISNUMBER($M27)),$V27/$M27,"n/a") -> 58.666667 | BA27: =IF(NOT(ISNUMBER($J27)),"n/a",IF($J27<70000,"1. <Rs70k",IF($J27<100000,"2. Rs70k-1L",IF($J27<150000,"3. Rs1-1.5L",IF($J27<200000,"4. Rs1.5-2L",IF($J27<300000,"5. Rs2-3L","6. >Rs3L")))))) -> 3. Rs1-1.5L | BB27: MEDIUM | BC27: BikeDekho (Aug-2026) | BD27: ZigWheels (updated 31-Jul-2026) | BE27: Charging time (7h15m) is the weakest in the premium set — a real competitive liability.
A28: S025 | B28: Ola Electric | C28: Ola Electric | D28: S1 Pro | E28: 4 kWh Gen 3 | F28: On sale | G28: Jan-2025 | H28: Premium | I28: 135000 | J28: 144999 | K28: Aug-2026 | L28: n/a | M28: 4 | N28: Fixed | O28: Li-ion | P28: n/a | Q28: Mid-drive IPM | R28: 11 | S28: n/a | T28: 125 | U28: n/a | V28: 242 | W28: IDC | X28: 145 | Y28: n/a | Z28: ~6h30m | AA28: Ola Hypercharger | AB28: 109 | AC28: 1900 | AD28: 850 | AE28: 1288 | AF28: 1359 | AG28: 160 | AH28: 791 | AI28: 34 | AJ28: 12-inch | AK28: Disc / Disc | AL28: Dual ABS on some trims | AM28: 7-inch TFT touchscreen | AN28: MoveOS, 4G, nav, OTA | AO28: 4 | AP28: Yes | AQ28: Yes | AR28: Cruise control, traction control, hill hold | AS28: IP67 | AT28: 3 yr | AU28: 3 yr | AV28: Gen 3 | AW28: n/a | AX28: Spec-sheet leader on power and claimed range | AY28: =IF(AND(ISNUMBER($J28),ISNUMBER($M28)),$J28/$M28,"n/a") -> 36249.75 | AZ28: =IF(AND(ISNUMBER($V28),ISNUMBER($M28)),$V28/$M28,"n/a") -> 60.5 | BA28: =IF(NOT(ISNUMBER($J28)),"n/a",IF($J28<70000,"1. <Rs70k",IF($J28<100000,"2. Rs70k-1L",IF($J28<150000,"3. Rs1-1.5L",IF($J28<200000,"4. Rs1.5-2L",IF($J28<300000,"5. Rs2-3L","6. >Rs3L")))))) -> 3. Rs1-1.5L | BB28: MEDIUM | BC28: BikeWale (Apr-2026) | BD28: BikeDekho (Aug-2026) | BE28: n/a
A29: S026 | B29: Ola Electric | C29: Ola Electric | D29: S1 Pro+ | E29: 4 kWh | F29: On sale | G29: 2025 | H29: Premium+ | I29: n/a | J29: 160005 | K29: Aug-2026 | L29: n/a | M29: 4 | N29: Fixed | O29: Li-ion | P29: n/a | Q29: Mid-drive IPM | R29: 13 | S29: n/a | T29: 141 | U29: n/a | V29: n/a | W29: IDC | X29: n/a | Y29: n/a | Z29: n/a | AA29: Ola Hypercharger | AB29: n/a | AC29: 1900 | AD29: 850 | AE29: 1288 | AF29: 1359 | AG29: 160 | AH29: 791 | AI29: 34 | AJ29: 12-inch | AK29: Disc / Disc | AL29: Dual-channel | AM29: 7-inch TFT | AN29: MoveOS 5 | AO29: 4 | AP29: Yes | AQ29: Yes | AR29: Brake-by-wire on select trims | AS29: IP67 | AT29: 3 yr | AU29: 3 yr | AV29: Gen 3 | AW29: n/a | AX29: Performance flagship scooter | AY29: =IF(AND(ISNUMBER($J29),ISNUMBER($M29)),$J29/$M29,"n/a") -> 40001.25 | AZ29: =IF(AND(ISNUMBER($V29),ISNUMBER($M29)),$V29/$M29,"n/a") -> n/a | BA29: =IF(NOT(ISNUMBER($J29)),"n/a",IF($J29<70000,"1. <Rs70k",IF($J29<100000,"2. Rs70k-1L",IF($J29<150000,"3. Rs1-1.5L",IF($J29<200000,"4. Rs1.5-2L",IF($J29<300000,"5. Rs2-3L","6. >Rs3L")))))) -> 4. Rs1.5-2L | BB29: MEDIUM | BC29: BikeWale (Apr-2026) | BD29: n/a | BE29: n/a
A30: S027 | B30: Ola Electric | C30: Ola Electric | D30: S1 Pro+ | E30: 5.2 kWh | F30: On sale | G30: 2025 (repriced Sankalp 2025) | H30: Premium+ flagship | I30: n/a | J30: 170000 | K30: Aug-2026 | L30: n/a | M30: 5.2 | N30: Fixed | O30: Li-ion 4680 cylindrical | P30: Ola in-house 4680 Bharat Cell (mass deliveries from Nov-2025) | Q30: Mid-drive IPM (ferrite, rare-earth-free) | R30: 13 | S30: n/a | T30: 141 | U30: n/a | V30: 320 | W30: IDC | X30: 180 | Y30: n/a | Z30: n/a | AA30: Ola Hypercharger | AB30: n/a | AC30: 1900 | AD30: 850 | AE30: 1288 | AF30: 1359 | AG30: 160 | AH30: 791 | AI30: 34 | AJ30: 12-inch | AK30: Disc / Disc | AL30: Dual-channel | AM30: 7-inch TFT | AN30: MoveOS 5, 4G, nav | AO30: 4 | AP30: Yes | AQ30: Yes | AR30: 4680 Bharat Cell; ferrite motor hedges rare-earth risk | AS30: IP67 | AT30: 3 yr | AU30: 3 yr | AV30: Gen 3 | AW30: Deepest vertical integration in Indian e-2W (cells + motor in-house) | AX30: The clearest test of whether cell vertical integration creates a moat | AY30: =IF(AND(ISNUMBER($J30),ISNUMBER($M30)),$J30/$M30,"n/a") -> 32692.308 | AZ30: =IF(AND(ISNUMBER($V30),ISNUMBER($M30)),$V30/$M30,"n/a") -> 61.538462 | BA30: =IF(NOT(ISNUMBER($J30)),"n/a",IF($J30<70000,"1. <Rs70k",IF($J30<100000,"2. Rs70k-1L",IF($J30<150000,"3. Rs1-1.5L",IF($J30<200000,"4. Rs1.5-2L",IF($J30<300000,"5. Rs2-3L","6. >Rs3L")))))) -> 4. Rs1.5-2L | BB30: MEDIUM | BC30: Ola Sankalp 2025 announcements | BD30: thebikejunction / BikeWale (Aug-2026) | BE30: THESIS-CRITICAL: Ola integrated deepest and lost the most share. Vertical integration did not protect it.
A31: S028 | B31: Hero MotoCorp (listed: HEROMOTOCO) | C31: Vida | D31: VX2 | E31: Go 2.2 kWh | F31: On sale | G31: Jul-2025 | H31: Entry | I31: 99490 | J31: 109583 | K31: Aug-2026 | L31: From Rs59,490 (BaaS) | M31: 2.2 | N31: Removable (1 pack) | O31: Li-ion | P31: n/a | Q31: PMSM | R31: 6 | S31: n/a | T31: 70 | U31: 4.2 | V31: 93 | W31: IDC | X31: 68 | Y31: 580 | Z31: 3h07m (0-80%); 1h41m with 1,000W RQ charger | AA31: 5,900+ public fast-charging points (Vida network) | AB31: 106 | AC31: n/a | AD31: n/a | AE31: n/a | AF31: n/a | AG31: n/a | AH31: 777 | AI31: 33.2 | AJ31: 12-inch | AK31: Drum / Drum | AL31: CBS | AM31: LCD | AN31: Bluetooth, keyless | AO31: 2 | AP31: n/a | AQ31: n/a | AR31: Removable IP67 batteries — key differentiator for apartment dwellers | AS31: IP67 | AT31: 3 yr | AU31: 3 yr | AV31: VX2 platform | AW31: High localisation | AX31: Removable-battery convenience + Hero's ~6,000-touchpoint ICE network | AY31: =IF(AND(ISNUMBER($J31),ISNUMBER($M31)),$J31/$M31,"n/a") -> 49810.455 | AZ31: =IF(AND(ISNUMBER($V31),ISNUMBER($M31)),$V31/$M31,"n/a") -> 42.272727 | BA31: =IF(NOT(ISNUMBER($J31)),"n/a",IF($J31<70000,"1. <Rs70k",IF($J31<100000,"2. Rs70k-1L",IF($J31<150000,"3. Rs1-1.5L",IF($J31<200000,"4. Rs1.5-2L",IF($J31<300000,"5. Rs2-3L","6. >Rs3L")))))) -> 3. Rs1-1.5L | BB31: HIGH | BC31: vidaworld.com/compare.html | BD31: Autocar India variant explainer (Jul-2026) | BE31: Vida FY26 grew 196% to 144,330 — fastest scaler among incumbents.
A32: S029 | B32: Hero MotoCorp | C32: Vida | D32: VX2 | E32: Go 2.2 RQ | F32: On sale | G32: 2025 | H32: Entry | I32: n/a | J32: n/a | K32: Aug-2026 | L32: n/a | M32: 2.2 | N32: Removable | O32: Li-ion | P32: n/a | Q32: PMSM | R32: 6 | S32: n/a | T32: 70 | U32: 4.2 | V32: 93 | W32: IDC | X32: 68 | Y32: 1000 | Z32: 1h41m (0-80%) | AA32: Yes | AB32: 106 | AC32: n/a | AD32: n/a | AE32: n/a | AF32: n/a | AG32: n/a | AH32: 777 | AI32: 33.2 | AJ32: 12-inch | AK32: Drum / Drum | AL32: CBS | AM32: LCD | AN32: Bluetooth | AO32: 2 | AP32: n/a | AQ32: n/a | AR32: Mechanically identical to Go 2.2; bundled 1,000W fast charger | AS32: IP67 | AT32: 3 yr | AU32: 3 yr | AV32: VX2 | AW32: High localisation | AX32: Charger-bundle SKU — a low-cost way to sell 'fast charging' | AY32: =IF(AND(ISNUMBER($J32),ISNUMBER($M32)),$J32/$M32,"n/a") -> n/a | AZ32: =IF(AND(ISNUMBER($V32),ISNUMBER($M32)),$V32/$M32,"n/a") -> 42.272727 | BA32: =IF(NOT(ISNUMBER($J32)),"n/a",IF($J32<70000,"1. <Rs70k",IF($J32<100000,"2. Rs70k-1L",IF($J32<150000,"3. Rs1-1.5L",IF($J32<200000,"4. Rs1.5-2L",IF($J32<300000,"5. Rs2-3L","6. >Rs3L")))))) -> n/a | BB32: HIGH | BC32: Autocar India variant explainer (Jul-2026) | BD32: n/a | BE32: n/a
A33: S030 | B33: Hero MotoCorp | C33: Vida | D33: VX2 | E33: Go 3.1 kWh | F33: On sale | G33: 2026 | H33: Entry-mid | I33: n/a | J33: n/a | K33: Aug-2026 | L33: n/a | M33: 3.1 | N33: Removable | O33: Li-ion | P33: n/a | Q33: PMSM | R33: 6 | S33: n/a | T33: 70 | U33: 4.5 | V33: 127 | W33: IDC | X33: 92 | Y33: n/a | Z33: n/a | AA33: Yes | AB33: n/a | AC33: n/a | AD33: n/a | AE33: n/a | AF33: n/a | AG33: n/a | AH33: 777 | AI33: 33.2 | AJ33: 12-inch | AK33: Drum / Drum | AL33: CBS | AM33: LCD | AN33: Bluetooth | AO33: 2 | AP33: n/a | AQ33: n/a | AR33: Removable packs | AS33: IP67 | AT33: 3 yr | AU33: 3 yr | AV33: VX2 | AW33: High localisation | AX33: Range step-up in the Go family | AY33: =IF(AND(ISNUMBER($J33),ISNUMBER($M33)),$J33/$M33,"n/a") -> n/a | AZ33: =IF(AND(ISNUMBER($V33),ISNUMBER($M33)),$V33/$M33,"n/a") -> 40.967742 | BA33: =IF(NOT(ISNUMBER($J33)),"n/a",IF($J33<70000,"1. <Rs70k",IF($J33<100000,"2. Rs70k-1L",IF($J33<150000,"3. Rs1-1.5L",IF($J33<200000,"4. Rs1.5-2L",IF($J33<300000,"5. Rs2-3L","6. >Rs3L")))))) -> n/a | BB33: HIGH | BC33: vidaworld.com/compare.html (Aug-2026) | BD33: n/a | BE33: Vida site quotes 127 and 128 km on different pages.
A34: S031 | B34: Hero MotoCorp | C34: Vida | D34: VX2 | E34: Go FB 3.1 kWh (fixed battery) | F34: On sale | G34: Aug-2026 | H34: Entry-mid | I34: 113000 | J34: 113000 | K34: Aug-2026 | L34: n/a | M34: 3.1 | N34: Fixed | O34: Li-ion | P34: n/a | Q34: PMSM | R34: 6 | S34: n/a | T34: 70 | U34: n/a | V34: 128 | W34: IDC | X34: 93 | Y34: 1000 | Z34: 65 min (0-80%) | AA34: Yes | AB34: n/a | AC34: n/a | AD34: n/a | AE34: n/a | AF34: n/a | AG34: n/a | AH34: 777 | AI34: 33.2 | AJ34: 12-inch | AK34: Drum / Drum | AL34: CBS | AM34: LCD | AN34: Bluetooth | AO34: 2 | AP34: n/a | AQ34: n/a | AR34: First Vida with a NON-removable pack — a deliberate cost-down move | AS34: IP67 | AT34: 3 yr | AU34: 3 yr | AV34: VX2 | AW34: High localisation | AX34: Signals Hero trading its removable-battery USP for price competitiveness | AY34: =IF(AND(ISNUMBER($J34),ISNUMBER($M34)),$J34/$M34,"n/a") -> 36451.613 | AZ34: =IF(AND(ISNUMBER($V34),ISNUMBER($M34)),$V34/$M34,"n/a") -> 41.290323 | BA34: =IF(NOT(ISNUMBER($J34)),"n/a",IF($J34<70000,"1. <Rs70k",IF($J34<100000,"2. Rs70k-1L",IF($J34<150000,"3. Rs1-1.5L",IF($J34<200000,"4. Rs1.5-2L",IF($J34<300000,"5. Rs2-3L","6. >Rs3L")))))) -> 3. Rs1-1.5L | BB34: HIGH | BC34: BikeDekho news (01-Aug-2026) | BD34: BikeWale (Jul-2026) | BE34: Strategically notable: incumbents are now competing on price, not features.
A35: S032 | B35: Hero MotoCorp | C35: Vida | D35: VX2 | E35: Go 3.4 kWh | F35: On sale | G35: 2026 | H35: Mid | I35: n/a | J35: n/a | K35: Aug-2026 | L35: n/a | M35: 3.4 | N35: Removable (2 packs) | O35: Li-ion | P35: n/a | Q35: PMSM | R35: 6 | S35: n/a | T35: 70 | U35: 4.2 | V35: 146 | W35: IDC | X35: 105 | Y35: n/a | Z35: 62 min (0-80%) on public fast charge | AA35: Yes | AB35: n/a | AC35: n/a | AD35: n/a | AE35: n/a | AF35: n/a | AG35: n/a | AH35: 777 | AI35: 33.2 | AJ35: 12-inch | AK35: Drum / Drum | AL35: CBS | AM35: LCD | AN35: Bluetooth | AO35: 2 | AP35: n/a | AQ35: n/a | AR35: Two removable 1.7 kWh packs | AS35: IP67 | AT35: 3 yr | AU35: 3 yr | AV35: VX2 | AW35: High localisation | AX35: n/a | AY35: =IF(AND(ISNUMBER($J35),ISNUMBER($M35)),$J35/$M35,"n/a") -> n/a | AZ35: =IF(AND(ISNUMBER($V35),ISNUMBER($M35)),$V35/$M35,"n/a") -> 42.941176 | BA35: =IF(NOT(ISNUMBER($J35)),"n/a",IF($J35<70000,"1. <Rs70k",IF($J35<100000,"2. Rs70k-1L",IF($J35<150000,"3. Rs1-1.5L",IF($J35<200000,"4. Rs1.5-2L",IF($J35<300000,"5. Rs2-3L","6. >Rs3L")))))) -> n/a | BB35: HIGH | BC35: vidaworld.com/compare.html | BD35: n/a | BE35: n/a
A36: S033 | B36: Hero MotoCorp | C36: Vida | D36: VX2 | E36: Plus 3.4 kWh | F36: On sale | G36: Jul-2025 | H36: Mid | I36: 110000 | J36: 120000 | K36: Aug-2026 | L36: BaaS available | M36: 3.4 | N36: Removable (2 packs) | O36: Li-ion | P36: n/a | Q36: PMSM | R36: 6 | S36: n/a | T36: 80 | U36: 3.1 | V36: 146 | W36: IDC | X36: 105 | Y36: 1000 | Z36: 62 min (0-80%) | AA36: Yes — 5,900+ points | AB36: n/a | AC36: n/a | AD36: n/a | AE36: n/a | AF36: n/a | AG36: n/a | AH36: 777 | AI36: 33.2 | AJ36: 12-inch | AK36: Disc / Drum | AL36: CBS | AM36: TFT | AN36: Bluetooth, 3 ride modes, keyless | AO36: 3 | AP36: n/a | AQ36: n/a | AR36: TFT dash, disc brake, 3 modes | AS36: IP67 | AT36: 3 yr | AU36: 3 yr | AV36: VX2 | AW36: High localisation | AX36: Volume workhorse of the Vida line | AY36: =IF(AND(ISNUMBER($J36),ISNUMBER($M36)),$J36/$M36,"n/a") -> 35294.118 | AZ36: =IF(AND(ISNUMBER($V36),ISNUMBER($M36)),$V36/$M36,"n/a") -> 42.941176 | BA36: =IF(NOT(ISNUMBER($J36)),"n/a",IF($J36<70000,"1. <Rs70k",IF($J36<100000,"2. Rs70k-1L",IF($J36<150000,"3. Rs1-1.5L",IF($J36<200000,"4. Rs1.5-2L",IF($J36<300000,"5. Rs2-3L","6. >Rs3L")))))) -> 3. Rs1-1.5L | BB36: HIGH | BC36: vidaworld.com | BD36: Autocar India (Jul-2026) | BE36: Autocar reader feedback flags AUX/app glitches and switchgear quality — a service-cost watch item.
A37: S034 | B37: Hero MotoCorp | C37: Vida | D37: VX2 | E37: Plus 4.4 kWh | F37: On sale | G37: Jul-2026 | H37: Upper-mass flagship | I37: 143990 | J37: 150990 | K37: Aug-2026 | L37: n/a | M37: 4.4 | N37: Removable (2 x 2.2 kWh) | O37: Li-ion | P37: n/a | Q37: PMSM | R37: 6 | S37: n/a | T37: 90 | U37: 3.1 | V37: 187 | W37: IDC | X37: 140 | Y37: 1000 | Z37: 65 min (0-80%) | AA37: Yes | AB37: n/a | AC37: n/a | AD37: n/a | AE37: n/a | AF37: n/a | AG37: n/a | AH37: 777 | AI37: 33.2 | AJ37: 12-inch | AK37: Disc / Drum | AL37: CBS | AM37: TFT | AN37: Bluetooth, nav, 3 modes | AO37: 3 | AP37: n/a | AQ37: n/a | AR37: Largest removable-battery pack in India; ~140 km real-world Eco per brochure | AS37: IP67 | AT37: 3 yr | AU37: 3 yr | AV37: VX2 | AW37: High localisation | AX37: Longest-range removable-battery scooter — a genuine functional niche | AY37: =IF(AND(ISNUMBER($J37),ISNUMBER($M37)),$J37/$M37,"n/a") -> 34315.909 | AZ37: =IF(AND(ISNUMBER($V37),ISNUMBER($M37)),$V37/$M37,"n/a") -> 42.5 | BA37: =IF(NOT(ISNUMBER($J37)),"n/a",IF($J37<70000,"1. <Rs70k",IF($J37<100000,"2. Rs70k-1L",IF($J37<150000,"3. Rs1-1.5L",IF($J37<200000,"4. Rs1.5-2L",IF($J37<300000,"5. Rs2-3L","6. >Rs3L")))))) -> 4. Rs1.5-2L | BB37: HIGH | BC37: Autopunditz (11-Jul-2026) | BD37: vidaworld.com/vx2-plus-electric-scooter.html | BE37: Rs1,43,990 was the 'effective' launch price inclusive of incentives; incentives lapsed 31-Jul-2026.
A38: S035 | B38: Hero MotoCorp | C38: Vida | D38: V2 | E38: Plus / Pro | F38: On sale (being phased down) | G38: 2024 | H38: Mid-premium | I38: n/a | J38: 120000 | K38: Aug-2026 | L38: n/a | M38: 3.94 | N38: Removable | O38: Li-ion | P38: n/a | Q38: PMSM | R38: 6 | S38: n/a | T38: 80 | U38: n/a | V38: 165 | W38: IDC | X38: 115 | Y38: n/a | Z38: n/a | AA38: Yes | AB38: n/a | AC38: n/a | AD38: n/a | AE38: n/a | AF38: n/a | AG38: n/a | AH38: n/a | AI38: n/a | AJ38: 12-inch | AK38: Disc / Drum | AL38: CBS | AM38: 7-inch TFT | AN38: 4G, nav, OTA | AO38: 3 | AP38: Yes | AQ38: Yes | AR38: Older-generation Vida flagship | AS38: IP67 | AT38: 3 yr | AU38: 3 yr | AV38: V2 platform | AW38: High localisation | AX38: n/a | AY38: =IF(AND(ISNUMBER($J38),ISNUMBER($M38)),$J38/$M38,"n/a") -> 30456.853 | AZ38: =IF(AND(ISNUMBER($V38),ISNUMBER($M38)),$V38/$M38,"n/a") -> 41.878173 | BA38: =IF(NOT(ISNUMBER($J38)),"n/a",IF($J38<70000,"1. <Rs70k",IF($J38<100000,"2. Rs70k-1L",IF($J38<150000,"3. Rs1-1.5L",IF($J38<200000,"4. Rs1.5-2L",IF($J38<300000,"5. Rs2-3L","6. >Rs3L")))))) -> 3. Rs1-1.5L | BB38: LOW | BC38: Aggregator listings (Aug-2026) | BD38: n/a | BE38: Superseded by VX2 range; verify current availability.
A39: S036 | B39: Honda Motor (HMSI) | C39: Honda | D39: Activa e: | E39: Standard | F39: On sale | G39: Feb-2025 | H39: Mass (swap-only) | I39: 117000 | J39: 118147 | K39: Aug-2026 | L39: Swap subscription via Honda e:Swap | M39: 3 | N39: Swappable (2 x 1.5 kWh Honda Mobile Power Pack e:) | O39: Li-ion | P39: Honda Power Pack Energy India | Q39: PMSM | R39: 6 | S39: 22 | T39: 80 | U39: 7.3 | V39: 102 | W39: IDC | X39: 75 | Y39: n/a | Z39: Swap only — no home charging | AA39: Honda e:Swap stations (Bengaluru, Delhi, Mumbai) | AB39: 118 | AC39: 1830 | AD39: 700 | AE39: 1141 | AF39: 1310 | AG39: 171 | AH39: 765 | AI39: n/a | AJ39: 12-inch | AK39: Disc / Drum | AL39: CBS | AM39: 5-inch LCD | AN39: Bluetooth | AO39: 3 | AP39: n/a | AQ39: n/a | AR39: Battery-swap-only architecture; based on Honda CUV e: global platform | AS39: n/a | AT39: 3 yr | AU39: Covered under swap subscription | AV39: Honda global e: platform | AW39: Assembled in India | AX39: Only major OEM committed to a pure swap model for personal scooters | AY39: =IF(AND(ISNUMBER($J39),ISNUMBER($M39)),$J39/$M39,"n/a") -> 39382.333 | AZ39: =IF(AND(ISNUMBER($V39),ISNUMBER($M39)),$V39/$M39,"n/a") -> 34 | BA39: =IF(NOT(ISNUMBER($J39)),"n/a",IF($J39<70000,"1. <Rs70k",IF($J39<100000,"2. Rs70k-1L",IF($J39<150000,"3. Rs1-1.5L",IF($J39<200000,"4. Rs1.5-2L",IF($J39<300000,"5. Rs2-3L","6. >Rs3L")))))) -> 3. Rs1-1.5L | BB39: HIGH | BC39: Autocar India Activa e: page (Aug-2026) | BD39: BikeDekho (Aug-2026) | BE39: Swap-only limits geography: launched only in Mumbai, Delhi, Bengaluru phase 1. Key constraint on Honda's share.
A40: S037 | B40: Honda Motor (HMSI) | C40: Honda | D40: Activa e: | E40: RoadSync Duo | F40: On sale | G40: Feb-2025 | H40: Mass (swap-only) | I40: 151000 | J40: 152747 | K40: Aug-2026 | L40: Swap subscription | M40: 3 | N40: Swappable (2 x 1.5 kWh) | O40: Li-ion | P40: Honda Power Pack Energy India | Q40: PMSM | R40: 6 | S40: 22 | T40: 80 | U40: 7.3 | V40: 102 | W40: IDC | X40: 75 | Y40: n/a | Z40: Swap only | AA40: Honda e:Swap | AB40: 118 | AC40: 1830 | AD40: 700 | AE40: 1141 | AF40: 1310 | AG40: 171 | AH40: 765 | AI40: n/a | AJ40: 12-inch | AK40: Disc / Drum | AL40: CBS | AM40: 7-inch TFT | AN40: Honda RoadSync Duo app, nav, call/SMS | AO40: 3 | AP40: n/a | AQ40: n/a | AR40: Large TFT with turn-by-turn navigation | AS40: n/a | AT40: 3 yr | AU40: Under subscription | AV40: Honda global e: platform | AW40: Assembled in India | AX40: Honda's premium connected trim | AY40: =IF(AND(ISNUMBER($J40),ISNUMBER($M40)),$J40/$M40,"n/a") -> 50915.667 | AZ40: =IF(AND(ISNUMBER($V40),ISNUMBER($M40)),$V40/$M40,"n/a") -> 34 | BA40: =IF(NOT(ISNUMBER($J40)),"n/a",IF($J40<70000,"1. <Rs70k",IF($J40<100000,"2. Rs70k-1L",IF($J40<150000,"3. Rs1-1.5L",IF($J40<200000,"4. Rs1.5-2L",IF($J40<300000,"5. Rs2-3L","6. >Rs3L")))))) -> 4. Rs1.5-2L | BB40: HIGH | BC40: Autocar India (Aug-2026) | BD40: BikeDekho (Aug-2026) | BE40: n/a
A41: S038 | B41: Honda Motor (HMSI) | C41: Honda | D41: QC1 | E41: Standard | F41: On sale | G41: Feb-2025 | H41: Entry | I41: 90022 | J41: 90022 | K41: Aug-2026 | L41: n/a | M41: 1.5 | N41: Fixed | O41: Li-ion | P41: n/a | Q41: In-wheel hub | R41: 1.8 | S41: 77 | T41: 50 | U41: n/a | V41: 80 | W41: IDC | X41: 58 | Y41: 330 | Z41: ~6h50m (0-100%) | AA41: No | AB41: 116 | AC41: 1815 | AD41: 700 | AE41: 1125 | AF41: 1300 | AG41: 170 | AH41: 765 | AI41: 26 | AJ41: 12-inch front / 10-inch rear | AK41: Drum / Drum | AL41: CBS | AM41: 5-inch LCD | AN41: Basic | AO41: 1 | AP41: n/a | AQ41: n/a | AR41: Cheapest Japanese-OEM EV in India; fixed pack, home charging | AS41: n/a | AT41: 3 yr | AU41: 3 yr | AV41: Honda entry EV platform | AW41: Assembled in India | AX41: Honda's price-point entry — low speed, low spec, brand-led | AY41: =IF(AND(ISNUMBER($J41),ISNUMBER($M41)),$J41/$M41,"n/a") -> 60014.667 | AZ41: =IF(AND(ISNUMBER($V41),ISNUMBER($M41)),$V41/$M41,"n/a") -> 53.333333 | BA41: =IF(NOT(ISNUMBER($J41)),"n/a",IF($J41<70000,"1. <Rs70k",IF($J41<100000,"2. Rs70k-1L",IF($J41<150000,"3. Rs1-1.5L",IF($J41<200000,"4. Rs1.5-2L",IF($J41<300000,"5. Rs2-3L","6. >Rs3L")))))) -> 2. Rs70k-1L | BB41: HIGH | BC41: Honda India / Autocar India | BD41: BikeDekho (Aug-2026) | BE41: 50 km/h top speed makes it a genuinely different product class from mainstream e-scooters.
A42: S039 | B42: Suzuki Motorcycle India | C42: Suzuki | D42: e-Access | E42: 3.07 kWh | F42: On sale | G42: Jan-2026 | H42: Mass | I42: n/a | J42: 188000 | K42: Aug-2026 | L42: n/a | M42: 3.07 | N42: Fixed | O42: Li-ion (LFP reported) | P42: n/a | Q42: PMSM | R42: 4.1 | S42: 15 | T42: 71 | U42: n/a | V42: 95 | W42: IDC | X42: 70 | Y42: n/a | Z42: ~2h12m (0-80%, fast charger); ~6h22m normal | AA42: Optional fast charger | AB42: 122 | AC42: 1872 | AD42: 700 | AE42: 1150 | AF42: 1265 | AG42: 160 | AH42: 765 | AI42: 17 | AJ42: 12-inch (90/90 R12 front, 100/80 R12 rear) | AK42: Disc / Drum | AL42: CBS | AM42: 4.2-inch LCD | AN42: Suzuki Ride Connect-e, Bluetooth, call/SMS alerts | AO42: 3 | AP42: n/a | AQ42: n/a | AR42: Access nameplate equity; conventional scooter ergonomics | AS42: n/a | AT42: 3 yr | AU42: 3 yr | AV42: Suzuki e-platform | AW42: Made in India (Kherki Dhaula) | AX42: Leverages the Access 125 brand — India's best-selling 125cc scooter | AY42: =IF(AND(ISNUMBER($J42),ISNUMBER($M42)),$J42/$M42,"n/a") -> 61237.785 | AZ42: =IF(AND(ISNUMBER($V42),ISNUMBER($M42)),$V42/$M42,"n/a") -> 30.944625 | BA42: =IF(NOT(ISNUMBER($J42)),"n/a",IF($J42<70000,"1. <Rs70k",IF($J42<100000,"2. Rs70k-1L",IF($J42<150000,"3. Rs1-1.5L",IF($J42<200000,"4. Rs1.5-2L",IF($J42<300000,"5. Rs2-3L","6. >Rs3L")))))) -> 4. Rs1.5-2L | BB42: MEDIUM | BC42: 91wheels specs (Aug-2026) | BD42: Autocar India comparison (Jul-2026) | BE42: PRICE FLAG: Rs1.88L is the aggregator-listed figure and looks high vs its 3 kWh / 95 km spec. Verify with Suzuki India before use.
A43: S040 | B43: Yamaha Motor India | C43: Yamaha | D43: EC-06 | E43: Standard | F43: On sale | G43: 2026 | H43: Mid-premium | I43: 167000 | J43: 172013 | K43: Aug-2026 | L43: n/a | M43: 4 | N43: Fixed | O43: Li-ion | P43: n/a | Q43: PMSM | R43: n/a | S43: n/a | T43: n/a | U43: n/a | V43: 169 | W43: IDC | X43: 120 | Y43: n/a | Z43: n/a | AA43: n/a | AB43: n/a | AC43: n/a | AD43: n/a | AE43: n/a | AF43: n/a | AG43: n/a | AH43: n/a | AI43: n/a | AJ43: 12-inch | AK43: Disc / Drum | AL43: CBS | AM43: TFT | AN43: n/a | AO43: n/a | AP43: n/a | AQ43: n/a | AR43: Assembled by River Mobility at Hoskote for Yamaha | AS43: n/a | AT43: 3 yr | AU43: 3 yr | AV43: River Indie-derived | AW43: Contract-manufactured in India | AX43: CONTRACT-MANUFACTURING PRECEDENT: a global OEM using an Indian startup's line — direct evidence that EV 2W manufacturing is outsourceable | AY43: =IF(AND(ISNUMBER($J43),ISNUMBER($M43)),$J43/$M43,"n/a") -> 43003.25 | AZ43: =IF(AND(ISNUMBER($V43),ISNUMBER($M43)),$V43/$M43,"n/a") -> 42.25 | BA43: =IF(NOT(ISNUMBER($J43)),"n/a",IF($J43<70000,"1. <Rs70k",IF($J43<100000,"2. Rs70k-1L",IF($J43<150000,"3. Rs1-1.5L",IF($J43<200000,"4. Rs1.5-2L",IF($J43<300000,"5. Rs2-3L","6. >Rs3L")))))) -> 4. Rs1.5-2L | BB43: HIGH | BC43: BikeWale price list (Aug-2026) | BD43: Autocar India (Jul-2026) | BE43: THESIS-CRITICAL: proves the powertrain/assembly barrier is low enough that Yamaha can buy rather than build.
A44: S041 | B44: River Mobility (private) | C44: River | D44: Indie | E44: Standard | F44: On sale | G44: 2023 | H44: Utility premium | I44: 125000 | J44: 146000 | K44: Aug-2026 | L44: n/a | M44: 4 | N44: Fixed | O44: Li-ion NMC | P44: Imported cells | Q44: PMSM | R44: 6.7 | S44: 26 | T44: 90 | U44: n/a | V44: 161 | W44: IDC | X44: 120 | Y44: n/a | Z44: ~5h (0-80%) | AA44: No | AB44: 124 | AC44: n/a | AD44: n/a | AE44: n/a | AF44: n/a | AG44: n/a | AH44: n/a | AI44: 43 | AJ44: 14-inch front / 12-inch rear | AK44: Disc / Drum | AL44: CBS | AM44: LCD | AN44: Bluetooth | AO44: 2 | AP44: n/a | AQ44: n/a | AR44: 43L boot expandable to 55L; metal panniers; 14-inch front wheel; 'SUV of scooters' | AS44: IP67 | AT44: 3 yr | AU44: 5 yr | AV44: River platform | AW44: Assembled at Hoskote, Karnataka | AX44: Purest utility-niche play in the market — cargo/practicality rather than range or speed | AY44: =IF(AND(ISNUMBER($J44),ISNUMBER($M44)),$J44/$M44,"n/a") -> 36500 | AZ44: =IF(AND(ISNUMBER($V44),ISNUMBER($M44)),$V44/$M44,"n/a") -> 40.25 | BA44: =IF(NOT(ISNUMBER($J44)),"n/a",IF($J44<70000,"1. <Rs70k",IF($J44<100000,"2. Rs70k-1L",IF($J44<150000,"3. Rs1-1.5L",IF($J44<200000,"4. Rs1.5-2L",IF($J44<300000,"5. Rs2-3L","6. >Rs3L")))))) -> 3. Rs1-1.5L | BB44: HIGH | BC44: ZigWheels electric scooters list (Aug-2026) | BD44: BikeWale (Aug-2026) | BE44: NICHE EXHIBIT: c.28,000 units CY2025; best-performing new entrant. Series C USD120m Nov-2025.
A45: S042 | B45: Simple Energy (private) | C45: Simple Energy | D45: One | E45: Standard | F45: On sale | G45: 2023 | H45: Long-range premium | I45: 145000 | J45: 158000 | K45: Aug-2026 | L45: n/a | M45: 5 | N45: Fixed (3.7 fixed + 1.3 removable) | O45: Li-ion | P45: n/a | Q45: Mid-drive | R45: 8.5 | S45: 72 | T45: 105 | U45: 2.77 | V45: 212 | W45: IDC | X45: 150 | Y45: n/a | Z45: n/a | AA45: n/a | AB45: 134 | AC45: n/a | AD45: n/a | AE45: n/a | AF45: n/a | AG45: n/a | AH45: n/a | AI45: 30 | AJ45: 12-inch | AK45: Disc / Disc | AL45: CBS | AM45: 7-inch touchscreen | AN45: 4G, nav, OTA | AO45: 4 | AP45: Yes | AQ45: Yes | AR45: Hybrid fixed + removable battery architecture | AS45: IP67 | AT45: 3 yr | AU45: 8 yr | AV45: Simple platform | AW45: Chamarajanagar, Karnataka | AX45: Long-range specialist | AY45: =IF(AND(ISNUMBER($J45),ISNUMBER($M45)),$J45/$M45,"n/a") -> 31600 | AZ45: =IF(AND(ISNUMBER($V45),ISNUMBER($M45)),$V45/$M45,"n/a") -> 42.4 | BA45: =IF(NOT(ISNUMBER($J45)),"n/a",IF($J45<70000,"1. <Rs70k",IF($J45<100000,"2. Rs70k-1L",IF($J45<150000,"3. Rs1-1.5L",IF($J45<200000,"4. Rs1.5-2L",IF($J45<300000,"5. Rs2-3L","6. >Rs3L")))))) -> 4. Rs1.5-2L | BB45: MEDIUM | BC45: ZigWheels (Aug-2026) | BD45: Company site | BE45: NICHE COUNTER-EXHIBIT: only c.4,806 cumulative units to Apr-2026 despite class-leading range. Spec differentiation without distribution does not scale.
A46: S043 | B46: Simple Energy | C46: Simple Energy | D46: One | E46: Ultra / Dot One | F46: On sale | G46: 2025-26 | H46: Long-range flagship / entry | I46: n/a | J46: 235000 | K46: Aug-2026 | L46: n/a | M46: 6.5 | N46: Fixed + removable | O46: Li-ion | P46: n/a | Q46: Mid-drive | R46: 8.5 | S46: 72 | T46: 105 | U46: n/a | V46: 248 | W46: IDC (400 km marketing claim) | X46: 170 | Y46: n/a | Z46: n/a | AA46: n/a | AB46: n/a | AC46: n/a | AD46: n/a | AE46: n/a | AF46: n/a | AG46: n/a | AH46: n/a | AI46: n/a | AJ46: 12-inch | AK46: Disc / Disc | AL46: CBS | AM46: 7-inch touchscreen | AN46: 4G, nav | AO46: 4 | AP46: Yes | AQ46: Yes | AR46: Highest claimed range of any Indian e-scooter | AS46: IP67 | AT46: 3 yr | AU46: 8 yr | AV46: Simple platform | AW46: n/a | AX46: Range halo — the clearest example of a spec claim not converting to volume | AY46: =IF(AND(ISNUMBER($J46),ISNUMBER($M46)),$J46/$M46,"n/a") -> 36153.846 | AZ46: =IF(AND(ISNUMBER($V46),ISNUMBER($M46)),$V46/$M46,"n/a") -> 38.153846 | BA46: =IF(NOT(ISNUMBER($J46)),"n/a",IF($J46<70000,"1. <Rs70k",IF($J46<100000,"2. Rs70k-1L",IF($J46<150000,"3. Rs1-1.5L",IF($J46<200000,"4. Rs1.5-2L",IF($J46<300000,"5. Rs2-3L","6. >Rs3L")))))) -> 5. Rs2-3L | BB46: LOW | BC46: ZigWheels / company claims | BD46: Research compilation | BE46: 400 km figure is a marketing claim, not a certified cycle number. Treat with caution.
A47: S044 | B47: Greaves Electric Mobility (Greaves Cotton, listed: GREAVESCOT) | C47: Ampere | D47: Nexus | E47: Standard / Pro | F47: On sale | G47: 2024 | H47: Mass | I47: 109900 | J47: 115000 | K47: Aug-2026 | L47: n/a | M47: 3 | N47: Fixed | O47: Li-ion LFP | P47: n/a | Q47: PMSM | R47: 4 | S47: n/a | T47: 93 | U47: n/a | V47: 136 | W47: IDC | X47: 100 | Y47: n/a | Z47: ~4h30m | AA47: No | AB47: n/a | AC47: n/a | AD47: n/a | AE47: n/a | AF47: n/a | AG47: n/a | AH47: n/a | AI47: 32 | AJ47: 12-inch | AK47: Disc / Drum | AL47: CBS | AM47: TFT | AN47: Bluetooth, nav | AO47: 3 | AP47: Yes | AQ47: n/a | AR47: LFP chemistry for cycle life; IP67 | AS47: IP67 | AT47: 3 yr | AU47: 3 yr | AV47: Nexus platform | AW47: Ranipet, Tamil Nadu | AX47: Value-mass challenger with LFP durability pitch | AY47: =IF(AND(ISNUMBER($J47),ISNUMBER($M47)),$J47/$M47,"n/a") -> 38333.333 | AZ47: =IF(AND(ISNUMBER($V47),ISNUMBER($M47)),$V47/$M47,"n/a") -> 45.333333 | BA47: =IF(NOT(ISNUMBER($J47)),"n/a",IF($J47<70000,"1. <Rs70k",IF($J47<100000,"2. Rs70k-1L",IF($J47<150000,"3. Rs1-1.5L",IF($J47<200000,"4. Rs1.5-2L",IF($J47<300000,"5. Rs2-3L","6. >Rs3L")))))) -> 3. Rs1-1.5L | BB47: MEDIUM | BC47: Greaves Electric Mobility / aggregator listings | BD47: Research compilation | BE47: FY26 61,563 units (+53%). Recovering from FAME-II subsidy clawback damage.
A48: S045 | B48: Greaves Electric Mobility | C48: Ampere | D48: Magnus EX / Magnus Neo | E48: Standard | F48: On sale | G48: 2022 | H48: Value entry | I48: n/a | J48: 80000 | K48: Aug-2026 | L48: n/a | M48: 2.3 | N48: Fixed | O48: Li-ion | P48: n/a | Q48: BLDC hub | R48: 1.2 | S48: n/a | T48: 50 | U48: n/a | V48: 100 | W48: Claimed | X48: 70 | Y48: n/a | Z48: ~5h | AA48: No | AB48: n/a | AC48: n/a | AD48: n/a | AE48: n/a | AF48: n/a | AG48: n/a | AH48: n/a | AI48: n/a | AJ48: 12-inch | AK48: Drum / Drum | AL48: CBS | AM48: LCD | AN48: Basic | AO48: 2 | AP48: n/a | AQ48: n/a | AR48: Low-speed value commuter | AS48: n/a | AT48: 3 yr | AU48: 3 yr | AV48: Magnus platform | AW48: Ranipet | AX48: Price-first value entry | AY48: =IF(AND(ISNUMBER($J48),ISNUMBER($M48)),$J48/$M48,"n/a") -> 34782.609 | AZ48: =IF(AND(ISNUMBER($V48),ISNUMBER($M48)),$V48/$M48,"n/a") -> 43.478261 | BA48: =IF(NOT(ISNUMBER($J48)),"n/a",IF($J48<70000,"1. <Rs70k",IF($J48<100000,"2. Rs70k-1L",IF($J48<150000,"3. Rs1-1.5L",IF($J48<200000,"4. Rs1.5-2L",IF($J48<300000,"5. Rs2-3L","6. >Rs3L")))))) -> 2. Rs70k-1L | BB48: LOW | BC48: Aggregator listings (Aug-2026) | BD48: n/a | BE48: Legacy first-generation product; verify current availability.
A49: S046 | B49: Kinetic Green (Firodia group, private) | C49: Kinetic Green | D49: DX / DX+ | E49: Standard | F49: On sale | G49: 2025 | H49: Mass (heritage revival) | I49: 111499 | J49: 117499 | K49: Aug-2026 | L49: n/a | M49: 2.6 | N49: Fixed | O49: Li-ion LFP | P49: n/a | Q49: BLDC hub | R49: n/a | S49: n/a | T49: 60 | U49: n/a | V49: 102 | W49: IDC | X49: 75 | Y49: n/a | Z49: n/a | AA49: No | AB49: n/a | AC49: n/a | AD49: n/a | AE49: n/a | AF49: n/a | AG49: n/a | AH49: n/a | AI49: 37 | AJ49: 12-inch | AK49: Drum / Drum | AL49: CBS | AM49: LCD | AN49: Bluetooth | AO49: 2 | AP49: Yes | AQ49: n/a | AR49: Revival of the Kinetic Honda DX nameplate; 37L boot | AS49: IP67 | AT49: 3 yr | AU49: 3 yr | AV49: DX platform | AW49: Ahmednagar, Maharashtra | AX49: Nostalgia/heritage niche — the same brand-equity play as RE Flying Flea, at the value end | AY49: =IF(AND(ISNUMBER($J49),ISNUMBER($M49)),$J49/$M49,"n/a") -> 45191.923 | AZ49: =IF(AND(ISNUMBER($V49),ISNUMBER($M49)),$V49/$M49,"n/a") -> 39.230769 | BA49: =IF(NOT(ISNUMBER($J49)),"n/a",IF($J49<70000,"1. <Rs70k",IF($J49<100000,"2. Rs70k-1L",IF($J49<150000,"3. Rs1-1.5L",IF($J49<200000,"4. Rs1.5-2L",IF($J49<300000,"5. Rs2-3L","6. >Rs3L")))))) -> 3. Rs1-1.5L | BB49: MEDIUM | BC49: Kinetic Green launch materials | BD49: Aggregator listings (Aug-2026) | BE49: NICHE EXHIBIT: tests whether heritage brand equity alone can win share without a service network.
A50: S047 | B50: BGauss (RR Global, private) | C50: BGauss | D50: RUV350 / RUV350i | E50: Standard | F50: On sale | G50: 2024 | H50: Mass | I50: 99999 | J50: 105000 | K50: Aug-2026 | L50: n/a | M50: 3.5 | N50: Fixed | O50: Li-ion | P50: n/a | Q50: BLDC hub | R50: n/a | S50: n/a | T50: 75 | U50: n/a | V50: 130 | W50: IDC | X50: 95 | Y50: n/a | Z50: n/a | AA50: No | AB50: n/a | AC50: n/a | AD50: n/a | AE50: n/a | AF50: n/a | AG50: n/a | AH50: n/a | AI50: n/a | AJ50: 12-inch | AK50: Disc / Drum | AL50: CBS | AM50: TFT | AN50: Bluetooth | AO50: 3 | AP50: Yes | AQ50: n/a | AR50: Rugged 'urban utility vehicle' styling | AS50: IP67 | AT50: 3 yr | AU50: 3 yr | AV50: RUV platform | AW50: Chakan, Maharashtra | AX50: Regional value challenger | AY50: =IF(AND(ISNUMBER($J50),ISNUMBER($M50)),$J50/$M50,"n/a") -> 30000 | AZ50: =IF(AND(ISNUMBER($V50),ISNUMBER($M50)),$V50/$M50,"n/a") -> 37.142857 | BA50: =IF(NOT(ISNUMBER($J50)),"n/a",IF($J50<70000,"1. <Rs70k",IF($J50<100000,"2. Rs70k-1L",IF($J50<150000,"3. Rs1-1.5L",IF($J50<200000,"4. Rs1.5-2L",IF($J50<300000,"5. Rs2-3L","6. >Rs3L")))))) -> 3. Rs1-1.5L | BB50: LOW | BC50: Aggregator listings (Aug-2026) | BD50: n/a | BE50: Sub-scale; structurally disadvantaged vs top-4 distribution.
A51: S048 | B51: BGauss | C51: BGauss | D51: C12i MAX | E51: Standard | F51: On sale | G51: 2023 | H51: Value | I51: n/a | J51: 95000 | K51: Aug-2026 | L51: n/a | M51: 2.6 | N51: Fixed | O51: Li-ion | P51: n/a | Q51: BLDC hub | R51: n/a | S51: n/a | T51: 60 | U51: n/a | V51: 100 | W51: Claimed | X51: 72 | Y51: n/a | Z51: n/a | AA51: No | AB51: n/a | AC51: n/a | AD51: n/a | AE51: n/a | AF51: n/a | AG51: n/a | AH51: n/a | AI51: n/a | AJ51: 12-inch | AK51: Drum / Drum | AL51: CBS | AM51: LCD | AN51: Bluetooth | AO51: 2 | AP51: n/a | AQ51: n/a | AR51: n/a | AS51: IP67 | AT51: 3 yr | AU51: 3 yr | AV51: C-series | AW51: Chakan | AX51: n/a | AY51: =IF(AND(ISNUMBER($J51),ISNUMBER($M51)),$J51/$M51,"n/a") -> 36538.462 | AZ51: =IF(AND(ISNUMBER($V51),ISNUMBER($M51)),$V51/$M51,"n/a") -> 38.461538 | BA51: =IF(NOT(ISNUMBER($J51)),"n/a",IF($J51<70000,"1. <Rs70k",IF($J51<100000,"2. Rs70k-1L",IF($J51<150000,"3. Rs1-1.5L",IF($J51<200000,"4. Rs1.5-2L",IF($J51<300000,"5. Rs2-3L","6. >Rs3L")))))) -> 2. Rs70k-1L | BB51: LOW | BC51: Aggregator listings (Aug-2026) | BD51: n/a | BE51: n/a
A52: S049 | B52: SAR Group (private) | C52: Lectrix | D52: SX25 / LXS 2.0 | E52: Standard | F52: On sale | G52: 2023 | H52: Low-speed entry | I52: n/a | J52: 67999 | K52: Aug-2026 | L52: n/a | M52: 1.5 | N52: Fixed | O52: Li-ion | P52: n/a | Q52: BLDC hub | R52: 0.25 | S52: n/a | T52: 25 | U52: n/a | V52: 60 | W52: Claimed | X52: 45 | Y52: n/a | Z52: n/a | AA52: No | AB52: n/a | AC52: n/a | AD52: n/a | AE52: n/a | AF52: n/a | AG52: n/a | AH52: n/a | AI52: n/a | AJ52: 10-inch | AK52: Drum / Drum | AL52: n/a | AM52: LCD | AN52: Basic | AO52: 1 | AP52: n/a | AQ52: n/a | AR52: Sub-250W / 25 km-h class: no licence or registration required | AS52: n/a | AT52: 2 yr | AU52: 2 yr | AV52: n/a | AW52: Hyderabad | AX52: Licence-free low-speed segment — a genuinely separate market from mainstream e-2W | AY52: =IF(AND(ISNUMBER($J52),ISNUMBER($M52)),$J52/$M52,"n/a") -> 45332.667 | AZ52: =IF(AND(ISNUMBER($V52),ISNUMBER($M52)),$V52/$M52,"n/a") -> 40 | BA52: =IF(NOT(ISNUMBER($J52)),"n/a",IF($J52<70000,"1. <Rs70k",IF($J52<100000,"2. Rs70k-1L",IF($J52<150000,"3. Rs1-1.5L",IF($J52<200000,"4. Rs1.5-2L",IF($J52<300000,"5. Rs2-3L","6. >Rs3L")))))) -> 1. <Rs70k | BB52: MEDIUM | BC52: BikeWale (cited as India's most affordable e-scooter, Aug-2026) | BD52: n/a | BE52: Low-speed sub-250W vehicles are NOT captured in Vahan registration data — a persistent gap in industry volume tracking.
A53: S050 | B53: Bounce (private) | C53: Bounce | D53: Infinity E1 / E1+ | E53: Standard | F53: On sale (limited) | G53: 2022 | H53: Value / swap | I53: n/a | J53: 79000 | K53: Aug-2026 | L53: Battery-as-a-Service from Rs36,000 + swap fee | M53: 1.9 | N53: Swappable | O53: Li-ion | P53: n/a | Q53: BLDC hub | R53: 1.5 | S53: n/a | T53: 65 | U53: n/a | V53: 85 | W53: Claimed | X53: 60 | Y53: n/a | Z53: n/a | AA53: Bounce swap network | AB53: n/a | AC53: n/a | AD53: n/a | AE53: n/a | AF53: n/a | AG53: n/a | AH53: n/a | AI53: n/a | AJ53: 12-inch | AK53: Drum / Drum | AL53: CBS | AM53: LCD | AN53: Bluetooth | AO53: 2 | AP53: n/a | AQ53: n/a | AR53: Pioneered BaaS pricing in India | AS53: n/a | AT53: 3 yr | AU53: Under BaaS | AV53: n/a | AW53: Bhiwadi, Rajasthan | AX53: BaaS pioneer — the pricing model has now been adopted by TVS and Hero | AY53: =IF(AND(ISNUMBER($J53),ISNUMBER($M53)),$J53/$M53,"n/a") -> 41578.947 | AZ53: =IF(AND(ISNUMBER($V53),ISNUMBER($M53)),$V53/$M53,"n/a") -> 44.736842 | BA53: =IF(NOT(ISNUMBER($J53)),"n/a",IF($J53<70000,"1. <Rs70k",IF($J53<100000,"2. Rs70k-1L",IF($J53<150000,"3. Rs1-1.5L",IF($J53<200000,"4. Rs1.5-2L",IF($J53<300000,"5. Rs2-3L","6. >Rs3L")))))) -> 2. Rs70k-1L | BB53: LOW | BC53: Aggregator listings / research compilation | BD53: n/a | BE53: Largely faded; its BaaS model was the durable contribution, not the product.
A54: S051 | B54: PURE EV (private) | C54: PURE EV | D54: ePluto 7G Max | E54: Standard | F54: On sale | G54: 2023 | H54: Value | I54: n/a | J54: 95000 | K54: Aug-2026 | L54: n/a | M54: 2.5 | N54: Removable | O54: Li-ion | P54: n/a | Q54: BLDC hub | R54: 2.2 | S54: n/a | T54: 60 | U54: n/a | V54: 120 | W54: Claimed | X54: 85 | Y54: n/a | Z54: n/a | AA54: No | AB54: n/a | AC54: n/a | AD54: n/a | AE54: n/a | AF54: n/a | AG54: n/a | AH54: n/a | AI54: n/a | AJ54: 12-inch | AK54: Drum / Drum | AL54: CBS | AM54: LCD | AN54: Bluetooth | AO54: 2 | AP54: n/a | AQ54: n/a | AR54: IIT-Hyderabad incubated; in-house BMS | AS54: n/a | AT54: 3 yr | AU54: 3 yr | AV54: n/a | AW54: Hyderabad | AX54: First-generation startup, now sub-scale | AY54: =IF(AND(ISNUMBER($J54),ISNUMBER($M54)),$J54/$M54,"n/a") -> 38000 | AZ54: =IF(AND(ISNUMBER($V54),ISNUMBER($M54)),$V54/$M54,"n/a") -> 48 | BA54: =IF(NOT(ISNUMBER($J54)),"n/a",IF($J54<70000,"1. <Rs70k",IF($J54<100000,"2. Rs70k-1L",IF($J54<150000,"3. Rs1-1.5L",IF($J54<200000,"4. Rs1.5-2L",IF($J54<300000,"5. Rs2-3L","6. >Rs3L")))))) -> 2. Rs70k-1L | BB54: LOW | BC54: Aggregator listings (Aug-2026) | BD54: n/a | BE54: Share collapsed post-FAME-II era; battery fire incidents damaged brand.
A55: S052 | B55: Okinawa Autotech (private) | C55: Okinawa | D55: Praise Pro / Dual100 / Okhi-90 | E55: Standard | F55: On sale (much reduced) | G55: 2019-2023 | H55: Value | I55: n/a | J55: 90000 | K55: Aug-2026 | L55: n/a | M55: 2 | N55: Removable | O55: Li-ion | P55: n/a | Q55: BLDC hub | R55: 1 | S55: n/a | T55: 58 | U55: n/a | V55: 88 | W55: Claimed | X55: 65 | Y55: n/a | Z55: n/a | AA55: No | AB55: n/a | AC55: n/a | AD55: n/a | AE55: n/a | AF55: n/a | AG55: n/a | AH55: n/a | AI55: n/a | AJ55: 12-inch | AK55: Drum / Drum | AL55: CBS | AM55: LCD | AN55: Bluetooth | AO55: 2 | AP55: n/a | AQ55: n/a | AR55: n/a | AS55: n/a | AT55: 3 yr | AU55: 3 yr | AV55: n/a | AW55: Bhiwadi, Rajasthan | AX55: FAILED-PLAYER CASE STUDY: peak-era share evaporated after FAME-II clawback and fire incidents | AY55: =IF(AND(ISNUMBER($J55),ISNUMBER($M55)),$J55/$M55,"n/a") -> 45000 | AZ55: =IF(AND(ISNUMBER($V55),ISNUMBER($M55)),$V55/$M55,"n/a") -> 44 | BA55: =IF(NOT(ISNUMBER($J55)),"n/a",IF($J55<70000,"1. <Rs70k",IF($J55<100000,"2. Rs70k-1L",IF($J55<150000,"3. Rs1-1.5L",IF($J55<200000,"4. Rs1.5-2L",IF($J55<300000,"5. Rs2-3L","6. >Rs3L")))))) -> 2. Rs70k-1L | BB55: LOW | BC55: Research compilation / MHI FAME-II proceedings | BD55: n/a | BE55: MHI committee gave a 'clean chit' Apr-2024, but commercial damage was terminal. Read across to today's sub-scale players.
A56: S053 | B56: Hero Electric (private, unrelated to Hero MotoCorp) | C56: Hero Electric | D56: Optima / Photon / NYX | E56: Standard | F56: Effectively exited | G56: 2018-2022 | H56: Value | I56: n/a | J56: n/a | K56: n.a. | L56: n/a | M56: 1.5 | N56: Removable | O56: Li-ion | P56: n/a | Q56: BLDC hub | R56: 1.2 | S56: n/a | T56: 45 | U56: n/a | V56: 82 | W56: Claimed | X56: 60 | Y56: n/a | Z56: n/a | AA56: No | AB56: n/a | AC56: n/a | AD56: n/a | AE56: n/a | AF56: n/a | AG56: n/a | AH56: n/a | AI56: n/a | AJ56: 12-inch | AK56: Drum / Drum | AL56: n/a | AM56: LCD | AN56: Basic | AO56: 2 | AP56: n/a | AQ56: n/a | AR56: n/a | AS56: n/a | AT56: n/a | AU56: n/a | AV56: n/a | AW56: Ludhiana | AX56: FAILED-PLAYER CASE STUDY: India's #1 e-2W maker in 2021-22, now effectively gone | AY56: =IF(AND(ISNUMBER($J56),ISNUMBER($M56)),$J56/$M56,"n/a") -> n/a | AZ56: =IF(AND(ISNUMBER($V56),ISNUMBER($M56)),$V56/$M56,"n/a") -> 54.666667 | BA56: =IF(NOT(ISNUMBER($J56)),"n/a",IF($J56<70000,"1. <Rs70k",IF($J56<100000,"2. Rs70k-1L",IF($J56<150000,"3. Rs1-1.5L",IF($J56<200000,"4. Rs1.5-2L",IF($J56<300000,"5. Rs2-3L","6. >Rs3L")))))) -> n/a | BB56: HIGH | BC56: MHI FAME-II show-cause proceedings (May-2023) | BD56: Inc42 / Business Today reporting | BE56: THESIS-CRITICAL: low entry barriers cut both ways — easy entry also means easy exit. >80% staff laid off post-clawback.
A57: S054 | B57: Wardwizard Innovations (listed: WARDWIZARD) | C57: Joy e-bike | D57: Mihos / Wolf+ / Gen Nxt Nanu+ | E57: Standard | F57: On sale | G57: 2021-2024 | H57: Value | I57: n/a | J57: 105000 | K57: Aug-2026 | L57: n/a | M57: 2.9 | N57: Removable | O57: Li-ion | P57: n/a | Q57: BLDC hub | R57: 2.5 | S57: n/a | T57: 75 | U57: n/a | V57: 110 | W57: Claimed | X57: 78 | Y57: n/a | Z57: n/a | AA57: No | AB57: n/a | AC57: n/a | AD57: n/a | AE57: n/a | AF57: n/a | AG57: n/a | AH57: n/a | AI57: n/a | AJ57: 12-inch | AK57: Disc / Drum | AL57: CBS | AM57: LCD | AN57: Bluetooth | AO57: 3 | AP57: n/a | AQ57: n/a | AR57: n/a | AS57: IP67 | AT57: 3 yr | AU57: 3 yr | AV57: n/a | AW57: Vadodara, Gujarat | AX57: Listed micro-cap value player | AY57: =IF(AND(ISNUMBER($J57),ISNUMBER($M57)),$J57/$M57,"n/a") -> 36206.897 | AZ57: =IF(AND(ISNUMBER($V57),ISNUMBER($M57)),$V57/$M57,"n/a") -> 37.931034 | BA57: =IF(NOT(ISNUMBER($J57)),"n/a",IF($J57<70000,"1. <Rs70k",IF($J57<100000,"2. Rs70k-1L",IF($J57<150000,"3. Rs1-1.5L",IF($J57<200000,"4. Rs1.5-2L",IF($J57<300000,"5. Rs2-3L","6. >Rs3L")))))) -> 3. Rs1-1.5L | BB57: LOW | BC57: Aggregator listings (Aug-2026) | BD57: n/a | BE57: Only listed pure-play e-2W micro-cap besides Ola and Ather.
A58: S055 | B58: Odysse Electric (private) | C58: Odysse | D58: E2Go / Vader / Snap | E58: Standard | F58: On sale | G58: 2021-2024 | H58: Value | I58: n/a | J58: 85000 | K58: Aug-2026 | L58: n/a | M58: 2 | N58: Removable | O58: Li-ion | P58: n/a | Q58: BLDC hub | R58: 1.5 | S58: n/a | T58: 60 | U58: n/a | V58: 90 | W58: Claimed | X58: 65 | Y58: n/a | Z58: n/a | AA58: No | AB58: n/a | AC58: n/a | AD58: n/a | AE58: n/a | AF58: n/a | AG58: n/a | AH58: n/a | AI58: n/a | AJ58: 12-inch | AK58: Drum / Drum | AL58: CBS | AM58: LCD | AN58: Basic | AO58: 2 | AP58: n/a | AQ58: n/a | AR58: n/a | AS58: n/a | AT58: 3 yr | AU58: 3 yr | AV58: n/a | AW58: Mumbai | AX58: n/a | AY58: =IF(AND(ISNUMBER($J58),ISNUMBER($M58)),$J58/$M58,"n/a") -> 42500 | AZ58: =IF(AND(ISNUMBER($V58),ISNUMBER($M58)),$V58/$M58,"n/a") -> 45 | BA58: =IF(NOT(ISNUMBER($J58)),"n/a",IF($J58<70000,"1. <Rs70k",IF($J58<100000,"2. Rs70k-1L",IF($J58<150000,"3. Rs1-1.5L",IF($J58<200000,"4. Rs1.5-2L",IF($J58<300000,"5. Rs2-3L","6. >Rs3L")))))) -> 2. Rs70k-1L | BB58: LOW | BC58: Aggregator listings (Aug-2026) | BD58: n/a | BE58: n/a
A59: S056 | B59: Quantum Energy / Battre / Zelio (private, various) | C59: Multiple | D59: Plasma / LOEV / Gracy (representative) | E59: Standard | F59: On sale | G59: 2021-2024 | H59: Low-speed value | I59: n/a | J59: 75000 | K59: Aug-2026 | L59: n/a | M59: 1.8 | N59: Removable | O59: Li-ion / lead-acid variants | P59: n/a | Q59: BLDC hub | R59: 1 | S59: n/a | T59: 45 | U59: n/a | V59: 80 | W59: Claimed | X59: 55 | Y59: n/a | Z59: n/a | AA59: No | AB59: n/a | AC59: n/a | AD59: n/a | AE59: n/a | AF59: n/a | AG59: n/a | AH59: n/a | AI59: n/a | AJ59: 10/12-inch | AK59: Drum / Drum | AL59: n/a | AM59: LCD | AN59: Basic | AO59: 1 | AP59: n/a | AQ59: n/a | AR59: Representative row for the fragmented regional low-speed tail | AS59: n/a | AT59: 1-3 yr | AU59: 1-3 yr | AV59: n/a | AW59: Various (Hyderabad, Gurugram, Hisar) | AX59: LONG-TAIL EXHIBIT: dozens of sub-scale brands exist because entry barriers are near-zero — and none has scaled | AY59: =IF(AND(ISNUMBER($J59),ISNUMBER($M59)),$J59/$M59,"n/a") -> 41666.667 | AZ59: =IF(AND(ISNUMBER($V59),ISNUMBER($M59)),$V59/$M59,"n/a") -> 44.444444 | BA59: =IF(NOT(ISNUMBER($J59)),"n/a",IF($J59<70000,"1. <Rs70k",IF($J59<100000,"2. Rs70k-1L",IF($J59<150000,"3. Rs1-1.5L",IF($J59<200000,"4. Rs1.5-2L",IF($J59<300000,"5. Rs2-3L","6. >Rs3L")))))) -> 2. Rs70k-1L | BB59: LOW | BC59: Aggregator listings / industry compilation | BD59: n/a | BE59: THESIS SUPPORT: the sheer number of these brands is the strongest evidence for low entry barriers; their collective irrelevance is the strongest evidence that distribution is the real moat.
A60: S057 | B60: Ultraviolette (private) | C60: Ultraviolette | D60: Tesseract | E60: Standard (pre-book) | F60: Pre-launch (bookings open) | G60: Deliveries Q1-2027 (guided) | H60: Premium maxi-scooter | I60: 120000 | J60: n/a | K60: Aug-2026 | L60: n/a | M60: 6 | N60: Fixed | O60: Li-ion | P60: In-house SRB pack | Q60: PMSM | R60: 14 | S60: n/a | T60: 125 | U60: 2.9 | V60: 261 | W60: IDC | X60: 180 | Y60: n/a | Z60: n/a | AA60: Yes | AB60: n/a | AC60: n/a | AD60: n/a | AE60: n/a | AF60: n/a | AG60: n/a | AH60: n/a | AI60: 34 | AJ60: 14-inch | AK60: Disc / Disc | AL60: Dual-channel | AM60: Touchscreen | AN60: 4G, nav, OTA | AO60: 4 | AP60: Yes | AQ60: Yes | AR60: 100V architecture; radar-based blind-spot detection and forward-collision warning (segment first) | AS60: n/a | AT60: 3 yr | AU60: 5 yr / 100,000 km | AV60: UV 100V platform | AW60: Bengaluru | AX60: Radar/ADAS-style features on a scooter — a genuine technology differentiation attempt | AY60: =IF(AND(ISNUMBER($J60),ISNUMBER($M60)),$J60/$M60,"n/a") -> n/a | AZ60: =IF(AND(ISNUMBER($V60),ISNUMBER($M60)),$V60/$M60,"n/a") -> 43.5 | BA60: =IF(NOT(ISNUMBER($J60)),"n/a",IF($J60<70000,"1. <Rs70k",IF($J60<100000,"2. Rs70k-1L",IF($J60<150000,"3. Rs1-1.5L",IF($J60<200000,"4. Rs1.5-2L",IF($J60<300000,"5. Rs2-3L","6. >Rs3L")))))) -> n/a | BB60: MEDIUM | BC60: ultraviolette.com (Q1 2027 shown) | BD60: Autocar India (Jun-2026) | BE60: Timing has ALREADY SLIPPED from Q1-2026 to Q1-2027. >70,000 pre-bookings reported. Do not model volumes before FY28.
A61: S058 | B61: BMW Motorrad (import) | C61: BMW | D61: CE 04 | E61: Standard | F61: On sale (CBU import) | G61: 2023 | H61: Ultra-premium import | I61: 1490000 | J61: 1890000 | K61: Aug-2026 | L61: n/a | M61: 8.9 | N61: Fixed | O61: Li-ion | P61: n/a | Q61: Liquid-cooled PMSM | R61: 31 | S61: 62 | T61: 120 | U61: 2.6 | V61: 130 | W61: WMTC | X61: 110 | Y61: n/a | Z61: ~1h40m (fast charge 0-80%) | AA61: Yes | AB61: 231 | AC61: n/a | AD61: n/a | AE61: n/a | AF61: 1675 | AG61: n/a | AH61: 780 | AI61: n/a | AJ61: 15/14-inch | AK61: Disc / Disc | AL61: Dual-channel ABS | AM61: 10.25-inch TFT | AN61: Connected, nav | AO61: 3 | AP61: Yes | AQ61: Yes | AR61: Halo import; defines the ceiling of the Indian e-scooter price ladder | AS61: n/a | AT61: 3 yr | AU61: 3 yr | AV61: BMW CE platform | AW61: CBU import | AX61: Price-ceiling reference point — shows how empty the >Rs3L scooter band is | AY61: =IF(AND(ISNUMBER($J61),ISNUMBER($M61)),$J61/$M61,"n/a") -> 212359.55 | AZ61: =IF(AND(ISNUMBER($V61),ISNUMBER($M61)),$V61/$M61,"n/a") -> 14.606742 | BA61: =IF(NOT(ISNUMBER($J61)),"n/a",IF($J61<70000,"1. <Rs70k",IF($J61<100000,"2. Rs70k-1L",IF($J61<150000,"3. Rs1-1.5L",IF($J61<200000,"4. Rs1.5-2L",IF($J61<300000,"5. Rs2-3L","6. >Rs3L")))))) -> 6. >Rs3L | BB61: MEDIUM | BC61: BikeWale (Aug-2026) | BD61: BMW Motorrad India | BE61: Negligible volume. Included as a price-band anchor, not as a competitor.

Sheet Motorcycles_Current
A1: ELECTRIC MOTORCYCLES — INDIA MODEL MASTER (VARIANT LEVEL)
A2: 29 variants, 14 brands. E-motorcycles are under 5 per cent of e-2W volume — this is a niche market, not a mass one. Data as of 25-Aug-2026.
A3: ID | B3: OEM / parent | C3: Brand | D3: Model | E3: Variant | F3: Status | G3: Launch (M-Y) | H3: Positioning tier | I3: Price at launch (Rs, ex-shwr) | J3: Price latest (Rs, ex-shwr Delhi) | K3: Price as-of | L3: BaaS / subscription price | M3: Battery (kWh) | N3: Battery type | O3: Chemistry | P3: Cell sourcing | Q3: Motor type / drive | R3: Peak power (kW) | S3: Torque (Nm) | T3: Top speed (km/h) | U3: 0-40 km/h (s) | V3: Claimed range (km) | W3: Range cycle | X3: Real-world range est. (km) | Y3: Charger (W) | Z3: Charge time 0-80% | AA3: Fast charge / network | AB3: Kerb weight (kg) | AC3: Length (mm) | AD3: Width (mm) | AE3: Height (mm) | AF3: Wheelbase (mm) | AG3: Ground clearance (mm) | AH3: Seat height (mm) | AI3: Transmission | AJ3: Wheels / tyres | AK3: Brakes (F/R) | AL3: ABS / CBS | AM3: Display | AN3: Connectivity | AO3: Ride modes | AP3: Reverse | AQ3: OTA updates | AR3: Other key features | AS3: IP rating | AT3: Vehicle warranty | AU3: Battery warranty | AV3: Platform | AW3: Manufacturing / localisation | AX3: Key differentiator | AY3: Rs per kWh (calc) | AZ3: km per kWh (calc) | BA3: Price band (calc) | BB3: Data confidence | BC3: Source 1 | BD3: Source 2 | BE3: Analyst notes
A4: M001 | B4: Ultraviolette Automotive (private) | C4: Ultraviolette | D4: F77 Mach 2 / SuperStreet | E4: Original 7.1 kWh | F4: On sale | G4: 2024 (Mach 2 update) | H4: Performance flagship | I4: 299000 | J4: 309000 | K4: Aug-2026 | L4: n/a | M4: 7.1 | N4: Fixed | O4: Li-ion NMC cylindrical | P4: In-house SRB-10 pack; imported cells | Q4: PMSM, chain drive | R4: 27 | S4: 100 | T4: 155 | U4: 2.9 | V4: 211 | W4: IDC | X4: 150 | Y4: n/a | Z4: ~1h30m (fast); ~5h (std) | AA4: UV Supernova DC fast-charging network | AB4: 207 | AC4: n/a | AD4: n/a | AE4: n/a | AF4: 1380 | AG4: n/a | AH4: 800 | AI4: Manual (single speed) | AJ4: 17-inch alloy | AK4: Disc / Disc | AL4: Dual-channel ABS | AM4: TFT with 4G | AN4: 4G, nav, OTA, telemetry | AO4: 4 | AP4: Yes | AQ4: Yes | AR4: 10 levels regen, 4-level traction control, ballistic ride modes, aviation-derived drivetrain | AS4: IP67 | AT4: 3 yr | AU4: 5 yr / 100,000 km | AV4: F77 platform | AW4: Bengaluru; exports to Central Europe | AX4: India's most credible performance-EV brand; genuine premium price realisation | AY4: =IF(AND(ISNUMBER($J4),ISNUMBER($M4)),$J4/$M4,"n/a") -> 43521.127 | AZ4: =IF(AND(ISNUMBER($V4),ISNUMBER($M4)),$V4/$M4,"n/a") -> 29.71831 | BA4: =IF(NOT(ISNUMBER($J4)),"n/a",IF($J4<70000,"1. <Rs70k",IF($J4<100000,"2. Rs70k-1L",IF($J4<150000,"3. Rs1-1.5L",IF($J4<200000,"4. Rs1.5-2L",IF($J4<300000,"5. Rs2-3L","6. >Rs3L")))))) -> 6. >Rs3L | BB4: HIGH | BC4: ultraviolette.com/f77 (Aug-2026) | BD4: BikeDekho / ZigWheels (Aug-2026) | BE4: NICHE EXHIBIT #1: sustains a Rs3L+ ASP. Raised USD45m Series E (Zoho, Lingotto) Dec-2025.
A5: M002 | B5: Ultraviolette | C5: Ultraviolette | D5: F77 Mach 2 / SuperStreet | E5: Recon 10.3 kWh | F5: On sale | G5: 2024 | H5: Performance flagship | I5: n/a | J5: 424000 | K5: Aug-2026 | L5: n/a | M5: 10.3 | N5: Fixed | O5: Li-ion NMC cylindrical | P5: In-house SRB-10 pack | Q5: PMSM, chain drive | R5: 30 | S5: 100 | T5: 155 | U5: 2.8 | V5: 323 | W5: IDC (WMTC 231 km) | X5: 210 | Y5: n/a | Z5: ~1h30m (fast) | AA5: UV Supernova network | AB5: 207 | AC5: n/a | AD5: n/a | AE5: n/a | AF5: 1380 | AG5: n/a | AH5: 800 | AI5: Manual (single speed) | AJ5: 17-inch alloy | AK5: Disc / Disc | AL5: Dual-channel ABS | AM5: TFT | AN5: 4G, nav, OTA | AO5: 4 | AP5: Yes | AQ5: Yes | AR5: Largest battery in any Indian e-motorcycle; 800,000 km battery-warranty marketing claim | AS5: IP67 | AT5: 3 yr | AU5: 5 yr / 100,000 km | AV5: F77 platform | AW5: Bengaluru | AX5: Longest-range electric motorcycle sold in India | AY5: =IF(AND(ISNUMBER($J5),ISNUMBER($M5)),$J5/$M5,"n/a") -> 41165.049 | AZ5: =IF(AND(ISNUMBER($V5),ISNUMBER($M5)),$V5/$M5,"n/a") -> 31.359223 | BA5: =IF(NOT(ISNUMBER($J5)),"n/a",IF($J5<70000,"1. <Rs70k",IF($J5<100000,"2. Rs70k-1L",IF($J5<150000,"3. Rs1-1.5L",IF($J5<200000,"4. Rs1.5-2L",IF($J5<300000,"5. Rs2-3L","6. >Rs3L")))))) -> 6. >Rs3L | BB5: HIGH | BC5: ultraviolette.com | BD5: BikeDekho (Aug-2026) | BE5: WMTC 231 km is the credible number; 323 km is IDC. Use WMTC for range comparisons vs global peers.
A6: M003 | B6: Ultraviolette | C6: Ultraviolette | D6: X47 Crossover | E6: Standard | F6: On sale | G6: 2025 | H6: Premium crossover | I6: 249000 | J6: 249000 | K6: Aug-2026 | L6: n/a | M6: 7.1 | N6: Fixed | O6: Li-ion | P6: In-house SRB pack | Q6: PMSM, chain drive | R6: 27 | S6: 100 | T6: 145 | U6: n/a | V6: 211 | W6: IDC | X6: 150 | Y6: n/a | Z6: ~1h30m (fast) | AA6: UV Supernova | AB6: n/a | AC6: n/a | AD6: n/a | AE6: n/a | AF6: n/a | AG6: n/a | AH6: n/a | AI6: Manual (single speed) | AJ6: 17-inch | AK6: Disc / Disc | AL6: Dual-channel ABS | AM6: TFT | AN6: 4G, nav, OTA | AO6: 4 | AP6: Yes | AQ6: Yes | AR6: Crossover ergonomics on the F77 powertrain — platform reuse to widen TAM | AS6: IP67 | AT6: 3 yr | AU6: 5 yr / 100,000 km | AV6: F77 platform | AW6: Bengaluru | AX6: Platform leverage: same powertrain, new body style, new price point | AY6: =IF(AND(ISNUMBER($J6),ISNUMBER($M6)),$J6/$M6,"n/a") -> 35070.423 | AZ6: =IF(AND(ISNUMBER($V6),ISNUMBER($M6)),$V6/$M6,"n/a") -> 29.71831 | BA6: =IF(NOT(ISNUMBER($J6)),"n/a",IF($J6<70000,"1. <Rs70k",IF($J6<100000,"2. Rs70k-1L",IF($J6<150000,"3. Rs1-1.5L",IF($J6<200000,"4. Rs1.5-2L",IF($J6<300000,"5. Rs2-3L","6. >Rs3L")))))) -> 5. Rs2-3L | BB6: HIGH | BC6: BikeDekho / ZigWheels (Aug-2026) | BD6: ultraviolette.com | BE6: n/a
A7: M004 | B7: Ola Electric (listed: OLAELEC) | C7: Ola Electric | D7: Roadster X | E7: 2.5 kWh | F7: On sale | G7: 2025 | H7: Entry commuter | I7: 74999 | J7: 79999 | K7: Aug-2026 | L7: n/a | M7: 2.5 | N7: Fixed | O7: Li-ion | P7: n/a | Q7: Mid-drive IPM, chain | R7: 7 | S7: n/a | T7: 105 | U7: n/a | V7: 117 | W7: IDC | X7: 80 | Y7: n/a | Z7: n/a | AA7: Ola Hypercharger | AB7: n/a | AC7: n/a | AD7: n/a | AE7: n/a | AF7: n/a | AG7: n/a | AH7: n/a | AI7: Single speed | AJ7: 17-inch | AK7: Disc / Drum | AL7: CBS | AM7: 4.3-inch LCD | AN7: MoveOS, Bluetooth | AO7: 3 | AP7: Yes | AQ7: Yes | AR7: Cheapest electric motorcycle from a top-5 OEM | AS7: IP67 | AT7: 3 yr | AU7: 3 yr | AV7: Roadster platform | AW7: Krishnagiri, Tamil Nadu | AX7: Aggressive price anchor for the e-motorcycle segment | AY7: =IF(AND(ISNUMBER($J7),ISNUMBER($M7)),$J7/$M7,"n/a") -> 31999.6 | AZ7: =IF(AND(ISNUMBER($V7),ISNUMBER($M7)),$V7/$M7,"n/a") -> 46.8 | BA7: =IF(NOT(ISNUMBER($J7)),"n/a",IF($J7<70000,"1. <Rs70k",IF($J7<100000,"2. Rs70k-1L",IF($J7<150000,"3. Rs1-1.5L",IF($J7<200000,"4. Rs1.5-2L",IF($J7<300000,"5. Rs2-3L","6. >Rs3L")))))) -> 2. Rs70k-1L | BB7: MEDIUM | BC7: Ola Electric price list (Aug-2026) | BD7: Research compilation | BE7: Ola claims c.50% of India's e-motorcycle segment — but the segment itself is <5% of e-2W volume.
A8: M005 | B8: Ola Electric | C8: Ola Electric | D8: Roadster X | E8: 3.5 kWh | F8: On sale | G8: 2025 | H8: Entry-mid commuter | I8: n/a | J8: 94999 | K8: Aug-2026 | L8: n/a | M8: 3.5 | N8: Fixed | O8: Li-ion | P8: n/a | Q8: Mid-drive IPM, chain | R8: 8.5 | S8: n/a | T8: 118 | U8: n/a | V8: 163 | W8: IDC | X8: 110 | Y8: n/a | Z8: n/a | AA8: Ola Hypercharger | AB8: n/a | AC8: n/a | AD8: n/a | AE8: n/a | AF8: n/a | AG8: n/a | AH8: n/a | AI8: Single speed | AJ8: 17-inch | AK8: Disc / Drum | AL8: CBS | AM8: 4.3-inch LCD | AN8: MoveOS | AO8: 3 | AP8: Yes | AQ8: Yes | AR8: n/a | AS8: IP67 | AT8: 3 yr | AU8: 3 yr | AV8: Roadster platform | AW8: Krishnagiri | AX8: n/a | AY8: =IF(AND(ISNUMBER($J8),ISNUMBER($M8)),$J8/$M8,"n/a") -> 27142.571 | AZ8: =IF(AND(ISNUMBER($V8),ISNUMBER($M8)),$V8/$M8,"n/a") -> 46.571429 | BA8: =IF(NOT(ISNUMBER($J8)),"n/a",IF($J8<70000,"1. <Rs70k",IF($J8<100000,"2. Rs70k-1L",IF($J8<150000,"3. Rs1-1.5L",IF($J8<200000,"4. Rs1.5-2L",IF($J8<300000,"5. Rs2-3L","6. >Rs3L")))))) -> 2. Rs70k-1L | BB8: MEDIUM | BC8: Ola Electric price list (Aug-2026) | BD8: n/a | BE8: n/a
A9: M006 | B9: Ola Electric | C9: Ola Electric | D9: Roadster X | E9: 4.5 kWh | F9: On sale | G9: 2025 | H9: Mid commuter | I9: n/a | J9: 114999 | K9: Aug-2026 | L9: n/a | M9: 4.5 | N9: Fixed | O9: Li-ion | P9: n/a | Q9: Mid-drive IPM, chain | R9: 11 | S9: n/a | T9: 125 | U9: n/a | V9: 208 | W9: IDC | X9: 140 | Y9: n/a | Z9: n/a | AA9: Ola Hypercharger | AB9: n/a | AC9: n/a | AD9: n/a | AE9: n/a | AF9: n/a | AG9: n/a | AH9: n/a | AI9: Single speed | AJ9: 17-inch | AK9: Disc / Disc | AL9: CBS | AM9: 4.3-inch LCD | AN9: MoveOS | AO9: 3 | AP9: Yes | AQ9: Yes | AR9: n/a | AS9: IP67 | AT9: 3 yr | AU9: 3 yr | AV9: Roadster platform | AW9: Krishnagiri | AX9: n/a | AY9: =IF(AND(ISNUMBER($J9),ISNUMBER($M9)),$J9/$M9,"n/a") -> 25555.333 | AZ9: =IF(AND(ISNUMBER($V9),ISNUMBER($M9)),$V9/$M9,"n/a") -> 46.222222 | BA9: =IF(NOT(ISNUMBER($J9)),"n/a",IF($J9<70000,"1. <Rs70k",IF($J9<100000,"2. Rs70k-1L",IF($J9<150000,"3. Rs1-1.5L",IF($J9<200000,"4. Rs1.5-2L",IF($J9<300000,"5. Rs2-3L","6. >Rs3L")))))) -> 3. Rs1-1.5L | BB9: MEDIUM | BC9: Ola Electric price list (Aug-2026) | BD9: n/a | BE9: n/a
A10: M007 | B10: Ola Electric | C10: Ola Electric | D10: Roadster X+ | E10: 4.5 kWh | F10: On sale | G10: 2025 | H10: Premium commuter | I10: n/a | J10: 149999 | K10: Aug-2026 | L10: n/a | M10: 4.5 | N10: Fixed | O10: Li-ion | P10: n/a | Q10: Mid-drive IPM, chain | R10: 11 | S10: n/a | T10: 125 | U10: n/a | V10: 208 | W10: IDC | X10: 140 | Y10: n/a | Z10: n/a | AA10: Ola Hypercharger | AB10: n/a | AC10: n/a | AD10: n/a | AE10: n/a | AF10: n/a | AG10: n/a | AH10: n/a | AI10: Single speed | AJ10: 17-inch | AK10: Disc / Disc | AL10: Dual-channel | AM10: 6.8-inch TFT touchscreen | AN10: MoveOS 5, 4G, nav | AO10: 4 | AP10: Yes | AQ10: Yes | AR10: Touchscreen TFT, cruise control | AS10: IP67 | AT10: 3 yr | AU10: 3 yr | AV10: Roadster platform | AW10: Krishnagiri | AX10: n/a | AY10: =IF(AND(ISNUMBER($J10),ISNUMBER($M10)),$J10/$M10,"n/a") -> 33333.111 | AZ10: =IF(AND(ISNUMBER($V10),ISNUMBER($M10)),$V10/$M10,"n/a") -> 46.222222 | BA10: =IF(NOT(ISNUMBER($J10)),"n/a",IF($J10<70000,"1. <Rs70k",IF($J10<100000,"2. Rs70k-1L",IF($J10<150000,"3. Rs1-1.5L",IF($J10<200000,"4. Rs1.5-2L",IF($J10<300000,"5. Rs2-3L","6. >Rs3L")))))) -> 3. Rs1-1.5L | BB10: MEDIUM | BC10: Ola Electric price list (Aug-2026) | BD10: n/a | BE10: n/a
A11: M008 | B11: Ola Electric | C11: Ola Electric | D11: Roadster X+ | E11: 9.1 kWh (4680 Bharat Cell) | F11: On sale | G11: 2025 (repriced at Sankalp 2025) | H11: Premium performance | I11: n/a | J11: 190000 | K11: Aug-2026 | L11: n/a | M11: 9.1 | N11: Fixed | O11: Li-ion 4680 cylindrical | P11: Ola in-house 4680 Bharat Cell | Q11: Mid-drive IPM (ferrite, rare-earth-free), chain | R11: 11 | S11: n/a | T11: 125 | U11: n/a | V11: 320 | W11: IDC | X11: 200 | Y11: n/a | Z11: n/a | AA11: Ola Hypercharger | AB11: n/a | AC11: n/a | AD11: n/a | AE11: n/a | AF11: n/a | AG11: n/a | AH11: n/a | AI11: Single speed | AJ11: 17-inch | AK11: Disc / Disc | AL11: Dual-channel | AM11: 6.8-inch TFT touchscreen | AN11: MoveOS 5, 4G, nav, OTA | AO11: 4 | AP11: Yes | AQ11: Yes | AR11: First mass-produced Indian vehicle on an indigenously-made 4680 cell | AS11: IP67 | AT11: 3 yr | AU11: 3 yr | AV11: Roadster platform | AW11: Krishnagiri gigafactory (c.2.5 GWh operational) | AX11: Ola's showcase for vertical integration — cell, motor and vehicle all in-house | AY11: =IF(AND(ISNUMBER($J11),ISNUMBER($M11)),$J11/$M11,"n/a") -> 20879.121 | AZ11: =IF(AND(ISNUMBER($V11),ISNUMBER($M11)),$V11/$M11,"n/a") -> 35.164835 | BA11: =IF(NOT(ISNUMBER($J11)),"n/a",IF($J11<70000,"1. <Rs70k",IF($J11<100000,"2. Rs70k-1L",IF($J11<150000,"3. Rs1-1.5L",IF($J11<200000,"4. Rs1.5-2L",IF($J11<300000,"5. Rs2-3L","6. >Rs3L")))))) -> 4. Rs1.5-2L | BB11: MEDIUM | BC11: Ola Sankalp 2025 | BD11: Research compilation | BE11: THESIS-CRITICAL: the most vertically-integrated product in India, from the OEM losing the most share.
A12: M009 | B12: Ola Electric | C12: Ola Electric | D12: Roadster / Roadster Pro | E12: Announced range | F12: Announced, limited availability | G12: 2025-26 | H12: Performance | I12: n/a | J12: n/a | K12: Aug-2026 | L12: n/a | M12: 16 | N12: Fixed | O12: Li-ion | P12: n/a | Q12: Mid-drive | R12: n/a | S12: n/a | T12: 194 | U12: 1.2 | V12: 579 | W12: IDC (claim) | X12: n/a | Y12: n/a | Z12: n/a | AA12: Ola Hypercharger | AB12: n/a | AC12: n/a | AD12: n/a | AE12: n/a | AF12: n/a | AG12: n/a | AH12: n/a | AI12: Single speed | AJ12: 17-inch | AK12: Disc / Disc | AL12: Dual-channel | AM12: TFT | AN12: MoveOS | AO12: 4 | AP12: Yes | AQ12: Yes | AR12: n/a | AS12: n/a | AT12: 3 yr | AU12: 3 yr | AV12: Roadster platform | AW12: Krishnagiri | AX12: Halo/concept-grade claims; treat volumes as zero until deliveries are verified | AY12: =IF(AND(ISNUMBER($J12),ISNUMBER($M12)),$J12/$M12,"n/a") -> n/a | AZ12: =IF(AND(ISNUMBER($V12),ISNUMBER($M12)),$V12/$M12,"n/a") -> 36.1875 | BA12: =IF(NOT(ISNUMBER($J12)),"n/a",IF($J12<70000,"1. <Rs70k",IF($J12<100000,"2. Rs70k-1L",IF($J12<150000,"3. Rs1-1.5L",IF($J12<200000,"4. Rs1.5-2L",IF($J12<300000,"5. Rs2-3L","6. >Rs3L")))))) -> n/a | BB12: LOW | BC12: Ola announcements (2024-25) | BD12: Research compilation | BE12: SPECULATIVE: repeatedly delayed. Do not model. 579 km claim is not a certified figure.
A13: M010 | B13: Revolt Motors (RattanIndia Enterprises, listed: RTNINDIA) | C13: Revolt | D13: RV400 | E13: Standard | F13: On sale | G13: 2019 (updates through 2025) | H13: Commuter | I13: n/a | J13: 142934 | K13: Aug-2026 | L13: n/a | M13: 3.24 | N13: Removable | O13: Li-ion | P13: n/a | Q13: Mid-drive, belt | R13: 3 | S13: 54 | T13: 85 | U13: n/a | V13: 150 | W13: IDC | X13: 110 | Y13: n/a | Z13: ~4h30m (0-80%) | AA13: No | AB13: 108 | AC13: 2043 | AD13: 806 | AE13: 1100 | AF13: 1350 | AG13: 215 | AH13: 814 | AI13: Single speed | AJ13: 17-inch | AK13: Disc / Disc | AL13: CBS | AM13: LCD | AN13: 4G, app connectivity, geofencing | AO13: 3 | AP13: n/a | AQ13: Yes | AR13: Artificial exhaust sound (4 selectable); removable battery; India's first e-motorcycle at scale | AS13: n/a | AT13: 5 yr / 75,000 km | AU13: 5 yr / 75,000 km | AV13: RV platform | AW13: Manesar, Haryana | AX13: First-mover in Indian e-motorcycles; commuter positioning | AY13: =IF(AND(ISNUMBER($J13),ISNUMBER($M13)),$J13/$M13,"n/a") -> 44115.432 | AZ13: =IF(AND(ISNUMBER($V13),ISNUMBER($M13)),$V13/$M13,"n/a") -> 46.296296 | BA13: =IF(NOT(ISNUMBER($J13)),"n/a",IF($J13<70000,"1. <Rs70k",IF($J13<100000,"2. Rs70k-1L",IF($J13<150000,"3. Rs1-1.5L",IF($J13<200000,"4. Rs1.5-2L",IF($J13<300000,"5. Rs2-3L","6. >Rs3L")))))) -> 3. Rs1-1.5L | BB13: HIGH | BC13: BikeWale (Aug-2026) | BD13: 91wheels comparison (Aug-2026) | BE13: Was named in the MHI FAME-II localisation show-cause notices (May-2023).
A14: M011 | B14: Revolt Motors | C14: Revolt | D14: RV400 BRZ | E14: Standard | F14: On sale | G14: 2023 | H14: Commuter value | I14: n/a | J14: 129950 | K14: Aug-2026 | L14: n/a | M14: 3.24 | N14: Removable | O14: Li-ion | P14: n/a | Q14: Mid-drive, belt | R14: 3 | S14: 54 | T14: 85 | U14: n/a | V14: 150 | W14: IDC | X14: 110 | Y14: n/a | Z14: ~4h30m | AA14: No | AB14: 108 | AC14: 2043 | AD14: 806 | AE14: 1100 | AF14: 1350 | AG14: 215 | AH14: 814 | AI14: Single speed | AJ14: 17-inch | AK14: Disc / Disc | AL14: CBS | AM14: LCD | AN14: 4G, app | AO14: 3 | AP14: n/a | AQ14: Yes | AR14: De-contented RV400 for price | AS14: n/a | AT14: 5 yr / 75,000 km | AU14: 5 yr / 75,000 km | AV14: RV platform | AW14: Manesar | AX14: n/a | AY14: =IF(AND(ISNUMBER($J14),ISNUMBER($M14)),$J14/$M14,"n/a") -> 40108.025 | AZ14: =IF(AND(ISNUMBER($V14),ISNUMBER($M14)),$V14/$M14,"n/a") -> 46.296296 | BA14: =IF(NOT(ISNUMBER($J14)),"n/a",IF($J14<70000,"1. <Rs70k",IF($J14<100000,"2. Rs70k-1L",IF($J14<150000,"3. Rs1-1.5L",IF($J14<200000,"4. Rs1.5-2L",IF($J14<300000,"5. Rs2-3L","6. >Rs3L")))))) -> 3. Rs1-1.5L | BB14: HIGH | BC14: ZigWheels / BikeDekho (Aug-2026) | BD14: n/a | BE14: n/a
A15: M012 | B15: Revolt Motors | C15: Revolt | D15: RVX / RVX Pro | E15: Standard | F15: On sale | G15: 2025 | H15: Commuter | I15: 124000 | J15: 132000 | K15: Aug-2026 | L15: n/a | M15: 3.24 | N15: Removable | O15: Li-ion | P15: n/a | Q15: Mid-drive, belt | R15: 4.5 | S15: n/a | T15: 90 | U15: n/a | V15: 150 | W15: IDC | X15: 110 | Y15: n/a | Z15: ~4h | AA15: No | AB15: n/a | AC15: n/a | AD15: n/a | AE15: n/a | AF15: n/a | AG15: n/a | AH15: n/a | AI15: Single speed | AJ15: 17-inch | AK15: Disc / Disc | AL15: CBS | AM15: TFT | AN15: 4G, nav, app | AO15: 3 | AP15: n/a | AQ15: Yes | AR15: Refreshed platform with TFT | AS15: n/a | AT15: 5 yr / 75,000 km | AU15: 5 yr | AV15: RV platform | AW15: Manesar | AX15: n/a | AY15: =IF(AND(ISNUMBER($J15),ISNUMBER($M15)),$J15/$M15,"n/a") -> 40740.741 | AZ15: =IF(AND(ISNUMBER($V15),ISNUMBER($M15)),$V15/$M15,"n/a") -> 46.296296 | BA15: =IF(NOT(ISNUMBER($J15)),"n/a",IF($J15<70000,"1. <Rs70k",IF($J15<100000,"2. Rs70k-1L",IF($J15<150000,"3. Rs1-1.5L",IF($J15<200000,"4. Rs1.5-2L",IF($J15<300000,"5. Rs2-3L","6. >Rs3L")))))) -> 3. Rs1-1.5L | BB15: MEDIUM | BC15: Research compilation / launch reporting (2025) | BD15: n/a | BE15: n/a
A16: M013 | B16: Revolt Motors | C16: Revolt | D16: RV1 | E16: Standard | F16: On sale | G16: 2024 | H16: Entry commuter | I16: 84990 | J16: 95000 | K16: Aug-2026 | L16: n/a | M16: 2.2 | N16: Removable | O16: Li-ion | P16: n/a | Q16: Mid-drive, belt | R16: 3 | S16: n/a | T16: 70 | U16: n/a | V16: 100 | W16: IDC | X16: 72 | Y16: n/a | Z16: ~3h30m | AA16: No | AB16: n/a | AC16: n/a | AD16: n/a | AE16: n/a | AF16: n/a | AG16: n/a | AH16: n/a | AI16: Single speed | AJ16: 17-inch | AK16: Disc / Drum | AL16: CBS | AM16: LCD | AN16: 4G, app | AO16: 2 | AP16: n/a | AQ16: n/a | AR16: Sub-Rs1L electric motorcycle | AS16: n/a | AT16: 5 yr / 75,000 km | AU16: 5 yr | AV16: RV1 platform | AW16: Manesar | AX16: Price-led attack on the 100-125cc ICE commuter segment | AY16: =IF(AND(ISNUMBER($J16),ISNUMBER($M16)),$J16/$M16,"n/a") -> 43181.818 | AZ16: =IF(AND(ISNUMBER($V16),ISNUMBER($M16)),$V16/$M16,"n/a") -> 45.454545 | BA16: =IF(NOT(ISNUMBER($J16)),"n/a",IF($J16<70000,"1. <Rs70k",IF($J16<100000,"2. Rs70k-1L",IF($J16<150000,"3. Rs1-1.5L",IF($J16<200000,"4. Rs1.5-2L",IF($J16<300000,"5. Rs2-3L","6. >Rs3L")))))) -> 2. Rs70k-1L | BB16: MEDIUM | BC16: BikeDekho (Jul-2026) | BD16: Research compilation | BE16: The RV1/RV1+ and Oben Rorr EZ at c.Rs1L are the only credible ICE-commuter price competitors today.
A17: M014 | B17: Revolt Motors | C17: Revolt | D17: RV1+ | E17: Standard | F17: On sale | G17: 2024 | H17: Entry commuter | I17: 89990 | J17: 105000 | K17: Aug-2026 | L17: n/a | M17: 3.24 | N17: Removable | O17: Li-ion | P17: n/a | Q17: Mid-drive, belt | R17: 3 | S17: n/a | T17: 70 | U17: n/a | V17: 160 | W17: IDC | X17: 115 | Y17: n/a | Z17: ~4h | AA17: No | AB17: n/a | AC17: n/a | AD17: n/a | AE17: n/a | AF17: n/a | AG17: n/a | AH17: n/a | AI17: Single speed | AJ17: 17-inch | AK17: Disc / Drum | AL17: CBS | AM17: LCD | AN17: 4G, app | AO17: 2 | AP17: n/a | AQ17: n/a | AR17: n/a | AS17: n/a | AT17: 5 yr / 75,000 km | AU17: 5 yr | AV17: RV1 platform | AW17: Manesar | AX17: n/a | AY17: =IF(AND(ISNUMBER($J17),ISNUMBER($M17)),$J17/$M17,"n/a") -> 32407.407 | AZ17: =IF(AND(ISNUMBER($V17),ISNUMBER($M17)),$V17/$M17,"n/a") -> 49.382716 | BA17: =IF(NOT(ISNUMBER($J17)),"n/a",IF($J17<70000,"1. <Rs70k",IF($J17<100000,"2. Rs70k-1L",IF($J17<150000,"3. Rs1-1.5L",IF($J17<200000,"4. Rs1.5-2L",IF($J17<300000,"5. Rs2-3L","6. >Rs3L")))))) -> 3. Rs1-1.5L | BB17: MEDIUM | BC17: BikeDekho (Jul-2026) | BD17: n/a | BE17: n/a
A18: M015 | B18: Oben Electric (private) | C18: Oben | D18: Rorr | E18: Standard | F18: On sale | G18: 2023 | H18: Value performance | I18: 149000 | J18: 149000 | K18: Aug-2026 | L18: n/a | M18: 4.4 | N18: Fixed | O18: LFP (in-house cell-to-pack) | P18: In-house LFP pack | Q18: Mid-drive, chain | R18: 7.5 | S18: 62 | T18: 100 | U18: 3 | V18: 187 | W18: IDC | X18: 130 | Y18: n/a | Z18: ~2h (0-80%) | AA18: No | AB18: 130 | AC18: n/a | AD18: n/a | AE18: n/a | AF18: 1350 | AG18: 220 | AH18: n/a | AI18: Single speed | AJ18: 17-inch | AK18: Disc / Disc | AL18: CBS | AM18: LCD | AN18: Bluetooth, app | AO18: 3 | AP18: n/a | AQ18: n/a | AR18: LFP chemistry (safety/cycle life); 220 mm ground clearance | AS18: IP67 | AT18: 3 yr | AU18: 8 yr / 100,000 km (LFP) | AV18: Rorr platform | AW18: Bengaluru | AX18: LFP-based safety and cycle-life positioning at a value price | AY18: =IF(AND(ISNUMBER($J18),ISNUMBER($M18)),$J18/$M18,"n/a") -> 33863.636 | AZ18: =IF(AND(ISNUMBER($V18),ISNUMBER($M18)),$V18/$M18,"n/a") -> 42.5 | BA18: =IF(NOT(ISNUMBER($J18)),"n/a",IF($J18<70000,"1. <Rs70k",IF($J18<100000,"2. Rs70k-1L",IF($J18<150000,"3. Rs1-1.5L",IF($J18<200000,"4. Rs1.5-2L",IF($J18<300000,"5. Rs2-3L","6. >Rs3L")))))) -> 3. Rs1-1.5L | BB18: MEDIUM | BC18: ZigWheels comparison (Aug-2026) | BD18: Research compilation | BE18: LFP is a genuine differentiator: no thermal-runaway history, longer cycle life, lower cell cost.
A19: M016 | B19: Oben Electric | C19: Oben | D19: Rorr EZ | E19: 2.6 / 3.4 / 4.4 kWh | F19: On sale | G19: 2025 | H19: Value commuter | I19: 89999 | J19: 99999 | K19: Aug-2026 | L19: n/a | M19: 4.4 | N19: Fixed | O19: LFP | P19: In-house LFP pack | Q19: Mid-drive, chain | R19: 7.5 | S19: 62 | T19: 95 | U19: 3.3 | V19: 175 | W19: IDC | X19: 125 | Y19: n/a | Z19: ~2h (0-80%) | AA19: No | AB19: n/a | AC19: n/a | AD19: n/a | AE19: n/a | AF19: n/a | AG19: 220 | AH19: n/a | AI19: Single speed | AJ19: 17-inch | AK19: Disc / Disc | AL19: CBS | AM19: LCD | AN19: Bluetooth, app | AO19: 3 | AP19: n/a | AQ19: n/a | AR19: Modular battery ladder within one body; sub-Rs1L entry | AS19: IP67 | AT19: 3 yr | AU19: 8 yr / 100,000 km | AV19: Rorr platform | AW19: Bengaluru | AX19: One chassis, three battery sizes — the cheapest way to build a product ladder | AY19: =IF(AND(ISNUMBER($J19),ISNUMBER($M19)),$J19/$M19,"n/a") -> 22727.045 | AZ19: =IF(AND(ISNUMBER($V19),ISNUMBER($M19)),$V19/$M19,"n/a") -> 39.772727 | BA19: =IF(NOT(ISNUMBER($J19)),"n/a",IF($J19<70000,"1. <Rs70k",IF($J19<100000,"2. Rs70k-1L",IF($J19<150000,"3. Rs1-1.5L",IF($J19<200000,"4. Rs1.5-2L",IF($J19<300000,"5. Rs2-3L","6. >Rs3L")))))) -> 2. Rs70k-1L | BB19: MEDIUM | BC19: BikeDekho (Jul-2026) | BD19: Research compilation | BE19: Battery-size laddering on a single chassis is now standard across the industry — further evidence of low differentiation cost.
A20: M017 | B20: Oben Electric | C20: Oben | D20: Rorr EZ Sigma | E20: Standard | F20: On sale | G20: 2026 | H20: Value sporty commuter | I20: n/a | J20: 119999 | K20: Aug-2026 | L20: n/a | M20: 4.4 | N20: Fixed | O20: LFP | P20: In-house | Q20: Mid-drive, chain | R20: 10 | S20: n/a | T20: 110 | U20: n/a | V20: 175 | W20: IDC | X20: 125 | Y20: n/a | Z20: ~2h | AA20: No | AB20: n/a | AC20: n/a | AD20: n/a | AE20: n/a | AF20: n/a | AG20: 220 | AH20: n/a | AI20: Single speed | AJ20: 17-inch | AK20: Disc / Disc | AL20: CBS | AM20: TFT | AN20: Bluetooth, app | AO20: 3 | AP20: n/a | AQ20: n/a | AR20: Positioned against 150cc ICE sport-commuters | AS20: IP67 | AT20: 3 yr | AU20: 8 yr / 100,000 km | AV20: Rorr platform | AW20: Bengaluru | AX20: Explicitly benchmarked against 150cc ICE on price and performance | AY20: =IF(AND(ISNUMBER($J20),ISNUMBER($M20)),$J20/$M20,"n/a") -> 27272.5 | AZ20: =IF(AND(ISNUMBER($V20),ISNUMBER($M20)),$V20/$M20,"n/a") -> 39.772727 | BA20: =IF(NOT(ISNUMBER($J20)),"n/a",IF($J20<70000,"1. <Rs70k",IF($J20<100000,"2. Rs70k-1L",IF($J20<150000,"3. Rs1-1.5L",IF($J20<200000,"4. Rs1.5-2L",IF($J20<300000,"5. Rs2-3L","6. >Rs3L")))))) -> 3. Rs1-1.5L | BB20: MEDIUM | BC20: BikeDekho review reference (2026) | BD20: n/a | BE20: n/a
A21: M018 | B21: Matter Motor Works (private) | C21: Matter | D21: Aera 5000 | E21: Standard | F21: On sale | G21: Mar-2023 (deliveries 2024-25) | H21: Premium differentiated | I21: n/a | J21: 183305 | K21: Aug-2026 | L21: n/a | M21: 5 | N21: Fixed, liquid-cooled | O21: Li-ion | P21: Imported cells; in-house liquid-cooled pack | Q21: Mid-drive, chain | R21: 10 | S21: 520 | T21: 105 | U21: n/a | V21: 172 | W21: IDC | X21: 125 | Y21: n/a | Z21: ~5h | AA21: No | AB21: 168 | AC21: n/a | AD21: n/a | AE21: n/a | AF21: n/a | AG21: n/a | AH21: n/a | AI21: 4-speed manual (HyperShift geared transmission) | AJ21: 17-inch | AK21: Disc / Disc | AL21: Dual-channel ABS | AM21: 7-inch TFT touchscreen | AN21: 4G, nav, OTA | AO21: 4 | AP21: n/a | AQ21: Yes | AR21: INDIA'S ONLY GEARED ELECTRIC MOTORCYCLE; liquid-cooled battery pack | AS21: IP67 | AT21: 3 yr | AU21: LIFETIME battery warranty (announced 2025) | AV21: Aera platform | AW21: Ahmedabad, Gujarat | AX21: The single most product-differentiated e-motorcycle in India — manual gearbox preserves the ICE riding ritual | AY21: =IF(AND(ISNUMBER($J21),ISNUMBER($M21)),$J21/$M21,"n/a") -> 36661 | AZ21: =IF(AND(ISNUMBER($V21),ISNUMBER($M21)),$V21/$M21,"n/a") -> 34.4 | BA21: =IF(NOT(ISNUMBER($J21)),"n/a",IF($J21<70000,"1. <Rs70k",IF($J21<100000,"2. Rs70k-1L",IF($J21<150000,"3. Rs1-1.5L",IF($J21<200000,"4. Rs1.5-2L",IF($J21<300000,"5. Rs2-3L","6. >Rs3L")))))) -> 4. Rs1.5-2L | BB21: HIGH | BC21: BikeWale / BikeDekho (Aug-2026) | BD21: Autocar Professional / Wikipedia (Matter Electric) | BE21: NICHE EXHIBIT #2: strong differentiation, negligible volume. Tests whether product novelty alone builds a business.
A22: M019 | B22: Matter Motor Works | C22: Matter | D22: Aera 5000+ | E22: Standard | F22: On sale | G22: 2024 | H22: Premium differentiated | I22: 193000 | J22: 193826 | K22: Aug-2026 | L22: n/a | M22: 5 | N22: Fixed, liquid-cooled | O22: Li-ion | P22: In-house liquid-cooled pack | Q22: Mid-drive, chain | R22: 11.5 | S22: 520 | T22: 105 | U22: n/a | V22: 172 | W22: IDC | X22: 125 | Y22: n/a | Z22: ~5h | AA22: No | AB22: 168 | AC22: n/a | AD22: n/a | AE22: n/a | AF22: n/a | AG22: n/a | AH22: n/a | AI22: 4-speed manual (HyperShift) | AJ22: 17-inch | AK22: Disc / Disc | AL22: Dual-channel ABS | AM22: 7-inch TFT touchscreen | AN22: 4G, nav, OTA, ride analytics | AO22: 4 | AP22: n/a | AQ22: Yes | AR22: Geared transmission + liquid cooling; lifetime battery warranty | AS22: IP67 | AT22: 3 yr | AU22: LIFETIME battery warranty | AV22: Aera platform | AW22: Ahmedabad | AX22: Top-spec geared e-motorcycle | AY22: =IF(AND(ISNUMBER($J22),ISNUMBER($M22)),$J22/$M22,"n/a") -> 38765.2 | AZ22: =IF(AND(ISNUMBER($V22),ISNUMBER($M22)),$V22/$M22,"n/a") -> 34.4 | BA22: =IF(NOT(ISNUMBER($J22)),"n/a",IF($J22<70000,"1. <Rs70k",IF($J22<100000,"2. Rs70k-1L",IF($J22<150000,"3. Rs1-1.5L",IF($J22<200000,"4. Rs1.5-2L",IF($J22<300000,"5. Rs2-3L","6. >Rs3L")))))) -> 4. Rs1.5-2L | BB22: HIGH | BC22: Autocar Professional (Rs1.93 lakh Delhi launch) | BD22: ETAuto lifetime battery warranty (2025) | BE22: Scaling from c.7 to c.150 dealers; stated 50,000-unit 2026 target is aspirational, not guidance.
A23: M020 | B23: Raptee.HV (private) | C23: Raptee.HV | D23: T30 | E23: STD | F23: On sale | G23: Deliveries from early 2026 | H23: Premium technology | I23: 239000 | J23: 239000 | K23: Aug-2026 | L23: n/a | M23: 5.4 | N23: Fixed | O23: Li-ion | P23: Imported cells; in-house HV pack | Q23: Mid-drive, chain | R23: 22 | S23: 70 | T23: 135 | U23: 3.5 | V23: 200 | W23: IDC (150 km real-world claimed) | X23: 150 | Y23: n/a | Z23: ~50 min (0-80%) on CCS2 DC | AA23: YES — CCS2, uses car fast-charging infrastructure | AB23: n/a | AC23: n/a | AD23: n/a | AE23: n/a | AF23: n/a | AG23: n/a | AH23: n/a | AI23: Single speed | AJ23: 17-inch | AK23: 320 mm disc / 230 mm disc | AL23: Dual-channel ABS | AM23: TFT touchscreen | AN23: 4G, nav, OTA | AO23: 4 | AP23: n/a | AQ23: Yes | AR23: INDIA'S FIRST HIGH-VOLTAGE (c.350-400V) E-MOTORCYCLE; CCS2 compatible | AS23: IP67 | AT23: 3 yr | AU23: 5 yr | AV23: HV platform | AW23: Chennai (SIPCOT Cheyyar land secured) | AX23: High-voltage architecture lets it charge on the existing car DC network — solves the charging-infrastructure problem structurally | AY23: =IF(AND(ISNUMBER($J23),ISNUMBER($M23)),$J23/$M23,"n/a") -> 44259.259 | AZ23: =IF(AND(ISNUMBER($V23),ISNUMBER($M23)),$V23/$M23,"n/a") -> 37.037037 | BA23: =IF(NOT(ISNUMBER($J23)),"n/a",IF($J23<70000,"1. <Rs70k",IF($J23<100000,"2. Rs70k-1L",IF($J23<150000,"3. Rs1-1.5L",IF($J23<200000,"4. Rs1.5-2L",IF($J23<300000,"5. Rs2-3L","6. >Rs3L")))))) -> 5. Rs2-3L | BB23: HIGH | BC23: 91wheels comparison (Aug-2026) | BD23: BikeDekho (Aug-2026) | BE23: NICHE EXHIBIT #3: the most technically interesting architecture bet. Raised c.USD12m+; raising USD15-20m Series A.
A24: M021 | B24: Raptee.HV | C24: Raptee.HV | D24: T30 | E24: Sport | F24: On sale | G24: 2026 | H24: Premium technology | I24: n/a | J24: 255000 | K24: Aug-2026 | L24: n/a | M24: 5.4 | N24: Fixed | O24: Li-ion | P24: In-house HV pack | Q24: Mid-drive, chain | R24: 22 | S24: 70 | T24: 135 | U24: 3.5 | V24: 200 | W24: IDC | X24: 150 | Y24: n/a | Z24: ~50 min (0-80%) CCS2 | AA24: Yes — CCS2 | AB24: n/a | AC24: n/a | AD24: n/a | AE24: n/a | AF24: n/a | AG24: n/a | AH24: n/a | AI24: Single speed | AJ24: 17-inch | AK24: Disc / Disc | AL24: Dual-channel ABS | AM24: TFT | AN24: 4G, nav | AO24: 4 | AP24: n/a | AQ24: Yes | AR24: n/a | AS24: IP67 | AT24: 3 yr | AU24: 5 yr | AV24: HV platform | AW24: Chennai | AX24: n/a | AY24: =IF(AND(ISNUMBER($J24),ISNUMBER($M24)),$J24/$M24,"n/a") -> 47222.222 | AZ24: =IF(AND(ISNUMBER($V24),ISNUMBER($M24)),$V24/$M24,"n/a") -> 37.037037 | BA24: =IF(NOT(ISNUMBER($J24)),"n/a",IF($J24<70000,"1. <Rs70k",IF($J24<100000,"2. Rs70k-1L",IF($J24<150000,"3. Rs1-1.5L",IF($J24<200000,"4. Rs1.5-2L",IF($J24<300000,"5. Rs2-3L","6. >Rs3L")))))) -> 5. Rs2-3L | BB24: MEDIUM | BC24: 91wheels (Aug-2026) | BD24: n/a | BE24: Variant pricing not consistently disclosed; verify.
A25: M022 | B25: Eicher Motors / Royal Enfield (listed: EICHERMOT) | C25: Flying Flea (Royal Enfield) | D25: Flying Flea C6 | E25: Standard | F25: On sale | G25: Apr-2026 | H25: Premium heritage urban | I25: 279000 | J25: 279000 | K25: Aug-2026 | L25: Rs1,99,000 with Battery-as-a-Service | M25: 3.91 | N25: Fixed | O25: Li-ion | P25: n/a | Q25: PMSM, belt drive | R25: 15.4 | S25: 60 | T25: 115 | U25: 3.7 | V25: 154 | W25: IDC | X25: 95 | Y25: n/a | Z25: 65 min (20-80%); c.2h full | AA25: Yes | AB25: 124 | AC25: n/a | AD25: n/a | AE25: n/a | AF25: n/a | AG25: n/a | AH25: n/a | AI25: Single speed | AJ25: 19-inch front / 18-inch rear | AK25: Disc / Disc | AL25: Dual-channel ABS | AM25: 3.5-inch circular touchscreen TFT | AN25: 4G, map navigation, call alerts, music control | AO25: n/a | AP25: n/a | AQ25: Yes | AR25: Forged aluminium/magnesium frame; GIRDER front suspension; keyless ignition; wireless phone charger; adjustable foot pegs; regen braking | AS25: n/a | AT25: 3 yr | AU25: 3 yr | AV25: Purpose-built Flying Flea EV platform | AW25: Chennai; RE global network | AX25: The strongest brand equity of any electric motorcycle in India, at the lightest weight (124 kg) | AY25: =IF(AND(ISNUMBER($J25),ISNUMBER($M25)),$J25/$M25,"n/a") -> 71355.499 | AZ25: =IF(AND(ISNUMBER($V25),ISNUMBER($M25)),$V25/$M25,"n/a") -> 39.386189 | BA25: =IF(NOT(ISNUMBER($J25)),"n/a",IF($J25<70000,"1. <Rs70k",IF($J25<100000,"2. Rs70k-1L",IF($J25<150000,"3. Rs1-1.5L",IF($J25<200000,"4. Rs1.5-2L",IF($J25<300000,"5. Rs2-3L","6. >Rs3L")))))) -> 5. Rs2-3L | BB25: HIGH | BC25: BikeWale (Apr-2026) | BD25: Electrek launch report (10-Apr-2026) | BE25: NICHE EXHIBIT #4 — the highest-probability niche winner. Note: Electrek publicly questions whether 154 km IDC from 3.91 kWh is credible; expect c.90-100 km real-world.
A26: M023 | B26: Tork Motors (private, Bharat Forge-backed) | C26: Tork | D26: Kratos R | E26: Standard | F26: On sale | G26: 2022 | H26: Performance commuter | I26: 167500 | J26: 175000 | K26: Aug-2026 | L26: n/a | M26: 4 | N26: Fixed | O26: Li-ion | P26: n/a | Q26: Axial flux mid-drive, chain | R26: 9 | S26: 38 | T26: 105 | U26: 3.5 | V26: 180 | W26: IDC | X26: 120 | Y26: n/a | Z26: ~1h (0-80%, fast charge) | AA26: Yes | AB26: 140 | AC26: n/a | AD26: n/a | AE26: n/a | AF26: 1340 | AG26: n/a | AH26: n/a | AI26: Single speed | AJ26: 17-inch | AK26: Disc / Disc | AL26: CBS | AM26: TFT | AN26: 4G, TIROS OS, nav, geofencing | AO26: 3 | AP26: n/a | AQ26: Yes | AR26: In-house axial flux motor and TIROS operating system | AS26: IP67 | AT26: 3 yr | AU26: 3 yr | AV26: Kratos platform | AW26: Pune, Maharashtra | AX26: In-house axial-flux motor — one of very few genuinely proprietary powertrain claims | AY26: =IF(AND(ISNUMBER($J26),ISNUMBER($M26)),$J26/$M26,"n/a") -> 43750 | AZ26: =IF(AND(ISNUMBER($V26),ISNUMBER($M26)),$V26/$M26,"n/a") -> 45 | BA26: =IF(NOT(ISNUMBER($J26)),"n/a",IF($J26<70000,"1. <Rs70k",IF($J26<100000,"2. Rs70k-1L",IF($J26<150000,"3. Rs1-1.5L",IF($J26<200000,"4. Rs1.5-2L",IF($J26<300000,"5. Rs2-3L","6. >Rs3L")))))) -> 4. Rs1.5-2L | BB26: MEDIUM | BC26: Research compilation / aggregator listings | BD26: n/a | BE26: Axial flux motor design is one of the few components that is NOT easily outsourced — worth tracking.
A27: M024 | B27: Tork Motors | C27: Tork | D27: Kratos X | E27: Standard | F27: On sale | G27: 2024 | H27: Performance commuter | I27: n/a | J27: 195000 | K27: Aug-2026 | L27: n/a | M27: 4 | N27: Fixed | O27: Li-ion | P27: n/a | Q27: Axial flux mid-drive | R27: 9 | S27: 38 | T27: 105 | U27: 3.5 | V27: 180 | W27: IDC | X27: 120 | Y27: n/a | Z27: ~1h | AA27: Yes | AB27: 140 | AC27: n/a | AD27: n/a | AE27: n/a | AF27: 1340 | AG27: n/a | AH27: n/a | AI27: Single speed | AJ27: 17-inch | AK27: Disc / Disc | AL27: CBS | AM27: TFT | AN27: TIROS OS, 4G | AO27: 3 | AP27: n/a | AQ27: Yes | AR27: n/a | AS27: IP67 | AT27: 3 yr | AU27: 3 yr | AV27: Kratos platform | AW27: Pune | AX27: n/a | AY27: =IF(AND(ISNUMBER($J27),ISNUMBER($M27)),$J27/$M27,"n/a") -> 48750 | AZ27: =IF(AND(ISNUMBER($V27),ISNUMBER($M27)),$V27/$M27,"n/a") -> 45 | BA27: =IF(NOT(ISNUMBER($J27)),"n/a",IF($J27<70000,"1. <Rs70k",IF($J27<100000,"2. Rs70k-1L",IF($J27<150000,"3. Rs1-1.5L",IF($J27<200000,"4. Rs1.5-2L",IF($J27<300000,"5. Rs2-3L","6. >Rs3L")))))) -> 4. Rs1.5-2L | BB27: LOW | BC27: Aggregator listings (Aug-2026) | BD27: n/a | BE27: n/a
A28: M025 | B28: Orxa Energies (private) | C28: Orxa | D28: Mantis | E28: Standard | F28: On sale (limited) | G28: 2024 | H28: Performance niche | I28: 359000 | J28: 375000 | K28: Aug-2026 | L28: n/a | M28: 8.9 | N28: Fixed | O28: Li-ion | P28: n/a | Q28: Mid-drive, chain | R28: 21 | S28: 93 | T28: 135 | U28: n/a | V28: 221 | W28: IDC | X28: 160 | Y28: n/a | Z28: ~1h30m fast | AA28: Yes | AB28: 180 | AC28: n/a | AD28: n/a | AE28: n/a | AF28: n/a | AG28: n/a | AH28: n/a | AI28: Single speed | AJ28: 17-inch | AK28: Disc / Disc | AL28: Dual-channel ABS | AM28: TFT | AN28: 4G, nav | AO28: 3 | AP28: n/a | AQ28: Yes | AR28: Low-volume performance streetfighter | AS28: n/a | AT28: 3 yr | AU28: 3 yr | AV28: Mantis platform | AW28: Bengaluru | AX28: Boutique performance — negligible volume | AY28: =IF(AND(ISNUMBER($J28),ISNUMBER($M28)),$J28/$M28,"n/a") -> 42134.831 | AZ28: =IF(AND(ISNUMBER($V28),ISNUMBER($M28)),$V28/$M28,"n/a") -> 24.831461 | BA28: =IF(NOT(ISNUMBER($J28)),"n/a",IF($J28<70000,"1. <Rs70k",IF($J28<100000,"2. Rs70k-1L",IF($J28<150000,"3. Rs1-1.5L",IF($J28<200000,"4. Rs1.5-2L",IF($J28<300000,"5. Rs2-3L","6. >Rs3L")))))) -> 6. >Rs3L | BB28: LOW | BC28: Aggregator listings / research compilation | BD28: n/a | BE28: Very low volume; included for completeness of the >Rs3L band.
A29: M026 | B29: Kabira Mobility (private) | C29: Kabira | D29: KM3000 Mark II / KM4000 Mark II | E29: Standard | F29: On sale (limited) | G29: 2021-2023 | H29: Performance value | I29: n/a | J29: 175000 | K29: Aug-2026 | L29: n/a | M29: 4 | N29: Removable | O29: Li-ion | P29: n/a | Q29: Mid-drive, chain | R29: 8 | S29: n/a | T29: 120 | U29: n/a | V29: 150 | W29: Claimed | X29: 105 | Y29: n/a | Z29: ~50 min fast charge | AA29: Yes | AB29: n/a | AC29: n/a | AD29: n/a | AE29: n/a | AF29: n/a | AG29: n/a | AH29: n/a | AI29: Single speed | AJ29: 17-inch | AK29: Disc / Disc | AL29: CBS | AM29: LCD | AN29: Bluetooth | AO29: 3 | AP29: n/a | AQ29: n/a | AR29: Removable battery performance bike | AS29: n/a | AT29: 3 yr | AU29: 3 yr | AV29: n/a | AW29: Goa | AX29: n/a | AY29: =IF(AND(ISNUMBER($J29),ISNUMBER($M29)),$J29/$M29,"n/a") -> 43750 | AZ29: =IF(AND(ISNUMBER($V29),ISNUMBER($M29)),$V29/$M29,"n/a") -> 37.5 | BA29: =IF(NOT(ISNUMBER($J29)),"n/a",IF($J29<70000,"1. <Rs70k",IF($J29<100000,"2. Rs70k-1L",IF($J29<150000,"3. Rs1-1.5L",IF($J29<200000,"4. Rs1.5-2L",IF($J29<300000,"5. Rs2-3L","6. >Rs3L")))))) -> 4. Rs1.5-2L | BB29: LOW | BC29: Aggregator listings (Aug-2026) | BD29: n/a | BE29: Availability inconsistent; verify before modelling.
A30: M027 | B30: HOP Electric (private) | C30: HOP | D30: OXO / OXO X | E30: Standard | F30: On sale | G30: 2023 | H30: Value commuter | I30: 124999 | J30: 139999 | K30: Aug-2026 | L30: n/a | M30: 3.75 | N30: Removable | O30: Li-ion | P30: n/a | Q30: Mid-drive | R30: 6.2 | S30: n/a | T30: 95 | U30: n/a | V30: 150 | W30: Claimed | X30: 105 | Y30: n/a | Z30: ~4h | AA30: No | AB30: n/a | AC30: n/a | AD30: n/a | AE30: n/a | AF30: n/a | AG30: n/a | AH30: n/a | AI30: Single speed | AJ30: 17-inch | AK30: Disc / Disc | AL30: CBS | AM30: LCD | AN30: Bluetooth, app | AO30: 3 | AP30: n/a | AQ30: n/a | AR30: n/a | AS30: IP67 | AT30: 3 yr | AU30: 3 yr | AV30: OXO platform | AW30: Jaipur, Rajasthan | AX30: n/a | AY30: =IF(AND(ISNUMBER($J30),ISNUMBER($M30)),$J30/$M30,"n/a") -> 37333.067 | AZ30: =IF(AND(ISNUMBER($V30),ISNUMBER($M30)),$V30/$M30,"n/a") -> 40 | BA30: =IF(NOT(ISNUMBER($J30)),"n/a",IF($J30<70000,"1. <Rs70k",IF($J30<100000,"2. Rs70k-1L",IF($J30<150000,"3. Rs1-1.5L",IF($J30<200000,"4. Rs1.5-2L",IF($J30<300000,"5. Rs2-3L","6. >Rs3L")))))) -> 3. Rs1-1.5L | BB30: LOW | BC30: Aggregator listings (Aug-2026) | BD30: n/a | BE30: n/a
A31: M028 | B31: Srivaru Motors (private) | C31: Srivaru | D31: Prana | E31: Standard / Grand | F31: On sale (limited) | G31: 2023 | H31: Niche premium | I31: n/a | J31: 220000 | K31: Aug-2026 | L31: n/a | M31: 6 | N31: Fixed | O31: Li-ion | P31: n/a | Q31: Mid-drive | R31: 13 | S31: n/a | T31: 123 | U31: n/a | V31: 156 | W31: Claimed | X31: 110 | Y31: n/a | Z31: n/a | AA31: No | AB31: n/a | AC31: n/a | AD31: n/a | AE31: n/a | AF31: n/a | AG31: n/a | AH31: n/a | AI31: Single speed | AJ31: 17-inch | AK31: Disc / Disc | AL31: CBS | AM31: LCD | AN31: n/a | AO31: 3 | AP31: n/a | AQ31: n/a | AR31: n/a | AS31: n/a | AT31: 3 yr | AU31: 3 yr | AV31: n/a | AW31: Coimbatore, Tamil Nadu | AX31: n/a | AY31: =IF(AND(ISNUMBER($J31),ISNUMBER($M31)),$J31/$M31,"n/a") -> 36666.667 | AZ31: =IF(AND(ISNUMBER($V31),ISNUMBER($M31)),$V31/$M31,"n/a") -> 26 | BA31: =IF(NOT(ISNUMBER($J31)),"n/a",IF($J31<70000,"1. <Rs70k",IF($J31<100000,"2. Rs70k-1L",IF($J31<150000,"3. Rs1-1.5L",IF($J31<200000,"4. Rs1.5-2L",IF($J31<300000,"5. Rs2-3L","6. >Rs3L")))))) -> 5. Rs2-3L | BB31: LOW | BC31: Aggregator listings / research compilation | BD31: n/a | BE31: Very low volume; status uncertain.
A32: M029 | B32: Komaki / LML / Others (private, various) | C32: Multiple | D32: Ranger / Venice / Star (representative) | E32: Standard | F32: On sale (fragmented) | G32: 2021-2024 | H32: Low-speed value | I32: n/a | J32: 130000 | K32: Aug-2026 | L32: n/a | M32: 4 | N32: Removable | O32: Li-ion / LFP | P32: n/a | Q32: Hub or mid-drive | R32: 3 | S32: n/a | T32: 80 | U32: n/a | V32: 180 | W32: Claimed | X32: 110 | Y32: n/a | Z32: n/a | AA32: No | AB32: n/a | AC32: n/a | AD32: n/a | AE32: n/a | AF32: n/a | AG32: n/a | AH32: n/a | AI32: Single speed | AJ32: 17-inch | AK32: Disc / Drum | AL32: CBS | AM32: LCD | AN32: Basic | AO32: 2 | AP32: n/a | AQ32: n/a | AR32: Representative row for the fragmented low-volume e-motorcycle tail | AS32: n/a | AT32: 1-3 yr | AU32: 1-3 yr | AV32: n/a | AW32: Various | AX32: LONG-TAIL EXHIBIT: many brands, negligible aggregate share | AY32: =IF(AND(ISNUMBER($J32),ISNUMBER($M32)),$J32/$M32,"n/a") -> 32500 | AZ32: =IF(AND(ISNUMBER($V32),ISNUMBER($M32)),$V32/$M32,"n/a") -> 45 | BA32: =IF(NOT(ISNUMBER($J32)),"n/a",IF($J32<70000,"1. <Rs70k",IF($J32<100000,"2. Rs70k-1L",IF($J32<150000,"3. Rs1-1.5L",IF($J32<200000,"4. Rs1.5-2L",IF($J32<300000,"5. Rs2-3L","6. >Rs3L")))))) -> 3. Rs1-1.5L | BB32: LOW | BC32: Industry compilation | BD32: n/a | BE32: Claimed range figures from this cohort are frequently uncertified — do not use for competitive analysis.

Sheet Pipeline
A1: PIPELINE — UPCOMING AND ANNOUNCED PRODUCTS
A2: Read the CONFIRMATION LEVEL column before modelling anything. Only COMPANY-CONFIRMED and COMPANY-GUIDED entries belong in a volume forecast.
A3: ID | B3: OEM / parent | C3: Brand | D3: Model | E3: Body type | F3: Segment | G3: Expected launch | H3: CONFIRMATION LEVEL | I3: Expected price | J3: Expected battery (kWh) | K3: Expected range | L3: Expected power | M3: Platform | N3: Known specs / what was shown | O3: Strategic rationale | P3: Source | Q3: Source date | R3: Risk flag / how to model
A4: P001 | B4: Ather Energy | C4: Ather | D4: EL platform (EL01) | E4: Scooter | F4: Mass-market | G4: Reveal 29-Aug-2026; volumes FY27 | H4: COMPANY-SIGNALLED (reveal date announced) | I4: Rs1.00-1.25 lakh (expected) | J4: n/a | K4: n/a | L4: n/a | M4: EL (new steel-chassis mass platform) | N4: Steel chassis to cut cost vs the aluminium-intensive 450/Rizta; targeted at the sub-Rs1.2L volume core | O4: Ather has no true entry product; EL is its answer to TVS Orbiter and Vida VX2 Go. Critical to Ather's volume trajectory. | P4: MeraEV / company reveal calendar | Q4: Aug-2026 | R4: Price band is an estimate, not company guidance. Do NOT model volumes before H2 FY27.
A5: P002 | B5: Ather Energy | C5: Ather | D5: Zenith motorcycle platform | E5: Motorcycle | F5: 125-300cc equivalent | G5: FY27+ | H5: COMPANY-CONFIRMED (platform), TIMING UNGUIDED | I5: n/a | J5: n/a | K5: n/a | L5: n/a | M5: Zenith (LFP-certified motorcycle platform) | N5: LFP chemistry certified; to be built at the new Maharashtra (Aurangabad) plant | O5: Ather's entry into e-motorcycles; extends the software/brand moat into a segment with no incumbent | P5: Business Standard | Q5: 2026 | R5: No product, price or date announced. Treat as optionality only.
A6: P003 | B6: Ultraviolette | C6: Ultraviolette | D6: Shockwave | E6: Motorcycle | F6: Funduro / entry-performance | G6: c.Sep-2026 (site shows Q1 2026 — SLIPPED) | H6: COMPANY-ANNOUNCED, TIMING SLIPPED | I6: Rs1.75 lakh (listed) | J6: c.4.2 kWh (reported) | K6: 165 km (listed) | L6: 10.8 kW (listed) | M6: UV compact platform | N6: Off-road-flavoured 'funduro'; pre-bookings open | O6: Takes UV down-market from Rs3L to Rs1.75L — the volume test for its brand | P6: ultraviolette.com; thebikejunction listing | Q6: Aug-2026 | R6: Timing has already slipped once. Treat Sep-2026 as best case.
A7: P004 | B7: Ultraviolette | C7: Ultraviolette | D7: Tesseract | E7: Scooter | F7: Premium maxi-scooter | G7: Q1 2027 (company site) | H7: COMPANY-GUIDED WINDOW | I7: Rs1.20 lakh (introductory, extended) | J7: 6.0 kWh | K7: 261 km IDC (claimed) | L7: 14 kW | M7: UV 100V platform | N7: Radar-based blind-spot detection and forward-collision warning; >70,000 pre-bookings reported | O7: First scooter from a motorcycle brand; ADAS-style tech as the differentiator | P7: ultraviolette.com (Q1 2027); Autocar India | Q7: Jun-2026 | R7: SLIPPED from Q1-2026 to Q1-2027. Pre-bookings are not orders.
A8: P005 | B8: Ultraviolette | C8: Ultraviolette | D8: F99 | E8: Motorcycle | F8: Track / halo | G8: Not confirmed | H8: ANNOUNCED, NO DATE | I8: Not announced | J8: n/a | K8: n/a | L8: n/a | M8: F99 platform | N8: Track-focused halo machine | O8: Brand halo, not volume | P8: ultraviolette.com | Q8: Aug-2026 | R8: Halo project. Model zero volume.
A9: P006 | B9: Eicher Motors / Royal Enfield | C9: Flying Flea | D9: Flying Flea S6 | E9: Motorcycle | F9: Premium scrambler | G9: FY27 (post-C6) | H9: COMPANY-CONFIRMED PRODUCT, TIMING UNGUIDED | I9: Expected c.Rs2.8-3.2 lakh (estimate) | J9: c.3.91 kWh (C6-derived) | K9: n/a | L9: c.15 kW (C6-derived) | M9: Flying Flea EV platform | N9: Scrambler bodystyle on the C6 platform; shown at Motoverse 2025 | O9: Platform leverage across two bodystyles; extends RE's heritage moat into EV | P9: Royal Enfield Motoverse 2025 | Q9: Nov-2025 | R9: Price is an ESTIMATE. No launch date announced.
A10: P007 | B10: Ola Electric | C10: Ola Electric | D10: Diamondhead | E10: Motorcycle | F10: Performance flagship | G10: CY2027 | H10: COMPANY-ANNOUNCED (Sankalp 2025) | I10: <Rs5 lakh (company statement) | J10: n/a | K10: n/a | L10: n/a | M10: New performance platform | N10: Hub-centre steering; custom in-house silicon | O10: Technology halo intended to rebuild Ola's brand credibility | P10: Ola Sankalp 2025 | Q10: 2025 | R10: Ola has a track record of announcing and delaying. Model zero volume.
A11: P008 | B11: Ola Electric | C11: Ola Electric | D11: Gen-4 platform | E11: Scooter + Motorcycle | F11: Across range | G11: FY27-FY28 | H11: COMPANY-SIGNALLED | I11: n/a | J11: n/a | K11: n/a | L11: n/a | M11: Gen-4 | N11: Further BOM reduction on the 4680 Bharat Cell and in-house ferrite motor | O11: Ola cut its auto-EBITDA breakeven from 50,000 to <25,000 units/month on Gen-3 BOM work; Gen-4 extends this | P11: Ola disclosures / research compilation | Q11: 2026 | R11: Breakeven claims are company statements, not audited.
A12: P009 | B12: Hero MotoCorp | C12: Vida | D12: VXZ (adventure) | E12: Motorcycle | F12: Adventure | G12: c.Feb-2027 | H12: MEDIA-REPORTED (patent leak) | I12: n/a | J12: n/a | K12: n/a | L12: n/a | M12: Zero Motorcycles-linked platform | N12: Adventure bodystyle; leverages Hero's equity investment in Zero Motorcycles | O12: Hero buying rather than building its e-motorcycle powertrain — direct evidence of outsourceability | P12: ZigWheels patent-filing report | Q12: 2026 | R12: SPECULATIVE. Patent filings are not launch commitments.
A13: P010 | B13: Hero MotoCorp | C13: Vida | D13: UBEX | E13: Motorcycle | F13: Street naked | G13: Not confirmed | H13: CONCEPT / SHOWN | I13: n/a | J13: n/a | K13: n/a | L13: n/a | M13: n/a | N13: Street-naked concept | O13: Segment-filling concept | P13: ZigWheels / show coverage | Q13: 2026 | R13: Concept only.
A14: P011 | B14: Hero MotoCorp | C14: Vida | D14: Z-series / next platform | E14: Scooter | F14: Premium | G14: FY27 | H14: MEDIA-REPORTED | I14: n/a | J14: n/a | K14: n/a | L14: n/a | M14: New Vida platform | N14: Premium step-up above VX2 | O14: Hero targets scaling Vida from c.15,000 to c.45,000 units/month (Chittoor plant); >Rs1,500 cr FY27 EV capex | P14: MeraEV / Motilal Oswal / company commentary | Q14: 2026 | R14: Volume target is management aspiration, not guidance.
... A26: P023 | B26: Greaves Electric Mobility | C26: Ampere | D26: New Nexus-platform products | E26: Scooter | F26: Mass | G26: FY27 | H26: COMPANY-SIGNALLED | I26: n/a | J26: n/a | K26: n/a | L26: n/a | M26: Nexus platform | N26: Portfolio refresh post-FAME-II recovery | O26: Greaves grew 53% in FY26 off a low base; watch whether that persists post-subsidy | P26: Company / media | Q26: 2026 | R26: n/a
A27: P024 | B27: Chinese OEMs (Niu, Yadea, Segway/Ninebot) | C27: Various | D27: India entry / licensing | E27: Scooter | F27: Mass | G27: Not confirmed | H27: SPECULATIVE | I27: n/a | J27: n/a | K27: n/a | L27: n/a | M27: n/a | N27: No confirmed India manufacturing plans | O27: The largest unmodelled competitive risk: Chinese e-2W OEMs have global scale and cost advantage | P27: WATCH ITEM: India-China trade and FDI policy is the binding constraint, not capability | Q27: Industry compilation | R27: 2026 | S27: SPECULATIVE. No confirmed entry. Monitor FDI/Press Note 3 policy changes.

Sheet Price_Band_Map
A1: PRICE-BAND MAP — WHERE THE MARKET IS CROWDED AND WHERE IT IS EMPTY
A2: Live counts driven by the calculated price-band column on the two model-master sheets. Add a model there and these numbers move.
A4: Price band (ex-showroom) | B4: Scooter variants | C4: Motorcycle variants | D4: Total | E4: Competitive read
A5: 1. <Rs70k | B5: =COUNTIF(Scooters_Current!$BA$4:$BA$61,$A5) -> 1 | C5: =COUNTIF(Motorcycles_Current!$BA$4:$BA$32,$A5) -> 0 | D5: =B5+C5 -> 1 | E5: Licence-free low-speed and BaaS-only offers. Invisible to Vahan. Not a real retail band yet.
A6: 2. Rs70k-1L | B6: =COUNTIF(Scooters_Current!$BA$4:$BA$61,$A6) -> 11 | C6: =COUNTIF(Motorcycles_Current!$BA$4:$BA$32,$A6) -> 4 | D6: =B6+C6 -> 15 | E6: THE NEW BATTLEGROUND. Entry variants from all four leaders now sit here. Expect the sharpest margin compression.
A7: 3. Rs1-1.5L | B7: =COUNTIF(Scooters_Current!$BA$4:$BA$61,$A7) -> 26 | C7: =COUNTIF(Motorcycles_Current!$BA$4:$BA$32,$A7) -> 10 | D7: =B7+C7 -> 36 | E7: MOST CROWDED BAND. Every major OEM competes here. This is where the mass-market commoditisation thesis plays out.
A8: 4. Rs1.5-2L | B8: =COUNTIF(Scooters_Current!$BA$4:$BA$61,$A8) -> 12 | C8: =COUNTIF(Motorcycles_Current!$BA$4:$BA$32,$A8) -> 6 | D8: =B8+C8 -> 18 | E8: Thinning. Buyers trade up only for genuine range or brand. Suzuki, Ather 450X, iQube ST, Vida Plus 4.4.
A9: 5. Rs2-3L | B9: =COUNTIF(Scooters_Current!$BA$4:$BA$61,$A9) -> 1 | C9: =COUNTIF(Motorcycles_Current!$BA$4:$BA$32,$A9) -> 5 | D9: =B9+C9 -> 6 | E9: Emerging premium niche. Almost entirely motorcycles — Raptee, UV X47, RE Flying Flea.
A10: 6. >Rs3L | B10: =COUNTIF(Scooters_Current!$BA$4:$BA$61,$A10) -> 1 | C10: =COUNTIF(Motorcycles_Current!$BA$4:$BA$32,$A10) -> 3 | D10: =B10+C10 -> 4 | E10: Sparse. UV F77 and imports only. The clearest structural white space in the market.
A11: TOTAL PRICED VARIANTS | B11: =SUM(B5:B10) -> 52 | C11: =SUM(C5:C10) -> 28 | D11: =SUM(D5:D10) -> 80
A13: AVERAGE PRICE AND SPEC BY BODY TYPE
A14: Metric | B14: Scooters | C14: Motorcycles
A15: Average latest price (Rs, ex-showroom) | B15: =IFERROR(AVERAGEIFS(Scooters_Current!$J$4:$J$61,Scooters_Current!$J$4:$J$61,"<500000"),"n/a") -> 126792.61 | C15: =IFERROR(AVERAGEIFS(Motorcycles_Current!$J$4:$J$32,Motorcycles_Current!$J$4:$J$32,"<500000"),"n/a") -> 183786
A16: Average battery (kWh) | B16: =IFERROR(AVERAGEIFS(Scooters_Current!$M$4:$M$61,Scooters_Current!$J$4:$J$61,"<500000"),"n/a") -> 3.2433333 | C16: =IFERROR(AVERAGEIFS(Motorcycles_Current!$M$4:$M$32,Motorcycles_Current!$J$4:$J$32,"<500000"),"n/a") -> 4.8685714
A17: Average claimed range (km) | B17: =IFERROR(AVERAGEIFS(Scooters_Current!$V$4:$V$61,Scooters_Current!$J$4:$J$61,"<500000"),"n/a") -> 140.08511 | C17: =IFERROR(AVERAGEIFS(Motorcycles_Current!$V$4:$V$32,Motorcycles_Current!$J$4:$J$32,"<500000"),"n/a") -> 182.96429
A18: Average peak power (kW) | B18: =IFERROR(AVERAGEIFS(Scooters_Current!$R$4:$R$61,Scooters_Current!$J$4:$J$61,"<500000"),"n/a") -> 4.8662791 | C18: =IFERROR(AVERAGEIFS(Motorcycles_Current!$R$4:$R$32,Motorcycles_Current!$J$4:$J$32,"<500000"),"n/a") -> 11.575
A19: Average Rs per kWh | B19: =IFERROR(AVERAGEIFS(Scooters_Current!$AY$4:$AY$61,Scooters_Current!$J$4:$J$61,"<500000"),"n/a") -> 40149.774 | C19: =IFERROR(AVERAGEIFS(Motorcycles_Current!$AY$4:$AY$32,Motorcycles_Current!$J$4:$J$32,"<500000"),"n/a") -> 38079.667
A21: Note: averages are unweighted across variants, not volume-weighted, and exclude any variant priced above Rs5 lakh (i.e. the imported BMW CE 04) so the mean is not distorted. They describe the shape of the product landscape, not the market.

Sheet Company_Profiles
A1: COMPANY PROFILES — OWNERSHIP, FINANCIALS, CAPACITY, NETWORK AND MOAT
A2: The 'identified moat' column is the analytical output: what actually protects each player, as distinct from what they claim.
A3: Company | B3: Type | C3: Ticker | D3: Market cap / valuation | E3: Listing status | F3: Backers / funding history | G3: Latest revenue | H3: Profitability | I3: FY26 e-2W volume (Vahan unless noted) | J3: Manufacturing | K3: Capex | L3: Distribution network | M3: Charging / swapping | N3: Cell and powertrain strategy | O3: Stated targets and guidance | P3: IDENTIFIED MOAT | Q3: Confidence | R3: Source
A4: TVS Motor Company | B4: Listed ICE incumbent | C4: TVSMOTOR (NSE/BSE) | D4: Large-cap (see Bloomberg TVSL IN) | E4: Long listed | F4: Self-funded from ICE profits | G4: Not disclosed separately for EV | H4: EV segment loss-making but cross-subsidised | I4: 341,513 (FY26 e-2W, +43.5%) | J4: Hosur, Tamil Nadu | K4: c.Rs3,500 cr fresh EV investment (announced) | L4: India's deepest 2W dealer + service network (shared with ICE) | M4: Jio-bp partnership for AC and DC public charging | N4: Outsourced cells; in-house pack assembly | O4: 40,000-50,000 e-2W/month through FY27; >10 lakh e-scooters already on road | P4: DISTRIBUTION + SERVICE NETWORK + BRAND. Not powertrain. | Q4: HIGH | R4: Vahan / company commentary / Motilal Oswal (2026)
A5: Bajaj Auto | B5: Listed ICE incumbent | C5: BAJAJ-AUTO (NSE/BSE) | D5: Large-cap (BJAUT IN) | E5: Long listed | F5: Self-funded | G5: Not disclosed separately | H5: EV cross-subsidised by ICE | I5: 289,349 (FY26 e-2W, +25.7%) | J5: Akurdi / Chakan, Maharashtra | K5: Not separately disclosed | L5: Chetak dealer network + Bajaj/Piaggio touchpoints | M5: Chetak charging partnerships | N5: Outsourced cells | O5: Targeting e-2W leadership via Chetak expansion | P5: ALL-METAL BODY (durability differentiation) + DISTRIBUTION + BRAND | Q5: HIGH | R5: Vahan / company disclosures
A6: Ather Energy | B6: Listed EV pure-play | C6: ATHERENERG (NSE/BSE) | D6: c.Rs57,000-58,000 cr (Aug-2026; +c.250% in 12 months) | E6: IPO 06-May-2025: Rs2,980.76 cr (fresh Rs2,626 cr + OFS Rs354.76 cr) at Rs321 | F6: Hero MotoCorp largest holder c.37%; approved c.Rs1,200 cr preferential issue (Hero Rs960 cr, India-Japan Fund Rs200 cr) | G6: Rs3,671 cr (FY26, +66%) | H6: Net loss Rs517 cr (FY26); first positive operating cash flow | I6: c.263,000 (FY26 company deliveries, +69%); 239,178 Vahan | J6: Hosur F1+F2 = 420,000/yr; Maharashtra (Aurangabad) Phase 1 c.500,000/yr planned | K6: c.Rs2,000 cr Maharashtra plant | L6: c.400 Ather Spaces / experience centres | M6: Ather Grid: >5,000-6,100 fast-charge points across 370-395 cities (3,675 own + c.1,400 partner) | N6: Outsourced cells; in-house pack, BMS, motor and full software stack (AtherStack) | O6: Q1 FY27: revenue Rs1,259.65 cr, net loss Rs51.09 cr, EBITDA margin -2.73%, 88,655 vehicles | P6: SOFTWARE (AtherStack, Pro Pack subscriptions) + CHARGING NETWORK + PREMIUM BRAND + Hero backing | Q6: HIGH | R6: NSE filings / Business Standard / Entrackr (2026)
A7: Ola Electric | B7: Listed EV pure-play | C7: OLAELEC (NSE/BSE) | D7: c.Rs17,000-19,000 cr (Aug-2026), down heavily from peak | E7: IPO Aug-2024 at Rs76; raised Rs6,146 cr | F7: SoftBank, Temasek and others pre-IPO | G7: Rs2,253 cr revenue from operations (FY26, c.-50%) | H7: Net loss c.Rs2,276 cr (FY26) | I7: 173,794 company deliveries (FY26) vs 325-375k guidance; 164,295 Vahan (-52.3%) | J7: Krishnagiri, Tamil Nadu (Futurefactory) + gigafactory c.2.5 GWh operational of c.6 GWh installed | K7: c.Rs5,300 cr cumulative manufacturing / battery / R&D capex | L7: Direct-to-consumer + own stores (service quality issues; CCPA intervention) | M7: Ola Hypercharger network | N7: FULLY VERTICALLY INTEGRATED: in-house 4680 Bharat Cell (mass deliveries Nov-2025) + in-house ferrite (rare-earth-free) motor | O7: Auto gross margin 30.6% FY26 (Q4 38.5%); Q4 FY26 first CFO-positive quarter (Rs91 cr); breakeven cut from 50,000 to <25,000 units/month | P7: CLAIMED: vertical integration. OBSERVED: no moat — share fell 30% to c.12% in one year. | Q7: HIGH | R7: Company disclosures / Business Standard / Vahan (2026)
A8: Hero MotoCorp (Vida) | B8: Listed ICE incumbent | C8: HEROMOTOCO (NSE/BSE) | D8: Large-cap (HMCL IN) | E8: Long listed | F8: Self-funded; also c.37% owner of Ather and investor in Zero Motorcycles (US) | G8: Not disclosed separately | H8: EV cross-subsidised | I8: 144,330 (FY26 e-2W, +196% — fastest growth among incumbents) | J8: Chittoor, Andhra Pradesh | K8: >Rs1,500 cr FY27 EV capex | L8: c.6,000+ ICE touchpoints being converted to Vida sales/service | M8: 5,900+ public fast-charging points cited by Vida | N8: Outsourced cells; removable-pack architecture; Zero Motorcycles tie-up for e-motorcycle tech | O8: Scaling Vida from c.15,000 to c.45,000 units/month | P8: LARGEST DISTRIBUTION NETWORK IN INDIA + dual exposure via the Ather stake | Q8: HIGH | R8: Vahan / vidaworld.com / company commentary
A9: Honda Motorcycle & Scooter India (HMSI) | B9: Unlisted subsidiary of Honda Motor | C9: n.a. (parent 7267 JP) | D9: n.a. | E9: n.a. | F9: Parent-funded | G9: Not disclosed | H9: Not disclosed | I9: Small (Activa e: + QC1 only) | J9: Narsapura, Karnataka | K9: Not disclosed | L9: India's largest scooter dealer network (Activa franchise) | M9: Honda e:Swap swapping stations (Bengaluru, Delhi, Mumbai) via Honda Power Pack Energy India | N9: Honda Mobile Power Pack e: swappable architecture | O9: 30 EV models globally by 2030 (Activa e: and QC1 were #12 and #13) | P9: THE ACTIVA BRAND + the deepest scooter service network. Currently unconverted into EV share. | Q9: HIGH | R9: Honda Global (Nov-2024) / Autocar India
A10: Eicher Motors (Royal Enfield / Flying Flea) | B10: Listed ICE incumbent | C10: EICHERMOT (NSE/BSE) | D10: Large-cap (EIM IN) | E10: Long listed | F10: Self-funded | G10: Not disclosed for EV | H10: EV loss-making, immaterial to group | I10: Small (Flying Flea C6 launched Apr-2026) | J10: Chennai | K10: Not separately disclosed | L10: RE's global premium dealer network + dedicated Flying Flea retail (Bengaluru expansion) | M10: Partnerships | N10: Outsourced cells; purpose-built EV platform | O10: Flying Flea as a distinct EV sub-brand; S6 to follow C6 | P10: GLOBAL HERITAGE BRAND EQUITY — unmatched by any EV-native player | Q10: HIGH | R10: BikeWale / Electrek (Apr-2026)
A11: Suzuki Motorcycle India | B11: Unlisted subsidiary | C11: n.a. (parent 7269 JP) | D11: n.a. | E11: n.a. | F11: Parent-funded | G11: Not disclosed | H11: Not disclosed | I11: Small (e-Access from Jan-2026) | J11: Kherki Dhaula, Haryana | K11: Not disclosed | L11: Suzuki 2W dealer network | M11: Partnerships | N11: Outsourced cells | O11: Phased e-Access rollout | P11: THE ACCESS 125 NAMEPLATE (India's best-selling 125cc scooter) | Q11: MEDIUM | R11: Autocar Professional / 91wheels
A12: Yamaha Motor India | B12: Unlisted subsidiary | C12: n.a. (parent 7272 JP) | D12: n.a. | E12: n.a. | F12: Parent-funded; also a Series B investor in River Mobility (Feb-2024) | G12: Not disclosed | H12: Not disclosed | I12: Very small (EC-06) | J12: CONTRACT-MANUFACTURED BY RIVER at Hoskote, Karnataka | K12: Minimal — capex avoided via contract manufacturing | L12: Yamaha 2W network | M12: Partnerships | N12: Buys the platform rather than building it | O12: Not disclosed | P12: NONE SPECIFIC TO EV — Yamaha has explicitly chosen to buy rather than build | Q12: HIGH | R12: Autocar India / BikeWale (Jul-2026)
A13: Greaves Electric Mobility (Greaves Cotton) | B13: Listed parent | C13: GREAVESCOT (NSE/BSE) | D13: Mid-cap | E13: Parent listed | F13: Parent-funded; Abdul Latif Jameel investment | G13: Not separately disclosed | H13: Loss-making | I13: 61,563 (FY26, +53.3%) | J13: Ranipet, Tamil Nadu | K13: Not disclosed | L13: Ampere dealer network | M13: Partnerships | N13: Outsourced cells; LFP on Nexus | O13: Portfolio refresh | P13: RECOVERING FROM FAME-II CLAWBACK — subsidy-era damage still visible | Q13: MEDIUM | R13: Vahan / company disclosures
A14: River Mobility | B14: Private EV pure-play | C14: n.a. | D14: Not disclosed | E14: Private | F14: Series C USD120m (c.Rs1,141 cr, Nov-2025) led by Elev8 Venture Partners and Claypond Capital (Ranjan Pai family office); Series B USD40m (Feb-2024, led by Yamaha); Series A USD15m. Strategic backers: Yamaha, Al-Futtaim, Mitsui, Marubeni, Toyota Ventures, Lowercarbon | G14: c.Rs1bn FY25; 'quadrupled' in FY26 (company statement) | H14: Loss-making | I14: c.28,000 units (CY2025); +426% in FY26 off a small base | J14: Hoskote, Karnataka | K14: Funded by Series C | L14: Growing own retail | M14: Partnerships | N14: Outsourced cells | O14: Second premium utility scooter targeted mid-2027 | P14: UTILITY NICHE + contract-manufacturing revenue from Yamaha (a genuinely differentiated business model) | Q14: HIGH | R14: Mercom / Autocar India / EVreporter (Nov-2025)
... A20: Hero Electric / Okinawa / Benling / Amo (first generation) | B20: Private — effectively exited or sub-scale | C20: n.a. | D20: n.a. | E20: Private | F20: Historic | G20: Collapsed | H20: Collapsed | I20: Collectively c.31% share in 2022, now negligible | J20: Ludhiana / Bhiwadi | K20: Historic | L20: Collapsed | M20: n.a. | N20: Imported kits (the cause of the FAME-II violations) | O20: n.a. | P20: NONE — the case study that proves easy entry also means easy exit | Q20: HIGH | R20: MHI FAME-II show-cause (May-2023); SFIO alleged Rs297 cr fraud; Rs469 cr refund demanded, c.Rs1,200 cr withheld; >80% staff laid off at Hero Electric and Benling. MHI committee gave Hero Electric and Okinawa a 'clean chit' Apr-2024.

Sheet Volumes_MarketShare
A1: VAHAN REGISTRATIONS AND MARKET SHARE — e-2W BY OEM
A2: Vahan retail registrations. FY22-FY24 figures are rounded industry compilations; FY25, FY26 and Jul-26 are the reliable series. Share, YoY and CAGR are live formulas.
A3: OEM | B3: FY22 | C3: FY23 | D3: FY24 | E3: FY25 | F3: FY26 | G3: Jul-26 (month) | H3: FY26 share % | I3: FY25 share % | J3: Share change (pp) | K3: FY26 YoY % | L3: FY22-FY26 CAGR %
A4: TVS Motor | B4: 9000 | C4: 94000 | D4: 180000 | E4: 237929 | F4: 341513 | G4: 55477 | H4: =IFERROR(F4/F$13,"n/a") -> 0.2436215 | I4: =IFERROR(E4/E$13,"n/a") -> 0.20675275 | J4: =IFERROR((F4/F$13-E4/E$13)*100,"n/a") -> 3.6868745 | K4: =IFERROR(F4/E4-1,"n/a") -> 0.43535677 | L4: =IFERROR((F4/B4)^(1/4)-1,"n/a") -> 1.4819395
A5: Bajaj Auto | B5: 4000 | C5: 36000 | D5: 116000 | E5: 231172 | F5: 289349 | G5: 45592 | H5: =IFERROR(F5/F$13,"n/a") -> 0.20640982 | I5: =IFERROR(E5/E$13,"n/a") -> 0.20088113 | J5: =IFERROR((F5/F$13-E5/E$13)*100,"n/a") -> 0.55286854 | K5: =IFERROR(F5/E5-1,"n/a") -> 0.2516611 | L5: =IFERROR((F5/B5)^(1/4)-1,"n/a") -> 1.9163557
A6: Ather Energy | B6: 20000 | C6: 92000 | D6: 109000 | E6: 131172 | F6: 239178 | G6: 29500 | H6: =IFERROR(F6/F$13,"n/a") -> 0.17061987 | I6: =IFERROR(E6/E$13,"n/a") -> 0.11398431 | J6: =IFERROR((F6/F$13-E6/E$13)*100,"n/a") -> 5.663556 | K6: =IFERROR(F6/E6-1,"n/a") -> 0.82339219 | L6: =IFERROR((F6/B6)^(1/4)-1,"n/a") -> 0.85961401
A7: Ola Electric | B7: 14000 | C7: 152000 | D7: 329000 | E7: 344300 | F7: 164295 | G7: 14102 | H7: =IFERROR(F7/F$13,"n/a") -> 0.11720138 | I7: =IFERROR(E7/E$13,"n/a") -> 0.29918578 | J7: =IFERROR((F7/F$13-E7/E$13)*100,"n/a") -> -18.19844 | K7: =IFERROR(F7/E7-1,"n/a") -> -0.52281441 | L7: =IFERROR((F7/B7)^(1/4)-1,"n/a") -> 0.85086217
A8: Hero MotoCorp (Vida) | B8: 0 | C8: 3000 | D8: 25000 | E8: 48738 | F8: 144330 | G8: 22883 | H8: =IFERROR(F8/F$13,"n/a") -> 0.10295916 | I8: =IFERROR(E8/E$13,"n/a") -> 0.042351776 | J8: =IFERROR((F8/F$13-E8/E$13)*100,"n/a") -> 6.0607382 | K8: =IFERROR(F8/E8-1,"n/a") -> 1.9613443 | L8: =IFERROR((F8/B8)^(1/4)-1,"n/a") -> n/a
A9: Greaves / Ampere | B9: 24000 | C9: 88000 | D9: 45000 | E9: 40169 | F9: 61563 | G9: n/a | H9: =IFERROR(F9/F$13,"n/a") -> 0.043916543 | I9: =IFERROR(E9/E$13,"n/a") -> 0.034905587 | J9: =IFERROR((F9/F$13-E9/E$13)*100,"n/a") -> 0.90109561 | K9: =IFERROR(F9/E9-1,"n/a") -> 0.53259977 | L9: =IFERROR((F9/B9)^(1/4)-1,"n/a") -> 0.26554366
A10: Hero Electric | B10: 65000 | C10: 103000 | D10: 25000 | E10: 5000 | F10: 1000 | G10: n/a | H10: =IFERROR(F10/F$13,"n/a") -> 0.00071335937 | I10: =IFERROR(E10/E$13,"n/a") -> 0.0043448414 | J10: =IFERROR((F10/F$13-E10/E$13)*100,"n/a") -> -0.3631482 | K10: =IFERROR(F10/E10-1,"n/a") -> -0.8 | L10: =IFERROR((F10/B10)^(1/4)-1,"n/a") -> -0.64781435
A11: Okinawa Autotech | B11: 46000 | C11: 96000 | D11: 18000 | E11: 4000 | F11: 1000 | G11: n/a | H11: =IFERROR(F11/F$13,"n/a") -> 0.00071335937 | I11: =IFERROR(E11/E$13,"n/a") -> 0.0034758731 | J11: =IFERROR((F11/F$13-E11/E$13)*100,"n/a") -> -0.27625137 | K11: =IFERROR(F11/E11-1,"n/a") -> -0.75 | L11: =IFERROR((F11/B11)^(1/4)-1,"n/a") -> -0.61601829
A12: Others (River, Simple, Kinetic, BGauss, Bounce, Pure, Joy, regional tail) | B12: 49000 | C12: 64000 | D12: 100000 | E12: 108310 | F12: 159590 | G12: n/a | H12: =IFERROR(F12/F$13,"n/a") -> 0.11384502 | I12: =IFERROR(E12/E$13,"n/a") -> 0.094117954 | J12: =IFERROR((F12/F$13-E12/E$13)*100,"n/a") -> 1.9727067 | K12: =IFERROR(F12/E12-1,"n/a") -> 0.47345582 | L12: =IFERROR((F12/B12)^(1/4)-1,"n/a") -> 0.34339089
A13: TOTAL INDUSTRY (Vahan) | B13: =SUM(B4:B12) -> 231000 | C13: =SUM(C4:C12) -> 728000 | D13: =SUM(D4:D12) -> 947000 | E13: =SUM(E4:E12) -> 1150790 | F13: =SUM(F4:F12) -> 1401818 | G13: =SUM(G4:G12) -> 167554 | H13: =IFERROR(F13/F$13,"n/a") -> 1 | I13: =IFERROR(E13/E$13,"n/a") -> 1 | J13: =IFERROR((F13/F$13-E13/E$13)*100,"n/a") -> 0 | K13: =IFERROR(F13/E13-1,"n/a") -> 0.21813537 | L13: =IFERROR((F13/B13)^(1/4)-1,"n/a") -> 0.56953105
A15: THE FY26 STORY IN ONE LINE: Ola fell 52 per cent while every incumbent grew. The four legacy players took roughly 80 per cent of the market.
A16: FADA H1 CY2026: 970,993 units, +53.3 per cent YoY. The top four (TVS, Bajaj, Hero, Ather) took 95.6 per cent of INCREMENTAL registrations. Ola registrations fell 44.1 per cent; share 6.8 per cent.
A17: Monthly milestones: Mar-26 c.190,941 (record at the time); Jun-26 194,300 (+75.5 per cent YoY); Jul-26 204,266 — the first month above 2 lakh. CY26 seven-month tally 11.7 lakh, +56 per cent YoY.
A18: Ola's monthly share fell as low as c.5.4 per cent in Mar-2026 (Whalesbook / Autocar Professional) before recovering to c.8 per cent by Jul-2026.
A19: Bengaluru was India's largest e-2W city in FY26 (98,892 units), ahead of Delhi (41,238).
A20: CAVEAT: FY22-FY24 OEM splits are rounded compilations from industry sources and should be treated as indicative. FY25 onward is reliable.

Sheet Industry_Penetration
A1: INDUSTRY VOLUMES AND EV PENETRATION
A2: Penetration and YoY are live formulas. Total 2W figures for FY22-FY25 are industry estimates; FY26 is the reported base.
A3: Fiscal year | B3: e-2W registrations | C3: Total 2W registrations | D3: EV penetration % | E3: e-2W YoY % | F3: Commentary
A4: FY22 | B4: 231000 | C4: 13500000 | D4: =IFERROR(B4/C4,"n/a") -> 0.017111111 | E4: n/a | F4: First real scale year; first-generation players (Hero Electric, Okinawa, Ampere) led
A5: FY23 | B5: 728000 | C5: 15900000 | D5: =IFERROR(B5/C5,"n/a") -> 0.045786164 | E5: =IFERROR(B5/B4-1,"n/a") -> 2.1515152 | F5: FAME-II peak subsidy year; explosive growth
A6: FY24 | B6: 947000 | C6: 17970000 | D6: =IFERROR(B6/C6,"n/a") -> 0.052698943 | E6: =IFERROR(B6/B5-1,"n/a") -> 0.30082418 | F6: FAME-II clawback year; first-generation players collapse
A7: FY25 | B7: 1150790 | C7: 18900000 | D7: =IFERROR(B7/C7,"n/a") -> 0.06088836 | E7: =IFERROR(B7/B6-1,"n/a") -> 0.21519535 | F7: Ola peaks at c.30% share
A8: FY26 | B8: 1401818 | C8: 21430000 | D8: =IFERROR(B8/C8,"n/a") -> 0.065413812 | E8: =IFERROR(B8/B7-1,"n/a") -> 0.21813537 | F8: Incumbents take over: top-4 c.80% share; Ola collapses; 6.54% penetration
A10: FY26 penetration of 6.54 per cent is the number that matters. It is far below NITI Aayog's targets.
A11: NITI Aayog's original 2019 target (with RMI) was 80 per cent of two- and three-wheelers electrified by 2030. The 2022 NITI-BCG revision cut this to 35-40 per cent. NITI's own September 2025 report noted EVs were only about 7.6 per cent of total vehicle sales in 2024.
A12: FY26 e-2W penetration is tracking c.6.5 per cent. Any model using the 30 per cent-plus 2030 penetration assumptions still circulating in sell-side research is anchored to a target that has already been abandoned twice.
A13: The demand test now under way: the PM E-DRIVE e-2W incentive lapsed 31-Jul-2026. If monthly volumes hold above c.1.7-2.0 lakh through Aug-Oct 2026, demand resilience is confirmed. A sharp drop would signal continued subsidy dependence.
A14: Scooters are roughly 95 per cent or more of e-2W volume. E-motorcycles remain under 5 per cent, held back by price, range on longer use-cases, weaker commuter TCO and, until 2026, almost no product availability.

Sheet Supply_Chain_Barriers
A1: SUPPLY CHAIN AND ENTRY BARRIERS — WHAT CAN BE BOUGHT AND WHAT CANNOT
A2: The analytical core. Powertrain components are outsourceable, so they are not moats. Distribution, brand, software and charging are not outsourceable, so they are.
A3: Component / capability | B3: Suppliers | C3: Outsourceability | D3: Barrier height | E3: Detail | F3: India context / mitigants | G3: READ-ACROSS TO THE ENTRY-BARRIER THESIS
A4: Battery cells | B4: LG Chem, Samsung SDI, EVE, CATL, Gotion, Amara Raja, Exide, TDSG, Log9 | C4: EASILY OUTSOURCED | D4: LOW | E4: Largest single BOM line. Merchant market is deep and global. Ola is the only Indian e-2W OEM making its own cells (4680 Bharat Cell, Krishnagiri, c.2.5 GWh operational). | F4: Domestic gigafactories in build: Exide-SVOLT, Amara Raja-Gotion, Reliance, Tata Agratas, JSW. | G4: THESIS SUPPORT: a new entrant can buy world-class cells off the shelf. This is the core reason EV 2W entry barriers are lower than ICE.
A5: Hub / PMSM motors | B5: Bosch, Napino, Lucas TVS, numerous Chinese suppliers; in-house at Ather, Ola, Tork | C5: EASILY OUTSOURCED | D5: LOW | E5: Hub motors are commoditised. Mid-drive and axial-flux designs (Tork) are harder. | F5: Sona Comstar developed a ferrite-assisted synchronous reluctance (rare-earth-free) motor for 2W/3W; magnet-less motor JVs with IRP Nexus (Israel) and Enedym (Canada). Sona's global differential-gear share reached c.8.7% in CY25 (from 4.5% in 2019). | G5: THESIS SUPPORT: motor supply is not a barrier. Ola's in-house ferrite motor is a rare-earth hedge, not a moat.
A6: Controllers / MCU / BMS | B6: Bosch, Napino, Varroc, Minda, Uno Minda, Sandhar; in-house at Ather, Ola, Ultraviolette | C6: OUTSOURCEABLE | D6: LOW-MEDIUM | E6: Merchant supply is adequate for mass products. In-house BMS matters for premium range/thermal claims. | F6: n/a | G6: Partial differentiation possible but rarely decisive at the mass end.
A7: On-board / off-board chargers | B7: Delta, Exicom, Servotech, in-house | C7: EASILY OUTSOURCED | D7: LOW | E7: Charger wattage is now a marketed spec (Vida's 580W vs 1,000W RQ variant is literally a charger-bundle SKU). | F7: n/a | G7: Charging SPEED is becoming a differentiator; charger HARDWARE is not.
A8: Rare-earth permanent magnets (NdFeB) | B8: Overwhelmingly China-dependent | C8: CONSTRAINED | D8: HIGH (2025-26) | E8: China's April-2025 export controls cost Sona Comstar c.3 weeks of production. | F8: Mitigants: Rs7,280 cr Indian sintered-magnet scheme (Nov-2025, 6,000 MTPA); ferrite/SRM motor designs at Sona and Ola. | G8: KEY SWING FACTOR on FY27 output and margins. A renewed China squeeze is the main downside risk to e-2W production.
A9: Software stack / OS | B9: In-house only (AtherStack, Ola MoveOS, Tork TIROS, Vida, UV) | C9: NOT OUTSOURCEABLE | D9: HIGH | E9: Cannot be bought. Enables OTA, subscriptions (Ather Pro Pack Rs14,000-20,000), telematics and connected features. | F9: n/a | G9: MOAT: one of the few genuinely defensible layers. Also the only recurring-revenue mechanism in the industry.
A10: Distribution and service network | B10: Owned | C10: NOT OUTSOURCEABLE | D10: VERY HIGH | E10: Hero has c.6,000+ ICE touchpoints; TVS, Bajaj and Honda comparably deep. Pure-plays must build from zero. | F10: Ather c.400 experience centres after 8 years. | G10: THE PRIMARY MOAT. It is what killed Ola (service failures, CCPA intervention) and what made TVS/Bajaj/Hero winners in FY26.
A11: Fast-charging network | B11: Owned or partnered | C11: NOT EASILY OUTSOURCEABLE | D11: MEDIUM-HIGH | E11: Ather Grid >5,000-6,100 points in 370-395 cities; Vida cites 5,900+; Ola Hypercharger; UV Supernova; TVS via Jio-bp. | F11: Swapping: Sun Mobility, Battery Smart, Honda Power Pack Energy, Chargeup, Zypp. | G11: Capital-intensive and slow to build. Raptee's CCS2 high-voltage approach sidesteps it by using the car network.
A12: Brand and trust | B12: Owned | C12: NOT OUTSOURCEABLE | D12: VERY HIGH | E12: Decisive in Ola's fall and in RE Flying Flea's and Suzuki e-Access's launches. | F12: n/a | G12: THE OTHER PRIMARY MOAT — and the one ICE incumbents already own outright.
A13: Vehicle dynamics, thermal management, NVH | B13: In-house engineering | C13: PARTIALLY OUTSOURCEABLE | D13: MEDIUM | E13: Matter's liquid-cooled pack and Ultraviolette's thermal work are genuine engineering differentiators. | F13: n/a | G13: The residual engineering barrier — real, but far lower than designing and industrialising an ICE engine.
A14: Contract manufacturing | B14: River manufactures the Yamaha EC-06 at Hoskote | C14: FULLY OUTSOURCEABLE | D14: VERY LOW | E14: A global OEM chose to buy an Indian startup's platform rather than build its own. | F14: n/a | G14: THESIS-CRITICAL EXHIBIT: the single clearest proof that EV 2W entry barriers are structurally low.
A16: Colour logic: GREEN = a high barrier, so a potential moat. RED = a low barrier, so not a moat. Every powertrain component is red. Every customer-facing capability is green. That asymmetry is the thesis.

Sheet Regulatory_Subsidy
A1: REGULATORY AND SUBSIDY LANDSCAPE
A2: The PM E-DRIVE e-2W demand incentive lapsed on 31 July 2026. This is the single most important near-term variable for the sector.
A3: Policy / regulation | B3: Detail | C3: Current status | D3: Confidence | E3: Source | F3: Why it matters
A4: PM E-DRIVE — e-2W demand incentive | B4: Rs2,500/kWh from Apr-2025 (cap Rs5,000; 15% of ex-factory; max ex-factory Rs1.5 lakh). Was Rs5,000/kWh in FY25 (cap Rs10,000). | C4: LAPSED 31-Jul-2026 for e-2Ws | D4: CONFIRMED | E4: MHI / PM E-DRIVE portal; electrive; DriveSpark | F4: THE SINGLE MOST IMPORTANT NEAR-TERM VARIABLE. No central per-kWh incentive for e-2Ws registered from Aug-2026. Aug-Oct 2026 monthly volumes are the demand-resilience test.
A5: PM E-DRIVE — scheme envelope | B5: Rs10,900 cr total outlay. Aug-2026 amendment raised the e-2W cap to 4,579,120 units and extended the overall scheme (e-3W, bus, truck, charging) to 31-Mar-2028. | C5: Active for non-2W categories to Mar-2028 | D5: CONFIRMED | E5: MHI / PM E-DRIVE portal (Aug-2026) | F5: e-2W demand incentive is over even though the scheme continues.
A6: GST 2.0 (effective 22-Sep-2025) | B6: ICE 2W <=350cc cut from 28% to 18%. ICE 2W >350cc raised to c.40% (from c.31% effective). EVs UNCHANGED at 5%. | C6: In force | D6: CONFIRMED | E6: GST Council | F6: Narrowed the EV/ICE price gap by c.Rs7,000-12,000 on commuters — yet e-2W volumes still grew through FY26. Bullish demand signal. The >350cc 40% slab hits premium ICE (KTM, RE 440/450/650, Triumph, Harley) but not EVs.
A7: FAME-II localisation clawback | B7: MHI show-cause notices (May-2023) to Hero Electric, Okinawa, Ampere/Greaves, Benling, Revolt, Amo for PMP/localisation violations. Rs469 cr refund demanded; c.Rs1,200 cr subsidies withheld. SFIO alleged c.Rs297 cr (USD35m) fraud. | C7: Largely concluded; MHI committee gave Hero Electric and Okinawa a 'clean chit' Apr-2024 | D7: CONFIRMED / REPORTED | E7: Inc42; Business Today; Deccan Herald; Reuters | F7: The event that destroyed the first generation of Indian e-2W players. Reputational and cash damage proved terminal even where the legal outcome was favourable.
A8: AIS-156 battery safety norms | B8: Mandatory battery safety, thermal propagation and cell-level testing standards following the 2022 fire incidents. | C8: In force | D8: CONFIRMED | E8: MoRTH / ARAI | F8: Raised the compliance bar meaningfully — one of the few REAL barriers to entry created since 2022. Weeded out the cheapest imported-kit assemblers.
A9: Auto PLI and ACC PLI | B9: Auto PLI for advanced automotive technology products; ACC PLI for battery cell manufacturing. | C9: Active | D9: CONFIRMED | E9: MHI | F9: Ather and others are PLI-certified. ACC PLI underwrites Ola's, Exide's and Amara Raja's cell ambitions.
A10: Sintered Rare Earth Permanent Magnet scheme | B10: Rs7,280 cr approved by Union Cabinet 26-Nov-2025 (Rs6,450 cr sales-linked incentives + Rs750 cr capital subsidy) for 6,000 MTPA across five beneficiaries. Supersedes an earlier Rs1,345 cr proposal. | C10: Approved; incentives from FY27 | D10: CONFIRMED | E10: PIB / pmindia.gov.in (26-Nov-2025) | F10: India's structural answer to China's April-2025 rare-earth export controls, which cost Sona Comstar c.3 weeks of production.
A11: State EV policies | B11: Delhi, Maharashtra, Karnataka, UP, Gujarat, Tamil Nadu, Rajasthan offer road-tax and registration exemptions plus, in some cases, per-kWh top-ups. | C11: Varies by state | D11: CONFIRMED / REPORTED | E11: State transport departments | F11: With the central e-2W incentive gone, state policy becomes the marginal price lever. Bengaluru was India's largest e-2W city in FY26 (98,892 units) vs Delhi (41,238).
A12: Low-speed EV exemption (<250W, <25 km/h) | B12: No driving licence or registration required. | C12: In force | D12: CONFIRMED | E12: CMVR | F12: IMPORTANT DATA CAVEAT: these vehicles do NOT appear in Vahan registration data, so all industry volume figures understate the true e-2W market.

Sheet BOM_Economics
A1: CELL AND PACK COST ECONOMICS
A2: Falling, outsourceable cell costs are the mechanism that lowers entry barriers. The FX cell is editable and drives every INR figure below.
A3: Item | B3: Value | C3: Unit | D3: Source | E3: Note
A4: Volume-weighted average battery PACK price (2025) | B4: 108 | C4: USD/kWh | D4: BloombergNEF annual battery price survey, 09-Dec-2025 | E4: Record low, -8% YoY
A5: BEV pack price (2025) | B5: 99 | C5: USD/kWh | D5: BloombergNEF, Dec-2025 | E5: First time below USD100/kWh
A6: LFP pack price (2025) | B6: 81 | C6: USD/kWh | D6: BloombergNEF, Dec-2025 | E6: LFP migration is what held pack prices down despite lithium's 2026 rebound
A7: NMC pack price (2025) | B7: 128 | C7: USD/kWh | D7: BloombergNEF, Dec-2025 | E7: Most Indian e-2Ws use NMC; Oben and Ampere use LFP
A8: Cell price (2025) | B8: 74 | C8: USD/kWh | D8: BloombergNEF, Dec-2025 | E8: Cell is c.70-75% of pack cost
A9: Cost of materials as % of total expenditure (Ather, Q1 FY27) | B9: 0.75 | C9: % of total expenditure | D9: Ather Q1 FY27 disclosure | E9: Mainly cells — the single dominant BOM line
A10: Ather adjusted gross margin ex-incentives (Q3 FY26) | B10: 0.23 | C10: % | D10: Ather disclosures | E10: Approaching ICE-2W gross-margin territory
A11: Ola auto gross margin (FY26) | B11: 0.306 | C11: % | D11: Ola FY26 disclosures | E11: Q4 FY26 reached 38.5%
A12: Ola auto-EBITDA breakeven volume (post Gen-3 BOM work) | B12: 25000 | C12: units/month | D12: Ola company statements | E12: Cut from 50,000/month — falling cell costs structurally lower the entry hurdle
A13: Lithium carbonate price move into 2026 | B13: 2 | C13: x YoY (early 2026) | D13: IEA | E13: Still c.70% below the 2022 peak; pack prices held via LFP migration and long-term contracts
A14: USD/INR assumption for BOM conversion | B14: 87 | C14: INR/USD | D14: Analyst assumption — UPDATE THIS CELL | E14: BLUE = user input. All INR BOM maths keys off this cell.
A16: DERIVED PACK COST BY BATTERY SIZE (at 2025 BNEF benchmarks)
A17: Pack size (kWh) | B17: Pack cost at USD108/kWh (USD) | C17: Pack cost (Rs) | D17: Pack cost (Rs) if LFP at USD81/kWh | E17: Indicative pack cost as % of a Rs1.20 lakh scooter
A18: 2.2 | B18: =A18*$B$4 -> 237.6 | C18: =B18*$B$14 -> 20671.2 | D18: =A18*$B$6*$B$14 -> 15503.4 | E18: =C18/120000 -> 0.17226
A19: 2.5 | B19: =A19*$B$4 -> 270 | C19: =B19*$B$14 -> 23490 | D19: =A19*$B$6*$B$14 -> 17617.5 | E19: =C19/120000 -> 0.19575
A20: 3 | B20: =A20*$B$4 -> 324 | C20: =B20*$B$14 -> 28188 | D20: =A20*$B$6*$B$14 -> 21141 | E20: =C20/120000 -> 0.2349
A21: 3.5 | B21: =A21*$B$4 -> 378 | C21: =B21*$B$14 -> 32886 | D21: =A21*$B$6*$B$14 -> 24664.5 | E21: =C21/120000 -> 0.27405
A22: 4 | B22: =A22*$B$4 -> 432 | C22: =B22*$B$14 -> 37584 | D22: =A22*$B$6*$B$14 -> 28188 | E22: =C22/120000 -> 0.3132
A23: 5 | B23: =A23*$B$4 -> 540 | C23: =B23*$B$14 -> 46980 | D23: =A23*$B$6*$B$14 -> 35235 | E23: =C23/120000 -> 0.3915
A24: 5.4 | B24: =A24*$B$4 -> 583.2 | C24: =B24*$B$14 -> 50738.4 | D24: =A24*$B$6*$B$14 -> 38053.8 | E24: =C24/120000 -> 0.42282
A25: 7.1 | B25: =A25*$B$4 -> 766.8 | C25: =B25*$B$14 -> 66711.6 | D25: =A25*$B$6*$B$14 -> 50033.7 | E25: =C25/120000 -> 0.55593
A26: 10.3 | B26: =A26*$B$4 -> 1112.4 | C26: =B26*$B$14 -> 96778.8 | D26: =A26*$B$6*$B$14 -> 72584.1 | E26: =C26/120000 -> 0.80649
A28: Read: an NMC pack for a 3.0 kWh mass-market scooter costs roughly a third of the vehicle's retail price at 2025 benchmarks. Every dollar off the cell price lowers the capital a new entrant needs and cuts breakeven volume — which is precisely why Ola was able to cut its stated auto-EBITDA breakeven from 50,000 to under 25,000 units a month. Lower breakeven means more entrants, not fewer. The Rs1.20 lakh denominator is an illustrative mass-market price point, not a specific model.

Sheet Sources
A1: MASTER SOURCE LIST
A2: Primary sources first. Aggregators are used only for specification and price fields where OEMs do not publish machine-readable data.
A3: Source | B3: Type | C3: Used for | D3: As-of / accessed
A4: Vahan / Parivahan dashboard (MoRTH) | B4: PRIMARY — government | C4: All registration volumes and market share | D4: Aug-2026
A5: FADA monthly and H1 CY2026 retail data | B5: PRIMARY — industry body | C5: Retail volumes, incremental share analysis | D5: Jul-2026
A6: atherenergy.com (Rizta and 450 spec sheets) | B6: PRIMARY — OEM | C6: Ather specifications, warranty, Ather Grid size | D6: Aug-2026
A7: tvsmotor.com (iQube variant pages) | B7: PRIMARY — OEM | C7: TVS iQube specifications, charging times, features | D7: Aug-2026
A8: chetak.com (series 25 / 30 / 35 pages) | B8: PRIMARY — OEM | C8: Bajaj Chetak specifications, boot space, warranty | D8: Aug-2026
A9: vidaworld.com (compare and variant pages) | B9: PRIMARY — OEM | C9: Vida VX2 full variant ladder, ranges, charge times | D9: Aug-2026
A10: ultraviolette.com | B10: PRIMARY — OEM | C10: F77 Mach 2, X47, Shockwave, Tesseract specs and timing | D10: Aug-2026
A11: Honda Global press release (30 EV models by 2030) | B11: PRIMARY — OEM | C11: Honda EV roadmap | D11: Nov-2024
A12: Ola Electric investor disclosures and Sankalp 2025 | B12: PRIMARY — OEM | C12: FY26 financials, 4680 cell, Roadster and Diamondhead | D12: 2025-2026
A13: Ather Energy NSE/BSE filings and IPO prospectus | B13: PRIMARY — regulatory | C13: IPO size, FY25/FY26/Q1 FY27 financials, capacity | D13: 2025-2026
A14: MHI / PM E-DRIVE scheme portal and notifications | B14: PRIMARY — government | C14: Subsidy rates, caps, terminal dates, scheme amendment | D14: Aug-2026
... A26: BikeWale / BikeDekho / ZigWheels / 91wheels | B26: AGGREGATOR | C26: Variant-level prices and specifications where OEMs do not publish | D26: Aug-2026
A28: Aggregator caution: BikeWale, BikeDekho, ZigWheels and 91wheels frequently disagree on ex-showroom prices, particularly since the PM E-DRIVE incentive lapsed on 31 July 2026. Where they conflict materially, the conflict is flagged in the Analyst notes column of the relevant model sheet rather than silently resolved.
