Workbook

Sheet Cover & Guide
A1: INDIA AUTO — COMMODITY COST MONITOR
A2: Proprietary commodity price database and blended cost-index framework for Indian and global auto OEM coverage.
A4: PURPOSE
A5: Turns the monthly SIAM Commodity Price Monitor into (i) a clean rolling raw database, (ii) FX-adjusted INR indices,
A6: (iii) segment-level bill-of-material baskets, and (iv) a quarterly QoQ / YoY cost read with a gross-margin translation.
A8: WHAT THIS ANSWERS
A9: 1. How much higher are commodity costs this quarter vs last quarter and vs last year — by segment, not just headline steel.
A10: 2. Which sub-complex (ferrous / non-ferrous / PGM / polymer / rubber / battery / energy) is driving the move.
A11: 3. What that means for OEM gross margin in bps, after inventory lag and assumed price pass-through.
A13: SHEET MAP
A14: Assumptions | B14: All levers live here — currency basis, base month, forecast drift, segment weights, RM % of ASP, pass-through, lag.
A15: Raw Data | B15: SIAM-reported prices, as published, in native units. THE ONLY SHEET YOU TYPE INTO EACH MONTH.
A16: INR Normalised | B16: Everything restated in INR per kg (or INR per bbl / litre) at the month's USD-INR. Captures currency drag.
A17: Commodity Indices | B17: Each commodity rebased to 100 at the chosen base month, on the chosen currency basis.
A18: Basket Weights | B18: The proprietary weight matrix: 6 segment BOM baskets + 7 sub-complex monitors. Edit weights here.
A19: Basket Monitors | B19: Monthly basket indices = weighted sum of commodity indices. Includes the blended India Auto Composite.
A20: Quarterly Dashboard | B20: The output page. Quarterly basket levels, QoQ, YoY, plus the current-quarter build-up and a commodity-level table.
A21: Margin & Scenarios | B21: Lagged realised cost move to gross-margin bps, and bear / base / bull scenarios for the current quarter.
A22: Methodology | B22: Full write-up of index construction, weighting logic, lag and pass-through treatment, and known limitations.
A23: Update Log | B23: Monthly update checklist and the version history.
A25: COLOUR CONVENTION
A26: Blue text | B26: Hardcoded input or scenario lever — safe to change.
A27: Black text | B27: Formula — do not overwrite.
A28: Green text | B28: Link to another sheet.
A29: Yellow fill | B29: Key assumption you should review before publishing anything off this.
A31: IMPORTANT DATA CAVEATS
A32: The SIAM deck's data tables start at July 2025 (through the latest edition). April-June 2025 appear only as plotted points on
A33: the FY26 chart lines and are not published as numbers, so they are NOT in this database. The series therefore begins Jul-25,
A34: which conveniently equals the start of Q2FY26. Q1FY26 comparisons are not possible from this source alone.
A35: The Baltic Dry Index was not published in the Aug-26 edition (marked '*' by SIAM); it is carried flat from Jul-26 and flagged
A36: in the Raw Data notes column. This affects only the Energy & Freight sub-complex monitor, not any segment BOM basket.
A38: Source: Society of Indian Automobile Manufacturers (SIAM), Commodity Price Monthly Monitor, August 2026 edition. Framework and weights are proprietary.

Sheet Assumptions
A1: ASSUMPTIONS & LEVERS
A2: Every blue cell is an input. Nothing else on this sheet should be overwritten.
A4: INDEX CONSTRUCTION
A5: Currency basis for indices | C5: INR | D5: INR basis captures rupee depreciation on dollar-priced inputs — that is what OEMs actually pay.
A6: Base month (= 100) | C6: Jul-25 | D6: Must exactly match a column header on Raw Data row 5.
A7: Base column position (calculated) | C7: =MATCH($C$6,'Raw Data'!$F$5:$S$5,0) -> 1 | D7: Do not edit.
A9: CURRENT-QUARTER FORECAST
A10: Latest actual month | C10: Aug-26
A11: Months of actual data in current quarter | C11: 2 | D11: Q2FY27 = Jul-Sep 26. Two months of actuals as at the Aug-26 SIAM deck.
A12: Assumed avg MoM drift for un-reported months (base) | C12: 0 | D12: 0.0% = spot-flat carry. This is the single most important forecast lever.
A13: Bear case MoM drift (cost inflation) | C13: 0.02
A14: Bull case MoM drift (cost deflation) | C14: -0.02
A16: BLENDED COMPOSITE — SEGMENT WEIGHTS | D16: Share of industry raw-material spend, not units. Set to sum to 100%.
A17: PV (ICE) | C17: 0.38
A18: 2W (ICE) | C18: 0.2
A19: CV | C19: 0.2
A20: Tractor | C20: 0.07
A21: BEV - PV | C21: 0.07
A22: E-2W | C22: 0.08
A23: Total | C23: =SUM(C17:C22) -> 1 | D23: Must equal 100.0%
A25: MARGIN TRANSLATION
A26: Raw material basket as % of ASP | D26: BofA works with metals at 20-25% of ASP for 4W and 2W; these are total-RM baskets so sit at the upper end.
A27: PV (ICE) | C27: 0.22
A28: 2W (ICE) | C28: 0.23
A29: CV | C29: 0.25
A30: Tractor | C30: 0.22
A31: BEV - PV | C31: 0.3
A32: E-2W | C32: 0.32
A34: Inventory / contract lag — weight on current quarter | C34: 0.35 | D34: Steel and aluminium contracts reprice with a lag; most of a quarter's spot move lands next quarter.
A35: Inventory / contract lag — weight on prior quarter | C35: 0.65 | D35: Two lag weights should sum to 100%.
A36: Lag weights total | C36: =C34+C35 -> 1
A37: Assumed pass-through to customer (price hikes) | C37: 0.5 | D37: 0% = OEM eats the entire move. 100% = fully recovered in the same quarter.
A40: Sources: SIAM Commodity Price Monthly Monitor (August 2026). BOM weights, segment weights, RM/ASP ratios, lag and pass-through are analyst estimates.

Sheet Raw Data
A1: RAW DATABASE — SIAM MONTHLY COMMODITY PRICES
A2: As published by SIAM, in native units. This is the only sheet to type into when the next monthly deck arrives.
A5: Commodity | B5: Category | C5: Unit | D5: Ccy | E5: SIAM pg | F5: Jul-25 | G5: Aug-25 | H5: Sept-25 | I5: Oct-25 | J5: Nov-25 | K5: Dec-25 | L5: Jan-26 | M5: Feb-26 | N5: Mar-26 | O5: Apr-26 | P5: May-26 | Q5: June-26 | R5: July-26 | S5: Aug-26 | T5: MoM % | U5: YoY % | V5: Notes
A6: FERROUS - FLAT, LONG & SPECIAL STEEL
A7: HR Steel (HRC 1.8mm, IS2062) | B7: Ferrous - Flat, Long & Special Steel | C7: INR/Tonne | D7: INR | E7: 5 | F7: 50950 | G7: 51437.5 | H7: 50812.5 | I7: 49812.5 | J7: 48187.5 | K7: 49080 | L7: 53612.5 | M7: 55212.5 | N7: 57625 | O7: 60550 | P7: 59750 | Q7: 61375 | R7: 60890 | S7: 61544 | T7: =IFERROR(S7/R7-1,"") -> 0.01074068 | U7: =IFERROR(S7/F7-1,"") -> 0.20792934 | V7: Mid-point of SIAM published low-high band
A8: CR Steel (CRC 0.90mm, IS513 GrO) | B8: Ferrous - Flat, Long & Special Steel | C8: INR/Tonne | D8: INR | E8: 6 | F8: 56450 | G8: 57000 | H8: 56500 | I8: 55500 | J8: 54937.5 | K8: 54870 | L8: 57850 | M8: 59637.5 | N8: 62625 | O8: 66450 | P8: 65750 | Q8: 65750 | R8: 65150 | S8: 65625 | T8: =IFERROR(S8/R8-1,"") -> 0.0072908672 | U8: =IFERROR(S8/F8-1,"") -> 0.16253322 | V8: Mid-point of SIAM published low-high band
A9: Alloy Steel - Forging (20MnCr5) | B9: Ferrous - Flat, Long & Special Steel | C9: INR/Tonne | D9: INR | E9: 7 | F9: 62000 | G9: 62000 | H9: 61250 | I9: 61000 | J9: 60250 | K9: 60000 | L9: 60800 | M9: 62000 | N9: 62000 | O9: 67380 | P9: 67330 | Q9: 65630 | R9: 62330 | S9: 62130 | T9: =IFERROR(S9/R9-1,"") -> -0.0032087277 | U9: =IFERROR(S9/F9-1,"") -> 0.0020967742
A10: Alloy Steel - Forging (EN-8) | B10: Ferrous - Flat, Long & Special Steel | C10: INR/Tonne | D10: INR | E10: 8 | F10: 61000 | G10: 61000 | H10: 60250 | I10: 60000 | J10: 59250 | K10: 59000 | L10: 59800 | M10: 61000 | N10: 61000 | O10: 64250 | P10: 64200 | Q10: 62500 | R10: 59200 | S10: 59000 | T10: =IFERROR(S10/R10-1,"") -> -0.0033783784 | U10: =IFERROR(S10/F10-1,"") -> -0.032786885
A11: Pig Iron (Foundry Grade B) | B11: Ferrous - Flat, Long & Special Steel | C11: INR/Tonne | D11: INR | E11: 9 | F11: 37625 | G11: 37600 | H11: 39250 | I11: 39200 | J11: 39000 | K11: 38250 | L11: 41600 | M11: 42667 | N11: 43500 | O11: 45250 | P11: 45500 | Q11: 44250 | R11: 46300 | S11: 48750 | T11: =IFERROR(S11/R11-1,"") -> 0.052915767 | U11: =IFERROR(S11/F11-1,"") -> 0.29568106
A12: Stainless Steel (G304 CR Coil) | B12: Ferrous - Flat, Long & Special Steel | C12: INR/Tonne | D12: INR | E12: 10 | F12: 193800 | G12: 197500 | H12: 200500 | I12: 200000 | J12: 192500 | K12: 190000 | L12: 198750 | M12: 203500 | N12: 215000 | O12: 226000 | P12: 231375 | Q12: 224500 | R12: 221000 | S12: 225000 | T12: =IFERROR(S12/R12-1,"") -> 0.018099548 | U12: =IFERROR(S12/F12-1,"") -> 0.16099071 | V12: Mid-point of SIAM published low-high band
A13: Stainless Steel (G304 HR Coil) | B13: Ferrous - Flat, Long & Special Steel | C13: INR/Tonne | D13: INR | E13: 11 | F13: 184000 | G13: 187125 | H13: 190500 | I13: 190000 | J13: 182500 | K13: 181600 | L13: 190500 | M13: 194250 | N13: 208000 | O13: 216400 | P13: 224250 | Q13: 218250 | R13: 214000 | S13: 218750 | T13: =IFERROR(S13/R13-1,"") -> 0.022196262 | U13: =IFERROR(S13/F13-1,"") -> 0.1888587 | V13: Mid-point of SIAM published low-high band
A14: Steel Scrap (RM end scrap) | B14: Ferrous - Flat, Long & Special Steel | C14: INR/Tonne | D14: INR | E14: 12 | F14: 36325 | G14: 36520 | H14: 35425 | I14: 34720 | J14: 33550 | K14: 33575 | L14: 35300 | M14: 37167 | N14: 38900 | O14: 40950 | P14: 40060 | Q14: 38700 | R14: 36780 | S14: 37275 | T14: =IFERROR(S14/R14-1,"") -> 0.013458401 | U14: =IFERROR(S14/F14-1,"") -> 0.026152787
A15: UPSTREAM STEEL INPUTS
A16: Coking Coal (Premium HCC, Australia) | B16: Upstream Steel Inputs | C16: USD/Tonne | D16: USD | E16: 13 | F16: 193 | G16: 203 | H16: 203 | I16: 208 | J16: 214 | K16: 227 | L16: 248 | M16: 263 | N16: 249 | O16: 255 | P16: 264 | Q16: 266 | R16: 252 | S16: 253 | T16: =IFERROR(S16/R16-1,"") -> 0.003968254 | U16: =IFERROR(S16/F16-1,"") -> 0.31088083
A17: Iron Ore (Fe 62%, Australia) | B17: Upstream Steel Inputs | C17: USD/Tonne | D17: USD | E17: 14 | F17: 99 | G17: 102 | H17: 105 | I17: 106 | J17: 104 | K17: 107 | L17: 106 | M17: 99 | N17: 106 | O17: 107 | P17: 109 | Q17: 101 | R17: 98 | S17: 96 | T17: =IFERROR(S17/R17-1,"") -> -0.020408163 | U17: =IFERROR(S17/F17-1,"") -> -0.03030303
A18: NON-FERROUS METALS
A19: Virgin Aluminium | B19: Non-Ferrous Metals | C19: USD/Tonne | D19: USD | E19: 16 | F19: 2604.2 | G19: 2594 | H19: 2653.3 | I19: 2786.3 | J19: 2822.9 | K19: 2875.5 | L19: 3148.4 | M19: 3065.4 | N19: 3370.2 | O19: 3600.6 | P19: 3670.2 | Q19: 3458.6 | R19: 3156 | S19: 3252 | T19: =IFERROR(S19/R19-1,"") -> 0.030418251 | U19: =IFERROR(S19/F19-1,"") -> 0.24875202
A20: Copper | B20: Non-Ferrous Metals | C20: USD/Tonne | D20: USD | E20: 17 | F20: 9778.2 | G20: 9645.9 | H20: 9952.7 | I20: 10696 | J20: 10800.8 | K20: 11803.8 | L20: 13088.9 | M20: 12967.8 | N20: 12499 | O20: 12891.4 | P20: 13507.1 | Q20: 13574.3 | R20: 13525.2 | S20: 14353.4 | T20: =IFERROR(S20/R20-1,"") -> 0.061233845 | U20: =IFERROR(S20/F20-1,"") -> 0.46789798
A21: Lead | B21: Non-Ferrous Metals | C21: USD/Tonne | D21: USD | E21: 18 | F21: 1994.9 | G21: 1945.2 | H21: 1954.5 | I21: 1968.2 | J21: 2001.8 | K21: 1942.3 | L21: 1998.3 | M21: 1916.1 | N21: 1879.8 | O21: 1922.7 | P21: 1991 | Q21: 1951.3 | R21: 1844.1 | S21: 1855.1 | T21: =IFERROR(S21/R21-1,"") -> 0.0059649694 | U21: =IFERROR(S21/F21-1,"") -> -0.070078701
A22: Nickel | B22: Non-Ferrous Metals | C22: USD/Tonne | D22: USD | E22: 19 | F22: 15023.3 | G22: 14909 | H22: 15102 | I22: 15079.8 | J22: 14689.3 | K22: 14878.8 | L22: 17844 | M22: 17132.8 | N22: 17093.2 | O22: 18005.8 | P22: 18805 | Q22: 17663.9 | R22: 16657.4 | S22: 16765.8 | T22: =IFERROR(S22/R22-1,"") -> 0.0065076182 | U22: =IFERROR(S22/F22-1,"") -> 0.1159865
A23: Zinc | B23: Non-Ferrous Metals | C23: USD/Tonne | D23: USD | E23: 20 | F23: 2758.8 | G23: 2784.4 | H23: 2930 | I23: 3149.1 | J23: 3187.4 | K23: 3159.7 | L23: 3220.2 | M23: 3320.8 | N23: 3187.9 | O23: 3361.6 | P23: 3488.2 | Q23: 3540.5 | R23: 3596.1 | S23: 3875.1 | T23: =IFERROR(S23/R23-1,"") -> 0.077584049 | U23: =IFERROR(S23/F23-1,"") -> 0.40463245
A24: PRECIOUS / PGM
A25: Platinum | B25: Precious / Pgm | C25: INR/gm | D25: INR | E25: 21 | F25: 3884.42 | G25: 3785.29 | H25: 4099.4 | I25: 4629.46 | J25: 4526.03 | K25: 5419.39 | L25: 7140.6 | M25: 6300.94 | N25: 6196 | O25: 6149.69 | P25: 6188.93 | Q25: 5372.09 | R25: 5041.2 | S25: 5502.57 | T25: =IFERROR(S25/R25-1,"") -> 0.091519876 | U25: =IFERROR(S25/F25-1,"") -> 0.41657442
A26: Palladium | B26: Precious / Pgm | C26: INR/gm | D26: INR | E26: 22 | F26: 3351.79 | G26: 3234.55 | H26: 3383.84 | I26: 4056.91 | J26: 4088.69 | K26: 4613.22 | L26: 5439.55 | M26: 5114.88 | N26: 4712.15 | O26: 4632.31 | P26: 4479.22 | Q26: 3961.58 | R26: 3956.24 | S26: 4168.59 | T26: =IFERROR(S26/R26-1,"") -> 0.053674701 | U26: =IFERROR(S26/F26-1,"") -> 0.24369068
A27: Rhodium | B27: Precious / Pgm | C27: INR/gm | D27: INR | E27: 23 | F27: 16427.41 | G27: 20359.26 | H27: 20273.75 | I27: 21590.22 | J27: 22894.99 | K27: 23523.36 | L27: 29578.83 | M27: 31919.66 | N27: 33686.43 | O27: 30287.54 | P27: 29887.72 | Q27: 24583.84 | R27: 25151.09 | S27: 26661.83 | T27: =IFERROR(S27/R27-1,"") -> 0.060066582 | U27: =IFERROR(S27/F27-1,"") -> 0.62300874
A28: POLYMERS
A29: Polypropylene (PP) | B29: Polymers | C29: INR/kg | D29: INR | E29: 25 | F29: 100 | G29: 100.5 | H29: 99.3 | I29: 99.4 | J29: 95.2 | K29: 94.3 | L29: 96.5 | M29: 98.2 | N29: 136.2 | O29: 137.5 | P29: 129.9 | Q29: 133 | R29: 131.5 | S29: 134.4 | T29: =IFERROR(S29/R29-1,"") -> 0.022053232 | U29: =IFERROR(S29/F29-1,"") -> 0.344
A30: ABS | B30: Polymers | C30: INR/kg | D30: INR | E30: 26 | F30: 147.3 | G30: 146.8 | H30: 143.1 | I30: 137.6 | J30: 130.7 | K30: 124.1 | L30: 126.4 | M30: 130.6 | N30: 170.4 | O30: 197 | P30: 188.6 | Q30: 190.2 | R30: 185.8 | S30: 171.8 | T30: =IFERROR(S30/R30-1,"") -> -0.075349839 | U30: =IFERROR(S30/F30-1,"") -> 0.16632722
A31: Polycarbonate (PC) | B31: Polymers | C31: INR/kg | D31: INR | E31: 27 | F31: 214.6 | G31: 218.3 | H31: 222.7 | I31: 221.6 | J31: 221.5 | K31: 209.6 | L31: 208.9 | M31: 194.4 | N31: 227.5 | O31: 264 | P31: 265.2 | Q31: 261.9 | R31: 255.5 | S31: 253 | T31: =IFERROR(S31/R31-1,"") -> -0.0097847358 | U31: =IFERROR(S31/F31-1,"") -> 0.17893756
A32: CHEMICALS
A33: Urea (Prilled), CFR | B33: Chemicals | C33: USD/Ton | D33: USD | E33: 29 | F33: 475.4 | G33: 531 | H33: 463.5 | I33: 445.44 | J33: 403.42 | K33: 419 | L33: 423.53 | M33: 425.8 | N33: 510 | O33: 678.07 | P33: 947 | Q33: 677.82 | R33: 447.1 | S33: 419.55 | T33: =IFERROR(S33/R33-1,"") -> -0.061619325 | U33: =IFERROR(S33/F33-1,"") -> -0.11748002 | V33: Not in auto BOM baskets; tracked for agri / tractor demand read-across
A34: RUBBER & CARBON BLACK
A35: Natural Rubber (RSS 4) | B35: Rubber & Carbon Black | C35: INR/kg | D35: INR | E35: 31 | F35: 207.26 | G35: 196.34 | H35: 188.41 | I35: 187.33 | J35: 186.05 | K35: 183.74 | L35: 191.68 | M35: 212.48 | N35: 217.35 | O35: 234.54 | P35: 255.96 | Q35: 268.98 | R35: 276.14 | S35: 278.76 | T35: =IFERROR(S35/R35-1,"") -> 0.0094879409 | U35: =IFERROR(S35/F35-1,"") -> 0.34497732
A36: Synthetic Rubber - SBR 1502 | B36: Rubber & Carbon Black | C36: INR/kg | D36: INR | E36: 32 | F36: 184.18 | G36: 174.33 | H36: 177.57 | I36: 177.44 | J36: 176.52 | K36: 161.7 | L36: 155.59 | M36: 150.2 | N36: 164.88 | O36: 264.11 | P36: 281.34 | Q36: 235.88 | R36: 246.62 | S36: 251.5 | T36: =IFERROR(S36/R36-1,"") -> 0.019787527 | U36: =IFERROR(S36/F36-1,"") -> 0.365512
A37: EPDM | B37: Rubber & Carbon Black | C37: INR/kg | D37: INR | E37: 33 | F37: 220.45 | G37: 219.12 | H37: 216.76 | I37: 215.11 | J37: 212.16 | K37: 211.48 | L37: 207.7 | M37: 205.19 | N37: 248.35 | O37: 276.67 | P37: 299.11 | Q37: 299.55 | R37: 288.02 | S37: 292.85 | T37: =IFERROR(S37/R37-1,"") -> 0.016769669 | U37: =IFERROR(S37/F37-1,"") -> 0.32841914
A38: Carbon Black (N330) | B38: Rubber & Carbon Black | C38: INR/kg | D38: INR | E38: 34 | F38: 113.05 | G38: 105.68 | H38: 102.9 | I38: 99.55 | J38: 96.16 | K38: 96.3 | L38: 93.5 | M38: 92.64 | N38: 92.64 | O38: 124.92 | P38: 134.57 | Q38: 150.77 | R38: 156.79 | S38: 155.42 | T38: =IFERROR(S38/R38-1,"") -> -0.0087378022 | U38: =IFERROR(S38/F38-1,"") -> 0.37478992
A39: Polybutadiene Rubber (1220) | B39: Rubber & Carbon Black | C39: INR/kg | D39: INR | E39: 35 | F39: 172.29 | G39: 169.86 | H39: 175.69 | I39: 171.66 | J39: 169.56 | K39: 168.85 | L39: 153.55 | M39: 150.95 | N39: 163.92 | O39: 272.11 | P39: 304.5 | Q39: 282.07 | R39: 272.59 | S39: 270.61 | T39: =IFERROR(S39/R39-1,"") -> -0.007263656 | U39: =IFERROR(S39/F39-1,"") -> 0.57066574
A40: ADVANCED CHEMISTRIES (BATTERY)
A41: Lithium Carbonate (99.5% batt grade) | B41: Advanced Chemistries (Battery) | C41: USD/kg | D41: USD | E41: 37 | F41: 8.41 | G41: 9.38 | H41: 9.38 | I41: 9.45 | J41: 10.27 | K41: 11.51 | L41: 17.52 | M41: 18.41 | N41: 19.89 | O41: 20.21 | P41: 21.91 | Q41: 20.81 | R41: 19.54 | S41: 19.3 | T41: =IFERROR(S41/R41-1,"") -> -0.012282497 | U41: =IFERROR(S41/F41-1,"") -> 1.294887
A42: Lithium Hydroxide (56.5% batt grade) | B42: Advanced Chemistries (Battery) | C42: USD/kg | D42: USD | E42: 38 | F42: 8.11 | G42: 8.57 | H42: 9.3 | I42: 9.53 | J42: 10.22 | K42: 10.79 | L42: 16.74 | M42: 17.61 | N42: 18.37 | O42: 18.6 | P42: 20.41 | Q42: 19.26 | R42: 18 | S42: 17.88 | T42: =IFERROR(S42/R42-1,"") -> -0.0066666667 | U42: =IFERROR(S42/F42-1,"") -> 1.2046856
A43: Cobalt Oxide (Co>=72%) | B43: Advanced Chemistries (Battery) | C43: USD/Tonne | D43: USD | E43: 39 | F43: 23609.04 | G43: 24467.11 | H43: 25463.81 | I43: 34974.42 | J43: 37624.7 | K43: 40070.61 | L43: 43388.17 | M43: 44065.57 | N43: 44410.41 | O43: 43944.98 | P43: 43430.18 | Q43: 41663.81 | R43: 38724.83 | S43: 35856.45 | T43: =IFERROR(S43/R43-1,"") -> -0.074070822 | U43: =IFERROR(S43/F43-1,"") -> 0.51875934
A44: Cobalt Metal (Co>=99.8%) | B44: Advanced Chemistries (Battery) | C44: USD/Tonne | D44: USD | E44: 40 | F44: 30705.9 | G44: 32574.97 | H44: 34755.78 | I44: 47864.6 | J44: 48967.18 | K44: 52328.66 | L44: 57060.9 | M44: 54547.2 | N44: 55128.45 | O44: 53662.14 | P44: 55289.12 | Q44: 51882.66 | R44: 47933.77 | S44: 42150.34 | T44: =IFERROR(S44/R44-1,"") -> -0.1206546 | U44: =IFERROR(S44/F44-1,"") -> 0.37271143
A45: RARE EARTH / MAGNETS
A46: NdFeB Magnet (GD - scrap) | B46: Rare Earth / Magnets | C46: USD/kg | D46: USD | E46: 42 | F46: 12.25 | G46: 12.24 | H46: 12.33 | I46: 12.34 | J46: 12.36 | K46: 12.47 | L46: 11.4 | M46: 11.5 | N46: 11.52 | O46: 11.61 | P46: 11.69 | Q46: 11.72 | R46: 11.72 | S46: 11.79 | T46: =IFERROR(S46/R46-1,"") -> 0.0059726962 | U46: =IFERROR(S46/F46-1,"") -> -0.03755102 | V46: Scrap proxy; sintered NdFeB contract prices are not published by SIAM
A47: ENERGY & FUELS
A48: Brent Crude (Europe spot FOB) | B48: Energy & Fuels | C48: USD/bbl | D48: USD | E48: 44 | F48: 70.67 | G48: 67.87 | H48: 67.96 | I48: 64.47 | J48: 64.54 | K48: 62.54 | L48: 66.6 | M48: 70.89 | N48: 103.13 | O48: 117.29 | P48: 107.14 | Q48: 86.11 | R48: 83.76 | S48: 91.08 | T48: =IFERROR(S48/R48-1,"") -> 0.08739255 | U48: =IFERROR(S48/F48-1,"") -> 0.28880713
A49: CNG - Delhi (IGL) | B49: Energy & Fuels | C49: INR/kg | D49: INR | E49: 45 | F49: 77.1 | G49: 77.1 | H49: 77.1 | I49: 77.1 | J49: 77.1 | K49: 77.1 | L49: 77.1 | M49: 77.1 | N49: 77.1 | O49: 77.1 | P49: 79.3 | Q49: 83.1 | R49: 83.1 | S49: 83.5 | T49: =IFERROR(S49/R49-1,"") -> 0.0048134777 | U49: =IFERROR(S49/F49-1,"") -> 0.083009079
A50: CNG - Mumbai (MGL) | B50: Energy & Fuels | C50: INR/kg | D50: INR | E50: 45 | F50: 80 | G50: 80 | H50: 80.5 | I50: 80.5 | J50: 80.5 | K50: 80.5 | L50: 80.5 | M50: 81 | N50: 81 | O50: 81.6 | P50: 83.3 | Q50: 86 | R50: 86 | S50: 86 | T50: =IFERROR(S50/R50-1,"") -> 0 | U50: =IFERROR(S50/F50-1,"") -> 0.075
A51: Petrol - Delhi | B51: Energy & Fuels | C51: INR/litre | D51: INR | E51: 46 | F51: 94.81 | G51: 94.81 | H51: 94.81 | I51: 94.81 | J51: 94.81 | K51: 94.81 | L51: 94.81 | M51: 94.81 | N51: 94.81 | O51: 94.81 | P51: 97.22 | Q51: 102.12 | R51: 102.12 | S51: 102.12 | T51: =IFERROR(S51/R51-1,"") -> 0 | U51: =IFERROR(S51/F51-1,"") -> 0.077101572
A52: Diesel - Delhi | B52: Energy & Fuels | C52: INR/litre | D52: INR | E52: 46 | F52: 87.71 | G52: 87.71 | H52: 87.71 | I52: 87.71 | J52: 87.71 | K52: 87.71 | L52: 87.71 | M52: 87.71 | N52: 87.71 | O52: 87.71 | P52: 90.16 | Q52: 95.2 | R52: 95.2 | S52: 95.2 | T52: =IFERROR(S52/R52-1,"") -> 0 | U52: =IFERROR(S52/F52-1,"") -> 0.085395052
A53: Petrol - Mumbai | B53: Energy & Fuels | C53: INR/litre | D53: INR | E53: 46 | F53: 103.49 | G53: 103.49 | H53: 103.49 | I53: 103.49 | J53: 103.49 | K53: 103.49 | L53: 103.49 | M53: 103.49 | N53: 103.49 | O53: 103.49 | P53: 106.05 | Q53: 111.21 | R53: 111.21 | S53: 111.21 | T53: =IFERROR(S53/R53-1,"") -> 0 | U53: =IFERROR(S53/F53-1,"") -> 0.074596579
A54: Diesel - Mumbai | B54: Energy & Fuels | C54: INR/litre | D54: INR | E54: 46 | F54: 90.01 | G54: 90.01 | H54: 90.01 | I54: 90.01 | J54: 90.01 | K54: 90.01 | L54: 90.01 | M54: 90.01 | N54: 90.01 | O54: 90.01 | P54: 92.58 | Q54: 97.83 | R54: 97.83 | S54: 97.83 | T54: =IFERROR(S54/R54-1,"") -> 0 | U54: =IFERROR(S54/F54-1,"") -> 0.086879236
A55: Ethanol - Sugarcane Juice | B55: Energy & Fuels | C55: INR/litre | D55: INR | E55: 47 | F55: 58 | G55: 58 | H55: 58 | I55: 58 | J55: 58 | K55: 58 | L55: 58 | M55: 58 | N55: 58 | O55: 58 | P55: 58 | Q55: 58 | R55: 58 | S55: 58 | T55: =IFERROR(S55/R55-1,"") -> 0 | U55: =IFERROR(S55/F55-1,"") -> 0
A56: Ethanol - B-Heavy Molasses | B56: Energy & Fuels | C56: INR/litre | D56: INR | E56: 47 | F56: 65.6 | G56: 65.6 | H56: 65.6 | I56: 65.6 | J56: 65.6 | K56: 65.6 | L56: 65.6 | M56: 65.6 | N56: 65.6 | O56: 65.6 | P56: 65.6 | Q56: 65.6 | R56: 65.6 | S56: 65.6 | T56: =IFERROR(S56/R56-1,"") -> 0 | U56: =IFERROR(S56/F56-1,"") -> 0
A57: Ethanol - C-Heavy Molasses | B57: Energy & Fuels | C57: INR/litre | D57: INR | E57: 47 | F57: 60.7 | G57: 60.7 | H57: 60.7 | I57: 60.7 | J57: 60.7 | K57: 60.7 | L57: 60.7 | M57: 60.7 | N57: 60.7 | O57: 60.7 | P57: 60.7 | Q57: 60.7 | R57: 60.7 | S57: 60.7 | T57: =IFERROR(S57/R57-1,"") -> 0 | U57: =IFERROR(S57/F57-1,"") -> 0
A58: FREIGHT
A59: Baltic Dry Index (Dry Bulk) | B59: Freight | C59: Index pts | D59: IDX | E59: 56 | F59: 1819 | G59: 2000 | H59: 2124 | I59: 1997 | J59: 2184 | K59: 2339 | L59: 1777 | M59: 2041 | N59: 2047 | O59: 2443 | P59: 3049 | Q59: 2775 | R59: 2770 | S59: 2770 | T59: =IFERROR(S59/R59-1,"") -> 0 | U59: =IFERROR(S59/F59-1,"") -> 0.52281473 | V59: SIAM did not publish an Aug-26 print in this edition (marked '*', 'data not published by source'); carried flat from Jul-26 pending confirmation next month.
A60: FX (period-end selling rate)
A61: USD / INR (selling) | B61: Fx (Period-End Selling Rate) | C61: INR | D61: INR | E61: 49 | F61: 86.71 | G61: 88.14 | H61: 88.89 | I61: 88.99 | J61: 89.42 | K61: 90.62 | L61: 91.34 | M61: 91.32 | N61: 93.24 | O61: 94.12 | P61: 96.16 | Q61: 95.52 | R61: 96.36 | S61: 96.05 | T61: =IFERROR(S61/R61-1,"") -> -0.0032171025 | U61: =IFERROR(S61/F61-1,"") -> 0.10771537
A62: GBP / INR (selling) | B62: Fx (Period-End Selling Rate) | C62: INR | D62: INR | E62: 50 | F62: 117.97 | G62: 119.21 | H62: 120.76 | I62: 119.78 | J62: 118.36 | K62: 122.04 | L62: 124.29 | M62: 124.91 | N62: 125.4 | O62: 127.34 | P62: 130.48 | Q62: 128.3 | R62: 129.8 | S62: 130.83 | T62: =IFERROR(S62/R62-1,"") -> 0.0079352851 | U62: =IFERROR(S62/F62-1,"") -> 0.10901077
A63: EUR / INR (selling) | B63: Fx (Period-End Selling Rate) | C63: INR | D63: INR | E63: 51 | F63: 102.16 | G63: 103.37 | H63: 105.15 | I63: 104.48 | J63: 104.24 | K63: 106.89 | L63: 108.03 | M63: 108.84 | N63: 108.74 | O63: 110.86 | P63: 113.12 | Q63: 111 | R63: 110.96 | S63: 112.12 | T63: =IFERROR(S63/R63-1,"") -> 0.010454218 | U63: =IFERROR(S63/F63-1,"") -> 0.097494127
A64: JPY 100 / INR (selling) | B64: Fx (Period-End Selling Rate) | C64: INR | D64: INR | E64: 52 | F64: 59.47 | G64: 60.12 | H64: 60.47 | I64: 59.22 | J64: 58.02 | K64: 58.5 | L64: 58.64 | M64: 59.3 | N64: 59.11 | O64: 59.46 | P64: 61.14 | Q64: 59.85 | R64: 59.69 | S64: 60.88 | T64: =IFERROR(S64/R64-1,"") -> 0.019936338 | U64: =IFERROR(S64/F64-1,"") -> 0.023709433
A65: CNY / INR | B65: Fx (Period-End Selling Rate) | C65: INR | D65: INR | E65: 53 | F65: 12.02 | G65: 12.23 | H65: 12.41 | I65: 12.41 | J65: 12.75 | K65: 12.86 | L65: 13.24 | M65: 13.15 | N65: 13.5 | O65: 13.72 | P65: 14.09 | Q65: 14.04 | R65: 14.17 | S65: 14.17 | T65: =IFERROR(S65/R65-1,"") -> 0 | U65: =IFERROR(S65/F65-1,"") -> 0.17886855
A66: POLICY & LENDING RATES
A67: Cash Reserve Ratio (%) | B67: Policy & Lending Rates | C67: % | D67: RATE | E67: 55 | F67: 4 | G67: 4 | H67: 3.5 | I67: 3.25 | J67: 3 | K67: 3 | L67: 3 | M67: 3 | N67: 3 | O67: 3 | P67: 3 | Q67: 3 | R67: 3 | S67: 3 | T67: =IFERROR(S67/R67-1,"") -> 0 | U67: =IFERROR(S67/F67-1,"") -> -0.25
A68: Bank Rate (% p.a.) | B68: Policy & Lending Rates | C68: % | D68: RATE | E68: 55 | F68: 5.75 | G68: 5.75 | H68: 5.75 | I68: 5.75 | J68: 5.5 | K68: 5.5 | L68: 5.5 | M68: 5.5 | N68: 5.5 | O68: 5.5 | P68: 5.5 | Q68: 5.5 | R68: 5.5 | S68: 5.5 | T68: =IFERROR(S68/R68-1,"") -> 0 | U68: =IFERROR(S68/F68-1,"") -> -0.043478261
A69: Base Rate - low (% p.a.) | B69: Policy & Lending Rates | C69: % | D69: RATE | E69: 55 | F69: 8.5 | G69: 8.5 | H69: 8.5 | I69: 8.35 | J69: 8.35 | K69: 8.35 | L69: 8.35 | M69: 8.35 | N69: 8.35 | O69: 8.35 | P69: 8.35 | Q69: 8.35 | R69: 8.4 | S69: 8.4 | T69: =IFERROR(S69/R69-1,"") -> 0 | U69: =IFERROR(S69/F69-1,"") -> -0.011764706
A70: Base Rate - high (% p.a.) | B70: Policy & Lending Rates | C70: % | D70: RATE | E70: 55 | F70: 10.3 | G70: 10.3 | H70: 10.3 | I70: 10 | J70: 10 | K70: 10 | L70: 10 | M70: 10 | N70: 10 | O70: 9.9 | P70: 9.9 | Q70: 9.9 | R70: 10 | S70: 10 | T70: =IFERROR(S70/R70-1,"") -> 0 | U70: =IFERROR(S70/F70-1,"") -> -0.029126214
A72: Source: SIAM Commodity Price Monthly Monitor, August 2026 (page references in column E). Range-quoted commodities are stored as the mid-point of SIAM's published low-high band.
A73: April-June 2025 are not published as numbers in the SIAM tables (chart-only), so the database begins Jul-25. The red-flagged Aug-26 Baltic Dry Index cell is carried flat, not a genuine print — see its note.

Sheet INR Normalised
A1: INR-NORMALISED PRICES
A2: All material inputs restated in INR per kg at that month's USD-INR selling rate. Isolates the currency drag on dollar-priced commodities.
A5: Commodity | B5: Category | C5: Normalised unit | D5: Conversion | E5: SIAM pg | F5: Jul-25 | G5: Aug-25 | H5: Sept-25 | I5: Oct-25 | J5: Nov-25 | K5: Dec-25 | L5: Jan-26 | M5: Feb-26 | N5: Mar-26 | O5: Apr-26 | P5: May-26 | Q5: June-26 | R5: July-26 | S5: Aug-26 | T5: MoM % | U5: YoY % | V5: Notes
A6: FERROUS - FLAT, LONG & SPECIAL STEEL
A7: ='Raw Data'!A7 -> HR Steel (HRC 1.8mm, IS2062) | B7: Ferrous - Flat, Long & Special Steel | C7: INR/kg | D7: / 1,000 | E7: 5 | F7: ='Raw Data'!F7/1000 -> 50.95 | G7: ='Raw Data'!G7/1000 -> 51.4375 | H7: ='Raw Data'!H7/1000 -> 50.8125 | I7: ='Raw Data'!I7/1000 -> 49.8125 | J7: ='Raw Data'!J7/1000 -> 48.1875 | K7: ='Raw Data'!K7/1000 -> 49.08 | L7: ='Raw Data'!L7/1000 -> 53.6125 | M7: ='Raw Data'!M7/1000 -> 55.2125 | ... S7: ='Raw Data'!S7/1000 -> 61.544 | T7: =IFERROR(S7/R7-1,"") -> 0.01074068 | U7: =IFERROR(S7/F7-1,"") -> 0.20792934
A8: ='Raw Data'!A8 -> CR Steel (CRC 0.90mm, IS513 GrO) | B8: Ferrous - Flat, Long & Special Steel | C8: INR/kg | D8: / 1,000 | E8: 6 | F8: ='Raw Data'!F8/1000 -> 56.45 | G8: ='Raw Data'!G8/1000 -> 57 | H8: ='Raw Data'!H8/1000 -> 56.5 | I8: ='Raw Data'!I8/1000 -> 55.5 | J8: ='Raw Data'!J8/1000 -> 54.9375 | K8: ='Raw Data'!K8/1000 -> 54.87 | L8: ='Raw Data'!L8/1000 -> 57.85 | M8: ='Raw Data'!M8/1000 -> 59.6375 | ... S8: ='Raw Data'!S8/1000 -> 65.625 | T8: =IFERROR(S8/R8-1,"") -> 0.0072908672 | U8: =IFERROR(S8/F8-1,"") -> 0.16253322
A9: ='Raw Data'!A9 -> Alloy Steel - Forging (20MnCr5) | B9: Ferrous - Flat, Long & Special Steel | C9: INR/kg | D9: / 1,000 | E9: 7 | F9: ='Raw Data'!F9/1000 -> 62 | G9: ='Raw Data'!G9/1000 -> 62 | H9: ='Raw Data'!H9/1000 -> 61.25 | I9: ='Raw Data'!I9/1000 -> 61 | J9: ='Raw Data'!J9/1000 -> 60.25 | K9: ='Raw Data'!K9/1000 -> 60 | L9: ='Raw Data'!L9/1000 -> 60.8 | M9: ='Raw Data'!M9/1000 -> 62 | ... S9: ='Raw Data'!S9/1000 -> 62.13 | T9: =IFERROR(S9/R9-1,"") -> -0.0032087277 | U9: =IFERROR(S9/F9-1,"") -> 0.0020967742
A10: ='Raw Data'!A10 -> Alloy Steel - Forging (EN-8) | B10: Ferrous - Flat, Long & Special Steel | C10: INR/kg | D10: / 1,000 | E10: 8 | F10: ='Raw Data'!F10/1000 -> 61 | G10: ='Raw Data'!G10/1000 -> 61 | H10: ='Raw Data'!H10/1000 -> 60.25 | I10: ='Raw Data'!I10/1000 -> 60 | J10: ='Raw Data'!J10/1000 -> 59.25 | K10: ='Raw Data'!K10/1000 -> 59 | L10: ='Raw Data'!L10/1000 -> 59.8 | M10: ='Raw Data'!M10/1000 -> 61 | ... S10: ='Raw Data'!S10/1000 -> 59 | T10: =IFERROR(S10/R10-1,"") -> -0.0033783784 | U10: =IFERROR(S10/F10-1,"") -> -0.032786885
A11: ='Raw Data'!A11 -> Pig Iron (Foundry Grade B) | B11: Ferrous - Flat, Long & Special Steel | C11: INR/kg | D11: / 1,000 | E11: 9 | F11: ='Raw Data'!F11/1000 -> 37.625 | G11: ='Raw Data'!G11/1000 -> 37.6 | H11: ='Raw Data'!H11/1000 -> 39.25 | I11: ='Raw Data'!I11/1000 -> 39.2 | J11: ='Raw Data'!J11/1000 -> 39 | K11: ='Raw Data'!K11/1000 -> 38.25 | L11: ='Raw Data'!L11/1000 -> 41.6 | M11: ='Raw Data'!M11/1000 -> 42.667 | ... S11: ='Raw Data'!S11/1000 -> 48.75 | T11: =IFERROR(S11/R11-1,"") -> 0.052915767 | U11: =IFERROR(S11/F11-1,"") -> 0.29568106
A12: ='Raw Data'!A12 -> Stainless Steel (G304 CR Coil) | B12: Ferrous - Flat, Long & Special Steel | C12: INR/kg | D12: / 1,000 | E12: 10 | F12: ='Raw Data'!F12/1000 -> 193.8 | G12: ='Raw Data'!G12/1000 -> 197.5 | H12: ='Raw Data'!H12/1000 -> 200.5 | I12: ='Raw Data'!I12/1000 -> 200 | J12: ='Raw Data'!J12/1000 -> 192.5 | K12: ='Raw Data'!K12/1000 -> 190 | L12: ='Raw Data'!L12/1000 -> 198.75 | M12: ='Raw Data'!M12/1000 -> 203.5 | ... S12: ='Raw Data'!S12/1000 -> 225 | T12: =IFERROR(S12/R12-1,"") -> 0.018099548 | U12: =IFERROR(S12/F12-1,"") -> 0.16099071
A13: ='Raw Data'!A13 -> Stainless Steel (G304 HR Coil) | B13: Ferrous - Flat, Long & Special Steel | C13: INR/kg | D13: / 1,000 | E13: 11 | F13: ='Raw Data'!F13/1000 -> 184 | G13: ='Raw Data'!G13/1000 -> 187.125 | H13: ='Raw Data'!H13/1000 -> 190.5 | I13: ='Raw Data'!I13/1000 -> 190 | J13: ='Raw Data'!J13/1000 -> 182.5 | K13: ='Raw Data'!K13/1000 -> 181.6 | L13: ='Raw Data'!L13/1000 -> 190.5 | M13: ='Raw Data'!M13/1000 -> 194.25 | ... S13: ='Raw Data'!S13/1000 -> 218.75 | T13: =IFERROR(S13/R13-1,"") -> 0.022196262 | U13: =IFERROR(S13/F13-1,"") -> 0.1888587
A14: ='Raw Data'!A14 -> Steel Scrap (RM end scrap) | B14: Ferrous - Flat, Long & Special Steel | C14: INR/kg | D14: / 1,000 | E14: 12 | F14: ='Raw Data'!F14/1000 -> 36.325 | G14: ='Raw Data'!G14/1000 -> 36.52 | H14: ='Raw Data'!H14/1000 -> 35.425 | I14: ='Raw Data'!I14/1000 -> 34.72 | J14: ='Raw Data'!J14/1000 -> 33.55 | K14: ='Raw Data'!K14/1000 -> 33.575 | L14: ='Raw Data'!L14/1000 -> 35.3 | M14: ='Raw Data'!M14/1000 -> 37.167 | ... S14: ='Raw Data'!S14/1000 -> 37.275 | T14: =IFERROR(S14/R14-1,"") -> 0.013458401 | U14: =IFERROR(S14/F14-1,"") -> 0.026152787
A15: UPSTREAM STEEL INPUTS
A16: ='Raw Data'!A16 -> Coking Coal (Premium HCC, Australia) | B16: Upstream Steel Inputs | C16: INR/kg | D16: x USD-INR / 1,000 | E16: 13 | F16: ='Raw Data'!F16*'Raw Data'!F$61/1000 -> 16.73503 | G16: ='Raw Data'!G16*'Raw Data'!G$61/1000 -> 17.89242 | H16: ='Raw Data'!H16*'Raw Data'!H$61/1000 -> 18.04467 | I16: ='Raw Data'!I16*'Raw Data'!I$61/1000 -> 18.50992 | J16: ='Raw Data'!J16*'Raw Data'!J$61/1000 -> 19.13588 | K16: ='Raw Data'!K16*'Raw Data'!K$61/1000 -> 20.57074 | L16: ='Raw Data'!L16*'Raw Data'!L$61/1000 -> 22.65232 | M16: ='Raw Data'!M16*'Raw Data'!M$61/1000 -> 24.01716 | ... S16: ='Raw Data'!S16*'Raw Data'!S$61/1000 -> 24.30065 | T16: =IFERROR(S16/R16-1,"") -> 0.00073838516 | U16: =IFERROR(S16/F16-1,"") -> 0.45208285 | V16: Dollar-priced: INR move = commodity move + rupee move
A17: ='Raw Data'!A17 -> Iron Ore (Fe 62%, Australia) | B17: Upstream Steel Inputs | C17: INR/kg | D17: x USD-INR / 1,000 | E17: 14 | F17: ='Raw Data'!F17*'Raw Data'!F$61/1000 -> 8.58429 | G17: ='Raw Data'!G17*'Raw Data'!G$61/1000 -> 8.99028 | H17: ='Raw Data'!H17*'Raw Data'!H$61/1000 -> 9.33345 | I17: ='Raw Data'!I17*'Raw Data'!I$61/1000 -> 9.43294 | J17: ='Raw Data'!J17*'Raw Data'!J$61/1000 -> 9.29968 | K17: ='Raw Data'!K17*'Raw Data'!K$61/1000 -> 9.69634 | L17: ='Raw Data'!L17*'Raw Data'!L$61/1000 -> 9.68204 | M17: ='Raw Data'!M17*'Raw Data'!M$61/1000 -> 9.04068 | ... S17: ='Raw Data'!S17*'Raw Data'!S$61/1000 -> 9.2208 | T17: =IFERROR(S17/R17-1,"") -> -0.023559611 | U17: =IFERROR(S17/F17-1,"") -> 0.074148241 | V17: Dollar-priced: INR move = commodity move + rupee move
A18: NON-FERROUS METALS
A19: ='Raw Data'!A19 -> Virgin Aluminium | B19: Non-Ferrous Metals | C19: INR/kg | D19: x USD-INR / 1,000 | E19: 16 | F19: ='Raw Data'!F19*'Raw Data'!F$61/1000 -> 225.81018 | G19: ='Raw Data'!G19*'Raw Data'!G$61/1000 -> 228.63516 | H19: ='Raw Data'!H19*'Raw Data'!H$61/1000 -> 235.85184 | I19: ='Raw Data'!I19*'Raw Data'!I$61/1000 -> 247.95284 | J19: ='Raw Data'!J19*'Raw Data'!J$61/1000 -> 252.42372 | K19: ='Raw Data'!K19*'Raw Data'!K$61/1000 -> 260.57781 | L19: ='Raw Data'!L19*'Raw Data'!L$61/1000 -> 287.57486 | M19: ='Raw Data'!M19*'Raw Data'!M$61/1000 -> 279.93233 | ... S19: ='Raw Data'!S19*'Raw Data'!S$61/1000 -> 312.3546 | T19: =IFERROR(S19/R19-1,"") -> 0.02710329 | U19: =IFERROR(S19/F19-1,"") -> 0.38326181 | V19: Dollar-priced: INR move = commodity move + rupee move
A20: ='Raw Data'!A20 -> Copper | B20: Non-Ferrous Metals | C20: INR/kg | D20: x USD-INR / 1,000 | E20: 17 | F20: ='Raw Data'!F20*'Raw Data'!F$61/1000 -> 847.86772 | G20: ='Raw Data'!G20*'Raw Data'!G$61/1000 -> 850.18963 | H20: ='Raw Data'!H20*'Raw Data'!H$61/1000 -> 884.6955 | I20: ='Raw Data'!I20*'Raw Data'!I$61/1000 -> 951.83704 | J20: ='Raw Data'!J20*'Raw Data'!J$61/1000 -> 965.80754 | K20: ='Raw Data'!K20*'Raw Data'!K$61/1000 -> 1069.6604 | L20: ='Raw Data'!L20*'Raw Data'!L$61/1000 -> 1195.5401 | M20: ='Raw Data'!M20*'Raw Data'!M$61/1000 -> 1184.2195 | ... S20: ='Raw Data'!S20*'Raw Data'!S$61/1000 -> 1378.6441 | T20: =IFERROR(S20/R20-1,"") -> 0.057819747 | U20: =IFERROR(S20/F20-1,"") -> 0.62601316 | V20: Dollar-priced: INR move = commodity move + rupee move
A21: ='Raw Data'!A21 -> Lead | B21: Non-Ferrous Metals | C21: INR/kg | D21: x USD-INR / 1,000 | E21: 18 | F21: ='Raw Data'!F21*'Raw Data'!F$61/1000 -> 172.97778 | G21: ='Raw Data'!G21*'Raw Data'!G$61/1000 -> 171.44993 | H21: ='Raw Data'!H21*'Raw Data'!H$61/1000 -> 173.7355 | I21: ='Raw Data'!I21*'Raw Data'!I$61/1000 -> 175.15012 | J21: ='Raw Data'!J21*'Raw Data'!J$61/1000 -> 179.00096 | K21: ='Raw Data'!K21*'Raw Data'!K$61/1000 -> 176.01123 | L21: ='Raw Data'!L21*'Raw Data'!L$61/1000 -> 182.52472 | M21: ='Raw Data'!M21*'Raw Data'!M$61/1000 -> 174.97825 | ... S21: ='Raw Data'!S21*'Raw Data'!S$61/1000 -> 178.18236 | T21: =IFERROR(S21/R21-1,"") -> 0.0027286769 | U21: =IFERROR(S21/F21-1,"") -> 0.030088119 | V21: Dollar-priced: INR move = commodity move + rupee move
A22: ='Raw Data'!A22 -> Nickel | B22: Non-Ferrous Metals | C22: INR/kg | D22: x USD-INR / 1,000 | E22: 19 | F22: ='Raw Data'!F22*'Raw Data'!F$61/1000 -> 1302.6703 | G22: ='Raw Data'!G22*'Raw Data'!G$61/1000 -> 1314.0793 | H22: ='Raw Data'!H22*'Raw Data'!H$61/1000 -> 1342.4168 | I22: ='Raw Data'!I22*'Raw Data'!I$61/1000 -> 1341.9514 | J22: ='Raw Data'!J22*'Raw Data'!J$61/1000 -> 1313.5172 | K22: ='Raw Data'!K22*'Raw Data'!K$61/1000 -> 1348.3169 | L22: ='Raw Data'!L22*'Raw Data'!L$61/1000 -> 1629.871 | M22: ='Raw Data'!M22*'Raw Data'!M$61/1000 -> 1564.5673 | ... S22: ='Raw Data'!S22*'Raw Data'!S$61/1000 -> 1610.3551 | T22: =IFERROR(S22/R22-1,"") -> 0.00326958 | U22: =IFERROR(S22/F22-1,"") -> 0.2361954 | V22: Dollar-priced: INR move = commodity move + rupee move
A23: ='Raw Data'!A23 -> Zinc | B23: Non-Ferrous Metals | C23: INR/kg | D23: x USD-INR / 1,000 | E23: 20 | F23: ='Raw Data'!F23*'Raw Data'!F$61/1000 -> 239.21555 | G23: ='Raw Data'!G23*'Raw Data'!G$61/1000 -> 245.41702 | H23: ='Raw Data'!H23*'Raw Data'!H$61/1000 -> 260.4477 | I23: ='Raw Data'!I23*'Raw Data'!I$61/1000 -> 280.23841 | J23: ='Raw Data'!J23*'Raw Data'!J$61/1000 -> 285.01731 | K23: ='Raw Data'!K23*'Raw Data'!K$61/1000 -> 286.33201 | L23: ='Raw Data'!L23*'Raw Data'!L$61/1000 -> 294.13307 | M23: ='Raw Data'!M23*'Raw Data'!M$61/1000 -> 303.25546 | ... S23: ='Raw Data'!S23*'Raw Data'!S$61/1000 -> 372.20335 | T23: =IFERROR(S23/R23-1,"") -> 0.074117351 | U23: =IFERROR(S23/F23-1,"") -> 0.55593296 | V23: Dollar-priced: INR move = commodity move + rupee move
A24: PRECIOUS / PGM
A25: ='Raw Data'!A25 -> Platinum | B25: Precious / Pgm | C25: INR/kg | D25: x 1,000 | E25: 21 | F25: ='Raw Data'!F25*1000 -> 3884420 | G25: ='Raw Data'!G25*1000 -> 3785290 | H25: ='Raw Data'!H25*1000 -> 4099400 | I25: ='Raw Data'!I25*1000 -> 4629460 | J25: ='Raw Data'!J25*1000 -> 4526030 | K25: ='Raw Data'!K25*1000 -> 5419390 | L25: ='Raw Data'!L25*1000 -> 7140600 | M25: ='Raw Data'!M25*1000 -> 6300940 | ... S25: ='Raw Data'!S25*1000 -> 5502570 | T25: =IFERROR(S25/R25-1,"") -> 0.091519876 | U25: =IFERROR(S25/F25-1,"") -> 0.41657442
A26: ='Raw Data'!A26 -> Palladium | B26: Precious / Pgm | C26: INR/kg | D26: x 1,000 | E26: 22 | F26: ='Raw Data'!F26*1000 -> 3351790 | G26: ='Raw Data'!G26*1000 -> 3234550 | H26: ='Raw Data'!H26*1000 -> 3383840 | I26: ='Raw Data'!I26*1000 -> 4056910 | J26: ='Raw Data'!J26*1000 -> 4088690 | K26: ='Raw Data'!K26*1000 -> 4613220 | L26: ='Raw Data'!L26*1000 -> 5439550 | M26: ='Raw Data'!M26*1000 -> 5114880 | ... S26: ='Raw Data'!S26*1000 -> 4168590 | T26: =IFERROR(S26/R26-1,"") -> 0.053674701 | U26: =IFERROR(S26/F26-1,"") -> 0.24369068
A27: ='Raw Data'!A27 -> Rhodium | B27: Precious / Pgm | C27: INR/kg | D27: x 1,000 | E27: 23 | F27: ='Raw Data'!F27*1000 -> 16427410 | G27: ='Raw Data'!G27*1000 -> 20359260 | H27: ='Raw Data'!H27*1000 -> 20273750 | I27: ='Raw Data'!I27*1000 -> 21590220 | J27: ='Raw Data'!J27*1000 -> 22894990 | K27: ='Raw Data'!K27*1000 -> 23523360 | L27: ='Raw Data'!L27*1000 -> 29578830 | M27: ='Raw Data'!M27*1000 -> 31919660 | ... S27: ='Raw Data'!S27*1000 -> 26661830 | T27: =IFERROR(S27/R27-1,"") -> 0.060066582 | U27: =IFERROR(S27/F27-1,"") -> 0.62300874
A28: POLYMERS
A29: ='Raw Data'!A29 -> Polypropylene (PP) | B29: Polymers | C29: INR/kg | D29: as reported | E29: 25 | F29: ='Raw Data'!F29 -> 100 | G29: ='Raw Data'!G29 -> 100.5 | H29: ='Raw Data'!H29 -> 99.3 | I29: ='Raw Data'!I29 -> 99.4 | J29: ='Raw Data'!J29 -> 95.2 | K29: ='Raw Data'!K29 -> 94.3 | L29: ='Raw Data'!L29 -> 96.5 | M29: ='Raw Data'!M29 -> 98.2 | ... S29: ='Raw Data'!S29 -> 134.4 | T29: =IFERROR(S29/R29-1,"") -> 0.022053232 | U29: =IFERROR(S29/F29-1,"") -> 0.344
A30: ='Raw Data'!A30 -> ABS | B30: Polymers | C30: INR/kg | D30: as reported | E30: 26 | F30: ='Raw Data'!F30 -> 147.3 | G30: ='Raw Data'!G30 -> 146.8 | H30: ='Raw Data'!H30 -> 143.1 | I30: ='Raw Data'!I30 -> 137.6 | J30: ='Raw Data'!J30 -> 130.7 | K30: ='Raw Data'!K30 -> 124.1 | L30: ='Raw Data'!L30 -> 126.4 | M30: ='Raw Data'!M30 -> 130.6 | ... S30: ='Raw Data'!S30 -> 171.8 | T30: =IFERROR(S30/R30-1,"") -> -0.075349839 | U30: =IFERROR(S30/F30-1,"") -> 0.16632722
A31: ='Raw Data'!A31 -> Polycarbonate (PC) | B31: Polymers | C31: INR/kg | D31: as reported | E31: 27 | F31: ='Raw Data'!F31 -> 214.6 | G31: ='Raw Data'!G31 -> 218.3 | H31: ='Raw Data'!H31 -> 222.7 | I31: ='Raw Data'!I31 -> 221.6 | J31: ='Raw Data'!J31 -> 221.5 | K31: ='Raw Data'!K31 -> 209.6 | L31: ='Raw Data'!L31 -> 208.9 | M31: ='Raw Data'!M31 -> 194.4 | ... S31: ='Raw Data'!S31 -> 253 | T31: =IFERROR(S31/R31-1,"") -> -0.0097847358 | U31: =IFERROR(S31/F31-1,"") -> 0.17893756
A32: CHEMICALS
A33: ='Raw Data'!A33 -> Urea (Prilled), CFR | B33: Chemicals | C33: INR/kg | D33: x USD-INR / 1,000 | E33: 29 | F33: ='Raw Data'!F33*'Raw Data'!F$61/1000 -> 41.221934 | G33: ='Raw Data'!G33*'Raw Data'!G$61/1000 -> 46.80234 | H33: ='Raw Data'!H33*'Raw Data'!H$61/1000 -> 41.200515 | I33: ='Raw Data'!I33*'Raw Data'!I$61/1000 -> 39.639706 | J33: ='Raw Data'!J33*'Raw Data'!J$61/1000 -> 36.073816 | K33: ='Raw Data'!K33*'Raw Data'!K$61/1000 -> 37.96978 | L33: ='Raw Data'!L33*'Raw Data'!L$61/1000 -> 38.68523 | M33: ='Raw Data'!M33*'Raw Data'!M$61/1000 -> 38.884056 | ... S33: ='Raw Data'!S33*'Raw Data'!S$61/1000 -> 40.297778 | T33: =IFERROR(S33/R33-1,"") -> -0.064638191 | U33: =IFERROR(S33/F33-1,"") -> -0.022419048 | V33: Dollar-priced: INR move = commodity move + rupee move
A34: RUBBER & CARBON BLACK
A35: ='Raw Data'!A35 -> Natural Rubber (RSS 4) | B35: Rubber & Carbon Black | C35: INR/kg | D35: as reported | E35: 31 | F35: ='Raw Data'!F35 -> 207.26 | G35: ='Raw Data'!G35 -> 196.34 | H35: ='Raw Data'!H35 -> 188.41 | I35: ='Raw Data'!I35 -> 187.33 | J35: ='Raw Data'!J35 -> 186.05 | K35: ='Raw Data'!K35 -> 183.74 | L35: ='Raw Data'!L35 -> 191.68 | M35: ='Raw Data'!M35 -> 212.48 | ... S35: ='Raw Data'!S35 -> 278.76 | T35: =IFERROR(S35/R35-1,"") -> 0.0094879409 | U35: =IFERROR(S35/F35-1,"") -> 0.34497732
A36: ='Raw Data'!A36 -> Synthetic Rubber - SBR 1502 | B36: Rubber & Carbon Black | C36: INR/kg | D36: as reported | E36: 32 | F36: ='Raw Data'!F36 -> 184.18 | G36: ='Raw Data'!G36 -> 174.33 | H36: ='Raw Data'!H36 -> 177.57 | I36: ='Raw Data'!I36 -> 177.44 | J36: ='Raw Data'!J36 -> 176.52 | K36: ='Raw Data'!K36 -> 161.7 | L36: ='Raw Data'!L36 -> 155.59 | M36: ='Raw Data'!M36 -> 150.2 | ... S36: ='Raw Data'!S36 -> 251.5 | T36: =IFERROR(S36/R36-1,"") -> 0.019787527 | U36: =IFERROR(S36/F36-1,"") -> 0.365512
A37: ='Raw Data'!A37 -> EPDM | B37: Rubber & Carbon Black | C37: INR/kg | D37: as reported | E37: 33 | F37: ='Raw Data'!F37 -> 220.45 | G37: ='Raw Data'!G37 -> 219.12 | H37: ='Raw Data'!H37 -> 216.76 | I37: ='Raw Data'!I37 -> 215.11 | J37: ='Raw Data'!J37 -> 212.16 | K37: ='Raw Data'!K37 -> 211.48 | L37: ='Raw Data'!L37 -> 207.7 | M37: ='Raw Data'!M37 -> 205.19 | ... S37: ='Raw Data'!S37 -> 292.85 | T37: =IFERROR(S37/R37-1,"") -> 0.016769669 | U37: =IFERROR(S37/F37-1,"") -> 0.32841914
A38: ='Raw Data'!A38 -> Carbon Black (N330) | B38: Rubber & Carbon Black | C38: INR/kg | D38: as reported | E38: 34 | F38: ='Raw Data'!F38 -> 113.05 | G38: ='Raw Data'!G38 -> 105.68 | H38: ='Raw Data'!H38 -> 102.9 | I38: ='Raw Data'!I38 -> 99.55 | J38: ='Raw Data'!J38 -> 96.16 | K38: ='Raw Data'!K38 -> 96.3 | L38: ='Raw Data'!L38 -> 93.5 | M38: ='Raw Data'!M38 -> 92.64 | ... S38: ='Raw Data'!S38 -> 155.42 | T38: =IFERROR(S38/R38-1,"") -> -0.0087378022 | U38: =IFERROR(S38/F38-1,"") -> 0.37478992
A39: ='Raw Data'!A39 -> Polybutadiene Rubber (1220) | B39: Rubber & Carbon Black | C39: INR/kg | D39: as reported | E39: 35 | F39: ='Raw Data'!F39 -> 172.29 | G39: ='Raw Data'!G39 -> 169.86 | H39: ='Raw Data'!H39 -> 175.69 | I39: ='Raw Data'!I39 -> 171.66 | J39: ='Raw Data'!J39 -> 169.56 | K39: ='Raw Data'!K39 -> 168.85 | L39: ='Raw Data'!L39 -> 153.55 | M39: ='Raw Data'!M39 -> 150.95 | ... S39: ='Raw Data'!S39 -> 270.61 | T39: =IFERROR(S39/R39-1,"") -> -0.007263656 | U39: =IFERROR(S39/F39-1,"") -> 0.57066574
A40: ADVANCED CHEMISTRIES (BATTERY)
A41: ='Raw Data'!A41 -> Lithium Carbonate (99.5% batt grade) | B41: Advanced Chemistries (Battery) | C41: INR/kg | D41: x USD-INR | E41: 37 | F41: ='Raw Data'!F41*'Raw Data'!F$61 -> 729.2311 | G41: ='Raw Data'!G41*'Raw Data'!G$61 -> 826.7532 | H41: ='Raw Data'!H41*'Raw Data'!H$61 -> 833.7882 | I41: ='Raw Data'!I41*'Raw Data'!I$61 -> 840.9555 | J41: ='Raw Data'!J41*'Raw Data'!J$61 -> 918.3434 | K41: ='Raw Data'!K41*'Raw Data'!K$61 -> 1043.0362 | L41: ='Raw Data'!L41*'Raw Data'!L$61 -> 1600.2768 | M41: ='Raw Data'!M41*'Raw Data'!M$61 -> 1681.2012 | ... S41: ='Raw Data'!S41*'Raw Data'!S$61 -> 1853.765 | T41: =IFERROR(S41/R41-1,"") -> -0.015460086 | U41: =IFERROR(S41/F41-1,"") -> 1.5420817 | V41: Dollar-priced: INR move = commodity move + rupee move
A42: ='Raw Data'!A42 -> Lithium Hydroxide (56.5% batt grade) | B42: Advanced Chemistries (Battery) | C42: INR/kg | D42: x USD-INR | E42: 38 | F42: ='Raw Data'!F42*'Raw Data'!F$61 -> 703.2181 | G42: ='Raw Data'!G42*'Raw Data'!G$61 -> 755.3598 | H42: ='Raw Data'!H42*'Raw Data'!H$61 -> 826.677 | I42: ='Raw Data'!I42*'Raw Data'!I$61 -> 848.0747 | J42: ='Raw Data'!J42*'Raw Data'!J$61 -> 913.8724 | K42: ='Raw Data'!K42*'Raw Data'!K$61 -> 977.7898 | L42: ='Raw Data'!L42*'Raw Data'!L$61 -> 1529.0316 | M42: ='Raw Data'!M42*'Raw Data'!M$61 -> 1608.1452 | ... S42: ='Raw Data'!S42*'Raw Data'!S$61 -> 1717.374 | T42: =IFERROR(S42/R42-1,"") -> -0.0098623218 | U42: =IFERROR(S42/F42-1,"") -> 1.4421641 | V42: Dollar-priced: INR move = commodity move + rupee move
A43: ='Raw Data'!A43 -> Cobalt Oxide (Co>=72%) | B43: Advanced Chemistries (Battery) | C43: INR/kg | D43: x USD-INR / 1,000 | E43: 39 | F43: ='Raw Data'!F43*'Raw Data'!F$61/1000 -> 2047.1399 | G43: ='Raw Data'!G43*'Raw Data'!G$61/1000 -> 2156.5311 | H43: ='Raw Data'!H43*'Raw Data'!H$61/1000 -> 2263.4781 | I43: ='Raw Data'!I43*'Raw Data'!I$61/1000 -> 3112.3736 | J43: ='Raw Data'!J43*'Raw Data'!J$61/1000 -> 3364.4007 | K43: ='Raw Data'!K43*'Raw Data'!K$61/1000 -> 3631.1987 | L43: ='Raw Data'!L43*'Raw Data'!L$61/1000 -> 3963.0754 | M43: ='Raw Data'!M43*'Raw Data'!M$61/1000 -> 4024.0679 | ... S43: ='Raw Data'!S43*'Raw Data'!S$61/1000 -> 3444.012 | T43: =IFERROR(S43/R43-1,"") -> -0.077049631 | U43: =IFERROR(S43/F43-1,"") -> 0.68235307 | V43: Dollar-priced: INR move = commodity move + rupee move
A44: ='Raw Data'!A44 -> Cobalt Metal (Co>=99.8%) | B44: Advanced Chemistries (Battery) | C44: INR/kg | D44: x USD-INR / 1,000 | E44: 40 | F44: ='Raw Data'!F44*'Raw Data'!F$61/1000 -> 2662.5086 | G44: ='Raw Data'!G44*'Raw Data'!G$61/1000 -> 2871.1579 | H44: ='Raw Data'!H44*'Raw Data'!H$61/1000 -> 3089.4413 | I44: ='Raw Data'!I44*'Raw Data'!I$61/1000 -> 4259.4708 | J44: ='Raw Data'!J44*'Raw Data'!J$61/1000 -> 4378.6452 | K44: ='Raw Data'!K44*'Raw Data'!K$61/1000 -> 4742.0232 | L44: ='Raw Data'!L44*'Raw Data'!L$61/1000 -> 5211.9426 | M44: ='Raw Data'!M44*'Raw Data'!M$61/1000 -> 4981.2503 | ... S44: ='Raw Data'!S44*'Raw Data'!S$61/1000 -> 4048.5402 | T44: =IFERROR(S44/R44-1,"") -> -0.12348355 | U44: =IFERROR(S44/F44-1,"") -> 0.52057356 | V44: Dollar-priced: INR move = commodity move + rupee move
A45: RARE EARTH / MAGNETS
A46: ='Raw Data'!A46 -> NdFeB Magnet (GD - scrap) | B46: Rare Earth / Magnets | C46: INR/kg | D46: x USD-INR | E46: 42 | F46: ='Raw Data'!F46*'Raw Data'!F$61 -> 1062.1975 | G46: ='Raw Data'!G46*'Raw Data'!G$61 -> 1078.8336 | H46: ='Raw Data'!H46*'Raw Data'!H$61 -> 1096.0137 | I46: ='Raw Data'!I46*'Raw Data'!I$61 -> 1098.1366 | J46: ='Raw Data'!J46*'Raw Data'!J$61 -> 1105.2312 | K46: ='Raw Data'!K46*'Raw Data'!K$61 -> 1130.0314 | L46: ='Raw Data'!L46*'Raw Data'!L$61 -> 1041.276 | M46: ='Raw Data'!M46*'Raw Data'!M$61 -> 1050.18 | ... S46: ='Raw Data'!S46*'Raw Data'!S$61 -> 1132.4295 | T46: =IFERROR(S46/R46-1,"") -> 0.0027363789 | U46: =IFERROR(S46/F46-1,"") -> 0.066119531 | V46: Dollar-priced: INR move = commodity move + rupee move
A47: ENERGY & FUELS
A48: ='Raw Data'!A48 -> Brent Crude (Europe spot FOB) | B48: Energy & Fuels | C48: INR/bbl | D48: x USD-INR | E48: 44 | F48: ='Raw Data'!F48*'Raw Data'!F$61 -> 6127.7957 | G48: ='Raw Data'!G48*'Raw Data'!G$61 -> 5982.0618 | H48: ='Raw Data'!H48*'Raw Data'!H$61 -> 6040.9644 | I48: ='Raw Data'!I48*'Raw Data'!I$61 -> 5737.1853 | J48: ='Raw Data'!J48*'Raw Data'!J$61 -> 5771.1668 | K48: ='Raw Data'!K48*'Raw Data'!K$61 -> 5667.3748 | L48: ='Raw Data'!L48*'Raw Data'!L$61 -> 6083.244 | M48: ='Raw Data'!M48*'Raw Data'!M$61 -> 6473.6748 | ... S48: ='Raw Data'!S48*'Raw Data'!S$61 -> 8748.234 | T48: =IFERROR(S48/R48-1,"") -> 0.083894297 | U48: =IFERROR(S48/F48-1,"") -> 0.42763147 | V48: Dollar-priced: INR move = commodity move + rupee move
A49: ='Raw Data'!A49 -> CNG - Delhi (IGL) | B49: Energy & Fuels | C49: INR/kg | D49: as reported | E49: 45 | F49: ='Raw Data'!F49 -> 77.1 | G49: ='Raw Data'!G49 -> 77.1 | H49: ='Raw Data'!H49 -> 77.1 | I49: ='Raw Data'!I49 -> 77.1 | J49: ='Raw Data'!J49 -> 77.1 | K49: ='Raw Data'!K49 -> 77.1 | L49: ='Raw Data'!L49 -> 77.1 | M49: ='Raw Data'!M49 -> 77.1 | ... S49: ='Raw Data'!S49 -> 83.5 | T49: =IFERROR(S49/R49-1,"") -> 0.0048134777 | U49: =IFERROR(S49/F49-1,"") -> 0.083009079
A50: ='Raw Data'!A50 -> CNG - Mumbai (MGL) | B50: Energy & Fuels | C50: INR/kg | D50: as reported | E50: 45 | F50: ='Raw Data'!F50 -> 80 | G50: ='Raw Data'!G50 -> 80 | H50: ='Raw Data'!H50 -> 80.5 | I50: ='Raw Data'!I50 -> 80.5 | J50: ='Raw Data'!J50 -> 80.5 | K50: ='Raw Data'!K50 -> 80.5 | L50: ='Raw Data'!L50 -> 80.5 | M50: ='Raw Data'!M50 -> 81 | ... S50: ='Raw Data'!S50 -> 86 | T50: =IFERROR(S50/R50-1,"") -> 0 | U50: =IFERROR(S50/F50-1,"") -> 0.075
A51: ='Raw Data'!A51 -> Petrol - Delhi | B51: Energy & Fuels | C51: INR/litre | D51: as reported | E51: 46 | F51: ='Raw Data'!F51 -> 94.81 | G51: ='Raw Data'!G51 -> 94.81 | H51: ='Raw Data'!H51 -> 94.81 | I51: ='Raw Data'!I51 -> 94.81 | J51: ='Raw Data'!J51 -> 94.81 | K51: ='Raw Data'!K51 -> 94.81 | L51: ='Raw Data'!L51 -> 94.81 | M51: ='Raw Data'!M51 -> 94.81 | ... S51: ='Raw Data'!S51 -> 102.12 | T51: =IFERROR(S51/R51-1,"") -> 0 | U51: =IFERROR(S51/F51-1,"") -> 0.077101572
A52: ='Raw Data'!A52 -> Diesel - Delhi | B52: Energy & Fuels | C52: INR/litre | D52: as reported | E52: 46 | F52: ='Raw Data'!F52 -> 87.71 | G52: ='Raw Data'!G52 -> 87.71 | H52: ='Raw Data'!H52 -> 87.71 | I52: ='Raw Data'!I52 -> 87.71 | J52: ='Raw Data'!J52 -> 87.71 | K52: ='Raw Data'!K52 -> 87.71 | L52: ='Raw Data'!L52 -> 87.71 | M52: ='Raw Data'!M52 -> 87.71 | ... S52: ='Raw Data'!S52 -> 95.2 | T52: =IFERROR(S52/R52-1,"") -> 0 | U52: =IFERROR(S52/F52-1,"") -> 0.085395052
A53: ='Raw Data'!A53 -> Petrol - Mumbai | B53: Energy & Fuels | C53: INR/litre | D53: as reported | E53: 46 | F53: ='Raw Data'!F53 -> 103.49 | G53: ='Raw Data'!G53 -> 103.49 | H53: ='Raw Data'!H53 -> 103.49 | I53: ='Raw Data'!I53 -> 103.49 | J53: ='Raw Data'!J53 -> 103.49 | K53: ='Raw Data'!K53 -> 103.49 | L53: ='Raw Data'!L53 -> 103.49 | M53: ='Raw Data'!M53 -> 103.49 | ... S53: ='Raw Data'!S53 -> 111.21 | T53: =IFERROR(S53/R53-1,"") -> 0 | U53: =IFERROR(S53/F53-1,"") -> 0.074596579
A54: ='Raw Data'!A54 -> Diesel - Mumbai | B54: Energy & Fuels | C54: INR/litre | D54: as reported | E54: 46 | F54: ='Raw Data'!F54 -> 90.01 | G54: ='Raw Data'!G54 -> 90.01 | H54: ='Raw Data'!H54 -> 90.01 | I54: ='Raw Data'!I54 -> 90.01 | J54: ='Raw Data'!J54 -> 90.01 | K54: ='Raw Data'!K54 -> 90.01 | L54: ='Raw Data'!L54 -> 90.01 | M54: ='Raw Data'!M54 -> 90.01 | ... S54: ='Raw Data'!S54 -> 97.83 | T54: =IFERROR(S54/R54-1,"") -> 0 | U54: =IFERROR(S54/F54-1,"") -> 0.086879236
A55: ='Raw Data'!A55 -> Ethanol - Sugarcane Juice | B55: Energy & Fuels | C55: INR/litre | D55: as reported | E55: 47 | F55: ='Raw Data'!F55 -> 58 | G55: ='Raw Data'!G55 -> 58 | H55: ='Raw Data'!H55 -> 58 | I55: ='Raw Data'!I55 -> 58 | J55: ='Raw Data'!J55 -> 58 | K55: ='Raw Data'!K55 -> 58 | L55: ='Raw Data'!L55 -> 58 | M55: ='Raw Data'!M55 -> 58 | ... S55: ='Raw Data'!S55 -> 58 | T55: =IFERROR(S55/R55-1,"") -> 0 | U55: =IFERROR(S55/F55-1,"") -> 0
A56: ='Raw Data'!A56 -> Ethanol - B-Heavy Molasses | B56: Energy & Fuels | C56: INR/litre | D56: as reported | E56: 47 | F56: ='Raw Data'!F56 -> 65.6 | G56: ='Raw Data'!G56 -> 65.6 | H56: ='Raw Data'!H56 -> 65.6 | I56: ='Raw Data'!I56 -> 65.6 | J56: ='Raw Data'!J56 -> 65.6 | K56: ='Raw Data'!K56 -> 65.6 | L56: ='Raw Data'!L56 -> 65.6 | M56: ='Raw Data'!M56 -> 65.6 | ... S56: ='Raw Data'!S56 -> 65.6 | T56: =IFERROR(S56/R56-1,"") -> 0 | U56: =IFERROR(S56/F56-1,"") -> 0
A57: ='Raw Data'!A57 -> Ethanol - C-Heavy Molasses | B57: Energy & Fuels | C57: INR/litre | D57: as reported | E57: 47 | F57: ='Raw Data'!F57 -> 60.7 | G57: ='Raw Data'!G57 -> 60.7 | H57: ='Raw Data'!H57 -> 60.7 | I57: ='Raw Data'!I57 -> 60.7 | J57: ='Raw Data'!J57 -> 60.7 | K57: ='Raw Data'!K57 -> 60.7 | L57: ='Raw Data'!L57 -> 60.7 | M57: ='Raw Data'!M57 -> 60.7 | ... S57: ='Raw Data'!S57 -> 60.7 | T57: =IFERROR(S57/R57-1,"") -> 0 | U57: =IFERROR(S57/F57-1,"") -> 0
A58: FREIGHT
A59: ='Raw Data'!A59 -> Baltic Dry Index (Dry Bulk) | B59: Freight | C59: Index pts | D59: as reported | E59: 56 | F59: ='Raw Data'!F59 -> 1819 | G59: ='Raw Data'!G59 -> 2000 | H59: ='Raw Data'!H59 -> 2124 | I59: ='Raw Data'!I59 -> 1997 | J59: ='Raw Data'!J59 -> 2184 | K59: ='Raw Data'!K59 -> 2339 | L59: ='Raw Data'!L59 -> 1777 | M59: ='Raw Data'!M59 -> 2041 | ... S59: ='Raw Data'!S59 -> 2770 | T59: =IFERROR(S59/R59-1,"") -> 0 | U59: =IFERROR(S59/F59-1,"") -> 0.52281473
A60: FX (period-end selling rate)
A61: ='Raw Data'!A61 -> USD / INR (selling) | B61: Fx (Period-End Selling Rate) | C61: INR | D61: as reported | E61: 49 | F61: ='Raw Data'!F61 -> 86.71 | G61: ='Raw Data'!G61 -> 88.14 | H61: ='Raw Data'!H61 -> 88.89 | I61: ='Raw Data'!I61 -> 88.99 | J61: ='Raw Data'!J61 -> 89.42 | K61: ='Raw Data'!K61 -> 90.62 | L61: ='Raw Data'!L61 -> 91.34 | M61: ='Raw Data'!M61 -> 91.32 | ... S61: ='Raw Data'!S61 -> 96.05 | T61: =IFERROR(S61/R61-1,"") -> -0.0032171025 | U61: =IFERROR(S61/F61-1,"") -> 0.10771537
A62: ='Raw Data'!A62 -> GBP / INR (selling) | B62: Fx (Period-End Selling Rate) | C62: INR | D62: as reported | E62: 50 | F62: ='Raw Data'!F62 -> 117.97 | G62: ='Raw Data'!G62 -> 119.21 | H62: ='Raw Data'!H62 -> 120.76 | I62: ='Raw Data'!I62 -> 119.78 | J62: ='Raw Data'!J62 -> 118.36 | K62: ='Raw Data'!K62 -> 122.04 | L62: ='Raw Data'!L62 -> 124.29 | M62: ='Raw Data'!M62 -> 124.91 | ... S62: ='Raw Data'!S62 -> 130.83 | T62: =IFERROR(S62/R62-1,"") -> 0.0079352851 | U62: =IFERROR(S62/F62-1,"") -> 0.10901077
A63: ='Raw Data'!A63 -> EUR / INR (selling) | B63: Fx (Period-End Selling Rate) | C63: INR | D63: as reported | E63: 51 | F63: ='Raw Data'!F63 -> 102.16 | G63: ='Raw Data'!G63 -> 103.37 | H63: ='Raw Data'!H63 -> 105.15 | I63: ='Raw Data'!I63 -> 104.48 | J63: ='Raw Data'!J63 -> 104.24 | K63: ='Raw Data'!K63 -> 106.89 | L63: ='Raw Data'!L63 -> 108.03 | M63: ='Raw Data'!M63 -> 108.84 | ... S63: ='Raw Data'!S63 -> 112.12 | T63: =IFERROR(S63/R63-1,"") -> 0.010454218 | U63: =IFERROR(S63/F63-1,"") -> 0.097494127
A64: ='Raw Data'!A64 -> JPY 100 / INR (selling) | B64: Fx (Period-End Selling Rate) | C64: INR | D64: as reported | E64: 52 | F64: ='Raw Data'!F64 -> 59.47 | G64: ='Raw Data'!G64 -> 60.12 | H64: ='Raw Data'!H64 -> 60.47 | I64: ='Raw Data'!I64 -> 59.22 | J64: ='Raw Data'!J64 -> 58.02 | K64: ='Raw Data'!K64 -> 58.5 | L64: ='Raw Data'!L64 -> 58.64 | M64: ='Raw Data'!M64 -> 59.3 | ... S64: ='Raw Data'!S64 -> 60.88 | T64: =IFERROR(S64/R64-1,"") -> 0.019936338 | U64: =IFERROR(S64/F64-1,"") -> 0.023709433
A65: ='Raw Data'!A65 -> CNY / INR | B65: Fx (Period-End Selling Rate) | C65: INR | D65: as reported | E65: 53 | F65: ='Raw Data'!F65 -> 12.02 | G65: ='Raw Data'!G65 -> 12.23 | H65: ='Raw Data'!H65 -> 12.41 | I65: ='Raw Data'!I65 -> 12.41 | J65: ='Raw Data'!J65 -> 12.75 | K65: ='Raw Data'!K65 -> 12.86 | L65: ='Raw Data'!L65 -> 13.24 | M65: ='Raw Data'!M65 -> 13.15 | ... S65: ='Raw Data'!S65 -> 14.17 | T65: =IFERROR(S65/R65-1,"") -> 0 | U65: =IFERROR(S65/F65-1,"") -> 0.17886855
A66: POLICY & LENDING RATES
A67: ='Raw Data'!A67 -> Cash Reserve Ratio (%) | B67: Policy & Lending Rates | C67: % | D67: n.a. | E67: 55 | F67: ='Raw Data'!F67 -> 4 | G67: ='Raw Data'!G67 -> 4 | H67: ='Raw Data'!H67 -> 3.5 | I67: ='Raw Data'!I67 -> 3.25 | J67: ='Raw Data'!J67 -> 3 | K67: ='Raw Data'!K67 -> 3 | L67: ='Raw Data'!L67 -> 3 | M67: ='Raw Data'!M67 -> 3 | ... S67: ='Raw Data'!S67 -> 3 | T67: =IFERROR(S67/R67-1,"") -> 0 | U67: =IFERROR(S67/F67-1,"") -> -0.25
A68: ='Raw Data'!A68 -> Bank Rate (% p.a.) | B68: Policy & Lending Rates | C68: % | D68: n.a. | E68: 55 | F68: ='Raw Data'!F68 -> 5.75 | G68: ='Raw Data'!G68 -> 5.75 | H68: ='Raw Data'!H68 -> 5.75 | I68: ='Raw Data'!I68 -> 5.75 | J68: ='Raw Data'!J68 -> 5.5 | K68: ='Raw Data'!K68 -> 5.5 | L68: ='Raw Data'!L68 -> 5.5 | M68: ='Raw Data'!M68 -> 5.5 | ... S68: ='Raw Data'!S68 -> 5.5 | T68: =IFERROR(S68/R68-1,"") -> 0 | U68: =IFERROR(S68/F68-1,"") -> -0.043478261
A69: ='Raw Data'!A69 -> Base Rate - low (% p.a.) | B69: Policy & Lending Rates | C69: % | D69: n.a. | E69: 55 | F69: ='Raw Data'!F69 -> 8.5 | G69: ='Raw Data'!G69 -> 8.5 | H69: ='Raw Data'!H69 -> 8.5 | I69: ='Raw Data'!I69 -> 8.35 | J69: ='Raw Data'!J69 -> 8.35 | K69: ='Raw Data'!K69 -> 8.35 | L69: ='Raw Data'!L69 -> 8.35 | M69: ='Raw Data'!M69 -> 8.35 | ... S69: ='Raw Data'!S69 -> 8.4 | T69: =IFERROR(S69/R69-1,"") -> 0 | U69: =IFERROR(S69/F69-1,"") -> -0.011764706
A70: ='Raw Data'!A70 -> Base Rate - high (% p.a.) | B70: Policy & Lending Rates | C70: % | D70: n.a. | E70: 55 | F70: ='Raw Data'!F70 -> 10.3 | G70: ='Raw Data'!G70 -> 10.3 | H70: ='Raw Data'!H70 -> 10.3 | I70: ='Raw Data'!I70 -> 10 | J70: ='Raw Data'!J70 -> 10 | K70: ='Raw Data'!K70 -> 10 | L70: ='Raw Data'!L70 -> 10 | M70: ='Raw Data'!M70 -> 10 | ... S70: ='Raw Data'!S70 -> 10 | T70: =IFERROR(S70/R70-1,"") -> 0 | U70: =IFERROR(S70/F70-1,"") -> -0.029126214
A72: Conversion uses the SIAM-published USD/INR selling rate for the same month (Raw Data row 61). Policy rates are shown unconverted.

Sheet Commodity Indices
A1: COMMODITY PRICE INDICES (BASE = 100)
A2: Each series rebased to the base month set on Assumptions, on the chosen currency basis. These feed every basket.
A5: Commodity | B5: Category | C5: Basis | D5: Base month | E5: Base = 100 | F5: Jul-25 | G5: Aug-25 | H5: Sept-25 | I5: Oct-25 | J5: Nov-25 | K5: Dec-25 | L5: Jan-26 | M5: Feb-26 | N5: Mar-26 | O5: Apr-26 | P5: May-26 | Q5: June-26 | R5: July-26 | S5: Aug-26 | T5: MoM % | U5: YoY % | V5: Notes
A6: FERROUS - FLAT, LONG & SPECIAL STEEL
A7: ='Raw Data'!A7 -> HR Steel (HRC 1.8mm, IS2062) | B7: Ferrous - Flat, Long & Special Steel | C7: =Assumptions!$C$5 -> INR | D7: =Assumptions!$C$6 -> Jul-25 | E7: 100 | F7: =IF(Assumptions!$C$5="INR",'INR Normalised'!F7,'Raw Data'!F7)/IF(Assumptions!$C$5="INR",INDEX('INR Normalised'!$F7:$S7,Assumptions!$C$7),INDEX('Raw Data'!$F7:$S7,Assumptions!$C$7))*100 -> 100 | G7: =IF(Assumptions!$C$5="INR",'INR Normalised'!G7,'Raw Data'!G7)/IF(Assumptions!$C$5="INR",INDEX('INR Normalised'!$F7:$S7,Assumptions!$C$7),INDEX('Raw Data'!$F7:$S7,Assumptions!$C$7))*100 -> 100.95682 | H7: =IF(Assumptions!$C$5="INR",'INR Normalised'!H7,'Raw Data'!H7)/IF(Assumptions!$C$5="INR",INDEX('INR Normalised'!$F7:$S7,Assumptions!$C$7),INDEX('Raw Data'!$F7:$S7,Assumptions!$C$7))*100 -> 99.730128 | I7: =IF(Assumptions!$C$5="INR",'INR Normalised'!I7,'Raw Data'!I7)/IF(Assumptions!$C$5="INR",INDEX('INR Normalised'!$F7:$S7,Assumptions!$C$7),INDEX('Raw Data'!$F7:$S7,Assumptions!$C$7))*100 -> 97.767419 | J7: =IF(Assumptions!$C$5="INR",'INR Normalised'!J7,'Raw Data'!J7)/IF(Assumptions!$C$5="INR",INDEX('INR Normalised'!$F7:$S7,Assumptions!$C$7),INDEX('Raw Data'!$F7:$S7,Assumptions!$C$7))*100 -> 94.578018 | K7: =IF(Assumptions!$C$5="INR",'INR Normalised'!K7,'Raw Data'!K7)/IF(Assumptions!$C$5="INR",INDEX('INR Normalised'!$F7:$S7,Assumptions!$C$7),INDEX('Raw Data'!$F7:$S7,Assumptions!$C$7))*100 -> 96.329735 | L7: =IF(Assumptions!$C$5="INR",'INR Normalised'!L7,'Raw Data'!L7)/IF(Assumptions!$C$5="INR",INDEX('INR Normalised'!$F7:$S7,Assumptions!$C$7),INDEX('Raw Data'!$F7:$S7,Assumptions!$C$7))*100 -> 105.22571 | M7: =IF(Assumptions!$C$5="INR",'INR Normalised'!M7,'Raw Data'!M7)/IF(Assumptions!$C$5="INR",INDEX('INR Normalised'!$F7:$S7,Assumptions!$C$7),INDEX('Raw Data'!$F7:$S7,Assumptions!$C$7))*100 -> 108.36605 | ... S7: =IF(Assumptions!$C$5="INR",'INR Normalised'!S7,'Raw Data'!S7)/IF(Assumptions!$C$5="INR",INDEX('INR Normalised'!$F7:$S7,Assumptions!$C$7),INDEX('Raw Data'!$F7:$S7,Assumptions!$C$7))*100 -> 120.79293 | T7: =IFERROR(S7/R7-1,"") -> 0.01074068 | U7: =IFERROR(S7/F7-1,"") -> 0.20792934
A8: ='Raw Data'!A8 -> CR Steel (CRC 0.90mm, IS513 GrO) | B8: Ferrous - Flat, Long & Special Steel | C8: =Assumptions!$C$5 -> INR | D8: =Assumptions!$C$6 -> Jul-25 | E8: 100 | F8: =IF(Assumptions!$C$5="INR",'INR Normalised'!F8,'Raw Data'!F8)/IF(Assumptions!$C$5="INR",INDEX('INR Normalised'!$F8:$S8,Assumptions!$C$7),INDEX('Raw Data'!$F8:$S8,Assumptions!$C$7))*100 -> 100 | G8: =IF(Assumptions!$C$5="INR",'INR Normalised'!G8,'Raw Data'!G8)/IF(Assumptions!$C$5="INR",INDEX('INR Normalised'!$F8:$S8,Assumptions!$C$7),INDEX('Raw Data'!$F8:$S8,Assumptions!$C$7))*100 -> 100.97431 | H8: =IF(Assumptions!$C$5="INR",'INR Normalised'!H8,'Raw Data'!H8)/IF(Assumptions!$C$5="INR",INDEX('INR Normalised'!$F8:$S8,Assumptions!$C$7),INDEX('Raw Data'!$F8:$S8,Assumptions!$C$7))*100 -> 100.08857 | I8: =IF(Assumptions!$C$5="INR",'INR Normalised'!I8,'Raw Data'!I8)/IF(Assumptions!$C$5="INR",INDEX('INR Normalised'!$F8:$S8,Assumptions!$C$7),INDEX('Raw Data'!$F8:$S8,Assumptions!$C$7))*100 -> 98.317095 | J8: =IF(Assumptions!$C$5="INR",'INR Normalised'!J8,'Raw Data'!J8)/IF(Assumptions!$C$5="INR",INDEX('INR Normalised'!$F8:$S8,Assumptions!$C$7),INDEX('Raw Data'!$F8:$S8,Assumptions!$C$7))*100 -> 97.320638 | K8: =IF(Assumptions!$C$5="INR",'INR Normalised'!K8,'Raw Data'!K8)/IF(Assumptions!$C$5="INR",INDEX('INR Normalised'!$F8:$S8,Assumptions!$C$7),INDEX('Raw Data'!$F8:$S8,Assumptions!$C$7))*100 -> 97.201063 | L8: =IF(Assumptions!$C$5="INR",'INR Normalised'!L8,'Raw Data'!L8)/IF(Assumptions!$C$5="INR",INDEX('INR Normalised'!$F8:$S8,Assumptions!$C$7),INDEX('Raw Data'!$F8:$S8,Assumptions!$C$7))*100 -> 102.48007 | M8: =IF(Assumptions!$C$5="INR",'INR Normalised'!M8,'Raw Data'!M8)/IF(Assumptions!$C$5="INR",INDEX('INR Normalised'!$F8:$S8,Assumptions!$C$7),INDEX('Raw Data'!$F8:$S8,Assumptions!$C$7))*100 -> 105.64659 | ... S8: =IF(Assumptions!$C$5="INR",'INR Normalised'!S8,'Raw Data'!S8)/IF(Assumptions!$C$5="INR",INDEX('INR Normalised'!$F8:$S8,Assumptions!$C$7),INDEX('Raw Data'!$F8:$S8,Assumptions!$C$7))*100 -> 116.25332 | T8: =IFERROR(S8/R8-1,"") -> 0.0072908672 | U8: =IFERROR(S8/F8-1,"") -> 0.16253322
A9: ='Raw Data'!A9 -> Alloy Steel - Forging (20MnCr5) | B9: Ferrous - Flat, Long & Special Steel | C9: =Assumptions!$C$5 -> INR | D9: =Assumptions!$C$6 -> Jul-25 | E9: 100 | F9: =IF(Assumptions!$C$5="INR",'INR Normalised'!F9,'Raw Data'!F9)/IF(Assumptions!$C$5="INR",INDEX('INR Normalised'!$F9:$S9,Assumptions!$C$7),INDEX('Raw Data'!$F9:$S9,Assumptions!$C$7))*100 -> 100 | G9: =IF(Assumptions!$C$5="INR",'INR Normalised'!G9,'Raw Data'!G9)/IF(Assumptions!$C$5="INR",INDEX('INR Normalised'!$F9:$S9,Assumptions!$C$7),INDEX('Raw Data'!$F9:$S9,Assumptions!$C$7))*100 -> 100 | H9: =IF(Assumptions!$C$5="INR",'INR Normalised'!H9,'Raw Data'!H9)/IF(Assumptions!$C$5="INR",INDEX('INR Normalised'!$F9:$S9,Assumptions!$C$7),INDEX('Raw Data'!$F9:$S9,Assumptions!$C$7))*100 -> 98.790323 | I9: =IF(Assumptions!$C$5="INR",'INR Normalised'!I9,'Raw Data'!I9)/IF(Assumptions!$C$5="INR",INDEX('INR Normalised'!$F9:$S9,Assumptions!$C$7),INDEX('Raw Data'!$F9:$S9,Assumptions!$C$7))*100 -> 98.387097 | J9: =IF(Assumptions!$C$5="INR",'INR Normalised'!J9,'Raw Data'!J9)/IF(Assumptions!$C$5="INR",INDEX('INR Normalised'!$F9:$S9,Assumptions!$C$7),INDEX('Raw Data'!$F9:$S9,Assumptions!$C$7))*100 -> 97.177419 | K9: =IF(Assumptions!$C$5="INR",'INR Normalised'!K9,'Raw Data'!K9)/IF(Assumptions!$C$5="INR",INDEX('INR Normalised'!$F9:$S9,Assumptions!$C$7),INDEX('Raw Data'!$F9:$S9,Assumptions!$C$7))*100 -> 96.774194 | L9: =IF(Assumptions!$C$5="INR",'INR Normalised'!L9,'Raw Data'!L9)/IF(Assumptions!$C$5="INR",INDEX('INR Normalised'!$F9:$S9,Assumptions!$C$7),INDEX('Raw Data'!$F9:$S9,Assumptions!$C$7))*100 -> 98.064516 | M9: =IF(Assumptions!$C$5="INR",'INR Normalised'!M9,'Raw Data'!M9)/IF(Assumptions!$C$5="INR",INDEX('INR Normalised'!$F9:$S9,Assumptions!$C$7),INDEX('Raw Data'!$F9:$S9,Assumptions!$C$7))*100 -> 100 | ... S9: =IF(Assumptions!$C$5="INR",'INR Normalised'!S9,'Raw Data'!S9)/IF(Assumptions!$C$5="INR",INDEX('INR Normalised'!$F9:$S9,Assumptions!$C$7),INDEX('Raw Data'!$F9:$S9,Assumptions!$C$7))*100 -> 100.20968 | T9: =IFERROR(S9/R9-1,"") -> -0.0032087277 | U9: =IFERROR(S9/F9-1,"") -> 0.0020967742
A10: ='Raw Data'!A10 -> Alloy Steel - Forging (EN-8) | B10: Ferrous - Flat, Long & Special Steel | C10: =Assumptions!$C$5 -> INR | D10: =Assumptions!$C$6 -> Jul-25 | E10: 100 | F10: =IF(Assumptions!$C$5="INR",'INR Normalised'!F10,'Raw Data'!F10)/IF(Assumptions!$C$5="INR",INDEX('INR Normalised'!$F10:$S10,Assumptions!$C$7),INDEX('Raw Data'!$F10:$S10,Assumptions!$C$7))*100 -> 100 | G10: =IF(Assumptions!$C$5="INR",'INR Normalised'!G10,'Raw Data'!G10)/IF(Assumptions!$C$5="INR",INDEX('INR Normalised'!$F10:$S10,Assumptions!$C$7),INDEX('Raw Data'!$F10:$S10,Assumptions!$C$7))*100 -> 100 | H10: =IF(Assumptions!$C$5="INR",'INR Normalised'!H10,'Raw Data'!H10)/IF(Assumptions!$C$5="INR",INDEX('INR Normalised'!$F10:$S10,Assumptions!$C$7),INDEX('Raw Data'!$F10:$S10,Assumptions!$C$7))*100 -> 98.770492 | I10: =IF(Assumptions!$C$5="INR",'INR Normalised'!I10,'Raw Data'!I10)/IF(Assumptions!$C$5="INR",INDEX('INR Normalised'!$F10:$S10,Assumptions!$C$7),INDEX('Raw Data'!$F10:$S10,Assumptions!$C$7))*100 -> 98.360656 | J10: =IF(Assumptions!$C$5="INR",'INR Normalised'!J10,'Raw Data'!J10)/IF(Assumptions!$C$5="INR",INDEX('INR Normalised'!$F10:$S10,Assumptions!$C$7),INDEX('Raw Data'!$F10:$S10,Assumptions!$C$7))*100 -> 97.131148 | K10: =IF(Assumptions!$C$5="INR",'INR Normalised'!K10,'Raw Data'!K10)/IF(Assumptions!$C$5="INR",INDEX('INR Normalised'!$F10:$S10,Assumptions!$C$7),INDEX('Raw Data'!$F10:$S10,Assumptions!$C$7))*100 -> 96.721311 | L10: =IF(Assumptions!$C$5="INR",'INR Normalised'!L10,'Raw Data'!L10)/IF(Assumptions!$C$5="INR",INDEX('INR Normalised'!$F10:$S10,Assumptions!$C$7),INDEX('Raw Data'!$F10:$S10,Assumptions!$C$7))*100 -> 98.032787 | M10: =IF(Assumptions!$C$5="INR",'INR Normalised'!M10,'Raw Data'!M10)/IF(Assumptions!$C$5="INR",INDEX('INR Normalised'!$F10:$S10,Assumptions!$C$7),INDEX('Raw Data'!$F10:$S10,Assumptions!$C$7))*100 -> 100 | ... S10: =IF(Assumptions!$C$5="INR",'INR Normalised'!S10,'Raw Data'!S10)/IF(Assumptions!$C$5="INR",INDEX('INR Normalised'!$F10:$S10,Assumptions!$C$7),INDEX('Raw Data'!$F10:$S10,Assumptions!$C$7))*100 -> 96.721311 | T10: =IFERROR(S10/R10-1,"") -> -0.0033783784 | U10: =IFERROR(S10/F10-1,"") -> -0.032786885
A11: ='Raw Data'!A11 -> Pig Iron (Foundry Grade B) | B11: Ferrous - Flat, Long & Special Steel | C11: =Assumptions!$C$5 -> INR | D11: =Assumptions!$C$6 -> Jul-25 | E11: 100 | F11: =IF(Assumptions!$C$5="INR",'INR Normalised'!F11,'Raw Data'!F11)/IF(Assumptions!$C$5="INR",INDEX('INR Normalised'!$F11:$S11,Assumptions!$C$7),INDEX('Raw Data'!$F11:$S11,Assumptions!$C$7))*100 -> 100 | G11: =IF(Assumptions!$C$5="INR",'INR Normalised'!G11,'Raw Data'!G11)/IF(Assumptions!$C$5="INR",INDEX('INR Normalised'!$F11:$S11,Assumptions!$C$7),INDEX('Raw Data'!$F11:$S11,Assumptions!$C$7))*100 -> 99.933555 | H11: =IF(Assumptions!$C$5="INR",'INR Normalised'!H11,'Raw Data'!H11)/IF(Assumptions!$C$5="INR",INDEX('INR Normalised'!$F11:$S11,Assumptions!$C$7),INDEX('Raw Data'!$F11:$S11,Assumptions!$C$7))*100 -> 104.31894 | I11: =IF(Assumptions!$C$5="INR",'INR Normalised'!I11,'Raw Data'!I11)/IF(Assumptions!$C$5="INR",INDEX('INR Normalised'!$F11:$S11,Assumptions!$C$7),INDEX('Raw Data'!$F11:$S11,Assumptions!$C$7))*100 -> 104.18605 | J11: =IF(Assumptions!$C$5="INR",'INR Normalised'!J11,'Raw Data'!J11)/IF(Assumptions!$C$5="INR",INDEX('INR Normalised'!$F11:$S11,Assumptions!$C$7),INDEX('Raw Data'!$F11:$S11,Assumptions!$C$7))*100 -> 103.65449 | K11: =IF(Assumptions!$C$5="INR",'INR Normalised'!K11,'Raw Data'!K11)/IF(Assumptions!$C$5="INR",INDEX('INR Normalised'!$F11:$S11,Assumptions!$C$7),INDEX('Raw Data'!$F11:$S11,Assumptions!$C$7))*100 -> 101.66113 | L11: =IF(Assumptions!$C$5="INR",'INR Normalised'!L11,'Raw Data'!L11)/IF(Assumptions!$C$5="INR",INDEX('INR Normalised'!$F11:$S11,Assumptions!$C$7),INDEX('Raw Data'!$F11:$S11,Assumptions!$C$7))*100 -> 110.56478 | M11: =IF(Assumptions!$C$5="INR",'INR Normalised'!M11,'Raw Data'!M11)/IF(Assumptions!$C$5="INR",INDEX('INR Normalised'!$F11:$S11,Assumptions!$C$7),INDEX('Raw Data'!$F11:$S11,Assumptions!$C$7))*100 -> 113.40066 | ... S11: =IF(Assumptions!$C$5="INR",'INR Normalised'!S11,'Raw Data'!S11)/IF(Assumptions!$C$5="INR",INDEX('INR Normalised'!$F11:$S11,Assumptions!$C$7),INDEX('Raw Data'!$F11:$S11,Assumptions!$C$7))*100 -> 129.56811 | T11: =IFERROR(S11/R11-1,"") -> 0.052915767 | U11: =IFERROR(S11/F11-1,"") -> 0.29568106
A12: ='Raw Data'!A12 -> Stainless Steel (G304 CR Coil) | B12: Ferrous - Flat, Long & Special Steel | C12: =Assumptions!$C$5 -> INR | D12: =Assumptions!$C$6 -> Jul-25 | E12: 100 | F12: =IF(Assumptions!$C$5="INR",'INR Normalised'!F12,'Raw Data'!F12)/IF(Assumptions!$C$5="INR",INDEX('INR Normalised'!$F12:$S12,Assumptions!$C$7),INDEX('Raw Data'!$F12:$S12,Assumptions!$C$7))*100 -> 100 | G12: =IF(Assumptions!$C$5="INR",'INR Normalised'!G12,'Raw Data'!G12)/IF(Assumptions!$C$5="INR",INDEX('INR Normalised'!$F12:$S12,Assumptions!$C$7),INDEX('Raw Data'!$F12:$S12,Assumptions!$C$7))*100 -> 101.90918 | H12: =IF(Assumptions!$C$5="INR",'INR Normalised'!H12,'Raw Data'!H12)/IF(Assumptions!$C$5="INR",INDEX('INR Normalised'!$F12:$S12,Assumptions!$C$7),INDEX('Raw Data'!$F12:$S12,Assumptions!$C$7))*100 -> 103.45717 | I12: =IF(Assumptions!$C$5="INR",'INR Normalised'!I12,'Raw Data'!I12)/IF(Assumptions!$C$5="INR",INDEX('INR Normalised'!$F12:$S12,Assumptions!$C$7),INDEX('Raw Data'!$F12:$S12,Assumptions!$C$7))*100 -> 103.19917 | J12: =IF(Assumptions!$C$5="INR",'INR Normalised'!J12,'Raw Data'!J12)/IF(Assumptions!$C$5="INR",INDEX('INR Normalised'!$F12:$S12,Assumptions!$C$7),INDEX('Raw Data'!$F12:$S12,Assumptions!$C$7))*100 -> 99.329205 | K12: =IF(Assumptions!$C$5="INR",'INR Normalised'!K12,'Raw Data'!K12)/IF(Assumptions!$C$5="INR",INDEX('INR Normalised'!$F12:$S12,Assumptions!$C$7),INDEX('Raw Data'!$F12:$S12,Assumptions!$C$7))*100 -> 98.039216 | L12: =IF(Assumptions!$C$5="INR",'INR Normalised'!L12,'Raw Data'!L12)/IF(Assumptions!$C$5="INR",INDEX('INR Normalised'!$F12:$S12,Assumptions!$C$7),INDEX('Raw Data'!$F12:$S12,Assumptions!$C$7))*100 -> 102.55418 | M12: =IF(Assumptions!$C$5="INR",'INR Normalised'!M12,'Raw Data'!M12)/IF(Assumptions!$C$5="INR",INDEX('INR Normalised'!$F12:$S12,Assumptions!$C$7),INDEX('Raw Data'!$F12:$S12,Assumptions!$C$7))*100 -> 105.00516 | ... S12: =IF(Assumptions!$C$5="INR",'INR Normalised'!S12,'Raw Data'!S12)/IF(Assumptions!$C$5="INR",INDEX('INR Normalised'!$F12:$S12,Assumptions!$C$7),INDEX('Raw Data'!$F12:$S12,Assumptions!$C$7))*100 -> 116.09907 | T12: =IFERROR(S12/R12-1,"") -> 0.018099548 | U12: =IFERROR(S12/F12-1,"") -> 0.16099071
A13: ='Raw Data'!A13 -> Stainless Steel (G304 HR Coil) | B13: Ferrous - Flat, Long & Special Steel | C13: =Assumptions!$C$5 -> INR | D13: =Assumptions!$C$6 -> Jul-25 | E13: 100 | F13: =IF(Assumptions!$C$5="INR",'INR Normalised'!F13,'Raw Data'!F13)/IF(Assumptions!$C$5="INR",INDEX('INR Normalised'!$F13:$S13,Assumptions!$C$7),INDEX('Raw Data'!$F13:$S13,Assumptions!$C$7))*100 -> 100 | G13: =IF(Assumptions!$C$5="INR",'INR Normalised'!G13,'Raw Data'!G13)/IF(Assumptions!$C$5="INR",INDEX('INR Normalised'!$F13:$S13,Assumptions!$C$7),INDEX('Raw Data'!$F13:$S13,Assumptions!$C$7))*100 -> 101.69837 | H13: =IF(Assumptions!$C$5="INR",'INR Normalised'!H13,'Raw Data'!H13)/IF(Assumptions!$C$5="INR",INDEX('INR Normalised'!$F13:$S13,Assumptions!$C$7),INDEX('Raw Data'!$F13:$S13,Assumptions!$C$7))*100 -> 103.53261 | I13: =IF(Assumptions!$C$5="INR",'INR Normalised'!I13,'Raw Data'!I13)/IF(Assumptions!$C$5="INR",INDEX('INR Normalised'!$F13:$S13,Assumptions!$C$7),INDEX('Raw Data'!$F13:$S13,Assumptions!$C$7))*100 -> 103.26087 | J13: =IF(Assumptions!$C$5="INR",'INR Normalised'!J13,'Raw Data'!J13)/IF(Assumptions!$C$5="INR",INDEX('INR Normalised'!$F13:$S13,Assumptions!$C$7),INDEX('Raw Data'!$F13:$S13,Assumptions!$C$7))*100 -> 99.184783 | K13: =IF(Assumptions!$C$5="INR",'INR Normalised'!K13,'Raw Data'!K13)/IF(Assumptions!$C$5="INR",INDEX('INR Normalised'!$F13:$S13,Assumptions!$C$7),INDEX('Raw Data'!$F13:$S13,Assumptions!$C$7))*100 -> 98.695652 | L13: =IF(Assumptions!$C$5="INR",'INR Normalised'!L13,'Raw Data'!L13)/IF(Assumptions!$C$5="INR",INDEX('INR Normalised'!$F13:$S13,Assumptions!$C$7),INDEX('Raw Data'!$F13:$S13,Assumptions!$C$7))*100 -> 103.53261 | M13: =IF(Assumptions!$C$5="INR",'INR Normalised'!M13,'Raw Data'!M13)/IF(Assumptions!$C$5="INR",INDEX('INR Normalised'!$F13:$S13,Assumptions!$C$7),INDEX('Raw Data'!$F13:$S13,Assumptions!$C$7))*100 -> 105.57065 | ... S13: =IF(Assumptions!$C$5="INR",'INR Normalised'!S13,'Raw Data'!S13)/IF(Assumptions!$C$5="INR",INDEX('INR Normalised'!$F13:$S13,Assumptions!$C$7),INDEX('Raw Data'!$F13:$S13,Assumptions!$C$7))*100 -> 118.88587 | T13: =IFERROR(S13/R13-1,"") -> 0.022196262 | U13: =IFERROR(S13/F13-1,"") -> 0.1888587
A14: ='Raw Data'!A14 -> Steel Scrap (RM end scrap) | B14: Ferrous - Flat, Long & Special Steel | C14: =Assumptions!$C$5 -> INR | D14: =Assumptions!$C$6 -> Jul-25 | E14: 100 | F14: =IF(Assumptions!$C$5="INR",'INR Normalised'!F14,'Raw Data'!F14)/IF(Assumptions!$C$5="INR",INDEX('INR Normalised'!$F14:$S14,Assumptions!$C$7),INDEX('Raw Data'!$F14:$S14,Assumptions!$C$7))*100 -> 100 | G14: =IF(Assumptions!$C$5="INR",'INR Normalised'!G14,'Raw Data'!G14)/IF(Assumptions!$C$5="INR",INDEX('INR Normalised'!$F14:$S14,Assumptions!$C$7),INDEX('Raw Data'!$F14:$S14,Assumptions!$C$7))*100 -> 100.53682 | H14: =IF(Assumptions!$C$5="INR",'INR Normalised'!H14,'Raw Data'!H14)/IF(Assumptions!$C$5="INR",INDEX('INR Normalised'!$F14:$S14,Assumptions!$C$7),INDEX('Raw Data'!$F14:$S14,Assumptions!$C$7))*100 -> 97.522368 | I14: =IF(Assumptions!$C$5="INR",'INR Normalised'!I14,'Raw Data'!I14)/IF(Assumptions!$C$5="INR",INDEX('INR Normalised'!$F14:$S14,Assumptions!$C$7),INDEX('Raw Data'!$F14:$S14,Assumptions!$C$7))*100 -> 95.581555 | J14: =IF(Assumptions!$C$5="INR",'INR Normalised'!J14,'Raw Data'!J14)/IF(Assumptions!$C$5="INR",INDEX('INR Normalised'!$F14:$S14,Assumptions!$C$7),INDEX('Raw Data'!$F14:$S14,Assumptions!$C$7))*100 -> 92.360633 | K14: =IF(Assumptions!$C$5="INR",'INR Normalised'!K14,'Raw Data'!K14)/IF(Assumptions!$C$5="INR",INDEX('INR Normalised'!$F14:$S14,Assumptions!$C$7),INDEX('Raw Data'!$F14:$S14,Assumptions!$C$7))*100 -> 92.429456 | L14: =IF(Assumptions!$C$5="INR",'INR Normalised'!L14,'Raw Data'!L14)/IF(Assumptions!$C$5="INR",INDEX('INR Normalised'!$F14:$S14,Assumptions!$C$7),INDEX('Raw Data'!$F14:$S14,Assumptions!$C$7))*100 -> 97.178252 | M14: =IF(Assumptions!$C$5="INR",'INR Normalised'!M14,'Raw Data'!M14)/IF(Assumptions!$C$5="INR",INDEX('INR Normalised'!$F14:$S14,Assumptions!$C$7),INDEX('Raw Data'!$F14:$S14,Assumptions!$C$7))*100 -> 102.31796 | ... S14: =IF(Assumptions!$C$5="INR",'INR Normalised'!S14,'Raw Data'!S14)/IF(Assumptions!$C$5="INR",INDEX('INR Normalised'!$F14:$S14,Assumptions!$C$7),INDEX('Raw Data'!$F14:$S14,Assumptions!$C$7))*100 -> 102.61528 | T14: =IFERROR(S14/R14-1,"") -> 0.013458401 | U14: =IFERROR(S14/F14-1,"") -> 0.026152787
A15: UPSTREAM STEEL INPUTS
A16: ='Raw Data'!A16 -> Coking Coal (Premium HCC, Australia) | B16: Upstream Steel Inputs | C16: =Assumptions!$C$5 -> INR | D16: =Assumptions!$C$6 -> Jul-25 | E16: 100 | F16: =IF(Assumptions!$C$5="INR",'INR Normalised'!F16,'Raw Data'!F16)/IF(Assumptions!$C$5="INR",INDEX('INR Normalised'!$F16:$S16,Assumptions!$C$7),INDEX('Raw Data'!$F16:$S16,Assumptions!$C$7))*100 -> 100 | G16: =IF(Assumptions!$C$5="INR",'INR Normalised'!G16,'Raw Data'!G16)/IF(Assumptions!$C$5="INR",INDEX('INR Normalised'!$F16:$S16,Assumptions!$C$7),INDEX('Raw Data'!$F16:$S16,Assumptions!$C$7))*100 -> 106.91597 | H16: =IF(Assumptions!$C$5="INR",'INR Normalised'!H16,'Raw Data'!H16)/IF(Assumptions!$C$5="INR",INDEX('INR Normalised'!$F16:$S16,Assumptions!$C$7),INDEX('Raw Data'!$F16:$S16,Assumptions!$C$7))*100 -> 107.82574 | I16: =IF(Assumptions!$C$5="INR",'INR Normalised'!I16,'Raw Data'!I16)/IF(Assumptions!$C$5="INR",INDEX('INR Normalised'!$F16:$S16,Assumptions!$C$7),INDEX('Raw Data'!$F16:$S16,Assumptions!$C$7))*100 -> 110.60584 | J16: =IF(Assumptions!$C$5="INR",'INR Normalised'!J16,'Raw Data'!J16)/IF(Assumptions!$C$5="INR",INDEX('INR Normalised'!$F16:$S16,Assumptions!$C$7),INDEX('Raw Data'!$F16:$S16,Assumptions!$C$7))*100 -> 114.34625 | K16: =IF(Assumptions!$C$5="INR",'INR Normalised'!K16,'Raw Data'!K16)/IF(Assumptions!$C$5="INR",INDEX('INR Normalised'!$F16:$S16,Assumptions!$C$7),INDEX('Raw Data'!$F16:$S16,Assumptions!$C$7))*100 -> 122.92025 | L16: =IF(Assumptions!$C$5="INR",'INR Normalised'!L16,'Raw Data'!L16)/IF(Assumptions!$C$5="INR",INDEX('INR Normalised'!$F16:$S16,Assumptions!$C$7),INDEX('Raw Data'!$F16:$S16,Assumptions!$C$7))*100 -> 135.35871 | M16: =IF(Assumptions!$C$5="INR",'INR Normalised'!M16,'Raw Data'!M16)/IF(Assumptions!$C$5="INR",INDEX('INR Normalised'!$F16:$S16,Assumptions!$C$7),INDEX('Raw Data'!$F16:$S16,Assumptions!$C$7))*100 -> 143.51429 | ... S16: =IF(Assumptions!$C$5="INR",'INR Normalised'!S16,'Raw Data'!S16)/IF(Assumptions!$C$5="INR",INDEX('INR Normalised'!$F16:$S16,Assumptions!$C$7),INDEX('Raw Data'!$F16:$S16,Assumptions!$C$7))*100 -> 145.20828 | T16: =IFERROR(S16/R16-1,"") -> 0.00073838516 | U16: =IFERROR(S16/F16-1,"") -> 0.45208285
A17: ='Raw Data'!A17 -> Iron Ore (Fe 62%, Australia) | B17: Upstream Steel Inputs | C17: =Assumptions!$C$5 -> INR | D17: =Assumptions!$C$6 -> Jul-25 | E17: 100 | F17: =IF(Assumptions!$C$5="INR",'INR Normalised'!F17,'Raw Data'!F17)/IF(Assumptions!$C$5="INR",INDEX('INR Normalised'!$F17:$S17,Assumptions!$C$7),INDEX('Raw Data'!$F17:$S17,Assumptions!$C$7))*100 -> 100 | G17: =IF(Assumptions!$C$5="INR",'INR Normalised'!G17,'Raw Data'!G17)/IF(Assumptions!$C$5="INR",INDEX('INR Normalised'!$F17:$S17,Assumptions!$C$7),INDEX('Raw Data'!$F17:$S17,Assumptions!$C$7))*100 -> 104.72945 | H17: =IF(Assumptions!$C$5="INR",'INR Normalised'!H17,'Raw Data'!H17)/IF(Assumptions!$C$5="INR",INDEX('INR Normalised'!$F17:$S17,Assumptions!$C$7),INDEX('Raw Data'!$F17:$S17,Assumptions!$C$7))*100 -> 108.7271 | I17: =IF(Assumptions!$C$5="INR",'INR Normalised'!I17,'Raw Data'!I17)/IF(Assumptions!$C$5="INR",INDEX('INR Normalised'!$F17:$S17,Assumptions!$C$7),INDEX('Raw Data'!$F17:$S17,Assumptions!$C$7))*100 -> 109.88608 | J17: =IF(Assumptions!$C$5="INR",'INR Normalised'!J17,'Raw Data'!J17)/IF(Assumptions!$C$5="INR",INDEX('INR Normalised'!$F17:$S17,Assumptions!$C$7),INDEX('Raw Data'!$F17:$S17,Assumptions!$C$7))*100 -> 108.33371 | K17: =IF(Assumptions!$C$5="INR",'INR Normalised'!K17,'Raw Data'!K17)/IF(Assumptions!$C$5="INR",INDEX('INR Normalised'!$F17:$S17,Assumptions!$C$7),INDEX('Raw Data'!$F17:$S17,Assumptions!$C$7))*100 -> 112.95448 | L17: =IF(Assumptions!$C$5="INR",'INR Normalised'!L17,'Raw Data'!L17)/IF(Assumptions!$C$5="INR",INDEX('INR Normalised'!$F17:$S17,Assumptions!$C$7),INDEX('Raw Data'!$F17:$S17,Assumptions!$C$7))*100 -> 112.7879 | M17: =IF(Assumptions!$C$5="INR",'INR Normalised'!M17,'Raw Data'!M17)/IF(Assumptions!$C$5="INR",INDEX('INR Normalised'!$F17:$S17,Assumptions!$C$7),INDEX('Raw Data'!$F17:$S17,Assumptions!$C$7))*100 -> 105.31657 | ... S17: =IF(Assumptions!$C$5="INR",'INR Normalised'!S17,'Raw Data'!S17)/IF(Assumptions!$C$5="INR",INDEX('INR Normalised'!$F17:$S17,Assumptions!$C$7),INDEX('Raw Data'!$F17:$S17,Assumptions!$C$7))*100 -> 107.41482 | T17: =IFERROR(S17/R17-1,"") -> -0.023559611 | U17: =IFERROR(S17/F17-1,"") -> 0.074148241
A18: NON-FERROUS METALS
A19: ='Raw Data'!A19 -> Virgin Aluminium | B19: Non-Ferrous Metals | C19: =Assumptions!$C$5 -> INR | D19: =Assumptions!$C$6 -> Jul-25 | E19: 100 | F19: =IF(Assumptions!$C$5="INR",'INR Normalised'!F19,'Raw Data'!F19)/IF(Assumptions!$C$5="INR",INDEX('INR Normalised'!$F19:$S19,Assumptions!$C$7),INDEX('Raw Data'!$F19:$S19,Assumptions!$C$7))*100 -> 100 | G19: =IF(Assumptions!$C$5="INR",'INR Normalised'!G19,'Raw Data'!G19)/IF(Assumptions!$C$5="INR",INDEX('INR Normalised'!$F19:$S19,Assumptions!$C$7),INDEX('Raw Data'!$F19:$S19,Assumptions!$C$7))*100 -> 101.25104 | H19: =IF(Assumptions!$C$5="INR",'INR Normalised'!H19,'Raw Data'!H19)/IF(Assumptions!$C$5="INR",INDEX('INR Normalised'!$F19:$S19,Assumptions!$C$7),INDEX('Raw Data'!$F19:$S19,Assumptions!$C$7))*100 -> 104.44695 | I19: =IF(Assumptions!$C$5="INR",'INR Normalised'!I19,'Raw Data'!I19)/IF(Assumptions!$C$5="INR",INDEX('INR Normalised'!$F19:$S19,Assumptions!$C$7),INDEX('Raw Data'!$F19:$S19,Assumptions!$C$7))*100 -> 109.80587 | J19: =IF(Assumptions!$C$5="INR",'INR Normalised'!J19,'Raw Data'!J19)/IF(Assumptions!$C$5="INR",INDEX('INR Normalised'!$F19:$S19,Assumptions!$C$7),INDEX('Raw Data'!$F19:$S19,Assumptions!$C$7))*100 -> 111.7858 | K19: =IF(Assumptions!$C$5="INR",'INR Normalised'!K19,'Raw Data'!K19)/IF(Assumptions!$C$5="INR",INDEX('INR Normalised'!$F19:$S19,Assumptions!$C$7),INDEX('Raw Data'!$F19:$S19,Assumptions!$C$7))*100 -> 115.39684 | L19: =IF(Assumptions!$C$5="INR",'INR Normalised'!L19,'Raw Data'!L19)/IF(Assumptions!$C$5="INR",INDEX('INR Normalised'!$F19:$S19,Assumptions!$C$7),INDEX('Raw Data'!$F19:$S19,Assumptions!$C$7))*100 -> 127.35248 | M19: =IF(Assumptions!$C$5="INR",'INR Normalised'!M19,'Raw Data'!M19)/IF(Assumptions!$C$5="INR",INDEX('INR Normalised'!$F19:$S19,Assumptions!$C$7),INDEX('Raw Data'!$F19:$S19,Assumptions!$C$7))*100 -> 123.96798 | ... S19: =IF(Assumptions!$C$5="INR",'INR Normalised'!S19,'Raw Data'!S19)/IF(Assumptions!$C$5="INR",INDEX('INR Normalised'!$F19:$S19,Assumptions!$C$7),INDEX('Raw Data'!$F19:$S19,Assumptions!$C$7))*100 -> 138.32618 | T19: =IFERROR(S19/R19-1,"") -> 0.02710329 | U19: =IFERROR(S19/F19-1,"") -> 0.38326181
A20: ='Raw Data'!A20 -> Copper | B20: Non-Ferrous Metals | C20: =Assumptions!$C$5 -> INR | D20: =Assumptions!$C$6 -> Jul-25 | E20: 100 | F20: =IF(Assumptions!$C$5="INR",'INR Normalised'!F20,'Raw Data'!F20)/IF(Assumptions!$C$5="INR",INDEX('INR Normalised'!$F20:$S20,Assumptions!$C$7),INDEX('Raw Data'!$F20:$S20,Assumptions!$C$7))*100 -> 100 | G20: =IF(Assumptions!$C$5="INR",'INR Normalised'!G20,'Raw Data'!G20)/IF(Assumptions!$C$5="INR",INDEX('INR Normalised'!$F20:$S20,Assumptions!$C$7),INDEX('Raw Data'!$F20:$S20,Assumptions!$C$7))*100 -> 100.27385 | H20: =IF(Assumptions!$C$5="INR",'INR Normalised'!H20,'Raw Data'!H20)/IF(Assumptions!$C$5="INR",INDEX('INR Normalised'!$F20:$S20,Assumptions!$C$7),INDEX('Raw Data'!$F20:$S20,Assumptions!$C$7))*100 -> 104.34358 | I20: =IF(Assumptions!$C$5="INR",'INR Normalised'!I20,'Raw Data'!I20)/IF(Assumptions!$C$5="INR",INDEX('INR Normalised'!$F20:$S20,Assumptions!$C$7),INDEX('Raw Data'!$F20:$S20,Assumptions!$C$7))*100 -> 112.26245 | J20: =IF(Assumptions!$C$5="INR",'INR Normalised'!J20,'Raw Data'!J20)/IF(Assumptions!$C$5="INR",INDEX('INR Normalised'!$F20:$S20,Assumptions!$C$7),INDEX('Raw Data'!$F20:$S20,Assumptions!$C$7))*100 -> 113.91017 | K20: =IF(Assumptions!$C$5="INR",'INR Normalised'!K20,'Raw Data'!K20)/IF(Assumptions!$C$5="INR",INDEX('INR Normalised'!$F20:$S20,Assumptions!$C$7),INDEX('Raw Data'!$F20:$S20,Assumptions!$C$7))*100 -> 126.15887 | L20: =IF(Assumptions!$C$5="INR",'INR Normalised'!L20,'Raw Data'!L20)/IF(Assumptions!$C$5="INR",INDEX('INR Normalised'!$F20:$S20,Assumptions!$C$7),INDEX('Raw Data'!$F20:$S20,Assumptions!$C$7))*100 -> 141.0055 | M20: =IF(Assumptions!$C$5="INR",'INR Normalised'!M20,'Raw Data'!M20)/IF(Assumptions!$C$5="INR",INDEX('INR Normalised'!$F20:$S20,Assumptions!$C$7),INDEX('Raw Data'!$F20:$S20,Assumptions!$C$7))*100 -> 139.67031 | ... S20: =IF(Assumptions!$C$5="INR",'INR Normalised'!S20,'Raw Data'!S20)/IF(Assumptions!$C$5="INR",INDEX('INR Normalised'!$F20:$S20,Assumptions!$C$7),INDEX('Raw Data'!$F20:$S20,Assumptions!$C$7))*100 -> 162.60132 | T20: =IFERROR(S20/R20-1,"") -> 0.057819747 | U20: =IFERROR(S20/F20-1,"") -> 0.62601316
A21: ='Raw Data'!A21 -> Lead | B21: Non-Ferrous Metals | C21: =Assumptions!$C$5 -> INR | D21: =Assumptions!$C$6 -> Jul-25 | E21: 100 | F21: =IF(Assumptions!$C$5="INR",'INR Normalised'!F21,'Raw Data'!F21)/IF(Assumptions!$C$5="INR",INDEX('INR Normalised'!$F21:$S21,Assumptions!$C$7),INDEX('Raw Data'!$F21:$S21,Assumptions!$C$7))*100 -> 100 | G21: =IF(Assumptions!$C$5="INR",'INR Normalised'!G21,'Raw Data'!G21)/IF(Assumptions!$C$5="INR",INDEX('INR Normalised'!$F21:$S21,Assumptions!$C$7),INDEX('Raw Data'!$F21:$S21,Assumptions!$C$7))*100 -> 99.116736 | H21: =IF(Assumptions!$C$5="INR",'INR Normalised'!H21,'Raw Data'!H21)/IF(Assumptions!$C$5="INR",INDEX('INR Normalised'!$F21:$S21,Assumptions!$C$7),INDEX('Raw Data'!$F21:$S21,Assumptions!$C$7))*100 -> 100.43805 | I21: =IF(Assumptions!$C$5="INR",'INR Normalised'!I21,'Raw Data'!I21)/IF(Assumptions!$C$5="INR",INDEX('INR Normalised'!$F21:$S21,Assumptions!$C$7),INDEX('Raw Data'!$F21:$S21,Assumptions!$C$7))*100 -> 101.25585 | J21: =IF(Assumptions!$C$5="INR",'INR Normalised'!J21,'Raw Data'!J21)/IF(Assumptions!$C$5="INR",INDEX('INR Normalised'!$F21:$S21,Assumptions!$C$7),INDEX('Raw Data'!$F21:$S21,Assumptions!$C$7))*100 -> 103.48205 | K21: =IF(Assumptions!$C$5="INR",'INR Normalised'!K21,'Raw Data'!K21)/IF(Assumptions!$C$5="INR",INDEX('INR Normalised'!$F21:$S21,Assumptions!$C$7),INDEX('Raw Data'!$F21:$S21,Assumptions!$C$7))*100 -> 101.75366 | L21: =IF(Assumptions!$C$5="INR",'INR Normalised'!L21,'Raw Data'!L21)/IF(Assumptions!$C$5="INR",INDEX('INR Normalised'!$F21:$S21,Assumptions!$C$7),INDEX('Raw Data'!$F21:$S21,Assumptions!$C$7))*100 -> 105.51917 | M21: =IF(Assumptions!$C$5="INR",'INR Normalised'!M21,'Raw Data'!M21)/IF(Assumptions!$C$5="INR",INDEX('INR Normalised'!$F21:$S21,Assumptions!$C$7),INDEX('Raw Data'!$F21:$S21,Assumptions!$C$7))*100 -> 101.15649 | ... S21: =IF(Assumptions!$C$5="INR",'INR Normalised'!S21,'Raw Data'!S21)/IF(Assumptions!$C$5="INR",INDEX('INR Normalised'!$F21:$S21,Assumptions!$C$7),INDEX('Raw Data'!$F21:$S21,Assumptions!$C$7))*100 -> 103.00881 | T21: =IFERROR(S21/R21-1,"") -> 0.0027286769 | U21: =IFERROR(S21/F21-1,"") -> 0.030088119
A22: ='Raw Data'!A22 -> Nickel | B22: Non-Ferrous Metals | C22: =Assumptions!$C$5 -> INR | D22: =Assumptions!$C$6 -> Jul-25 | E22: 100 | F22: =IF(Assumptions!$C$5="INR",'INR Normalised'!F22,'Raw Data'!F22)/IF(Assumptions!$C$5="INR",INDEX('INR Normalised'!$F22:$S22,Assumptions!$C$7),INDEX('Raw Data'!$F22:$S22,Assumptions!$C$7))*100 -> 100 | G22: =IF(Assumptions!$C$5="INR",'INR Normalised'!G22,'Raw Data'!G22)/IF(Assumptions!$C$5="INR",INDEX('INR Normalised'!$F22:$S22,Assumptions!$C$7),INDEX('Raw Data'!$F22:$S22,Assumptions!$C$7))*100 -> 100.87581 | H22: =IF(Assumptions!$C$5="INR",'INR Normalised'!H22,'Raw Data'!H22)/IF(Assumptions!$C$5="INR",INDEX('INR Normalised'!$F22:$S22,Assumptions!$C$7),INDEX('Raw Data'!$F22:$S22,Assumptions!$C$7))*100 -> 103.05115 | I22: =IF(Assumptions!$C$5="INR",'INR Normalised'!I22,'Raw Data'!I22)/IF(Assumptions!$C$5="INR",INDEX('INR Normalised'!$F22:$S22,Assumptions!$C$7),INDEX('Raw Data'!$F22:$S22,Assumptions!$C$7))*100 -> 103.01543 | J22: =IF(Assumptions!$C$5="INR",'INR Normalised'!J22,'Raw Data'!J22)/IF(Assumptions!$C$5="INR",INDEX('INR Normalised'!$F22:$S22,Assumptions!$C$7),INDEX('Raw Data'!$F22:$S22,Assumptions!$C$7))*100 -> 100.83266 | K22: =IF(Assumptions!$C$5="INR",'INR Normalised'!K22,'Raw Data'!K22)/IF(Assumptions!$C$5="INR",INDEX('INR Normalised'!$F22:$S22,Assumptions!$C$7),INDEX('Raw Data'!$F22:$S22,Assumptions!$C$7))*100 -> 103.50407 | L22: =IF(Assumptions!$C$5="INR",'INR Normalised'!L22,'Raw Data'!L22)/IF(Assumptions!$C$5="INR",INDEX('INR Normalised'!$F22:$S22,Assumptions!$C$7),INDEX('Raw Data'!$F22:$S22,Assumptions!$C$7))*100 -> 125.11768 | M22: =IF(Assumptions!$C$5="INR",'INR Normalised'!M22,'Raw Data'!M22)/IF(Assumptions!$C$5="INR",INDEX('INR Normalised'!$F22:$S22,Assumptions!$C$7),INDEX('Raw Data'!$F22:$S22,Assumptions!$C$7))*100 -> 120.10462 | ... S22: =IF(Assumptions!$C$5="INR",'INR Normalised'!S22,'Raw Data'!S22)/IF(Assumptions!$C$5="INR",INDEX('INR Normalised'!$F22:$S22,Assumptions!$C$7),INDEX('Raw Data'!$F22:$S22,Assumptions!$C$7))*100 -> 123.61954 | T22: =IFERROR(S22/R22-1,"") -> 0.00326958 | U22: =IFERROR(S22/F22-1,"") -> 0.2361954
A23: ='Raw Data'!A23 -> Zinc | B23: Non-Ferrous Metals | C23: =Assumptions!$C$5 -> INR | D23: =Assumptions!$C$6 -> Jul-25 | E23: 100 | F23: =IF(Assumptions!$C$5="INR",'INR Normalised'!F23,'Raw Data'!F23)/IF(Assumptions!$C$5="INR",INDEX('INR Normalised'!$F23:$S23,Assumptions!$C$7),INDEX('Raw Data'!$F23:$S23,Assumptions!$C$7))*100 -> 100 | G23: =IF(Assumptions!$C$5="INR",'INR Normalised'!G23,'Raw Data'!G23)/IF(Assumptions!$C$5="INR",INDEX('INR Normalised'!$F23:$S23,Assumptions!$C$7),INDEX('Raw Data'!$F23:$S23,Assumptions!$C$7))*100 -> 102.59242 | H23: =IF(Assumptions!$C$5="INR",'INR Normalised'!H23,'Raw Data'!H23)/IF(Assumptions!$C$5="INR",INDEX('INR Normalised'!$F23:$S23,Assumptions!$C$7),INDEX('Raw Data'!$F23:$S23,Assumptions!$C$7))*100 -> 108.87574 | I23: =IF(Assumptions!$C$5="INR",'INR Normalised'!I23,'Raw Data'!I23)/IF(Assumptions!$C$5="INR",INDEX('INR Normalised'!$F23:$S23,Assumptions!$C$7),INDEX('Raw Data'!$F23:$S23,Assumptions!$C$7))*100 -> 117.14891 | J23: =IF(Assumptions!$C$5="INR",'INR Normalised'!J23,'Raw Data'!J23)/IF(Assumptions!$C$5="INR",INDEX('INR Normalised'!$F23:$S23,Assumptions!$C$7),INDEX('Raw Data'!$F23:$S23,Assumptions!$C$7))*100 -> 119.14665 | K23: =IF(Assumptions!$C$5="INR",'INR Normalised'!K23,'Raw Data'!K23)/IF(Assumptions!$C$5="INR",INDEX('INR Normalised'!$F23:$S23,Assumptions!$C$7),INDEX('Raw Data'!$F23:$S23,Assumptions!$C$7))*100 -> 119.69624 | L23: =IF(Assumptions!$C$5="INR",'INR Normalised'!L23,'Raw Data'!L23)/IF(Assumptions!$C$5="INR",INDEX('INR Normalised'!$F23:$S23,Assumptions!$C$7),INDEX('Raw Data'!$F23:$S23,Assumptions!$C$7))*100 -> 122.95734 | M23: =IF(Assumptions!$C$5="INR",'INR Normalised'!M23,'Raw Data'!M23)/IF(Assumptions!$C$5="INR",INDEX('INR Normalised'!$F23:$S23,Assumptions!$C$7),INDEX('Raw Data'!$F23:$S23,Assumptions!$C$7))*100 -> 126.7708 | ... S23: =IF(Assumptions!$C$5="INR",'INR Normalised'!S23,'Raw Data'!S23)/IF(Assumptions!$C$5="INR",INDEX('INR Normalised'!$F23:$S23,Assumptions!$C$7),INDEX('Raw Data'!$F23:$S23,Assumptions!$C$7))*100 -> 155.5933 | T23: =IFERROR(S23/R23-1,"") -> 0.074117351 | U23: =IFERROR(S23/F23-1,"") -> 0.55593296
A24: PRECIOUS / PGM
A25: ='Raw Data'!A25 -> Platinum | B25: Precious / Pgm | C25: =Assumptions!$C$5 -> INR | D25: =Assumptions!$C$6 -> Jul-25 | E25: 100 | F25: =IF(Assumptions!$C$5="INR",'INR Normalised'!F25,'Raw Data'!F25)/IF(Assumptions!$C$5="INR",INDEX('INR Normalised'!$F25:$S25,Assumptions!$C$7),INDEX('Raw Data'!$F25:$S25,Assumptions!$C$7))*100 -> 100 | G25: =IF(Assumptions!$C$5="INR",'INR Normalised'!G25,'Raw Data'!G25)/IF(Assumptions!$C$5="INR",INDEX('INR Normalised'!$F25:$S25,Assumptions!$C$7),INDEX('Raw Data'!$F25:$S25,Assumptions!$C$7))*100 -> 97.44801 | H25: =IF(Assumptions!$C$5="INR",'INR Normalised'!H25,'Raw Data'!H25)/IF(Assumptions!$C$5="INR",INDEX('INR Normalised'!$F25:$S25,Assumptions!$C$7),INDEX('Raw Data'!$F25:$S25,Assumptions!$C$7))*100 -> 105.53442 | I25: =IF(Assumptions!$C$5="INR",'INR Normalised'!I25,'Raw Data'!I25)/IF(Assumptions!$C$5="INR",INDEX('INR Normalised'!$F25:$S25,Assumptions!$C$7),INDEX('Raw Data'!$F25:$S25,Assumptions!$C$7))*100 -> 119.18021 | J25: =IF(Assumptions!$C$5="INR",'INR Normalised'!J25,'Raw Data'!J25)/IF(Assumptions!$C$5="INR",INDEX('INR Normalised'!$F25:$S25,Assumptions!$C$7),INDEX('Raw Data'!$F25:$S25,Assumptions!$C$7))*100 -> 116.51752 | K25: =IF(Assumptions!$C$5="INR",'INR Normalised'!K25,'Raw Data'!K25)/IF(Assumptions!$C$5="INR",INDEX('INR Normalised'!$F25:$S25,Assumptions!$C$7),INDEX('Raw Data'!$F25:$S25,Assumptions!$C$7))*100 -> 139.51607 | L25: =IF(Assumptions!$C$5="INR",'INR Normalised'!L25,'Raw Data'!L25)/IF(Assumptions!$C$5="INR",INDEX('INR Normalised'!$F25:$S25,Assumptions!$C$7),INDEX('Raw Data'!$F25:$S25,Assumptions!$C$7))*100 -> 183.82667 | M25: =IF(Assumptions!$C$5="INR",'INR Normalised'!M25,'Raw Data'!M25)/IF(Assumptions!$C$5="INR",INDEX('INR Normalised'!$F25:$S25,Assumptions!$C$7),INDEX('Raw Data'!$F25:$S25,Assumptions!$C$7))*100 -> 162.21057 | ... S25: =IF(Assumptions!$C$5="INR",'INR Normalised'!S25,'Raw Data'!S25)/IF(Assumptions!$C$5="INR",INDEX('INR Normalised'!$F25:$S25,Assumptions!$C$7),INDEX('Raw Data'!$F25:$S25,Assumptions!$C$7))*100 -> 141.65744 | T25: =IFERROR(S25/R25-1,"") -> 0.091519876 | U25: =IFERROR(S25/F25-1,"") -> 0.41657442
A26: ='Raw Data'!A26 -> Palladium | B26: Precious / Pgm | C26: =Assumptions!$C$5 -> INR | D26: =Assumptions!$C$6 -> Jul-25 | E26: 100 | F26: =IF(Assumptions!$C$5="INR",'INR Normalised'!F26,'Raw Data'!F26)/IF(Assumptions!$C$5="INR",INDEX('INR Normalised'!$F26:$S26,Assumptions!$C$7),INDEX('Raw Data'!$F26:$S26,Assumptions!$C$7))*100 -> 100 | G26: =IF(Assumptions!$C$5="INR",'INR Normalised'!G26,'Raw Data'!G26)/IF(Assumptions!$C$5="INR",INDEX('INR Normalised'!$F26:$S26,Assumptions!$C$7),INDEX('Raw Data'!$F26:$S26,Assumptions!$C$7))*100 -> 96.502167 | H26: =IF(Assumptions!$C$5="INR",'INR Normalised'!H26,'Raw Data'!H26)/IF(Assumptions!$C$5="INR",INDEX('INR Normalised'!$F26:$S26,Assumptions!$C$7),INDEX('Raw Data'!$F26:$S26,Assumptions!$C$7))*100 -> 100.95621 | I26: =IF(Assumptions!$C$5="INR",'INR Normalised'!I26,'Raw Data'!I26)/IF(Assumptions!$C$5="INR",INDEX('INR Normalised'!$F26:$S26,Assumptions!$C$7),INDEX('Raw Data'!$F26:$S26,Assumptions!$C$7))*100 -> 121.03712 | J26: =IF(Assumptions!$C$5="INR",'INR Normalised'!J26,'Raw Data'!J26)/IF(Assumptions!$C$5="INR",INDEX('INR Normalised'!$F26:$S26,Assumptions!$C$7),INDEX('Raw Data'!$F26:$S26,Assumptions!$C$7))*100 -> 121.98527 | K26: =IF(Assumptions!$C$5="INR",'INR Normalised'!K26,'Raw Data'!K26)/IF(Assumptions!$C$5="INR",INDEX('INR Normalised'!$F26:$S26,Assumptions!$C$7),INDEX('Raw Data'!$F26:$S26,Assumptions!$C$7))*100 -> 137.63452 | L26: =IF(Assumptions!$C$5="INR",'INR Normalised'!L26,'Raw Data'!L26)/IF(Assumptions!$C$5="INR",INDEX('INR Normalised'!$F26:$S26,Assumptions!$C$7),INDEX('Raw Data'!$F26:$S26,Assumptions!$C$7))*100 -> 162.28791 | M26: =IF(Assumptions!$C$5="INR",'INR Normalised'!M26,'Raw Data'!M26)/IF(Assumptions!$C$5="INR",INDEX('INR Normalised'!$F26:$S26,Assumptions!$C$7),INDEX('Raw Data'!$F26:$S26,Assumptions!$C$7))*100 -> 152.60145 | ... S26: =IF(Assumptions!$C$5="INR",'INR Normalised'!S26,'Raw Data'!S26)/IF(Assumptions!$C$5="INR",INDEX('INR Normalised'!$F26:$S26,Assumptions!$C$7),INDEX('Raw Data'!$F26:$S26,Assumptions!$C$7))*100 -> 124.36907 | T26: =IFERROR(S26/R26-1,"") -> 0.053674701 | U26: =IFERROR(S26/F26-1,"") -> 0.24369068
A27: ='Raw Data'!A27 -> Rhodium | B27: Precious / Pgm | C27: =Assumptions!$C$5 -> INR | D27: =Assumptions!$C$6 -> Jul-25 | E27: 100 | F27: =IF(Assumptions!$C$5="INR",'INR Normalised'!F27,'Raw Data'!F27)/IF(Assumptions!$C$5="INR",INDEX('INR Normalised'!$F27:$S27,Assumptions!$C$7),INDEX('Raw Data'!$F27:$S27,Assumptions!$C$7))*100 -> 100 | G27: =IF(Assumptions!$C$5="INR",'INR Normalised'!G27,'Raw Data'!G27)/IF(Assumptions!$C$5="INR",INDEX('INR Normalised'!$F27:$S27,Assumptions!$C$7),INDEX('Raw Data'!$F27:$S27,Assumptions!$C$7))*100 -> 123.93469 | H27: =IF(Assumptions!$C$5="INR",'INR Normalised'!H27,'Raw Data'!H27)/IF(Assumptions!$C$5="INR",INDEX('INR Normalised'!$F27:$S27,Assumptions!$C$7),INDEX('Raw Data'!$F27:$S27,Assumptions!$C$7))*100 -> 123.41416 | I27: =IF(Assumptions!$C$5="INR",'INR Normalised'!I27,'Raw Data'!I27)/IF(Assumptions!$C$5="INR",INDEX('INR Normalised'!$F27:$S27,Assumptions!$C$7),INDEX('Raw Data'!$F27:$S27,Assumptions!$C$7))*100 -> 131.42802 | J27: =IF(Assumptions!$C$5="INR",'INR Normalised'!J27,'Raw Data'!J27)/IF(Assumptions!$C$5="INR",INDEX('INR Normalised'!$F27:$S27,Assumptions!$C$7),INDEX('Raw Data'!$F27:$S27,Assumptions!$C$7))*100 -> 139.37066 | K27: =IF(Assumptions!$C$5="INR",'INR Normalised'!K27,'Raw Data'!K27)/IF(Assumptions!$C$5="INR",INDEX('INR Normalised'!$F27:$S27,Assumptions!$C$7),INDEX('Raw Data'!$F27:$S27,Assumptions!$C$7))*100 -> 143.19579 | L27: =IF(Assumptions!$C$5="INR",'INR Normalised'!L27,'Raw Data'!L27)/IF(Assumptions!$C$5="INR",INDEX('INR Normalised'!$F27:$S27,Assumptions!$C$7),INDEX('Raw Data'!$F27:$S27,Assumptions!$C$7))*100 -> 180.05778 | M27: =IF(Assumptions!$C$5="INR",'INR Normalised'!M27,'Raw Data'!M27)/IF(Assumptions!$C$5="INR",INDEX('INR Normalised'!$F27:$S27,Assumptions!$C$7),INDEX('Raw Data'!$F27:$S27,Assumptions!$C$7))*100 -> 194.30732 | ... S27: =IF(Assumptions!$C$5="INR",'INR Normalised'!S27,'Raw Data'!S27)/IF(Assumptions!$C$5="INR",INDEX('INR Normalised'!$F27:$S27,Assumptions!$C$7),INDEX('Raw Data'!$F27:$S27,Assumptions!$C$7))*100 -> 162.30087 | T27: =IFERROR(S27/R27-1,"") -> 0.060066582 | U27: =IFERROR(S27/F27-1,"") -> 0.62300874
A28: POLYMERS
A29: ='Raw Data'!A29 -> Polypropylene (PP) | B29: Polymers | C29: =Assumptions!$C$5 -> INR | D29: =Assumptions!$C$6 -> Jul-25 | E29: 100 | F29: =IF(Assumptions!$C$5="INR",'INR Normalised'!F29,'Raw Data'!F29)/IF(Assumptions!$C$5="INR",INDEX('INR Normalised'!$F29:$S29,Assumptions!$C$7),INDEX('Raw Data'!$F29:$S29,Assumptions!$C$7))*100 -> 100 | G29: =IF(Assumptions!$C$5="INR",'INR Normalised'!G29,'Raw Data'!G29)/IF(Assumptions!$C$5="INR",INDEX('INR Normalised'!$F29:$S29,Assumptions!$C$7),INDEX('Raw Data'!$F29:$S29,Assumptions!$C$7))*100 -> 100.5 | H29: =IF(Assumptions!$C$5="INR",'INR Normalised'!H29,'Raw Data'!H29)/IF(Assumptions!$C$5="INR",INDEX('INR Normalised'!$F29:$S29,Assumptions!$C$7),INDEX('Raw Data'!$F29:$S29,Assumptions!$C$7))*100 -> 99.3 | I29: =IF(Assumptions!$C$5="INR",'INR Normalised'!I29,'Raw Data'!I29)/IF(Assumptions!$C$5="INR",INDEX('INR Normalised'!$F29:$S29,Assumptions!$C$7),INDEX('Raw Data'!$F29:$S29,Assumptions!$C$7))*100 -> 99.4 | J29: =IF(Assumptions!$C$5="INR",'INR Normalised'!J29,'Raw Data'!J29)/IF(Assumptions!$C$5="INR",INDEX('INR Normalised'!$F29:$S29,Assumptions!$C$7),INDEX('Raw Data'!$F29:$S29,Assumptions!$C$7))*100 -> 95.2 | K29: =IF(Assumptions!$C$5="INR",'INR Normalised'!K29,'Raw Data'!K29)/IF(Assumptions!$C$5="INR",INDEX('INR Normalised'!$F29:$S29,Assumptions!$C$7),INDEX('Raw Data'!$F29:$S29,Assumptions!$C$7))*100 -> 94.3 | L29: =IF(Assumptions!$C$5="INR",'INR Normalised'!L29,'Raw Data'!L29)/IF(Assumptions!$C$5="INR",INDEX('INR Normalised'!$F29:$S29,Assumptions!$C$7),INDEX('Raw Data'!$F29:$S29,Assumptions!$C$7))*100 -> 96.5 | M29: =IF(Assumptions!$C$5="INR",'INR Normalised'!M29,'Raw Data'!M29)/IF(Assumptions!$C$5="INR",INDEX('INR Normalised'!$F29:$S29,Assumptions!$C$7),INDEX('Raw Data'!$F29:$S29,Assumptions!$C$7))*100 -> 98.2 | ... S29: =IF(Assumptions!$C$5="INR",'INR Normalised'!S29,'Raw Data'!S29)/IF(Assumptions!$C$5="INR",INDEX('INR Normalised'!$F29:$S29,Assumptions!$C$7),INDEX('Raw Data'!$F29:$S29,Assumptions!$C$7))*100 -> 134.4 | T29: =IFERROR(S29/R29-1,"") -> 0.022053232 | U29: =IFERROR(S29/F29-1,"") -> 0.344
A30: ='Raw Data'!A30 -> ABS | B30: Polymers | C30: =Assumptions!$C$5 -> INR | D30: =Assumptions!$C$6 -> Jul-25 | E30: 100 | F30: =IF(Assumptions!$C$5="INR",'INR Normalised'!F30,'Raw Data'!F30)/IF(Assumptions!$C$5="INR",INDEX('INR Normalised'!$F30:$S30,Assumptions!$C$7),INDEX('Raw Data'!$F30:$S30,Assumptions!$C$7))*100 -> 100 | G30: =IF(Assumptions!$C$5="INR",'INR Normalised'!G30,'Raw Data'!G30)/IF(Assumptions!$C$5="INR",INDEX('INR Normalised'!$F30:$S30,Assumptions!$C$7),INDEX('Raw Data'!$F30:$S30,Assumptions!$C$7))*100 -> 99.660557 | H30: =IF(Assumptions!$C$5="INR",'INR Normalised'!H30,'Raw Data'!H30)/IF(Assumptions!$C$5="INR",INDEX('INR Normalised'!$F30:$S30,Assumptions!$C$7),INDEX('Raw Data'!$F30:$S30,Assumptions!$C$7))*100 -> 97.148676 | I30: =IF(Assumptions!$C$5="INR",'INR Normalised'!I30,'Raw Data'!I30)/IF(Assumptions!$C$5="INR",INDEX('INR Normalised'!$F30:$S30,Assumptions!$C$7),INDEX('Raw Data'!$F30:$S30,Assumptions!$C$7))*100 -> 93.4148 | J30: =IF(Assumptions!$C$5="INR",'INR Normalised'!J30,'Raw Data'!J30)/IF(Assumptions!$C$5="INR",INDEX('INR Normalised'!$F30:$S30,Assumptions!$C$7),INDEX('Raw Data'!$F30:$S30,Assumptions!$C$7))*100 -> 88.730482 | K30: =IF(Assumptions!$C$5="INR",'INR Normalised'!K30,'Raw Data'!K30)/IF(Assumptions!$C$5="INR",INDEX('INR Normalised'!$F30:$S30,Assumptions!$C$7),INDEX('Raw Data'!$F30:$S30,Assumptions!$C$7))*100 -> 84.24983 | L30: =IF(Assumptions!$C$5="INR",'INR Normalised'!L30,'Raw Data'!L30)/IF(Assumptions!$C$5="INR",INDEX('INR Normalised'!$F30:$S30,Assumptions!$C$7),INDEX('Raw Data'!$F30:$S30,Assumptions!$C$7))*100 -> 85.81127 | M30: =IF(Assumptions!$C$5="INR",'INR Normalised'!M30,'Raw Data'!M30)/IF(Assumptions!$C$5="INR",INDEX('INR Normalised'!$F30:$S30,Assumptions!$C$7),INDEX('Raw Data'!$F30:$S30,Assumptions!$C$7))*100 -> 88.662593 | ... S30: =IF(Assumptions!$C$5="INR",'INR Normalised'!S30,'Raw Data'!S30)/IF(Assumptions!$C$5="INR",INDEX('INR Normalised'!$F30:$S30,Assumptions!$C$7),INDEX('Raw Data'!$F30:$S30,Assumptions!$C$7))*100 -> 116.63272 | T30: =IFERROR(S30/R30-1,"") -> -0.075349839 | U30: =IFERROR(S30/F30-1,"") -> 0.16632722
A31: ='Raw Data'!A31 -> Polycarbonate (PC) | B31: Polymers | C31: =Assumptions!$C$5 -> INR | D31: =Assumptions!$C$6 -> Jul-25 | E31: 100 | F31: =IF(Assumptions!$C$5="INR",'INR Normalised'!F31,'Raw Data'!F31)/IF(Assumptions!$C$5="INR",INDEX('INR Normalised'!$F31:$S31,Assumptions!$C$7),INDEX('Raw Data'!$F31:$S31,Assumptions!$C$7))*100 -> 100 | G31: =IF(Assumptions!$C$5="INR",'INR Normalised'!G31,'Raw Data'!G31)/IF(Assumptions!$C$5="INR",INDEX('INR Normalised'!$F31:$S31,Assumptions!$C$7),INDEX('Raw Data'!$F31:$S31,Assumptions!$C$7))*100 -> 101.72414 | H31: =IF(Assumptions!$C$5="INR",'INR Normalised'!H31,'Raw Data'!H31)/IF(Assumptions!$C$5="INR",INDEX('INR Normalised'!$F31:$S31,Assumptions!$C$7),INDEX('Raw Data'!$F31:$S31,Assumptions!$C$7))*100 -> 103.77446 | I31: =IF(Assumptions!$C$5="INR",'INR Normalised'!I31,'Raw Data'!I31)/IF(Assumptions!$C$5="INR",INDEX('INR Normalised'!$F31:$S31,Assumptions!$C$7),INDEX('Raw Data'!$F31:$S31,Assumptions!$C$7))*100 -> 103.26188 | J31: =IF(Assumptions!$C$5="INR",'INR Normalised'!J31,'Raw Data'!J31)/IF(Assumptions!$C$5="INR",INDEX('INR Normalised'!$F31:$S31,Assumptions!$C$7),INDEX('Raw Data'!$F31:$S31,Assumptions!$C$7))*100 -> 103.21528 | K31: =IF(Assumptions!$C$5="INR",'INR Normalised'!K31,'Raw Data'!K31)/IF(Assumptions!$C$5="INR",INDEX('INR Normalised'!$F31:$S31,Assumptions!$C$7),INDEX('Raw Data'!$F31:$S31,Assumptions!$C$7))*100 -> 97.670084 | L31: =IF(Assumptions!$C$5="INR",'INR Normalised'!L31,'Raw Data'!L31)/IF(Assumptions!$C$5="INR",INDEX('INR Normalised'!$F31:$S31,Assumptions!$C$7),INDEX('Raw Data'!$F31:$S31,Assumptions!$C$7))*100 -> 97.343896 | M31: =IF(Assumptions!$C$5="INR",'INR Normalised'!M31,'Raw Data'!M31)/IF(Assumptions!$C$5="INR",INDEX('INR Normalised'!$F31:$S31,Assumptions!$C$7),INDEX('Raw Data'!$F31:$S31,Assumptions!$C$7))*100 -> 90.587139 | ... S31: =IF(Assumptions!$C$5="INR",'INR Normalised'!S31,'Raw Data'!S31)/IF(Assumptions!$C$5="INR",INDEX('INR Normalised'!$F31:$S31,Assumptions!$C$7),INDEX('Raw Data'!$F31:$S31,Assumptions!$C$7))*100 -> 117.89376 | T31: =IFERROR(S31/R31-1,"") -> -0.0097847358 | U31: =IFERROR(S31/F31-1,"") -> 0.17893756
A32: CHEMICALS
A33: ='Raw Data'!A33 -> Urea (Prilled), CFR | B33: Chemicals | C33: =Assumptions!$C$5 -> INR | D33: =Assumptions!$C$6 -> Jul-25 | E33: 100 | F33: =IF(Assumptions!$C$5="INR",'INR Normalised'!F33,'Raw Data'!F33)/IF(Assumptions!$C$5="INR",INDEX('INR Normalised'!$F33:$S33,Assumptions!$C$7),INDEX('Raw Data'!$F33:$S33,Assumptions!$C$7))*100 -> 100 | G33: =IF(Assumptions!$C$5="INR",'INR Normalised'!G33,'Raw Data'!G33)/IF(Assumptions!$C$5="INR",INDEX('INR Normalised'!$F33:$S33,Assumptions!$C$7),INDEX('Raw Data'!$F33:$S33,Assumptions!$C$7))*100 -> 113.53747 | H33: =IF(Assumptions!$C$5="INR",'INR Normalised'!H33,'Raw Data'!H33)/IF(Assumptions!$C$5="INR",INDEX('INR Normalised'!$F33:$S33,Assumptions!$C$7),INDEX('Raw Data'!$F33:$S33,Assumptions!$C$7))*100 -> 99.94804 | I33: =IF(Assumptions!$C$5="INR",'INR Normalised'!I33,'Raw Data'!I33)/IF(Assumptions!$C$5="INR",INDEX('INR Normalised'!$F33:$S33,Assumptions!$C$7),INDEX('Raw Data'!$F33:$S33,Assumptions!$C$7))*100 -> 96.161683 | J33: =IF(Assumptions!$C$5="INR",'INR Normalised'!J33,'Raw Data'!J33)/IF(Assumptions!$C$5="INR",INDEX('INR Normalised'!$F33:$S33,Assumptions!$C$7),INDEX('Raw Data'!$F33:$S33,Assumptions!$C$7))*100 -> 87.511218 | K33: =IF(Assumptions!$C$5="INR",'INR Normalised'!K33,'Raw Data'!K33)/IF(Assumptions!$C$5="INR",INDEX('INR Normalised'!$F33:$S33,Assumptions!$C$7),INDEX('Raw Data'!$F33:$S33,Assumptions!$C$7))*100 -> 92.110622 | L33: =IF(Assumptions!$C$5="INR",'INR Normalised'!L33,'Raw Data'!L33)/IF(Assumptions!$C$5="INR",INDEX('INR Normalised'!$F33:$S33,Assumptions!$C$7),INDEX('Raw Data'!$F33:$S33,Assumptions!$C$7))*100 -> 93.846228 | M33: =IF(Assumptions!$C$5="INR",'INR Normalised'!M33,'Raw Data'!M33)/IF(Assumptions!$C$5="INR",INDEX('INR Normalised'!$F33:$S33,Assumptions!$C$7),INDEX('Raw Data'!$F33:$S33,Assumptions!$C$7))*100 -> 94.328558 | ... S33: =IF(Assumptions!$C$5="INR",'INR Normalised'!S33,'Raw Data'!S33)/IF(Assumptions!$C$5="INR",INDEX('INR Normalised'!$F33:$S33,Assumptions!$C$7),INDEX('Raw Data'!$F33:$S33,Assumptions!$C$7))*100 -> 97.758095 | T33: =IFERROR(S33/R33-1,"") -> -0.064638191 | U33: =IFERROR(S33/F33-1,"") -> -0.022419048
A34: RUBBER & CARBON BLACK
A35: ='Raw Data'!A35 -> Natural Rubber (RSS 4) | B35: Rubber & Carbon Black | C35: =Assumptions!$C$5 -> INR | D35: =Assumptions!$C$6 -> Jul-25 | E35: 100 | F35: =IF(Assumptions!$C$5="INR",'INR Normalised'!F35,'Raw Data'!F35)/IF(Assumptions!$C$5="INR",INDEX('INR Normalised'!$F35:$S35,Assumptions!$C$7),INDEX('Raw Data'!$F35:$S35,Assumptions!$C$7))*100 -> 100 | G35: =IF(Assumptions!$C$5="INR",'INR Normalised'!G35,'Raw Data'!G35)/IF(Assumptions!$C$5="INR",INDEX('INR Normalised'!$F35:$S35,Assumptions!$C$7),INDEX('Raw Data'!$F35:$S35,Assumptions!$C$7))*100 -> 94.731255 | H35: =IF(Assumptions!$C$5="INR",'INR Normalised'!H35,'Raw Data'!H35)/IF(Assumptions!$C$5="INR",INDEX('INR Normalised'!$F35:$S35,Assumptions!$C$7),INDEX('Raw Data'!$F35:$S35,Assumptions!$C$7))*100 -> 90.905143 | I35: =IF(Assumptions!$C$5="INR",'INR Normalised'!I35,'Raw Data'!I35)/IF(Assumptions!$C$5="INR",INDEX('INR Normalised'!$F35:$S35,Assumptions!$C$7),INDEX('Raw Data'!$F35:$S35,Assumptions!$C$7))*100 -> 90.384059 | J35: =IF(Assumptions!$C$5="INR",'INR Normalised'!J35,'Raw Data'!J35)/IF(Assumptions!$C$5="INR",INDEX('INR Normalised'!$F35:$S35,Assumptions!$C$7),INDEX('Raw Data'!$F35:$S35,Assumptions!$C$7))*100 -> 89.766477 | K35: =IF(Assumptions!$C$5="INR",'INR Normalised'!K35,'Raw Data'!K35)/IF(Assumptions!$C$5="INR",INDEX('INR Normalised'!$F35:$S35,Assumptions!$C$7),INDEX('Raw Data'!$F35:$S35,Assumptions!$C$7))*100 -> 88.651935 | L35: =IF(Assumptions!$C$5="INR",'INR Normalised'!L35,'Raw Data'!L35)/IF(Assumptions!$C$5="INR",INDEX('INR Normalised'!$F35:$S35,Assumptions!$C$7),INDEX('Raw Data'!$F35:$S35,Assumptions!$C$7))*100 -> 92.482872 | M35: =IF(Assumptions!$C$5="INR",'INR Normalised'!M35,'Raw Data'!M35)/IF(Assumptions!$C$5="INR",INDEX('INR Normalised'!$F35:$S35,Assumptions!$C$7),INDEX('Raw Data'!$F35:$S35,Assumptions!$C$7))*100 -> 102.51858 | ... S35: =IF(Assumptions!$C$5="INR",'INR Normalised'!S35,'Raw Data'!S35)/IF(Assumptions!$C$5="INR",INDEX('INR Normalised'!$F35:$S35,Assumptions!$C$7),INDEX('Raw Data'!$F35:$S35,Assumptions!$C$7))*100 -> 134.49773 | T35: =IFERROR(S35/R35-1,"") -> 0.0094879409 | U35: =IFERROR(S35/F35-1,"") -> 0.34497732
A36: ='Raw Data'!A36 -> Synthetic Rubber - SBR 1502 | B36: Rubber & Carbon Black | C36: =Assumptions!$C$5 -> INR | D36: =Assumptions!$C$6 -> Jul-25 | E36: 100 | F36: =IF(Assumptions!$C$5="INR",'INR Normalised'!F36,'Raw Data'!F36)/IF(Assumptions!$C$5="INR",INDEX('INR Normalised'!$F36:$S36,Assumptions!$C$7),INDEX('Raw Data'!$F36:$S36,Assumptions!$C$7))*100 -> 100 | G36: =IF(Assumptions!$C$5="INR",'INR Normalised'!G36,'Raw Data'!G36)/IF(Assumptions!$C$5="INR",INDEX('INR Normalised'!$F36:$S36,Assumptions!$C$7),INDEX('Raw Data'!$F36:$S36,Assumptions!$C$7))*100 -> 94.651971 | H36: =IF(Assumptions!$C$5="INR",'INR Normalised'!H36,'Raw Data'!H36)/IF(Assumptions!$C$5="INR",INDEX('INR Normalised'!$F36:$S36,Assumptions!$C$7),INDEX('Raw Data'!$F36:$S36,Assumptions!$C$7))*100 -> 96.41112 | I36: =IF(Assumptions!$C$5="INR",'INR Normalised'!I36,'Raw Data'!I36)/IF(Assumptions!$C$5="INR",INDEX('INR Normalised'!$F36:$S36,Assumptions!$C$7),INDEX('Raw Data'!$F36:$S36,Assumptions!$C$7))*100 -> 96.340536 | J36: =IF(Assumptions!$C$5="INR",'INR Normalised'!J36,'Raw Data'!J36)/IF(Assumptions!$C$5="INR",INDEX('INR Normalised'!$F36:$S36,Assumptions!$C$7),INDEX('Raw Data'!$F36:$S36,Assumptions!$C$7))*100 -> 95.841025 | K36: =IF(Assumptions!$C$5="INR",'INR Normalised'!K36,'Raw Data'!K36)/IF(Assumptions!$C$5="INR",INDEX('INR Normalised'!$F36:$S36,Assumptions!$C$7),INDEX('Raw Data'!$F36:$S36,Assumptions!$C$7))*100 -> 87.794549 | L36: =IF(Assumptions!$C$5="INR",'INR Normalised'!L36,'Raw Data'!L36)/IF(Assumptions!$C$5="INR",INDEX('INR Normalised'!$F36:$S36,Assumptions!$C$7),INDEX('Raw Data'!$F36:$S36,Assumptions!$C$7))*100 -> 84.477142 | M36: =IF(Assumptions!$C$5="INR",'INR Normalised'!M36,'Raw Data'!M36)/IF(Assumptions!$C$5="INR",INDEX('INR Normalised'!$F36:$S36,Assumptions!$C$7),INDEX('Raw Data'!$F36:$S36,Assumptions!$C$7))*100 -> 81.550657 | ... S36: =IF(Assumptions!$C$5="INR",'INR Normalised'!S36,'Raw Data'!S36)/IF(Assumptions!$C$5="INR",INDEX('INR Normalised'!$F36:$S36,Assumptions!$C$7),INDEX('Raw Data'!$F36:$S36,Assumptions!$C$7))*100 -> 136.5512 | T36: =IFERROR(S36/R36-1,"") -> 0.019787527 | U36: =IFERROR(S36/F36-1,"") -> 0.365512
A37: ='Raw Data'!A37 -> EPDM | B37: Rubber & Carbon Black | C37: =Assumptions!$C$5 -> INR | D37: =Assumptions!$C$6 -> Jul-25 | E37: 100 | F37: =IF(Assumptions!$C$5="INR",'INR Normalised'!F37,'Raw Data'!F37)/IF(Assumptions!$C$5="INR",INDEX('INR Normalised'!$F37:$S37,Assumptions!$C$7),INDEX('Raw Data'!$F37:$S37,Assumptions!$C$7))*100 -> 100 | G37: =IF(Assumptions!$C$5="INR",'INR Normalised'!G37,'Raw Data'!G37)/IF(Assumptions!$C$5="INR",INDEX('INR Normalised'!$F37:$S37,Assumptions!$C$7),INDEX('Raw Data'!$F37:$S37,Assumptions!$C$7))*100 -> 99.396689 | H37: =IF(Assumptions!$C$5="INR",'INR Normalised'!H37,'Raw Data'!H37)/IF(Assumptions!$C$5="INR",INDEX('INR Normalised'!$F37:$S37,Assumptions!$C$7),INDEX('Raw Data'!$F37:$S37,Assumptions!$C$7))*100 -> 98.326151 | I37: =IF(Assumptions!$C$5="INR",'INR Normalised'!I37,'Raw Data'!I37)/IF(Assumptions!$C$5="INR",INDEX('INR Normalised'!$F37:$S37,Assumptions!$C$7),INDEX('Raw Data'!$F37:$S37,Assumptions!$C$7))*100 -> 97.577682 | J37: =IF(Assumptions!$C$5="INR",'INR Normalised'!J37,'Raw Data'!J37)/IF(Assumptions!$C$5="INR",INDEX('INR Normalised'!$F37:$S37,Assumptions!$C$7),INDEX('Raw Data'!$F37:$S37,Assumptions!$C$7))*100 -> 96.23951 | K37: =IF(Assumptions!$C$5="INR",'INR Normalised'!K37,'Raw Data'!K37)/IF(Assumptions!$C$5="INR",INDEX('INR Normalised'!$F37:$S37,Assumptions!$C$7),INDEX('Raw Data'!$F37:$S37,Assumptions!$C$7))*100 -> 95.93105 | L37: =IF(Assumptions!$C$5="INR",'INR Normalised'!L37,'Raw Data'!L37)/IF(Assumptions!$C$5="INR",INDEX('INR Normalised'!$F37:$S37,Assumptions!$C$7),INDEX('Raw Data'!$F37:$S37,Assumptions!$C$7))*100 -> 94.216376 | M37: =IF(Assumptions!$C$5="INR",'INR Normalised'!M37,'Raw Data'!M37)/IF(Assumptions!$C$5="INR",INDEX('INR Normalised'!$F37:$S37,Assumptions!$C$7),INDEX('Raw Data'!$F37:$S37,Assumptions!$C$7))*100 -> 93.077795 | ... S37: =IF(Assumptions!$C$5="INR",'INR Normalised'!S37,'Raw Data'!S37)/IF(Assumptions!$C$5="INR",INDEX('INR Normalised'!$F37:$S37,Assumptions!$C$7),INDEX('Raw Data'!$F37:$S37,Assumptions!$C$7))*100 -> 132.84191 | T37: =IFERROR(S37/R37-1,"") -> 0.016769669 | U37: =IFERROR(S37/F37-1,"") -> 0.32841914
A38: ='Raw Data'!A38 -> Carbon Black (N330) | B38: Rubber & Carbon Black | C38: =Assumptions!$C$5 -> INR | D38: =Assumptions!$C$6 -> Jul-25 | E38: 100 | F38: =IF(Assumptions!$C$5="INR",'INR Normalised'!F38,'Raw Data'!F38)/IF(Assumptions!$C$5="INR",INDEX('INR Normalised'!$F38:$S38,Assumptions!$C$7),INDEX('Raw Data'!$F38:$S38,Assumptions!$C$7))*100 -> 100 | G38: =IF(Assumptions!$C$5="INR",'INR Normalised'!G38,'Raw Data'!G38)/IF(Assumptions!$C$5="INR",INDEX('INR Normalised'!$F38:$S38,Assumptions!$C$7),INDEX('Raw Data'!$F38:$S38,Assumptions!$C$7))*100 -> 93.480761 | H38: =IF(Assumptions!$C$5="INR",'INR Normalised'!H38,'Raw Data'!H38)/IF(Assumptions!$C$5="INR",INDEX('INR Normalised'!$F38:$S38,Assumptions!$C$7),INDEX('Raw Data'!$F38:$S38,Assumptions!$C$7))*100 -> 91.021672 | I38: =IF(Assumptions!$C$5="INR",'INR Normalised'!I38,'Raw Data'!I38)/IF(Assumptions!$C$5="INR",INDEX('INR Normalised'!$F38:$S38,Assumptions!$C$7),INDEX('Raw Data'!$F38:$S38,Assumptions!$C$7))*100 -> 88.058381 | J38: =IF(Assumptions!$C$5="INR",'INR Normalised'!J38,'Raw Data'!J38)/IF(Assumptions!$C$5="INR",INDEX('INR Normalised'!$F38:$S38,Assumptions!$C$7),INDEX('Raw Data'!$F38:$S38,Assumptions!$C$7))*100 -> 85.059708 | K38: =IF(Assumptions!$C$5="INR",'INR Normalised'!K38,'Raw Data'!K38)/IF(Assumptions!$C$5="INR",INDEX('INR Normalised'!$F38:$S38,Assumptions!$C$7),INDEX('Raw Data'!$F38:$S38,Assumptions!$C$7))*100 -> 85.183547 | L38: =IF(Assumptions!$C$5="INR",'INR Normalised'!L38,'Raw Data'!L38)/IF(Assumptions!$C$5="INR",INDEX('INR Normalised'!$F38:$S38,Assumptions!$C$7),INDEX('Raw Data'!$F38:$S38,Assumptions!$C$7))*100 -> 82.706767 | M38: =IF(Assumptions!$C$5="INR",'INR Normalised'!M38,'Raw Data'!M38)/IF(Assumptions!$C$5="INR",INDEX('INR Normalised'!$F38:$S38,Assumptions!$C$7),INDEX('Raw Data'!$F38:$S38,Assumptions!$C$7))*100 -> 81.946042 | ... S38: =IF(Assumptions!$C$5="INR",'INR Normalised'!S38,'Raw Data'!S38)/IF(Assumptions!$C$5="INR",INDEX('INR Normalised'!$F38:$S38,Assumptions!$C$7),INDEX('Raw Data'!$F38:$S38,Assumptions!$C$7))*100 -> 137.47899 | T38: =IFERROR(S38/R38-1,"") -> -0.0087378022 | U38: =IFERROR(S38/F38-1,"") -> 0.37478992
A39: ='Raw Data'!A39 -> Polybutadiene Rubber (1220) | B39: Rubber & Carbon Black | C39: =Assumptions!$C$5 -> INR | D39: =Assumptions!$C$6 -> Jul-25 | E39: 100 | F39: =IF(Assumptions!$C$5="INR",'INR Normalised'!F39,'Raw Data'!F39)/IF(Assumptions!$C$5="INR",INDEX('INR Normalised'!$F39:$S39,Assumptions!$C$7),INDEX('Raw Data'!$F39:$S39,Assumptions!$C$7))*100 -> 100 | G39: =IF(Assumptions!$C$5="INR",'INR Normalised'!G39,'Raw Data'!G39)/IF(Assumptions!$C$5="INR",INDEX('INR Normalised'!$F39:$S39,Assumptions!$C$7),INDEX('Raw Data'!$F39:$S39,Assumptions!$C$7))*100 -> 98.589587 | H39: =IF(Assumptions!$C$5="INR",'INR Normalised'!H39,'Raw Data'!H39)/IF(Assumptions!$C$5="INR",INDEX('INR Normalised'!$F39:$S39,Assumptions!$C$7),INDEX('Raw Data'!$F39:$S39,Assumptions!$C$7))*100 -> 101.97342 | I39: =IF(Assumptions!$C$5="INR",'INR Normalised'!I39,'Raw Data'!I39)/IF(Assumptions!$C$5="INR",INDEX('INR Normalised'!$F39:$S39,Assumptions!$C$7),INDEX('Raw Data'!$F39:$S39,Assumptions!$C$7))*100 -> 99.634337 | J39: =IF(Assumptions!$C$5="INR",'INR Normalised'!J39,'Raw Data'!J39)/IF(Assumptions!$C$5="INR",INDEX('INR Normalised'!$F39:$S39,Assumptions!$C$7),INDEX('Raw Data'!$F39:$S39,Assumptions!$C$7))*100 -> 98.415462 | K39: =IF(Assumptions!$C$5="INR",'INR Normalised'!K39,'Raw Data'!K39)/IF(Assumptions!$C$5="INR",INDEX('INR Normalised'!$F39:$S39,Assumptions!$C$7),INDEX('Raw Data'!$F39:$S39,Assumptions!$C$7))*100 -> 98.003366 | L39: =IF(Assumptions!$C$5="INR",'INR Normalised'!L39,'Raw Data'!L39)/IF(Assumptions!$C$5="INR",INDEX('INR Normalised'!$F39:$S39,Assumptions!$C$7),INDEX('Raw Data'!$F39:$S39,Assumptions!$C$7))*100 -> 89.12299 | M39: =IF(Assumptions!$C$5="INR",'INR Normalised'!M39,'Raw Data'!M39)/IF(Assumptions!$C$5="INR",INDEX('INR Normalised'!$F39:$S39,Assumptions!$C$7),INDEX('Raw Data'!$F39:$S39,Assumptions!$C$7))*100 -> 87.613907 | ... S39: =IF(Assumptions!$C$5="INR",'INR Normalised'!S39,'Raw Data'!S39)/IF(Assumptions!$C$5="INR",INDEX('INR Normalised'!$F39:$S39,Assumptions!$C$7),INDEX('Raw Data'!$F39:$S39,Assumptions!$C$7))*100 -> 157.06657 | T39: =IFERROR(S39/R39-1,"") -> -0.007263656 | U39: =IFERROR(S39/F39-1,"") -> 0.57066574
A40: ADVANCED CHEMISTRIES (BATTERY)
A41: ='Raw Data'!A41 -> Lithium Carbonate (99.5% batt grade) | B41: Advanced Chemistries (Battery) | C41: =Assumptions!$C$5 -> INR | D41: =Assumptions!$C$6 -> Jul-25 | E41: 100 | F41: =IF(Assumptions!$C$5="INR",'INR Normalised'!F41,'Raw Data'!F41)/IF(Assumptions!$C$5="INR",INDEX('INR Normalised'!$F41:$S41,Assumptions!$C$7),INDEX('Raw Data'!$F41:$S41,Assumptions!$C$7))*100 -> 100 | G41: =IF(Assumptions!$C$5="INR",'INR Normalised'!G41,'Raw Data'!G41)/IF(Assumptions!$C$5="INR",INDEX('INR Normalised'!$F41:$S41,Assumptions!$C$7),INDEX('Raw Data'!$F41:$S41,Assumptions!$C$7))*100 -> 113.37328 | H41: =IF(Assumptions!$C$5="INR",'INR Normalised'!H41,'Raw Data'!H41)/IF(Assumptions!$C$5="INR",INDEX('INR Normalised'!$F41:$S41,Assumptions!$C$7),INDEX('Raw Data'!$F41:$S41,Assumptions!$C$7))*100 -> 114.33799 | I41: =IF(Assumptions!$C$5="INR",'INR Normalised'!I41,'Raw Data'!I41)/IF(Assumptions!$C$5="INR",INDEX('INR Normalised'!$F41:$S41,Assumptions!$C$7),INDEX('Raw Data'!$F41:$S41,Assumptions!$C$7))*100 -> 115.32085 | J41: =IF(Assumptions!$C$5="INR",'INR Normalised'!J41,'Raw Data'!J41)/IF(Assumptions!$C$5="INR",INDEX('INR Normalised'!$F41:$S41,Assumptions!$C$7),INDEX('Raw Data'!$F41:$S41,Assumptions!$C$7))*100 -> 125.93311 | K41: =IF(Assumptions!$C$5="INR",'INR Normalised'!K41,'Raw Data'!K41)/IF(Assumptions!$C$5="INR",INDEX('INR Normalised'!$F41:$S41,Assumptions!$C$7),INDEX('Raw Data'!$F41:$S41,Assumptions!$C$7))*100 -> 143.03233 | L41: =IF(Assumptions!$C$5="INR",'INR Normalised'!L41,'Raw Data'!L41)/IF(Assumptions!$C$5="INR",INDEX('INR Normalised'!$F41:$S41,Assumptions!$C$7),INDEX('Raw Data'!$F41:$S41,Assumptions!$C$7))*100 -> 219.44714 | M41: =IF(Assumptions!$C$5="INR",'INR Normalised'!M41,'Raw Data'!M41)/IF(Assumptions!$C$5="INR",INDEX('INR Normalised'!$F41:$S41,Assumptions!$C$7),INDEX('Raw Data'!$F41:$S41,Assumptions!$C$7))*100 -> 230.54436 | ... S41: =IF(Assumptions!$C$5="INR",'INR Normalised'!S41,'Raw Data'!S41)/IF(Assumptions!$C$5="INR",INDEX('INR Normalised'!$F41:$S41,Assumptions!$C$7),INDEX('Raw Data'!$F41:$S41,Assumptions!$C$7))*100 -> 254.20817 | T41: =IFERROR(S41/R41-1,"") -> -0.015460086 | U41: =IFERROR(S41/F41-1,"") -> 1.5420817
A42: ='Raw Data'!A42 -> Lithium Hydroxide (56.5% batt grade) | B42: Advanced Chemistries (Battery) | C42: =Assumptions!$C$5 -> INR | D42: =Assumptions!$C$6 -> Jul-25 | E42: 100 | F42: =IF(Assumptions!$C$5="INR",'INR Normalised'!F42,'Raw Data'!F42)/IF(Assumptions!$C$5="INR",INDEX('INR Normalised'!$F42:$S42,Assumptions!$C$7),INDEX('Raw Data'!$F42:$S42,Assumptions!$C$7))*100 -> 100 | G42: =IF(Assumptions!$C$5="INR",'INR Normalised'!G42,'Raw Data'!G42)/IF(Assumptions!$C$5="INR",INDEX('INR Normalised'!$F42:$S42,Assumptions!$C$7),INDEX('Raw Data'!$F42:$S42,Assumptions!$C$7))*100 -> 107.41473 | H42: =IF(Assumptions!$C$5="INR",'INR Normalised'!H42,'Raw Data'!H42)/IF(Assumptions!$C$5="INR",INDEX('INR Normalised'!$F42:$S42,Assumptions!$C$7),INDEX('Raw Data'!$F42:$S42,Assumptions!$C$7))*100 -> 117.55627 | I42: =IF(Assumptions!$C$5="INR",'INR Normalised'!I42,'Raw Data'!I42)/IF(Assumptions!$C$5="INR",INDEX('INR Normalised'!$F42:$S42,Assumptions!$C$7),INDEX('Raw Data'!$F42:$S42,Assumptions!$C$7))*100 -> 120.5991 | J42: =IF(Assumptions!$C$5="INR",'INR Normalised'!J42,'Raw Data'!J42)/IF(Assumptions!$C$5="INR",INDEX('INR Normalised'!$F42:$S42,Assumptions!$C$7),INDEX('Raw Data'!$F42:$S42,Assumptions!$C$7))*100 -> 129.95576 | K42: =IF(Assumptions!$C$5="INR",'INR Normalised'!K42,'Raw Data'!K42)/IF(Assumptions!$C$5="INR",INDEX('INR Normalised'!$F42:$S42,Assumptions!$C$7),INDEX('Raw Data'!$F42:$S42,Assumptions!$C$7))*100 -> 139.04503 | L42: =IF(Assumptions!$C$5="INR",'INR Normalised'!L42,'Raw Data'!L42)/IF(Assumptions!$C$5="INR",INDEX('INR Normalised'!$F42:$S42,Assumptions!$C$7),INDEX('Raw Data'!$F42:$S42,Assumptions!$C$7))*100 -> 217.43348 | M42: =IF(Assumptions!$C$5="INR",'INR Normalised'!M42,'Raw Data'!M42)/IF(Assumptions!$C$5="INR",INDEX('INR Normalised'!$F42:$S42,Assumptions!$C$7),INDEX('Raw Data'!$F42:$S42,Assumptions!$C$7))*100 -> 228.6837 | ... S42: =IF(Assumptions!$C$5="INR",'INR Normalised'!S42,'Raw Data'!S42)/IF(Assumptions!$C$5="INR",INDEX('INR Normalised'!$F42:$S42,Assumptions!$C$7),INDEX('Raw Data'!$F42:$S42,Assumptions!$C$7))*100 -> 244.21641 | T42: =IFERROR(S42/R42-1,"") -> -0.0098623218 | U42: =IFERROR(S42/F42-1,"") -> 1.4421641
A43: ='Raw Data'!A43 -> Cobalt Oxide (Co>=72%) | B43: Advanced Chemistries (Battery) | C43: =Assumptions!$C$5 -> INR | D43: =Assumptions!$C$6 -> Jul-25 | E43: 100 | F43: =IF(Assumptions!$C$5="INR",'INR Normalised'!F43,'Raw Data'!F43)/IF(Assumptions!$C$5="INR",INDEX('INR Normalised'!$F43:$S43,Assumptions!$C$7),INDEX('Raw Data'!$F43:$S43,Assumptions!$C$7))*100 -> 100 | G43: =IF(Assumptions!$C$5="INR",'INR Normalised'!G43,'Raw Data'!G43)/IF(Assumptions!$C$5="INR",INDEX('INR Normalised'!$F43:$S43,Assumptions!$C$7),INDEX('Raw Data'!$F43:$S43,Assumptions!$C$7))*100 -> 105.34361 | H43: =IF(Assumptions!$C$5="INR",'INR Normalised'!H43,'Raw Data'!H43)/IF(Assumptions!$C$5="INR",INDEX('INR Normalised'!$F43:$S43,Assumptions!$C$7),INDEX('Raw Data'!$F43:$S43,Assumptions!$C$7))*100 -> 110.56783 | I43: =IF(Assumptions!$C$5="INR",'INR Normalised'!I43,'Raw Data'!I43)/IF(Assumptions!$C$5="INR",INDEX('INR Normalised'!$F43:$S43,Assumptions!$C$7),INDEX('Raw Data'!$F43:$S43,Assumptions!$C$7))*100 -> 152.03522 | J43: =IF(Assumptions!$C$5="INR",'INR Normalised'!J43,'Raw Data'!J43)/IF(Assumptions!$C$5="INR",INDEX('INR Normalised'!$F43:$S43,Assumptions!$C$7),INDEX('Raw Data'!$F43:$S43,Assumptions!$C$7))*100 -> 164.3464 | K43: =IF(Assumptions!$C$5="INR",'INR Normalised'!K43,'Raw Data'!K43)/IF(Assumptions!$C$5="INR",INDEX('INR Normalised'!$F43:$S43,Assumptions!$C$7),INDEX('Raw Data'!$F43:$S43,Assumptions!$C$7))*100 -> 177.37912 | L43: =IF(Assumptions!$C$5="INR",'INR Normalised'!L43,'Raw Data'!L43)/IF(Assumptions!$C$5="INR",INDEX('INR Normalised'!$F43:$S43,Assumptions!$C$7),INDEX('Raw Data'!$F43:$S43,Assumptions!$C$7))*100 -> 193.59085 | M43: =IF(Assumptions!$C$5="INR",'INR Normalised'!M43,'Raw Data'!M43)/IF(Assumptions!$C$5="INR",INDEX('INR Normalised'!$F43:$S43,Assumptions!$C$7),INDEX('Raw Data'!$F43:$S43,Assumptions!$C$7))*100 -> 196.57025 | ... S43: =IF(Assumptions!$C$5="INR",'INR Normalised'!S43,'Raw Data'!S43)/IF(Assumptions!$C$5="INR",INDEX('INR Normalised'!$F43:$S43,Assumptions!$C$7),INDEX('Raw Data'!$F43:$S43,Assumptions!$C$7))*100 -> 168.23531 | T43: =IFERROR(S43/R43-1,"") -> -0.077049631 | U43: =IFERROR(S43/F43-1,"") -> 0.68235307
A44: ='Raw Data'!A44 -> Cobalt Metal (Co>=99.8%) | B44: Advanced Chemistries (Battery) | C44: =Assumptions!$C$5 -> INR | D44: =Assumptions!$C$6 -> Jul-25 | E44: 100 | F44: =IF(Assumptions!$C$5="INR",'INR Normalised'!F44,'Raw Data'!F44)/IF(Assumptions!$C$5="INR",INDEX('INR Normalised'!$F44:$S44,Assumptions!$C$7),INDEX('Raw Data'!$F44:$S44,Assumptions!$C$7))*100 -> 100 | G44: =IF(Assumptions!$C$5="INR",'INR Normalised'!G44,'Raw Data'!G44)/IF(Assumptions!$C$5="INR",INDEX('INR Normalised'!$F44:$S44,Assumptions!$C$7),INDEX('Raw Data'!$F44:$S44,Assumptions!$C$7))*100 -> 107.83657 | H44: =IF(Assumptions!$C$5="INR",'INR Normalised'!H44,'Raw Data'!H44)/IF(Assumptions!$C$5="INR",INDEX('INR Normalised'!$F44:$S44,Assumptions!$C$7),INDEX('Raw Data'!$F44:$S44,Assumptions!$C$7))*100 -> 116.03498 | I44: =IF(Assumptions!$C$5="INR",'INR Normalised'!I44,'Raw Data'!I44)/IF(Assumptions!$C$5="INR",INDEX('INR Normalised'!$F44:$S44,Assumptions!$C$7),INDEX('Raw Data'!$F44:$S44,Assumptions!$C$7))*100 -> 159.97961 | J44: =IF(Assumptions!$C$5="INR",'INR Normalised'!J44,'Raw Data'!J44)/IF(Assumptions!$C$5="INR",INDEX('INR Normalised'!$F44:$S44,Assumptions!$C$7),INDEX('Raw Data'!$F44:$S44,Assumptions!$C$7))*100 -> 164.45563 | K44: =IF(Assumptions!$C$5="INR",'INR Normalised'!K44,'Raw Data'!K44)/IF(Assumptions!$C$5="INR",INDEX('INR Normalised'!$F44:$S44,Assumptions!$C$7),INDEX('Raw Data'!$F44:$S44,Assumptions!$C$7))*100 -> 178.10358 | L44: =IF(Assumptions!$C$5="INR",'INR Normalised'!L44,'Raw Data'!L44)/IF(Assumptions!$C$5="INR",INDEX('INR Normalised'!$F44:$S44,Assumptions!$C$7),INDEX('Raw Data'!$F44:$S44,Assumptions!$C$7))*100 -> 195.75308 | M44: =IF(Assumptions!$C$5="INR",'INR Normalised'!M44,'Raw Data'!M44)/IF(Assumptions!$C$5="INR",INDEX('INR Normalised'!$F44:$S44,Assumptions!$C$7),INDEX('Raw Data'!$F44:$S44,Assumptions!$C$7))*100 -> 187.08861 | ... S44: =IF(Assumptions!$C$5="INR",'INR Normalised'!S44,'Raw Data'!S44)/IF(Assumptions!$C$5="INR",INDEX('INR Normalised'!$F44:$S44,Assumptions!$C$7),INDEX('Raw Data'!$F44:$S44,Assumptions!$C$7))*100 -> 152.05736 | T44: =IFERROR(S44/R44-1,"") -> -0.12348355 | U44: =IFERROR(S44/F44-1,"") -> 0.52057356
A45: RARE EARTH / MAGNETS
A46: ='Raw Data'!A46 -> NdFeB Magnet (GD - scrap) | B46: Rare Earth / Magnets | C46: =Assumptions!$C$5 -> INR | D46: =Assumptions!$C$6 -> Jul-25 | E46: 100 | F46: =IF(Assumptions!$C$5="INR",'INR Normalised'!F46,'Raw Data'!F46)/IF(Assumptions!$C$5="INR",INDEX('INR Normalised'!$F46:$S46,Assumptions!$C$7),INDEX('Raw Data'!$F46:$S46,Assumptions!$C$7))*100 -> 100 | G46: =IF(Assumptions!$C$5="INR",'INR Normalised'!G46,'Raw Data'!G46)/IF(Assumptions!$C$5="INR",INDEX('INR Normalised'!$F46:$S46,Assumptions!$C$7),INDEX('Raw Data'!$F46:$S46,Assumptions!$C$7))*100 -> 101.5662 | H46: =IF(Assumptions!$C$5="INR",'INR Normalised'!H46,'Raw Data'!H46)/IF(Assumptions!$C$5="INR",INDEX('INR Normalised'!$F46:$S46,Assumptions!$C$7),INDEX('Raw Data'!$F46:$S46,Assumptions!$C$7))*100 -> 103.18361 | I46: =IF(Assumptions!$C$5="INR",'INR Normalised'!I46,'Raw Data'!I46)/IF(Assumptions!$C$5="INR",INDEX('INR Normalised'!$F46:$S46,Assumptions!$C$7),INDEX('Raw Data'!$F46:$S46,Assumptions!$C$7))*100 -> 103.38347 | J46: =IF(Assumptions!$C$5="INR",'INR Normalised'!J46,'Raw Data'!J46)/IF(Assumptions!$C$5="INR",INDEX('INR Normalised'!$F46:$S46,Assumptions!$C$7),INDEX('Raw Data'!$F46:$S46,Assumptions!$C$7))*100 -> 104.05138 | K46: =IF(Assumptions!$C$5="INR",'INR Normalised'!K46,'Raw Data'!K46)/IF(Assumptions!$C$5="INR",INDEX('INR Normalised'!$F46:$S46,Assumptions!$C$7),INDEX('Raw Data'!$F46:$S46,Assumptions!$C$7))*100 -> 106.38619 | L46: =IF(Assumptions!$C$5="INR",'INR Normalised'!L46,'Raw Data'!L46)/IF(Assumptions!$C$5="INR",INDEX('INR Normalised'!$F46:$S46,Assumptions!$C$7),INDEX('Raw Data'!$F46:$S46,Assumptions!$C$7))*100 -> 98.030357 | M46: =IF(Assumptions!$C$5="INR",'INR Normalised'!M46,'Raw Data'!M46)/IF(Assumptions!$C$5="INR",INDEX('INR Normalised'!$F46:$S46,Assumptions!$C$7),INDEX('Raw Data'!$F46:$S46,Assumptions!$C$7))*100 -> 98.868619 | ... S46: =IF(Assumptions!$C$5="INR",'INR Normalised'!S46,'Raw Data'!S46)/IF(Assumptions!$C$5="INR",INDEX('INR Normalised'!$F46:$S46,Assumptions!$C$7),INDEX('Raw Data'!$F46:$S46,Assumptions!$C$7))*100 -> 106.61195 | T46: =IFERROR(S46/R46-1,"") -> 0.0027363789 | U46: =IFERROR(S46/F46-1,"") -> 0.066119531
A47: ENERGY & FUELS
A48: ='Raw Data'!A48 -> Brent Crude (Europe spot FOB) | B48: Energy & Fuels | C48: =Assumptions!$C$5 -> INR | D48: =Assumptions!$C$6 -> Jul-25 | E48: 100 | F48: =IF(Assumptions!$C$5="INR",'INR Normalised'!F48,'Raw Data'!F48)/IF(Assumptions!$C$5="INR",INDEX('INR Normalised'!$F48:$S48,Assumptions!$C$7),INDEX('Raw Data'!$F48:$S48,Assumptions!$C$7))*100 -> 100 | G48: =IF(Assumptions!$C$5="INR",'INR Normalised'!G48,'Raw Data'!G48)/IF(Assumptions!$C$5="INR",INDEX('INR Normalised'!$F48:$S48,Assumptions!$C$7),INDEX('Raw Data'!$F48:$S48,Assumptions!$C$7))*100 -> 97.621757 | H48: =IF(Assumptions!$C$5="INR",'INR Normalised'!H48,'Raw Data'!H48)/IF(Assumptions!$C$5="INR",INDEX('INR Normalised'!$F48:$S48,Assumptions!$C$7),INDEX('Raw Data'!$F48:$S48,Assumptions!$C$7))*100 -> 98.582993 | I48: =IF(Assumptions!$C$5="INR",'INR Normalised'!I48,'Raw Data'!I48)/IF(Assumptions!$C$5="INR",INDEX('INR Normalised'!$F48:$S48,Assumptions!$C$7),INDEX('Raw Data'!$F48:$S48,Assumptions!$C$7))*100 -> 93.625597 | J48: =IF(Assumptions!$C$5="INR",'INR Normalised'!J48,'Raw Data'!J48)/IF(Assumptions!$C$5="INR",INDEX('INR Normalised'!$F48:$S48,Assumptions!$C$7),INDEX('Raw Data'!$F48:$S48,Assumptions!$C$7))*100 -> 94.180144 | K48: =IF(Assumptions!$C$5="INR",'INR Normalised'!K48,'Raw Data'!K48)/IF(Assumptions!$C$5="INR",INDEX('INR Normalised'!$F48:$S48,Assumptions!$C$7),INDEX('Raw Data'!$F48:$S48,Assumptions!$C$7))*100 -> 92.486354 | L48: =IF(Assumptions!$C$5="INR",'INR Normalised'!L48,'Raw Data'!L48)/IF(Assumptions!$C$5="INR",INDEX('INR Normalised'!$F48:$S48,Assumptions!$C$7),INDEX('Raw Data'!$F48:$S48,Assumptions!$C$7))*100 -> 99.272957 | M48: =IF(Assumptions!$C$5="INR",'INR Normalised'!M48,'Raw Data'!M48)/IF(Assumptions!$C$5="INR",INDEX('INR Normalised'!$F48:$S48,Assumptions!$C$7),INDEX('Raw Data'!$F48:$S48,Assumptions!$C$7))*100 -> 105.64443 | ... S48: =IF(Assumptions!$C$5="INR",'INR Normalised'!S48,'Raw Data'!S48)/IF(Assumptions!$C$5="INR",INDEX('INR Normalised'!$F48:$S48,Assumptions!$C$7),INDEX('Raw Data'!$F48:$S48,Assumptions!$C$7))*100 -> 142.76315 | T48: =IFERROR(S48/R48-1,"") -> 0.083894297 | U48: =IFERROR(S48/F48-1,"") -> 0.42763147
A49: ='Raw Data'!A49 -> CNG - Delhi (IGL) | B49: Energy & Fuels | C49: =Assumptions!$C$5 -> INR | D49: =Assumptions!$C$6 -> Jul-25 | E49: 100 | F49: =IF(Assumptions!$C$5="INR",'INR Normalised'!F49,'Raw Data'!F49)/IF(Assumptions!$C$5="INR",INDEX('INR Normalised'!$F49:$S49,Assumptions!$C$7),INDEX('Raw Data'!$F49:$S49,Assumptions!$C$7))*100 -> 100 | G49: =IF(Assumptions!$C$5="INR",'INR Normalised'!G49,'Raw Data'!G49)/IF(Assumptions!$C$5="INR",INDEX('INR Normalised'!$F49:$S49,Assumptions!$C$7),INDEX('Raw Data'!$F49:$S49,Assumptions!$C$7))*100 -> 100 | H49: =IF(Assumptions!$C$5="INR",'INR Normalised'!H49,'Raw Data'!H49)/IF(Assumptions!$C$5="INR",INDEX('INR Normalised'!$F49:$S49,Assumptions!$C$7),INDEX('Raw Data'!$F49:$S49,Assumptions!$C$7))*100 -> 100 | I49: =IF(Assumptions!$C$5="INR",'INR Normalised'!I49,'Raw Data'!I49)/IF(Assumptions!$C$5="INR",INDEX('INR Normalised'!$F49:$S49,Assumptions!$C$7),INDEX('Raw Data'!$F49:$S49,Assumptions!$C$7))*100 -> 100 | J49: =IF(Assumptions!$C$5="INR",'INR Normalised'!J49,'Raw Data'!J49)/IF(Assumptions!$C$5="INR",INDEX('INR Normalised'!$F49:$S49,Assumptions!$C$7),INDEX('Raw Data'!$F49:$S49,Assumptions!$C$7))*100 -> 100 | K49: =IF(Assumptions!$C$5="INR",'INR Normalised'!K49,'Raw Data'!K49)/IF(Assumptions!$C$5="INR",INDEX('INR Normalised'!$F49:$S49,Assumptions!$C$7),INDEX('Raw Data'!$F49:$S49,Assumptions!$C$7))*100 -> 100 | L49: =IF(Assumptions!$C$5="INR",'INR Normalised'!L49,'Raw Data'!L49)/IF(Assumptions!$C$5="INR",INDEX('INR Normalised'!$F49:$S49,Assumptions!$C$7),INDEX('Raw Data'!$F49:$S49,Assumptions!$C$7))*100 -> 100 | M49: =IF(Assumptions!$C$5="INR",'INR Normalised'!M49,'Raw Data'!M49)/IF(Assumptions!$C$5="INR",INDEX('INR Normalised'!$F49:$S49,Assumptions!$C$7),INDEX('Raw Data'!$F49:$S49,Assumptions!$C$7))*100 -> 100 | ... S49: =IF(Assumptions!$C$5="INR",'INR Normalised'!S49,'Raw Data'!S49)/IF(Assumptions!$C$5="INR",INDEX('INR Normalised'!$F49:$S49,Assumptions!$C$7),INDEX('Raw Data'!$F49:$S49,Assumptions!$C$7))*100 -> 108.30091 | T49: =IFERROR(S49/R49-1,"") -> 0.0048134777 | U49: =IFERROR(S49/F49-1,"") -> 0.083009079
A50: ='Raw Data'!A50 -> CNG - Mumbai (MGL) | B50: Energy & Fuels | C50: =Assumptions!$C$5 -> INR | D50: =Assumptions!$C$6 -> Jul-25 | E50: 100 | F50: =IF(Assumptions!$C$5="INR",'INR Normalised'!F50,'Raw Data'!F50)/IF(Assumptions!$C$5="INR",INDEX('INR Normalised'!$F50:$S50,Assumptions!$C$7),INDEX('Raw Data'!$F50:$S50,Assumptions!$C$7))*100 -> 100 | G50: =IF(Assumptions!$C$5="INR",'INR Normalised'!G50,'Raw Data'!G50)/IF(Assumptions!$C$5="INR",INDEX('INR Normalised'!$F50:$S50,Assumptions!$C$7),INDEX('Raw Data'!$F50:$S50,Assumptions!$C$7))*100 -> 100 | H50: =IF(Assumptions!$C$5="INR",'INR Normalised'!H50,'Raw Data'!H50)/IF(Assumptions!$C$5="INR",INDEX('INR Normalised'!$F50:$S50,Assumptions!$C$7),INDEX('Raw Data'!$F50:$S50,Assumptions!$C$7))*100 -> 100.625 | I50: =IF(Assumptions!$C$5="INR",'INR Normalised'!I50,'Raw Data'!I50)/IF(Assumptions!$C$5="INR",INDEX('INR Normalised'!$F50:$S50,Assumptions!$C$7),INDEX('Raw Data'!$F50:$S50,Assumptions!$C$7))*100 -> 100.625 | J50: =IF(Assumptions!$C$5="INR",'INR Normalised'!J50,'Raw Data'!J50)/IF(Assumptions!$C$5="INR",INDEX('INR Normalised'!$F50:$S50,Assumptions!$C$7),INDEX('Raw Data'!$F50:$S50,Assumptions!$C$7))*100 -> 100.625 | K50: =IF(Assumptions!$C$5="INR",'INR Normalised'!K50,'Raw Data'!K50)/IF(Assumptions!$C$5="INR",INDEX('INR Normalised'!$F50:$S50,Assumptions!$C$7),INDEX('Raw Data'!$F50:$S50,Assumptions!$C$7))*100 -> 100.625 | L50: =IF(Assumptions!$C$5="INR",'INR Normalised'!L50,'Raw Data'!L50)/IF(Assumptions!$C$5="INR",INDEX('INR Normalised'!$F50:$S50,Assumptions!$C$7),INDEX('Raw Data'!$F50:$S50,Assumptions!$C$7))*100 -> 100.625 | M50: =IF(Assumptions!$C$5="INR",'INR Normalised'!M50,'Raw Data'!M50)/IF(Assumptions!$C$5="INR",INDEX('INR Normalised'!$F50:$S50,Assumptions!$C$7),INDEX('Raw Data'!$F50:$S50,Assumptions!$C$7))*100 -> 101.25 | ... S50: =IF(Assumptions!$C$5="INR",'INR Normalised'!S50,'Raw Data'!S50)/IF(Assumptions!$C$5="INR",INDEX('INR Normalised'!$F50:$S50,Assumptions!$C$7),INDEX('Raw Data'!$F50:$S50,Assumptions!$C$7))*100 -> 107.5 | T50: =IFERROR(S50/R50-1,"") -> 0 | U50: =IFERROR(S50/F50-1,"") -> 0.075
A51: ='Raw Data'!A51 -> Petrol - Delhi | B51: Energy & Fuels | C51: =Assumptions!$C$5 -> INR | D51: =Assumptions!$C$6 -> Jul-25 | E51: 100 | F51: =IF(Assumptions!$C$5="INR",'INR Normalised'!F51,'Raw Data'!F51)/IF(Assumptions!$C$5="INR",INDEX('INR Normalised'!$F51:$S51,Assumptions!$C$7),INDEX('Raw Data'!$F51:$S51,Assumptions!$C$7))*100 -> 100 | G51: =IF(Assumptions!$C$5="INR",'INR Normalised'!G51,'Raw Data'!G51)/IF(Assumptions!$C$5="INR",INDEX('INR Normalised'!$F51:$S51,Assumptions!$C$7),INDEX('Raw Data'!$F51:$S51,Assumptions!$C$7))*100 -> 100 | H51: =IF(Assumptions!$C$5="INR",'INR Normalised'!H51,'Raw Data'!H51)/IF(Assumptions!$C$5="INR",INDEX('INR Normalised'!$F51:$S51,Assumptions!$C$7),INDEX('Raw Data'!$F51:$S51,Assumptions!$C$7))*100 -> 100 | I51: =IF(Assumptions!$C$5="INR",'INR Normalised'!I51,'Raw Data'!I51)/IF(Assumptions!$C$5="INR",INDEX('INR Normalised'!$F51:$S51,Assumptions!$C$7),INDEX('Raw Data'!$F51:$S51,Assumptions!$C$7))*100 -> 100 | J51: =IF(Assumptions!$C$5="INR",'INR Normalised'!J51,'Raw Data'!J51)/IF(Assumptions!$C$5="INR",INDEX('INR Normalised'!$F51:$S51,Assumptions!$C$7),INDEX('Raw Data'!$F51:$S51,Assumptions!$C$7))*100 -> 100 | K51: =IF(Assumptions!$C$5="INR",'INR Normalised'!K51,'Raw Data'!K51)/IF(Assumptions!$C$5="INR",INDEX('INR Normalised'!$F51:$S51,Assumptions!$C$7),INDEX('Raw Data'!$F51:$S51,Assumptions!$C$7))*100 -> 100 | L51: =IF(Assumptions!$C$5="INR",'INR Normalised'!L51,'Raw Data'!L51)/IF(Assumptions!$C$5="INR",INDEX('INR Normalised'!$F51:$S51,Assumptions!$C$7),INDEX('Raw Data'!$F51:$S51,Assumptions!$C$7))*100 -> 100 | M51: =IF(Assumptions!$C$5="INR",'INR Normalised'!M51,'Raw Data'!M51)/IF(Assumptions!$C$5="INR",INDEX('INR Normalised'!$F51:$S51,Assumptions!$C$7),INDEX('Raw Data'!$F51:$S51,Assumptions!$C$7))*100 -> 100 | ... S51: =IF(Assumptions!$C$5="INR",'INR Normalised'!S51,'Raw Data'!S51)/IF(Assumptions!$C$5="INR",INDEX('INR Normalised'!$F51:$S51,Assumptions!$C$7),INDEX('Raw Data'!$F51:$S51,Assumptions!$C$7))*100 -> 107.71016 | T51: =IFERROR(S51/R51-1,"") -> 0 | U51: =IFERROR(S51/F51-1,"") -> 0.077101572
A52: ='Raw Data'!A52 -> Diesel - Delhi | B52: Energy & Fuels | C52: =Assumptions!$C$5 -> INR | D52: =Assumptions!$C$6 -> Jul-25 | E52: 100 | F52: =IF(Assumptions!$C$5="INR",'INR Normalised'!F52,'Raw Data'!F52)/IF(Assumptions!$C$5="INR",INDEX('INR Normalised'!$F52:$S52,Assumptions!$C$7),INDEX('Raw Data'!$F52:$S52,Assumptions!$C$7))*100 -> 100 | G52: =IF(Assumptions!$C$5="INR",'INR Normalised'!G52,'Raw Data'!G52)/IF(Assumptions!$C$5="INR",INDEX('INR Normalised'!$F52:$S52,Assumptions!$C$7),INDEX('Raw Data'!$F52:$S52,Assumptions!$C$7))*100 -> 100 | H52: =IF(Assumptions!$C$5="INR",'INR Normalised'!H52,'Raw Data'!H52)/IF(Assumptions!$C$5="INR",INDEX('INR Normalised'!$F52:$S52,Assumptions!$C$7),INDEX('Raw Data'!$F52:$S52,Assumptions!$C$7))*100 -> 100 | I52: =IF(Assumptions!$C$5="INR",'INR Normalised'!I52,'Raw Data'!I52)/IF(Assumptions!$C$5="INR",INDEX('INR Normalised'!$F52:$S52,Assumptions!$C$7),INDEX('Raw Data'!$F52:$S52,Assumptions!$C$7))*100 -> 100 | J52: =IF(Assumptions!$C$5="INR",'INR Normalised'!J52,'Raw Data'!J52)/IF(Assumptions!$C$5="INR",INDEX('INR Normalised'!$F52:$S52,Assumptions!$C$7),INDEX('Raw Data'!$F52:$S52,Assumptions!$C$7))*100 -> 100 | K52: =IF(Assumptions!$C$5="INR",'INR Normalised'!K52,'Raw Data'!K52)/IF(Assumptions!$C$5="INR",INDEX('INR Normalised'!$F52:$S52,Assumptions!$C$7),INDEX('Raw Data'!$F52:$S52,Assumptions!$C$7))*100 -> 100 | L52: =IF(Assumptions!$C$5="INR",'INR Normalised'!L52,'Raw Data'!L52)/IF(Assumptions!$C$5="INR",INDEX('INR Normalised'!$F52:$S52,Assumptions!$C$7),INDEX('Raw Data'!$F52:$S52,Assumptions!$C$7))*100 -> 100 | M52: =IF(Assumptions!$C$5="INR",'INR Normalised'!M52,'Raw Data'!M52)/IF(Assumptions!$C$5="INR",INDEX('INR Normalised'!$F52:$S52,Assumptions!$C$7),INDEX('Raw Data'!$F52:$S52,Assumptions!$C$7))*100 -> 100 | ... S52: =IF(Assumptions!$C$5="INR",'INR Normalised'!S52,'Raw Data'!S52)/IF(Assumptions!$C$5="INR",INDEX('INR Normalised'!$F52:$S52,Assumptions!$C$7),INDEX('Raw Data'!$F52:$S52,Assumptions!$C$7))*100 -> 108.53951 | T52: =IFERROR(S52/R52-1,"") -> 0 | U52: =IFERROR(S52/F52-1,"") -> 0.085395052
A53: ='Raw Data'!A53 -> Petrol - Mumbai | B53: Energy & Fuels | C53: =Assumptions!$C$5 -> INR | D53: =Assumptions!$C$6 -> Jul-25 | E53: 100 | F53: =IF(Assumptions!$C$5="INR",'INR Normalised'!F53,'Raw Data'!F53)/IF(Assumptions!$C$5="INR",INDEX('INR Normalised'!$F53:$S53,Assumptions!$C$7),INDEX('Raw Data'!$F53:$S53,Assumptions!$C$7))*100 -> 100 | G53: =IF(Assumptions!$C$5="INR",'INR Normalised'!G53,'Raw Data'!G53)/IF(Assumptions!$C$5="INR",INDEX('INR Normalised'!$F53:$S53,Assumptions!$C$7),INDEX('Raw Data'!$F53:$S53,Assumptions!$C$7))*100 -> 100 | H53: =IF(Assumptions!$C$5="INR",'INR Normalised'!H53,'Raw Data'!H53)/IF(Assumptions!$C$5="INR",INDEX('INR Normalised'!$F53:$S53,Assumptions!$C$7),INDEX('Raw Data'!$F53:$S53,Assumptions!$C$7))*100 -> 100 | I53: =IF(Assumptions!$C$5="INR",'INR Normalised'!I53,'Raw Data'!I53)/IF(Assumptions!$C$5="INR",INDEX('INR Normalised'!$F53:$S53,Assumptions!$C$7),INDEX('Raw Data'!$F53:$S53,Assumptions!$C$7))*100 -> 100 | J53: =IF(Assumptions!$C$5="INR",'INR Normalised'!J53,'Raw Data'!J53)/IF(Assumptions!$C$5="INR",INDEX('INR Normalised'!$F53:$S53,Assumptions!$C$7),INDEX('Raw Data'!$F53:$S53,Assumptions!$C$7))*100 -> 100 | K53: =IF(Assumptions!$C$5="INR",'INR Normalised'!K53,'Raw Data'!K53)/IF(Assumptions!$C$5="INR",INDEX('INR Normalised'!$F53:$S53,Assumptions!$C$7),INDEX('Raw Data'!$F53:$S53,Assumptions!$C$7))*100 -> 100 | L53: =IF(Assumptions!$C$5="INR",'INR Normalised'!L53,'Raw Data'!L53)/IF(Assumptions!$C$5="INR",INDEX('INR Normalised'!$F53:$S53,Assumptions!$C$7),INDEX('Raw Data'!$F53:$S53,Assumptions!$C$7))*100 -> 100 | M53: =IF(Assumptions!$C$5="INR",'INR Normalised'!M53,'Raw Data'!M53)/IF(Assumptions!$C$5="INR",INDEX('INR Normalised'!$F53:$S53,Assumptions!$C$7),INDEX('Raw Data'!$F53:$S53,Assumptions!$C$7))*100 -> 100 | ... S53: =IF(Assumptions!$C$5="INR",'INR Normalised'!S53,'Raw Data'!S53)/IF(Assumptions!$C$5="INR",INDEX('INR Normalised'!$F53:$S53,Assumptions!$C$7),INDEX('Raw Data'!$F53:$S53,Assumptions!$C$7))*100 -> 107.45966 | T53: =IFERROR(S53/R53-1,"") -> 0 | U53: =IFERROR(S53/F53-1,"") -> 0.074596579
A54: ='Raw Data'!A54 -> Diesel - Mumbai | B54: Energy & Fuels | C54: =Assumptions!$C$5 -> INR | D54: =Assumptions!$C$6 -> Jul-25 | E54: 100 | F54: =IF(Assumptions!$C$5="INR",'INR Normalised'!F54,'Raw Data'!F54)/IF(Assumptions!$C$5="INR",INDEX('INR Normalised'!$F54:$S54,Assumptions!$C$7),INDEX('Raw Data'!$F54:$S54,Assumptions!$C$7))*100 -> 100 | G54: =IF(Assumptions!$C$5="INR",'INR Normalised'!G54,'Raw Data'!G54)/IF(Assumptions!$C$5="INR",INDEX('INR Normalised'!$F54:$S54,Assumptions!$C$7),INDEX('Raw Data'!$F54:$S54,Assumptions!$C$7))*100 -> 100 | H54: =IF(Assumptions!$C$5="INR",'INR Normalised'!H54,'Raw Data'!H54)/IF(Assumptions!$C$5="INR",INDEX('INR Normalised'!$F54:$S54,Assumptions!$C$7),INDEX('Raw Data'!$F54:$S54,Assumptions!$C$7))*100 -> 100 | I54: =IF(Assumptions!$C$5="INR",'INR Normalised'!I54,'Raw Data'!I54)/IF(Assumptions!$C$5="INR",INDEX('INR Normalised'!$F54:$S54,Assumptions!$C$7),INDEX('Raw Data'!$F54:$S54,Assumptions!$C$7))*100 -> 100 | J54: =IF(Assumptions!$C$5="INR",'INR Normalised'!J54,'Raw Data'!J54)/IF(Assumptions!$C$5="INR",INDEX('INR Normalised'!$F54:$S54,Assumptions!$C$7),INDEX('Raw Data'!$F54:$S54,Assumptions!$C$7))*100 -> 100 | K54: =IF(Assumptions!$C$5="INR",'INR Normalised'!K54,'Raw Data'!K54)/IF(Assumptions!$C$5="INR",INDEX('INR Normalised'!$F54:$S54,Assumptions!$C$7),INDEX('Raw Data'!$F54:$S54,Assumptions!$C$7))*100 -> 100 | L54: =IF(Assumptions!$C$5="INR",'INR Normalised'!L54,'Raw Data'!L54)/IF(Assumptions!$C$5="INR",INDEX('INR Normalised'!$F54:$S54,Assumptions!$C$7),INDEX('Raw Data'!$F54:$S54,Assumptions!$C$7))*100 -> 100 | M54: =IF(Assumptions!$C$5="INR",'INR Normalised'!M54,'Raw Data'!M54)/IF(Assumptions!$C$5="INR",INDEX('INR Normalised'!$F54:$S54,Assumptions!$C$7),INDEX('Raw Data'!$F54:$S54,Assumptions!$C$7))*100 -> 100 | ... S54: =IF(Assumptions!$C$5="INR",'INR Normalised'!S54,'Raw Data'!S54)/IF(Assumptions!$C$5="INR",INDEX('INR Normalised'!$F54:$S54,Assumptions!$C$7),INDEX('Raw Data'!$F54:$S54,Assumptions!$C$7))*100 -> 108.68792 | T54: =IFERROR(S54/R54-1,"") -> 0 | U54: =IFERROR(S54/F54-1,"") -> 0.086879236
A55: ='Raw Data'!A55 -> Ethanol - Sugarcane Juice | B55: Energy & Fuels | C55: =Assumptions!$C$5 -> INR | D55: =Assumptions!$C$6 -> Jul-25 | E55: 100 | F55: =IF(Assumptions!$C$5="INR",'INR Normalised'!F55,'Raw Data'!F55)/IF(Assumptions!$C$5="INR",INDEX('INR Normalised'!$F55:$S55,Assumptions!$C$7),INDEX('Raw Data'!$F55:$S55,Assumptions!$C$7))*100 -> 100 | G55: =IF(Assumptions!$C$5="INR",'INR Normalised'!G55,'Raw Data'!G55)/IF(Assumptions!$C$5="INR",INDEX('INR Normalised'!$F55:$S55,Assumptions!$C$7),INDEX('Raw Data'!$F55:$S55,Assumptions!$C$7))*100 -> 100 | H55: =IF(Assumptions!$C$5="INR",'INR Normalised'!H55,'Raw Data'!H55)/IF(Assumptions!$C$5="INR",INDEX('INR Normalised'!$F55:$S55,Assumptions!$C$7),INDEX('Raw Data'!$F55:$S55,Assumptions!$C$7))*100 -> 100 | I55: =IF(Assumptions!$C$5="INR",'INR Normalised'!I55,'Raw Data'!I55)/IF(Assumptions!$C$5="INR",INDEX('INR Normalised'!$F55:$S55,Assumptions!$C$7),INDEX('Raw Data'!$F55:$S55,Assumptions!$C$7))*100 -> 100 | J55: =IF(Assumptions!$C$5="INR",'INR Normalised'!J55,'Raw Data'!J55)/IF(Assumptions!$C$5="INR",INDEX('INR Normalised'!$F55:$S55,Assumptions!$C$7),INDEX('Raw Data'!$F55:$S55,Assumptions!$C$7))*100 -> 100 | K55: =IF(Assumptions!$C$5="INR",'INR Normalised'!K55,'Raw Data'!K55)/IF(Assumptions!$C$5="INR",INDEX('INR Normalised'!$F55:$S55,Assumptions!$C$7),INDEX('Raw Data'!$F55:$S55,Assumptions!$C$7))*100 -> 100 | L55: =IF(Assumptions!$C$5="INR",'INR Normalised'!L55,'Raw Data'!L55)/IF(Assumptions!$C$5="INR",INDEX('INR Normalised'!$F55:$S55,Assumptions!$C$7),INDEX('Raw Data'!$F55:$S55,Assumptions!$C$7))*100 -> 100 | M55: =IF(Assumptions!$C$5="INR",'INR Normalised'!M55,'Raw Data'!M55)/IF(Assumptions!$C$5="INR",INDEX('INR Normalised'!$F55:$S55,Assumptions!$C$7),INDEX('Raw Data'!$F55:$S55,Assumptions!$C$7))*100 -> 100 | ... S55: =IF(Assumptions!$C$5="INR",'INR Normalised'!S55,'Raw Data'!S55)/IF(Assumptions!$C$5="INR",INDEX('INR Normalised'!$F55:$S55,Assumptions!$C$7),INDEX('Raw Data'!$F55:$S55,Assumptions!$C$7))*100 -> 100 | T55: =IFERROR(S55/R55-1,"") -> 0 | U55: =IFERROR(S55/F55-1,"") -> 0
A56: ='Raw Data'!A56 -> Ethanol - B-Heavy Molasses | B56: Energy & Fuels | C56: =Assumptions!$C$5 -> INR | D56: =Assumptions!$C$6 -> Jul-25 | E56: 100 | F56: =IF(Assumptions!$C$5="INR",'INR Normalised'!F56,'Raw Data'!F56)/IF(Assumptions!$C$5="INR",INDEX('INR Normalised'!$F56:$S56,Assumptions!$C$7),INDEX('Raw Data'!$F56:$S56,Assumptions!$C$7))*100 -> 100 | G56: =IF(Assumptions!$C$5="INR",'INR Normalised'!G56,'Raw Data'!G56)/IF(Assumptions!$C$5="INR",INDEX('INR Normalised'!$F56:$S56,Assumptions!$C$7),INDEX('Raw Data'!$F56:$S56,Assumptions!$C$7))*100 -> 100 | H56: =IF(Assumptions!$C$5="INR",'INR Normalised'!H56,'Raw Data'!H56)/IF(Assumptions!$C$5="INR",INDEX('INR Normalised'!$F56:$S56,Assumptions!$C$7),INDEX('Raw Data'!$F56:$S56,Assumptions!$C$7))*100 -> 100 | I56: =IF(Assumptions!$C$5="INR",'INR Normalised'!I56,'Raw Data'!I56)/IF(Assumptions!$C$5="INR",INDEX('INR Normalised'!$F56:$S56,Assumptions!$C$7),INDEX('Raw Data'!$F56:$S56,Assumptions!$C$7))*100 -> 100 | J56: =IF(Assumptions!$C$5="INR",'INR Normalised'!J56,'Raw Data'!J56)/IF(Assumptions!$C$5="INR",INDEX('INR Normalised'!$F56:$S56,Assumptions!$C$7),INDEX('Raw Data'!$F56:$S56,Assumptions!$C$7))*100 -> 100 | K56: =IF(Assumptions!$C$5="INR",'INR Normalised'!K56,'Raw Data'!K56)/IF(Assumptions!$C$5="INR",INDEX('INR Normalised'!$F56:$S56,Assumptions!$C$7),INDEX('Raw Data'!$F56:$S56,Assumptions!$C$7))*100 -> 100 | L56: =IF(Assumptions!$C$5="INR",'INR Normalised'!L56,'Raw Data'!L56)/IF(Assumptions!$C$5="INR",INDEX('INR Normalised'!$F56:$S56,Assumptions!$C$7),INDEX('Raw Data'!$F56:$S56,Assumptions!$C$7))*100 -> 100 | M56: =IF(Assumptions!$C$5="INR",'INR Normalised'!M56,'Raw Data'!M56)/IF(Assumptions!$C$5="INR",INDEX('INR Normalised'!$F56:$S56,Assumptions!$C$7),INDEX('Raw Data'!$F56:$S56,Assumptions!$C$7))*100 -> 100 | ... S56: =IF(Assumptions!$C$5="INR",'INR Normalised'!S56,'Raw Data'!S56)/IF(Assumptions!$C$5="INR",INDEX('INR Normalised'!$F56:$S56,Assumptions!$C$7),INDEX('Raw Data'!$F56:$S56,Assumptions!$C$7))*100 -> 100 | T56: =IFERROR(S56/R56-1,"") -> 0 | U56: =IFERROR(S56/F56-1,"") -> 0
A57: ='Raw Data'!A57 -> Ethanol - C-Heavy Molasses | B57: Energy & Fuels | C57: =Assumptions!$C$5 -> INR | D57: =Assumptions!$C$6 -> Jul-25 | E57: 100 | F57: =IF(Assumptions!$C$5="INR",'INR Normalised'!F57,'Raw Data'!F57)/IF(Assumptions!$C$5="INR",INDEX('INR Normalised'!$F57:$S57,Assumptions!$C$7),INDEX('Raw Data'!$F57:$S57,Assumptions!$C$7))*100 -> 100 | G57: =IF(Assumptions!$C$5="INR",'INR Normalised'!G57,'Raw Data'!G57)/IF(Assumptions!$C$5="INR",INDEX('INR Normalised'!$F57:$S57,Assumptions!$C$7),INDEX('Raw Data'!$F57:$S57,Assumptions!$C$7))*100 -> 100 | H57: =IF(Assumptions!$C$5="INR",'INR Normalised'!H57,'Raw Data'!H57)/IF(Assumptions!$C$5="INR",INDEX('INR Normalised'!$F57:$S57,Assumptions!$C$7),INDEX('Raw Data'!$F57:$S57,Assumptions!$C$7))*100 -> 100 | I57: =IF(Assumptions!$C$5="INR",'INR Normalised'!I57,'Raw Data'!I57)/IF(Assumptions!$C$5="INR",INDEX('INR Normalised'!$F57:$S57,Assumptions!$C$7),INDEX('Raw Data'!$F57:$S57,Assumptions!$C$7))*100 -> 100 | J57: =IF(Assumptions!$C$5="INR",'INR Normalised'!J57,'Raw Data'!J57)/IF(Assumptions!$C$5="INR",INDEX('INR Normalised'!$F57:$S57,Assumptions!$C$7),INDEX('Raw Data'!$F57:$S57,Assumptions!$C$7))*100 -> 100 | K57: =IF(Assumptions!$C$5="INR",'INR Normalised'!K57,'Raw Data'!K57)/IF(Assumptions!$C$5="INR",INDEX('INR Normalised'!$F57:$S57,Assumptions!$C$7),INDEX('Raw Data'!$F57:$S57,Assumptions!$C$7))*100 -> 100 | L57: =IF(Assumptions!$C$5="INR",'INR Normalised'!L57,'Raw Data'!L57)/IF(Assumptions!$C$5="INR",INDEX('INR Normalised'!$F57:$S57,Assumptions!$C$7),INDEX('Raw Data'!$F57:$S57,Assumptions!$C$7))*100 -> 100 | M57: =IF(Assumptions!$C$5="INR",'INR Normalised'!M57,'Raw Data'!M57)/IF(Assumptions!$C$5="INR",INDEX('INR Normalised'!$F57:$S57,Assumptions!$C$7),INDEX('Raw Data'!$F57:$S57,Assumptions!$C$7))*100 -> 100 | ... S57: =IF(Assumptions!$C$5="INR",'INR Normalised'!S57,'Raw Data'!S57)/IF(Assumptions!$C$5="INR",INDEX('INR Normalised'!$F57:$S57,Assumptions!$C$7),INDEX('Raw Data'!$F57:$S57,Assumptions!$C$7))*100 -> 100 | T57: =IFERROR(S57/R57-1,"") -> 0 | U57: =IFERROR(S57/F57-1,"") -> 0
A58: FREIGHT
A59: ='Raw Data'!A59 -> Baltic Dry Index (Dry Bulk) | B59: Freight | C59: =Assumptions!$C$5 -> INR | D59: =Assumptions!$C$6 -> Jul-25 | E59: 100 | F59: =IF(Assumptions!$C$5="INR",'INR Normalised'!F59,'Raw Data'!F59)/IF(Assumptions!$C$5="INR",INDEX('INR Normalised'!$F59:$S59,Assumptions!$C$7),INDEX('Raw Data'!$F59:$S59,Assumptions!$C$7))*100 -> 100 | G59: =IF(Assumptions!$C$5="INR",'INR Normalised'!G59,'Raw Data'!G59)/IF(Assumptions!$C$5="INR",INDEX('INR Normalised'!$F59:$S59,Assumptions!$C$7),INDEX('Raw Data'!$F59:$S59,Assumptions!$C$7))*100 -> 109.95052 | H59: =IF(Assumptions!$C$5="INR",'INR Normalised'!H59,'Raw Data'!H59)/IF(Assumptions!$C$5="INR",INDEX('INR Normalised'!$F59:$S59,Assumptions!$C$7),INDEX('Raw Data'!$F59:$S59,Assumptions!$C$7))*100 -> 116.76745 | I59: =IF(Assumptions!$C$5="INR",'INR Normalised'!I59,'Raw Data'!I59)/IF(Assumptions!$C$5="INR",INDEX('INR Normalised'!$F59:$S59,Assumptions!$C$7),INDEX('Raw Data'!$F59:$S59,Assumptions!$C$7))*100 -> 109.7856 | J59: =IF(Assumptions!$C$5="INR",'INR Normalised'!J59,'Raw Data'!J59)/IF(Assumptions!$C$5="INR",INDEX('INR Normalised'!$F59:$S59,Assumptions!$C$7),INDEX('Raw Data'!$F59:$S59,Assumptions!$C$7))*100 -> 120.06597 | K59: =IF(Assumptions!$C$5="INR",'INR Normalised'!K59,'Raw Data'!K59)/IF(Assumptions!$C$5="INR",INDEX('INR Normalised'!$F59:$S59,Assumptions!$C$7),INDEX('Raw Data'!$F59:$S59,Assumptions!$C$7))*100 -> 128.58714 | L59: =IF(Assumptions!$C$5="INR",'INR Normalised'!L59,'Raw Data'!L59)/IF(Assumptions!$C$5="INR",INDEX('INR Normalised'!$F59:$S59,Assumptions!$C$7),INDEX('Raw Data'!$F59:$S59,Assumptions!$C$7))*100 -> 97.691039 | M59: =IF(Assumptions!$C$5="INR",'INR Normalised'!M59,'Raw Data'!M59)/IF(Assumptions!$C$5="INR",INDEX('INR Normalised'!$F59:$S59,Assumptions!$C$7),INDEX('Raw Data'!$F59:$S59,Assumptions!$C$7))*100 -> 112.20451 | ... S59: =IF(Assumptions!$C$5="INR",'INR Normalised'!S59,'Raw Data'!S59)/IF(Assumptions!$C$5="INR",INDEX('INR Normalised'!$F59:$S59,Assumptions!$C$7),INDEX('Raw Data'!$F59:$S59,Assumptions!$C$7))*100 -> 152.28147 | T59: =IFERROR(S59/R59-1,"") -> 0 | U59: =IFERROR(S59/F59-1,"") -> 0.52281473
A60: FX (period-end selling rate)
A61: ='Raw Data'!A61 -> USD / INR (selling) | B61: Fx (Period-End Selling Rate) | C61: =Assumptions!$C$5 -> INR | D61: =Assumptions!$C$6 -> Jul-25 | E61: 100 | F61: =IF(Assumptions!$C$5="INR",'INR Normalised'!F61,'Raw Data'!F61)/IF(Assumptions!$C$5="INR",INDEX('INR Normalised'!$F61:$S61,Assumptions!$C$7),INDEX('Raw Data'!$F61:$S61,Assumptions!$C$7))*100 -> 100 | G61: =IF(Assumptions!$C$5="INR",'INR Normalised'!G61,'Raw Data'!G61)/IF(Assumptions!$C$5="INR",INDEX('INR Normalised'!$F61:$S61,Assumptions!$C$7),INDEX('Raw Data'!$F61:$S61,Assumptions!$C$7))*100 -> 101.64918 | H61: =IF(Assumptions!$C$5="INR",'INR Normalised'!H61,'Raw Data'!H61)/IF(Assumptions!$C$5="INR",INDEX('INR Normalised'!$F61:$S61,Assumptions!$C$7),INDEX('Raw Data'!$F61:$S61,Assumptions!$C$7))*100 -> 102.51413 | I61: =IF(Assumptions!$C$5="INR",'INR Normalised'!I61,'Raw Data'!I61)/IF(Assumptions!$C$5="INR",INDEX('INR Normalised'!$F61:$S61,Assumptions!$C$7),INDEX('Raw Data'!$F61:$S61,Assumptions!$C$7))*100 -> 102.62945 | J61: =IF(Assumptions!$C$5="INR",'INR Normalised'!J61,'Raw Data'!J61)/IF(Assumptions!$C$5="INR",INDEX('INR Normalised'!$F61:$S61,Assumptions!$C$7),INDEX('Raw Data'!$F61:$S61,Assumptions!$C$7))*100 -> 103.12536 | K61: =IF(Assumptions!$C$5="INR",'INR Normalised'!K61,'Raw Data'!K61)/IF(Assumptions!$C$5="INR",INDEX('INR Normalised'!$F61:$S61,Assumptions!$C$7),INDEX('Raw Data'!$F61:$S61,Assumptions!$C$7))*100 -> 104.50928 | L61: =IF(Assumptions!$C$5="INR",'INR Normalised'!L61,'Raw Data'!L61)/IF(Assumptions!$C$5="INR",INDEX('INR Normalised'!$F61:$S61,Assumptions!$C$7),INDEX('Raw Data'!$F61:$S61,Assumptions!$C$7))*100 -> 105.33964 | M61: =IF(Assumptions!$C$5="INR",'INR Normalised'!M61,'Raw Data'!M61)/IF(Assumptions!$C$5="INR",INDEX('INR Normalised'!$F61:$S61,Assumptions!$C$7),INDEX('Raw Data'!$F61:$S61,Assumptions!$C$7))*100 -> 105.31657 | ... S61: =IF(Assumptions!$C$5="INR",'INR Normalised'!S61,'Raw Data'!S61)/IF(Assumptions!$C$5="INR",INDEX('INR Normalised'!$F61:$S61,Assumptions!$C$7),INDEX('Raw Data'!$F61:$S61,Assumptions!$C$7))*100 -> 110.77154 | T61: =IFERROR(S61/R61-1,"") -> -0.0032171025 | U61: =IFERROR(S61/F61-1,"") -> 0.10771537
A62: ='Raw Data'!A62 -> GBP / INR (selling) | B62: Fx (Period-End Selling Rate) | C62: =Assumptions!$C$5 -> INR | D62: =Assumptions!$C$6 -> Jul-25 | E62: 100 | F62: =IF(Assumptions!$C$5="INR",'INR Normalised'!F62,'Raw Data'!F62)/IF(Assumptions!$C$5="INR",INDEX('INR Normalised'!$F62:$S62,Assumptions!$C$7),INDEX('Raw Data'!$F62:$S62,Assumptions!$C$7))*100 -> 100 | G62: =IF(Assumptions!$C$5="INR",'INR Normalised'!G62,'Raw Data'!G62)/IF(Assumptions!$C$5="INR",INDEX('INR Normalised'!$F62:$S62,Assumptions!$C$7),INDEX('Raw Data'!$F62:$S62,Assumptions!$C$7))*100 -> 101.05111 | H62: =IF(Assumptions!$C$5="INR",'INR Normalised'!H62,'Raw Data'!H62)/IF(Assumptions!$C$5="INR",INDEX('INR Normalised'!$F62:$S62,Assumptions!$C$7),INDEX('Raw Data'!$F62:$S62,Assumptions!$C$7))*100 -> 102.36501 | I62: =IF(Assumptions!$C$5="INR",'INR Normalised'!I62,'Raw Data'!I62)/IF(Assumptions!$C$5="INR",INDEX('INR Normalised'!$F62:$S62,Assumptions!$C$7),INDEX('Raw Data'!$F62:$S62,Assumptions!$C$7))*100 -> 101.53429 | J62: =IF(Assumptions!$C$5="INR",'INR Normalised'!J62,'Raw Data'!J62)/IF(Assumptions!$C$5="INR",INDEX('INR Normalised'!$F62:$S62,Assumptions!$C$7),INDEX('Raw Data'!$F62:$S62,Assumptions!$C$7))*100 -> 100.33059 | K62: =IF(Assumptions!$C$5="INR",'INR Normalised'!K62,'Raw Data'!K62)/IF(Assumptions!$C$5="INR",INDEX('INR Normalised'!$F62:$S62,Assumptions!$C$7),INDEX('Raw Data'!$F62:$S62,Assumptions!$C$7))*100 -> 103.45003 | L62: =IF(Assumptions!$C$5="INR",'INR Normalised'!L62,'Raw Data'!L62)/IF(Assumptions!$C$5="INR",INDEX('INR Normalised'!$F62:$S62,Assumptions!$C$7),INDEX('Raw Data'!$F62:$S62,Assumptions!$C$7))*100 -> 105.35729 | M62: =IF(Assumptions!$C$5="INR",'INR Normalised'!M62,'Raw Data'!M62)/IF(Assumptions!$C$5="INR",INDEX('INR Normalised'!$F62:$S62,Assumptions!$C$7),INDEX('Raw Data'!$F62:$S62,Assumptions!$C$7))*100 -> 105.88285 | ... S62: =IF(Assumptions!$C$5="INR",'INR Normalised'!S62,'Raw Data'!S62)/IF(Assumptions!$C$5="INR",INDEX('INR Normalised'!$F62:$S62,Assumptions!$C$7),INDEX('Raw Data'!$F62:$S62,Assumptions!$C$7))*100 -> 110.90108 | T62: =IFERROR(S62/R62-1,"") -> 0.0079352851 | U62: =IFERROR(S62/F62-1,"") -> 0.10901077
A63: ='Raw Data'!A63 -> EUR / INR (selling) | B63: Fx (Period-End Selling Rate) | C63: =Assumptions!$C$5 -> INR | D63: =Assumptions!$C$6 -> Jul-25 | E63: 100 | F63: =IF(Assumptions!$C$5="INR",'INR Normalised'!F63,'Raw Data'!F63)/IF(Assumptions!$C$5="INR",INDEX('INR Normalised'!$F63:$S63,Assumptions!$C$7),INDEX('Raw Data'!$F63:$S63,Assumptions!$C$7))*100 -> 100 | G63: =IF(Assumptions!$C$5="INR",'INR Normalised'!G63,'Raw Data'!G63)/IF(Assumptions!$C$5="INR",INDEX('INR Normalised'!$F63:$S63,Assumptions!$C$7),INDEX('Raw Data'!$F63:$S63,Assumptions!$C$7))*100 -> 101.18442 | H63: =IF(Assumptions!$C$5="INR",'INR Normalised'!H63,'Raw Data'!H63)/IF(Assumptions!$C$5="INR",INDEX('INR Normalised'!$F63:$S63,Assumptions!$C$7),INDEX('Raw Data'!$F63:$S63,Assumptions!$C$7))*100 -> 102.92678 | I63: =IF(Assumptions!$C$5="INR",'INR Normalised'!I63,'Raw Data'!I63)/IF(Assumptions!$C$5="INR",INDEX('INR Normalised'!$F63:$S63,Assumptions!$C$7),INDEX('Raw Data'!$F63:$S63,Assumptions!$C$7))*100 -> 102.27095 | J63: =IF(Assumptions!$C$5="INR",'INR Normalised'!J63,'Raw Data'!J63)/IF(Assumptions!$C$5="INR",INDEX('INR Normalised'!$F63:$S63,Assumptions!$C$7),INDEX('Raw Data'!$F63:$S63,Assumptions!$C$7))*100 -> 102.03602 | K63: =IF(Assumptions!$C$5="INR",'INR Normalised'!K63,'Raw Data'!K63)/IF(Assumptions!$C$5="INR",INDEX('INR Normalised'!$F63:$S63,Assumptions!$C$7),INDEX('Raw Data'!$F63:$S63,Assumptions!$C$7))*100 -> 104.62999 | L63: =IF(Assumptions!$C$5="INR",'INR Normalised'!L63,'Raw Data'!L63)/IF(Assumptions!$C$5="INR",INDEX('INR Normalised'!$F63:$S63,Assumptions!$C$7),INDEX('Raw Data'!$F63:$S63,Assumptions!$C$7))*100 -> 105.74589 | M63: =IF(Assumptions!$C$5="INR",'INR Normalised'!M63,'Raw Data'!M63)/IF(Assumptions!$C$5="INR",INDEX('INR Normalised'!$F63:$S63,Assumptions!$C$7),INDEX('Raw Data'!$F63:$S63,Assumptions!$C$7))*100 -> 106.53876 | ... S63: =IF(Assumptions!$C$5="INR",'INR Normalised'!S63,'Raw Data'!S63)/IF(Assumptions!$C$5="INR",INDEX('INR Normalised'!$F63:$S63,Assumptions!$C$7),INDEX('Raw Data'!$F63:$S63,Assumptions!$C$7))*100 -> 109.74941 | T63: =IFERROR(S63/R63-1,"") -> 0.010454218 | U63: =IFERROR(S63/F63-1,"") -> 0.097494127
A64: ='Raw Data'!A64 -> JPY 100 / INR (selling) | B64: Fx (Period-End Selling Rate) | C64: =Assumptions!$C$5 -> INR | D64: =Assumptions!$C$6 -> Jul-25 | E64: 100 | F64: =IF(Assumptions!$C$5="INR",'INR Normalised'!F64,'Raw Data'!F64)/IF(Assumptions!$C$5="INR",INDEX('INR Normalised'!$F64:$S64,Assumptions!$C$7),INDEX('Raw Data'!$F64:$S64,Assumptions!$C$7))*100 -> 100 | G64: =IF(Assumptions!$C$5="INR",'INR Normalised'!G64,'Raw Data'!G64)/IF(Assumptions!$C$5="INR",INDEX('INR Normalised'!$F64:$S64,Assumptions!$C$7),INDEX('Raw Data'!$F64:$S64,Assumptions!$C$7))*100 -> 101.09299 | H64: =IF(Assumptions!$C$5="INR",'INR Normalised'!H64,'Raw Data'!H64)/IF(Assumptions!$C$5="INR",INDEX('INR Normalised'!$F64:$S64,Assumptions!$C$7),INDEX('Raw Data'!$F64:$S64,Assumptions!$C$7))*100 -> 101.68152 | I64: =IF(Assumptions!$C$5="INR",'INR Normalised'!I64,'Raw Data'!I64)/IF(Assumptions!$C$5="INR",INDEX('INR Normalised'!$F64:$S64,Assumptions!$C$7),INDEX('Raw Data'!$F64:$S64,Assumptions!$C$7))*100 -> 99.57962 | J64: =IF(Assumptions!$C$5="INR",'INR Normalised'!J64,'Raw Data'!J64)/IF(Assumptions!$C$5="INR",INDEX('INR Normalised'!$F64:$S64,Assumptions!$C$7),INDEX('Raw Data'!$F64:$S64,Assumptions!$C$7))*100 -> 97.561796 | K64: =IF(Assumptions!$C$5="INR",'INR Normalised'!K64,'Raw Data'!K64)/IF(Assumptions!$C$5="INR",INDEX('INR Normalised'!$F64:$S64,Assumptions!$C$7),INDEX('Raw Data'!$F64:$S64,Assumptions!$C$7))*100 -> 98.368926 | L64: =IF(Assumptions!$C$5="INR",'INR Normalised'!L64,'Raw Data'!L64)/IF(Assumptions!$C$5="INR",INDEX('INR Normalised'!$F64:$S64,Assumptions!$C$7),INDEX('Raw Data'!$F64:$S64,Assumptions!$C$7))*100 -> 98.604338 | M64: =IF(Assumptions!$C$5="INR",'INR Normalised'!M64,'Raw Data'!M64)/IF(Assumptions!$C$5="INR",INDEX('INR Normalised'!$F64:$S64,Assumptions!$C$7),INDEX('Raw Data'!$F64:$S64,Assumptions!$C$7))*100 -> 99.714142 | ... S64: =IF(Assumptions!$C$5="INR",'INR Normalised'!S64,'Raw Data'!S64)/IF(Assumptions!$C$5="INR",INDEX('INR Normalised'!$F64:$S64,Assumptions!$C$7),INDEX('Raw Data'!$F64:$S64,Assumptions!$C$7))*100 -> 102.37094 | T64: =IFERROR(S64/R64-1,"") -> 0.019936338 | U64: =IFERROR(S64/F64-1,"") -> 0.023709433
A65: ='Raw Data'!A65 -> CNY / INR | B65: Fx (Period-End Selling Rate) | C65: =Assumptions!$C$5 -> INR | D65: =Assumptions!$C$6 -> Jul-25 | E65: 100 | F65: =IF(Assumptions!$C$5="INR",'INR Normalised'!F65,'Raw Data'!F65)/IF(Assumptions!$C$5="INR",INDEX('INR Normalised'!$F65:$S65,Assumptions!$C$7),INDEX('Raw Data'!$F65:$S65,Assumptions!$C$7))*100 -> 100 | G65: =IF(Assumptions!$C$5="INR",'INR Normalised'!G65,'Raw Data'!G65)/IF(Assumptions!$C$5="INR",INDEX('INR Normalised'!$F65:$S65,Assumptions!$C$7),INDEX('Raw Data'!$F65:$S65,Assumptions!$C$7))*100 -> 101.74709 | H65: =IF(Assumptions!$C$5="INR",'INR Normalised'!H65,'Raw Data'!H65)/IF(Assumptions!$C$5="INR",INDEX('INR Normalised'!$F65:$S65,Assumptions!$C$7),INDEX('Raw Data'!$F65:$S65,Assumptions!$C$7))*100 -> 103.24459 | I65: =IF(Assumptions!$C$5="INR",'INR Normalised'!I65,'Raw Data'!I65)/IF(Assumptions!$C$5="INR",INDEX('INR Normalised'!$F65:$S65,Assumptions!$C$7),INDEX('Raw Data'!$F65:$S65,Assumptions!$C$7))*100 -> 103.24459 | J65: =IF(Assumptions!$C$5="INR",'INR Normalised'!J65,'Raw Data'!J65)/IF(Assumptions!$C$5="INR",INDEX('INR Normalised'!$F65:$S65,Assumptions!$C$7),INDEX('Raw Data'!$F65:$S65,Assumptions!$C$7))*100 -> 106.07321 | K65: =IF(Assumptions!$C$5="INR",'INR Normalised'!K65,'Raw Data'!K65)/IF(Assumptions!$C$5="INR",INDEX('INR Normalised'!$F65:$S65,Assumptions!$C$7),INDEX('Raw Data'!$F65:$S65,Assumptions!$C$7))*100 -> 106.98835 | L65: =IF(Assumptions!$C$5="INR",'INR Normalised'!L65,'Raw Data'!L65)/IF(Assumptions!$C$5="INR",INDEX('INR Normalised'!$F65:$S65,Assumptions!$C$7),INDEX('Raw Data'!$F65:$S65,Assumptions!$C$7))*100 -> 110.14975 | M65: =IF(Assumptions!$C$5="INR",'INR Normalised'!M65,'Raw Data'!M65)/IF(Assumptions!$C$5="INR",INDEX('INR Normalised'!$F65:$S65,Assumptions!$C$7),INDEX('Raw Data'!$F65:$S65,Assumptions!$C$7))*100 -> 109.401 | ... S65: =IF(Assumptions!$C$5="INR",'INR Normalised'!S65,'Raw Data'!S65)/IF(Assumptions!$C$5="INR",INDEX('INR Normalised'!$F65:$S65,Assumptions!$C$7),INDEX('Raw Data'!$F65:$S65,Assumptions!$C$7))*100 -> 117.88686 | T65: =IFERROR(S65/R65-1,"") -> 0 | U65: =IFERROR(S65/F65-1,"") -> 0.17886855
A66: POLICY & LENDING RATES
A67: ='Raw Data'!A67 -> Cash Reserve Ratio (%) | B67: Policy & Lending Rates | C67: not indexed
A68: ='Raw Data'!A68 -> Bank Rate (% p.a.) | B68: Policy & Lending Rates | C68: not indexed
A69: ='Raw Data'!A69 -> Base Rate - low (% p.a.) | B69: Policy & Lending Rates | C69: not indexed
A70: ='Raw Data'!A70 -> Base Rate - high (% p.a.) | B70: Policy & Lending Rates | C70: not indexed
A72: Index = price in month M divided by price in the base month, x100. Policy rates are levels, not prices, and are not indexed.

Sheet Basket Weights
A1: PROPRIETARY BASKET WEIGHTS
A2: Bill-of-material weights (%) by segment, plus sub-complex monitors. Every blue cell is editable. Each column must sum to 100.
C4: SEGMENT BOM BASKETS | I4: SUB-COMPLEX MONITORS
A5: Commodity | B5: Category | C5: PV (ICE) | D5: 2W (ICE) | E5: CV | F5: Tractor | G5: BEV - PV | H5: E-2W | I5: Ferrous | J5: Non-Ferrous | K5: PGM | L5: Polymers | M5: Rubber & CB | N5: Battery Chem | O5: Energy & Freight
A6: FERROUS - FLAT, LONG & SPECIAL STEEL
A7: ='Raw Data'!A7 -> HR Steel (HRC 1.8mm, IS2062) | B7: Ferrous - Flat, Long & Special Steel | C7: 23 | D7: 20 | E7: 28 | F7: 30 | G7: 12 | H7: 14 | I7: 32 | J7: 0 | K7: 0 | L7: 0 | M7: 0 | N7: 0 | O7: 0
A8: ='Raw Data'!A8 -> CR Steel (CRC 0.90mm, IS513 GrO) | B8: Ferrous - Flat, Long & Special Steel | C8: 16 | D8: 12 | E8: 10 | F8: 8 | G8: 8 | H8: 8 | I8: 22 | J8: 0 | K8: 0 | L8: 0 | M8: 0 | N8: 0 | O8: 0
A9: ='Raw Data'!A9 -> Alloy Steel - Forging (20MnCr5) | B9: Ferrous - Flat, Long & Special Steel | C9: 4 | D9: 5 | E9: 6 | F9: 8 | G9: 0 | H9: 0 | I9: 8 | J9: 0 | K9: 0 | L9: 0 | M9: 0 | N9: 0 | O9: 0
A10: ='Raw Data'!A10 -> Alloy Steel - Forging (EN-8) | B10: Ferrous - Flat, Long & Special Steel | C10: 3 | D10: 4 | E10: 5 | F10: 6 | G10: 0 | H10: 0 | I10: 6 | J10: 0 | K10: 0 | L10: 0 | M10: 0 | N10: 0 | O10: 0
A11: ='Raw Data'!A11 -> Pig Iron (Foundry Grade B) | B11: Ferrous - Flat, Long & Special Steel | C11: 3 | D11: 3 | E11: 4 | F11: 8 | G11: 0 | H11: 0 | I11: 10 | J11: 0 | K11: 0 | L11: 0 | M11: 0 | N11: 0 | O11: 0
A12: ='Raw Data'!A12 -> Stainless Steel (G304 CR Coil) | B12: Ferrous - Flat, Long & Special Steel | C12: 2 | D12: 3 | E12: 1 | F12: 0 | G12: 1 | H12: 0 | I12: 5 | J12: 0 | K12: 0 | L12: 0 | M12: 0 | N12: 0 | O12: 0
A13: ='Raw Data'!A13 -> Stainless Steel (G304 HR Coil) | B13: Ferrous - Flat, Long & Special Steel | C13: 0 | D13: 0 | E13: 0 | F13: 0 | G13: 0 | H13: 0 | I13: 3 | J13: 0 | K13: 0 | L13: 0 | M13: 0 | N13: 0 | O13: 0
A14: ='Raw Data'!A14 -> Steel Scrap (RM end scrap) | B14: Ferrous - Flat, Long & Special Steel | C14: 2 | D14: 2 | E14: 3 | F14: 4 | G14: 1 | H14: 1 | I14: 6 | J14: 0 | K14: 0 | L14: 0 | M14: 0 | N14: 0 | O14: 0
A15: UPSTREAM STEEL INPUTS
A16: ='Raw Data'!A16 -> Coking Coal (Premium HCC, Australia) | B16: Upstream Steel Inputs | C16: 0 | D16: 0 | E16: 0 | F16: 0 | G16: 0 | H16: 0 | I16: 3 | J16: 0 | K16: 0 | L16: 0 | M16: 0 | N16: 0 | O16: 15
A17: ='Raw Data'!A17 -> Iron Ore (Fe 62%, Australia) | B17: Upstream Steel Inputs | C17: 0 | D17: 0 | E17: 0 | F17: 0 | G17: 0 | H17: 0 | I17: 5 | J17: 0 | K17: 0 | L17: 0 | M17: 0 | N17: 0 | O17: 0
A18: NON-FERROUS METALS
A19: ='Raw Data'!A19 -> Virgin Aluminium | B19: Non-Ferrous Metals | C19: 14 | D19: 20 | E19: 10 | F19: 6 | G19: 15 | H19: 18 | I19: 0 | J19: 55 | K19: 0 | L19: 0 | M19: 0 | N19: 0 | O19: 0
A20: ='Raw Data'!A20 -> Copper | B20: Non-Ferrous Metals | C20: 6 | D20: 5 | E20: 5 | F20: 5 | G20: 12 | H20: 10 | I20: 0 | J20: 25 | K20: 0 | L20: 0 | M20: 0 | N20: 0 | O20: 0
A21: ='Raw Data'!A21 -> Lead | B21: Non-Ferrous Metals | C21: 1 | D21: 2 | E21: 1 | F21: 2 | G21: 0 | H21: 0 | I21: 0 | J21: 5 | K21: 0 | L21: 0 | M21: 0 | N21: 0 | O21: 0
A22: ='Raw Data'!A22 -> Nickel | B22: Non-Ferrous Metals | C22: 1 | D22: 1 | E22: 1 | F22: 0 | G22: 3 | H22: 2 | I22: 0 | J22: 7 | K22: 0 | L22: 0 | M22: 0 | N22: 0 | O22: 0
A23: ='Raw Data'!A23 -> Zinc | B23: Non-Ferrous Metals | C23: 2 | D23: 2 | E23: 2 | F23: 2 | G23: 1 | H23: 0 | I23: 0 | J23: 8 | K23: 0 | L23: 0 | M23: 0 | N23: 0 | O23: 0
A24: PRECIOUS / PGM
A25: ='Raw Data'!A25 -> Platinum | B25: Precious / Pgm | C25: 1.5 | D25: 1 | E25: 1 | F25: 0 | G25: 0 | H25: 0 | I25: 0 | J25: 0 | K25: 40 | L25: 0 | M25: 0 | N25: 0 | O25: 0
A26: ='Raw Data'!A26 -> Palladium | B26: Precious / Pgm | C26: 2 | D26: 1.5 | E26: 2 | F26: 0 | G26: 0 | H26: 0 | I26: 0 | J26: 0 | K26: 40 | L26: 0 | M26: 0 | N26: 0 | O26: 0
A27: ='Raw Data'!A27 -> Rhodium | B27: Precious / Pgm | C27: 1 | D27: 0.5 | E27: 1 | F27: 0 | G27: 0 | H27: 0 | I27: 0 | J27: 0 | K27: 20 | L27: 0 | M27: 0 | N27: 0 | O27: 0
A28: POLYMERS
A29: ='Raw Data'!A29 -> Polypropylene (PP) | B29: Polymers | C29: 6 | D29: 6 | E29: 5 | F29: 4 | G29: 5 | H29: 7 | I29: 0 | J29: 0 | K29: 0 | L29: 55 | M29: 0 | N29: 0 | O29: 0
A30: ='Raw Data'!A30 -> ABS | B30: Polymers | C30: 3 | D30: 4 | E30: 2 | F30: 2 | G30: 3 | H30: 4 | I30: 0 | J30: 0 | K30: 0 | L30: 30 | M30: 0 | N30: 0 | O30: 0
A31: ='Raw Data'!A31 -> Polycarbonate (PC) | B31: Polymers | C31: 2 | D31: 1 | E31: 1 | F31: 0 | G31: 2 | H31: 0 | I31: 0 | J31: 0 | K31: 0 | L31: 15 | M31: 0 | N31: 0 | O31: 0
A32: CHEMICALS
A33: ='Raw Data'!A33 -> Urea (Prilled), CFR | B33: Chemicals | C33: 0 | D33: 0 | E33: 0 | F33: 0 | G33: 0 | H33: 0 | I33: 0 | J33: 0 | K33: 0 | L33: 0 | M33: 0 | N33: 0 | O33: 0
A34: RUBBER & CARBON BLACK
A35: ='Raw Data'!A35 -> Natural Rubber (RSS 4) | B35: Rubber & Carbon Black | C35: 2.5 | D35: 3 | E35: 6 | F35: 8 | G35: 2 | H35: 2 | I35: 0 | J35: 0 | K35: 0 | L35: 0 | M35: 40 | N35: 0 | O35: 0
A36: ='Raw Data'!A36 -> Synthetic Rubber - SBR 1502 | B36: Rubber & Carbon Black | C36: 1.5 | D36: 1.5 | E36: 2 | F36: 2 | G36: 1 | H36: 0 | I36: 0 | J36: 0 | K36: 0 | L36: 0 | M36: 20 | N36: 0 | O36: 0
A37: ='Raw Data'!A37 -> EPDM | B37: Rubber & Carbon Black | C37: 1.5 | D37: 0.5 | E37: 1 | F37: 1 | G37: 1 | H37: 0 | I37: 0 | J37: 0 | K37: 0 | L37: 0 | M37: 12 | N37: 0 | O37: 0
A38: ='Raw Data'!A38 -> Carbon Black (N330) | B38: Rubber & Carbon Black | C38: 1 | D38: 1 | E38: 2 | F38: 3 | G38: 1 | H38: 1 | I38: 0 | J38: 0 | K38: 0 | L38: 0 | M38: 18 | N38: 0 | O38: 0
A39: ='Raw Data'!A39 -> Polybutadiene Rubber (1220) | B39: Rubber & Carbon Black | C39: 1 | D39: 1 | E39: 1 | F39: 1 | G39: 0 | H39: 0 | I39: 0 | J39: 0 | K39: 0 | L39: 0 | M39: 10 | N39: 0 | O39: 0
A40: ADVANCED CHEMISTRIES (BATTERY)
A41: ='Raw Data'!A41 -> Lithium Carbonate (99.5% batt grade) | B41: Advanced Chemistries (Battery) | C41: 0 | D41: 0 | E41: 0 | F41: 0 | G41: 12 | H41: 14 | I41: 0 | J41: 0 | K41: 0 | L41: 0 | M41: 0 | N41: 40 | O41: 0
A42: ='Raw Data'!A42 -> Lithium Hydroxide (56.5% batt grade) | B42: Advanced Chemistries (Battery) | C42: 0 | D42: 0 | E42: 0 | F42: 0 | G42: 8 | H42: 8 | I42: 0 | J42: 0 | K42: 0 | L42: 0 | M42: 0 | N42: 25 | O42: 0
A43: ='Raw Data'!A43 -> Cobalt Oxide (Co>=72%) | B43: Advanced Chemistries (Battery) | C43: 0 | D43: 0 | E43: 0 | F43: 0 | G43: 4 | H43: 3 | I43: 0 | J43: 0 | K43: 0 | L43: 0 | M43: 0 | N43: 15 | O43: 0
A44: ='Raw Data'!A44 -> Cobalt Metal (Co>=99.8%) | B44: Advanced Chemistries (Battery) | C44: 0 | D44: 0 | E44: 0 | F44: 0 | G44: 2 | H44: 1 | I44: 0 | J44: 0 | K44: 0 | L44: 0 | M44: 0 | N44: 10 | O44: 0
A45: RARE EARTH / MAGNETS
A46: ='Raw Data'!A46 -> NdFeB Magnet (GD - scrap) | B46: Rare Earth / Magnets | C46: 0 | D46: 0 | E46: 0 | F46: 0 | G46: 6 | H46: 7 | I46: 0 | J46: 0 | K46: 0 | L46: 0 | M46: 0 | N46: 10 | O46: 0
A47: ENERGY & FUELS
A48: ='Raw Data'!A48 -> Brent Crude (Europe spot FOB) | B48: Energy & Fuels | C48: 0 | D48: 0 | E48: 0 | F48: 0 | G48: 0 | H48: 0 | I48: 0 | J48: 0 | K48: 0 | L48: 0 | M48: 0 | N48: 0 | O48: 35
A49: ='Raw Data'!A49 -> CNG - Delhi (IGL) | B49: Energy & Fuels | C49: 0 | D49: 0 | E49: 0 | F49: 0 | G49: 0 | H49: 0 | I49: 0 | J49: 0 | K49: 0 | L49: 0 | M49: 0 | N49: 0 | O49: 10
A50: ='Raw Data'!A50 -> CNG - Mumbai (MGL) | B50: Energy & Fuels | C50: 0 | D50: 0 | E50: 0 | F50: 0 | G50: 0 | H50: 0 | I50: 0 | J50: 0 | K50: 0 | L50: 0 | M50: 0 | N50: 0 | O50: 0
A51: ='Raw Data'!A51 -> Petrol - Delhi | B51: Energy & Fuels | C51: 0 | D51: 0 | E51: 0 | F51: 0 | G51: 0 | H51: 0 | I51: 0 | J51: 0 | K51: 0 | L51: 0 | M51: 0 | N51: 0 | O51: 0
A52: ='Raw Data'!A52 -> Diesel - Delhi | B52: Energy & Fuels | C52: 0 | D52: 0 | E52: 0 | F52: 0 | G52: 0 | H52: 0 | I52: 0 | J52: 0 | K52: 0 | L52: 0 | M52: 0 | N52: 0 | O52: 20
A53: ='Raw Data'!A53 -> Petrol - Mumbai | B53: Energy & Fuels | C53: 0 | D53: 0 | E53: 0 | F53: 0 | G53: 0 | H53: 0 | I53: 0 | J53: 0 | K53: 0 | L53: 0 | M53: 0 | N53: 0 | O53: 0
A54: ='Raw Data'!A54 -> Diesel - Mumbai | B54: Energy & Fuels | C54: 0 | D54: 0 | E54: 0 | F54: 0 | G54: 0 | H54: 0 | I54: 0 | J54: 0 | K54: 0 | L54: 0 | M54: 0 | N54: 0 | O54: 0
A55: ='Raw Data'!A55 -> Ethanol - Sugarcane Juice | B55: Energy & Fuels | C55: 0 | D55: 0 | E55: 0 | F55: 0 | G55: 0 | H55: 0 | I55: 0 | J55: 0 | K55: 0 | L55: 0 | M55: 0 | N55: 0 | O55: 0
A56: ='Raw Data'!A56 -> Ethanol - B-Heavy Molasses | B56: Energy & Fuels | C56: 0 | D56: 0 | E56: 0 | F56: 0 | G56: 0 | H56: 0 | I56: 0 | J56: 0 | K56: 0 | L56: 0 | M56: 0 | N56: 0 | O56: 0
A57: ='Raw Data'!A57 -> Ethanol - C-Heavy Molasses | B57: Energy & Fuels | C57: 0 | D57: 0 | E57: 0 | F57: 0 | G57: 0 | H57: 0 | I57: 0 | J57: 0 | K57: 0 | L57: 0 | M57: 0 | N57: 0 | O57: 0
A58: FREIGHT
A59: ='Raw Data'!A59 -> Baltic Dry Index (Dry Bulk) | B59: Freight | C59: 0 | D59: 0 | E59: 0 | F59: 0 | G59: 0 | H59: 0 | I59: 0 | J59: 0 | K59: 0 | L59: 0 | M59: 0 | N59: 0 | O59: 20
A60: FX (period-end selling rate)
A61: ='Raw Data'!A61 -> USD / INR (selling) | B61: Fx (Period-End Selling Rate) | C61: 0 | D61: 0 | E61: 0 | F61: 0 | G61: 0 | H61: 0 | I61: 0 | J61: 0 | K61: 0 | L61: 0 | M61: 0 | N61: 0 | O61: 0
A62: ='Raw Data'!A62 -> GBP / INR (selling) | B62: Fx (Period-End Selling Rate) | C62: 0 | D62: 0 | E62: 0 | F62: 0 | G62: 0 | H62: 0 | I62: 0 | J62: 0 | K62: 0 | L62: 0 | M62: 0 | N62: 0 | O62: 0
A63: ='Raw Data'!A63 -> EUR / INR (selling) | B63: Fx (Period-End Selling Rate) | C63: 0 | D63: 0 | E63: 0 | F63: 0 | G63: 0 | H63: 0 | I63: 0 | J63: 0 | K63: 0 | L63: 0 | M63: 0 | N63: 0 | O63: 0
A64: ='Raw Data'!A64 -> JPY 100 / INR (selling) | B64: Fx (Period-End Selling Rate) | C64: 0 | D64: 0 | E64: 0 | F64: 0 | G64: 0 | H64: 0 | I64: 0 | J64: 0 | K64: 0 | L64: 0 | M64: 0 | N64: 0 | O64: 0
A65: ='Raw Data'!A65 -> CNY / INR | B65: Fx (Period-End Selling Rate) | C65: 0 | D65: 0 | E65: 0 | F65: 0 | G65: 0 | H65: 0 | I65: 0 | J65: 0 | K65: 0 | L65: 0 | M65: 0 | N65: 0 | O65: 0
A66: POLICY & LENDING RATES
A67: ='Raw Data'!A67 -> Cash Reserve Ratio (%) | B67: Policy & Lending Rates
A68: ='Raw Data'!A68 -> Bank Rate (% p.a.) | B68: Policy & Lending Rates
A69: ='Raw Data'!A69 -> Base Rate - low (% p.a.) | B69: Policy & Lending Rates
A70: ='Raw Data'!A70 -> Base Rate - high (% p.a.) | B70: Policy & Lending Rates
A72: TOTAL (must equal 100.0) | C72: =SUM(C7:C59) -> 100 | D72: =SUM(D7:D59) -> 100 | E72: =SUM(E7:E59) -> 100 | F72: =SUM(F7:F59) -> 100 | G72: =SUM(G7:G59) -> 100 | H72: =SUM(H7:H59) -> 100 | I72: =SUM(I7:I59) -> 100 | J72: =SUM(J7:J59) -> 100 | ... O72: =SUM(O7:O59) -> 100
A74: Weights are analyst estimates of raw-material value share within a typical bill of materials for each segment, cross-checked against SIAM's own end-use consumption shares (e.g. construction 48% of HR steel, autos 9%; lead-acid batteries 80% of lead; catalytic converters 84% of rhodium; stainless 69% of nickel).
A75: Sub-complex monitors are standalone: they re-weight only within their own complex and are not additive to the segment baskets.
A76: Tractors carry no PGM weight — they are not emission-catalyst equipped in the same way; consistent with BofA's observation that tractors are unaffected by PGM inflation.

Sheet Basket Monitors
A1: BASKET & SUB-COMPLEX MONITORS (MONTHLY)
A2: Weighted commodity indices. Same base month and currency basis as the Commodity Indices sheet.
A5: Basket | B5: Type | F5: Jul-25 | G5: Aug-25 | H5: Sept-25 | I5: Oct-25 | J5: Nov-25 | K5: Dec-25 | L5: Jan-26 | M5: Feb-26 | N5: Mar-26 | O5: Apr-26 | P5: May-26 | Q5: June-26 | R5: July-26 | S5: Aug-26 | T5: MoM % | U5: YoY % | V5: Comment
A6: SEGMENT BOM BASKETS
A7: PV (ICE) | B7: Segment BOM | F7: =SUMPRODUCT('Basket Weights'!$C$7:$C$59,'Commodity Indices'!F$7:F$59)/SUM('Basket Weights'!$C$7:$C$59) -> 100 | G7: =SUMPRODUCT('Basket Weights'!$C$7:$C$59,'Commodity Indices'!G$7:G$59)/SUM('Basket Weights'!$C$7:$C$59) -> 100.55136 | H7: =SUMPRODUCT('Basket Weights'!$C$7:$C$59,'Commodity Indices'!H$7:H$59)/SUM('Basket Weights'!$C$7:$C$59) -> 101.01945 | I7: =SUMPRODUCT('Basket Weights'!$C$7:$C$59,'Commodity Indices'!I$7:I$59)/SUM('Basket Weights'!$C$7:$C$59) -> 102.09871 | J7: =SUMPRODUCT('Basket Weights'!$C$7:$C$59,'Commodity Indices'!J$7:J$59)/SUM('Basket Weights'!$C$7:$C$59) -> 100.95893 | K7: =SUMPRODUCT('Basket Weights'!$C$7:$C$59,'Commodity Indices'!K$7:K$59)/SUM('Basket Weights'!$C$7:$C$59) -> 102.73175 | L7: =SUMPRODUCT('Basket Weights'!$C$7:$C$59,'Commodity Indices'!L$7:L$59)/SUM('Basket Weights'!$C$7:$C$59) -> 110.6548 | M7: =SUMPRODUCT('Basket Weights'!$C$7:$C$59,'Commodity Indices'!M$7:M$59)/SUM('Basket Weights'!$C$7:$C$59) -> 111.52976 | ... S7: =SUMPRODUCT('Basket Weights'!$C$7:$C$59,'Commodity Indices'!S$7:S$59)/SUM('Basket Weights'!$C$7:$C$59) -> 126.55906 | T7: =IFERROR(S7/R7-1,"") -> 0.01834461 | U7: =IFERROR(S7/F7-1,"") -> 0.26559061
A8: 2W (ICE) | B8: Segment BOM | F8: =SUMPRODUCT('Basket Weights'!$D$7:$D$59,'Commodity Indices'!F$7:F$59)/SUM('Basket Weights'!$D$7:$D$59) -> 100 | G8: =SUMPRODUCT('Basket Weights'!$D$7:$D$59,'Commodity Indices'!G$7:G$59)/SUM('Basket Weights'!$D$7:$D$59) -> 100.4359 | H8: =SUMPRODUCT('Basket Weights'!$D$7:$D$59,'Commodity Indices'!H$7:H$59)/SUM('Basket Weights'!$D$7:$D$59) -> 101.01743 | I8: =SUMPRODUCT('Basket Weights'!$D$7:$D$59,'Commodity Indices'!I$7:I$59)/SUM('Basket Weights'!$D$7:$D$59) -> 102.23021 | J8: =SUMPRODUCT('Basket Weights'!$D$7:$D$59,'Commodity Indices'!J$7:J$59)/SUM('Basket Weights'!$D$7:$D$59) -> 101.22023 | K8: =SUMPRODUCT('Basket Weights'!$D$7:$D$59,'Commodity Indices'!K$7:K$59)/SUM('Basket Weights'!$D$7:$D$59) -> 102.79694 | L8: =SUMPRODUCT('Basket Weights'!$D$7:$D$59,'Commodity Indices'!L$7:L$59)/SUM('Basket Weights'!$D$7:$D$59) -> 110.44569 | M8: =SUMPRODUCT('Basket Weights'!$D$7:$D$59,'Commodity Indices'!M$7:M$59)/SUM('Basket Weights'!$D$7:$D$59) -> 111.17288 | ... S8: =SUMPRODUCT('Basket Weights'!$D$7:$D$59,'Commodity Indices'!S$7:S$59)/SUM('Basket Weights'!$D$7:$D$59) -> 126.30891 | T8: =IFERROR(S8/R8-1,"") -> 0.017060352 | U8: =IFERROR(S8/F8-1,"") -> 0.26308909
A9: CV | B9: Segment BOM | F9: =SUMPRODUCT('Basket Weights'!$E$7:$E$59,'Commodity Indices'!F$7:F$59)/SUM('Basket Weights'!$E$7:$E$59) -> 100 | G9: =SUMPRODUCT('Basket Weights'!$E$7:$E$59,'Commodity Indices'!G$7:G$59)/SUM('Basket Weights'!$E$7:$E$59) -> 100.19417 | H9: =SUMPRODUCT('Basket Weights'!$E$7:$E$59,'Commodity Indices'!H$7:H$59)/SUM('Basket Weights'!$E$7:$E$59) -> 100.26681 | I9: =SUMPRODUCT('Basket Weights'!$E$7:$E$59,'Commodity Indices'!I$7:I$59)/SUM('Basket Weights'!$E$7:$E$59) -> 100.95501 | J9: =SUMPRODUCT('Basket Weights'!$E$7:$E$59,'Commodity Indices'!J$7:J$59)/SUM('Basket Weights'!$E$7:$E$59) -> 99.627473 | K9: =SUMPRODUCT('Basket Weights'!$E$7:$E$59,'Commodity Indices'!K$7:K$59)/SUM('Basket Weights'!$E$7:$E$59) -> 101.12333 | L9: =SUMPRODUCT('Basket Weights'!$E$7:$E$59,'Commodity Indices'!L$7:L$59)/SUM('Basket Weights'!$E$7:$E$59) -> 108.53655 | M9: =SUMPRODUCT('Basket Weights'!$E$7:$E$59,'Commodity Indices'!M$7:M$59)/SUM('Basket Weights'!$E$7:$E$59) -> 110.12541 | ... S9: =SUMPRODUCT('Basket Weights'!$E$7:$E$59,'Commodity Indices'!S$7:S$59)/SUM('Basket Weights'!$E$7:$E$59) -> 125.26712 | T9: =IFERROR(S9/R9-1,"") -> 0.017516627 | U9: =IFERROR(S9/F9-1,"") -> 0.25267116
A10: Tractor | B10: Segment BOM | F10: =SUMPRODUCT('Basket Weights'!$F$7:$F$59,'Commodity Indices'!F$7:F$59)/SUM('Basket Weights'!$F$7:$F$59) -> 100 | G10: =SUMPRODUCT('Basket Weights'!$F$7:$F$59,'Commodity Indices'!G$7:G$59)/SUM('Basket Weights'!$F$7:$F$59) -> 99.773123 | H10: =SUMPRODUCT('Basket Weights'!$F$7:$F$59,'Commodity Indices'!H$7:H$59)/SUM('Basket Weights'!$F$7:$F$59) -> 99.521514 | I10: =SUMPRODUCT('Basket Weights'!$F$7:$F$59,'Commodity Indices'!I$7:I$59)/SUM('Basket Weights'!$F$7:$F$59) -> 99.311619 | J10: =SUMPRODUCT('Basket Weights'!$F$7:$F$59,'Commodity Indices'!J$7:J$59)/SUM('Basket Weights'!$F$7:$F$59) -> 97.782222 | K10: =SUMPRODUCT('Basket Weights'!$F$7:$F$59,'Commodity Indices'!K$7:K$59)/SUM('Basket Weights'!$F$7:$F$59) -> 98.510933 | L10: =SUMPRODUCT('Basket Weights'!$F$7:$F$59,'Commodity Indices'!L$7:L$59)/SUM('Basket Weights'!$F$7:$F$59) -> 104.46551 | M10: =SUMPRODUCT('Basket Weights'!$F$7:$F$59,'Commodity Indices'!M$7:M$59)/SUM('Basket Weights'!$F$7:$F$59) -> 106.9055 | ... S10: =SUMPRODUCT('Basket Weights'!$F$7:$F$59,'Commodity Indices'!S$7:S$59)/SUM('Basket Weights'!$F$7:$F$59) -> 123.65289 | T10: =IFERROR(S10/R10-1,"") -> 0.015773755 | U10: =IFERROR(S10/F10-1,"") -> 0.23652889
A11: BEV - PV | B11: Segment BOM | F11: =SUMPRODUCT('Basket Weights'!$G$7:$G$59,'Commodity Indices'!F$7:F$59)/SUM('Basket Weights'!$G$7:$G$59) -> 100 | G11: =SUMPRODUCT('Basket Weights'!$G$7:$G$59,'Commodity Indices'!G$7:G$59)/SUM('Basket Weights'!$G$7:$G$59) -> 102.97158 | H11: =SUMPRODUCT('Basket Weights'!$G$7:$G$59,'Commodity Indices'!H$7:H$59)/SUM('Basket Weights'!$G$7:$G$59) -> 105.04319 | I11: =SUMPRODUCT('Basket Weights'!$G$7:$G$59,'Commodity Indices'!I$7:I$59)/SUM('Basket Weights'!$G$7:$G$59) -> 109.22516 | J11: =SUMPRODUCT('Basket Weights'!$G$7:$G$59,'Commodity Indices'!J$7:J$59)/SUM('Basket Weights'!$G$7:$G$59) -> 111.37289 | K11: =SUMPRODUCT('Basket Weights'!$G$7:$G$59,'Commodity Indices'!K$7:K$59)/SUM('Basket Weights'!$G$7:$G$59) -> 116.97693 | L11: =SUMPRODUCT('Basket Weights'!$G$7:$G$59,'Commodity Indices'!L$7:L$59)/SUM('Basket Weights'!$G$7:$G$59) -> 138.90818 | M11: =SUMPRODUCT('Basket Weights'!$G$7:$G$59,'Commodity Indices'!M$7:M$59)/SUM('Basket Weights'!$G$7:$G$59) -> 141.24982 | ... S11: =SUMPRODUCT('Basket Weights'!$G$7:$G$59,'Commodity Indices'!S$7:S$59)/SUM('Basket Weights'!$G$7:$G$59) -> 157.05327 | T11: =IFERROR(S11/R11-1,"") -> 0.00153603 | U11: =IFERROR(S11/F11-1,"") -> 0.57053267
A12: E-2W | B12: Segment BOM | F12: =SUMPRODUCT('Basket Weights'!$H$7:$H$59,'Commodity Indices'!F$7:F$59)/SUM('Basket Weights'!$H$7:$H$59) -> 100 | G12: =SUMPRODUCT('Basket Weights'!$H$7:$H$59,'Commodity Indices'!G$7:G$59)/SUM('Basket Weights'!$H$7:$H$59) -> 103.15196 | H12: =SUMPRODUCT('Basket Weights'!$H$7:$H$59,'Commodity Indices'!H$7:H$59)/SUM('Basket Weights'!$H$7:$H$59) -> 104.91768 | I12: =SUMPRODUCT('Basket Weights'!$H$7:$H$59,'Commodity Indices'!I$7:I$59)/SUM('Basket Weights'!$H$7:$H$59) -> 108.13363 | J12: =SUMPRODUCT('Basket Weights'!$H$7:$H$59,'Commodity Indices'!J$7:J$59)/SUM('Basket Weights'!$H$7:$H$59) -> 110.22408 | K12: =SUMPRODUCT('Basket Weights'!$H$7:$H$59,'Commodity Indices'!K$7:K$59)/SUM('Basket Weights'!$H$7:$H$59) -> 115.93738 | L12: =SUMPRODUCT('Basket Weights'!$H$7:$H$59,'Commodity Indices'!L$7:L$59)/SUM('Basket Weights'!$H$7:$H$59) -> 139.03697 | M12: =SUMPRODUCT('Basket Weights'!$H$7:$H$59,'Commodity Indices'!M$7:M$59)/SUM('Basket Weights'!$H$7:$H$59) -> 141.87955 | ... S12: =SUMPRODUCT('Basket Weights'!$H$7:$H$59,'Commodity Indices'!S$7:S$59)/SUM('Basket Weights'!$H$7:$H$59) -> 158.16364 | T12: =IFERROR(S12/R12-1,"") -> 0.0017851749 | U12: =IFERROR(S12/F12-1,"") -> 0.58163643
A13: SUB-COMPLEX MONITORS
A14: Ferrous | B14: Sub-complex | F14: =SUMPRODUCT('Basket Weights'!$I$7:$I$59,'Commodity Indices'!F$7:F$59)/SUM('Basket Weights'!$I$7:$I$59) -> 100 | G14: =SUMPRODUCT('Basket Weights'!$I$7:$I$59,'Commodity Indices'!G$7:G$59)/SUM('Basket Weights'!$I$7:$I$59) -> 101.13646 | H14: =SUMPRODUCT('Basket Weights'!$I$7:$I$59,'Commodity Indices'!H$7:H$59)/SUM('Basket Weights'!$I$7:$I$59) -> 100.99578 | I14: =SUMPRODUCT('Basket Weights'!$I$7:$I$59,'Commodity Indices'!I$7:I$59)/SUM('Basket Weights'!$I$7:$I$59) -> 99.911704 | J14: =SUMPRODUCT('Basket Weights'!$I$7:$I$59,'Commodity Indices'!J$7:J$59)/SUM('Basket Weights'!$I$7:$I$59) -> 97.973732 | K14: =SUMPRODUCT('Basket Weights'!$I$7:$I$59,'Commodity Indices'!K$7:K$59)/SUM('Basket Weights'!$I$7:$I$59) -> 98.665005 | L14: =SUMPRODUCT('Basket Weights'!$I$7:$I$59,'Commodity Indices'!L$7:L$59)/SUM('Basket Weights'!$I$7:$I$59) -> 104.76599 | M14: =SUMPRODUCT('Basket Weights'!$I$7:$I$59,'Commodity Indices'!M$7:M$59)/SUM('Basket Weights'!$I$7:$I$59) -> 107.38716 | ... S14: =SUMPRODUCT('Basket Weights'!$I$7:$I$59,'Commodity Indices'!S$7:S$59)/SUM('Basket Weights'!$I$7:$I$59) -> 116.26177 | T14: =IFERROR(S14/R14-1,"") -> 0.011638933 | U14: =IFERROR(S14/F14-1,"") -> 0.16261769
A15: Non-Ferrous | B15: Sub-complex | F15: =SUMPRODUCT('Basket Weights'!$J$7:$J$59,'Commodity Indices'!F$7:F$59)/SUM('Basket Weights'!$J$7:$J$59) -> 100 | G15: =SUMPRODUCT('Basket Weights'!$J$7:$J$59,'Commodity Indices'!G$7:G$59)/SUM('Basket Weights'!$J$7:$J$59) -> 100.98107 | H15: =SUMPRODUCT('Basket Weights'!$J$7:$J$59,'Commodity Indices'!H$7:H$59)/SUM('Basket Weights'!$J$7:$J$59) -> 104.47726 | I15: =SUMPRODUCT('Basket Weights'!$J$7:$J$59,'Commodity Indices'!I$7:I$59)/SUM('Basket Weights'!$J$7:$J$59) -> 110.10463 | J15: =SUMPRODUCT('Basket Weights'!$J$7:$J$59,'Commodity Indices'!J$7:J$59)/SUM('Basket Weights'!$J$7:$J$59) -> 111.72385 | K15: =SUMPRODUCT('Basket Weights'!$J$7:$J$59,'Commodity Indices'!K$7:K$59)/SUM('Basket Weights'!$J$7:$J$59) -> 116.91665 | L15: =SUMPRODUCT('Basket Weights'!$J$7:$J$59,'Commodity Indices'!L$7:L$59)/SUM('Basket Weights'!$J$7:$J$59) -> 129.16602 | M15: =SUMPRODUCT('Basket Weights'!$J$7:$J$59,'Commodity Indices'!M$7:M$59)/SUM('Basket Weights'!$J$7:$J$59) -> 126.70678 | ... S15: =SUMPRODUCT('Basket Weights'!$J$7:$J$59,'Commodity Indices'!S$7:S$59)/SUM('Basket Weights'!$J$7:$J$59) -> 142.981 | T15: =IFERROR(S15/R15-1,"") -> 0.037218906 | U15: =IFERROR(S15/F15-1,"") -> 0.42981
A16: PGM | B16: Sub-complex | F16: =SUMPRODUCT('Basket Weights'!$K$7:$K$59,'Commodity Indices'!F$7:F$59)/SUM('Basket Weights'!$K$7:$K$59) -> 100 | G16: =SUMPRODUCT('Basket Weights'!$K$7:$K$59,'Commodity Indices'!G$7:G$59)/SUM('Basket Weights'!$K$7:$K$59) -> 102.36701 | H16: =SUMPRODUCT('Basket Weights'!$K$7:$K$59,'Commodity Indices'!H$7:H$59)/SUM('Basket Weights'!$K$7:$K$59) -> 107.27908 | I16: =SUMPRODUCT('Basket Weights'!$K$7:$K$59,'Commodity Indices'!I$7:I$59)/SUM('Basket Weights'!$K$7:$K$59) -> 122.37254 | J16: =SUMPRODUCT('Basket Weights'!$K$7:$K$59,'Commodity Indices'!J$7:J$59)/SUM('Basket Weights'!$K$7:$K$59) -> 123.27525 | K16: =SUMPRODUCT('Basket Weights'!$K$7:$K$59,'Commodity Indices'!K$7:K$59)/SUM('Basket Weights'!$K$7:$K$59) -> 139.49939 | L16: =SUMPRODUCT('Basket Weights'!$K$7:$K$59,'Commodity Indices'!L$7:L$59)/SUM('Basket Weights'!$K$7:$K$59) -> 174.45739 | M16: =SUMPRODUCT('Basket Weights'!$K$7:$K$59,'Commodity Indices'!M$7:M$59)/SUM('Basket Weights'!$K$7:$K$59) -> 164.78627 | ... S16: =SUMPRODUCT('Basket Weights'!$K$7:$K$59,'Commodity Indices'!S$7:S$59)/SUM('Basket Weights'!$K$7:$K$59) -> 138.87078 | T16: =IFERROR(S16/R16-1,"") -> 0.070325218 | U16: =IFERROR(S16/F16-1,"") -> 0.38870779
A17: Polymers | B17: Sub-complex | F17: =SUMPRODUCT('Basket Weights'!$L$7:$L$59,'Commodity Indices'!F$7:F$59)/SUM('Basket Weights'!$L$7:$L$59) -> 100 | G17: =SUMPRODUCT('Basket Weights'!$L$7:$L$59,'Commodity Indices'!G$7:G$59)/SUM('Basket Weights'!$L$7:$L$59) -> 100.43179 | H17: =SUMPRODUCT('Basket Weights'!$L$7:$L$59,'Commodity Indices'!H$7:H$59)/SUM('Basket Weights'!$L$7:$L$59) -> 99.325772 | I17: =SUMPRODUCT('Basket Weights'!$L$7:$L$59,'Commodity Indices'!I$7:I$59)/SUM('Basket Weights'!$L$7:$L$59) -> 98.183722 | J17: =SUMPRODUCT('Basket Weights'!$L$7:$L$59,'Commodity Indices'!J$7:J$59)/SUM('Basket Weights'!$L$7:$L$59) -> 94.461437 | K17: =SUMPRODUCT('Basket Weights'!$L$7:$L$59,'Commodity Indices'!K$7:K$59)/SUM('Basket Weights'!$L$7:$L$59) -> 91.790462 | L17: =SUMPRODUCT('Basket Weights'!$L$7:$L$59,'Commodity Indices'!L$7:L$59)/SUM('Basket Weights'!$L$7:$L$59) -> 93.419965 | M17: =SUMPRODUCT('Basket Weights'!$L$7:$L$59,'Commodity Indices'!M$7:M$59)/SUM('Basket Weights'!$L$7:$L$59) -> 94.196849 | ... S17: =SUMPRODUCT('Basket Weights'!$L$7:$L$59,'Commodity Indices'!S$7:S$59)/SUM('Basket Weights'!$L$7:$L$59) -> 126.59388 | T17: =IFERROR(S17/R17-1,"") -> -0.011178037 | U17: =IFERROR(S17/F17-1,"") -> 0.2659388
A18: Rubber & CB | B18: Sub-complex | F18: =SUMPRODUCT('Basket Weights'!$M$7:$M$59,'Commodity Indices'!F$7:F$59)/SUM('Basket Weights'!$M$7:$M$59) -> 100 | G18: =SUMPRODUCT('Basket Weights'!$M$7:$M$59,'Commodity Indices'!G$7:G$59)/SUM('Basket Weights'!$M$7:$M$59) -> 95.435995 | H18: =SUMPRODUCT('Basket Weights'!$M$7:$M$59,'Commodity Indices'!H$7:H$59)/SUM('Basket Weights'!$M$7:$M$59) -> 94.024662 | I18: =SUMPRODUCT('Basket Weights'!$M$7:$M$59,'Commodity Indices'!I$7:I$59)/SUM('Basket Weights'!$M$7:$M$59) -> 92.944995 | J18: =SUMPRODUCT('Basket Weights'!$M$7:$M$59,'Commodity Indices'!J$7:J$59)/SUM('Basket Weights'!$M$7:$M$59) -> 91.775831 | K18: =SUMPRODUCT('Basket Weights'!$M$7:$M$59,'Commodity Indices'!K$7:K$59)/SUM('Basket Weights'!$M$7:$M$59) -> 89.664785 | L18: =SUMPRODUCT('Basket Weights'!$M$7:$M$59,'Commodity Indices'!L$7:L$59)/SUM('Basket Weights'!$M$7:$M$59) -> 88.994059 | M18: =SUMPRODUCT('Basket Weights'!$M$7:$M$59,'Commodity Indices'!M$7:M$59)/SUM('Basket Weights'!$M$7:$M$59) -> 91.998575 | ... S18: =SUMPRODUCT('Basket Weights'!$M$7:$M$59,'Commodity Indices'!S$7:S$59)/SUM('Basket Weights'!$M$7:$M$59) -> 137.50324 | T18: =IFERROR(S18/R18-1,"") -> 0.0070707308 | U18: =IFERROR(S18/F18-1,"") -> 0.37503238
A19: Battery Chem | B19: Sub-complex | F19: =SUMPRODUCT('Basket Weights'!$N$7:$N$59,'Commodity Indices'!F$7:F$59)/SUM('Basket Weights'!$N$7:$N$59) -> 100 | G19: =SUMPRODUCT('Basket Weights'!$N$7:$N$59,'Commodity Indices'!G$7:G$59)/SUM('Basket Weights'!$N$7:$N$59) -> 108.94481 | H19: =SUMPRODUCT('Basket Weights'!$N$7:$N$59,'Commodity Indices'!H$7:H$59)/SUM('Basket Weights'!$N$7:$N$59) -> 113.6313 | I19: =SUMPRODUCT('Basket Weights'!$N$7:$N$59,'Commodity Indices'!I$7:I$59)/SUM('Basket Weights'!$N$7:$N$59) -> 125.41971 | J19: =SUMPRODUCT('Basket Weights'!$N$7:$N$59,'Commodity Indices'!J$7:J$59)/SUM('Basket Weights'!$N$7:$N$59) -> 134.36484 | K19: =SUMPRODUCT('Basket Weights'!$N$7:$N$59,'Commodity Indices'!K$7:K$59)/SUM('Basket Weights'!$N$7:$N$59) -> 147.03003 | L19: =SUMPRODUCT('Basket Weights'!$N$7:$N$59,'Commodity Indices'!L$7:L$59)/SUM('Basket Weights'!$N$7:$N$59) -> 200.5542 | M19: =SUMPRODUCT('Basket Weights'!$N$7:$N$59,'Commodity Indices'!M$7:M$59)/SUM('Basket Weights'!$N$7:$N$59) -> 207.46993 | ... S19: =SUMPRODUCT('Basket Weights'!$N$7:$N$59,'Commodity Indices'!S$7:S$59)/SUM('Basket Weights'!$N$7:$N$59) -> 213.8396 | T19: =IFERROR(S19/R19-1,"") -> -0.029167829 | U19: =IFERROR(S19/F19-1,"") -> 1.138396
A20: Energy & Freight | B20: Sub-complex | F20: =SUMPRODUCT('Basket Weights'!$O$7:$O$59,'Commodity Indices'!F$7:F$59)/SUM('Basket Weights'!$O$7:$O$59) -> 100 | G20: =SUMPRODUCT('Basket Weights'!$O$7:$O$59,'Commodity Indices'!G$7:G$59)/SUM('Basket Weights'!$O$7:$O$59) -> 102.19512 | H20: =SUMPRODUCT('Basket Weights'!$O$7:$O$59,'Commodity Indices'!H$7:H$59)/SUM('Basket Weights'!$O$7:$O$59) -> 104.0314 | I20: =SUMPRODUCT('Basket Weights'!$O$7:$O$59,'Commodity Indices'!I$7:I$59)/SUM('Basket Weights'!$O$7:$O$59) -> 101.31695 | J20: =SUMPRODUCT('Basket Weights'!$O$7:$O$59,'Commodity Indices'!J$7:J$59)/SUM('Basket Weights'!$O$7:$O$59) -> 104.12818 | K20: =SUMPRODUCT('Basket Weights'!$O$7:$O$59,'Commodity Indices'!K$7:K$59)/SUM('Basket Weights'!$O$7:$O$59) -> 106.52569 | L20: =SUMPRODUCT('Basket Weights'!$O$7:$O$59,'Commodity Indices'!L$7:L$59)/SUM('Basket Weights'!$O$7:$O$59) -> 104.58755 | M20: =SUMPRODUCT('Basket Weights'!$O$7:$O$59,'Commodity Indices'!M$7:M$59)/SUM('Basket Weights'!$O$7:$O$59) -> 110.9436 | ... S20: =SUMPRODUCT('Basket Weights'!$O$7:$O$59,'Commodity Indices'!S$7:S$59)/SUM('Basket Weights'!$O$7:$O$59) -> 134.74263 | T20: =IFERROR(S20/R20-1,"") -> 0.030085854 | U20: =IFERROR(S20/F20-1,"") -> 0.34742631
A22: BLENDED INDIA AUTO COMPOSITE
A23: India Auto Cost Composite | B23: Segment-weighted blend | F23: =(Assumptions!$C$17*F7+Assumptions!$C$18*F8+Assumptions!$C$19*F9+Assumptions!$C$20*F10+Assumptions!$C$21*F11+Assumptions!$C$22*F12)/Assumptions!$C$23 -> 100 | G23: =(Assumptions!$C$17*G7+Assumptions!$C$18*G8+Assumptions!$C$19*G9+Assumptions!$C$20*G10+Assumptions!$C$21*G11+Assumptions!$C$22*G12)/Assumptions!$C$23 -> 100.77982 | H23: =(Assumptions!$C$17*H7+Assumptions!$C$18*H8+Assumptions!$C$19*H9+Assumptions!$C$20*H10+Assumptions!$C$21*H11+Assumptions!$C$22*H12)/Assumptions!$C$23 -> 101.35718 | I23: =(Assumptions!$C$17*I7+Assumptions!$C$18*I8+Assumptions!$C$19*I9+Assumptions!$C$20*I10+Assumptions!$C$21*I11+Assumptions!$C$22*I12)/Assumptions!$C$23 -> 102.68282 | J23: =(Assumptions!$C$17*J7+Assumptions!$C$18*J8+Assumptions!$C$19*J9+Assumptions!$C$20*J10+Assumptions!$C$21*J11+Assumptions!$C$22*J12)/Assumptions!$C$23 -> 101.99272 | K23: =(Assumptions!$C$17*K7+Assumptions!$C$18*K8+Assumptions!$C$19*K9+Assumptions!$C$20*K10+Assumptions!$C$21*K11+Assumptions!$C$22*K12)/Assumptions!$C$23 -> 104.18126 | L23: =(Assumptions!$C$17*L7+Assumptions!$C$18*L8+Assumptions!$C$19*L9+Assumptions!$C$20*L10+Assumptions!$C$21*L11+Assumptions!$C$22*L12)/Assumptions!$C$23 -> 114.00439 | M23: =(Assumptions!$C$17*M7+Assumptions!$C$18*M8+Assumptions!$C$19*M9+Assumptions!$C$20*M10+Assumptions!$C$21*M11+Assumptions!$C$22*M12)/Assumptions!$C$23 -> 115.3622 | ... S23: =(Assumptions!$C$17*S7+Assumptions!$C$18*S8+Assumptions!$C$19*S9+Assumptions!$C$20*S10+Assumptions!$C$21*S11+Assumptions!$C$22*S12)/Assumptions!$C$23 -> 130.71017 | T23: =IFERROR(S23/R23-1,"") -> 0.014712637 | U23: =IFERROR(S23/F23-1,"") -> 0.3071017
A25: Basket index = SUMPRODUCT(weights, commodity indices) / SUM(weights). Composite = segment weights from Assumptions applied to the six BOM baskets.

Sheet Quarterly Dashboard
A1: QUARTERLY COST DASHBOARD
A2: The output page: where commodity costs sit this quarter versus last quarter and last year.
A4: 1. CURRENT QUARTER BUILD-UP (Q2FY27, Jul-Sep 2026)
A5: Jul-26 and Aug-26 are reported. Sep-26 is grown at the base MoM drift lever on Assumptions.
A6: Basket | B6: Jul-26 (A) | C6: Aug-26 (A) | D6: Sep-26 (E) | E6: Q2FY27E avg
A7: PV (ICE) | B7: ='Basket Monitors'!R7 -> 124.27921 | C7: ='Basket Monitors'!S7 -> 126.55906 | D7: =C7*(1+Assumptions!$C$12) -> 126.55906 | E7: =AVERAGE(B7:D7) -> 125.79911
A8: 2W (ICE) | B8: ='Basket Monitors'!R8 -> 124.19018 | C8: ='Basket Monitors'!S8 -> 126.30891 | D8: =C8*(1+Assumptions!$C$12) -> 126.30891 | E8: =AVERAGE(B8:D8) -> 125.60267
A9: CV | B9: ='Basket Monitors'!R9 -> 123.11063 | C9: ='Basket Monitors'!S9 -> 125.26712 | D9: =C9*(1+Assumptions!$C$12) -> 125.26712 | E9: =AVERAGE(B9:D9) -> 124.54829
A10: Tractor | B10: ='Basket Monitors'!R10 -> 121.73271 | C10: ='Basket Monitors'!S10 -> 123.65289 | D10: =C10*(1+Assumptions!$C$12) -> 123.65289 | E10: =AVERAGE(B10:D10) -> 123.01283
A11: BEV - PV | B11: ='Basket Monitors'!R11 -> 156.8124 | C11: ='Basket Monitors'!S11 -> 157.05327 | D11: =C11*(1+Assumptions!$C$12) -> 157.05327 | E11: =AVERAGE(B11:D11) -> 156.97298
A12: E-2W | B12: ='Basket Monitors'!R12 -> 157.8818 | C12: ='Basket Monitors'!S12 -> 158.16364 | D12: =C12*(1+Assumptions!$C$12) -> 158.16364 | E12: =AVERAGE(B12:D12) -> 158.06969
A13: Ferrous | B13: ='Basket Monitors'!R14 -> 114.92417 | C13: ='Basket Monitors'!S14 -> 116.26177 | D13: =C13*(1+Assumptions!$C$12) -> 116.26177 | E13: =AVERAGE(B13:D13) -> 115.8159
A14: Non-Ferrous | B14: ='Basket Monitors'!R15 -> 137.85036 | C14: ='Basket Monitors'!S15 -> 142.981 | D14: =C14*(1+Assumptions!$C$12) -> 142.981 | E14: =AVERAGE(B14:D14) -> 141.27079
A15: PGM | B15: ='Basket Monitors'!R16 -> 129.74634 | C15: ='Basket Monitors'!S16 -> 138.87078 | D15: =C15*(1+Assumptions!$C$12) -> 138.87078 | E15: =AVERAGE(B15:D15) -> 135.8293
A16: Polymers | B16: ='Basket Monitors'!R17 -> 128.02495 | C16: ='Basket Monitors'!S17 -> 126.59388 | D16: =C16*(1+Assumptions!$C$12) -> 126.59388 | E16: =AVERAGE(B16:D16) -> 127.0709
A17: Rubber & CB | B17: ='Basket Monitors'!R18 -> 136.53782 | C17: ='Basket Monitors'!S18 -> 137.50324 | D17: =C17*(1+Assumptions!$C$12) -> 137.50324 | E17: =AVERAGE(B17:D17) -> 137.18143
A18: Battery Chem | B18: ='Basket Monitors'!R19 -> 220.26422 | C18: ='Basket Monitors'!S19 -> 213.8396 | D18: =C18*(1+Assumptions!$C$12) -> 213.8396 | E18: =AVERAGE(B18:D18) -> 215.98114
A19: Energy & Freight | B19: ='Basket Monitors'!R20 -> 130.80718 | C19: ='Basket Monitors'!S20 -> 134.74263 | D19: =C19*(1+Assumptions!$C$12) -> 134.74263 | E19: =AVERAGE(B19:D19) -> 133.43082
A20: Composite | B20: ='Basket Monitors'!R23 -> 128.81496 | C20: ='Basket Monitors'!S23 -> 130.71017 | D20: =C20*(1+Assumptions!$C$12) -> 130.71017 | E20: =AVERAGE(B20:D20) -> 130.07843
A23: 2. QUARTERLY BASKET LEVELS AND MOVES
A24: Quarterly index = simple average of the three monthly index readings. Q2FY27E per the build-up above.
A25: Basket | B25: Q2FY26 | C25: Q3FY26 | D25: Q4FY26 | E25: Q1FY27 | F25: Q2FY27E | G25: QoQ % | H25: YoY %
A26: PV (ICE) | B26: =AVERAGE('Basket Monitors'!F7:H7) -> 100.5236 | C26: =AVERAGE('Basket Monitors'!I7:K7) -> 101.9298 | D26: =AVERAGE('Basket Monitors'!L7:N7) -> 113.89043 | E26: =AVERAGE('Basket Monitors'!O7:Q7) -> 127.88753 | F26: =E7 -> 125.79911 | G26: =IFERROR(F26/E26-1,"") -> -0.016330108 | H26: =IFERROR(F26/B26-1,"") -> 0.25143851
A27: 2W (ICE) | B27: =AVERAGE('Basket Monitors'!F8:H8) -> 100.48444 | C27: =AVERAGE('Basket Monitors'!I8:K8) -> 102.08246 | D27: =AVERAGE('Basket Monitors'!L8:N8) -> 113.78038 | E27: =AVERAGE('Basket Monitors'!O8:Q8) -> 128.66399 | F27: =E8 -> 125.60267 | G27: =IFERROR(F27/E27-1,"") -> -0.023793147 | H27: =IFERROR(F27/B27-1,"") -> 0.24997128
A28: CV | B28: =AVERAGE('Basket Monitors'!F9:H9) -> 100.15366 | C28: =AVERAGE('Basket Monitors'!I9:K9) -> 100.5686 | D28: =AVERAGE('Basket Monitors'!L9:N9) -> 111.77394 | E28: =AVERAGE('Basket Monitors'!O9:Q9) -> 125.55058 | F28: =E9 -> 124.54829 | G28: =IFERROR(F28/E28-1,"") -> -0.0079831361 | H28: =IFERROR(F28/B28-1,"") -> 0.24357204
A29: Tractor | B29: =AVERAGE('Basket Monitors'!F10:H10) -> 99.764879 | C29: =AVERAGE('Basket Monitors'!I10:K10) -> 98.534925 | D29: =AVERAGE('Basket Monitors'!L10:N10) -> 107.97363 | E29: =AVERAGE('Basket Monitors'!O10:Q10) -> 122.45969 | F29: =E10 -> 123.01283 | G29: =IFERROR(F29/E29-1,"") -> 0.0045169069 | H29: =IFERROR(F29/B29-1,"") -> 0.23302739
A30: BEV - PV | B30: =AVERAGE('Basket Monitors'!F11:H11) -> 102.67159 | C30: =AVERAGE('Basket Monitors'!I11:K11) -> 112.52499 | D30: =AVERAGE('Basket Monitors'!L11:N11) -> 144.1429 | E30: =AVERAGE('Basket Monitors'!O11:Q11) -> 163.35778 | F30: =E11 -> 156.97298 | G30: =IFERROR(F30/E30-1,"") -> -0.039084762 | H30: =IFERROR(F30/B30-1,"") -> 0.52888426
A31: E-2W | B31: =AVERAGE('Basket Monitors'!F12:H12) -> 102.68988 | C31: =AVERAGE('Basket Monitors'!I12:K12) -> 111.4317 | D31: =AVERAGE('Basket Monitors'!L12:N12) -> 145.06088 | E31: =AVERAGE('Basket Monitors'!O12:Q12) -> 164.77296 | F31: =E12 -> 158.06969 | G31: =IFERROR(F31/E31-1,"") -> -0.040681855 | H31: =IFERROR(F31/B31-1,"") -> 0.53929184
A32: Ferrous | B32: =AVERAGE('Basket Monitors'!F14:H14) -> 100.71075 | C32: =AVERAGE('Basket Monitors'!I14:K14) -> 98.850147 | D32: =AVERAGE('Basket Monitors'!L14:N14) -> 107.86525 | E32: =AVERAGE('Basket Monitors'!O14:Q14) -> 116.95649 | F32: =E13 -> 115.8159 | G32: =IFERROR(F32/E32-1,"") -> -0.0097522339 | H32: =IFERROR(F32/B32-1,"") -> 0.14998556
A33: Non-Ferrous | B33: =AVERAGE('Basket Monitors'!F15:H15) -> 101.81944 | C33: =AVERAGE('Basket Monitors'!I15:K15) -> 112.91504 | D33: =AVERAGE('Basket Monitors'!L15:N15) -> 130.11491 | E33: =AVERAGE('Basket Monitors'!O15:Q15) -> 146.1421 | F33: =E14 -> 141.27079 | G33: =IFERROR(F33/E33-1,"") -> -0.033332688 | H33: =IFERROR(F33/B33-1,"") -> 0.38746376
A34: PGM | B34: =AVERAGE('Basket Monitors'!F16:H16) -> 103.21536 | C34: =AVERAGE('Basket Monitors'!I16:K16) -> 128.38239 | D34: =AVERAGE('Basket Monitors'!L16:N16) -> 166.76472 | E34: =AVERAGE('Basket Monitors'!O16:Q16) -> 147.19421 | F34: =E15 -> 135.8293 | G34: =IFERROR(F34/E34-1,"") -> -0.077210333 | H34: =IFERROR(F34/B34-1,"") -> 0.31597947
A35: Polymers | B35: =AVERAGE('Basket Monitors'!F17:H17) -> 99.919187 | C35: =AVERAGE('Basket Monitors'!I17:K17) -> 94.811874 | D35: =AVERAGE('Basket Monitors'!L17:N17) -> 104.37773 | E35: =AVERAGE('Basket Monitors'!O17:Q17) -> 130.92893 | F35: =E16 -> 127.0709 | G35: =IFERROR(F35/E35-1,"") -> -0.02946654 | H35: =IFERROR(F35/B35-1,"") -> 0.27173676
A36: Rubber & CB | B36: =AVERAGE('Basket Monitors'!F18:H18) -> 96.486886 | C36: =AVERAGE('Basket Monitors'!I18:K18) -> 91.46187 | D36: =AVERAGE('Basket Monitors'!L18:N18) -> 92.875787 | E36: =AVERAGE('Basket Monitors'!O18:Q18) -> 131.40959 | F36: =E17 -> 137.18143 | G36: =IFERROR(F36/E36-1,"") -> 0.043922518 | H36: =IFERROR(F36/B36-1,"") -> 0.42176245
A37: Battery Chem | B37: =AVERAGE('Basket Monitors'!F19:H19) -> 107.52537 | C37: =AVERAGE('Basket Monitors'!I19:K19) -> 135.60486 | D37: =AVERAGE('Basket Monitors'!L19:N19) -> 210.13379 | E37: =AVERAGE('Basket Monitors'!O19:Q19) -> 235.1267 | F37: =E18 -> 215.98114 | G37: =IFERROR(F37/E37-1,"") -> -0.081426586 | H37: =IFERROR(F37/B37-1,"") -> 1.0086528
A38: Energy & Freight | B38: =AVERAGE('Basket Monitors'!F20:H20) -> 102.0755 | C38: =AVERAGE('Basket Monitors'!I20:K20) -> 103.99027 | D38: =AVERAGE('Basket Monitors'!L20:N20) -> 114.59011 | E38: =AVERAGE('Basket Monitors'!O20:Q20) -> 140.0483 | F38: =E19 -> 133.43082 | G38: =IFERROR(F38/E38-1,"") -> -0.047251435 | H38: =IFERROR(F38/B38-1,"") -> 0.30717762
A39: Composite | B39: =AVERAGE('Basket Monitors'!F23:H23) -> 100.71233 | C39: =AVERAGE('Basket Monitors'!I23:K23) -> 102.95226 | D39: =AVERAGE('Basket Monitors'!L23:N23) -> 117.64225 | E39: =AVERAGE('Basket Monitors'!O23:Q23) -> 132.62923 | F39: =E20 -> 130.07843 | G39: =IFERROR(F39/E39-1,"") -> -0.019232548 | H39: =IFERROR(F39/B39-1,"") -> 0.29158397
A42: 3. QoQ HISTORY BY BASKET (%)
A43: Basket | B43: Q3FY26 | C43: Q4FY26 | D43: Q1FY27 | E43: Q2FY27E
A44: PV (ICE) | B44: =IFERROR(C26/B26-1,"") -> 0.01398868 | C44: =IFERROR(D26/C26-1,"") -> 0.11734184 | D44: =IFERROR(E26/D26-1,"") -> 0.1228997 | E44: =IFERROR(F26/E26-1,"") -> -0.016330108
A45: 2W (ICE) | B45: =IFERROR(C27/B27-1,"") -> 0.015903114 | C45: =IFERROR(D27/C27-1,"") -> 0.11459291 | D45: =IFERROR(E27/D27-1,"") -> 0.13080993 | E45: =IFERROR(F27/E27-1,"") -> -0.023793147
A46: CV | B46: =IFERROR(C28/B28-1,"") -> 0.0041430919 | C46: =IFERROR(D28/C28-1,"") -> 0.11141983 | D46: =IFERROR(E28/D28-1,"") -> 0.12325445 | E46: =IFERROR(F28/E28-1,"") -> -0.0079831361
A47: Tractor | B47: =IFERROR(C29/B29-1,"") -> -0.012328527 | C47: =IFERROR(D29/C29-1,"") -> 0.095790433 | D47: =IFERROR(E29/D29-1,"") -> 0.13416296 | E47: =IFERROR(F29/E29-1,"") -> 0.0045169069
A48: BEV - PV | B48: =IFERROR(C30/B30-1,"") -> 0.095970089 | C48: =IFERROR(D30/C30-1,"") -> 0.28098565 | D48: =IFERROR(E30/D30-1,"") -> 0.13330437 | E48: =IFERROR(F30/E30-1,"") -> -0.039084762
A49: E-2W | B49: =IFERROR(C31/B31-1,"") -> 0.085128322 | C49: =IFERROR(D31/C31-1,"") -> 0.3017919 | D49: =IFERROR(E31/D31-1,"") -> 0.13588835 | E49: =IFERROR(F31/E31-1,"") -> -0.040681855
A50: Ferrous | B50: =IFERROR(C32/B32-1,"") -> -0.018474691 | C50: =IFERROR(D32/C32-1,"") -> 0.091199685 | D50: =IFERROR(E32/D32-1,"") -> 0.084283328 | E50: =IFERROR(F32/E32-1,"") -> -0.0097522339
A51: Non-Ferrous | B51: =IFERROR(C33/B33-1,"") -> 0.10897328 | C51: =IFERROR(D33/C33-1,"") -> 0.15232576 | D51: =IFERROR(E33/D33-1,"") -> 0.12317716 | E51: =IFERROR(F33/E33-1,"") -> -0.033332688
A52: PGM | B52: =IFERROR(C34/B34-1,"") -> 0.24383026 | C52: =IFERROR(D34/C34-1,"") -> 0.29896879 | D52: =IFERROR(E34/D34-1,"") -> -0.117354 | E52: =IFERROR(F34/E34-1,"") -> -0.077210333
A53: Polymers | B53: =IFERROR(C35/B35-1,"") -> -0.051114437 | C53: =IFERROR(D35/C35-1,"") -> 0.10089297 | D53: =IFERROR(E35/D35-1,"") -> 0.25437611 | E53: =IFERROR(F35/E35-1,"") -> -0.02946654
A54: Rubber & CB | B54: =IFERROR(C36/B36-1,"") -> -0.052079776 | C54: =IFERROR(D36/C36-1,"") -> 0.015459088 | D54: =IFERROR(E36/D36-1,"") -> 0.41489612 | E54: =IFERROR(F36/E36-1,"") -> 0.043922518
A55: Battery Chem | B55: =IFERROR(C37/B37-1,"") -> 0.26114294 | C55: =IFERROR(D37/C37-1,"") -> 0.5496037 | D55: =IFERROR(E37/D37-1,"") -> 0.11893808 | E55: =IFERROR(F37/E37-1,"") -> -0.081426586
... A57: Composite | B57: =IFERROR(C39/B39-1,"") -> 0.022240892 | C57: =IFERROR(D39/C39-1,"") -> 0.14268739 | D57: =IFERROR(E39/D39-1,"") -> 0.12739452 | E57: =IFERROR(F39/E39-1,"") -> -0.019232548
A60: 4. COMMODITY-LEVEL QUARTERLY TABLE (index, base = 100)
