Workbook

Sheet Read Me
A1: India Auto OEMs — Manufacturing Capacity Database, FY10–FY26
A2: 12 OEMs | Company-level and plant-level capacity history, event logs, platforms and forward pipeline | Compiled 14-Oct-2026
A4: WHAT THIS IS
A5: Purpose | B5: One-stop reference for installed capacity, plant footprint, capacity events, platforms and announced additions across 12 Indian OEMs, built for capacity forecasting and utilisation analysis.
A6: Coverage | B6: Maruti Suzuki, Hyundai Motor India, M&M (SUV), Tata Motors PV, Tata Motors CV, Ashok Leyland, Bajaj Auto, TVS Motor, Royal Enfield (Eicher), Hero MotoCorp, Ola Electric, Ather Energy.
A7: Sheet map | B7: Summary (cross-company comparison, outlook tiers, charts) -> one sheet per OEM (sections A–H) -> Gap Register (what is missing and where to find it) -> Source Log (every ID cited) -> Chart Data (links feeding charts).
A9: OEM SHEET LAYOUT
A10: A. Snapshot | B10: Latest disclosed capacity, FY26 volume and utilisation, outlook base, company target and a one-line bottom line.
A11: B. History FY10–FY26 | B11: Row 19 is the capacity series used everywhere else. Rows 21–24 hold actual production and sales. Rows 25–28 are formulas. Row 30 cites source IDs per year; row 31 annotates each year.
A12: C. Plant matrix | B12: Plant-level capacity (and production where disclosed) by fiscal year. Only disclosed points are entered — gaps are deliberate.
A13: D–G | B13: Plant register, chronological capacity event log, platform/model/plant allocation, and forward pipeline split into certainty tiers.
A14: H. Analyst notes | B14: Interpretation, data caveats and what to check next.
A16: CONVENTIONS
A17: Fiscal year | B17: FY = year ending 31 March (FY26 = Apr-2025 to Mar-2026).
A18: Placement | B18: Capacity sits in the FY whose year-end it represents. A statement made in Apr–Jul with no intervening event is placed at the prior year-end (e.g., May-2016 HMIL 680k -> FY16). Post-FY26 events (FY27 YTD) appear in the event log and pipeline, not in row 19.
A19: Units | B19: Vehicles per annum unless stated. M&M discloses units/month — annualised x12 by formula. Ola cell capacity is in GWh and never summed with vehicles.
A20: Capacity definitions | B20: Companies use 'installed capacity', 'production ability', 'operational capacity' or 'design capacity' inconsistently. The basis code (row 20) and the snapshot definition record which one is used.
A21: Utilisation | B21: Three formula variants: production ÷ FY-end capacity (company convention), production ÷ average of opening and closing capacity (better in commissioning years), and sales ÷ FY-end capacity (fallback where production is undisclosed).
A22: Outlook tiers | B22: Tier 1 = commissioned after FY26 or under execution. Tier 2 = announced with site/timeline. Memo = targets, GWh items, shared or unquantified items — excluded from sums. 'Gap to target' = company target − (base + Tier 1 + Tier 2).
A24: COLOUR CODES
A25: Blue text | B25: Hard-coded input taken from a cited source.
A26: Black text | B26: Formula.
A27: Green text | B27: Link to another sheet.
A28: Orange fill | B28: Verify: lower-tier source, lower bound, or inferred date — use with care.
A29: Light blue fill | B29: Bracketed carry: identical disclosures before and after with no change announced in between (basis code marked *).
A31: SOURCE TIERS
A32: A | B32: Statutory/exchange filing, annual report, offer document (DRHP/RHP), SEC 20-F.
A33: B | B33: Company press release or company-published material.
A34: C | B34: Reputable media reporting company statements.
A35: D | B35: Secondary aggregator or encyclopaedic source — flagged for verification.
A37: WHY THERE ARE GAPS
A38: Disclosure regime | B38: Under the old Schedule VI (to FY11), Indian companies disclosed licensed and installed capacity in the notes to accounts. Revised Schedule VI (from FY12) dropped this, so capacity disclosure became voluntary — the main reason company totals thin out from FY12 for Tata, Ashok Leyland, Hero and TVS.
A39: No estimation | B39: Missing years are left blank. No interpolation, no analyst estimates in historical rows. The Gap Register lists each missing series and the document most likely to fill it.
A40: Volumes | B40: Production is used where disclosed; otherwise sales/dispatches; for EV pure-plays, retail registrations (labelled). Pre-FY12 Tata volumes are global 'Tata & other brand' figures and not like-for-like.

Sheet Summary
A1: Summary — Manufacturing capacity across 12 Indian OEMs
A2: All figures link to OEM sheets (green). Units: vehicles p.a. FY = year to 31-Mar. As of 14-Oct-2026.
A4: KEY TAKEAWAYS
A5: PV build cycle. | C5: ="Maruti, Hyundai, M&M and Tata PV exit FY26 with "&TEXT(C56/1000000,"0.0")&"m units of capacity; Tier 1 + Tier 2 projects take this to "&TEXT(H56/1000000,"0.0")&"m (+"&TEXT(H56/C56-1,"0%")&"), led by Maruti and M&M." -> Maruti, Hyundai, M&M and Tata PV exit FY26 with 5.1m units of capacity; Tier 1 + Tier 2 projects take this to 7.8m (+53%), led by Maruti and M&M.
A6: Utilisation splits the sector. | C6: ="FY26 utilisation is tight at Maruti ("&TEXT(L29,"0%")&"), TVS ("&TEXT(L36,"0%")&"), M&M ("&TEXT(L31,"0%")&") and Royal Enfield ("&TEXT(L37,"0%")&"); loose at Ola ("&TEXT(L39,"0%")&"), Ather ("&TEXT(L40,"0%")&"), Bajaj ("&TEXT(L35,"0%")&"), Tata PV ("&TEXT(L32,"0%")&") and Hyundai ("&TEXT(L30,"0%")&", diluted by Talegaon)." -> FY26 utilisation is tight at Maruti (98%), TVS (87%), M&M (85%) and Royal Enfield (85%); loose at Ola (16%), Ather (57%), Bajaj (71%), Tata PV (71%) and Hyundai (77%, diluted by Talegaon).
A7: Disclosure is the binding data constraint. | C7: ="Since Revised Schedule VI (FY12) capacity disclosure is voluntary: Tata CV, Ashok Leyland and Hero have no current company total in sources reviewed; see Gap Register for the documents that fill each series." -> Since Revised Schedule VI (FY12) capacity disclosure is voluntary: Tata CV, Ashok Leyland and Hero have no current company total in sources reviewed; see Gap Register for the documents that fill each series.
A8: 2W EV capacity: overbuilt at Ola, underbuilt elsewhere. | C8: ="Ola runs at "&TEXT(L39,"0%")&" of its 1.0m line while others add EV capacity: Bajaj Chetak 50k -> 60k/month, TVS EV to 50k/month, Hero Vida 25k -> 50k+/month, Ather +500k at AURIC (Q3FY27)." -> Ola runs at 16% of its 1.0m line while others add EV capacity: Bajaj Chetak 50k -> 60k/month, TVS EV to 50k/month, Hero Vida 25k -> 50k+/month, Ather +500k at AURIC (Q3FY27).
A9: Targets are mostly backed by named projects. | C9: ="Maruti's gap to 4.0m is "&TEXT(M44/1000000,"0.0")&"m; Tata PV's gap to 1.3m is "&TEXT(M47/1000,"0")&"k (debottlenecking not yet quantified); M&M's visible pipeline exceeds its 2x target by "&TEXT(-M46/1000,"0")&"k." -> Maruti's gap to 4.0m is 0.1m; Tata PV's gap to 1.3m is 100k (debottlenecking not yet quantified); M&M's visible pipeline exceeds its 2x target by 36k.
A11: 1. INSTALLED CAPACITY, FY-END, FY10–FY26 (units p.a.; blank = not disclosed in sources reviewed)
A12: Company | B12: Segment | C12: FY10 | D12: FY11 | E12: FY12 | F12: FY13 | G12: FY14 | H12: FY15 | I12: FY16 | J12: FY17 | K12: FY18 | L12: FY19 | M12: FY20 | N12: FY21 | O12: FY22 | P12: FY23 | Q12: FY24 | R12: FY25 | S12: FY26 | T12: Years disclosed (of 17) | U12: Capacity definition
A13: Maruti Suzuki | B13: PV | C13: =IF(ISNUMBER('Maruti Suzuki'!C19),'Maruti Suzuki'!C19,"") -> 1000000 | D13: =IF(ISNUMBER('Maruti Suzuki'!D19),'Maruti Suzuki'!D19,"") -> 1200000 | E13: =IF(ISNUMBER('Maruti Suzuki'!E19),'Maruti Suzuki'!E19,"") | F13: =IF(ISNUMBER('Maruti Suzuki'!F19),'Maruti Suzuki'!F19,"") | G13: =IF(ISNUMBER('Maruti Suzuki'!G19),'Maruti Suzuki'!G19,"") | H13: =IF(ISNUMBER('Maruti Suzuki'!H19),'Maruti Suzuki'!H19,"") -> 1500000 | I13: =IF(ISNUMBER('Maruti Suzuki'!I19),'Maruti Suzuki'!I19,"") -> 1500000 | J13: =IF(ISNUMBER('Maruti Suzuki'!J19),'Maruti Suzuki'!J19,"") -> 1750000 | ... S13: =IF(ISNUMBER('Maruti Suzuki'!S19),'Maruti Suzuki'!S19,"") -> 2400000 | T13: =COUNT(C13:S13) -> 14 | U13: ='Maruti Suzuki'!C7 -> Annual vehicle production capacity as stated by MSIL/Suzuki (two-shift basis), all four sites
A14: Hyundai India | B14: PV | C14: =IF(ISNUMBER('Hyundai India'!C19),'Hyundai India'!C19,"") -> 600000 | D14: =IF(ISNUMBER('Hyundai India'!D19),'Hyundai India'!D19,"") | E14: =IF(ISNUMBER('Hyundai India'!E19),'Hyundai India'!E19,"") | F14: =IF(ISNUMBER('Hyundai India'!F19),'Hyundai India'!F19,"") | G14: =IF(ISNUMBER('Hyundai India'!G19),'Hyundai India'!G19,"") | H14: =IF(ISNUMBER('Hyundai India'!H19),'Hyundai India'!H19,"") | I14: =IF(ISNUMBER('Hyundai India'!I19),'Hyundai India'!I19,"") -> 680000 | J14: =IF(ISNUMBER('Hyundai India'!J19),'Hyundai India'!J19,"") | ... S14: =IF(ISNUMBER('Hyundai India'!S19),'Hyundai India'!S19,"") -> 994000 | T14: =COUNT(C14:S14) -> 11 | U14: ='Hyundai India'!C7 -> Installed annual vehicle capacity per HMIL (DRHP/AR basis)
A15: M&M | B15: PV | C15: =IF(ISNUMBER('M&M'!C19),'M&M'!C19,"") | D15: =IF(ISNUMBER('M&M'!D19),'M&M'!D19,"") | E15: =IF(ISNUMBER('M&M'!E19),'M&M'!E19,"") | F15: =IF(ISNUMBER('M&M'!F19),'M&M'!F19,"") | G15: =IF(ISNUMBER('M&M'!G19),'M&M'!G19,"") | H15: =IF(ISNUMBER('M&M'!H19),'M&M'!H19,"") | I15: =IF(ISNUMBER('M&M'!I19),'M&M'!I19,"") | J15: =IF(ISNUMBER('M&M'!J19),'M&M'!J19,"") | ... S15: =IF(ISNUMBER('M&M'!S19),'M&M'!S19,"") -> 774000 | T15: =COUNT(C15:S15) -> 6 | U15: ='M&M'!C7 -> Operational SUV capacity, units/month x 12 (ICE 56.5k + BEV 8k at FY26 exit)
A16: Tata PV | B16: PV | C16: =IF(ISNUMBER('Tata PV'!C19),'Tata PV'!C19,"") | D16: =IF(ISNUMBER('Tata PV'!D19),'Tata PV'!D19,"") | E16: =IF(ISNUMBER('Tata PV'!E19),'Tata PV'!E19,"") | F16: =IF(ISNUMBER('Tata PV'!F19),'Tata PV'!F19,"") | G16: =IF(ISNUMBER('Tata PV'!G19),'Tata PV'!G19,"") | H16: =IF(ISNUMBER('Tata PV'!H19),'Tata PV'!H19,"") | I16: =IF(ISNUMBER('Tata PV'!I19),'Tata PV'!I19,"") | J16: =IF(ISNUMBER('Tata PV'!J19),'Tata PV'!J19,"") | ... S16: =IF(ISNUMBER('Tata PV'!S19),'Tata PV'!S19,"") -> 900000 | T16: =COUNT(C16:S16) -> 2 | U16: ='Tata PV'!C7 -> Installed PV capacity per management commentary (c.0.9m); Investor Day 2024 cited '1mn+' incl. expandable Sanand-2
A17: Tata CV | B17: CV | C17: =IF(ISNUMBER('Tata CV'!C19),'Tata CV'!C19,"") | D17: =IF(ISNUMBER('Tata CV'!D19),'Tata CV'!D19,"") | E17: =IF(ISNUMBER('Tata CV'!E19),'Tata CV'!E19,"") | F17: =IF(ISNUMBER('Tata CV'!F19),'Tata CV'!F19,"") | G17: =IF(ISNUMBER('Tata CV'!G19),'Tata CV'!G19,"") | H17: =IF(ISNUMBER('Tata CV'!H19),'Tata CV'!H19,"") | I17: =IF(ISNUMBER('Tata CV'!I19),'Tata CV'!I19,"") | J17: =IF(ISNUMBER('Tata CV'!J19),'Tata CV'!J19,"") | ... S17: =IF(ISNUMBER('Tata CV'!S19),'Tata CV'!S19,"") | T17: =COUNT(C17:S17) -> 0 | U17: ='Tata CV'!C7 -> No consolidated CV installed capacity found in sources reviewed
A18: Ashok Leyland | B18: CV | C18: =IF(ISNUMBER('Ashok Leyland'!C19),'Ashok Leyland'!C19,"") | D18: =IF(ISNUMBER('Ashok Leyland'!D19),'Ashok Leyland'!D19,"") -> 150000 | E18: =IF(ISNUMBER('Ashok Leyland'!E19),'Ashok Leyland'!E19,"") | F18: =IF(ISNUMBER('Ashok Leyland'!F19),'Ashok Leyland'!F19,"") | G18: =IF(ISNUMBER('Ashok Leyland'!G19),'Ashok Leyland'!G19,"") | H18: =IF(ISNUMBER('Ashok Leyland'!H19),'Ashok Leyland'!H19,"") | I18: =IF(ISNUMBER('Ashok Leyland'!I19),'Ashok Leyland'!I19,"") | J18: =IF(ISNUMBER('Ashok Leyland'!J19),'Ashok Leyland'!J19,"") | ... S18: =IF(ISNUMBER('Ashok Leyland'!S19),'Ashok Leyland'!S19,"") | T18: =COUNT(C18:S18) -> 1 | U18: ='Ashok Leyland'!C7 -> Installed capacity across seven plants (2010); no later company total found
A19: Bajaj Auto | B19: 2W/3W | C19: =IF(ISNUMBER('Bajaj Auto'!C19),'Bajaj Auto'!C19,"") | D19: =IF(ISNUMBER('Bajaj Auto'!D19),'Bajaj Auto'!D19,"") -> 5040000 | E19: =IF(ISNUMBER('Bajaj Auto'!E19),'Bajaj Auto'!E19,"") -> 5040000 | F19: =IF(ISNUMBER('Bajaj Auto'!F19),'Bajaj Auto'!F19,"") | G19: =IF(ISNUMBER('Bajaj Auto'!G19),'Bajaj Auto'!G19,"") | H19: =IF(ISNUMBER('Bajaj Auto'!H19),'Bajaj Auto'!H19,"") -> 6060000 | I19: =IF(ISNUMBER('Bajaj Auto'!I19),'Bajaj Auto'!I19,"") | J19: =IF(ISNUMBER('Bajaj Auto'!J19),'Bajaj Auto'!J19,"") | ... S19: =IF(ISNUMBER('Bajaj Auto'!S19),'Bajaj Auto'!S19,"") -> 7200000 | T19: =COUNT(C19:S19) -> 6 | U19: ='Bajaj Auto'!C7 -> Installed capacity, 2W + 3W (company statements)
A20: TVS Motor | B20: 2W/3W | C20: =IF(ISNUMBER('TVS Motor'!C19),'TVS Motor'!C19,"") | D20: =IF(ISNUMBER('TVS Motor'!D19),'TVS Motor'!D19,"") | E20: =IF(ISNUMBER('TVS Motor'!E19),'TVS Motor'!E19,"") | F20: =IF(ISNUMBER('TVS Motor'!F19),'TVS Motor'!F19,"") | G20: =IF(ISNUMBER('TVS Motor'!G19),'TVS Motor'!G19,"") | H20: =IF(ISNUMBER('TVS Motor'!H19),'TVS Motor'!H19,"") | I20: =IF(ISNUMBER('TVS Motor'!I19),'TVS Motor'!I19,"") | J20: =IF(ISNUMBER('TVS Motor'!J19),'TVS Motor'!J19,"") | ... S20: =IF(ISNUMBER('TVS Motor'!S19),'TVS Motor'!S19,"") -> 6800000 | T20: =COUNT(C20:S20) -> 2 | U20: ='TVS Motor'!C7 -> Total annual capacity per management (May-2026); earlier website figures split 2W/3W
A21: Royal Enfield | B21: 2W | C21: =IF(ISNUMBER('Royal Enfield'!C19),'Royal Enfield'!C19,"") | D21: =IF(ISNUMBER('Royal Enfield'!D19),'Royal Enfield'!D19,"") | E21: =IF(ISNUMBER('Royal Enfield'!E19),'Royal Enfield'!E19,"") | F21: =IF(ISNUMBER('Royal Enfield'!F19),'Royal Enfield'!F19,"") | G21: =IF(ISNUMBER('Royal Enfield'!G19),'Royal Enfield'!G19,"") | H21: =IF(ISNUMBER('Royal Enfield'!H19),'Royal Enfield'!H19,"") | I21: =IF(ISNUMBER('Royal Enfield'!I19),'Royal Enfield'!I19,"") | J21: =IF(ISNUMBER('Royal Enfield'!J19),'Royal Enfield'!J19,"") | ... S21: =IF(ISNUMBER('Royal Enfield'!S19),'Royal Enfield'!S19,"") -> 1460000 | T21: =COUNT(C21:S21) -> 3 | U21: ='Royal Enfield'!C7 -> Annual motorcycle capacity per Eicher ('around 14.6 lakh')
A22: Hero MotoCorp | B22: 2W | C22: =IF(ISNUMBER('Hero MotoCorp'!C19),'Hero MotoCorp'!C19,"") | D22: =IF(ISNUMBER('Hero MotoCorp'!D19),'Hero MotoCorp'!D19,"") | E22: =IF(ISNUMBER('Hero MotoCorp'!E19),'Hero MotoCorp'!E19,"") | F22: =IF(ISNUMBER('Hero MotoCorp'!F19),'Hero MotoCorp'!F19,"") | G22: =IF(ISNUMBER('Hero MotoCorp'!G19),'Hero MotoCorp'!G19,"") | H22: =IF(ISNUMBER('Hero MotoCorp'!H19),'Hero MotoCorp'!H19,"") -> 7650000 | I22: =IF(ISNUMBER('Hero MotoCorp'!I19),'Hero MotoCorp'!I19,"") | J22: =IF(ISNUMBER('Hero MotoCorp'!J19),'Hero MotoCorp'!J19,"") | ... S22: =IF(ISNUMBER('Hero MotoCorp'!S19),'Hero MotoCorp'!S19,"") | T22: =COUNT(C22:S22) -> 2 | U22: ='Hero MotoCorp'!C7 -> Plant-wise design capacity (11.6m); operational 9.1m at Mar-2020 per secondary source
A23: Ola Electric | B23: 2W-EV | C23: =IF(ISNUMBER('Ola Electric'!C19),'Ola Electric'!C19,"") | D23: =IF(ISNUMBER('Ola Electric'!D19),'Ola Electric'!D19,"") | E23: =IF(ISNUMBER('Ola Electric'!E19),'Ola Electric'!E19,"") | F23: =IF(ISNUMBER('Ola Electric'!F19),'Ola Electric'!F19,"") | G23: =IF(ISNUMBER('Ola Electric'!G19),'Ola Electric'!G19,"") | H23: =IF(ISNUMBER('Ola Electric'!H19),'Ola Electric'!H19,"") | I23: =IF(ISNUMBER('Ola Electric'!I19),'Ola Electric'!I19,"") | J23: =IF(ISNUMBER('Ola Electric'!J19),'Ola Electric'!J19,"") | ... S23: =IF(ISNUMBER('Ola Electric'!S19),'Ola Electric'!S19,"") | T23: =COUNT(C23:S23) -> 2 | U23: ='Ola Electric'!C7 -> Futurefactory installed vehicle capacity (DRHP); cells tracked separately in GWh
A24: Ather Energy | B24: 2W-EV | C24: =IF(ISNUMBER('Ather Energy'!C19),'Ather Energy'!C19,"") | D24: =IF(ISNUMBER('Ather Energy'!D19),'Ather Energy'!D19,"") | E24: =IF(ISNUMBER('Ather Energy'!E19),'Ather Energy'!E19,"") | F24: =IF(ISNUMBER('Ather Energy'!F19),'Ather Energy'!F19,"") | G24: =IF(ISNUMBER('Ather Energy'!G19),'Ather Energy'!G19,"") | H24: =IF(ISNUMBER('Ather Energy'!H19),'Ather Energy'!H19,"") | I24: =IF(ISNUMBER('Ather Energy'!I19),'Ather Energy'!I19,"") | J24: =IF(ISNUMBER('Ather Energy'!J19),'Ather Energy'!J19,"") | ... S24: =IF(ISNUMBER('Ather Energy'!S19),'Ather Energy'!S19,"") -> 420000 | T24: =COUNT(C24:S24) -> 5 | U24: ='Ather Energy'!C7 -> Hosur vehicle assembly capacity (c.35k/month)
A25: Orange/blue flags on the OEM sheets (verify / bracketed carry) are not repeated here. M&M = SUV operational capacity (monthly x12); Ola = Futurefactory vehicles only.
A27: 2. LATEST SNAPSHOT, FY26 UTILISATION AND CAPACITY GROWTH
A28: Company | B28: Segment | C28: Latest disclosed capacity | D28: As of | F28: Vehicle assembly sites | I28: FY26 volume | J28: Volume basis | L28: FY26 utilisation | M28: First FY in series | N28: Capacity (first) | O28: Last FY in series | P28: Capacity (last) | Q28: CAGR first -> last | R28: Bottom line
A29: Maruti Suzuki | B29: PV | C29: ='Maruti Suzuki'!C5 -> 2900000 | D29: ='Maruti Suzuki'!C6 -> 30-Jul-2026 | F29: ='Maruti Suzuki'!C8 -> 4 — Gurugram, Manesar, Kharkhoda (Haryana); Hansalpur (Gujarat). 5th site (Khoraj, Gujarat) in land stage | I29: ='Maruti Suzuki'!C9 -> 2340000 | J29: ='Maruti Suzuki'!C10 -> Production (FY26, company: >23.4 lakh) | L29: ='Maruti Suzuki'!C11 -> 0.975 | M29: FY10 | N29: ='Maruti Suzuki'!C19 -> 1000000 | O29: FY26 | P29: ='Maruti Suzuki'!S19 -> 2400000 | Q29: =IFERROR((P29/N29)^(1/(VALUE(RIGHT(O29,2))-VALUE(RIGHT(M29,2))))-1,"") -> 0.056241441 | R29: ='Maruti Suzuki'!C15 -> Capacity, not demand, is the binding constraint. FY26 output of 2.34m runs at c.94% of average installed capacity with c.190k orders pending at year-end. Two 250k plants (Kharkhoda-2, Hansalpur-D) are already live in FY27, and announced sites (Kharkhoda to 1m, Khoraj 1m, net of the Gurugram exit) cover almost all of the 4m FY31 target.
A30: Hyundai India | B30: PV | C30: ='Hyundai India'!C5 -> 994000 | D30: ='Hyundai India'!C6 -> FY26 (Mar-2026) | F30: ='Hyundai India'!C8 -> 2 — Chennai (Plants 1 & 2), Talegaon/Pune | I30: ='Hyundai India'!C9 -> 769280 | J30: ='Hyundai India'!C10 -> Production (FY26 AR, plant-wise) | L30: ='Hyundai India'!C11 -> 0.77392354 | M30: FY10 | N30: ='Hyundai India'!C19 -> 600000 | O30: FY26 | P30: ='Hyundai India'!S19 -> 994000 | Q30: =IFERROR((P30/N30)^(1/(VALUE(RIGHT(O30,2))-VALUE(RIGHT(M30,2))))-1,"") -> 0.032053464 | R30: ='Hyundai India'!C15 -> Talegaon resets the denominator. Capacity rises 21% to 994k in FY26 while output grows <1%; utilisation on year-end capacity falls to c.77%. The FY27-FY28 debate is about filling Pune and Chennai Plant 1, not adding new capacity.
A31: M&M | B31: PV | C31: ='M&M'!C5 -> 774000 | D31: ='M&M'!C6 -> FY26 exit (64.5k/month) | F31: ='M&M'!C8 -> SUVs: Chakan, Nashik (+ Haridwar/Zaheerabad under MLMML); Nagpur from 2028 | I31: ='M&M'!C9 -> 660276 | J31: ='M&M'!C10 -> Domestic SUV sales (FY26) — exports excluded | L31: ='M&M'!C11 -> 0.85306977 | M31: FY20 | N31: ='M&M'!M19 -> 228000 | O31: FY26 | P31: ='M&M'!S19 -> 774000 | Q31: =IFERROR((P31/N31)^(1/(VALUE(RIGHT(O31,2))-VALUE(RIGHT(M31,2))))-1,"") -> 0.22593568 | R31: ='M&M'!C15 -> The fastest capacity ramp in Indian PVs — running behind its own plan. SUV capacity more than triples from 19k/month (FY20) to 64.5k (FY26) and is guided to 82k by H2FY27 and c.132k/month by FY31 with Nagpur. FY25 (59k vs 64k plan) and FY26 (64.5k vs 72k plan) both undershoot guidance — execution slippage is the watch item.
A32: Tata PV | B32: PV | C32: ='Tata PV'!C5 -> 900000 | D32: ='Tata PV'!C6 -> Jun/Jul-2026 (mgmt) | F32: ='Tata PV'!C8 -> 5+ — Pune (five plants), Ranjangaon (JV), Sanand I & II, Panapakkam | I32: ='Tata PV'!C9 -> 642000 | J32: ='Tata PV'!C10 -> Total PV sales FY26 (c.642k incl. exports) | L32: ='Tata PV'!C11 -> 0.71333333 | M32: FY22 | N32: ='Tata PV'!O19 -> 480000 | O32: FY26 | P32: ='Tata PV'!S19 -> 900000 | Q32: =IFERROR((P32/N32)^(1/(VALUE(RIGHT(O32,2))-VALUE(RIGHT(M32,2))))-1,"") -> 0.17017366 | R32: ='Tata PV'!C15 -> Ample in aggregate, tight by model. c.0.9m installed vs c.642k FY26 sales (c.71%) yet management cites demand of c.70k/month outrunning supply — the constraint sits in specific shops and lines, which the Sanand +300k brownfield and multi-product line flexibility target.
A33: Tata CV | B33: CV | C33: ='Tata CV'!C5 -> n.d. | D33: ='Tata CV'!C6 -> Not disclosed | F33: ='Tata CV'!C8 -> 5 — Jamshedpur, Pune, Lucknow, Pantnagar, Dharwad | I33: ='Tata CV'!C9 -> 428329 | J33: ='Tata CV'!C10 -> Total CV sales FY26 (domestic + exports) | L33: ='Tata CV'!C11 -> n.d. | M33: n.d. | O33: n.d. | R33: ='Tata CV'!C15 -> The story is footprint, not units. No consolidated CV capacity figure is published post-FY11. FY26 sales rise 14% to 428k with capex guided at only 2-4% of revenue — brownfield headroom is assumed adequate. The Iveco tender (settlement 30-Oct-2026) adds a European/LatAm footprint and takes combined volume to 540k+.
A34: Ashok Leyland | B34: CV | C34: ='Ashok Leyland'!C5 -> 150000 | D34: ='Ashok Leyland'!C6 -> Sep-2010 (latest found) | F34: ='Ashok Leyland'!C8 -> 8 vehicle sites in India incl. Vijayawada (2025) and Lucknow EV (2026) | I34: ='Ashok Leyland'!C9 -> 220437 | J34: ='Ashok Leyland'!C10 -> Total deliveries FY26 (incl. exports) | L34: ='Ashok Leyland'!C11 -> n.d. | M34: n.d. | O34: n.d. | R34: ='Ashok Leyland'!C15 -> Disclosure stops in 2010. New capacity since is bus- and EV-led (Vijayawada 4,800 p.a., Lucknow 2,500 -> 5,000 p.a.) while FY26 deliveries hit a record 220k. Truck capacity headroom must be confirmed with management before modelling the next upcycle.
A35: Bajaj Auto | B35: 2W/3W | C35: ='Bajaj Auto'!C5 -> 7200000 | D35: ='Bajaj Auto'!C6 -> Jul-2026 (c.600k/month) | F35: ='Bajaj Auto'!C8 -> 4 — Waluj, Chakan (2 plants), Pantnagar, Akurdi (Chetak) | I35: ='Bajaj Auto'!C9 -> 5117667 | J35: ='Bajaj Auto'!C10 -> Total sales FY26 (domestic + exports) | L35: ='Bajaj Auto'!C11 -> 0.71078708 | M35: FY11 | N35: ='Bajaj Auto'!D19 -> 5040000 | O35: FY26 | P35: ='Bajaj Auto'!S19 -> 7200000 | Q35: =IFERROR((P35/N35)^(1/(VALUE(RIGHT(O35,2))-VALUE(RIGHT(M35,2))))-1,"") -> 0.024063288 | R35: ='Bajaj Auto'!C15 -> Exports drive the capacity call. FY26 volume of 5.12m (44% exports) sits at c.71% of the c.7.2m installed base, yet management is adding c.20% — read this as a mix-specific constraint (Chetak, CV/3W, premium motorcycles), not blanket shortage.
A36: TVS Motor | B36: 2W/3W | C36: ='TVS Motor'!C5 -> 6800000 | D36: ='TVS Motor'!C6 -> May-2026 (mgmt) | F36: ='TVS Motor'!C8 -> 3 in India — Hosur, Mysuru, Nalagarh (+ Karawang, Indonesia) | I36: ='TVS Motor'!C9 -> 5889000 | J36: ='TVS Motor'!C10 -> Total sales FY26 (2W + 3W incl. exports) | L36: ='TVS Motor'!C11 -> 0.86602941 | M36: FY23 | N36: ='TVS Motor'!P19 -> 5190000 | O36: FY26 | P36: ='TVS Motor'!S19 -> 6800000 | Q36: =IFERROR((P36/N36)^(1/(VALUE(RIGHT(O36,2))-VALUE(RIGHT(M36,2))))-1,"") -> 0.094243188 | R36: ='TVS Motor'!C15 -> TVS is outgrowing its plants. FY26 sales rise 24% to 5.89m on c.6.8m capacity (c.87%); management adds 1.5m within 12 months and is evaluating a new site, with EV lines going to 50k/month.
A37: Royal Enfield | B37: 2W | C37: ='Royal Enfield'!C5 -> 1460000 | D37: ='Royal Enfield'!C6 -> Feb/May-2026 | F37: ='Royal Enfield'!C8 -> 4 — Thiruvottiyur, Oragadam, Vallam Vadagal, Cheyyar (all Tamil Nadu) | I37: ='Royal Enfield'!C9 -> 1238659 | J37: ='Royal Enfield'!C10 -> Total sales FY26 (domestic + exports) | L37: ='Royal Enfield'!C11 -> 0.84839658 | M37: FY18 | N37: ='Royal Enfield'!K19 -> 825000 | O37: FY26 | P37: ='Royal Enfield'!S19 -> 1460000 | Q37: =IFERROR((P37/N37)^(1/(VALUE(RIGHT(O37,2))-VALUE(RIGHT(M37,2))))-1,"") -> 0.073958163 | R37: ='Royal Enfield'!C15 -> Running hot, expanding cheaply. FY26 volume of 1.24m (+23%) on c.1.46m capacity (c.85%); the Rs958cr Cheyyar expansion to 2.0m by FY28 costs c.Rs18k per unit of added capacity.
A38: Hero MotoCorp | B38: 2W | C38: ='Hero MotoCorp'!C5 -> 11600000 | D38: ='Hero MotoCorp'!C6 -> Mar-2020 (design, incl. Chittoor at full ramp) | F38: ='Hero MotoCorp'!C8 -> 6 — Dharuhera, Gurugram, Haridwar, Neemrana, Halol, Chittoor | I38: ='Hero MotoCorp'!C9 -> 6468834 | J38: ='Hero MotoCorp'!C10 -> Total dispatches FY26 (domestic + exports) | L38: ='Hero MotoCorp'!C11 -> 0.5576581 | M38: FY15 | N38: ='Hero MotoCorp'!H19 -> 7650000 | O38: FY20 | P38: ='Hero MotoCorp'!M19 -> 9100000 | Q38: =IFERROR((P38/N38)^(1/(VALUE(RIGHT(O38,2))-VALUE(RIGHT(M38,2))))-1,"") -> 0.035323308 | R38: ='Hero MotoCorp'!C15 -> Largest installed base, weakest current disclosure. Plant design capacity of 11.6m (2020) vs 6.47m FY26 dispatches implies c.5m units of structural slack; incremental capex now goes to EV lines (Vida 25k -> 50k+/month), not ICE.
A39: Ola Electric | B39: 2W-EV | C39: ='Ola Electric'!C5 -> 1000000 | D39: ='Ola Electric'!C6 -> Oct-2023 (DRHP) | F39: ='Ola Electric'!C8 -> 1 vehicle site (Futurefactory) + cell Gigafactory | I39: ='Ola Electric'!C9 -> 164295 | J39: ='Ola Electric'!C10 -> Retail registrations FY26 (media; not company deliveries) | L39: ='Ola Electric'!C11 -> 0.164295 | M39: FY22 | N39: ='Ola Electric'!O19 -> 500000 | O39: FY24 | P39: ='Ola Electric'!Q19 -> 1000000 | Q39: =IFERROR((P39/N39)^(1/(VALUE(RIGHT(O39,2))-VALUE(RIGHT(M39,2))))-1,"") -> 0.41421356 | R39: ='Ola Electric'!C15 -> Massive overcapacity in vehicles; capital has moved to cells. 1.0m vehicle capacity vs 164k FY26 retail (c.16%) after a 52% volume decline; the gigafactory runs at c.2.5 GWh installed with 5-6 GWh targeted.
A40: Ather Energy | B40: 2W-EV | C40: ='Ather Energy'!C5 -> 420000 | D40: ='Ather Energy'!C6 -> Aug-2026 | F40: ='Ather Energy'!C8 -> 1 (Hosur, two units); AURIC Bidkin commissioning Q3FY27 | I40: ='Ather Energy'!C9 -> 239178 | J40: ='Ather Energy'!C10 -> Retail registrations FY26 (media) | L40: ='Ather Energy'!C11 -> 0.56947143 | M40: FY22 | N40: ='Ather Energy'!O19 -> 120000 | O40: FY26 | P40: ='Ather Energy'!S19 -> 420000 | Q40: =IFERROR((P40/N40)^(1/(VALUE(RIGHT(O40,2))-VALUE(RIGHT(M40,2))))-1,"") -> 0.3677824 | R40: ='Ather Energy'!C15 -> Capacity is about to more than double. Hosur's 420k (c.57% utilised on FY26 retail of 239k) plus AURIC phase 1 (500k) in Q3FY27 takes capacity to 920k; management already flags 13-15k lost sales a month and is weighing an earlier phase 2.
A42: 3. CAPACITY OUTLOOK BY CERTAINTY TIER (units p.a.) — is the company target backed by named projects?
A43: Company | B43: Segment | C43: Base capacity | D43: Base | F43: Tier 1 adds | G43: Tier 2 adds | H43: Visible capacity | I43: Visible ÷ base | J43: Company target | K43: Target timing | M43: Gap to target | N43: Read-across
A44: Maruti Suzuki | B44: PV | C44: ='Maruti Suzuki'!C12 -> 2400000 | D44: ='Maruti Suzuki'!F12 -> FY26 year-end (row 19) | F44: =SUMIFS('Maruti Suzuki'!$D$83:$D$88,'Maruti Suzuki'!$G$83:$G$88,"Tier 1") -> 500000 | G44: =SUMIFS('Maruti Suzuki'!$D$83:$D$88,'Maruti Suzuki'!$G$83:$G$88,"Tier 2") -> 1000000 | H44: =IF(ISNUMBER(C44),C44+F44+G44,"") -> 3900000 | I44: =IF(AND(ISNUMBER(H44),ISNUMBER(C44)),H44/C44,"") -> 1.625 | J44: ='Maruti Suzuki'!C13 -> 4000000 | K44: ='Maruti Suzuki'!C14 -> FY2030-31 | M44: =IF(AND(ISNUMBER(J44),ISNUMBER(H44)),J44-H44,"") -> 100000 | N44: Tier 1 already live; Tier 2 includes the Gurugram exit (-0.5m). Remaining gap to 4m is small.
A45: Hyundai India | B45: PV | C45: ='Hyundai India'!C12 -> 994000 | D45: ='Hyundai India'!F12 -> FY26 year-end (row 19) | F45: =SUMIFS('Hyundai India'!$D$73:$D$74,'Hyundai India'!$G$73:$G$74,"Tier 1") -> 80000 | G45: =SUMIFS('Hyundai India'!$D$73:$D$74,'Hyundai India'!$G$73:$G$74,"Tier 2") -> 0 | H45: =IF(ISNUMBER(C45),C45+F45+G45,"") -> 1074000 | I45: =IF(AND(ISNUMBER(H45),ISNUMBER(C45)),H45/C45,"") -> 1.0804829 | J45: ='Hyundai India'!C13 -> 1074000 | K45: ='Hyundai India'!C14 -> Talegaon at 250k (c.2028) | M45: =IF(AND(ISNUMBER(J45),ISNUMBER(H45)),J45-H45,"") -> 0 | N45: Only Talegaon ramp is visible; no new site announced.
A46: M&M | B46: PV | C46: ='M&M'!C12 -> 774000 | D46: ='M&M'!F12 -> FY26 year-end (row 19) | F46: =SUMIFS('M&M'!$D$87:$D$92,'M&M'!$G$87:$G$92,"Tier 1") -> 210000 | G46: =SUMIFS('M&M'!$D$87:$D$92,'M&M'!$G$87:$G$92,"Tier 2") -> 600000 | H46: =IF(ISNUMBER(C46),C46+F46+G46,"") -> 1584000 | I46: =IF(AND(ISNUMBER(H46),ISNUMBER(C46)),H46/C46,"") -> 2.0465116 | J46: ='M&M'!C13 -> 1548000 | K46: ='M&M'!C14 -> FY31 (2x FY26) | M46: =IF(AND(ISNUMBER(J46),ISNUMBER(H46)),J46-H46,"") -> -36000 | N46: Visible pipeline exceeds the 2x target; delivery risk sits in timing, not scope.
A47: Tata PV | B47: PV | C47: ='Tata PV'!C12 -> 900000 | D47: ='Tata PV'!F12 -> FY26 year-end (row 19) | F47: =SUMIFS('Tata PV'!$D$76:$D$79,'Tata PV'!$G$76:$G$79,"Tier 1") -> 0 | G47: =SUMIFS('Tata PV'!$D$76:$D$79,'Tata PV'!$G$76:$G$79,"Tier 2") -> 300000 | H47: =IF(ISNUMBER(C47),C47+F47+G47,"") -> 1200000 | I47: =IF(AND(ISNUMBER(H47),ISNUMBER(C47)),H47/C47,"") -> 1.3333333 | J47: ='Tata PV'!C13 -> 1300000 | K47: ='Tata PV'!C14 -> 2-3 years from Jun-2026 (c.FY29) | M47: =IF(AND(ISNUMBER(J47),ISNUMBER(H47)),J47-H47,"") -> 100000 | N47: Gap = debottlenecking not yet quantified; Panapakkam held as memo.
A48: Tata CV | B48: CV | C48: ='Tata CV'!C12 -> n.d. | D48: ='Tata CV'!F12 -> No disclosed current base | F48: =SUMIFS('Tata CV'!$D$70:$D$71,'Tata CV'!$G$70:$G$71,"Tier 1") -> 0 | G48: =SUMIFS('Tata CV'!$D$70:$D$71,'Tata CV'!$G$70:$G$71,"Tier 2") -> 0 | H48: =IF(ISNUMBER(C48),C48+F48+G48,"") | I48: =IF(AND(ISNUMBER(H48),ISNUMBER(C48)),H48/C48,"") | J48: ='Tata CV'!C13 -> n.d. | K48: ='Tata CV'!C14 -> n.a. | M48: =IF(AND(ISNUMBER(J48),ISNUMBER(H48)),J48-H48,"") | N48: No India capacity adds disclosed; Iveco is a global footprint event.
A49: Ashok Leyland | B49: CV | C49: ='Ashok Leyland'!C12 -> n.d. | D49: ='Ashok Leyland'!F12 -> No disclosed current base | F49: =SUMIFS('Ashok Leyland'!$D$75:$D$75,'Ashok Leyland'!$G$75:$G$75,"Tier 1") -> 0 | G49: =SUMIFS('Ashok Leyland'!$D$75:$D$75,'Ashok Leyland'!$G$75:$G$75,"Tier 2") -> 2500 | H49: =IF(ISNUMBER(C49),C49+F49+G49,"") | I49: =IF(AND(ISNUMBER(H49),ISNUMBER(C49)),H49/C49,"") | J49: ='Ashok Leyland'!C13 -> n.d. | K49: ='Ashok Leyland'!C14 -> n.a. | M49: =IF(AND(ISNUMBER(J49),ISNUMBER(H49)),J49-H49,"") | N49: Truck capacity undisclosed; only small EV/bus adds visible.
A50: Bajaj Auto | B50: 2W/3W | C50: ='Bajaj Auto'!C12 -> 7200000 | D50: ='Bajaj Auto'!F12 -> FY26 year-end (row 19) | F50: =SUMIFS('Bajaj Auto'!$D$76:$D$78,'Bajaj Auto'!$G$76:$G$78,"Tier 1") -> 720000 | G50: =SUMIFS('Bajaj Auto'!$D$76:$D$78,'Bajaj Auto'!$G$76:$G$78,"Tier 2") -> 720000 | H50: =IF(ISNUMBER(C50),C50+F50+G50,"") -> 8640000 | I50: =IF(AND(ISNUMBER(H50),ISNUMBER(C50)),H50/C50,"") -> 1.2 | J50: ='Bajaj Auto'!C13 -> 8640000 | K50: ='Bajaj Auto'!C14 -> FY27-end / early FY28 (+20%) | M50: =IF(AND(ISNUMBER(J50),ISNUMBER(H50)),J50-H50,"") -> 0 | N50: Company guides +20%; visible equals target by construction.
A51: TVS Motor | B51: 2W/3W | C51: ='TVS Motor'!C12 -> 6800000 | D51: ='TVS Motor'!F12 -> FY26 year-end (row 19) | F51: =SUMIFS('TVS Motor'!$D$67:$D$69,'TVS Motor'!$G$67:$G$69,"Tier 1") -> 0 | G51: =SUMIFS('TVS Motor'!$D$67:$D$69,'TVS Motor'!$G$67:$G$69,"Tier 2") -> 1500000 | H51: =IF(ISNUMBER(C51),C51+F51+G51,"") -> 8300000 | I51: =IF(AND(ISNUMBER(H51),ISNUMBER(C51)),H51/C51,"") -> 1.2205882 | J51: ='TVS Motor'!C13 -> 8300000 | K51: ='TVS Motor'!C14 -> Within 12 months of May-2026 | M51: =IF(AND(ISNUMBER(J51),ISNUMBER(H51)),J51-H51,"") -> 0 | N51: +1.5m in 12 months; new-site decision pending.
A52: Royal Enfield | B52: 2W | C52: ='Royal Enfield'!C12 -> 1460000 | D52: ='Royal Enfield'!F12 -> FY26 year-end (row 19) | F52: =SUMIFS('Royal Enfield'!$D$68:$D$68,'Royal Enfield'!$G$68:$G$68,"Tier 1") -> 540000 | G52: =SUMIFS('Royal Enfield'!$D$68:$D$68,'Royal Enfield'!$G$68:$G$68,"Tier 2") -> 0 | H52: =IF(ISNUMBER(C52),C52+F52+G52,"") -> 2000000 | I52: =IF(AND(ISNUMBER(H52),ISNUMBER(C52)),H52/C52,"") -> 1.369863 | J52: ='Royal Enfield'!C13 -> 2000000 | K52: ='Royal Enfield'!C14 -> FY28 | M52: =IF(AND(ISNUMBER(J52),ISNUMBER(H52)),J52-H52,"") -> 0 | N52: Single, funded project closes the gap to 2.0m.
A53: Hero MotoCorp | B53: 2W | C53: ='Hero MotoCorp'!C12 -> n.d. | D53: ='Hero MotoCorp'!F12 -> No disclosed current base | F53: =SUMIFS('Hero MotoCorp'!$D$71:$D$71,'Hero MotoCorp'!$G$71:$G$71,"Tier 1") -> 300000 | G53: =SUMIFS('Hero MotoCorp'!$D$71:$D$71,'Hero MotoCorp'!$G$71:$G$71,"Tier 2") -> 0 | H53: =IF(ISNUMBER(C53),C53+F53+G53,"") | I53: =IF(AND(ISNUMBER(H53),ISNUMBER(C53)),H53/C53,"") | J53: ='Hero MotoCorp'!C13 -> n.d. | K53: ='Hero MotoCorp'!C14 -> n.a. | M53: =IF(AND(ISNUMBER(J53),ISNUMBER(H53)),J53-H53,"") | N53: No current base; only EV additions visible.
A54: Ola Electric | B54: 2W-EV | C54: ='Ola Electric'!C12 -> 1000000 | D54: ='Ola Electric'!F12 -> FY24 year-end (row 19) | F54: =SUMIFS('Ola Electric'!$D$61:$D$63,'Ola Electric'!$G$61:$G$63,"Tier 1") -> 0 | G54: =SUMIFS('Ola Electric'!$D$61:$D$63,'Ola Electric'!$G$61:$G$63,"Tier 2") -> 0 | H54: =IF(ISNUMBER(C54),C54+F54+G54,"") -> 1000000 | I54: =IF(AND(ISNUMBER(H54),ISNUMBER(C54)),H54/C54,"") -> 1 | J54: ='Ola Electric'!C13 -> n.d. | K54: ='Ola Electric'!C14 -> n.a. (cells: 5-6 GWh FY27; 20 GWh PLI) | M54: =IF(AND(ISNUMBER(J54),ISNUMBER(H54)),J54-H54,"") | N54: No vehicle adds; cell ramp tracked in GWh (memo).
A55: Ather Energy | B55: 2W-EV | C55: ='Ather Energy'!C12 -> 420000 | D55: ='Ather Energy'!F12 -> FY26 year-end (row 19) | F55: =SUMIFS('Ather Energy'!$D$61:$D$62,'Ather Energy'!$G$61:$G$62,"Tier 1") -> 500000 | G55: =SUMIFS('Ather Energy'!$D$61:$D$62,'Ather Energy'!$G$61:$G$62,"Tier 2") -> 500000 | H55: =IF(ISNUMBER(C55),C55+F55+G55,"") -> 1420000 | I55: =IF(AND(ISNUMBER(H55),ISNUMBER(C55)),H55/C55,"") -> 3.3809524 | J55: ='Ather Energy'!C13 -> n.d. | K55: ='Ather Energy'!C14 -> AURIC phase 1 Q3FY27; phase 2 in planning | M55: =IF(AND(ISNUMBER(J55),ISNUMBER(H55)),J55-H55,"") | N55: AURIC phase 1 is Tier 1; phase 2 derived from site design.
A56: PV big four (sum) | C56: =SUM(C44:C47) -> 5068000 | F56: =SUM(F44:F47) -> 790000 | G56: =SUM(G44:G47) -> 1900000 | H56: =SUM(H44:H47) -> 7758000 | I56: =IF(C56>0,H56/C56,"") -> 1.5307814 | J56: Maruti, Hyundai, M&M, Tata PV
A58: 4. CHARTS (markers = disclosed data points; lines connect disclosed points only)

Sheet Maruti Suzuki
A1: Maruti Suzuki India Ltd (MSIL) — incl. Hansalpur (ex-Suzuki Motor Gujarat)
A2: MARUTI IN | Segment: PV | Units: vehicles p.a. unless stated | FY = year to 31-Mar | As of 14-Oct-2026
A3: Scope: Group India car capacity: Gurugram + Manesar + Kharkhoda (MSIL) and Hansalpur (Suzuki Motor Gujarat, 100% Suzuki until it became an MSIL subsidiary in FY24; since merged into MSIL). Excludes Toyota-built models sold by MSIL.
A4: A. SNAPSHOT
A5: Latest disclosed installed capacity (units p.a.) | C5: 2900000 | F5: As of 30-Jul-2026 [MS21]
A6: As of | C6: 30-Jul-2026
A7: Capacity definition / scope | C7: Annual vehicle production capacity as stated by MSIL/Suzuki (two-shift basis), all four sites
A8: Vehicle assembly sites | C8: 4 — Gurugram, Manesar, Kharkhoda (Haryana); Hansalpur (Gujarat). 5th site (Khoraj, Gujarat) in land stage
A9: FY26 volume (units) | C9: =IF(ISNUMBER(S21),S21,"n.d.") -> 2340000 | F9: Production (FY26, company: >23.4 lakh)
A10: FY26 volume basis | C10: Production (FY26, company: >23.4 lakh)
A11: FY26 utilisation | C11: =IFERROR(C9/S19,"n.d.") -> 0.975 | F11: FY26 volume ÷ FY26 year-end capacity (row 19)
A12: Outlook base capacity (units p.a.) | C12: =S19 -> 2400000 | F12: FY26 year-end (row 19)
A13: Company capacity target (units p.a.) | C13: 4000000 | F13: [MS11; MS23]
A14: Target timing | C14: FY2030-31
A15: Bottom line | C15: Capacity, not demand, is the binding constraint. FY26 output of 2.34m runs at c.94% of average installed capacity with c.190k orders pending at year-end. Two 250k plants (Kharkhoda-2, Hansalpur-D) are already live in FY27, and announced sites (Kharkhoda to 1m, Khoraj 1m, net of the Gurugram exit) cover almost all of the 4m FY31 target.
A17: B. COMPANY-LEVEL CAPACITY AND OUTPUT HISTORY, FY10–FY26 (blue = sourced input; black = formula; orange = verify; light blue = bracketed carry)
A18: Metric | B18: Unit | C18: FY10 | D18: FY11 | E18: FY12 | F18: FY13 | G18: FY14 | H18: FY15 | I18: FY16 | J18: FY17 | K18: FY18 | L18: FY19 | M18: FY20 | N18: FY21 | O18: FY22 | P18: FY23 | Q18: FY24 | R18: FY25 | S18: FY26 | T18: Notes
A19: Installed capacity, FY-end (reported) | B19: units p.a. | C19: 1000000 | D19: 1200000 | H19: 1500000 | I19: 1500000 | J19: 1750000 | K19: 1750000 | L19: 2000000 | M19: 2000000 | N19: 2000000 | O19: 2250000 | P19: 2250000 | Q19: 2250000 | R19: 2600000 | S19: 2400000 | T19: Group capacity incl. Hansalpur from FY17. FY12-FY14 FY-end figures not found in sources reviewed (Plant B Oct-2011, Plant C 2013).
A20: Capacity basis code | B20: code | C20: R | D20: R | H20: R | I20: R | J20: S | K20: S | L20: R | M20: R | N20: R | O20: R | P20: R | Q20: R | R20: R | S20: R | T20: R = company-reported total; S = sum of company-disclosed plants; M = management statement via media; A = monthly x12; D = DRHP/RHP
A21: Production — actual | B21: units | H21: 1308128 | P21: 1922000 | Q21: 1984000 | R21: 2102000 | S21: 2340000 | T21: FY23-FY26 rounded to thousands as reported. FY10 production >1.0m (millionth car rolled out 23-Mar-2010) — not entered.
A22: Sales / dispatches — actual, total | B22: units | C22: 1018365 | M22: 1563297 | N22: 1457861 | R22: 2234266 | S22: 2422713 | T22: Total = domestic incl. OEM supplies + exports. FY10 from AR; FY20-21 from monthly release; FY25-26 from results release.
A23: of which domestic | B23: units | C23: 870790 | I23: 1305351 | J23: 1444541 | K23: 1653500 | L23: 1753700 | M23: 1436124 | N23: 1323396 | R23: 1901681 | S23: 1974939 | T23: FY16-FY21: PV+LCV excl. OEM supplies to Toyota (not like-for-like with FY25-26, which include OEM supplies of c.113k in FY26).
A24: of which exports | B24: units | C24: 147575 | M24: 102171 | N24: 96139 | R24: 332585 | S24: 447774
A25: Utilisation — production ÷ FY-end capacity | B25: % | C25: =IF(AND(ISNUMBER(C21),ISNUMBER(C19)),C21/C19,"") | D25: =IF(AND(ISNUMBER(D21),ISNUMBER(D19)),D21/D19,"") | E25: =IF(AND(ISNUMBER(E21),ISNUMBER(E19)),E21/E19,"") | F25: =IF(AND(ISNUMBER(F21),ISNUMBER(F19)),F21/F19,"") | G25: =IF(AND(ISNUMBER(G21),ISNUMBER(G19)),G21/G19,"") | H25: =IF(AND(ISNUMBER(H21),ISNUMBER(H19)),H21/H19,"") -> 0.87208533 | I25: =IF(AND(ISNUMBER(I21),ISNUMBER(I19)),I21/I19,"") | J25: =IF(AND(ISNUMBER(J21),ISNUMBER(J19)),J21/J19,"") | ... S25: =IF(AND(ISNUMBER(S21),ISNUMBER(S19)),S21/S19,"") -> 0.975 | T25: Formula. Company convention (e.g., HMIL DRHP). Depressed in commissioning years.
A26: Utilisation — production ÷ avg(opening, closing) capacity | B26: % | C26: =IF(AND(ISNUMBER(C21),ISNUMBER(C19)),C21/C19,"") | D26: =IF(AND(ISNUMBER(D21),ISNUMBER(D19)),D21/IF(ISNUMBER(C19),AVERAGE(C19,D19),D19),"") | E26: =IF(AND(ISNUMBER(E21),ISNUMBER(E19)),E21/IF(ISNUMBER(D19),AVERAGE(D19,E19),E19),"") | F26: =IF(AND(ISNUMBER(F21),ISNUMBER(F19)),F21/IF(ISNUMBER(E19),AVERAGE(E19,F19),F19),"") | G26: =IF(AND(ISNUMBER(G21),ISNUMBER(G19)),G21/IF(ISNUMBER(F19),AVERAGE(F19,G19),G19),"") | H26: =IF(AND(ISNUMBER(H21),ISNUMBER(H19)),H21/IF(ISNUMBER(G19),AVERAGE(G19,H19),H19),"") -> 0.87208533 | I26: =IF(AND(ISNUMBER(I21),ISNUMBER(I19)),I21/IF(ISNUMBER(H19),AVERAGE(H19,I19),I19),"") | J26: =IF(AND(ISNUMBER(J21),ISNUMBER(J19)),J21/IF(ISNUMBER(I19),AVERAGE(I19,J19),J19),"") | K26: =IF(AND(ISNUMBER(K21),ISNUMBER(K19)),K21/IF(ISNUMBER(J19),AVERAGE(J19,K19),K19),"") | ... S26: =IF(AND(ISNUMBER(S21),ISNUMBER(S19)),S21/IF(ISNUMBER(R19),AVERAGE(R19,S19),S19),"") -> 0.936 | T26: Formula. Uses closing capacity where opening not disclosed.
A27: Utilisation — sales ÷ FY-end capacity | B27: % | C27: =IF(ISNUMBER(C19),IF(ISNUMBER(C22),C22/C19,IF(ISNUMBER(C23),C23/C19,"")),"") -> 1.018365 | D27: =IF(ISNUMBER(D19),IF(ISNUMBER(D22),D22/D19,IF(ISNUMBER(D23),D23/D19,"")),"") | E27: =IF(ISNUMBER(E19),IF(ISNUMBER(E22),E22/E19,IF(ISNUMBER(E23),E23/E19,"")),"") | F27: =IF(ISNUMBER(F19),IF(ISNUMBER(F22),F22/F19,IF(ISNUMBER(F23),F23/F19,"")),"") | G27: =IF(ISNUMBER(G19),IF(ISNUMBER(G22),G22/G19,IF(ISNUMBER(G23),G23/G19,"")),"") | H27: =IF(ISNUMBER(H19),IF(ISNUMBER(H22),H22/H19,IF(ISNUMBER(H23),H23/H19,"")),"") | I27: =IF(ISNUMBER(I19),IF(ISNUMBER(I22),I22/I19,IF(ISNUMBER(I23),I23/I19,"")),"") -> 0.870234 | J27: =IF(ISNUMBER(J19),IF(ISNUMBER(J22),J22/J19,IF(ISNUMBER(J23),J23/J19,"")),"") -> 0.825452 | ... S27: =IF(ISNUMBER(S19),IF(ISNUMBER(S22),S22/S19,IF(ISNUMBER(S23),S23/S19,"")),"") -> 1.0094638 | T27: Formula. Uses total sales, else domestic (understates where exports excluded).
A28: Capacity change vs prior FY | B28: units p.a. | D28: =IF(AND(ISNUMBER(D19),ISNUMBER(C19)),D19-C19,"") -> 200000 | E28: =IF(AND(ISNUMBER(E19),ISNUMBER(D19)),E19-D19,"") | F28: =IF(AND(ISNUMBER(F19),ISNUMBER(E19)),F19-E19,"") | G28: =IF(AND(ISNUMBER(G19),ISNUMBER(F19)),G19-F19,"") | H28: =IF(AND(ISNUMBER(H19),ISNUMBER(G19)),H19-G19,"") | I28: =IF(AND(ISNUMBER(I19),ISNUMBER(H19)),I19-H19,"") -> 0 | J28: =IF(AND(ISNUMBER(J19),ISNUMBER(I19)),J19-I19,"") -> 250000 | K28: =IF(AND(ISNUMBER(K19),ISNUMBER(J19)),K19-J19,"") -> 0 | ... S28: =IF(AND(ISNUMBER(S19),ISNUMBER(R19)),S19-R19,"") -> -200000 | T28: Formula; blank where either year undisclosed.
A29: Utilisation — company-reported | B29: % | T29: MSIL does not publish a utilisation %; FY26 release states sales were capacity-limited.
A30: Source IDs (see Source Log) | C30: MS01; MS02; MS04 | D30: MS03; MS05 | E30: MS30 | F30: MS03 | G30: MS13 | H30: MS06; MS07 | I30: MS07; MS08 | J30: MS06; MS07; MS10 | K30: MS10; MS29 | L30: MS09; MS10 | M30: MS10; MS22 | N30: MS10; MS22 | O30: MS10 | P30: MS12; MS19 | Q30: HY10; MS15; MS19 | R30: MS13; MS14; MS15; MS17; MS19 | S30: MS16; MS17; MS18; MS20
A31: Year notes | C31: Gurugram 0.70m (3 plants) + Manesar 0.30m | D31: 0.85m + 0.35m via productivity, no new plant | E31: Manesar Plant B (+0.25m) SOP Oct-2011 | F31: Plan: 1.75m by FY13-end incl. Plant C | G31: Manesar Plant C commissioned (2013) | H31: Implied by Suzuki: Gujarat +0.25m takes India to 1.75m | I31: Gurugram 0.7m + Manesar 0.8m; effective c.1.45m | J31: SMG Plant A SOP 1-Feb-2017 | K31: MSIL 1.5-1.55m (sources differ) + SMG 0.25m | L31: SMG Plant B + powertrain (Jan-2019) | M31: No change until Plant C | N31: No change until Plant C | O31: SMG Plant C SOP Apr-2021 | P31: 1.5m Haryana + 0.75m Gujarat | Q31: Unchanged; +0.1m Manesar line falls in FY25 | R31: +0.1m Manesar (Apr-24); Kharkhoda P1 (Feb-25) | S31: Gurugram restated 0.7m -> 0.5m
A33: C. PLANT-LEVEL CAPACITY AND OUTPUT BY FISCAL YEAR (disclosed points only; no interpolation)
A34: Plant / line | B34: Unit | C34: FY10 | D34: FY11 | E34: FY12 | F34: FY13 | G34: FY14 | H34: FY15 | I34: FY16 | J34: FY17 | K34: FY18 | L34: FY19 | M34: FY20 | N34: FY21 | O34: FY22 | P34: FY23 | Q34: FY24 | R34: FY25 | S34: FY26 | T34: Notes [sources]
A35: Gurugram (Haryana) | B35: units p.a. | C35: 700000 | D35: 850000 | I35: 700000 | R35: 700000 | S35: 500000 | T35: 3 assembly plants; Plant 1 (c.0.16m) phase-out from 2009; restated to 0.5m by May-2026 [MS02; MS03; MS07; MS23; MS20]
A36: Manesar (Haryana) | B36: units p.a. | C36: 300000 | D36: 350000 | I36: 800000 | R36: 900000 | S36: 900000 | T36: Plant A 2007, Plant B Oct-2011, Plant C 2013, +0.1m line Apr-2024 [MS02; MS03; MS07; MS13; MS20]
A37: Memo: Gurugram + Manesar combined (company-stated) | B37: units p.a. | L37: 1500000 | N37: 1500000 | P37: 1500000 | T37: 'Production ability' of MSIL's Haryana plants [MS09; MS10; MS12]
A38: Hansalpur (Gujarat) — ex-SMG | B38: units p.a. | J38: 250000 | K38: 250000 | L38: 500000 | M38: 500000 | N38: 500000 | O38: 750000 | P38: 750000 | Q38: 750000 | R38: 750000 | S38: 750000 | T38: Sum of plants at 250k each: A Feb-2017, B Jan-2019, C Apr-2021 (D Jul-2026 = FY27) [MS10; MS11; MS21]
A39: Kharkhoda (Haryana) | B39: units p.a. | R39: 250000 | S39: 250000 | T39: Plant 1 SOP 25-Feb-2025; Plant 2 SOP 18-May-2026 (FY27) [MS14; MS20]
A40: Hansalpur powertrain — engines | B40: engines p.a. | O40: 500000 | T40: SOP Jan-2019 with Plant B; 500k transmissions also [MS10]
A42: D. PLANT REGISTER
A43: Plant / site | B43: Location | D43: Entity / ownership | F43: SOP / commissioned | G43: Vehicle category | I43: Key models (latest disclosed) | M43: Platforms | O43: Initial capacity (units p.a.) | P43: Latest capacity (units p.a.) | Q43: As of | R43: Status | S43: Notes | V43: Sources [confidence]
A44: Gurugram | B44: Gurugram, Haryana | D44: MSIL | F44: Dec-1983 | G44: PV (small cars, vans) | I44: 2009 disclosure: 800, Alto, WagonR, Estilo, Omni, Gypsy, Eeco. Current allocation not in sources reviewed | M44: Legacy + HEARTECT | P44: 500000 | Q44: May-2026 | R44: Operating; relocation intent | S44: c.300 acres; 3 vehicle plants; restated 0.7m -> 0.5m; Kharkhoda chosen as relocation site (2021) | V44: [High/Med] MS02; MS20; MS24; MS26
A45: Manesar | B45: Manesar, Haryana | D45: MSIL | F45: Oct-2006 / Feb-2007 (A); Oct-2011 (B); 2013 (C) | G45: PV | I45: Brezza, Ertiga, XL6, Wagon R, Dzire, S-Presso, Ciaz, Celerio (Apr-2024) | M45: HEARTECT | O45: 300000 | P45: 900000 | Q45: May-2026 | R45: Operating | S45: c.600 acres; diesel engine plant (2006, Fiat licence); >10m cumulative by Oct-2024 | V45: [High] MS13; MS20; MS27; MS28
A46: Hansalpur | B46: Hansalpur, Gujarat | D46: SMG (Suzuki 100%) -> MSIL sub. (Dec-2023) -> merged into MSIL | F46: A Feb-2017; B Jan-2019; C Apr-2021; D 30-Jul-2026 | G46: PV incl. BEV | I46: Baleno (A); Fronx, Swift (B); Fronx, e Vitara (C); e Vitara (D) | M46: HEARTECT; HEARTECT-e | O46: 250000 | P46: 1000000 | Q46: 30-Jul-2026 | R46: Operating | S46: c.640 acres; powertrain 0.5m engines + 0.5m transmissions; c.47% of MSIL FY26 exports; Plant D capex Rs3,900cr | V46: [High] MS10; MS11; MS21
A47: Kharkhoda | B47: Sonipat, Haryana | D47: MSIL | F47: P1 25-Feb-2025; P2 18-May-2026 | G47: PV (SUV) | I47: Brezza, Victoris | M47: n.d. | O47: 250000 | P47: 500000 | Q47: 18-May-2026 | R47: Operating; ramp to 1.0m (4 x 0.25m) | S47: c.800-900 acres; Rs11,000cr phase 1 (Rs18,000cr three-plant plan, 2021) | V47: [High] MS14; MS20; MS25; MS26
A48: Khoraj (Sanand) | B48: Khoraj Industrial Estate, Gujarat | D48: MSIL | F48: Planned | G48: PV | I48: — | M48: — | P48: up to 1,000,000 (planned) | Q48: Mar-2026 | R48: Land approved; phasing TBD | S48: Rs4,960cr for land and early-stage development | V48: [High] MS16; MS18
A49: Memo: Toyota Kirloskar (Bidadi) | B49: Bidadi, Karnataka | D49: Toyota Kirloskar Motor | F49: — | G49: PV (contract supply) | I49: Grand Vitara, Invicto (built by Toyota for MSIL) | M49: — | P49: n.a. | Q49: — | R49: Outside MSIL capacity | S49: MSIL volumes can exceed own capacity; verify supply volumes from MSIL related-party disclosures | V49: [Medium — not in source log; verify]
A51: E. CAPACITY EVENT LOG (chronological; positive = addition)
A52: Event | B52: Date | C52: FY | D52: Type | F52: Plant / site | H52: Capacity change (units p.a.) | I52: Plant capacity after | J52: Company capacity after | K52: Capex (Rs cr) | L52: Status | N52: Notes | V52: Sources
A53: First production (Maruti 800) | B53: Dec-1983 | C53: FY84 | D53: New plant | F53: Gurugram | L53: Commissioned | N53: Start of Maruti production | V53: MS05
A54: Manesar Plant A + diesel engine plant | B54: Oct-2006 / Feb-2007 | C54: FY07 | D54: New plant | F54: Manesar | H54: 300000 | I54: 300000 | L54: Commissioned | N54: Diesel engines under Fiat licence | V54: MS05; MS28
A55: Gurugram Plant 1 car production phase-out | B55: Sep-2009 | C55: FY10 | D55: Closure (partial) | F55: Gurugram Plant 1 | L55: Announced | N55: c.160k line to be phased out gradually; space reassigned to engines (media) | V55: MS24
A56: Board approves Manesar Plant B | B56: 23-Jan-2010 | C56: FY10 | D56: Expansion approved | F56: Manesar Plant B | H56: 250000 | K56: 1700 | L56: Approved | N56: SOP targeted Apr-2012 | V56: MS01; MS02
A57: AGM: Plant C announced; capacity 1.2m via productivity | B57: 07-Sep-2010 | C57: FY11 | D57: Expansion / debottlenecking | F57: Manesar Plant C; Gurugram | H57: 250000 | J57: 1200000 | K57: 1925 | L57: Announced | N57: Target 1.75m by FY13 incl. productivity; Rs2,500cr engine + R&D | V57: MS03
A58: Manesar Plant B SOP | B58: Oct-2011 | C58: FY12 | D58: New plant | F58: Manesar Plant B | H58: 250000 | K58: 1700 | L58: Commissioned | N58: Six months ahead of schedule | V58: MS30; MS13
A59: Manesar Plant C SOP | B59: 2013 | C59: FY13/14 | D59: New plant | F59: Manesar Plant C | H59: 250000 | I59: 800000 | K59: 1925 | L59: Commissioned | N59: Manesar reaches 0.8m (two shifts) | V59: MS13; MS07
A60: Suzuki Motor Gujarat incorporated | B60: Mar-2014 | C60: FY14 | D60: New entity | F60: Hansalpur | L60: Incorporated | N60: 100% Suzuki; supplies MSIL at cost; minority approval Dec-2015 | V60: MS10; MS08
A61: Hansalpur Plant A SOP | B61: 01-Feb-2017 | C61: FY17 | D61: New plant | F61: Hansalpur A | H61: 250000 | I61: 250000 | J61: 1750000 | L61: Commissioned | N61: Baleno | V61: MS10
A62: Hansalpur Plant B + powertrain SOP | B62: Jan-2019 | C62: FY19 | D62: New plant | F62: Hansalpur B | H62: 250000 | I62: 500000 | J62: 2000000 | L62: Commissioned | N62: Swift; engines 0.5m, transmissions 0.5m | V62: MS09; MS10
A63: Hansalpur Plant C SOP | B63: Apr-2021 | C63: FY22 | D63: New plant | F63: Hansalpur C | H63: 250000 | I63: 750000 | J63: 2250000 | L63: Commissioned | N63: Dzire initially | V63: MS10
A64: Kharkhoda land allotted | B64: Nov-2021 | C64: FY22 | D64: New site | F64: Kharkhoda | K64: 18000 | L64: Land allotted | N64: c.900 acres; three 250k plants planned (later four) | V64: MS26
A65: Kharkhoda foundation stone | B65: Aug-2022 | C65: FY23 | D65: Construction start | F65: Kharkhoda | K65: 11000 | L65: Under construction | N65: Phase 1 investment | V65: MS12; MS14
A66: SMG becomes MSIL subsidiary | B66: Dec-2023 | C66: FY24 | D66: Ownership change | F66: Hansalpur | L66: Completed | N66: Ends contract-manufacturing structure | V66: MS11
A67: Additional Manesar line | B67: 09-Apr-2024 | C67: FY25 | D67: Debottlenecking (new line) | F67: Manesar Plant A | H67: 100000 | I67: 900000 | J67: 2350000 | L67: Commissioned | N67: Ertiga first off line | V67: MS13; MS15
A68: Kharkhoda Plant 1 SOP | B68: 25-Feb-2025 | C68: FY25 | D68: New plant | F68: Kharkhoda P1 | H68: 250000 | I68: 250000 | J68: 2600000 | K68: 11000 | L68: Commissioned | N68: Brezza | V68: MS14; MS15
A69: Gurugram capacity restated | B69: By Mar-2026 (n.d.) | C69: FY26 | D69: Restatement | F69: Gurugram | H69: -200000 | I69: 500000 | J69: 2400000 | L69: Restated | N69: No dated announcement found; consistent with relocation | V69: MS16; MS18; MS20
A70: Khoraj land approved | B70: Mar-2026 | C70: FY26 | D70: New site | F70: Khoraj, Gujarat | H70: 1000000 | K70: 4960 | L70: Approved (land) | N70: Up to 1m; phasing to be decided by board | V70: MS16; MS18
A71: Kharkhoda Plant 2 SOP | B71: 18-May-2026 | C71: FY27 | D71: New plant | F71: Kharkhoda P2 | H71: 250000 | I71: 500000 | J71: 2650000 | L71: Commissioned | N71: Victoris, Brezza | V71: MS20
A72: Hansalpur Plant D SOP | B72: 30-Jul-2026 | C72: FY27 | D72: New plant | F72: Hansalpur D | H72: 250000 | I72: 1000000 | J72: 2900000 | K72: 3900 | L72: Commissioned | N72: e Vitara; first Suzuki site at 1m | V72: MS21
A74: F. PLATFORMS, MODELS AND PLANT ALLOCATION (confidence in brackets; model-plant mapping is rarely company-disclosed)
A75: Platform / architecture | B75: Powertrain | D75: Segment | F75: Models | L75: Plant(s) | O75: First SOP | P75: Notes | V75: Sources [confidence]
A76: HEARTECT | B76: ICE (petrol, CNG; mild/strong hybrid capable) | D76: Hatch, sedan, MPV, compact SUV | F76: Swift, Dzire, Baleno, Fronx, Ertiga, XL6, Wagon R, Celerio, S-Presso, Alto K10, Ignis | L76: Manesar, Hansalpur, Gurugram | O76: 2016 (Baleno) | P76: Suzuki's lightweight platform; model-level mapping from media, not MSIL filings | V76: [Medium] MS13; MS21
A77: HEARTECT-e | B77: BEV | D77: Mid SUV | F77: e Vitara (also supplied to Toyota) | L77: Hansalpur C, D | O77: FY26 | P77: Exported to 44 countries by Apr-2026 | V77: [Medium-High] MS17; MS21
A78: SUV architecture (Brezza / Victoris) | B78: ICE / CNG / hybrid | D78: Compact & mid SUV | F78: Brezza, Victoris | L78: Kharkhoda, Manesar | O78: 2016 / 2025 | P78: Platform name not disclosed in sources reviewed | V78: [Low] MS13; MS20
A79: Ladder frame (Jimny) | B79: ICE | D79: Off-roader | F79: Jimny 5-door | L79: n.d. (verify) | O79: 2023 | P79: Plant not confirmed in sources reviewed | V79: [Low]
A81: G. FORWARD CAPACITY PIPELINE — Tier 1 = commissioned after FY26 or under execution; Tier 2 = announced with timeline/site; Memo = not summed
A82: Project | B82: Location | D82: Capacity add (units p.a.) | E82: Expected timing | F82: Capex (Rs cr) | G82: Tier | H82: Status (as of 14-Oct-2026) | J82: Notes | V82: Sources
A83: Kharkhoda Plant 2 | B83: Haryana | D83: 250000 | E83: FY27 (18-May-2026) | G83: Tier 1 | H83: Commissioned | J83: Victoris, Brezza | V83: MS20
A84: Hansalpur Plant D | B84: Gujarat | D84: 250000 | E84: FY27 (30-Jul-2026) | F84: 3900 | G84: Tier 1 | H84: Commissioned | J84: e Vitara | V84: MS21
A85: Kharkhoda Plants 3-4 | B85: Haryana | D85: 500000 | E85: By c.FY33 ('over next 8 years' from Feb-2025) | G85: Tier 2 | H85: Planned in site master plan | J85: Site designed for 4 x 250k | V85: MS25; MS20
A86: Khoraj greenfield | B86: Gujarat | D86: 1000000 | E86: Phasing TBD by board | F86: 4960 | G86: Tier 2 | H86: Land approved Mar-2026 | J86: Capex shown is land and early-stage works only | V86: MS16; MS18
A87: Gurugram exit (relocation) | B87: Haryana | D87: -500000 | E87: n.d. | G87: Tier 2 | H87: Intent stated since 2018-21 | J87: Treated as capacity loss once Kharkhoda/Khoraj are up | V87: MS26; MS29
A88: Company target: c.4m by FY31 | B88: India | E88: FY2030-31 | F88: 45000 | G88: Memo | H88: Target | J88: c.Rs45,000cr programme (media) | V88: MS11; MS23
A90: H. ANALYST NOTES
A91: Disclosure quality is high. MSIL and Suzuki disclose plant-wise capacity at every commissioning; the only true gap is FY12-FY14 year-end figures.
A92: Gurugram is being restated, not closed. Capacity falls from 0.7m (Feb-2025) to 0.5m (May-2026) with no dated announcement — treat as relocation-linked.
A93: Gujarat is the export and EV engine. Hansalpur ships c.47% of FY26 exports and hosts all BEV capacity (Plants C, D).
A94: Toyota supply sits outside the capacity base. Grand Vitara and Invicto are built by Toyota Kirloskar; MSIL sales can exceed own-plant capacity.
A95: Commissioning years understate utilisation. FY25 year-end utilisation is diluted by Kharkhoda (SOP 25-Feb-2025); use the average-capacity row.

Sheet Hyundai India
A1: Hyundai Motor India Ltd (HMIL)
A2: HYUNDAI IN | Segment: PV | Units: vehicles p.a. unless stated | FY = year to 31-Mar | As of 14-Oct-2026
A3: Scope: Chennai (Sriperumbudur: Plant 1 and Plant 2 — separate assembly lines) and Talegaon (Pune, ex-GM India) from Oct-2025. Excludes Kia India (Anantapur), a sister HMG company.
A4: A. SNAPSHOT
A5: Latest disclosed installed capacity (units p.a.) | C5: 994000 | F5: As of FY26 (Mar-2026) [HY11; HY15]
A6: As of | C6: FY26 (Mar-2026)
A7: Capacity definition / scope | C7: Installed annual vehicle capacity per HMIL (DRHP/AR basis)
A8: Vehicle assembly sites | C8: 2 — Chennai (Plants 1 & 2), Talegaon/Pune
A9: FY26 volume (units) | C9: =IF(ISNUMBER(S21),S21,"n.d.") -> 769280 | F9: Production (FY26 AR, plant-wise)
A10: FY26 volume basis | C10: Production (FY26 AR, plant-wise)
A11: FY26 utilisation | C11: =IFERROR(C9/S19,"n.d.") -> 0.77392354 | F11: FY26 volume ÷ FY26 year-end capacity (row 19)
A12: Outlook base capacity (units p.a.) | C12: =S19 -> 994000 | F12: FY26 year-end (row 19)
A13: Company capacity target (units p.a.) | C13: 1074000 | F13: [HY10; HY12]
A14: Target timing | C14: Talegaon at 250k (c.2028)
A15: Bottom line | C15: Talegaon resets the denominator. Capacity rises 21% to 994k in FY26 while output grows <1%; utilisation on year-end capacity falls to c.77%. The FY27-FY28 debate is about filling Pune and Chennai Plant 1, not adding new capacity.
A17: B. COMPANY-LEVEL CAPACITY AND OUTPUT HISTORY, FY10–FY26 (blue = sourced input; black = formula; orange = verify; light blue = bracketed carry)
A18: Metric | B18: Unit | C18: FY10 | D18: FY11 | E18: FY12 | F18: FY13 | G18: FY14 | H18: FY15 | I18: FY16 | J18: FY17 | K18: FY18 | L18: FY19 | M18: FY20 | N18: FY21 | O18: FY22 | P18: FY23 | Q18: FY24 | R18: FY25 | S18: FY26 | T18: Notes
A19: Installed capacity, FY-end (reported) | B19: units p.a. | C19: 600000 | I19: 680000 | K19: 700000 | L19: 750000 | M19: 750000 | N19: 750000 | O19: 758000 | P19: 770000 | Q19: 824000 | R19: 824000 | S19: 994000 | T19: FY11-FY15 and FY17 not found. FY20-FY21 bracketed (7.5 lakh until H1-2023 per Aug-2023 statement; DRHP shows 758k for FY22 — rounding).
A20: Capacity basis code | B20: code | C20: M | I20: M | K20: M | L20: M | M20: M* | N20: M* | O20: D | P20: D | Q20: D | R20: R | S20: R | T20: R = company-reported total; S = sum of company-disclosed plants; M = management statement via media; A = monthly x12; D = DRHP/RHP
A21: Production — actual | B21: units | O21: 606100 | P21: 727300 | Q21: 787500 | R21: 762900 | S21: 769280 | T21: FY22-FY26 from FY26 AR Board's Report (plant-wise in section C). CY2016 665k and CY2017 678k (calendar) noted in HY18.
A22: Sales / dispatches — actual, total | B22: units | O22: 610760 | P22: 720565 | Q22: 777876 | R22: 762052 | S22: 775031 | T22: Domestic + exports per FY26 AR.
A23: of which domestic | B23: units | O23: 481500 | P23: 567546 | Q23: 614721 | R23: 598666 | S23: 584906
A24: of which exports | B24: units | O24: 129260 | P24: 153019 | Q24: 163155 | R24: 163386 | S24: 190125
A25: Utilisation — production ÷ FY-end capacity | B25: % | C25: =IF(AND(ISNUMBER(C21),ISNUMBER(C19)),C21/C19,"") | D25: =IF(AND(ISNUMBER(D21),ISNUMBER(D19)),D21/D19,"") | E25: =IF(AND(ISNUMBER(E21),ISNUMBER(E19)),E21/E19,"") | F25: =IF(AND(ISNUMBER(F21),ISNUMBER(F19)),F21/F19,"") | G25: =IF(AND(ISNUMBER(G21),ISNUMBER(G19)),G21/G19,"") | H25: =IF(AND(ISNUMBER(H21),ISNUMBER(H19)),H21/H19,"") | I25: =IF(AND(ISNUMBER(I21),ISNUMBER(I19)),I21/I19,"") | J25: =IF(AND(ISNUMBER(J21),ISNUMBER(J19)),J21/J19,"") | ... S25: =IF(AND(ISNUMBER(S21),ISNUMBER(S19)),S21/S19,"") -> 0.77392354 | T25: Formula. Company convention (e.g., HMIL DRHP). Depressed in commissioning years.
A26: Utilisation — production ÷ avg(opening, closing) capacity | B26: % | C26: =IF(AND(ISNUMBER(C21),ISNUMBER(C19)),C21/C19,"") | D26: =IF(AND(ISNUMBER(D21),ISNUMBER(D19)),D21/IF(ISNUMBER(C19),AVERAGE(C19,D19),D19),"") | E26: =IF(AND(ISNUMBER(E21),ISNUMBER(E19)),E21/IF(ISNUMBER(D19),AVERAGE(D19,E19),E19),"") | F26: =IF(AND(ISNUMBER(F21),ISNUMBER(F19)),F21/IF(ISNUMBER(E19),AVERAGE(E19,F19),F19),"") | G26: =IF(AND(ISNUMBER(G21),ISNUMBER(G19)),G21/IF(ISNUMBER(F19),AVERAGE(F19,G19),G19),"") | H26: =IF(AND(ISNUMBER(H21),ISNUMBER(H19)),H21/IF(ISNUMBER(G19),AVERAGE(G19,H19),H19),"") | I26: =IF(AND(ISNUMBER(I21),ISNUMBER(I19)),I21/IF(ISNUMBER(H19),AVERAGE(H19,I19),I19),"") | J26: =IF(AND(ISNUMBER(J21),ISNUMBER(J19)),J21/IF(ISNUMBER(I19),AVERAGE(I19,J19),J19),"") | K26: =IF(AND(ISNUMBER(K21),ISNUMBER(K19)),K21/IF(ISNUMBER(J19),AVERAGE(J19,K19),K19),"") | ... S26: =IF(AND(ISNUMBER(S21),ISNUMBER(S19)),S21/IF(ISNUMBER(R19),AVERAGE(R19,S19),S19),"") -> 0.84629263 | T26: Formula. Uses closing capacity where opening not disclosed.
A27: Utilisation — sales ÷ FY-end capacity | B27: % | C27: =IF(ISNUMBER(C19),IF(ISNUMBER(C22),C22/C19,IF(ISNUMBER(C23),C23/C19,"")),"") | D27: =IF(ISNUMBER(D19),IF(ISNUMBER(D22),D22/D19,IF(ISNUMBER(D23),D23/D19,"")),"") | E27: =IF(ISNUMBER(E19),IF(ISNUMBER(E22),E22/E19,IF(ISNUMBER(E23),E23/E19,"")),"") | F27: =IF(ISNUMBER(F19),IF(ISNUMBER(F22),F22/F19,IF(ISNUMBER(F23),F23/F19,"")),"") | G27: =IF(ISNUMBER(G19),IF(ISNUMBER(G22),G22/G19,IF(ISNUMBER(G23),G23/G19,"")),"") | H27: =IF(ISNUMBER(H19),IF(ISNUMBER(H22),H22/H19,IF(ISNUMBER(H23),H23/H19,"")),"") | I27: =IF(ISNUMBER(I19),IF(ISNUMBER(I22),I22/I19,IF(ISNUMBER(I23),I23/I19,"")),"") | J27: =IF(ISNUMBER(J19),IF(ISNUMBER(J22),J22/J19,IF(ISNUMBER(J23),J23/J19,"")),"") | ... S27: =IF(ISNUMBER(S19),IF(ISNUMBER(S22),S22/S19,IF(ISNUMBER(S23),S23/S19,"")),"") -> 0.77970926 | T27: Formula. Uses total sales, else domestic (understates where exports excluded).
A28: Capacity change vs prior FY | B28: units p.a. | D28: =IF(AND(ISNUMBER(D19),ISNUMBER(C19)),D19-C19,"") | E28: =IF(AND(ISNUMBER(E19),ISNUMBER(D19)),E19-D19,"") | F28: =IF(AND(ISNUMBER(F19),ISNUMBER(E19)),F19-E19,"") | G28: =IF(AND(ISNUMBER(G19),ISNUMBER(F19)),G19-F19,"") | H28: =IF(AND(ISNUMBER(H19),ISNUMBER(G19)),H19-G19,"") | I28: =IF(AND(ISNUMBER(I19),ISNUMBER(H19)),I19-H19,"") | J28: =IF(AND(ISNUMBER(J19),ISNUMBER(I19)),J19-I19,"") | K28: =IF(AND(ISNUMBER(K19),ISNUMBER(J19)),K19-J19,"") | ... S28: =IF(AND(ISNUMBER(S19),ISNUMBER(R19)),S19-R19,"") -> 170000 | T28: Formula; blank where either year undisclosed.
A29: Utilisation — company-reported | B29: % | O29: 0.7996 | P29: 0.9445 | T29: DRHP: Chennai utilisation on closing installed capacity (row 25 replicates this basis).
A30: Source IDs (see Source Log) | C30: HY04 | D30: HY04 | I30: HY05 | J30: HY05; HY18 | K30: HY06; HY18 | L30: HY07 | M30: HY09 | N30: HY09 | O30: HY08; HY11 | P30: HY08; HY11 | Q30: HY09; HY10; HY11 | R30: HY11 | S30: HY11; HY15
A31: Year notes | C31: Plant 2 (Feb-2008) doubled capacity to 0.6m | D31: c.12% debottleneck to c.670k planned | I31: Stated May-2016 as fully utilised | J31: Third plant (1m) evaluated; not executed | K31: Stated Mar/Jul-2018 | L31: +50k from Jan-2019 (value engineering) | M31: Bracketed: 7.5 lakh until H1-CY2023 | N31: Bracketed: 7.5 lakh until H1-CY2023 | O31: DRHP | P31: DRHP | Q31: 770k -> 824k (H1-CY2023) | R31: Talegaon engine shop SOP Jun-2025 (FY26) | S31: Talegaon vehicles from 1-Oct-2025 (+170k)
A33: C. PLANT-LEVEL CAPACITY AND OUTPUT BY FISCAL YEAR (disclosed points only; no interpolation)
A34: Plant / line | B34: Unit | C34: FY10 | D34: FY11 | E34: FY12 | F34: FY13 | G34: FY14 | H34: FY15 | I34: FY16 | J34: FY17 | K34: FY18 | L34: FY19 | M34: FY20 | N34: FY21 | O34: FY22 | P34: FY23 | Q34: FY24 | R34: FY25 | S34: FY26 | T34: Notes [sources]
A35: Chennai (Plants 1+2) capacity | B35: units p.a. | C35: 600000 | I35: 680000 | K35: 700000 | L35: 750000 | M35: 750000 | N35: 750000 | O35: 758000 | P35: 770000 | Q35: 824000 | R35: 824000 | S35: 824000 | T35: Plant 1 (1998, 300k reached 2006) + Plant 2 (Feb-2008, 300k) [HY01; HY02; HY08; HY11]
A36: Talegaon / Pune capacity | B36: units p.a. | S36: 170000 | T36: SOP 1-Oct-2025; to 250k by 2028 [HY11; HY12]
A37: Production — Chennai Plant 1 | B37: units | O37: 289308 | P37: 350342 | Q37: 408150 | R37: 408800 | S37: 352375 | T37: FY26 AR [HY11]
A38: Production — Chennai Plant 2 | B38: units | O38: 316792 | P38: 376958 | Q38: 379350 | R38: 354100 | S38: 352075 | T38: FY26 AR [HY11]
A39: Production — Pune (Talegaon) | B39: units | S39: 64830 | T39: Six months of operation [HY11]
A40: Check: plant production sum | B40: units | C40: =IF(COUNT(C37,C38,C39)=0,"",SUM(C37,C38,C39)) | D40: =IF(COUNT(D37,D38,D39)=0,"",SUM(D37,D38,D39)) | E40: =IF(COUNT(E37,E38,E39)=0,"",SUM(E37,E38,E39)) | F40: =IF(COUNT(F37,F38,F39)=0,"",SUM(F37,F38,F39)) | G40: =IF(COUNT(G37,G38,G39)=0,"",SUM(G37,G38,G39)) | H40: =IF(COUNT(H37,H38,H39)=0,"",SUM(H37,H38,H39)) | I40: =IF(COUNT(I37,I38,I39)=0,"",SUM(I37,I38,I39)) | J40: =IF(COUNT(J37,J38,J39)=0,"",SUM(J37,J38,J39)) | ... S40: =IF(COUNT(S37,S38,S39)=0,"",SUM(S37,S38,S39)) -> 769280 | T40: Formula; should equal row 21
A41: Talegaon engine capacity | B41: engines p.a. | S41: 150000 | T41: Engine shop SOP 16-Jun-2025 [HY12; HY13]
A43: D. PLANT REGISTER
A44: Plant / site | B44: Location | D44: Entity / ownership | F44: SOP / commissioned | G44: Vehicle category | I44: Key models (latest disclosed) | M44: Platforms | O44: Initial capacity (units p.a.) | P44: Latest capacity (units p.a.) | Q44: As of | R44: Status | S44: Notes | V44: Sources [confidence]
A45: Chennai Plant 1 | B45: Irungattukottai/Sriperumbudur, Tamil Nadu | D45: HMIL | F45: 1998 | G45: PV | I45: Separate assembly line; model split not disclosed | M45: K1 / K2 (see F) | P45: 824,000 (Chennai combined) | Q45: FY26 | R45: Operating | S45: HMC's first integrated plant outside Korea; 300k installed reached in 2006; 525-acre site shared with Plant 2 | V45: [High] HY01; HY02; HY11
A46: Chennai Plant 2 | B46: Sriperumbudur, Tamil Nadu | D46: HMIL | F46: 02-Feb-2008 | G46: PV | I46: Separate assembly line; model split not disclosed | M46: K1 / K2 | O46: 300000 | P46: 824,000 (Chennai combined) | Q46: FY26 | R46: Operating | S46: Built Nov-2005 to 2007; c.US$1bn; doubled capacity to 600k | V46: [High] HY01; HY17
A47: Chennai powertrain | B47: Sriperumbudur, Tamil Nadu | D47: HMIL | F47: 2008 | G47: Engines & transmissions | I47: Kappa 1.2L at SOP | M47: — | O47: 300000 | P47: n.d. | Q47: 2008 | R47: Operating | S47: Capacity in engines p.a. | V47: [Medium] HY03
A48: Talegaon (Pune) | B48: MIDC Talegaon, Maharashtra | D48: HMIL (ex-GM India assets) | F48: Engines 16-Jun-2025; vehicles 1-Oct-2025 | G48: PV | I48: Venue (2nd gen) first | M48: K1 | O48: 170000 | P48: 170000 | Q48: Oct-2025 | R48: Ramp-up | S48: GM-era 130k vehicles / 160k engines; investment Rs7,000cr -> Rs11,000cr; 250k by 2028; engine capacity 150k | V48: [High] HY09; HY11; HY12; HY13; HY14
A50: E. CAPACITY EVENT LOG (chronological; positive = addition)
A51: Event | B51: Date | C51: FY | D51: Type | F51: Plant / site | H51: Capacity change (units p.a.) | I51: Plant capacity after | J51: Company capacity after | K51: Capex (Rs cr) | L51: Status | N51: Notes | V51: Sources
A52: Chennai Plant 1 SOP (Santro) | B52: 1998 | C52: FY99 | D52: New plant | F52: Chennai Plant 1 | L52: Commissioned | N52: Installed 300k reached 2006; 327k produced in CY2007 | V52: HY02
A53: Chennai Plant 2 SOP | B53: 02-Feb-2008 | C53: FY08 | D53: New plant | F53: Chennai Plant 2 | H53: 300000 | I53: 300000 | J53: 600000 | K53: c.US$1bn | L53: Commissioned | N53: Global small-car export hub | V53: HY01; HY17
A54: Engine & transmission plant | B54: 2008 | C54: FY09 | D54: Powertrain | F54: Chennai | H54: 300000 | L54: Commissioned | N54: Engines p.a. | V54: HY03
A55: c.12% debottleneck planned | B55: Aug-2010 | C55: FY11 | D55: Debottlenecking | F55: Chennai | H55: 70000 | J55: 670000 | L55: Announced | N55: Delivery not confirmed in sources | V55: HY04
A56: Capacity fully utilised at 680k; third plant evaluated | B56: May-2016 | C56: FY17 | D56: Plan (not executed) | F56: Third plant (Gujarat preferred) | H56: 1000000 | J56: 680000 | K56: 4500 | L56: Not executed | N56: Kia's Anantapur plant (2019) later served HMG growth | V56: HY05
A57: +50k via value engineering | B57: Jul-2018 / Jan-2019 | C57: FY19 | D57: Debottlenecking | F57: Chennai | H57: 50000 | I57: 750000 | J57: 750000 | K57: 0 | L57: Completed | N57: No incremental investment | V57: HY06; HY07
A58: Proposal: +100k (50k CKD, 50k CBU) | B58: Nov-2018 | C58: FY19 | D58: Expansion (proposed) | F58: Chennai | H58: 100000 | I58: 800000 | L58: Proposed | N58: Delivered as 758k-824k path through FY24 | V58: HY19
A59: Debottlenecking to 824k | B59: H1-CY2023 | C59: FY24 | D59: Debottlenecking | F59: Chennai | H59: 54000 | I59: 824000 | J59: 824000 | L59: Completed | N59: 770k (FY23) -> 824k | V59: HY09; HY10
A60: Talegaon APA with GM India | B60: 16-Aug-2023 | C60: FY24 | D60: Acquisition | F60: Talegaon | L60: Completed | N60: GM plant idle since 2020 | V60: HY09
A61: Talegaon engine shop SOP | B61: 16-Jun-2025 | C61: FY26 | D61: Powertrain | F61: Talegaon | H61: 150000 | L61: Commissioned | N61: Engines p.a. | V61: HY12; HY13
A62: Talegaon vehicle SOP | B62: 01-Oct-2025 | C62: FY26 | D62: New plant | F62: Talegaon | H62: 170000 | I62: 170000 | J62: 994000 | K62: 11000 | L62: Commissioned | N62: Capex = total Talegaon commitment (raised from Rs7,000cr) | V62: HY11; HY12
A63: Chennai modernisation | B63: 2025 | C63: FY26 | D63: Upgrade | F63: Chennai | K63: 1500 | L63: Committed | N63: No capacity figure attached | V63: HY16
A65: F. PLATFORMS, MODELS AND PLANT ALLOCATION (confidence in brackets; model-plant mapping is rarely company-disclosed)
A66: Platform / architecture | B66: Powertrain | D66: Segment | F66: Models | L66: Plant(s) | O66: First SOP | P66: Notes | V66: Sources [confidence]
A67: K1 (HMG small-car platform) | B67: ICE (petrol, diesel, CNG) | D67: Hatch, compact sedan, sub-4m SUV | F67: Grand i10 Nios, Aura, Exter, i20, Venue | L67: Chennai; Talegaon (Venue Gen 2) | O67: — | P67: Shared with Kia India (Sonet) — Kia capacity not included | V67: [Medium] HY14
A68: K2 (HMG mid platform) | B68: ICE; BEV derivative (Creta Electric) | D68: Sedan, mid SUV | F68: Verna, Creta, Alcazar, Creta Electric | L68: Chennai | O68: — | P68: Shared with Kia Seltos/Carens | V68: [Medium]
A69: E-GMP | B69: BEV | D69: Premium crossover | F69: Ioniq 5 (local assembly) | L69: Chennai | O69: 2023 | P69: Low volume | V69: [Medium]
A71: G. FORWARD CAPACITY PIPELINE — Tier 1 = commissioned after FY26 or under execution; Tier 2 = announced with timeline/site; Memo = not summed
A72: Project | B72: Location | D72: Capacity add (units p.a.) | E72: Expected timing | F72: Capex (Rs cr) | G72: Tier | H72: Status (as of 14-Oct-2026) | J72: Notes | V72: Sources
A73: Talegaon ramp to 250k | B73: Pune | D73: 80000 | E73: By 2028 | G73: Tier 1 | H73: Under way (phased) | J73: Within Rs11,000cr Talegaon commitment | V73: HY10; HY12
A74: Chennai modernisation | B74: Tamil Nadu | E74: FY26-FY27 | F74: 1500 | G74: Memo | H74: Committed | J74: Modernisation, no capacity number | V74: HY16
A76: H. ANALYST NOTES
A77: Capacity barely moved for a decade. 600k (FY10) -> 680k (FY16) -> 750k (FY19) through debottlenecking only; Talegaon is the first new site since 2008.
A78: Plant 1 is the swing line. Plant 1 output falls c.14% in FY26 (408,800 -> 352,375) as Venue moves to Pune.
A79: Reported utilisation uses closing capacity. DRHP: 79.96% (FY22), 94.45% (FY23) — row 25 replicates this basis.
A80: Exports absorb slack. Exports rise 16% to 190,125 in FY26 while domestic falls 2%.

Sheet M&M
A1: Mahindra & Mahindra Ltd — Automotive (SUV)
A2: MM IN | Segment: PV | Units: vehicles p.a. unless stated | FY = year to 31-Mar | As of 14-Oct-2026
A3: Scope: SUV operational capacity disclosed by M&M in units/month (ICE + BEV); annualised x12. Excludes LCV/3W (MLMML), trucks and tractors unless stated.
A4: A. SNAPSHOT
A5: Latest disclosed installed capacity (units p.a.) | C5: 774000 | F5: As of FY26 exit (64.5k/month) [MM08; MM11]
A6: As of | C6: FY26 exit (64.5k/month)
A7: Capacity definition / scope | C7: Operational SUV capacity, units/month x 12 (ICE 56.5k + BEV 8k at FY26 exit)
A8: Vehicle assembly sites | C8: SUVs: Chakan, Nashik (+ Haridwar/Zaheerabad under MLMML); Nagpur from 2028
A9: FY26 volume (units) | C9: =IF(ISNUMBER(S23),S23,"n.d.") -> 660276 | F9: Domestic SUV sales (FY26) — exports excluded
A10: FY26 volume basis | C10: Domestic SUV sales (FY26) — exports excluded
A11: FY26 utilisation | C11: =IFERROR(C9/S19,"n.d.") -> 0.85306977 | F11: FY26 volume ÷ FY26 year-end capacity (row 19)
A12: Outlook base capacity (units p.a.) | C12: =S19 -> 774000 | F12: FY26 year-end (row 19)
A13: Company capacity target (units p.a.) | C13: =2*S19 -> 1548000 | F13: [MM08; MM09]
A14: Target timing | C14: FY31 (2x FY26)
A15: Bottom line | C15: The fastest capacity ramp in Indian PVs — running behind its own plan. SUV capacity more than triples from 19k/month (FY20) to 64.5k (FY26) and is guided to 82k by H2FY27 and c.132k/month by FY31 with Nagpur. FY25 (59k vs 64k plan) and FY26 (64.5k vs 72k plan) both undershoot guidance — execution slippage is the watch item.
A17: B. COMPANY-LEVEL CAPACITY AND OUTPUT HISTORY, FY10–FY26 (blue = sourced input; black = formula; orange = verify; light blue = bracketed carry)
A18: Metric | B18: Unit | C18: FY10 | D18: FY11 | E18: FY12 | F18: FY13 | G18: FY14 | H18: FY15 | I18: FY16 | J18: FY17 | K18: FY18 | L18: FY19 | M18: FY20 | N18: FY21 | O18: FY22 | P18: FY23 | Q18: FY24 | R18: FY25 | S18: FY26 | T18: Notes
A19: Installed capacity, FY-end (reported) | B19: units p.a. | M19: =IF(ISNUMBER(M35),M35*12,"") -> 228000 | O19: =IF(ISNUMBER(O35),O35*12,"") -> 348000 | P19: =IF(ISNUMBER(P35),P35*12,"") -> 468000 | Q19: =IF(ISNUMBER(Q35),Q35*12,"") -> 588000 | R19: =IF(ISNUMBER(R35),R35*12,"") -> 708000 | S19: =IF(ISNUMBER(S35),S35*12,"") -> 774000 | T19: Formula: monthly operational capacity (section C) x 12. No consistent company series before FY20 in sources reviewed.
A20: Capacity basis code | B20: code | M20: A | O20: A | P20: A | Q20: A | R20: A | S20: A | T20: R = company-reported total; S = sum of company-disclosed plants; M = management statement via media; A = monthly x12; D = DRHP/RHP
A21: Production — actual | B21: units | T21: Not disclosed in sources reviewed.
A22: Sales / dispatches — actual, total | B22: units | T22: Total SUV incl. exports not captured.
A23: of which domestic | B23: units | R23: 551487 | S23: 660276 | T23: Domestic SUV volumes (record 660,276 in FY26).
A24: of which exports | B24: units
A25: Utilisation — production ÷ FY-end capacity | B25: % | C25: =IF(AND(ISNUMBER(C21),ISNUMBER(C19)),C21/C19,"") | D25: =IF(AND(ISNUMBER(D21),ISNUMBER(D19)),D21/D19,"") | E25: =IF(AND(ISNUMBER(E21),ISNUMBER(E19)),E21/E19,"") | F25: =IF(AND(ISNUMBER(F21),ISNUMBER(F19)),F21/F19,"") | G25: =IF(AND(ISNUMBER(G21),ISNUMBER(G19)),G21/G19,"") | H25: =IF(AND(ISNUMBER(H21),ISNUMBER(H19)),H21/H19,"") | I25: =IF(AND(ISNUMBER(I21),ISNUMBER(I19)),I21/I19,"") | J25: =IF(AND(ISNUMBER(J21),ISNUMBER(J19)),J21/J19,"") | ... S25: =IF(AND(ISNUMBER(S21),ISNUMBER(S19)),S21/S19,"") | T25: Formula. Company convention (e.g., HMIL DRHP). Depressed in commissioning years.
A26: Utilisation — production ÷ avg(opening, closing) capacity | B26: % | C26: =IF(AND(ISNUMBER(C21),ISNUMBER(C19)),C21/C19,"") | D26: =IF(AND(ISNUMBER(D21),ISNUMBER(D19)),D21/IF(ISNUMBER(C19),AVERAGE(C19,D19),D19),"") | E26: =IF(AND(ISNUMBER(E21),ISNUMBER(E19)),E21/IF(ISNUMBER(D19),AVERAGE(D19,E19),E19),"") | F26: =IF(AND(ISNUMBER(F21),ISNUMBER(F19)),F21/IF(ISNUMBER(E19),AVERAGE(E19,F19),F19),"") | G26: =IF(AND(ISNUMBER(G21),ISNUMBER(G19)),G21/IF(ISNUMBER(F19),AVERAGE(F19,G19),G19),"") | H26: =IF(AND(ISNUMBER(H21),ISNUMBER(H19)),H21/IF(ISNUMBER(G19),AVERAGE(G19,H19),H19),"") | I26: =IF(AND(ISNUMBER(I21),ISNUMBER(I19)),I21/IF(ISNUMBER(H19),AVERAGE(H19,I19),I19),"") | J26: =IF(AND(ISNUMBER(J21),ISNUMBER(J19)),J21/IF(ISNUMBER(I19),AVERAGE(I19,J19),J19),"") | K26: =IF(AND(ISNUMBER(K21),ISNUMBER(K19)),K21/IF(ISNUMBER(J19),AVERAGE(J19,K19),K19),"") | ... S26: =IF(AND(ISNUMBER(S21),ISNUMBER(S19)),S21/IF(ISNUMBER(R19),AVERAGE(R19,S19),S19),"") | T26: Formula. Uses closing capacity where opening not disclosed.
A27: Utilisation — sales ÷ FY-end capacity | B27: % | C27: =IF(ISNUMBER(C19),IF(ISNUMBER(C22),C22/C19,IF(ISNUMBER(C23),C23/C19,"")),"") | D27: =IF(ISNUMBER(D19),IF(ISNUMBER(D22),D22/D19,IF(ISNUMBER(D23),D23/D19,"")),"") | E27: =IF(ISNUMBER(E19),IF(ISNUMBER(E22),E22/E19,IF(ISNUMBER(E23),E23/E19,"")),"") | F27: =IF(ISNUMBER(F19),IF(ISNUMBER(F22),F22/F19,IF(ISNUMBER(F23),F23/F19,"")),"") | G27: =IF(ISNUMBER(G19),IF(ISNUMBER(G22),G22/G19,IF(ISNUMBER(G23),G23/G19,"")),"") | H27: =IF(ISNUMBER(H19),IF(ISNUMBER(H22),H22/H19,IF(ISNUMBER(H23),H23/H19,"")),"") | I27: =IF(ISNUMBER(I19),IF(ISNUMBER(I22),I22/I19,IF(ISNUMBER(I23),I23/I19,"")),"") | J27: =IF(ISNUMBER(J19),IF(ISNUMBER(J22),J22/J19,IF(ISNUMBER(J23),J23/J19,"")),"") | ... S27: =IF(ISNUMBER(S19),IF(ISNUMBER(S22),S22/S19,IF(ISNUMBER(S23),S23/S19,"")),"") -> 0.85306977 | T27: Formula. Uses total sales, else domestic (understates where exports excluded).
A28: Capacity change vs prior FY | B28: units p.a. | D28: =IF(AND(ISNUMBER(D19),ISNUMBER(C19)),D19-C19,"") | E28: =IF(AND(ISNUMBER(E19),ISNUMBER(D19)),E19-D19,"") | F28: =IF(AND(ISNUMBER(F19),ISNUMBER(E19)),F19-E19,"") | G28: =IF(AND(ISNUMBER(G19),ISNUMBER(F19)),G19-F19,"") | H28: =IF(AND(ISNUMBER(H19),ISNUMBER(G19)),H19-G19,"") | I28: =IF(AND(ISNUMBER(I19),ISNUMBER(H19)),I19-H19,"") | J28: =IF(AND(ISNUMBER(J19),ISNUMBER(I19)),J19-I19,"") | K28: =IF(AND(ISNUMBER(K19),ISNUMBER(J19)),K19-J19,"") | ... S28: =IF(AND(ISNUMBER(S19),ISNUMBER(R19)),S19-R19,"") -> 66000 | T28: Formula; blank where either year undisclosed.
A29: Utilisation — company-reported | B29: % | T29: Q4FY25: >90% SUV utilisation (MM07); Q3FY26: EV 93%, CV 86% (MM15) — not entered as point values.
A30: Source IDs (see Source Log) | C30: MM01 | M30: MM05 | O30: MM03; MM04 | P30: MM04; MM05 | Q30: MM05 | R30: MM08; MM13 | S30: MM08; MM11; MM12
A31: Year notes | C31: Chakan SOP 13-Mar-2010 (0.3m incl. 50k trucks) | M31: 19k/month | O31: 29k/month (stated Q2FY23) | P31: 39k/month | Q31: 49k/month | R31: 59k/month vs 64k plan | S31: 64.5k/month vs 72k plan; Nagpur announced
A33: C. PLANT-LEVEL CAPACITY AND OUTPUT BY FISCAL YEAR (disclosed points only; no interpolation)
A34: Plant / line | B34: Unit | C34: FY10 | D34: FY11 | E34: FY12 | F34: FY13 | G34: FY14 | H34: FY15 | I34: FY16 | J34: FY17 | K34: FY18 | L34: FY19 | M34: FY20 | N34: FY21 | O34: FY22 | P34: FY23 | Q34: FY24 | R34: FY25 | S34: FY26 | T34: Notes [sources]
A35: SUV operational capacity — total | B35: units/month | M35: 19000 | O35: 29000 | P35: 39000 | Q35: 49000 | R35: 59000 | S35: 64500 | T35: Drives row 19 (x12) [MM03; MM04; MM05; MM08]
A36: of which ICE | B36: units/month | R36: 54000 | S36: 56500 | T36: [MM07; MM08]
A37: of which BEV | B37: units/month | R37: 5000 | S37: 8000 | T37: INGLO + XUV400 [MM08]
A38: Memo: capacity guided a year earlier | B38: units/month | R38: 64000 | S38: 72000 | T38: Plan vs delivery [MM05]
A39: Chakan plant (all vehicles) | B39: units p.a. | C39: 300000 | M39: 320000 | T39: Incl. trucks; 2019 statement placed in FY20 [MM01; MM02]
A41: D. PLANT REGISTER
A42: Plant / site | B42: Location | D42: Entity / ownership | F42: SOP / commissioned | G42: Vehicle category | I42: Key models (latest disclosed) | M42: Platforms | O42: Initial capacity (units p.a.) | P42: Latest capacity (units p.a.) | Q42: As of | R42: Status | S42: Notes | V42: Sources [confidence]
A43: Chakan | B43: Pune, Maharashtra | D43: M&M (EVs via Mahindra Electric Automobile) | F43: 13-Mar-2010 | G43: SUV; trucks; BEV | I43: Scorpio-N, trucks 0.75-49t (2022); XUV700, Thar Roxx, INGLO BEVs (per media) | M43: Scorpio-N ladder; W601; INGLO; NU_IQ (FY28) | O43: 300000 | P43: 320000 | Q43: c.2019 | R43: Operating; +10k/month NU_IQ by FY28 | S43: 700 acres; engine shop 120k UV + 40k truck engines at SOP; capex c.Rs4,000cr planned (2007) | V43: [High/Med] MM01; MM02; MM14; MM16; MM09
A44: Nashik (Satpur) | B44: Nashik, Maharashtra | D44: M&M | F44: pre-2000 (n.d.) | G44: SUV | I44: Allocation not disclosed in sources reviewed | M44: X100; legacy ladder | P44: n.d. | Q44: — | R44: Operating | S44: 2006 plan: 80k -> 150k p.a. | V44: [Medium] MM17
A45: Igatpuri (engines) | B45: Nashik, Maharashtra | D45: M&M | F45: n.d. | G45: Powertrain | I45: Engines | M45: — | O45: 450/day (2006) | P45: 1,100/day | Q45: n.d. | R45: Operating | S45: Land being added in Igatpuri-Nashik corridor for engine capacity (2026) | V45: [Medium] MM17; MM18; MM10
A46: Haridwar | B46: Uttarakhand | D46: Mahindra Last Mile Mobility (MLMML) | F46: Dec-2005 | G46: SUV (Bolero); e-3W | I46: Bolero; Scorpio (to 2022); e-Alfa, e-Treo | M46: Legacy ladder | P46: n.d. | Q46: — | R46: Operating | S46: Millionth vehicle c.2019 | V46: [Medium] MM02; MM18
A47: Zaheerabad | B47: Telangana | D47: MLMML | F47: n.d. | G47: LCV, 3W | I47: n.d. | M47: — | P47: n.d. | Q47: — | R47: Operating | S47: Millionth vehicle c.2019 | V47: [Medium] MM02; MM18
A48: Kandivali | B48: Mumbai, Maharashtra | D48: M&M | F48: First plant (n.d.) | G48: Legacy UVs / components | I48: n.d. | M48: — | P48: n.d. | Q48: — | R48: Operating | S48: Millionth vehicle pre-2019 | V48: [Low] MM02
A49: Nagpur (new) | B49: Nagpur, Maharashtra | D49: M&M | F49: 2028 (planned) | G49: SUV (ICE/EV) + tractors | I49: — | M49: NU_IQ | P49: >500,000 vehicles + 100,000 tractors (full) | Q49: Feb-2026 | R49: Announced | S49: 1,500 acres; Rs15,000cr over a decade; supplier park at Sambhajinagar; +20k/month H1FY30, +20k/month H1FY31 | V49: [High] MM08; MM10
A51: E. CAPACITY EVENT LOG (chronological; positive = addition)
A52: Event | B52: Date | C52: FY | D52: Type | F52: Plant / site | H52: Capacity change (units p.a.) | I52: Plant capacity after | J52: Company capacity after | K52: Capex (Rs cr) | L52: Status | N52: Notes | V52: Sources
A53: Haridwar SOP | B53: Dec-2005 | C53: FY06 | D53: New plant | F53: Haridwar | L53: Commissioned | N53: Now MLMML | V53: MM02
A54: Nashik expansion plan | B54: 2006 | C54: FY07 | D54: Expansion (planned) | F54: Nashik | H54: 70000 | I54: 150000 | K54: 550 | L54: Announced | N54: Capex = US$118m incl. new line; Igatpuri engines 450 -> 800/day | V54: MM17
A55: Chakan inaugurated | B55: 13-Mar-2010 | C55: FY10 | D55: New plant | F55: Chakan | H55: 300000 | I55: 300000 | K55: 4000 | L55: Commissioned | N55: Incl. 50k trucks; capex per 2007 plan | V55: MM01; MM16
A56: SUV capacity 19k/month | B56: Mar-2020 | C56: FY20 | D56: Disclosure | F56: All SUV | J56: 228000 | L56: Reported | N56: Pre-ramp base | V56: MM05
A57: Capacity plan 29k -> 49k/month | B57: Nov-2022 | C57: FY23 | D57: Expansion plan | F57: Multiple | L57: Announced | N57: Thar, XUV300/400, XUV700, Scorpio-N (section F2) | V57: MM03
A58: 39k/month achieved | B58: Mar-2023 | C58: FY23 | D58: Debottlenecking | F58: Multiple | J58: 468000 | L58: Completed | V58: MM04
A59: 49k/month achieved | B59: Mar-2024 | C59: FY24 | D59: Debottlenecking | F59: Multiple | J59: 588000 | L59: Completed | V59: MM05
A60: EV capacity for INGLO | B60: Nov-2024 | C60: FY25 | D60: New lines (BEV) | F60: Chakan | L60: Announced | N60: 10k/month by Mar-2025 guided; 5k reported at FY25-end | V60: MM06; MM08
A61: 59k/month at FY25-end | B61: Mar-2025 | C61: FY25 | D61: Disclosure | F61: Multiple | J61: 708000 | L61: Reported | N61: 54k ICE + 5k BEV vs 64k plan | V61: MM07; MM08
A62: Nagpur integrated plant announced | B62: 06-Feb-2026 | C62: FY26 | D62: New plant (announced) | F62: Nagpur | H62: 500000 | K62: 15000 | L62: Announced | N62: Vehicles >500k + tractors 100k; SOP 2028 | V62: MM10
A63: 64.5k/month at FY26-end | B63: Mar-2026 | C63: FY26 | D63: Disclosure | F63: Multiple | J63: 774000 | L63: Reported | N63: 56.5k ICE + 8k BEV vs 72k plan | V63: MM08; MM11
A65: F. PLATFORMS, MODELS AND PLANT ALLOCATION (confidence in brackets; model-plant mapping is rarely company-disclosed)
A66: Platform / architecture | B66: Powertrain | D66: Segment | F66: Models | L66: Plant(s) | O66: First SOP | P66: Notes | V66: Sources [confidence]
A67: Scorpio-N body-on-frame | B67: ICE | D67: Mid/large SUV | F67: Scorpio-N, Thar Roxx | L67: Chakan | O67: 2022 | V67: [Medium] MM14
A68: W601 monocoque | B68: ICE | D68: Mid SUV | F68: XUV700 / XUV 7XO | L68: Chakan (per media) | O68: 2021 | V68: [Medium]
A69: X100 (Tivoli-derived) | B69: ICE + BEV | D69: Sub-4m SUV | F69: XUV300 -> XUV 3XO; XUV400; XUV 3XO EV | L69: Nashik (per media) | O69: 2019 | V69: [Medium]
A70: INGLO (born-electric) | B70: BEV | D70: SUV | F70: BE 6, XEV 9e, XEV 9S | L70: Chakan | O70: 2025 | P70: Company-named platform | V70: [High] MM06; MM08
A71: NU_IQ (modular, multi-energy) | B71: ICE / hybrid / BEV | D71: Compact SUVs | F71: Vision S/X/T-derived (from FY27) | L71: Chakan (+10k/month), Nagpur | O71: FY27-FY28 | P71: Company-named platform | V71: [High] MM09; MM10
A72: Legacy ladder frame | B72: ICE | D72: Utility SUV | F72: Bolero, Bolero Neo, Scorpio Classic, Thar 3-door | L72: Nashik / Chakan / Haridwar (mix n.d.) | O72: — | P72: Bolero 9.5k and Scorpio Classic 5.5k per month | V72: [Low-Med] MM18
A74: F2. MODEL-LEVEL CAPACITY DISCLOSURES (units/month)
A75: Model / family | B75: Plant | D75: Capacity before (units/month) | E75: Capacity after (units/month) | F75: Timing | H75: Notes | V75: Sources
A76: Thar (3-door) | B76: n.d. | D76: 4000 | E76: 6000 | F76: By Q4FY23 | V76: MM03
A77: XUV300 / XUV400 | B77: n.d. | D77: 5000 | E77: 9500 | F77: 7.5k Q4FY23; 9.5k Q3FY24 | V77: MM03
A78: XUV700 | B78: Chakan (media) | D78: 6000 | E78: 10000 | F78: Q3FY24 | V78: MM03
A79: Scorpio-N | B79: Chakan | D79: 6000 | E79: 10000 | F79: Q4FY24 | V79: MM03
A80: Thar 3-door + Thar Roxx (fungible) | B80: n.d. | D80: 9500 | E80: 11500 | F80: Jan-2025 ('a couple of thousand') | H80: After value is approximate | V80: MM06
A81: Bolero family | B81: n.d. | D81: 9500 | E81: 9500 | F81: Ongoing | V81: MM18
A82: Scorpio Classic (incl. pickup) | B82: n.d. | D82: 5500 | E82: 5500 | F82: Ongoing | V82: MM18
A83: BEV (INGLO + XUV400) | B83: Chakan | D83: 5000 | E83: 12000 | F83: FY25 5k; FY26 8k; H2FY27 12k | V83: MM08; MM09
A85: G. FORWARD CAPACITY PIPELINE — Tier 1 = commissioned after FY26 or under execution; Tier 2 = announced with timeline/site; Memo = not summed
A86: Project | B86: Location | D86: Capacity add (units p.a.) | E86: Expected timing | F86: Capex (Rs cr) | G86: Tier | H86: Status (as of 14-Oct-2026) | J86: Notes | V86: Sources
A87: H1FY27 ICE debottlenecking (56.5k -> 60k/month) | B87: Existing plants | D87: =3500*12 -> 42000 | E87: H1FY27 | G87: Tier 1 | H87: Under execution ('on track') | J87: 3.5k/month x 12 | V87: MM08; MM19
A88: H2FY27 new-launch capacity (+10k ICE, +4k BEV per month) | B88: Existing plants | D88: =14000*12 -> 168000 | E88: H2FY27 | F88: 27000 | G88: Tier 1 | H88: Confirmed by company | J88: Capex = FY25-FY27 auto programme | V88: MM07; MM09
A89: Chakan NU_IQ line (+10k/month) | B89: Chakan | D89: =10000*12 -> 120000 | E89: By FY28-end | G89: Tier 2 | H89: Announced | J89: Takes operational capacity to 92k/month | V89: MM09
A90: Nagpur phase 1 (+20k/month) | B90: Nagpur | D90: =20000*12 -> 240000 | E90: H1FY30 | F90: 15000 | G90: Tier 2 | H90: Announced; SOP 2028 | J90: Capex = total Nagpur over a decade | V90: MM08; MM10
A91: Nagpur phase 2 (+20k/month) | B91: Nagpur | D91: =20000*12 -> 240000 | E91: H1FY31 | G91: Tier 2 | H91: Announced | J91: c.132k/month total | V91: MM08
A92: Target: double capacity FY26 -> FY31 | B92: India | E92: FY31 | G92: Memo | H92: Target | J92: Separately 'c.10 lakh by 2030' reported (MM11) | V92: MM08; MM11
A94: H. ANALYST NOTES
A95: Ramp is real but runs behind plan. FY25 exit 59k vs 64k guided; FY26 exit 64.5k vs 72k guided — c.8-10% annual slippage.
A96: BEV is still a small slice. 8k/month (12% of total) at FY26-end; EV lines run at 93% (Q3FY26, media).
A97: Utilisation proxy excludes exports. FY26 domestic SUV volume vs annualised capacity gives c.85%; true utilisation is higher.
A98: Pre-FY20 history is a gap. No consistent auto capacity series before FY20 in sources reviewed — fill from ARs.

Sheet Tata PV
A1: Tata Motors Passenger Vehicles Ltd (TMPV) — India PV/EV (ex-JLR plants abroad)
A2: TMPV IN | Segment: PV | Units: vehicles p.a. unless stated | FY = year to 31-Mar | As of 14-Oct-2026
A3: Scope: India PV/EV capacity: Pune (Pimpri/Chikhli), Ranjangaon (FIAPL JV with Stellantis), Sanand I, Sanand II (ex-Ford, TPEML), Panapakkam (with JLR, from Feb-2026). TMPV demerged from the CV business on 1-Oct-2025.
A4: A. SNAPSHOT
A5: Latest disclosed installed capacity (units p.a.) | C5: 900000 | F5: As of Jun/Jul-2026 (mgmt) [TP12; TP08]
A6: As of | C6: Jun/Jul-2026 (mgmt)
A7: Capacity definition / scope | C7: Installed PV capacity per management commentary (c.0.9m); Investor Day 2024 cited '1mn+' incl. expandable Sanand-2
A8: Vehicle assembly sites | C8: 5+ — Pune (five plants), Ranjangaon (JV), Sanand I & II, Panapakkam
A9: FY26 volume (units) | C9: =IF(ISNUMBER(S22),S22,"n.d.") -> 642000 | F9: Total PV sales FY26 (c.642k incl. exports)
A10: FY26 volume basis | C10: Total PV sales FY26 (c.642k incl. exports)
A11: FY26 utilisation | C11: =IFERROR(C9/S19,"n.d.") -> 0.71333333 | F11: FY26 volume ÷ FY26 year-end capacity (row 19)
A12: Outlook base capacity (units p.a.) | C12: =S19 -> 900000 | F12: FY26 year-end (row 19)
A13: Company capacity target (units p.a.) | C13: 1300000 | F13: [TP11; TP12]
A14: Target timing | C14: 2-3 years from Jun-2026 (c.FY29)
A15: Bottom line | C15: Ample in aggregate, tight by model. c.0.9m installed vs c.642k FY26 sales (c.71%) yet management cites demand of c.70k/month outrunning supply — the constraint sits in specific shops and lines, which the Sanand +300k brownfield and multi-product line flexibility target.
A17: B. COMPANY-LEVEL CAPACITY AND OUTPUT HISTORY, FY10–FY26 (blue = sourced input; black = formula; orange = verify; light blue = bracketed carry)
A18: Metric | B18: Unit | C18: FY10 | D18: FY11 | E18: FY12 | F18: FY13 | G18: FY14 | H18: FY15 | I18: FY16 | J18: FY17 | K18: FY18 | L18: FY19 | M18: FY20 | N18: FY21 | O18: FY22 | P18: FY23 | Q18: FY24 | R18: FY25 | S18: FY26 | T18: Notes
A19: Installed capacity, FY-end (reported) | B19: units p.a. | O19: 480000 | S19: 900000 | T19: Management-commentary only; no year-end series since FY11. FY24 '1mn+' (Investor Day) vs c.0.9m (Jun-2026) — definitional (expandable vs installed); not entered.
A20: Capacity basis code | B20: code | O20: M | S20: M | T20: R = company-reported total; S = sum of company-disclosed plants; M = management statement via media; A = monthly x12; D = DRHP/RHP
A21: Production — actual | B21: units | T21: Not disclosed in sources reviewed.
A22: Sales / dispatches — actual, total | B22: units | C22: =232006+35107 -> 267113 | D22: =269194+53544 -> 322738 | E22: =298991+56329 -> 355320 | S22: 642000 | T22: FY10-FY12: 'Tata & other brand' cars + UVs per 20-F (incl. Fiat cars distributed and exports) — not like-for-like. FY26 c.642k (rounded, media).
A23: of which domestic | B23: units | R23: 553585 | S23: 631387 | T23: Domestic PV (incl. EV).
A24: of which exports | B24: units
A25: Utilisation — production ÷ FY-end capacity | B25: % | C25: =IF(AND(ISNUMBER(C21),ISNUMBER(C19)),C21/C19,"") | D25: =IF(AND(ISNUMBER(D21),ISNUMBER(D19)),D21/D19,"") | E25: =IF(AND(ISNUMBER(E21),ISNUMBER(E19)),E21/E19,"") | F25: =IF(AND(ISNUMBER(F21),ISNUMBER(F19)),F21/F19,"") | G25: =IF(AND(ISNUMBER(G21),ISNUMBER(G19)),G21/G19,"") | H25: =IF(AND(ISNUMBER(H21),ISNUMBER(H19)),H21/H19,"") | I25: =IF(AND(ISNUMBER(I21),ISNUMBER(I19)),I21/I19,"") | J25: =IF(AND(ISNUMBER(J21),ISNUMBER(J19)),J21/J19,"") | ... S25: =IF(AND(ISNUMBER(S21),ISNUMBER(S19)),S21/S19,"") | T25: Formula. Company convention (e.g., HMIL DRHP). Depressed in commissioning years.
A26: Utilisation — production ÷ avg(opening, closing) capacity | B26: % | C26: =IF(AND(ISNUMBER(C21),ISNUMBER(C19)),C21/C19,"") | D26: =IF(AND(ISNUMBER(D21),ISNUMBER(D19)),D21/IF(ISNUMBER(C19),AVERAGE(C19,D19),D19),"") | E26: =IF(AND(ISNUMBER(E21),ISNUMBER(E19)),E21/IF(ISNUMBER(D19),AVERAGE(D19,E19),E19),"") | F26: =IF(AND(ISNUMBER(F21),ISNUMBER(F19)),F21/IF(ISNUMBER(E19),AVERAGE(E19,F19),F19),"") | G26: =IF(AND(ISNUMBER(G21),ISNUMBER(G19)),G21/IF(ISNUMBER(F19),AVERAGE(F19,G19),G19),"") | H26: =IF(AND(ISNUMBER(H21),ISNUMBER(H19)),H21/IF(ISNUMBER(G19),AVERAGE(G19,H19),H19),"") | I26: =IF(AND(ISNUMBER(I21),ISNUMBER(I19)),I21/IF(ISNUMBER(H19),AVERAGE(H19,I19),I19),"") | J26: =IF(AND(ISNUMBER(J21),ISNUMBER(J19)),J21/IF(ISNUMBER(I19),AVERAGE(I19,J19),J19),"") | K26: =IF(AND(ISNUMBER(K21),ISNUMBER(K19)),K21/IF(ISNUMBER(J19),AVERAGE(J19,K19),K19),"") | ... S26: =IF(AND(ISNUMBER(S21),ISNUMBER(S19)),S21/IF(ISNUMBER(R19),AVERAGE(R19,S19),S19),"") | T26: Formula. Uses closing capacity where opening not disclosed.
A27: Utilisation — sales ÷ FY-end capacity | B27: % | C27: =IF(ISNUMBER(C19),IF(ISNUMBER(C22),C22/C19,IF(ISNUMBER(C23),C23/C19,"")),"") | D27: =IF(ISNUMBER(D19),IF(ISNUMBER(D22),D22/D19,IF(ISNUMBER(D23),D23/D19,"")),"") | E27: =IF(ISNUMBER(E19),IF(ISNUMBER(E22),E22/E19,IF(ISNUMBER(E23),E23/E19,"")),"") | F27: =IF(ISNUMBER(F19),IF(ISNUMBER(F22),F22/F19,IF(ISNUMBER(F23),F23/F19,"")),"") | G27: =IF(ISNUMBER(G19),IF(ISNUMBER(G22),G22/G19,IF(ISNUMBER(G23),G23/G19,"")),"") | H27: =IF(ISNUMBER(H19),IF(ISNUMBER(H22),H22/H19,IF(ISNUMBER(H23),H23/H19,"")),"") | I27: =IF(ISNUMBER(I19),IF(ISNUMBER(I22),I22/I19,IF(ISNUMBER(I23),I23/I19,"")),"") | J27: =IF(ISNUMBER(J19),IF(ISNUMBER(J22),J22/J19,IF(ISNUMBER(J23),J23/J19,"")),"") | ... S27: =IF(ISNUMBER(S19),IF(ISNUMBER(S22),S22/S19,IF(ISNUMBER(S23),S23/S19,"")),"") -> 0.71333333 | T27: Formula. Uses total sales, else domestic (understates where exports excluded).
A28: Capacity change vs prior FY | B28: units p.a. | D28: =IF(AND(ISNUMBER(D19),ISNUMBER(C19)),D19-C19,"") | E28: =IF(AND(ISNUMBER(E19),ISNUMBER(D19)),E19-D19,"") | F28: =IF(AND(ISNUMBER(F19),ISNUMBER(E19)),F19-E19,"") | G28: =IF(AND(ISNUMBER(G19),ISNUMBER(F19)),G19-F19,"") | H28: =IF(AND(ISNUMBER(H19),ISNUMBER(G19)),H19-G19,"") | I28: =IF(AND(ISNUMBER(I19),ISNUMBER(H19)),I19-H19,"") | J28: =IF(AND(ISNUMBER(J19),ISNUMBER(I19)),J19-I19,"") | K28: =IF(AND(ISNUMBER(K19),ISNUMBER(J19)),K19-J19,"") | ... S28: =IF(AND(ISNUMBER(S19),ISNUMBER(R19)),S19-R19,"") | T28: Formula; blank where either year undisclosed.
A29: Utilisation — company-reported | B29: %
A30: Source IDs (see Source Log) | C30: TP01 | D30: TP01; TP02 | E30: TP01 | L30: TP04 | O30: TP05 | P30: TP06 | Q30: TP07 | R30: MM13 | S30: TP08; TP11; TP12; MM13
A31: Year notes | C31: Nano interim at Pantnagar; Sanand from Jun-2010 | D31: Nano capacity 250k (Sanand I) | E31: JLR CKD at Pune from May-2011 | L31: Sanand I 154k at 100% utilisation | O31: 480k across plants (pre-Ford) | P31: Sanand II acquired (Jan-2023) | Q31: Investor Day: '1mn+' incl. Sanand-2 300k (exp. 420k) | S31: Panapakkam SOP 9-Feb-2026; demerger 1-Oct-2025
A33: C. PLANT-LEVEL CAPACITY AND OUTPUT BY FISCAL YEAR (disclosed points only; no interpolation)
A34: Plant / line | B34: Unit | C34: FY10 | D34: FY11 | E34: FY12 | F34: FY13 | G34: FY14 | H34: FY15 | I34: FY16 | J34: FY17 | K34: FY18 | L34: FY19 | M34: FY20 | N34: FY21 | O34: FY22 | P34: FY23 | Q34: FY24 | R34: FY25 | S34: FY26 | T34: Notes [sources]
A35: Sanand I (Nano -> Tiago/Tigor) | B35: units p.a. | D35: 250000 | L35: 154000 | T35: Nano installed 250k; Aug-2018 statement placed in FY19 [TP02; TP04]
A36: Sanand II (ex-Ford) | B36: units p.a. | Q36: 300000 | R36: 300000 | T36: 300k, expandable to 420k [TP06; TP07]
A37: Pune PV (Pimpri/Chikhli) | B37: units p.a. | T37: Not disclosed
A38: Ranjangaon (FIAPL JV) | B38: units p.a. | T38: Not disclosed
A39: Panapakkam (with JLR) | B39: units p.a. | T39: Design 250k over 5-7 years; phase 1 CKD c.30k (media) [TP09; TP10]
A41: D. PLANT REGISTER
A42: Plant / site | B42: Location | D42: Entity / ownership | F42: SOP / commissioned | G42: Vehicle category | I42: Key models (latest disclosed) | M42: Platforms | O42: Initial capacity (units p.a.) | P42: Latest capacity (units p.a.) | Q42: As of | R42: Status | S42: Notes | V42: Sources [confidence]
A43: Pune — Pimpri/Chikhli | B43: Pune, Maharashtra | D43: TMPV | F43: 1991 (PV entry) | G43: PV; JLR CKD | I43: Harrier, Safari, Altroz, Punch (2022); JLR CKD (Freelander 2 from May-2011; later RR/RRS) | M43: OMEGA; ALFA | P43: n.d. | Q43: — | R43: Operating | S43: 'Five plants in Pune' (mgmt, Jul-2026); JLR CKD to move to Panapakkam | V43: [Medium] TP01; TP05; TP12
A44: Ranjangaon (FIAPL) | B44: Pune, Maharashtra | D44: JV with Fiat/Stellantis | F44: Apr-2008 | G44: PV + powertrain | I44: Nexon (2022); historically Linea, Punto, Manza | M44: X1 (legacy) | P44: n.d. | Q44: — | R44: Operating | S44: Also engines and transmissions | V44: [Medium] TP01; TP05
A45: Sanand I | B45: Sanand, Gujarat | D45: TMPV | F45: Jun-2010 | G45: PV, EV | I45: Tiago, Tigor (incl. Tigor EV from Dec-2017); Nano 2010-18 | M45: X1 (legacy) | O45: 250000 | P45: 154000 | Q45: Aug-2018 | R45: Operating | S45: Built after Singur exit (Oct-2008); Nano interim at Pantnagar | V45: [High] TP02; TP03; TP04
A46: Sanand II (ex-Ford) | B46: Sanand, Gujarat | D46: Tata Passenger Electric Mobility (TPEML) | F46: Acquired Jan-2023; SOP within 12 months | G46: PV, EV | I46: n.d. in sources reviewed | M46: n.d. | O46: 300000 | P46: 300000 | Q46: Jun-2024 | R46: Operating; +300k brownfield announced | S46: Expandable to 420k; adjacent to Sanand I and vendor park | V46: [High] TP06; TP07; TP11
A47: Panapakkam | B47: Ranipet, Tamil Nadu | D47: TMPV with JLR | F47: 09-Feb-2026 | G47: PV incl. EV (Tata + JLR) | I47: Range Rover Evoque (CKD) first | M47: Future next-gen platforms incl. EV | O47: c.30,000 (media) | P47: 250,000 design | Q47: Feb-2026 | R47: Ramp-up (phase 1 CKD) | S47: Rs9,000cr; c.470 acres; 100% renewable; to centralise JLR CKD | V47: [High design / Low initial] TP08; TP09; TP10
A48: Memo: Pantnagar (Nano interim) | B48: Uttarakhand | D48: Tata Motors | F48: 2009 | G48: PV (interim) | I48: Nano | M48: — | O48: c.60,000 (5,000/month) | P48: Exited | Q48: 2010 | R48: Ended after Sanand SOP | V48: [Low] TP03
A50: E. CAPACITY EVENT LOG (chronological; positive = addition)
A51: Event | B51: Date | C51: FY | D51: Type | F51: Plant / site | H51: Capacity change (units p.a.) | I51: Plant capacity after | J51: Company capacity after | K51: Capex (Rs cr) | L51: Status | N51: Notes | V51: Sources
A52: Entry into PVs | B52: 1991 | C52: FY92 | D52: Business entry | F52: Pune | L52: — | N52: Sierra; Indica 1998 | V52: TP01
A53: FIAPL Ranjangaon JV plant | B53: Apr-2008 | C53: FY09 | D53: JV plant | F53: Ranjangaon | L53: Established | N53: With Fiat (now Stellantis) | V53: TP01
A54: Nano interim production | B54: 2009 | C54: FY10 | D54: Interim | F54: Pantnagar | H54: 60000 | L54: Interim | N54: 5,000/month | V54: TP03
A55: Sanand I SOP (Nano) | B55: Jun-2010 | C55: FY11 | D55: New plant | F55: Sanand I | H55: 250000 | I55: 250000 | L55: Commissioned | N55: Output <50% of capacity (2011) | V55: TP02; TP04
A56: JLR CKD at Pune | B56: May-2011 | C56: FY12 | D56: CKD line | F56: Pune | L56: Commissioned | N56: Freelander 2 | V56: TP01
A57: Sanand I capacity stated | B57: Aug-2018 | C57: FY19 | D57: Disclosure | F57: Sanand I | I57: 154000 | L57: Reported | N57: At 100% utilisation | V57: TP04
A58: Group PV capacity stated | B58: Mar-2022 | C58: FY22 | D58: Disclosure | F58: All | J58: 480000 | L58: Reported | V58: TP05
A59: MoU to acquire Ford Sanand | B59: 30-May-2022 | C59: FY23 | D59: Acquisition (MoU) | F59: Sanand II | H59: 300000 | L59: Completed Jan-2023 | N59: Scalable to 420k | V59: TP06
A60: Sanand II SOP | B60: Within 12 months of acquisition | C60: FY24 | D60: Plant restart | F60: Sanand II | H60: 300000 | I60: 300000 | L60: Commissioned | N60: Investor Day: capacity '1mn+' | V60: TP07
A61: Panapakkam groundbreaking | B61: Sep-2024 | C61: FY25 | D61: Construction start | F61: Panapakkam | K61: 9000 | L61: Under construction | V61: TP08; TP09
A62: CV/PV demerger effective | B62: 01-Oct-2025 | C62: FY26 | D62: Corporate | F62: — | L62: Effective | N62: TMPV = PV + EV + JLR | V62: TC06
A63: Panapakkam SOP (Evoque CKD) | B63: 09-Feb-2026 | C63: FY26 | D63: New plant | F63: Panapakkam | I63: 250k design | J63: 900000 | K63: 9000 | L63: Commissioned (phase 1) | N63: Ramp over 5-7 years | V63: TP08; TP09
A64: Plan to 1.3m capacity | B64: 30-Jun-2026 | C64: FY27 | D64: Expansion (announced) | F64: Sanand + debottlenecking | H64: 400000 | J64: 1300000 | L64: Announced | N64: Sanand +300k brownfield | V64: TP11; TP12
A66: F. PLATFORMS, MODELS AND PLANT ALLOCATION (confidence in brackets; model-plant mapping is rarely company-disclosed)
A67: Platform / architecture | B67: Powertrain | D67: Segment | F67: Models | L67: Plant(s) | O67: First SOP | P67: Notes | V67: Sources [confidence]
A68: ALFA | B68: ICE (+EV variants) | D68: Premium hatch, micro-SUV | F68: Altroz, Punch | L68: Pune | O68: 2020 | V68: [Medium] TP05
A69: OMEGA (JLR D8-derived) | B69: ICE; acti.ev+ variant for Harrier.ev | D69: Mid SUV | F69: Harrier, Safari | L69: Pune | O69: 2019 | V69: [Medium] TP05
A70: X1 (legacy) | B70: ICE / EV | D70: Hatch, sedan, sub-4m SUV | F70: Tiago, Tigor, Nexon (ICE & EV) | L70: Sanand I; Ranjangaon | O70: 2016-17 | P70: Naming per media | V70: [Low-Med] TP04; TP05
A71: acti.ev (Gen-2 pure EV) | B71: BEV | D71: Micro to mid SUV | F71: Punch.ev, Curvv.ev | L71: n.d. | O71: 2024 | P71: Company: underpins next-gen Tata.ev products | V71: [Medium] TP07
A72: Avinya (Gen-3) | B72: BEV | D72: Premium | F72: Avinya | L72: n.d. (Panapakkam candidate) | O72: FY27+ | P72: Platform synergies with JLR | V72: [Low] TP07
A74: G. FORWARD CAPACITY PIPELINE — Tier 1 = commissioned after FY26 or under execution; Tier 2 = announced with timeline/site; Memo = not summed
A75: Project | B75: Location | D75: Capacity add (units p.a.) | E75: Expected timing | F75: Capex (Rs cr) | G75: Tier | H75: Status (as of 14-Oct-2026) | J75: Notes | V75: Sources
A76: Sanand brownfield (+300k) | B76: Gujarat | D76: 300000 | E76: 2-3 years from Jun-2026 | G76: Tier 2 | H76: Announced | J76: Flexible ICE/CNG/EV lines | V76: TP11; TP12
A77: Debottlenecking of existing shops | B77: Pune / Sanand / Ranjangaon | E77: FY27+ | G77: Memo | H77: Under way | J77: Not quantified; explains residual to 1.3m | V77: TP11
A78: Panapakkam ramp to 250k (shared with JLR) | B78: Tamil Nadu | D78: 250000 | E78: 5-7 years from Feb-2026 | F78: 9000 | G78: Memo | H78: Phase 1 CKD live | J78: Excluded from TMPV total: shared with JLR and not cited in the 1.3m roadmap | V78: TP09; TP10
A79: Target: 1.3m installed | B79: India | E79: c.FY29 | G79: Memo | H79: Target | J79: FY31 PV volume aspiration >1.2m | V79: TP11
A81: H. ANALYST NOTES
A82: Ford Sanand was the cheapest capacity in the sector. 300k (expandable to 420k) in production within 12 months of acquisition.
A83: Disclosure is commentary-only. No year-end series since FY11; Investor Day (1mn+) and Jun-2026 (c.0.9m) differ on definition.
A84: Panapakkam is a JLR-first site. Evoque CKD first; Tata-brand volume there is a FY28+ story.
A85: Volume history is not like-for-like. FY10-FY12 20-F volumes include Fiat cars distributed; use FY25-FY26 for utilisation.

Sheet Tata CV
A1: Tata Motors Ltd (TMCV) — commercial vehicles (formerly TML Commercial Vehicles)
A2: TMCV IN | Segment: CV | Units: vehicles p.a. unless stated | FY = year to 31-Mar | As of 14-Oct-2026
A3: Scope: India CV plants: Jamshedpur, Pune (CV), Lucknow, Pantnagar, Dharwad ('5 plants' per Investor Day 2024). Excludes Tata Daewoo (Korea) and pending Iveco acquisition.
A4: A. SNAPSHOT
A5: Latest disclosed installed capacity (units p.a.) | C5: n.d. | F5: As of Not disclosed [—]
A6: As of | C6: Not disclosed
A7: Capacity definition / scope | C7: No consolidated CV installed capacity found in sources reviewed
A8: Vehicle assembly sites | C8: 5 — Jamshedpur, Pune, Lucknow, Pantnagar, Dharwad
A9: FY26 volume (units) | C9: =IF(ISNUMBER(S22),S22,"n.d.") -> 428329 | F9: Total CV sales FY26 (domestic + exports)
A10: FY26 volume basis | C10: Total CV sales FY26 (domestic + exports)
A11: FY26 utilisation | C11: ="n.d." -> n.d. | F11: No current capacity disclosure
A12: Outlook base capacity (units p.a.) | C12: n.d. | F12: No disclosed current base
A13: Company capacity target (units p.a.) | C13: n.d. | F13: [—]
A14: Target timing | C14: n.a.
A15: Bottom line | C15: The story is footprint, not units. No consolidated CV capacity figure is published post-FY11. FY26 sales rise 14% to 428k with capex guided at only 2-4% of revenue — brownfield headroom is assumed adequate. The Iveco tender (settlement 30-Oct-2026) adds a European/LatAm footprint and takes combined volume to 540k+.
A17: B. COMPANY-LEVEL CAPACITY AND OUTPUT HISTORY, FY10–FY26 (blue = sourced input; black = formula; orange = verify; light blue = bracketed carry)
A18: Metric | B18: Unit | C18: FY10 | D18: FY11 | E18: FY12 | F18: FY13 | G18: FY14 | H18: FY15 | I18: FY16 | J18: FY17 | K18: FY18 | L18: FY19 | M18: FY20 | N18: FY21 | O18: FY22 | P18: FY23 | Q18: FY24 | R18: FY25 | S18: FY26 | T18: Notes
A19: Installed capacity, FY-end (reported) | B19: units p.a. | T19: Not disclosed in sources reviewed. Last statutory disclosure would be the FY11 'licensed and installed capacity' note (old Schedule VI).
A20: Capacity basis code | B20: code | T20: R = company-reported total; S = sum of company-disclosed plants; M = management statement via media; A = monthly x12; D = DRHP/RHP
A21: Production — actual | B21: units | T21: Not disclosed in sources reviewed.
A22: Sales / dispatches — actual, total | B22: units | C22: =228987+179661 -> 408648 | D22: =311167+201564 -> 512731 | E22: =365677+234236 -> 599913 | R22: 376903 | S22: 428329 | T22: FY10-FY12: LCV + M&HCV 'Tata & other brand' per 20-F — includes Tata Daewoo (Korea) and international ops; not like-for-like with FY25-FY26 (India CV business).
A23: of which domestic | B23: units | R23: 358570 | S23: 400113
A24: of which exports | B24: units | R24: 18333 | S24: 28216
A25: Utilisation — production ÷ FY-end capacity | B25: % | C25: =IF(AND(ISNUMBER(C21),ISNUMBER(C19)),C21/C19,"") | D25: =IF(AND(ISNUMBER(D21),ISNUMBER(D19)),D21/D19,"") | E25: =IF(AND(ISNUMBER(E21),ISNUMBER(E19)),E21/E19,"") | F25: =IF(AND(ISNUMBER(F21),ISNUMBER(F19)),F21/F19,"") | G25: =IF(AND(ISNUMBER(G21),ISNUMBER(G19)),G21/G19,"") | H25: =IF(AND(ISNUMBER(H21),ISNUMBER(H19)),H21/H19,"") | I25: =IF(AND(ISNUMBER(I21),ISNUMBER(I19)),I21/I19,"") | J25: =IF(AND(ISNUMBER(J21),ISNUMBER(J19)),J21/J19,"") | ... S25: =IF(AND(ISNUMBER(S21),ISNUMBER(S19)),S21/S19,"") | T25: Formula. Company convention (e.g., HMIL DRHP). Depressed in commissioning years.
A26: Utilisation — production ÷ avg(opening, closing) capacity | B26: % | C26: =IF(AND(ISNUMBER(C21),ISNUMBER(C19)),C21/C19,"") | D26: =IF(AND(ISNUMBER(D21),ISNUMBER(D19)),D21/IF(ISNUMBER(C19),AVERAGE(C19,D19),D19),"") | E26: =IF(AND(ISNUMBER(E21),ISNUMBER(E19)),E21/IF(ISNUMBER(D19),AVERAGE(D19,E19),E19),"") | F26: =IF(AND(ISNUMBER(F21),ISNUMBER(F19)),F21/IF(ISNUMBER(E19),AVERAGE(E19,F19),F19),"") | G26: =IF(AND(ISNUMBER(G21),ISNUMBER(G19)),G21/IF(ISNUMBER(F19),AVERAGE(F19,G19),G19),"") | H26: =IF(AND(ISNUMBER(H21),ISNUMBER(H19)),H21/IF(ISNUMBER(G19),AVERAGE(G19,H19),H19),"") | I26: =IF(AND(ISNUMBER(I21),ISNUMBER(I19)),I21/IF(ISNUMBER(H19),AVERAGE(H19,I19),I19),"") | J26: =IF(AND(ISNUMBER(J21),ISNUMBER(J19)),J21/IF(ISNUMBER(I19),AVERAGE(I19,J19),J19),"") | K26: =IF(AND(ISNUMBER(K21),ISNUMBER(K19)),K21/IF(ISNUMBER(J19),AVERAGE(J19,K19),K19),"") | ... S26: =IF(AND(ISNUMBER(S21),ISNUMBER(S19)),S21/IF(ISNUMBER(R19),AVERAGE(R19,S19),S19),"") | T26: Formula. Uses closing capacity where opening not disclosed.
A27: Utilisation — sales ÷ FY-end capacity | B27: % | C27: =IF(ISNUMBER(C19),IF(ISNUMBER(C22),C22/C19,IF(ISNUMBER(C23),C23/C19,"")),"") | D27: =IF(ISNUMBER(D19),IF(ISNUMBER(D22),D22/D19,IF(ISNUMBER(D23),D23/D19,"")),"") | E27: =IF(ISNUMBER(E19),IF(ISNUMBER(E22),E22/E19,IF(ISNUMBER(E23),E23/E19,"")),"") | F27: =IF(ISNUMBER(F19),IF(ISNUMBER(F22),F22/F19,IF(ISNUMBER(F23),F23/F19,"")),"") | G27: =IF(ISNUMBER(G19),IF(ISNUMBER(G22),G22/G19,IF(ISNUMBER(G23),G23/G19,"")),"") | H27: =IF(ISNUMBER(H19),IF(ISNUMBER(H22),H22/H19,IF(ISNUMBER(H23),H23/H19,"")),"") | I27: =IF(ISNUMBER(I19),IF(ISNUMBER(I22),I22/I19,IF(ISNUMBER(I23),I23/I19,"")),"") | J27: =IF(ISNUMBER(J19),IF(ISNUMBER(J22),J22/J19,IF(ISNUMBER(J23),J23/J19,"")),"") | ... S27: =IF(ISNUMBER(S19),IF(ISNUMBER(S22),S22/S19,IF(ISNUMBER(S23),S23/S19,"")),"") | T27: Formula. Uses total sales, else domestic (understates where exports excluded).
A28: Capacity change vs prior FY | B28: units p.a. | D28: =IF(AND(ISNUMBER(D19),ISNUMBER(C19)),D19-C19,"") | E28: =IF(AND(ISNUMBER(E19),ISNUMBER(D19)),E19-D19,"") | F28: =IF(AND(ISNUMBER(F19),ISNUMBER(E19)),F19-E19,"") | G28: =IF(AND(ISNUMBER(G19),ISNUMBER(F19)),G19-F19,"") | H28: =IF(AND(ISNUMBER(H19),ISNUMBER(G19)),H19-G19,"") | I28: =IF(AND(ISNUMBER(I19),ISNUMBER(H19)),I19-H19,"") | J28: =IF(AND(ISNUMBER(J19),ISNUMBER(I19)),J19-I19,"") | K28: =IF(AND(ISNUMBER(K19),ISNUMBER(J19)),K19-J19,"") | ... S28: =IF(AND(ISNUMBER(S19),ISNUMBER(R19)),S19-R19,"") | T28: Formula; blank where either year undisclosed.
A29: Utilisation — company-reported | B29: %
A30: Source IDs (see Source Log) | C30: TP01 | D30: TP01 | E30: TP01 | R30: TC05 | S30: TC05; TC03
A31: Year notes | C31: Prima launched (with Tata Daewoo) | E31: Ultra LCV/ICV range shown (Auto Expo 2012) | M31: MHCV production added at Pantnagar (c.2019-20) | R31: Investor Day: 5 CV plants; capex 2-4% of revenue | S31: Demerger 1-Oct-2025; Lucknow rated >100k
A33: C. PLANT-LEVEL CAPACITY AND OUTPUT BY FISCAL YEAR (disclosed points only; no interpolation)
A34: Plant / line | B34: Unit | C34: FY10 | D34: FY11 | E34: FY12 | F34: FY13 | G34: FY14 | H34: FY15 | I34: FY16 | J34: FY17 | K34: FY18 | L34: FY19 | M34: FY20 | N34: FY21 | O34: FY22 | P34: FY23 | Q34: FY24 | R34: FY25 | S34: FY26 | T34: Notes [sources]
A35: Pantnagar (design at SOP) | B35: units p.a. | T35: 2.25 lakh p.a. planned at SOP (Apr-2007) [TC02]
A36: Lucknow (rated) | B36: units p.a. | S36: 100000 | T36: 'More than 100,000' (Apr-2026) — lower bound [TC03]
A38: D. PLANT REGISTER
A39: Plant / site | B39: Location | D39: Entity / ownership | F39: SOP / commissioned | G39: Vehicle category | I39: Key models (latest disclosed) | M39: Platforms | O39: Initial capacity (units p.a.) | P39: Latest capacity (units p.a.) | Q39: As of | R39: Status | S39: Notes | V39: Sources [confidence]
A40: Jamshedpur | B40: Jharkhand | D40: TMCV | F40: 1945 (CVs from 1954) | G40: M&HCV trucks | I40: Prima, Signa (per media) | M40: Prima; Signa | P40: n.d. | Q40: — | R40: Operating | S40: First plant; CVs since 1954 under Daimler-Benz collaboration | V40: [Medium] TP01
A41: Pune (CV) | B41: Pimpri/Chinchwad, Maharashtra | D41: TMCV | F41: n.d. | G41: LCV/ICV/SCV, vans | I41: n.d. in sources reviewed | M41: Ultra (n.d.) | P41: n.d. | Q41: — | R41: Operating | S41: Shares campus history with PV operations | V41: [Low] TP01; TC10
A42: Lucknow | B42: Uttar Pradesh | D42: TMCV | F42: 1992 | G42: Trucks and buses incl. e-buses, FCEV | I42: n.d. | M42: n.d. | P42: >100,000 (rated) | Q42: Apr-2026 | R42: Operating | S42: c.600 acres; 1m cumulative; 100% renewable power | V42: [High] TC03
A43: Pantnagar | B43: Uttarakhand | D43: TMCV | F43: Aug-2007 | G43: SCV (Ace, Magic, Intra); MHCV from c.2019 | I43: Ace family | M43: Ace; Intra | O43: 225000 | P43: n.d. | Q43: — | R43: Operating | S43: Rs1,000cr; built in c.11 months; Uttarakhand fiscal incentives | V43: [Medium] TC02; TC09; TP01
A44: Dharwad | B44: Karnataka | D44: TMCV (ex-Tata Marcopolo JV) | F44: FY09 | G44: Buses (bodies, fully built) | I44: n.d. | M44: — | P44: n.d. | Q44: — | R44: Operating | S44: Marcopolo JV formed May-2006 (TML 51%) | V44: [Medium] TP01
A45: Memo: Iveco Group | B45: Europe, LatAm | D45: TML CV Holdings BV (offeror) | F45: — | G45: Trucks, vans, buses, powertrain (FPT) | I45: — | M45: — | P45: n.d. | Q45: — | R45: Tender open; settlement 30-Oct-2026 | S45: EUR3.8bn; combined 540k+ units; no plant closures for two years post-close | V45: [High] TC07; TC08
A47: E. CAPACITY EVENT LOG (chronological; positive = addition)
A48: Event | B48: Date | C48: FY | D48: Type | F48: Plant / site | H48: Capacity change (units p.a.) | I48: Plant capacity after | J48: Company capacity after | K48: Capex (Rs cr) | L48: Status | N48: Notes | V48: Sources
A49: Tata Daewoo acquisition | B49: 2004 | C49: FY05 | D49: Acquisition | F49: Gunsan, Korea | L49: Completed | N49: Co-developed Prima | V49: TP01
A50: Tata Marcopolo JV | B50: May-2006 | C50: FY07 | D50: JV | F50: Dharwad | L50: Production from FY09 | N50: TML 51% | V50: TP01
A51: Pantnagar SOP (Ace) | B51: Aug-2007 | C51: FY08 | D51: New plant | F51: Pantnagar | H51: 225000 | I51: 225000 | K51: 1000 | L51: Commissioned | N51: Capacity = plan at announcement (Dec-2006) | V51: TC02; TP01
A52: MHCV production added at Pantnagar | B52: c.2019-20 | C52: FY20 | D52: Line addition | F52: Pantnagar | L52: Operating | N52: Plan to raise MHCV output (Jul-2020) | V52: TC09
A53: Investor Day: five CV plants | B53: 11-Jun-2024 | C53: FY25 | D53: Disclosure | F53: All | L53: — | N53: Capex 2-4% of revenue; bus body capacity raised for seasonal peaks | V53: TP07
A54: Iveco offer announced | B54: 30-Jul-2025 | C54: FY26 | D54: Acquisition (announced) | F54: Iveco (Europe/LatAm) | K54: EUR3.8bn | L54: Announced | N54: Excludes Iveco Defence | V54: TC08
A55: CV/PV demerger effective | B55: 01-Oct-2025 | C55: FY26 | D55: Corporate | F55: — | L55: Effective | N55: TML CV renamed Tata Motors Ltd | V55: TC06
A56: Lucknow 10 lakh cumulative | B56: 15-Apr-2026 | C56: FY27 | D56: Milestone | F56: Lucknow | I56: >100,000 rated | L56: — | V56: TC03
A57: Iveco tender offer | B57: 07-Sep to 26-Oct-2026 | C57: FY27 | D57: Acquisition (tender) | F57: Iveco | K57: EUR3.8bn | L57: Settlement 30-Oct-2026 | N57: Consob approval 3-Sep-2026 | V57: TC07
A59: F. PLATFORMS, MODELS AND PLANT ALLOCATION (confidence in brackets; model-plant mapping is rarely company-disclosed)
A60: Platform / architecture | B60: Powertrain | D60: Segment | F60: Models | L60: Plant(s) | O60: First SOP | P60: Notes | V60: Sources [confidence]
A61: Ace | B61: ICE / CNG / EV | D61: SCV (<1t) | F61: Ace family, Ace EV, Magic | L61: Pantnagar | O61: May-2005 | P61: 100k units in 22 months | V61: [High] TP01
A62: Intra / Yodha | B62: ICE / CNG | D62: Pickups | F62: Intra V-series, Yodha | L62: n.d. | O62: 2019 | V62: [Low]
A63: Ultra | B63: ICE / EV | D63: LCV/ICV 5-14t; buses | F63: Ultra trucks, Ultra EV bus | L63: n.d. | O63: 2012 | P63: Shown at Auto Expo 2012 | V63: [Medium] TP01
A64: Signa | B64: ICE | D64: M&HCV | F64: Signa range | L64: Jamshedpur / Lucknow (n.d.) | O64: 2016 | V64: [Low]
A65: Prima | B65: ICE | D65: HCV | F65: Prima | L65: Jamshedpur | O65: FY10 | P65: Co-developed with Tata Daewoo | V65: [High] TP01
A66: Buses (Starbus, Magna, e-bus, FCEV) | B66: ICE / BEV / FCEV | D66: Buses | F66: Starbus EV, FCEV bus | L66: Lucknow; Dharwad | O66: — | V66: [Medium] TC03
A68: G. FORWARD CAPACITY PIPELINE — Tier 1 = commissioned after FY26 or under execution; Tier 2 = announced with timeline/site; Memo = not summed
A69: Project | B69: Location | D69: Capacity add (units p.a.) | E69: Expected timing | F69: Capex (Rs cr) | G69: Tier | H69: Status (as of 14-Oct-2026) | J69: Notes | V69: Sources
A70: Iveco acquisition | B70: Europe / LatAm | E70: Settlement 30-Oct-2026 | F70: EUR3.8bn | G70: Memo | H70: Tender open | J70: Not India capacity | V70: TC07; TC08
A71: India CV capacity additions | B71: India | E71: — | G71: Memo | H71: None disclosed | J71: Capex guided at 2-4% of revenue | V71: TP07
A73: H. ANALYST NOTES
A74: No capacity series exists in public sources reviewed. Retrieve the FY10-FY11 Schedule VI note and 20-F Item 4.D to anchor history.
A75: Volume has recovered without new plants. FY26 CV sales of 428k (+14%), Q4 +25% YoY.
A76: Iveco changes the denominator, not India. Combined 540k+ units; Tata committed to no plant closures for two years.

Sheet Ashok Leyland
A1: Ashok Leyland Ltd
A2: AL IN | Segment: CV | Units: vehicles p.a. unless stated | FY = year to 31-Mar | As of 14-Oct-2026
A3: Scope: India CV plants: Ennore, Hosur I/II (+ LCV), Alwar, Bhandara, Pantnagar, Vijayawada (buses), Lucknow (EV). Overseas (RAK UAE, Optare UK) excluded.
A4: A. SNAPSHOT
A5: Latest disclosed installed capacity (units p.a.) | C5: 150000 | F5: As of Sep-2010 (latest found) [AL03]
A6: As of | C6: Sep-2010 (latest found)
A7: Capacity definition / scope | C7: Installed capacity across seven plants (2010); no later company total found
A8: Vehicle assembly sites | C8: 8 vehicle sites in India incl. Vijayawada (2025) and Lucknow EV (2026)
A9: FY26 volume (units) | C9: =IF(ISNUMBER(S22),S22,"n.d.") -> 220437 | F9: Total deliveries FY26 (incl. exports)
A10: FY26 volume basis | C10: Total deliveries FY26 (incl. exports)
A11: FY26 utilisation | C11: ="n.d." -> n.d. | F11: No current capacity disclosure
A12: Outlook base capacity (units p.a.) | C12: n.d. | F12: No disclosed current base
A13: Company capacity target (units p.a.) | C13: n.d. | F13: [—]
A14: Target timing | C14: n.a.
A15: Bottom line | C15: Disclosure stops in 2010. New capacity since is bus- and EV-led (Vijayawada 4,800 p.a., Lucknow 2,500 -> 5,000 p.a.) while FY26 deliveries hit a record 220k. Truck capacity headroom must be confirmed with management before modelling the next upcycle.
A17: B. COMPANY-LEVEL CAPACITY AND OUTPUT HISTORY, FY10–FY26 (blue = sourced input; black = formula; orange = verify; light blue = bracketed carry)
A18: Metric | B18: Unit | C18: FY10 | D18: FY11 | E18: FY12 | F18: FY13 | G18: FY14 | H18: FY15 | I18: FY16 | J18: FY17 | K18: FY18 | L18: FY19 | M18: FY20 | N18: FY21 | O18: FY22 | P18: FY23 | Q18: FY24 | R18: FY25 | S18: FY26 | T18: Notes
A19: Installed capacity, FY-end (reported) | B19: units p.a. | D19: 150000 | T19: Only FY11 (150k) found. FY10: 100k across six plants (Oct-2009) + Pantnagar (75k) from Mar-2010 — company total at FY10-end not stated.
A20: Capacity basis code | B20: code | D20: M | T20: R = company-reported total; S = sum of company-disclosed plants; M = management statement via media; A = monthly x12; D = DRHP/RHP
A21: Production — actual | B21: units | T21: Not disclosed in sources reviewed.
A22: Sales / dispatches — actual, total | B22: units | S22: 220437 | T22: FY26 deliveries per Automotive World (company data). FY10 sales c.64k per CFO (Sep-2010) — not entered.
A23: of which domestic | B23: units
A24: of which exports | B24: units | S24: 18082 | T24: Exports 8.2% of FY26 volume.
A25: Utilisation — production ÷ FY-end capacity | B25: % | C25: =IF(AND(ISNUMBER(C21),ISNUMBER(C19)),C21/C19,"") | D25: =IF(AND(ISNUMBER(D21),ISNUMBER(D19)),D21/D19,"") | E25: =IF(AND(ISNUMBER(E21),ISNUMBER(E19)),E21/E19,"") | F25: =IF(AND(ISNUMBER(F21),ISNUMBER(F19)),F21/F19,"") | G25: =IF(AND(ISNUMBER(G21),ISNUMBER(G19)),G21/G19,"") | H25: =IF(AND(ISNUMBER(H21),ISNUMBER(H19)),H21/H19,"") | I25: =IF(AND(ISNUMBER(I21),ISNUMBER(I19)),I21/I19,"") | J25: =IF(AND(ISNUMBER(J21),ISNUMBER(J19)),J21/J19,"") | ... S25: =IF(AND(ISNUMBER(S21),ISNUMBER(S19)),S21/S19,"") | T25: Formula. Company convention (e.g., HMIL DRHP). Depressed in commissioning years.
A26: Utilisation — production ÷ avg(opening, closing) capacity | B26: % | C26: =IF(AND(ISNUMBER(C21),ISNUMBER(C19)),C21/C19,"") | D26: =IF(AND(ISNUMBER(D21),ISNUMBER(D19)),D21/IF(ISNUMBER(C19),AVERAGE(C19,D19),D19),"") | E26: =IF(AND(ISNUMBER(E21),ISNUMBER(E19)),E21/IF(ISNUMBER(D19),AVERAGE(D19,E19),E19),"") | F26: =IF(AND(ISNUMBER(F21),ISNUMBER(F19)),F21/IF(ISNUMBER(E19),AVERAGE(E19,F19),F19),"") | G26: =IF(AND(ISNUMBER(G21),ISNUMBER(G19)),G21/IF(ISNUMBER(F19),AVERAGE(F19,G19),G19),"") | H26: =IF(AND(ISNUMBER(H21),ISNUMBER(H19)),H21/IF(ISNUMBER(G19),AVERAGE(G19,H19),H19),"") | I26: =IF(AND(ISNUMBER(I21),ISNUMBER(I19)),I21/IF(ISNUMBER(H19),AVERAGE(H19,I19),I19),"") | J26: =IF(AND(ISNUMBER(J21),ISNUMBER(J19)),J21/IF(ISNUMBER(I19),AVERAGE(I19,J19),J19),"") | K26: =IF(AND(ISNUMBER(K21),ISNUMBER(K19)),K21/IF(ISNUMBER(J19),AVERAGE(J19,K19),K19),"") | ... S26: =IF(AND(ISNUMBER(S21),ISNUMBER(S19)),S21/IF(ISNUMBER(R19),AVERAGE(R19,S19),S19),"") | T26: Formula. Uses closing capacity where opening not disclosed.
A27: Utilisation — sales ÷ FY-end capacity | B27: % | C27: =IF(ISNUMBER(C19),IF(ISNUMBER(C22),C22/C19,IF(ISNUMBER(C23),C23/C19,"")),"") | D27: =IF(ISNUMBER(D19),IF(ISNUMBER(D22),D22/D19,IF(ISNUMBER(D23),D23/D19,"")),"") | E27: =IF(ISNUMBER(E19),IF(ISNUMBER(E22),E22/E19,IF(ISNUMBER(E23),E23/E19,"")),"") | F27: =IF(ISNUMBER(F19),IF(ISNUMBER(F22),F22/F19,IF(ISNUMBER(F23),F23/F19,"")),"") | G27: =IF(ISNUMBER(G19),IF(ISNUMBER(G22),G22/G19,IF(ISNUMBER(G23),G23/G19,"")),"") | H27: =IF(ISNUMBER(H19),IF(ISNUMBER(H22),H22/H19,IF(ISNUMBER(H23),H23/H19,"")),"") | I27: =IF(ISNUMBER(I19),IF(ISNUMBER(I22),I22/I19,IF(ISNUMBER(I23),I23/I19,"")),"") | J27: =IF(ISNUMBER(J19),IF(ISNUMBER(J22),J22/J19,IF(ISNUMBER(J23),J23/J19,"")),"") | ... S27: =IF(ISNUMBER(S19),IF(ISNUMBER(S22),S22/S19,IF(ISNUMBER(S23),S23/S19,"")),"") | T27: Formula. Uses total sales, else domestic (understates where exports excluded).
A28: Capacity change vs prior FY | B28: units p.a. | D28: =IF(AND(ISNUMBER(D19),ISNUMBER(C19)),D19-C19,"") | E28: =IF(AND(ISNUMBER(E19),ISNUMBER(D19)),E19-D19,"") | F28: =IF(AND(ISNUMBER(F19),ISNUMBER(E19)),F19-E19,"") | G28: =IF(AND(ISNUMBER(G19),ISNUMBER(F19)),G19-F19,"") | H28: =IF(AND(ISNUMBER(H19),ISNUMBER(G19)),H19-G19,"") | I28: =IF(AND(ISNUMBER(I19),ISNUMBER(H19)),I19-H19,"") | J28: =IF(AND(ISNUMBER(J19),ISNUMBER(I19)),J19-I19,"") | K28: =IF(AND(ISNUMBER(K19),ISNUMBER(J19)),K19-J19,"") | ... S28: =IF(AND(ISNUMBER(S19),ISNUMBER(R19)),S19-R19,"") | T28: Formula; blank where either year undisclosed.
A29: Utilisation — company-reported | B29: %
A30: Source IDs (see Source Log) | C30: AL01; AL02 | D30: AL03 | E30: AL04 | N30: AL11 | R30: AL05 | S30: AL06; AL07
A31: Year notes | C31: Oct-2009: 100k across 6 plants; Pantnagar SOP Mar-2010 | D31: 150k across 7 plants | E31: Dost LCV 55k at Hosur (date inferred) | N31: AVTR (Jun-2020), Phoenix LCV (Sep-2020) | R31: Vijayawada bus plant 4,800 p.a. (Mar-2025) | S31: Lucknow EV plant (Jan-2026); record 220k
A33: C. PLANT-LEVEL CAPACITY AND OUTPUT BY FISCAL YEAR (disclosed points only; no interpolation)
A34: Plant / line | B34: Unit | C34: FY10 | D34: FY11 | E34: FY12 | F34: FY13 | G34: FY14 | H34: FY15 | I34: FY16 | J34: FY17 | K34: FY18 | L34: FY19 | M34: FY20 | N34: FY21 | O34: FY22 | P34: FY23 | Q34: FY24 | R34: FY25 | S34: FY26 | T34: Notes [sources]
A35: Pantnagar | B35: units p.a. | C35: 75000 | T35: Installed 75k at SOP (Mar-2010); 50k cited in 2009 plan [AL01; AL02]
A36: Hosur — LCV (Dost) | B36: units p.a. | E36: 55000 | T36: Article undated (c.2012) [AL04]
A37: Vijayawada (Malavalli) — buses | B37: units p.a. | R37: 4800 | S37: 4800 | T37: SOP 19-Mar-2025 [AL05]
A38: Lucknow — EV | B38: units p.a. | S38: 2500 | T38: Phase 1; to 5,000 [AL06]
A40: D. PLANT REGISTER
A41: Plant / site | B41: Location | D41: Entity / ownership | F41: SOP / commissioned | G41: Vehicle category | I41: Key models (latest disclosed) | M41: Platforms | O41: Initial capacity (units p.a.) | P41: Latest capacity (units p.a.) | Q41: As of | R41: Status | S41: Notes | V41: Sources [confidence]
A42: Ennore | B42: Chennai, Tamil Nadu | D42: AL | F42: 1949 | G42: Trucks, buses | I42: n.d. | M42: — | P42: n.d. | Q42: — | R42: Operating | S42: Original plant | V42: [Medium] AL08
A43: Hosur I | B43: Tamil Nadu | D43: AL | F43: 1980 | G43: Engines, spares distribution | I43: — | M43: — | P43: n.d. | Q43: — | R43: Operating | V43: [Medium] AL08; AL09
A44: Hosur II | B44: Tamil Nadu | D44: AL | F44: 1996 | G44: Trucks (wide range) | I44: AVTR range | M44: AVTR | P44: n.d. | Q44: — | R44: Operating | V44: [Medium] AL08; AL09
A45: Hosur — LCV | B45: Tamil Nadu | D45: AL (ex-Nissan JV) | F45: 2011 | G45: LCV | I45: Dost, Bada Dost | M45: Dost; Phoenix | O45: 55000 | P45: n.d. | Q45: c.2012 | R45: Operating | S45: Pillaipakkam LCV greenfield proposed c.2012 — status not verified | V45: [Medium] AL04
A46: Alwar | B46: Rajasthan | D46: AL | F46: Aug-1982 | G46: Buses, chassis | I46: ULE buses | M46: — | O46: 200 ULE buses/month (2009) | P46: n.d. | Q46: — | R46: Operating | S46: Plan to 300 ULE/month (2009); c.110 chassis/day | V46: [Medium] AL01; AL08
A47: Bhandara | B47: Maharashtra | D47: AL | F47: Mar-1982 | G47: Components / aggregates (n.d.) | I47: — | M47: — | P47: n.d. | Q47: — | R47: Operating | V47: [Low] AL08
A48: Pantnagar | B48: Uttarakhand | D48: AL | F48: Mar-2010 | G48: M&HCV | I48: U-Truck -> AVTR | M48: U-Truck; AVTR | O48: 75000 | P48: n.d. | Q48: — | R48: Operating | S48: Integrated plant for <Rs1,500cr (Rs1,300cr per BS) | V48: [High] AL01; AL02
A49: Vijayawada (Malavalli) | B49: Andhra Pradesh | D49: AL (+ Switch Mobility EVs) | F49: 19-Mar-2025 | G49: Buses — diesel & electric | I49: AL diesel buses; Switch e-buses | M49: Switch EiV | O49: 4800 | P49: 4800 | Q49: Mar-2025 | R49: Operating at full capacity from day one | S49: 75 acres | V49: [High] AL05
A50: Lucknow (EV) | B50: Uttar Pradesh | D50: AL | F50: 09-Jan-2026 | G50: e-buses, e-travellers, e-cargo (ICE-capable) | I50: 17-18 seater e-bus first | M50: — | O50: 2500 | P50: 2500 | Q50: Jan-2026 | R50: Ramp to 5,000 | S50: 70 acres; >Rs1,000cr | V50: [High] AL06; AL10
A51: Sriperumbudur foundry | B51: Tamil Nadu | D51: AL | F51: n.d. | G51: Castings | I51: — | M51: — | P51: n.d. | Q51: — | R51: Operating | V51: [Medium] AL09
A53: E. CAPACITY EVENT LOG (chronological; positive = addition)
A54: Event | B54: Date | C54: FY | D54: Type | F54: Plant / site | H54: Capacity change (units p.a.) | I54: Plant capacity after | J54: Company capacity after | K54: Capex (Rs cr) | L54: Status | N54: Notes | V54: Sources
A55: Plant history | B55: 1949-1996 | C55: — | D55: New plants | F55: Ennore; Hosur I; Bhandara; Alwar; Hosur II | L55: Commissioned | N55: 1949, 1980, Mar-1982, Aug-1982, 1996 | V55: AL08
A56: Installed capacity 100k (six plants) | B56: Oct-2009 | C56: FY10 | D56: Disclosure | F56: All | J56: 100000 | L56: Reported | N56: Alwar ULE 200 -> 300/month planned | V56: AL01
A57: Pantnagar SOP | B57: Mar-2010 | C57: FY10 | D57: New plant | F57: Pantnagar | H57: 75000 | I57: 75000 | K57: 1300 | L57: Commissioned | N57: U-Truck platform | V57: AL01; AL02
A58: Installed capacity 150k (seven plants) | B58: Sep-2010 | C58: FY11 | D58: Disclosure | F58: All | J58: 150000 | L58: Reported | N58: Pantnagar to 4,000/month by FY12-end | V58: AL03
A59: Dost LCV line | B59: 2011-12 | C59: FY12 | D59: New line | F59: Hosur | H59: 55000 | I59: 55000 | L59: Commissioned | N59: Nissan JV product | V59: AL04
A60: AVTR modular truck platform | B60: Jun-2020 | C60: FY21 | D60: Platform | F60: — | L60: Launched | V60: AL11
A61: Vijayawada bus plant | B61: 19-Mar-2025 | C61: FY25 | D61: New plant | F61: Vijayawada | H61: 4800 | I61: 4800 | L61: Commissioned | N61: Diesel + Switch EV buses | V61: AL05
A62: Lucknow EV plant | B62: 09-Jan-2026 | C62: FY26 | D62: New plant | F62: Lucknow | H62: 2500 | I62: 2500 | K62: 1000 | L62: Commissioned (phase 1) | N62: To 5,000 in phases | V62: AL06; AL10
A64: F. PLATFORMS, MODELS AND PLANT ALLOCATION (confidence in brackets; model-plant mapping is rarely company-disclosed)
A65: Platform / architecture | B65: Powertrain | D65: Segment | F65: Models | L65: Plant(s) | O65: First SOP | P65: Notes | V65: Sources [confidence]
A66: U-Truck | B66: ICE | D66: M&HCV | F66: U-Truck range (U3723 etc.) | L66: Pantnagar | O66: 2010 | P66: Superseded by AVTR | V66: [High] AL02
A67: AVTR (modular) | B67: ICE; CNG/LNG/EV variants | D67: M&HCV 18.5-55t | F67: AVTR range | L67: Hosur II, Pantnagar (n.d.) | O67: Jun-2020 | V67: [Medium] AL11
A68: Phoenix (LCV) | B68: ICE / CNG / EV | D68: LCV | F68: Bada Dost | L68: Hosur | O68: Sep-2020 | V68: [Medium] AL11
A69: Dost | B69: ICE | D69: LCV | F69: Dost | L69: Hosur | O69: 2011 | P69: Nissan JV-derived | V69: [Medium] AL04
A70: Buses (Falcon, Viking, Garud) | B70: ICE | D70: Buses | F70: Garud 15m multi-axle (Jul-2024) | L70: Alwar, Ennore, Vijayawada (n.d.) | O70: — | V70: [Medium] AL11
A71: Switch EiV (e-bus) | B71: BEV | D71: Buses incl. double-decker | F71: Switch EiV12, EiV22 | L71: Vijayawada; Lucknow | O71: — | P71: Switch Mobility subsidiary | V71: [Medium] AL05; AL06
A73: G. FORWARD CAPACITY PIPELINE — Tier 1 = commissioned after FY26 or under execution; Tier 2 = announced with timeline/site; Memo = not summed
A74: Project | B74: Location | D74: Capacity add (units p.a.) | E74: Expected timing | F74: Capex (Rs cr) | G74: Tier | H74: Status (as of 14-Oct-2026) | J74: Notes | V74: Sources
A75: Lucknow EV ramp (2,500 -> 5,000) | B75: Uttar Pradesh | D75: 2500 | E75: In phases | G75: Tier 2 | H75: Announced | V75: AL06
A77: H. ANALYST NOTES
A78: Disclosure stops in 2010. The only company totals found are 100k (Oct-2009) and 150k (Sep-2010).
A79: New capacity is bus- and EV-led. Vijayawada (4,800) and Lucknow (2,500 -> 5,000) are small relative to the truck base.
A80: Record volume on an unknown denominator. FY26 deliveries 220,437; exports 18,082 (8.2%).

Sheet Bajaj Auto
A1: Bajaj Auto Ltd
A2: BJAUT IN | Segment: 2W/3W | Units: vehicles p.a. unless stated | FY = year to 31-Mar | As of 14-Oct-2026
A3: Scope: India 2W + 3W/commercial vehicles + Chetak EV: Waluj, Chakan (incl. Chakan 2), Pantnagar, Akurdi (Chetak). Excludes Brazil (Manaus) CKD and KTM.
A4: A. SNAPSHOT
A5: Latest disclosed installed capacity (units p.a.) | C5: 7200000 | F5: As of Jul-2026 (c.600k/month) [BA07; BA03]
A6: As of | C6: Jul-2026 (c.600k/month)
A7: Capacity definition / scope | C7: Installed capacity, 2W + 3W (company statements)
A8: Vehicle assembly sites | C8: 4 — Waluj, Chakan (2 plants), Pantnagar, Akurdi (Chetak)
A9: FY26 volume (units) | C9: =IF(ISNUMBER(S22),S22,"n.d.") -> 5117667 | F9: Total sales FY26 (domestic + exports)
A10: FY26 volume basis | C10: Total sales FY26 (domestic + exports)
A11: FY26 utilisation | C11: =IFERROR(C9/S19,"n.d.") -> 0.71078708 | F11: FY26 volume ÷ FY26 year-end capacity (row 19)
A12: Outlook base capacity (units p.a.) | C12: =S19 -> 7200000 | F12: FY26 year-end (row 19)
A13: Company capacity target (units p.a.) | C13: =1.2*S19 -> 8640000 | F13: [BA07]
A14: Target timing | C14: FY27-end / early FY28 (+20%)
A15: Bottom line | C15: Exports drive the capacity call. FY26 volume of 5.12m (44% exports) sits at c.71% of the c.7.2m installed base, yet management is adding c.20% — read this as a mix-specific constraint (Chetak, CV/3W, premium motorcycles), not blanket shortage.
A17: B. COMPANY-LEVEL CAPACITY AND OUTPUT HISTORY, FY10–FY26 (blue = sourced input; black = formula; orange = verify; light blue = bracketed carry)
A18: Metric | B18: Unit | C18: FY10 | D18: FY11 | E18: FY12 | F18: FY13 | G18: FY14 | H18: FY15 | I18: FY16 | J18: FY17 | K18: FY18 | L18: FY19 | M18: FY20 | N18: FY21 | O18: FY22 | P18: FY23 | Q18: FY24 | R18: FY25 | S18: FY26 | T18: Notes
A19: Installed capacity, FY-end (reported) | B19: units p.a. | D19: 5040000 | E19: 5040000 | H19: 6060000 | N19: 6330000 | Q19: 7100000 | S19: 7200000 | T19: FY11-FY12 and FY21 per AR wording quoted by a data aggregator; FY15 per AR Directors' Report copy. FY24 7.1m from a secondary source — verify. FY26 = c.600k/month (Jul-2026).
A20: Capacity basis code | B20: code | D20: R | E20: R | H20: R | N20: R | Q20: M | S20: M | T20: R = company-reported total; S = sum of company-disclosed plants; M = management statement via media; A = monthly x12; D = DRHP/RHP
A21: Production — actual | B21: units | T21: Not captured — Bajaj ARs publish production; retrieve.
A22: Sales / dispatches — actual, total | B22: units | R22: 4650966 | S22: 5117667 | T22: FY26 record 5,117,667 (previous peak FY19).
A23: of which domestic | B23: units | R23: 2787685 | S23: 2867484
A24: of which exports | B24: units | R24: 1863281 | S24: 2250183 | T24: Exports 44% of FY26 volume.
A25: Utilisation — production ÷ FY-end capacity | B25: % | C25: =IF(AND(ISNUMBER(C21),ISNUMBER(C19)),C21/C19,"") | D25: =IF(AND(ISNUMBER(D21),ISNUMBER(D19)),D21/D19,"") | E25: =IF(AND(ISNUMBER(E21),ISNUMBER(E19)),E21/E19,"") | F25: =IF(AND(ISNUMBER(F21),ISNUMBER(F19)),F21/F19,"") | G25: =IF(AND(ISNUMBER(G21),ISNUMBER(G19)),G21/G19,"") | H25: =IF(AND(ISNUMBER(H21),ISNUMBER(H19)),H21/H19,"") | I25: =IF(AND(ISNUMBER(I21),ISNUMBER(I19)),I21/I19,"") | J25: =IF(AND(ISNUMBER(J21),ISNUMBER(J19)),J21/J19,"") | ... S25: =IF(AND(ISNUMBER(S21),ISNUMBER(S19)),S21/S19,"") | T25: Formula. Company convention (e.g., HMIL DRHP). Depressed in commissioning years.
A26: Utilisation — production ÷ avg(opening, closing) capacity | B26: % | C26: =IF(AND(ISNUMBER(C21),ISNUMBER(C19)),C21/C19,"") | D26: =IF(AND(ISNUMBER(D21),ISNUMBER(D19)),D21/IF(ISNUMBER(C19),AVERAGE(C19,D19),D19),"") | E26: =IF(AND(ISNUMBER(E21),ISNUMBER(E19)),E21/IF(ISNUMBER(D19),AVERAGE(D19,E19),E19),"") | F26: =IF(AND(ISNUMBER(F21),ISNUMBER(F19)),F21/IF(ISNUMBER(E19),AVERAGE(E19,F19),F19),"") | G26: =IF(AND(ISNUMBER(G21),ISNUMBER(G19)),G21/IF(ISNUMBER(F19),AVERAGE(F19,G19),G19),"") | H26: =IF(AND(ISNUMBER(H21),ISNUMBER(H19)),H21/IF(ISNUMBER(G19),AVERAGE(G19,H19),H19),"") | I26: =IF(AND(ISNUMBER(I21),ISNUMBER(I19)),I21/IF(ISNUMBER(H19),AVERAGE(H19,I19),I19),"") | J26: =IF(AND(ISNUMBER(J21),ISNUMBER(J19)),J21/IF(ISNUMBER(I19),AVERAGE(I19,J19),J19),"") | K26: =IF(AND(ISNUMBER(K21),ISNUMBER(K19)),K21/IF(ISNUMBER(J19),AVERAGE(J19,K19),K19),"") | ... S26: =IF(AND(ISNUMBER(S21),ISNUMBER(S19)),S21/IF(ISNUMBER(R19),AVERAGE(R19,S19),S19),"") | T26: Formula. Uses closing capacity where opening not disclosed.
A27: Utilisation — sales ÷ FY-end capacity | B27: % | C27: =IF(ISNUMBER(C19),IF(ISNUMBER(C22),C22/C19,IF(ISNUMBER(C23),C23/C19,"")),"") | D27: =IF(ISNUMBER(D19),IF(ISNUMBER(D22),D22/D19,IF(ISNUMBER(D23),D23/D19,"")),"") | E27: =IF(ISNUMBER(E19),IF(ISNUMBER(E22),E22/E19,IF(ISNUMBER(E23),E23/E19,"")),"") | F27: =IF(ISNUMBER(F19),IF(ISNUMBER(F22),F22/F19,IF(ISNUMBER(F23),F23/F19,"")),"") | G27: =IF(ISNUMBER(G19),IF(ISNUMBER(G22),G22/G19,IF(ISNUMBER(G23),G23/G19,"")),"") | H27: =IF(ISNUMBER(H19),IF(ISNUMBER(H22),H22/H19,IF(ISNUMBER(H23),H23/H19,"")),"") | I27: =IF(ISNUMBER(I19),IF(ISNUMBER(I22),I22/I19,IF(ISNUMBER(I23),I23/I19,"")),"") | J27: =IF(ISNUMBER(J19),IF(ISNUMBER(J22),J22/J19,IF(ISNUMBER(J23),J23/J19,"")),"") | ... S27: =IF(ISNUMBER(S19),IF(ISNUMBER(S22),S22/S19,IF(ISNUMBER(S23),S23/S19,"")),"") -> 0.71078708 | T27: Formula. Uses total sales, else domestic (understates where exports excluded).
A28: Capacity change vs prior FY | B28: units p.a. | D28: =IF(AND(ISNUMBER(D19),ISNUMBER(C19)),D19-C19,"") | E28: =IF(AND(ISNUMBER(E19),ISNUMBER(D19)),E19-D19,"") -> 0 | F28: =IF(AND(ISNUMBER(F19),ISNUMBER(E19)),F19-E19,"") | G28: =IF(AND(ISNUMBER(G19),ISNUMBER(F19)),G19-F19,"") | H28: =IF(AND(ISNUMBER(H19),ISNUMBER(G19)),H19-G19,"") | I28: =IF(AND(ISNUMBER(I19),ISNUMBER(H19)),I19-H19,"") | J28: =IF(AND(ISNUMBER(J19),ISNUMBER(I19)),J19-I19,"") | K28: =IF(AND(ISNUMBER(K19),ISNUMBER(J19)),K19-J19,"") | ... S28: =IF(AND(ISNUMBER(S19),ISNUMBER(R19)),S19-R19,"") | T28: Formula; blank where either year undisclosed.
A29: Utilisation — company-reported | B29: %
A30: Source IDs (see Source Log) | C30: BA01 | D30: BA01; BA02; BA03 | E30: BA03; BA04 | F30: BA04 | H30: BA05 | I30: BA05 | N30: BA03 | Q30: BA06 | R30: BA06; BA08 | S30: BA03; BA07; BA08
A31: Year notes | C31: Pantnagar 0.6m -> 1.2m (2009) | D31: Pantnagar Plant II -> 1.8m (Oct-2010) | E31: 4.5m 2W + 0.5m 3W | F31: Plan: 6.3m (5.7m 2W + 0.6m 3W) | I31: Plan: 6.12m by Mar-2016 | Q31: Secondary source (verify) | R31: Brazil (Manaus) CKD 20k/month from Jun-2024 | S31: +20% in two phases announced Jul-2026
A33: C. PLANT-LEVEL CAPACITY AND OUTPUT BY FISCAL YEAR (disclosed points only; no interpolation)
A34: Plant / line | B34: Unit | C34: FY10 | D34: FY11 | E34: FY12 | F34: FY13 | G34: FY14 | H34: FY15 | I34: FY16 | J34: FY17 | K34: FY18 | L34: FY19 | M34: FY20 | N34: FY21 | O34: FY22 | P34: FY23 | Q34: FY24 | R34: FY25 | S34: FY26 | T34: Notes [sources]
A35: Pantnagar | B35: units p.a. | C35: 1200000 | D35: 1800000 | T35: 0.6m at SOP (2007) [BA01; BA02]
A36: Chakan | B36: units p.a. | D36: 1200000 | T36: [BA02]
A37: Waluj | B37: units p.a. | T37: Not disclosed
A38: Company — 2W capacity | B38: units p.a. | E38: 4500000 | T38: [BA04]
A39: Company — 3W capacity | B39: units p.a. | E39: 500000 | T39: [BA04]
A41: D. PLANT REGISTER
A42: Plant / site | B42: Location | D42: Entity / ownership | F42: SOP / commissioned | G42: Vehicle category | I42: Key models (latest disclosed) | M42: Platforms | O42: Initial capacity (units p.a.) | P42: Latest capacity (units p.a.) | Q42: As of | R42: Status | S42: Notes | V42: Sources [confidence]
A43: Waluj | B43: Chhatrapati Sambhajinagar, Maharashtra | D43: Bajaj Auto | F43: 05-Nov-1985 | G43: Motorcycles; 3W / commercial vehicles; Qute | I43: RE/Maxima 3W, Qute, motorcycles (n.d.) | M43: — | P43: n.d. | Q43: — | R43: Operating; CV capacity in 2026 expansion | V43: [Medium] BA03; BA07
A44: Chakan | B44: Pune, Maharashtra | D44: Bajaj Auto | F44: 1998 | G44: Premium motorcycles | I44: Pulsar, Dominar, KTM 125-390 | M44: Pulsar; KTM | P44: 1200000 | Q44: 2010 | R44: Operating | V44: [Medium] BA02; BA03
A45: Chakan 2 | B45: Pune, Maharashtra | D45: Bajaj Auto | F45: 2024 | G45: Premium motorcycles | I45: Triumph Speed 400, Scrambler 400X | M45: Triumph TR-series | P45: n.d. | Q45: — | R45: Operating | V45: [Medium] BA10
A46: Pantnagar | B46: Uttarakhand | D46: Bajaj Auto | F46: 09-Apr-2007 | G46: Commuter motorcycles | I46: Platina, Discover, Pulsar 135LS (2010) | M46: — | O46: 600000 | P46: 1800000 | Q46: Oct-2010 | R46: Operating | S46: 66 acres; Rs230cr initial; 10-yr excise exemption drove siting | V46: [High] BA01; BA02
A47: Akurdi (Chetak) | B47: Pune, Maharashtra | D47: Bajaj Auto / Chetak Technology | F47: Vehicle assembly shut 3-Sep-2007; Chetak EV from 2020 | G47: Electric scooters | I47: Chetak | M47: Chetak EV | P47: c.50,000/month (to 60,000) | Q47: Jul-2026 | R47: Operating; expanding | S47: Also R&D centre | V47: [Medium] BA03; BA07
A48: Memo: Manaus (Brazil) | B48: Brazil | D48: Bajaj subsidiary | F48: Jun-2024 | G48: Motorcycles (CKD) | I48: n.d. | M48: — | O48: 20,000/month | P48: n.d. | Q48: 2024 | R48: Operating | S48: Outside India capacity | V48: [Low] BA06
A50: E. CAPACITY EVENT LOG (chronological; positive = addition)
A51: Event | B51: Date | C51: FY | D51: Type | F51: Plant / site | H51: Capacity change (units p.a.) | I51: Plant capacity after | J51: Company capacity after | K51: Capex (Rs cr) | L51: Status | N51: Notes | V51: Sources
A52: Waluj SOP | B52: 05-Nov-1985 | C52: FY86 | D52: New plant | F52: Waluj | L52: Commissioned | V52: BA03
A53: Chakan SOP | B53: 1998 | C53: FY99 | D53: New plant | F53: Chakan | L53: Commissioned | V53: BA03
A54: Pantnagar SOP | B54: 09-Apr-2007 | C54: FY08 | D54: New plant | F54: Pantnagar | H54: 600000 | I54: 600000 | K54: 230 | L54: Commissioned | V54: BA01; BA03
A55: Akurdi vehicle assembly shut | B55: 03-Sep-2007 | C55: FY08 | D55: Closure | F55: Akurdi | L55: Closed | N55: Higher cost of production | V55: BA03
A56: Pantnagar doubled | B56: 2009 | C56: FY10 | D56: Expansion | F56: Pantnagar | H56: 600000 | I56: 1200000 | L56: Completed | V56: BA01
A57: Pantnagar Plant II | B57: Sep/Oct-2010 | C57: FY11 | D57: Expansion | F57: Pantnagar | H57: 600000 | I57: 1800000 | J57: 5040000 | K57: 75 | L57: Completed | N57: 1.2m -> 1.5m -> 1.8m | V57: BA01; BA02
A58: Plan to 6.3m | B58: May-2012 | C58: FY13 | D58: Expansion plan | F58: Waluj, Chakan, Pantnagar | H58: 1300000 | J58: 6300000 | L58: Announced | N58: 5.7m 2W + 0.6m 3W | V58: BA04
A59: Installed capacity 6.06m | B59: FY15 | C59: FY15 | D59: Disclosure | F59: All | J59: 6060000 | L59: Reported | N59: 6.12m by Mar-2016 planned | V59: BA05
A60: Installed capacity 6.33m | B60: 31-Mar-2021 | C60: FY21 | D60: Disclosure | F60: All | J60: 6330000 | L60: Reported | V60: BA03
A61: Chakan 2 (Triumph) SOP | B61: 2024 | C61: FY25 | D61: New plant | F61: Chakan 2 | L61: Commissioned | V61: BA10
A62: Brazil plant | B62: Jun-2024 | C62: FY25 | D62: New plant (overseas) | F62: Manaus | H62: 240000 | I62: 240000 | L62: Commissioned | N62: 20k/month | V62: BA06
A63: +20% capacity in two phases | B63: 21-Jul-2026 | C63: FY27 | D63: Expansion (announced) | F63: Motorcycles, Waluj CV, Akurdi | H63: 1440000 | J63: 8640000 | L63: Announced | N63: +10% in 3-4 months; +10% by FY27-end/early FY28 | V63: BA07
A65: F. PLATFORMS, MODELS AND PLANT ALLOCATION (confidence in brackets; model-plant mapping is rarely company-disclosed)
A66: Platform / architecture | B66: Powertrain | D66: Segment | F66: Models | L66: Plant(s) | O66: First SOP | P66: Notes | V66: Sources [confidence]
A67: Pulsar family | B67: ICE | D67: 125-400cc motorcycles | F67: Pulsar N/NS/RS | L67: Chakan (Pantnagar for 135LS in 2010) | O67: 2001 | V67: [Medium] BA01
A68: KTM / Dominar | B68: ICE | D68: Premium motorcycles | F68: KTM 125-390, Dominar | L68: Chakan | O68: 2012 | V68: [Medium]
A69: Triumph 400 (TR-series) | B69: ICE | D69: Premium motorcycles | F69: Speed 400, Scrambler 400X | L69: Chakan 2 | O69: 2024 | V69: [Medium] BA10
A70: Commuter (Platina/CT) | B70: ICE | D70: 100-125cc | F70: Platina, CT | L70: Pantnagar | O70: — | V70: [Medium] BA01
A71: Chetak EV | B71: BEV | D71: Electric scooter | F71: Chetak range | L71: Akurdi | O71: 2020 | P71: FY26 retail 289,349 | V71: [Medium] BA07; EV01
A72: 3W / Qute | B72: ICE / CNG / EV | D72: 3W, quadricycle | F72: RE, Maxima, Qute | L72: Waluj | O72: — | V72: [Medium] BA07
A74: G. FORWARD CAPACITY PIPELINE — Tier 1 = commissioned after FY26 or under execution; Tier 2 = announced with timeline/site; Memo = not summed
A75: Project | B75: Location | D75: Capacity add (units p.a.) | E75: Expected timing | F75: Capex (Rs cr) | G75: Tier | H75: Status (as of 14-Oct-2026) | J75: Notes | V75: Sources
A76: Phase 1: +10% capacity | B76: Motorcycles, Waluj, Akurdi | D76: =0.1*S19 -> 720000 | E76: 3-4 months from Jul-2026 | G76: Tier 1 | H76: Under execution | J76: 10% of FY26 base | V76: BA07
A77: Phase 2: +10% capacity | B77: Motorcycles, Waluj, Akurdi | D77: =0.1*S19 -> 720000 | E77: FY27-end / early FY28 | G77: Tier 2 | H77: Announced | V77: BA07
A78: Chetak 50k -> 60k/month | B78: Akurdi | D78: =10000*12 -> 120000 | E78: 'Next couple of months' (Jul-2026) | G78: Memo | H78: Within the 20% programme | J78: Not additive to phases | V78: BA07
A80: H. ANALYST NOTES
A81: Disclosure exists — retrieval is the gap. Bajaj Directors' Reports state installed capacity most years; FY13-FY20 and FY22-FY25 to be filled from ARs.
A82: Pantnagar tripled in three years on tax incentives. 0.6m (2007) -> 1.8m (Oct-2010).
A83: FY26 utilisation of c.71% understates tightness. The +20% programme targets EV, CV/3W and premium lines.

Sheet TVS Motor
A1: TVS Motor Company Ltd
A2: TVSL IN | Segment: 2W/3W | Units: vehicles p.a. unless stated | FY = year to 31-Mar | As of 14-Oct-2026
A3: Scope: 2W + 3W capacity: Hosur, Mysuru, Nalagarh (India) and Karawang (Indonesia) — company figures may include Karawang.
A4: A. SNAPSHOT
A5: Latest disclosed installed capacity (units p.a.) | C5: 6800000 | F5: As of May-2026 (mgmt) [TV05]
A6: As of | C6: May-2026 (mgmt)
A7: Capacity definition / scope | C7: Total annual capacity per management (May-2026); earlier website figures split 2W/3W
A8: Vehicle assembly sites | C8: 3 in India — Hosur, Mysuru, Nalagarh (+ Karawang, Indonesia)
A9: FY26 volume (units) | C9: =IF(ISNUMBER(S22),S22,"n.d.") -> 5889000 | F9: Total sales FY26 (2W + 3W incl. exports)
A10: FY26 volume basis | C10: Total sales FY26 (2W + 3W incl. exports)
A11: FY26 utilisation | C11: =IFERROR(C9/S19,"n.d.") -> 0.86602941 | F11: FY26 volume ÷ FY26 year-end capacity (row 19)
A12: Outlook base capacity (units p.a.) | C12: =S19 -> 6800000 | F12: FY26 year-end (row 19)
A13: Company capacity target (units p.a.) | C13: 8300000 | F13: [TV05]
A14: Target timing | C14: Within 12 months of May-2026
A15: Bottom line | C15: TVS is outgrowing its plants. FY26 sales rise 24% to 5.89m on c.6.8m capacity (c.87%); management adds 1.5m within 12 months and is evaluating a new site, with EV lines going to 50k/month.
A17: B. COMPANY-LEVEL CAPACITY AND OUTPUT HISTORY, FY10–FY26 (blue = sourced input; black = formula; orange = verify; light blue = bracketed carry)
A18: Metric | B18: Unit | C18: FY10 | D18: FY11 | E18: FY12 | F18: FY13 | G18: FY14 | H18: FY15 | I18: FY16 | J18: FY17 | K18: FY18 | L18: FY19 | M18: FY20 | N18: FY21 | O18: FY22 | P18: FY23 | Q18: FY24 | R18: FY25 | S18: FY26 | T18: Notes
A19: Installed capacity, FY-end (reported) | B19: units p.a. | P19: 5190000 | S19: 6800000 | T19: Older '4m 2W + 120k 3W' (undated, aggregator) and website '5.5m 2W + 250k 3W' (undated) not placed in a year.
A20: Capacity basis code | B20: code | P20: S | S20: M | T20: R = company-reported total; S = sum of company-disclosed plants; M = management statement via media; A = monthly x12; D = DRHP/RHP
A21: Production — actual | B21: units | T21: Not captured — retrieve from ARs.
A22: Sales / dispatches — actual, total | B22: units | M22: =M23+M24 -> 3263507 | R22: 4744000 | S22: 5889000 | T22: FY20 = sum of 2W/3W domestic and export components; FY25-FY26 lakh-rounded per company release.
A23: of which domestic | B23: units | M23: =2410755+11934 -> 2422689 | T23: FY20: 2W 2,410,755 + 3W 11,934.
A24: of which exports | B24: units | M24: =678841+161977 -> 840818 | R24: 1195000 | S24: 1585000 | T24: FY20: 2W 678,841 + 3W 161,977.
A25: Utilisation — production ÷ FY-end capacity | B25: % | C25: =IF(AND(ISNUMBER(C21),ISNUMBER(C19)),C21/C19,"") | D25: =IF(AND(ISNUMBER(D21),ISNUMBER(D19)),D21/D19,"") | E25: =IF(AND(ISNUMBER(E21),ISNUMBER(E19)),E21/E19,"") | F25: =IF(AND(ISNUMBER(F21),ISNUMBER(F19)),F21/F19,"") | G25: =IF(AND(ISNUMBER(G21),ISNUMBER(G19)),G21/G19,"") | H25: =IF(AND(ISNUMBER(H21),ISNUMBER(H19)),H21/H19,"") | I25: =IF(AND(ISNUMBER(I21),ISNUMBER(I19)),I21/I19,"") | J25: =IF(AND(ISNUMBER(J21),ISNUMBER(J19)),J21/J19,"") | ... S25: =IF(AND(ISNUMBER(S21),ISNUMBER(S19)),S21/S19,"") | T25: Formula. Company convention (e.g., HMIL DRHP). Depressed in commissioning years.
A26: Utilisation — production ÷ avg(opening, closing) capacity | B26: % | C26: =IF(AND(ISNUMBER(C21),ISNUMBER(C19)),C21/C19,"") | D26: =IF(AND(ISNUMBER(D21),ISNUMBER(D19)),D21/IF(ISNUMBER(C19),AVERAGE(C19,D19),D19),"") | E26: =IF(AND(ISNUMBER(E21),ISNUMBER(E19)),E21/IF(ISNUMBER(D19),AVERAGE(D19,E19),E19),"") | F26: =IF(AND(ISNUMBER(F21),ISNUMBER(F19)),F21/IF(ISNUMBER(E19),AVERAGE(E19,F19),F19),"") | G26: =IF(AND(ISNUMBER(G21),ISNUMBER(G19)),G21/IF(ISNUMBER(F19),AVERAGE(F19,G19),G19),"") | H26: =IF(AND(ISNUMBER(H21),ISNUMBER(H19)),H21/IF(ISNUMBER(G19),AVERAGE(G19,H19),H19),"") | I26: =IF(AND(ISNUMBER(I21),ISNUMBER(I19)),I21/IF(ISNUMBER(H19),AVERAGE(H19,I19),I19),"") | J26: =IF(AND(ISNUMBER(J21),ISNUMBER(J19)),J21/IF(ISNUMBER(I19),AVERAGE(I19,J19),J19),"") | K26: =IF(AND(ISNUMBER(K21),ISNUMBER(K19)),K21/IF(ISNUMBER(J19),AVERAGE(J19,K19),K19),"") | ... S26: =IF(AND(ISNUMBER(S21),ISNUMBER(S19)),S21/IF(ISNUMBER(R19),AVERAGE(R19,S19),S19),"") | T26: Formula. Uses closing capacity where opening not disclosed.
A27: Utilisation — sales ÷ FY-end capacity | B27: % | C27: =IF(ISNUMBER(C19),IF(ISNUMBER(C22),C22/C19,IF(ISNUMBER(C23),C23/C19,"")),"") | D27: =IF(ISNUMBER(D19),IF(ISNUMBER(D22),D22/D19,IF(ISNUMBER(D23),D23/D19,"")),"") | E27: =IF(ISNUMBER(E19),IF(ISNUMBER(E22),E22/E19,IF(ISNUMBER(E23),E23/E19,"")),"") | F27: =IF(ISNUMBER(F19),IF(ISNUMBER(F22),F22/F19,IF(ISNUMBER(F23),F23/F19,"")),"") | G27: =IF(ISNUMBER(G19),IF(ISNUMBER(G22),G22/G19,IF(ISNUMBER(G23),G23/G19,"")),"") | H27: =IF(ISNUMBER(H19),IF(ISNUMBER(H22),H22/H19,IF(ISNUMBER(H23),H23/H19,"")),"") | I27: =IF(ISNUMBER(I19),IF(ISNUMBER(I22),I22/I19,IF(ISNUMBER(I23),I23/I19,"")),"") | J27: =IF(ISNUMBER(J19),IF(ISNUMBER(J22),J22/J19,IF(ISNUMBER(J23),J23/J19,"")),"") | ... S27: =IF(ISNUMBER(S19),IF(ISNUMBER(S22),S22/S19,IF(ISNUMBER(S23),S23/S19,"")),"") -> 0.86602941 | T27: Formula. Uses total sales, else domestic (understates where exports excluded).
A28: Capacity change vs prior FY | B28: units p.a. | D28: =IF(AND(ISNUMBER(D19),ISNUMBER(C19)),D19-C19,"") | E28: =IF(AND(ISNUMBER(E19),ISNUMBER(D19)),E19-D19,"") | F28: =IF(AND(ISNUMBER(F19),ISNUMBER(E19)),F19-E19,"") | G28: =IF(AND(ISNUMBER(G19),ISNUMBER(F19)),G19-F19,"") | H28: =IF(AND(ISNUMBER(H19),ISNUMBER(G19)),H19-G19,"") | I28: =IF(AND(ISNUMBER(I19),ISNUMBER(H19)),I19-H19,"") | J28: =IF(AND(ISNUMBER(J19),ISNUMBER(I19)),J19-I19,"") | K28: =IF(AND(ISNUMBER(K19),ISNUMBER(J19)),K19-J19,"") | ... S28: =IF(AND(ISNUMBER(S19),ISNUMBER(R19)),S19-R19,"") | T28: Formula; blank where either year undisclosed.
A29: Utilisation — company-reported | B29: %
A30: Source IDs (see Source Log) | M30: TV02 | P30: TV03 | R30: TV06 | S30: TV05; TV06; TV07
A31: Year notes | M31: Hosur 2.5m; Mysuru 1.7m | P31: 4.95m 2W + 0.24m 3W (website) | R31: Website later shows 5.5m 2W + 0.25m 3W (undated) | S31: 6.8m; +1.5m in 12 months
A33: C. PLANT-LEVEL CAPACITY AND OUTPUT BY FISCAL YEAR (disclosed points only; no interpolation)
A34: Plant / line | B34: Unit | C34: FY10 | D34: FY11 | E34: FY12 | F34: FY13 | G34: FY14 | H34: FY15 | I34: FY16 | J34: FY17 | K34: FY18 | L34: FY19 | M34: FY20 | N34: FY21 | O34: FY22 | P34: FY23 | Q34: FY24 | R34: FY25 | S34: FY26 | T34: Notes [sources]
A35: Hosur | B35: units p.a. | M35: 2500000 | T35: [TV02]
A36: Mysuru | B36: units p.a. | M36: 1700000 | T36: [TV02]
A37: Company — 2W capacity | B37: units p.a. | P37: 4950000 | T37: [TV03]
A38: Company — 3W capacity | B38: units p.a. | P38: 240000 | T38: [TV03]
A40: D. PLANT REGISTER
A41: Plant / site | B41: Location | D41: Entity / ownership | F41: SOP / commissioned | G41: Vehicle category | I41: Key models (latest disclosed) | M41: Platforms | O41: Initial capacity (units p.a.) | P41: Latest capacity (units p.a.) | Q41: As of | R41: Status | S41: Notes | V41: Sources [confidence]
A42: Hosur | B42: Tamil Nadu | D42: TVS Motor | F42: 1979 (moped division) | G42: Motorcycles, scooters, mopeds, EV; BMW 310 (contract) | I42: iQube; BMW G 310 series; Norton (future) | M42: see F | P42: 2500000 | Q42: May-2020 | R42: Operating | S42: 200,000th BMW Dec-2025; Platinum GreenCo | V42: [High] TV01; TV02; TV05; TV07
A43: Mysuru | B43: Karnataka | D43: TVS Motor | F43: n.d. | G43: 2W, 3W (n.d.) | I43: n.d. | M43: — | P43: 1700000 | Q43: May-2020 | R43: Operating | V43: [Medium] TV02
A44: Nalagarh | B44: Himachal Pradesh | D44: TVS Motor | F44: FY08 | G44: 2W | I44: n.d. | M44: — | O44: 400000 | P44: Scalable to 600,000 | Q44: FY07 | R44: Operating | S44: Gold GreenCo | V44: [Medium] TV01; TV07
A45: Memo: Karawang | B45: Indonesia | D45: PT TVS Motor Company Indonesia | F45: FY08 | G45: 2W | I45: n.d. | M45: — | O45: 300000 | P45: n.d. | Q45: FY08 | R45: Operating | V45: [Medium] TV01
A46: Memo: new plant | B46: Gujarat / MP / Karnataka / TN (media) | D46: TVS Motor | F46: — | G46: 2W, 3W | I46: — | M46: — | P46: n.d. | Q46: May-2026 | R46: Under evaluation | S46: Not confirmed | V46: [Low] TV05
A48: E. CAPACITY EVENT LOG (chronological; positive = addition)
A49: Event | B49: Date | C49: FY | D49: Type | F49: Plant / site | H49: Capacity change (units p.a.) | I49: Plant capacity after | J49: Company capacity after | K49: Capex (Rs cr) | L49: Status | N49: Notes | V49: Sources
A50: Hosur moped division | B50: 1979 | C50: FY80 | D50: New plant | F50: Hosur | L50: Commissioned | N50: Sundaram-Clayton | V50: TV01
A51: Nalagarh SOP | B51: FY08 | C51: FY08 | D51: New plant | F51: Nalagarh | H51: 400000 | I51: 400000 | L51: Commissioned | N51: Scalable to 600k | V51: TV01
A52: Karawang SOP | B52: FY08 | C52: FY08 | D52: New plant (overseas) | F52: Karawang | H52: 300000 | I52: 300000 | L52: Commissioned | V52: TV01
A53: Plant capacities stated | B53: May-2020 | C53: FY20 | D53: Disclosure | F53: Hosur; Mysuru | L53: Reported | N53: 2.5m and 1.7m | V53: TV02
A54: Capacity 4.95m 2W + 0.24m 3W | B54: c.FY23 | C54: FY23 | D54: Disclosure | F54: All | J54: 5190000 | L54: Reported | N54: Company website | V54: TV03
A55: Capacity 6.8m; +1.5m plan | B55: May-2026 | C55: FY27 | D55: Expansion (announced) | F55: All (+ possible new site) | H55: 1500000 | J55: 8300000 | K55: 1000 | L55: Announced | N55: Capex = Norton mfg infra in FY27 | V55: TV05
A57: F. PLATFORMS, MODELS AND PLANT ALLOCATION (confidence in brackets; model-plant mapping is rarely company-disclosed)
A58: Platform / architecture | B58: Powertrain | D58: Segment | F58: Models | L58: Plant(s) | O58: First SOP | P58: Notes | V58: Sources [confidence]
A59: Apache / RR 310 | B59: ICE | D59: Premium motorcycles | F59: Apache RTR/RR (RR 310 on BMW G 310 base) | L59: Hosur (n.d.) | O59: 2005 | V59: [Medium]
A60: Jupiter / Ntorq | B60: ICE | D60: Scooters | F60: Jupiter, Ntorq | L60: n.d. | O60: 2013 / 2018 | V60: [Medium]
A61: iQube / Orbiter | B61: BEV | D61: Electric scooters | F61: iQube, Orbiter | L61: Hosur | O61: 2020 | P61: iQube >800k cumulative; India EV sales 0.37m in FY26 | V61: [Medium] TV07
A62: BMW G 310 (contract manufacturing) | B62: ICE | D62: Premium motorcycles | F62: BMW G 310 R/GS, F 450 GS | L62: Hosur | O62: 2016 | P62: 200,000th unit Dec-2025 | V62: [Medium] TV07
A63: King 3W | B63: ICE / CNG / EV | D63: 3W | F63: King range | L63: n.d. | O63: — | P63: 3W sales +63% in FY26 | V63: [Low] TV06
A65: G. FORWARD CAPACITY PIPELINE — Tier 1 = commissioned after FY26 or under execution; Tier 2 = announced with timeline/site; Memo = not summed
A66: Project | B66: Location | D66: Capacity add (units p.a.) | E66: Expected timing | F66: Capex (Rs cr) | G66: Tier | H66: Status (as of 14-Oct-2026) | J66: Notes | V66: Sources
A67: +1.5m capacity within 12 months | B67: Existing plants / possible new site | D67: 1500000 | E67: By c.May-2027 | G67: Tier 2 | H67: Announced by management | J67: Location mix n.d. | V67: TV05
A68: EV capacity to 50k/month | B68: Hosur | E68: FY27 | G68: Memo | H68: Planned | J68: Demand >40k/month (May-2026) | V68: TV05
A69: Norton manufacturing infrastructure | B69: Hosur / UK | E69: FY27 | F69: 1000 | G69: Memo | H69: Budgeted | J69: Part of Rs3,500cr Norton programme | V69: TV05
A71: H. ANALYST NOTES
A72: Fastest-growing incumbent. FY26 sales +24% to 5.89m; 3W +63%; exports +33% to 1.59m.
A73: Capacity definitions vary. Website figures split 2W (4.95m -> 5.5m) and 3W (240k -> 250k); May-2026 figure (6.8m) is a total.
A74: Pre-FY20 history is a gap. Retrieve installed capacity from Directors' Reports FY10-FY22.

Sheet Royal Enfield
A1: Eicher Motors Ltd — Royal Enfield
A2: EIM IN | Segment: 2W | Units: vehicles p.a. unless stated | FY = year to 31-Mar | As of 14-Oct-2026
A3: Scope: Royal Enfield motorcycles: Thiruvottiyur, Oragadam, Vallam Vadagal, Cheyyar (Tamil Nadu). Seven overseas CKD units excluded. VECV (trucks/buses JV) excluded.
A4: A. SNAPSHOT
A5: Latest disclosed installed capacity (units p.a.) | C5: 1460000 | F5: As of Feb/May-2026 [RE06; RE07]
A6: As of | C6: Feb/May-2026
A7: Capacity definition / scope | C7: Annual motorcycle capacity per Eicher ('around 14.6 lakh')
A8: Vehicle assembly sites | C8: 4 — Thiruvottiyur, Oragadam, Vallam Vadagal, Cheyyar (all Tamil Nadu)
A9: FY26 volume (units) | C9: =IF(ISNUMBER(S22),S22,"n.d.") -> 1238659 | F9: Total sales FY26 (domestic + exports)
A10: FY26 volume basis | C10: Total sales FY26 (domestic + exports)
A11: FY26 utilisation | C11: =IFERROR(C9/S19,"n.d.") -> 0.84839658 | F11: FY26 volume ÷ FY26 year-end capacity (row 19)
A12: Outlook base capacity (units p.a.) | C12: =S19 -> 1460000 | F12: FY26 year-end (row 19)
A13: Company capacity target (units p.a.) | C13: 2000000 | F13: [RE06; RE07]
A14: Target timing | C14: FY28
A15: Bottom line | C15: Running hot, expanding cheaply. FY26 volume of 1.24m (+23%) on c.1.46m capacity (c.85%); the Rs958cr Cheyyar expansion to 2.0m by FY28 costs c.Rs18k per unit of added capacity.
A17: B. COMPANY-LEVEL CAPACITY AND OUTPUT HISTORY, FY10–FY26 (blue = sourced input; black = formula; orange = verify; light blue = bracketed carry)
A18: Metric | B18: Unit | C18: FY10 | D18: FY11 | E18: FY12 | F18: FY13 | G18: FY14 | H18: FY15 | I18: FY16 | J18: FY17 | K18: FY18 | L18: FY19 | M18: FY20 | N18: FY21 | O18: FY22 | P18: FY23 | Q18: FY24 | R18: FY25 | S18: FY26 | T18: Notes
A19: Installed capacity, FY-end (reported) | B19: units p.a. | K19: 825000 | L19: 950000 | S19: 1460000 | T19: FY18 = planned combined capacity for the year; FY13-FY14 company totals ambiguous (150k combined in CY2013). FY20-FY25 not found.
A20: Capacity basis code | B20: code | K20: M | L20: M | S20: R | T20: R = company-reported total; S = sum of company-disclosed plants; M = management statement via media; A = monthly x12; D = DRHP/RHP
A21: Production — actual | B21: units | J21: 667135 | T21: FY17 'produced and sold' 667,135.
A22: Sales / dispatches — actual, total | B22: units | J22: 667135 | K22: 820000 | R22: 1009900 | S22: 1238659 | T22: FY18 8.2 lakh (rounded).
A23: of which domestic | B23: units | R23: 902757 | S23: 1107343
A24: of which exports | B24: units | R24: 107143 | S24: 131316 | T24: Exports 10.6% of FY26 volume.
A25: Utilisation — production ÷ FY-end capacity | B25: % | C25: =IF(AND(ISNUMBER(C21),ISNUMBER(C19)),C21/C19,"") | D25: =IF(AND(ISNUMBER(D21),ISNUMBER(D19)),D21/D19,"") | E25: =IF(AND(ISNUMBER(E21),ISNUMBER(E19)),E21/E19,"") | F25: =IF(AND(ISNUMBER(F21),ISNUMBER(F19)),F21/F19,"") | G25: =IF(AND(ISNUMBER(G21),ISNUMBER(G19)),G21/G19,"") | H25: =IF(AND(ISNUMBER(H21),ISNUMBER(H19)),H21/H19,"") | I25: =IF(AND(ISNUMBER(I21),ISNUMBER(I19)),I21/I19,"") | J25: =IF(AND(ISNUMBER(J21),ISNUMBER(J19)),J21/J19,"") | ... S25: =IF(AND(ISNUMBER(S21),ISNUMBER(S19)),S21/S19,"") | T25: Formula. Company convention (e.g., HMIL DRHP). Depressed in commissioning years.
A26: Utilisation — production ÷ avg(opening, closing) capacity | B26: % | C26: =IF(AND(ISNUMBER(C21),ISNUMBER(C19)),C21/C19,"") | D26: =IF(AND(ISNUMBER(D21),ISNUMBER(D19)),D21/IF(ISNUMBER(C19),AVERAGE(C19,D19),D19),"") | E26: =IF(AND(ISNUMBER(E21),ISNUMBER(E19)),E21/IF(ISNUMBER(D19),AVERAGE(D19,E19),E19),"") | F26: =IF(AND(ISNUMBER(F21),ISNUMBER(F19)),F21/IF(ISNUMBER(E19),AVERAGE(E19,F19),F19),"") | G26: =IF(AND(ISNUMBER(G21),ISNUMBER(G19)),G21/IF(ISNUMBER(F19),AVERAGE(F19,G19),G19),"") | H26: =IF(AND(ISNUMBER(H21),ISNUMBER(H19)),H21/IF(ISNUMBER(G19),AVERAGE(G19,H19),H19),"") | I26: =IF(AND(ISNUMBER(I21),ISNUMBER(I19)),I21/IF(ISNUMBER(H19),AVERAGE(H19,I19),I19),"") | J26: =IF(AND(ISNUMBER(J21),ISNUMBER(J19)),J21/IF(ISNUMBER(I19),AVERAGE(I19,J19),J19),"") | K26: =IF(AND(ISNUMBER(K21),ISNUMBER(K19)),K21/IF(ISNUMBER(J19),AVERAGE(J19,K19),K19),"") | ... S26: =IF(AND(ISNUMBER(S21),ISNUMBER(S19)),S21/IF(ISNUMBER(R19),AVERAGE(R19,S19),S19),"") | T26: Formula. Uses closing capacity where opening not disclosed.
A27: Utilisation — sales ÷ FY-end capacity | B27: % | C27: =IF(ISNUMBER(C19),IF(ISNUMBER(C22),C22/C19,IF(ISNUMBER(C23),C23/C19,"")),"") | D27: =IF(ISNUMBER(D19),IF(ISNUMBER(D22),D22/D19,IF(ISNUMBER(D23),D23/D19,"")),"") | E27: =IF(ISNUMBER(E19),IF(ISNUMBER(E22),E22/E19,IF(ISNUMBER(E23),E23/E19,"")),"") | F27: =IF(ISNUMBER(F19),IF(ISNUMBER(F22),F22/F19,IF(ISNUMBER(F23),F23/F19,"")),"") | G27: =IF(ISNUMBER(G19),IF(ISNUMBER(G22),G22/G19,IF(ISNUMBER(G23),G23/G19,"")),"") | H27: =IF(ISNUMBER(H19),IF(ISNUMBER(H22),H22/H19,IF(ISNUMBER(H23),H23/H19,"")),"") | I27: =IF(ISNUMBER(I19),IF(ISNUMBER(I22),I22/I19,IF(ISNUMBER(I23),I23/I19,"")),"") | J27: =IF(ISNUMBER(J19),IF(ISNUMBER(J22),J22/J19,IF(ISNUMBER(J23),J23/J19,"")),"") | ... S27: =IF(ISNUMBER(S19),IF(ISNUMBER(S22),S22/S19,IF(ISNUMBER(S23),S23/S19,"")),"") -> 0.84839658 | T27: Formula. Uses total sales, else domestic (understates where exports excluded).
A28: Capacity change vs prior FY | B28: units p.a. | D28: =IF(AND(ISNUMBER(D19),ISNUMBER(C19)),D19-C19,"") | E28: =IF(AND(ISNUMBER(E19),ISNUMBER(D19)),E19-D19,"") | F28: =IF(AND(ISNUMBER(F19),ISNUMBER(E19)),F19-E19,"") | G28: =IF(AND(ISNUMBER(G19),ISNUMBER(F19)),G19-F19,"") | H28: =IF(AND(ISNUMBER(H19),ISNUMBER(G19)),H19-G19,"") | I28: =IF(AND(ISNUMBER(I19),ISNUMBER(H19)),I19-H19,"") | J28: =IF(AND(ISNUMBER(J19),ISNUMBER(I19)),J19-I19,"") | K28: =IF(AND(ISNUMBER(K19),ISNUMBER(J19)),K19-J19,"") | ... S28: =IF(AND(ISNUMBER(S19),ISNUMBER(R19)),S19-R19,"") | T28: Formula; blank where either year undisclosed.
A29: Utilisation — company-reported | B29: %
A30: Source IDs (see Source Log) | F30: RE02 | G30: RE01; RE02 | J30: RE03 | K30: RE03; RE04 | L30: RE04 | R30: RE08 | S30: RE05; RE06; RE07; RE08
A31: Year notes | F31: FY13 production c.113k | G31: Oragadam phase 1 (150k) SOP 2013 | H31: Oragadam phase 2 to 250k planned | J31: 'Nearing installed capacity' at 667k | K31: Vallam Vadagal ph1 (300k) SOP 28-Aug-2017 | L31: VV phase 2 | S31: Cheyyar opened Jun-2025
A33: C. PLANT-LEVEL CAPACITY AND OUTPUT BY FISCAL YEAR (disclosed points only; no interpolation)
A34: Plant / line | B34: Unit | C34: FY10 | D34: FY11 | E34: FY12 | F34: FY13 | G34: FY14 | H34: FY15 | I34: FY16 | J34: FY17 | K34: FY18 | L34: FY19 | M34: FY20 | N34: FY21 | O34: FY22 | P34: FY23 | Q34: FY24 | R34: FY25 | S34: FY26 | T34: Notes [sources]
A35: Oragadam | B35: units p.a. | G35: 150000 | T35: Phase 1; phase 2 to 250k planned [RE01; RE02]
A36: Vallam Vadagal | B36: units p.a. | K36: 300000 | T36: Phase 1 [RE03]
A37: Oragadam + Vallam Vadagal combined | B37: units p.a. | S37: 1000000 | T37: 'Over one million' (Jun-2025) — lower bound [RE05]
A38: Cheyyar | B38: units p.a. | T38: Not disclosed at opening; +540k by FY28 [RE05; RE07]
A40: D. PLANT REGISTER
A41: Plant / site | B41: Location | D41: Entity / ownership | F41: SOP / commissioned | G41: Vehicle category | I41: Key models (latest disclosed) | M41: Platforms | O41: Initial capacity (units p.a.) | P41: Latest capacity (units p.a.) | Q41: As of | R41: Status | S41: Notes | V41: Sources [confidence]
A42: Thiruvottiyur | B42: Chennai, Tamil Nadu | D42: Eicher (RE) | F42: Legacy (1950s) | G42: Engines / legacy | I42: n.d. | M42: — | P42: n.d. | Q42: — | R42: Operating | S42: Engine plant and chrome plating retained after Oragadam (2013) | V42: [Medium] RE02; RE06
A43: Oragadam | B43: Tamil Nadu | D43: Eicher (RE) | F43: 2013 | G43: Motorcycles | I43: n.d. | M43: — | O43: 150000 | P43: n.d. | Q43: — | R43: Operating | S43: Rs150cr phase 1; phase 2 to 250k | V43: [Medium] RE01; RE02
A44: Vallam Vadagal | B44: Tamil Nadu | D44: Eicher (RE) | F44: 28-Aug-2017 | G44: Motorcycles | I44: n.d. | M44: — | O44: 300000 | P44: n.d. | Q44: — | R44: Operating | S44: 50 acres; phase 2 2018-19 | V44: [High] RE03; RE04
A45: Cheyyar | B45: SIPCOT, Tamil Nadu | D45: Eicher (RE) | F45: Jun-2025 | G45: Motorcycles; future EV (Flying Flea) | I45: Bullet 650, Flying Flea C6/S6 (planned) | M45: 650 twin; Flying Flea | O45: n.d. | P45: +540,000 by FY28 | Q45: Feb-2026 | R45: Operating; expanding | S45: 50 acres; Rs958cr expansion | V45: [High] RE05; RE06; RE07
A46: Memo: overseas CKD | B46: 7 units (incl. LatAm, SE Asia, Nepal, Bangladesh) | D46: RE subsidiaries/partners | F46: — | G46: CKD assembly | I46: — | M46: — | P46: n.d. | Q46: May-2026 | R46: Operating | S46: Outside India capacity | V46: [Medium] RE06
A48: E. CAPACITY EVENT LOG (chronological; positive = addition)
A49: Event | B49: Date | C49: FY | D49: Type | F49: Plant / site | H49: Capacity change (units p.a.) | I49: Plant capacity after | J49: Company capacity after | K49: Capex (Rs cr) | L49: Status | N49: Notes | V49: Sources
A50: Oragadam phase 1 | B50: 2013 | C50: FY13/14 | D50: New plant | F50: Oragadam | H50: 150000 | I50: 150000 | K50: 150 | L50: Commissioned | N50: Combined 150k in 2013 | V50: RE01; RE02
A51: Oragadam phase 2 | B51: 2014 | C51: FY15 | D51: Expansion | F51: Oragadam | H51: 100000 | I51: 250000 | L51: Planned (delivery n.d.) | V51: RE02
A52: Vallam Vadagal land | B52: Oct-2014 | C52: FY15 | D52: New site | F52: Vallam Vadagal | L52: Acquired | N52: 50 acres | V52: RE03
A53: Vallam Vadagal phase 1 | B53: 28-Aug-2017 | C53: FY18 | D53: New plant | F53: Vallam Vadagal | H53: 300000 | I53: 300000 | J53: 825000 | K53: 800 | L53: Commissioned | N53: Capex = FY18 programme | V53: RE03
A54: Vallam Vadagal phase 2 | B54: FY19 | C54: FY19 | D54: Expansion | F54: Vallam Vadagal | J54: 950000 | K54: 800 | L54: Commissioned | N54: Capex = FY19 programme | V54: RE04
A55: Cheyyar construction | B55: Apr-2023 | C55: FY24 | D55: Construction start | F55: Cheyyar | L55: Started | N55: Part of Rs1,000-1,500cr 2023 plan | V55: RE05
A56: Cheyyar opened | B56: Jun-2025 | C56: FY26 | D56: New plant | F56: Cheyyar | J56: 1460000 | L56: Commissioned | N56: Capacity not disclosed | V56: RE05; RE06
A57: Cheyyar expansion approved | B57: Feb-2026 | C57: FY26 | D57: Expansion (approved) | F57: Cheyyar | H57: 540000 | J57: 2000000 | K57: 958 | L57: Phased from Q1FY27 | N57: Complete FY28 | V57: RE06; RE07
A59: F. PLATFORMS, MODELS AND PLANT ALLOCATION (confidence in brackets; model-plant mapping is rarely company-disclosed)
A60: Platform / architecture | B60: Powertrain | D60: Segment | F60: Models | L60: Plant(s) | O60: First SOP | P60: Notes | V60: Sources [confidence]
A61: J-platform (350cc) | B61: ICE | D61: Mid-size motorcycles | F61: Classic 350, Meteor 350, Hunter 350, Bullet 350, Goan Classic | L61: n.d. | O61: 2020 | V61: [Medium]
A62: Sherpa 450 | B62: ICE | D62: Adventure / roadster | F62: Himalayan 450, Guerrilla 450 | L62: n.d. | O62: 2023 | V62: [Medium]
A63: 650 twin | B63: ICE | D63: 650cc | F63: Interceptor, Continental GT, Super Meteor, Shotgun, Bear, Classic 650, Bullet 650 | L63: n.d. (Cheyyar for Bullet 650) | O63: 2018 | V63: [Medium] RE07
A64: Flying Flea | B64: BEV | D64: Electric urban motorcycles | F64: C6, S6 | L64: Cheyyar | O64: FY27 (planned) | V64: [Medium] RE05; RE07
A66: G. FORWARD CAPACITY PIPELINE — Tier 1 = commissioned after FY26 or under execution; Tier 2 = announced with timeline/site; Memo = not summed
A67: Project | B67: Location | D67: Capacity add (units p.a.) | E67: Expected timing | F67: Capex (Rs cr) | G67: Tier | H67: Status (as of 14-Oct-2026) | J67: Notes | V67: Sources
A68: Cheyyar expansion (+540k) | B68: Tamil Nadu | D68: 540000 | E68: Phased Q1FY27 -> FY28 | F68: 958 | G68: Tier 1 | H68: Under execution | J68: Funded from internal accruals | V68: RE06; RE07
A70: H. ANALYST NOTES
A71: Running hot. FY26 volumes +23% to 1.24m; CY2025 first year above 1m.
A72: Capex-light expansion. Rs958cr for 540k units is c.Rs18k per unit of capacity.
A73: Disclosure is lumpy. Company totals found for FY18, FY19 and FY26 only; FY20-FY25 to be retrieved.

Sheet Hero MotoCorp
A1: Hero MotoCorp Ltd
A2: HMCL IN | Segment: 2W | Units: vehicles p.a. unless stated | FY = year to 31-Mar | As of 14-Oct-2026
A3: Scope: India 2W plants: Dharuhera, Gurugram, Haridwar, Neemrana, Halol (Vadodara), Chittoor (Sri City). Colombia and Bangladesh excluded.
A4: A. SNAPSHOT
A5: Latest disclosed installed capacity (units p.a.) | C5: 11600000 | F5: As of Mar-2020 (design, incl. Chittoor at full ramp) [HE03]
A6: As of | C6: Mar-2020 (design, incl. Chittoor at full ramp)
A7: Capacity definition / scope | C7: Plant-wise design capacity (11.6m); operational 9.1m at Mar-2020 per secondary source
A8: Vehicle assembly sites | C8: 6 — Dharuhera, Gurugram, Haridwar, Neemrana, Halol, Chittoor
A9: FY26 volume (units) | C9: =IF(ISNUMBER(S22),S22,"n.d.") -> 6468834 | F9: Total dispatches FY26 (domestic + exports)
A10: FY26 volume basis | C10: Total dispatches FY26 (domestic + exports)
A11: FY26 utilisation | C11: =IFERROR(C9/C5,"n.d.") -> 0.5576581 | F11: FY26 volume ÷ latest disclosed capacity (Mar-2020 (design, incl. Chittoor at full ramp)) — indicative only
A12: Outlook base capacity (units p.a.) | C12: n.d. | F12: No disclosed current base
A13: Company capacity target (units p.a.) | C13: n.d. | F13: [—]
A14: Target timing | C14: n.a.
A15: Bottom line | C15: Largest installed base, weakest current disclosure. Plant design capacity of 11.6m (2020) vs 6.47m FY26 dispatches implies c.5m units of structural slack; incremental capex now goes to EV lines (Vida 25k -> 50k+/month), not ICE.
A17: B. COMPANY-LEVEL CAPACITY AND OUTPUT HISTORY, FY10–FY26 (blue = sourced input; black = formula; orange = verify; light blue = bracketed carry)
A18: Metric | B18: Unit | C18: FY10 | D18: FY11 | E18: FY12 | F18: FY13 | G18: FY14 | H18: FY15 | I18: FY16 | J18: FY17 | K18: FY18 | L18: FY19 | M18: FY20 | N18: FY21 | O18: FY22 | P18: FY23 | Q18: FY24 | R18: FY25 | S18: FY26 | T18: Notes
A19: Installed capacity, FY-end (reported) | B19: units p.a. | H19: 7650000 | M19: 9100000 | T19: FY15 = 4 plants incl. Neemrana. FY20 9.1m (operational, eight facilities incl. overseas) per Wikipedia — verify vs AR; plant design sum 11.6m in section C.
A20: Capacity basis code | B20: code | H20: M | M20: R | T20: R = company-reported total; S = sum of company-disclosed plants; M = management statement via media; A = monthly x12; D = DRHP/RHP
A21: Production — actual | B21: units | T21: Not captured — retrieve from ARs.
A22: Sales / dispatches — actual, total | B22: units | R22: 5899187 | S22: 6468834
A23: of which domestic | B23: units | R23: 5611758 | S23: 6066048
A24: of which exports | B24: units | R24: 287429 | S24: 402786 | T24: Exports 6.2% of FY26 volume.
A25: Utilisation — production ÷ FY-end capacity | B25: % | C25: =IF(AND(ISNUMBER(C21),ISNUMBER(C19)),C21/C19,"") | D25: =IF(AND(ISNUMBER(D21),ISNUMBER(D19)),D21/D19,"") | E25: =IF(AND(ISNUMBER(E21),ISNUMBER(E19)),E21/E19,"") | F25: =IF(AND(ISNUMBER(F21),ISNUMBER(F19)),F21/F19,"") | G25: =IF(AND(ISNUMBER(G21),ISNUMBER(G19)),G21/G19,"") | H25: =IF(AND(ISNUMBER(H21),ISNUMBER(H19)),H21/H19,"") | I25: =IF(AND(ISNUMBER(I21),ISNUMBER(I19)),I21/I19,"") | J25: =IF(AND(ISNUMBER(J21),ISNUMBER(J19)),J21/J19,"") | ... S25: =IF(AND(ISNUMBER(S21),ISNUMBER(S19)),S21/S19,"") | T25: Formula. Company convention (e.g., HMIL DRHP). Depressed in commissioning years.
A26: Utilisation — production ÷ avg(opening, closing) capacity | B26: % | C26: =IF(AND(ISNUMBER(C21),ISNUMBER(C19)),C21/C19,"") | D26: =IF(AND(ISNUMBER(D21),ISNUMBER(D19)),D21/IF(ISNUMBER(C19),AVERAGE(C19,D19),D19),"") | E26: =IF(AND(ISNUMBER(E21),ISNUMBER(E19)),E21/IF(ISNUMBER(D19),AVERAGE(D19,E19),E19),"") | F26: =IF(AND(ISNUMBER(F21),ISNUMBER(F19)),F21/IF(ISNUMBER(E19),AVERAGE(E19,F19),F19),"") | G26: =IF(AND(ISNUMBER(G21),ISNUMBER(G19)),G21/IF(ISNUMBER(F19),AVERAGE(F19,G19),G19),"") | H26: =IF(AND(ISNUMBER(H21),ISNUMBER(H19)),H21/IF(ISNUMBER(G19),AVERAGE(G19,H19),H19),"") | I26: =IF(AND(ISNUMBER(I21),ISNUMBER(I19)),I21/IF(ISNUMBER(H19),AVERAGE(H19,I19),I19),"") | J26: =IF(AND(ISNUMBER(J21),ISNUMBER(J19)),J21/IF(ISNUMBER(I19),AVERAGE(I19,J19),J19),"") | K26: =IF(AND(ISNUMBER(K21),ISNUMBER(K19)),K21/IF(ISNUMBER(J19),AVERAGE(J19,K19),K19),"") | ... S26: =IF(AND(ISNUMBER(S21),ISNUMBER(S19)),S21/IF(ISNUMBER(R19),AVERAGE(R19,S19),S19),"") | T26: Formula. Uses closing capacity where opening not disclosed.
A27: Utilisation — sales ÷ FY-end capacity | B27: % | C27: =IF(ISNUMBER(C19),IF(ISNUMBER(C22),C22/C19,IF(ISNUMBER(C23),C23/C19,"")),"") | D27: =IF(ISNUMBER(D19),IF(ISNUMBER(D22),D22/D19,IF(ISNUMBER(D23),D23/D19,"")),"") | E27: =IF(ISNUMBER(E19),IF(ISNUMBER(E22),E22/E19,IF(ISNUMBER(E23),E23/E19,"")),"") | F27: =IF(ISNUMBER(F19),IF(ISNUMBER(F22),F22/F19,IF(ISNUMBER(F23),F23/F19,"")),"") | G27: =IF(ISNUMBER(G19),IF(ISNUMBER(G22),G22/G19,IF(ISNUMBER(G23),G23/G19,"")),"") | H27: =IF(ISNUMBER(H19),IF(ISNUMBER(H22),H22/H19,IF(ISNUMBER(H23),H23/H19,"")),"") | I27: =IF(ISNUMBER(I19),IF(ISNUMBER(I22),I22/I19,IF(ISNUMBER(I23),I23/I19,"")),"") | J27: =IF(ISNUMBER(J19),IF(ISNUMBER(J22),J22/J19,IF(ISNUMBER(J23),J23/J19,"")),"") | ... S27: =IF(ISNUMBER(S19),IF(ISNUMBER(S22),S22/S19,IF(ISNUMBER(S23),S23/S19,"")),"") | T27: Formula. Uses total sales, else domestic (understates where exports excluded).
A28: Capacity change vs prior FY | B28: units p.a. | D28: =IF(AND(ISNUMBER(D19),ISNUMBER(C19)),D19-C19,"") | E28: =IF(AND(ISNUMBER(E19),ISNUMBER(D19)),E19-D19,"") | F28: =IF(AND(ISNUMBER(F19),ISNUMBER(E19)),F19-E19,"") | G28: =IF(AND(ISNUMBER(G19),ISNUMBER(F19)),G19-F19,"") | H28: =IF(AND(ISNUMBER(H19),ISNUMBER(G19)),H19-G19,"") | I28: =IF(AND(ISNUMBER(I19),ISNUMBER(H19)),I19-H19,"") | J28: =IF(AND(ISNUMBER(J19),ISNUMBER(I19)),J19-I19,"") | K28: =IF(AND(ISNUMBER(K19),ISNUMBER(J19)),K19-J19,"") | ... S28: =IF(AND(ISNUMBER(S19),ISNUMBER(R19)),S19-R19,"") | T28: Formula; blank where either year undisclosed.
A29: Utilisation — company-reported | B29: %
A30: Source IDs (see Source Log) | E30: HE01 | H30: HE02 | K30: HE04 | M30: HE03; HE05 | R30: HE06 | S30: HE06; HE07
A31: Year notes | E31: Oct-2011: 6.15m (3 plants); 7.0m targeted by Mar-2012 | H31: Neemrana SOP Oct-2014 | K31: Combined c.9m (c.2018) | M31: Chittoor SOP 19-Mar-2020; design 11.6m | S31: EV capacity 15k -> 25k/month
A33: C. PLANT-LEVEL CAPACITY AND OUTPUT BY FISCAL YEAR (disclosed points only; no interpolation)
A34: Plant / line | B34: Unit | C34: FY10 | D34: FY11 | E34: FY12 | F34: FY13 | G34: FY14 | H34: FY15 | I34: FY16 | J34: FY17 | K34: FY18 | L34: FY19 | M34: FY20 | N34: FY21 | O34: FY22 | P34: FY23 | Q34: FY24 | R34: FY25 | S34: FY26 | T34: Notes [sources]
A35: Haridwar | B35: units p.a. | M35: 2700000 | T35: 9,500/day [HE03; HE04]
A36: Dharuhera | B36: units p.a. | M36: 2100000 | T36: [HE03]
A37: Gurugram | B37: units p.a. | M37: 2100000 | T37: [HE03]
A38: Neemrana | B38: units p.a. | H38: 750000 | M38: 1100000 | T38: [HE02; HE03]
A39: Halol / Vadodara | B39: units p.a. | M39: 1800000 | T39: [HE03]
A40: Chittoor / Sri City (design) | B40: units p.a. | M40: 1800000 | T40: Three phases [HE03]
A41: Sum of plant design capacities | B41: units p.a. | C41: =IF(COUNT(C35,C36,C37,C38,C39,C40)=0,"",SUM(C35,C36,C37,C38,C39,C40)) | D41: =IF(COUNT(D35,D36,D37,D38,D39,D40)=0,"",SUM(D35,D36,D37,D38,D39,D40)) | E41: =IF(COUNT(E35,E36,E37,E38,E39,E40)=0,"",SUM(E35,E36,E37,E38,E39,E40)) | F41: =IF(COUNT(F35,F36,F37,F38,F39,F40)=0,"",SUM(F35,F36,F37,F38,F39,F40)) | G41: =IF(COUNT(G35,G36,G37,G38,G39,G40)=0,"",SUM(G35,G36,G37,G38,G39,G40)) | H41: =IF(COUNT(H35,H36,H37,H38,H39,H40)=0,"",SUM(H35,H36,H37,H38,H39,H40)) -> 750000 | I41: =IF(COUNT(I35,I36,I37,I38,I39,I40)=0,"",SUM(I35,I36,I37,I38,I39,I40)) | J41: =IF(COUNT(J35,J36,J37,J38,J39,J40)=0,"",SUM(J35,J36,J37,J38,J39,J40)) | ... S41: =IF(COUNT(S35,S36,S37,S38,S39,S40)=0,"",SUM(S35,S36,S37,S38,S39,S40)) | T41: Formula; FY20 = 11.6m design
A43: D. PLANT REGISTER
A44: Plant / site | B44: Location | D44: Entity / ownership | F44: SOP / commissioned | G44: Vehicle category | I44: Key models (latest disclosed) | M44: Platforms | O44: Initial capacity (units p.a.) | P44: Latest capacity (units p.a.) | Q44: As of | R44: Status | S44: Notes | V44: Sources [confidence]
A45: Dharuhera | B45: Haryana | D45: Hero MotoCorp | F45: 1985 | G45: Motorcycles, scooters | I45: n.d. | M45: — | P45: 2100000 | Q45: Mar-2020 | R45: Operating | S45: First Hero Honda plant | V45: [Medium] HE03; HE05
A46: Gurugram | B46: Haryana | D46: Hero MotoCorp | F46: n.d. | G46: Motorcycles, scooters | I46: n.d. | M46: — | P46: 2100000 | Q46: Mar-2020 | R46: Operating | V46: [Medium] HE03
A47: Haridwar | B47: Uttarakhand | D47: Hero MotoCorp | F47: 2008 (n.d.) | G47: Commuter motorcycles | I47: Splendor family (n.d.) | M47: — | P47: 2700000 | Q47: Mar-2020 | R47: Operating | S47: 9,500/day; 'world's largest 2W plant'; 25m cumulative (c.2018) | V47: [High] HE01; HE03; HE04
A48: Neemrana | B48: Rajasthan | D48: Hero MotoCorp | F48: Oct-2014 | G48: Premium motorcycles | I48: X440 / Mavrick 440 (media) | M48: 440 platform | O48: 750000 | P48: 1100000 | Q48: Mar-2020 | R48: Operating | S48: Rs1,050cr initial | V48: [High] HE02; HE03
A49: Halol / Vadodara | B49: Gujarat | D49: Hero MotoCorp | F49: c.2016 (n.d.) | G49: Scooters (n.d.) | I49: n.d. | M49: — | P49: 1800000 | Q49: Mar-2020 | R49: Operating | V49: [Medium] HE03
A50: Chittoor / Sri City | B50: Andhra Pradesh | D50: Hero MotoCorp | F50: 19-Mar-2020 | G50: Motorcycles, scooters; Vida EV | I50: Vida V-series | M50: Vida | P50: 1,800,000 design; EV 25,000/month | Q50: May-2026 | R50: Operating; EV doubling | S50: 600 acres; three-phase build | V50: [High] HE03; HE07
A51: Memo: Colombia, Bangladesh | B51: Overseas | D51: Hero subsidiaries/JV | F51: n.d. | G51: Assembly | I51: — | M51: — | P51: n.d. | Q51: — | R51: Operating | S51: Outside India capacity | V51: [Medium] HE03
A53: E. CAPACITY EVENT LOG (chronological; positive = addition)
A54: Event | B54: Date | C54: FY | D54: Type | F54: Plant / site | H54: Capacity change (units p.a.) | I54: Plant capacity after | J54: Company capacity after | K54: Capex (Rs cr) | L54: Status | N54: Notes | V54: Sources
A55: Capacity 6.15m; 7.0m targeted | B55: Oct-2011 | C55: FY12 | D55: Debottlenecking | F55: Dharuhera, Gurugram, Haridwar | H55: 850000 | J55: 7000000 | L55: Announced | N55: Three-shift operation; Haridwar 8,000 -> 9,500/day | V55: HE01
A56: Neemrana SOP | B56: Oct-2014 | C56: FY15 | D56: New plant | F56: Neemrana | H56: 750000 | I56: 750000 | J56: 7650000 | K56: 1050 | L56: Commissioned | V56: HE02
A57: Halol (Gujarat) SOP | B57: c.2016 (n.d.) | C57: FY17 | D57: New plant | F57: Halol | L57: Commissioned | N57: Design 1.8m (2020) | V57: HE03
A58: Chittoor SOP | B58: 19-Mar-2020 | C58: FY20 | D58: New plant | F58: Chittoor | H58: 1800000 | I58: 1800000 | J58: 11600000 | L58: Commissioned (phased) | N58: Company total = design; operational 9.1m (verify) | V58: HE03; HE05
A59: EV capacity 15k -> 25k/month | B59: May-2026 | C59: FY27 | D59: Expansion (EV) | F59: Sri City | H59: 120000 | K59: 1500 | L59: Completed; doubling planned | N59: Capex = total FY27 plan | V59: HE07
A61: F. PLATFORMS, MODELS AND PLANT ALLOCATION (confidence in brackets; model-plant mapping is rarely company-disclosed)
A62: Platform / architecture | B62: Powertrain | D62: Segment | F62: Models | L62: Plant(s) | O62: First SOP | P62: Notes | V62: Sources [confidence]
A63: 100-110cc commuter | B63: ICE | D63: Entry motorcycles | F63: Splendor, HF Deluxe, Passion | L63: Haridwar et al. (n.d.) | O63: — | V63: [Medium]
A64: 125cc | B64: ICE | D64: Executive motorcycles | F64: Glamour, Super Splendor, Xtreme 125R | L64: n.d. | O64: — | V64: [Medium]
A65: 440 platform | B65: ICE | D65: Premium (with Harley-Davidson) | F65: Harley-Davidson X440, Mavrick 440 | L65: Neemrana (media) | O65: 2023 | V65: [Medium]
A66: Scooters | B66: ICE | D66: 110-125cc | F66: Destini, Xoom, Pleasure | L66: Halol (n.d.) | O66: — | V66: [Low]
A67: Vida | B67: BEV | D67: Electric scooters | F67: Vida V-series, VX2 | L67: Chittoor (Sri City) | O67: 2022 | P67: FY26 retail 144,230 | V67: [Medium] HE07; EV01
A69: G. FORWARD CAPACITY PIPELINE — Tier 1 = commissioned after FY26 or under execution; Tier 2 = announced with timeline/site; Memo = not summed
A70: Project | B70: Location | D70: Capacity add (units p.a.) | E70: Expected timing | F70: Capex (Rs cr) | G70: Tier | H70: Status (as of 14-Oct-2026) | J70: Notes | V70: Sources
A71: EV capacity 25k -> 50k+/month | B71: Sri City | D71: =25000*12 -> 300000 | E71: FY27 | F71: 1500 | G71: Tier 1 | H71: Ramping | J71: Capex = total FY27 plan incl. non-EV items | V71: HE07
A73: H. ANALYST NOTES
A74: Structural slack is large. FY26 dispatches 6.47m vs 9.1m operational (FY20, verify) or 11.6m design — c.56-71% utilisation.
A75: Incremental capex is EV-led. No ICE capacity additions announced since Chittoor.
A76: Current capacity needs AR retrieval. FY21-FY26 company totals not found in sources reviewed.

Sheet Ola Electric
A1: Ola Electric Mobility Ltd
A2: OLAELEC IN | Segment: 2W-EV | Units: vehicles p.a. unless stated | FY = year to 31-Mar | As of 14-Oct-2026
A3: Scope: Futurefactory (vehicles) and Gigafactory (cells, Ola Cell Technologies), Krishnagiri, Tamil Nadu.
A4: A. SNAPSHOT
A5: Latest disclosed installed capacity (units p.a.) | C5: 1000000 | F5: As of Oct-2023 (DRHP) [OL03]
A6: As of | C6: Oct-2023 (DRHP)
A7: Capacity definition / scope | C7: Futurefactory installed vehicle capacity (DRHP); cells tracked separately in GWh
A8: Vehicle assembly sites | C8: 1 vehicle site (Futurefactory) + cell Gigafactory
A9: FY26 volume (units) | C9: =IF(ISNUMBER(S22),S22,"n.d.") -> 164295 | F9: Retail registrations FY26 (media; not company deliveries)
A10: FY26 volume basis | C10: Retail registrations FY26 (media; not company deliveries)
A11: FY26 utilisation | C11: =IFERROR(C9/C5,"n.d.") -> 0.164295 | F11: FY26 volume ÷ latest disclosed capacity (Oct-2023 (DRHP)) — indicative only
A12: Outlook base capacity (units p.a.) | C12: =Q19 -> 1000000 | F12: FY24 year-end (row 19)
A13: Company capacity target (units p.a.) | C13: n.d. | F13: [OL04; OL06; OL07]
A14: Target timing | C14: n.a. (cells: 5-6 GWh FY27; 20 GWh PLI)
A15: Bottom line | C15: Massive overcapacity in vehicles; capital has moved to cells. 1.0m vehicle capacity vs 164k FY26 retail (c.16%) after a 52% volume decline; the gigafactory runs at c.2.5 GWh installed with 5-6 GWh targeted.
A17: B. COMPANY-LEVEL CAPACITY AND OUTPUT HISTORY, FY10–FY26 (blue = sourced input; black = formula; orange = verify; light blue = bracketed carry)
A18: Metric | B18: Unit | C18: FY10 | D18: FY11 | E18: FY12 | F18: FY13 | G18: FY14 | H18: FY15 | I18: FY16 | J18: FY17 | K18: FY18 | L18: FY19 | M18: FY20 | N18: FY21 | O18: FY22 | P18: FY23 | Q18: FY24 | R18: FY25 | S18: FY26 | T18: Notes
A19: Installed capacity, FY-end (reported) | B19: units p.a. | O19: 500000 | Q19: 1000000 | T19: FY22 placed from Apr-2022 statement (one line, 0.5m). FY24 per DRHP (as of Oct-2023). No later vehicle capacity found.
A20: Capacity basis code | B20: code | O20: M | Q20: D | T20: R = company-reported total; S = sum of company-disclosed plants; M = management statement via media; A = monthly x12; D = DRHP/RHP
A21: Production — actual | B21: units | T21: Not disclosed in sources reviewed.
A22: Sales / dispatches — actual, total | B22: units | R22: 344300 | S22: 164295 | T22: Retail registrations (media, Vahan-based) — not company-reported deliveries.
A23: of which domestic | B23: units
A24: of which exports | B24: units
A25: Utilisation — production ÷ FY-end capacity | B25: % | C25: =IF(AND(ISNUMBER(C21),ISNUMBER(C19)),C21/C19,"") | D25: =IF(AND(ISNUMBER(D21),ISNUMBER(D19)),D21/D19,"") | E25: =IF(AND(ISNUMBER(E21),ISNUMBER(E19)),E21/E19,"") | F25: =IF(AND(ISNUMBER(F21),ISNUMBER(F19)),F21/F19,"") | G25: =IF(AND(ISNUMBER(G21),ISNUMBER(G19)),G21/G19,"") | H25: =IF(AND(ISNUMBER(H21),ISNUMBER(H19)),H21/H19,"") | I25: =IF(AND(ISNUMBER(I21),ISNUMBER(I19)),I21/I19,"") | J25: =IF(AND(ISNUMBER(J21),ISNUMBER(J19)),J21/J19,"") | ... S25: =IF(AND(ISNUMBER(S21),ISNUMBER(S19)),S21/S19,"") | T25: Formula. Company convention (e.g., HMIL DRHP). Depressed in commissioning years.
A26: Utilisation — production ÷ avg(opening, closing) capacity | B26: % | C26: =IF(AND(ISNUMBER(C21),ISNUMBER(C19)),C21/C19,"") | D26: =IF(AND(ISNUMBER(D21),ISNUMBER(D19)),D21/IF(ISNUMBER(C19),AVERAGE(C19,D19),D19),"") | E26: =IF(AND(ISNUMBER(E21),ISNUMBER(E19)),E21/IF(ISNUMBER(D19),AVERAGE(D19,E19),E19),"") | F26: =IF(AND(ISNUMBER(F21),ISNUMBER(F19)),F21/IF(ISNUMBER(E19),AVERAGE(E19,F19),F19),"") | G26: =IF(AND(ISNUMBER(G21),ISNUMBER(G19)),G21/IF(ISNUMBER(F19),AVERAGE(F19,G19),G19),"") | H26: =IF(AND(ISNUMBER(H21),ISNUMBER(H19)),H21/IF(ISNUMBER(G19),AVERAGE(G19,H19),H19),"") | I26: =IF(AND(ISNUMBER(I21),ISNUMBER(I19)),I21/IF(ISNUMBER(H19),AVERAGE(H19,I19),I19),"") | J26: =IF(AND(ISNUMBER(J21),ISNUMBER(J19)),J21/IF(ISNUMBER(I19),AVERAGE(I19,J19),J19),"") | K26: =IF(AND(ISNUMBER(K21),ISNUMBER(K19)),K21/IF(ISNUMBER(J19),AVERAGE(J19,K19),K19),"") | ... S26: =IF(AND(ISNUMBER(S21),ISNUMBER(S19)),S21/IF(ISNUMBER(R19),AVERAGE(R19,S19),S19),"") | T26: Formula. Uses closing capacity where opening not disclosed.
A27: Utilisation — sales ÷ FY-end capacity | B27: % | C27: =IF(ISNUMBER(C19),IF(ISNUMBER(C22),C22/C19,IF(ISNUMBER(C23),C23/C19,"")),"") | D27: =IF(ISNUMBER(D19),IF(ISNUMBER(D22),D22/D19,IF(ISNUMBER(D23),D23/D19,"")),"") | E27: =IF(ISNUMBER(E19),IF(ISNUMBER(E22),E22/E19,IF(ISNUMBER(E23),E23/E19,"")),"") | F27: =IF(ISNUMBER(F19),IF(ISNUMBER(F22),F22/F19,IF(ISNUMBER(F23),F23/F19,"")),"") | G27: =IF(ISNUMBER(G19),IF(ISNUMBER(G22),G22/G19,IF(ISNUMBER(G23),G23/G19,"")),"") | H27: =IF(ISNUMBER(H19),IF(ISNUMBER(H22),H22/H19,IF(ISNUMBER(H23),H23/H19,"")),"") | I27: =IF(ISNUMBER(I19),IF(ISNUMBER(I22),I22/I19,IF(ISNUMBER(I23),I23/I19,"")),"") | J27: =IF(ISNUMBER(J19),IF(ISNUMBER(J22),J22/J19,IF(ISNUMBER(J23),J23/J19,"")),"") | ... S27: =IF(ISNUMBER(S19),IF(ISNUMBER(S22),S22/S19,IF(ISNUMBER(S23),S23/S19,"")),"") | T27: Formula. Uses total sales, else domestic (understates where exports excluded).
A28: Capacity change vs prior FY | B28: units p.a. | D28: =IF(AND(ISNUMBER(D19),ISNUMBER(C19)),D19-C19,"") | E28: =IF(AND(ISNUMBER(E19),ISNUMBER(D19)),E19-D19,"") | F28: =IF(AND(ISNUMBER(F19),ISNUMBER(E19)),F19-E19,"") | G28: =IF(AND(ISNUMBER(G19),ISNUMBER(F19)),G19-F19,"") | H28: =IF(AND(ISNUMBER(H19),ISNUMBER(G19)),H19-G19,"") | I28: =IF(AND(ISNUMBER(I19),ISNUMBER(H19)),I19-H19,"") | J28: =IF(AND(ISNUMBER(J19),ISNUMBER(I19)),J19-I19,"") | K28: =IF(AND(ISNUMBER(K19),ISNUMBER(J19)),K19-J19,"") | ... S28: =IF(AND(ISNUMBER(S19),ISNUMBER(R19)),S19-R19,"") | T28: Formula; blank where either year undisclosed.
A29: Utilisation — company-reported | B29: %
A30: Source IDs (see Source Log) | N30: OL01; OL08 | O30: OL02 | Q30: OL03; OL07 | R30: EV01 | S30: EV01; OL04; OL06
A31: Year notes | N31: Construction; phase 1 planned at 2m | O31: One line; c.1,000/day | Q31: DRHP: 1.0m; cells 1.5 GWh phase 1A | S31: Q1 68,192; Q3 32,680 deliveries; cells c.2.5 GWh
A33: C. PLANT-LEVEL CAPACITY AND OUTPUT BY FISCAL YEAR (disclosed points only; no interpolation)
A34: Plant / line | B34: Unit | C34: FY10 | D34: FY11 | E34: FY12 | F34: FY13 | G34: FY14 | H34: FY15 | I34: FY16 | J34: FY17 | K34: FY18 | L34: FY19 | M34: FY20 | N34: FY21 | O34: FY22 | P34: FY23 | Q34: FY24 | R34: FY25 | S34: FY26 | T34: Notes [sources]
A35: Futurefactory — vehicles | B35: units p.a. | O35: 500000 | Q35: 1000000 | T35: [OL02; OL03]
A36: Gigafactory — cell capacity | B36: GWh | Q36: 1.5 | S36: 2.5 | T36: Phase 1A 1.5 GWh; c.2.5 GWh installed Feb-2026 [OL03; OL06]
A38: D. PLANT REGISTER
A39: Plant / site | B39: Location | D39: Entity / ownership | F39: SOP / commissioned | G39: Vehicle category | I39: Key models (latest disclosed) | M39: Platforms | O39: Initial capacity (units p.a.) | P39: Latest capacity (units p.a.) | Q39: As of | R39: Status | S39: Notes | V39: Sources [confidence]
A40: Futurefactory | B40: Pochampalli, Krishnagiri, Tamil Nadu | D40: Ola Electric Technologies | F40: 2021 | G40: E-scooters, e-motorcycles | I40: S1 range, Roadster | M40: Gen 1-3; Roadster | O40: 500000 | P40: 1000000 | Q40: Oct-2023 | R40: Operating; heavily under-utilised | S40: 500 acres; master plan 10 lines / 10m p.a.; Rs2,400cr phase 1 MoU (Dec-2020) | V40: [High] OL01; OL02; OL03; OL08
A41: Gigafactory (cells) | B41: Krishnagiri, Tamil Nadu | D41: Ola Cell Technologies | F41: Mar-2024 (phase 1A) | G41: Li-ion cells (4680 'Bharat Cell') | I41: — | M41: 4680 | O41: 1.5 GWh | P41: c.2.5 GWh installed | Q41: Feb-2026 | R41: Ramp-up | S41: PLI ACC allotment 20 GWh; site potential 100 GWh; Rs2,800cr for 5 GWh (Rs1,500cr spent by Jul-2025); 5 GWh ~ 1.2m vehicles | V41: [High] OL03; OL04; OL05; OL06; OL07
A43: E. CAPACITY EVENT LOG (chronological; positive = addition)
A44: Event | B44: Date | C44: FY | D44: Type | F44: Plant / site | H44: Capacity change (units p.a.) | I44: Plant capacity after | J44: Company capacity after | K44: Capex (Rs cr) | L44: Status | N44: Notes | V44: Sources
A45: MoU with Tamil Nadu | B45: Dec-2020 | C45: FY21 | D45: New site | F45: Futurefactory | K45: 2400 | L45: Signed | V45: OL08
A46: Construction; phase 1 at 2m p.a. planned | B46: Mar-2021 | C46: FY21 | D46: Construction | F46: Futurefactory | H46: 2000000 | L46: Planned | N46: 10m p.a. with 10 lines at full build | V46: OL01
A47: One line, 0.5m installed | B47: Apr-2022 | C47: FY22/23 | D47: Disclosure | F47: Futurefactory | I47: 500000 | J47: 500000 | L47: Reported | N47: c.1,000 units/day | V47: OL02
A48: Installed 1.0m; PLI ACC 20 GWh | B48: Oct-2023 | C48: FY24 | D48: Expansion | F48: Futurefactory | H48: 500000 | I48: 1000000 | J48: 1000000 | L48: Reported (DRHP) | V48: OL03; OL07
A49: Gigafactory phase 1A (1.5 GWh) | B49: Mar-2024 | C49: FY24 | D49: New plant (cells) | F49: Gigafactory | I49: 1.5 GWh | L49: Commissioned | N49: IPO proceeds to take cells to 6.4 GWh | V49: OL03
A50: Cells: 1.4 GWh utilised by FY26-end; 5 GWh through FY27 | B50: 14-Jul-2025 | C50: FY26 | D50: Plan (cells) | F50: Gigafactory | K50: 2800 | L50: Guided | V50: OL04; OL05
A51: Cells c.2.5 GWh installed | B51: 13-Feb-2026 | C51: FY26 | D51: Expansion (cells) | F51: Gigafactory | I51: 2.5 GWh | L51: Reported | N51: 6 GWh by Mar-2026 planned | V51: OL06
A53: F. PLATFORMS, MODELS AND PLANT ALLOCATION (confidence in brackets; model-plant mapping is rarely company-disclosed)
A54: Platform / architecture | B54: Powertrain | D54: Segment | F54: Models | L54: Plant(s) | O54: First SOP | P54: Notes | V54: Sources [confidence]
A55: S1 Gen 1-3 | B55: BEV | D55: Electric scooters | F55: S1 Pro, S1 Air, S1 X (Gen 1-3) | L55: Futurefactory | O55: 2021 | V55: [Medium] OL02
A56: Roadster | B56: BEV | D56: Electric motorcycles | F56: Roadster X, Roadster Pro | L56: Futurefactory | O56: 2025 | P56: Rollout in phases (Jul-2025) | V56: [Medium] OL04
A57: 4680 Bharat Cell | B57: Cell | D57: Battery cells | F57: Used in own vehicles; Ola Shakti storage | L57: Gigafactory | O57: 2025 | P57: Rare-earth-free motor also productionised | V57: [Medium] OL05; OL06
A59: G. FORWARD CAPACITY PIPELINE — Tier 1 = commissioned after FY26 or under execution; Tier 2 = announced with timeline/site; Memo = not summed
A60: Project | B60: Location | D60: Capacity add (units p.a.) | E60: Expected timing | F60: Capex (Rs cr) | G60: Tier | H60: Status (as of 14-Oct-2026) | J60: Notes | V60: Sources
A61: Cells to 5-6 GWh | B61: Gigafactory | E61: FY27 | F61: 2800 | G61: Memo | H61: Ramp-up | J61: GWh, not vehicles (5 GWh ~ 1.2m vehicles) | V61: OL04; OL05; OL06
A62: Cells to 20 GWh (PLI allotment) | B62: Gigafactory | E62: Long term | G62: Memo | H62: Aspiration | V62: OL07
A63: Vehicle capacity additions | B63: Futurefactory | E63: — | G63: Memo | H63: None disclosed | V63: OL03
A65: H. ANALYST NOTES
A66: Overcapacity is the defining fact. c.16% utilisation of the 1.0m line on FY26 retail; FY25 was c.34%.
A67: Capital is shifting to cells. Cell capacity 1.5 -> 2.5 GWh installed with 5-6 GWh targeted; vehicle capex is dormant.
A68: Volume definitions differ. Retail (Vahan) and company deliveries diverge; quarterly deliveries FY26: Q1 68,192, Q3 32,680.

Sheet Ather Energy
A1: Ather Energy Ltd
A2: ATHERENERG IN | Segment: 2W-EV | Units: vehicles p.a. unless stated | FY = year to 31-Mar | As of 14-Oct-2026
A3: Scope: Hosur (Tamil Nadu) vehicle and battery plants; AURIC Bidkin (Maharashtra) from Q3FY27.
A4: A. SNAPSHOT
A5: Latest disclosed installed capacity (units p.a.) | C5: 420000 | F5: As of Aug-2026 [AT05]
A6: As of | C6: Aug-2026
A7: Capacity definition / scope | C7: Hosur vehicle assembly capacity (c.35k/month)
A8: Vehicle assembly sites | C8: 1 (Hosur, two units); AURIC Bidkin commissioning Q3FY27
A9: FY26 volume (units) | C9: =IF(ISNUMBER(S22),S22,"n.d.") -> 239178 | F9: Retail registrations FY26 (media)
A10: FY26 volume basis | C10: Retail registrations FY26 (media)
A11: FY26 utilisation | C11: =IFERROR(C9/S19,"n.d.") -> 0.56947143 | F11: FY26 volume ÷ FY26 year-end capacity (row 19)
A12: Outlook base capacity (units p.a.) | C12: =S19 -> 420000 | F12: FY26 year-end (row 19)
A13: Company capacity target (units p.a.) | C13: n.d. | F13: [AT05]
A14: Target timing | C14: AURIC phase 1 Q3FY27; phase 2 in planning
A15: Bottom line | C15: Capacity is about to more than double. Hosur's 420k (c.57% utilised on FY26 retail of 239k) plus AURIC phase 1 (500k) in Q3FY27 takes capacity to 920k; management already flags 13-15k lost sales a month and is weighing an earlier phase 2.
A17: B. COMPANY-LEVEL CAPACITY AND OUTPUT HISTORY, FY10–FY26 (blue = sourced input; black = formula; orange = verify; light blue = bracketed carry)
A18: Metric | B18: Unit | C18: FY10 | D18: FY11 | E18: FY12 | F18: FY13 | G18: FY14 | H18: FY15 | I18: FY16 | J18: FY17 | K18: FY18 | L18: FY19 | M18: FY20 | N18: FY21 | O18: FY22 | P18: FY23 | Q18: FY24 | R18: FY25 | S18: FY26 | T18: Notes
A19: Installed capacity, FY-end (reported) | B19: units p.a. | O19: 120000 | P19: 420000 | Q19: 420000 | R19: 420000 | S19: 420000 | T19: FY24-FY25 bracketed: identical 420k disclosures in Nov-2022 and Aug-2026 with no change announced.
A20: Capacity basis code | B20: code | O20: M | P20: M | Q20: M* | R20: M* | S20: M | T20: R = company-reported total; S = sum of company-disclosed plants; M = management statement via media; A = monthly x12; D = DRHP/RHP
A21: Production — actual | B21: units | T21: Not disclosed in sources reviewed.
A22: Sales / dispatches — actual, total | B22: units | R22: 131172 | S22: 239178 | T22: Retail registrations (media) — not company-reported sales.
A23: of which domestic | B23: units
A24: of which exports | B24: units
A25: Utilisation — production ÷ FY-end capacity | B25: % | C25: =IF(AND(ISNUMBER(C21),ISNUMBER(C19)),C21/C19,"") | D25: =IF(AND(ISNUMBER(D21),ISNUMBER(D19)),D21/D19,"") | E25: =IF(AND(ISNUMBER(E21),ISNUMBER(E19)),E21/E19,"") | F25: =IF(AND(ISNUMBER(F21),ISNUMBER(F19)),F21/F19,"") | G25: =IF(AND(ISNUMBER(G21),ISNUMBER(G19)),G21/G19,"") | H25: =IF(AND(ISNUMBER(H21),ISNUMBER(H19)),H21/H19,"") | I25: =IF(AND(ISNUMBER(I21),ISNUMBER(I19)),I21/I19,"") | J25: =IF(AND(ISNUMBER(J21),ISNUMBER(J19)),J21/J19,"") | ... S25: =IF(AND(ISNUMBER(S21),ISNUMBER(S19)),S21/S19,"") | T25: Formula. Company convention (e.g., HMIL DRHP). Depressed in commissioning years.
A26: Utilisation — production ÷ avg(opening, closing) capacity | B26: % | C26: =IF(AND(ISNUMBER(C21),ISNUMBER(C19)),C21/C19,"") | D26: =IF(AND(ISNUMBER(D21),ISNUMBER(D19)),D21/IF(ISNUMBER(C19),AVERAGE(C19,D19),D19),"") | E26: =IF(AND(ISNUMBER(E21),ISNUMBER(E19)),E21/IF(ISNUMBER(D19),AVERAGE(D19,E19),E19),"") | F26: =IF(AND(ISNUMBER(F21),ISNUMBER(F19)),F21/IF(ISNUMBER(E19),AVERAGE(E19,F19),F19),"") | G26: =IF(AND(ISNUMBER(G21),ISNUMBER(G19)),G21/IF(ISNUMBER(F19),AVERAGE(F19,G19),G19),"") | H26: =IF(AND(ISNUMBER(H21),ISNUMBER(H19)),H21/IF(ISNUMBER(G19),AVERAGE(G19,H19),H19),"") | I26: =IF(AND(ISNUMBER(I21),ISNUMBER(I19)),I21/IF(ISNUMBER(H19),AVERAGE(H19,I19),I19),"") | J26: =IF(AND(ISNUMBER(J21),ISNUMBER(J19)),J21/IF(ISNUMBER(I19),AVERAGE(I19,J19),J19),"") | K26: =IF(AND(ISNUMBER(K21),ISNUMBER(K19)),K21/IF(ISNUMBER(J19),AVERAGE(J19,K19),K19),"") | ... S26: =IF(AND(ISNUMBER(S21),ISNUMBER(S19)),S21/IF(ISNUMBER(R19),AVERAGE(R19,S19),S19),"") | T26: Formula. Uses closing capacity where opening not disclosed.
A27: Utilisation — sales ÷ FY-end capacity | B27: % | C27: =IF(ISNUMBER(C19),IF(ISNUMBER(C22),C22/C19,IF(ISNUMBER(C23),C23/C19,"")),"") | D27: =IF(ISNUMBER(D19),IF(ISNUMBER(D22),D22/D19,IF(ISNUMBER(D23),D23/D19,"")),"") | E27: =IF(ISNUMBER(E19),IF(ISNUMBER(E22),E22/E19,IF(ISNUMBER(E23),E23/E19,"")),"") | F27: =IF(ISNUMBER(F19),IF(ISNUMBER(F22),F22/F19,IF(ISNUMBER(F23),F23/F19,"")),"") | G27: =IF(ISNUMBER(G19),IF(ISNUMBER(G22),G22/G19,IF(ISNUMBER(G23),G23/G19,"")),"") | H27: =IF(ISNUMBER(H19),IF(ISNUMBER(H22),H22/H19,IF(ISNUMBER(H23),H23/H19,"")),"") | I27: =IF(ISNUMBER(I19),IF(ISNUMBER(I22),I22/I19,IF(ISNUMBER(I23),I23/I19,"")),"") | J27: =IF(ISNUMBER(J19),IF(ISNUMBER(J22),J22/J19,IF(ISNUMBER(J23),J23/J19,"")),"") | ... S27: =IF(ISNUMBER(S19),IF(ISNUMBER(S22),S22/S19,IF(ISNUMBER(S23),S23/S19,"")),"") -> 0.56947143 | T27: Formula. Uses total sales, else domestic (understates where exports excluded).
A28: Capacity change vs prior FY | B28: units p.a. | D28: =IF(AND(ISNUMBER(D19),ISNUMBER(C19)),D19-C19,"") | E28: =IF(AND(ISNUMBER(E19),ISNUMBER(D19)),E19-D19,"") | F28: =IF(AND(ISNUMBER(F19),ISNUMBER(E19)),F19-E19,"") | G28: =IF(AND(ISNUMBER(G19),ISNUMBER(F19)),G19-F19,"") | H28: =IF(AND(ISNUMBER(H19),ISNUMBER(G19)),H19-G19,"") | I28: =IF(AND(ISNUMBER(I19),ISNUMBER(H19)),I19-H19,"") | J28: =IF(AND(ISNUMBER(J19),ISNUMBER(I19)),J19-I19,"") | K28: =IF(AND(ISNUMBER(K19),ISNUMBER(J19)),K19-J19,"") | ... S28: =IF(AND(ISNUMBER(S19),ISNUMBER(R19)),S19-R19,"") -> 0 | T28: Formula; blank where either year undisclosed.
A29: Utilisation — company-reported | B29: %
A30: Source IDs (see Source Log) | O30: AT01; AT03 | P30: AT01; AT02 | Q30: AT01; AT05 | R30: AT01; AT05; EV01 | S30: AT05; EV01
A31: Year notes | O31: Hosur plant 1 (since 2021) | P31: Hosur plant 2 (23-Nov-2022) | Q31: Bracketed (no change disclosed) | R31: AURIC announced Jun-2024 (FY25) | S31: AURIC phase 1 due Q3FY27
A33: C. PLANT-LEVEL CAPACITY AND OUTPUT BY FISCAL YEAR (disclosed points only; no interpolation)
A34: Plant / line | B34: Unit | C34: FY10 | D34: FY11 | E34: FY12 | F34: FY13 | G34: FY14 | H34: FY15 | I34: FY16 | J34: FY17 | K34: FY18 | L34: FY19 | M34: FY20 | N34: FY21 | O34: FY22 | P34: FY23 | Q34: FY24 | R34: FY25 | S34: FY26 | T34: Notes [sources]
A35: Hosur plant 1 | B35: units p.a. | O35: 120000 | T35: [AT01]
A36: Hosur site total (plants 1+2) | B36: units p.a. | P36: 420000 | Q36: 420000 | R36: 420000 | S36: 420000 | T36: [AT01; AT05]
A37: AURIC Bidkin | B37: units p.a. | T37: Phase 1 500k from Q3FY27 [AT05]
A39: D. PLANT REGISTER
A40: Plant / site | B40: Location | D40: Entity / ownership | F40: SOP / commissioned | G40: Vehicle category | I40: Key models (latest disclosed) | M40: Platforms | O40: Initial capacity (units p.a.) | P40: Latest capacity (units p.a.) | Q40: As of | R40: Status | S40: Notes | V40: Sources [confidence]
A41: Hosur plant 1 | B41: Hosur, Tamil Nadu | D41: Ather Energy | F41: 2021 | G41: E-scooters | I41: 450 series | M41: 450 | O41: 120000 | P41: Part of 420,000 site | Q41: Nov-2022 | R41: Operating | V41: [Medium] AT01; AT03
A42: Hosur plant 2 | B42: Hosur, Tamil Nadu | D42: Ather Energy | F42: 23-Nov-2022 | G42: Vehicle assembly (2 lines) + battery packs (5 lines) | I42: 450, Rizta | M42: 450; Rizta | P42: 420,000 (site) | Q42: Aug-2026 | R42: Operating; capacity-constrained | S42: 300k sq ft | V42: [High] AT01; AT02; AT05
A43: AURIC Bidkin | B43: Chhatrapati Sambhajinagar, Maharashtra | D43: Ather Energy | F43: Q3FY27 (phase 1) | G43: Vehicles + battery packs | I43: EL platform scooters | M43: EL | O43: 500000 | P43: Up to 1,000,000 (site) | Q43: Aug-2026 | R43: Commissioning | S43: Rs2,000cr+; c.100 acres | V43: [High] AT03; AT04; AT05
A45: E. CAPACITY EVENT LOG (chronological; positive = addition)
A46: Event | B46: Date | C46: FY | D46: Type | F46: Plant / site | H46: Capacity change (units p.a.) | I46: Plant capacity after | J46: Company capacity after | K46: Capex (Rs cr) | L46: Status | N46: Notes | V46: Sources
A47: Hosur plant 1 | B47: 2021 | C47: FY22 | D47: New plant | F47: Hosur | H47: 120000 | I47: 120000 | J47: 120000 | L47: Commissioned | V47: AT01; AT03
A48: Hosur plant 2 | B48: 23-Nov-2022 | C48: FY23 | D48: New plant | F48: Hosur | H48: 300000 | I48: 420000 | J48: 420000 | L48: Commissioned | N48: Battery 5 lines, vehicle 2 lines | V48: AT01; AT02
A49: AURIC plant announced | B49: Jun-2024 | C49: FY25 | D49: New plant (announced) | F49: AURIC Bidkin | H49: 1000000 | K49: 2000 | L49: Announced | N49: Vehicles + battery packs | V49: AT03; AT04
A50: AURIC phase 1 commissioning | B50: Q3FY27 | C50: FY27 | D50: New plant | F50: AURIC Bidkin | H50: 500000 | I50: 500000 | J50: 920000 | L50: Commissioning | N50: Phase 2 being evaluated | V50: AT05
A52: F. PLATFORMS, MODELS AND PLANT ALLOCATION (confidence in brackets; model-plant mapping is rarely company-disclosed)
A53: Platform / architecture | B53: Powertrain | D53: Segment | F53: Models | L53: Plant(s) | O53: First SOP | P53: Notes | V53: Sources [confidence]
A54: 450 | B54: BEV | D54: Performance scooters | F54: 450S, 450X, 450 Apex | L54: Hosur | O54: 2018 | V54: [Medium] AT01
A55: Rizta | B55: BEV | D55: Family scooter | F55: Rizta | L55: Hosur | O55: 2024 | V55: [Medium]
A56: EL | B56: BEV | D56: Low-cost scooters | F56: EL-based scooters | L56: Hosur + AURIC | O56: FY27 | P56: Target c.60k/month across two plants | V56: [Medium] AT05
A57: Zenith | B57: BEV | D57: Electric motorcycles | F57: — | L57: n.d. | O57: n.d. | P57: Unveiled Aug-2025 | V57: [Low]
A59: G. FORWARD CAPACITY PIPELINE — Tier 1 = commissioned after FY26 or under execution; Tier 2 = announced with timeline/site; Memo = not summed
A60: Project | B60: Location | D60: Capacity add (units p.a.) | E60: Expected timing | F60: Capex (Rs cr) | G60: Tier | H60: Status (as of 14-Oct-2026) | J60: Notes | V60: Sources
A61: AURIC phase 1 | B61: Maharashtra | D61: 500000 | E61: Q3FY27 | F61: 2000 | G61: Tier 1 | H61: Commissioning | J61: Capex = site programme | V61: AT04; AT05
A62: AURIC phase 2 | B62: Maharashtra | D62: 500000 | E62: TBD (planning) | G62: Tier 2 | H62: Planning; may be accelerated | J62: Derived: 1.0m site design less 0.5m phase 1 | V62: AT03; AT05
A64: H. ANALYST NOTES
A65: Demand already outruns Hosur. Management cites 13-15k lost sales per month (Aug-2026).
