Workbook

Sheet Read Me
A1: M&M Growth Gems — Financial & Qualitative Deep Dive
A2: Bernstein India Autos | Companion to the SOTP scenario framework | All figures Rs cr unless stated
A4: PURPOSE | B4: Ten Growth Gems in one place: what each business does, how it is performing, what is driving growth, and what we expect through FY30. Feeds the valuation scenarios in the companion SOTP workbook.
A6: HOW TO READ THE NUMBERS | B6: BLACK figures = reported actuals, sourced to a named document (see the Source column on every sheet). BLUE figures = our estimates or extrapolations. NOT reported. Every one has its basis stated. GREY 'n/l' = not located in any accessible disclosure. Deliberately left empty rather than guessed. FY27E-FY30E column headers are shaded gold to make the actual/estimate break obvious at a glance.
A8: ACCURACY DISCIPLINE | B8: No number is presented as reported unless a source is named. Where sources conflict (e.g. M&M's own press-release PAT vs Screener's net-profit line), BOTH are shown and the conflict is logged. The unlisted gems are thinly disclosed — roughly a third of the historic cells are genuinely unavailable in public sources. Read the Data Quality Log before circulating anything.
A10: THE ONE THING TO DO NEXT | B10: Pull Form AOC-1 (Statement of salient features of subsidiaries, s.129(3)) from the M&M FY25 and FY26 Integrated Annual Report PDFs on bseindia.com. It discloses, per subsidiary: share capital, reserves, total assets, total liabilities, turnover, PBT, tax, PAT and % shareholding. That single document closes most of the 'n/l' cells on the Revenue, PAT and Balance Sheet tabs.
A12: TAB GUIDE | B12: Gems Overview ......... what each gem does, market position, recent milestones, management targets Revenue ............... FY21A-FY26A actuals, FY27E-FY30E estimates, CAGR, growth-driver commentary EBITDA ................ EBITDA and margins, with margin-driver commentary PAT ................... PAT and margins Group Contribution .... M&M share of gem PAT and % of group PAT Balance Sheet & CF .... net worth, gearing, capital intensity, self-funding status Growth Drivers ........ per gem: what's driving revenue now, margins, FY30 outlook, what breaks the thesis Group Financials ...... M&M consolidated and standalone FY21-FY26 for context Milestones ............ dated events over the last 24 months and forward catalysts Data Quality Log ...... every conflict, ambiguity and gap, named Sources ............... master source list
A14: TAXONOMY NOTE | B14: The gem list is verified against Anish Shah's Q4 FY25 call (5 May 2025) and the second Mahindra Investor Day (20-21 Nov 2025). Six Scalable gems carry a US$2-3bn valuation target each by 2030; four Emerging gems carry US$1bn. Bristlecone, Agri/Krish-e, Teqo, HZPC, Summit, Solarize and the Manulife life-insurance JV are NOT Growth Gems and are excluded.

Sheet Gems Overview
A1: The Ten Growth Gems — what they are and where they stand
A2: Taxonomy verified against the Q4 FY25 call (5 May 2025) and the Nov-2025 Investor Day
A4: Gem | B4: Category | C4: M&M stake | D4: What it does | E4: Market position | F4: Recent milestones (last 24 months, dated) | G4: Management target | H4: Stake / structure note
A5: Mahindra Last Mile Mobility | B5: Scalable | C5: 0.7579 | D5: India's #1 electric commercial vehicle maker — electric and ICE/CNG three-wheelers (Treo, Zor, Alfa) and small four-wheel last-mile cargo/passenger vehicles (Jeeto). Carved out of M&M standalone: asset transfer approved 22-Mar-23, entity incorporated 29-May-23, commercial operations from Sep-23. | E5: c.40% share of the L5 electric three-wheeler segment (FY26). India's #1 electric-3W company four years running. 136,855 vehicles sold in FY26, of which 100,000+ electric. Electric 3W penetration itself went from 12% to 40% in two years. | F5: 30-Jul-26: unicorn — Rs 322cr raised led by Lightrock (with IFC and the India-Japan Fund/NIIF) at a Rs 10,822cr ($1.24bn) post-money valuation; M&M stake 78.11% to 75.79%. Aug-26: crossed 400,000 cumulative EV sales, India's first CV maker to do so. New Telangana plant. Exports to 10+ markets. Prior: IFC Rs 600cr at up to Rs 6,020cr (2023); India-Japan Fund Rs 400cr (Jan-24). | G5: 1 million EVs on Indian roads by 2031; 50% portfolio electrification by FY30; category to grow c.2x industry; IPO planned H2 FY27. | H5: Post Lightrock round, 30-Jul-26 (was 78.11%)
A6: Mahindra Trucks & Buses (MTBD + SML) | B6: Scalable | C6: 0.5896 | D6: Trucks and buses above 3.5T (ILCV and HCV) under the Mahindra Truck & Bus (Blazo, Furio) and SML brands. MTBD has historically been a division inside M&M standalone, not a separate legal entity; SML is separately listed as SML Mahindra. | E6: 6.0% share of >3.5T CV in FY26, up from c.3% pre-SML. India's 3rd-largest ILCV bus player. Nov-25 combined T&B sales 2,232 units, +57% YoY (SML +102%). | F6: Apr-25: agreed to buy 58.96% of SML Isuzu for Rs 555cr (Rs 650/share; open offer Rs 1,554.60). Jun-25: CCI clearance. Aug-25: completed, renamed SML Mahindra. 29-Jul-26: announced transfer of the MTBD division into listed SML Mahindra for Rs 525cr (c.$55m), closing by Jan-27 — consolidating all >3.5T CV under one listed entity. | G6: Rs 15,000cr combined business by FY31; 10-12% CV share by FY31 and 20%+ by FY36. India CV market seen going from c.Rs 1,50,000cr (FY25) to c.Rs 2,00,000cr (FY31). | H6: SML Mahindra 58.96%; MTBD 100% (inside M&M standalone until the Jan-27 transfer)
A7: Mahindra Susten | B7: Scalable | C7: 0.7 | D7: Renewable-energy developer/IPP and solar EPC — solar, hybrid and battery storage. The legal entity (Mahindra Susten Pvt Ltd) also houses Mahindra Teqo and MachinePulse. Seeded India's largest renewables InvIT, listed Aug-23 at c.1.54 GWp. | E7: Leading renewable IPP/EPC. c.6.4 GWp of total connectivity secured (FY26 Integrated Annual Report); 560 MWp commissioned in FY26. | F7: 2025: 560 MWp solar commissioned in Gujarat and Rajasthan. Mar-26: Rs 1,025cr financing for a 300 MW Rajasthan project. Dec-24: Rs 1,448cr financing for 560 MW. Jan-25: SBTi approval. 15 MWh BESS at Modhera. Avinash Rao appointed MD & CEO. Sep-22: Ontario Teachers' bought 30% at c.Rs 2,371cr equity value ($300m), with an option for a further 9.99%. | G7: 5x scale-up by 2030; c.1.5 GW to c.7 GW. InvIT provides a repeatable capital-recycling route (ROFO to the Trust). | H7: ESTIMATE. OTPP holds 30% (Sep-22) with an option for a further 9.99% — confirm via AOC-1
A8: Mahindra Logistics (MAHLOG IN) | B8: Scalable | C8: 0.58 | D8: India's largest non-captive third-party logistics provider — contract logistics and warehousing, B2B express, freight forwarding, last-mile delivery, and enterprise/B2C mobility (Alyte). 400+ corporate clients. | E8: #1 non-captive 3PL in India by revenue. | F8: FY26: returned to profitability. MD & CEO Hemant Sikka: after 11 straight quarters of losses, the company returned to profit on sharper execution. Express reached a positive gross margin (1.3% in FY26); white space cut from 1.6m to 0.7m sq ft; freight-forwarding EBITDA +48%; mobility revenue +22%. Rights issue completed in FY26. | G8: Sustained margin expansion off the turnaround; scale the asset-right 3PL model. | H8: Listed
A9: Mahindra Holidays / Club Mahindra (MHRIL IN) | B9: Scalable | C9: 0.67 | D9: India's #1 vacation-ownership and leisure-hospitality brand (Club Mahindra), plus the European arm Holiday Club Resorts (HCRO, Finland). 6,228 keys across 125+ resorts as at FY26. | E9: #1 in Indian vacation ownership. Deferred revenue of c.Rs 5,700cr+ underpins forward visibility. | F9: FY26: c.900 gross keys added — a record — taking inventory to 6,228. New Keystone membership product. Premiumisation lifted AUR c.83% in Q4 FY26. A c.Rs 234cr Mauritius/HCRO impairment hit consolidated FY26 PAT. Acquiring Aditatva Estates (Chikmagalur) for Rs 37.5cr for a new resort. | G9: 10,000 rooms by FY30; '3x keys, 3x revenue, 4x PAT this decade'; aspiration to be India's #1 leisure hospitality player. | H9: Listed
A10: Mahindra Lifespace Developers (MAHLIFE IN) | B10: Scalable | C10: 0.51 | D10: Residential real estate (Mahindra Lifespaces) plus integrated cities and industrial clusters (IC&IC), including the Mahindra World City JVs. | E10: Mid-sized listed developer with a c.Rs 50,000cr GDV pipeline and a net-cash balance sheet (net debt/equity -0.27 at FY26). | F10: FY26: consolidated PAT up 386% to Rs 298.17cr from Rs 61.35cr. Residential pre-sales Rs 3,405cr (+21%); consolidated sales Rs 4,118cr (+25%); GDV additions Rs 18,060cr; total GDV pipeline c.Rs 50,000cr. Rights issue completed. Kandivali deal added Rs 5,600cr GDV; Bhandup (Rs 12,400cr GDV) and Mahalaxmi launches slated Q4 FY26/Q1 FY27. | G10: Rs 8,000-10,000cr annual pre-sales and 5x scale by FY30. FY27 pre-sales guidance Rs 4,500-5,000cr with Rs 10,000cr of launches. IC&IC Rs 400-500cr revenue and Rs 100-150cr PAT annually. Total-PAT ambition c.Rs 1,500cr. | H10: Listed
A11: Mahindra Accelo | B11: Emerging | C11: 1 | D11: Steel processing and service centres, high-end electrical-steel and EV components, and India's largest organised auto-recycling network (CERO; Mahindra MSTC Recycling — 7 RVSFs and 42 collection centres). | E11: #1 organised auto recycler in India; a top electrical-steel component supplier. Note it also acts as a captive steel service centre for M&M's UV business, so revenue tracks M&M volumes and steel prices. | F11: Oct-24: Zero Waste to Landfill certification. 2025/26: recognised as top ELV recycler. FY25 Integrated Annual Report cites a 5-year revenue CAGR of 30.85% and PAT CAGR of 49.21%, with net debt/equity at 0.10. | G11: c.25% share of organised recycling by FY28; $1bn valuation. | H11: ESTIMATE — confirm via AOC-1
A12: Mahindra Aerostructures | B12: Emerging | C12: 1 | D12: Tier-1 aerostructures supplier — metallic assemblies and machined components to Boeing, Airbus and Embraer. Direct Tier-1 to Boeing and Airbus since FY18. | E12: Small but strategically positioned. Named one of the top four most advanced manufacturing sites globally by Aero Excellence International — the only Indian firm on that list. Retains Airbus SQIP 'Accredited' status. | F12: Order book inflected hard: c.$1bn of orders secured in just over a year, against roughly $150m accumulated over the preceding fifteen years combined (Raksha Anirveda, Nov-25). Anchored by the Jun-25 Aernnova contract of c.$300m (Rs 2,585cr) for Airbus/Embraer work. Novavayu Aerospace Ltd set up for aircraft and defence manufacturing. | G12: c.12x revenue growth this decade; top-10 global aerostructures supplier; $1bn valuation. | H12: 100% indirect via Mahindra Aerospace
A13: Classic Legends (Jawa / Yezdi / BSA) | B13: Emerging | C13: 0.6 | D13: Mass-premium motorcycles under the Jawa, Yezdi and BSA brands. Founded 2015, operations from 2018; co-founders Anupam Thareja and Boman Irani, Mahindra-backed. | E13: c.5% of India's mass-premium motorcycle segment, against Royal Enfield at 80%+ and over 1.2m units a year. Retail units: FY23 44,000, FY24 36,680, FY25 32,482, FY26 45,409 (+40%). | F13: FY26 was the first profitable year in the company's history, on 45,409 retails (+40% YoY), with H2 FY26 up 100% YoY. The manufacturing facility was acquired from Mahindra at no cost, so there is no depreciation or interest burden. Rs 350cr invested in product development across 12 products. Aug-25: c.5,000 units held up at US Customs amid tariff disruption. | G13: 2028 IPO; global expansion — BSA into Western markets, Jawa into Eastern Europe and South America, Yezdi in India; dealer network from c.350 to 500+; $1bn valuation aspiration. | H13: ESTIMATE — confirm via AOC-1
A14: Car&Bike / Mahindra First Choice Wheels | B14: Emerging | C14: 0.545 | D14: India's largest used-car enterprise-services platform — Car&Bike retail and franchise, YMS, AutoInspekt (inspections) and eDiig (auctions). Distinct from Mahindra First Choice Services (workshops), which was sold to TVS Automobile Solutions in Feb-21. | E14: Largest enterprise-services platform in the organised used-car market, competing with Cars24, Spinny and CarTrade. Prior valuation c.$265m (2018). | F14: FY25 revenue fell c.59% to Rs 313cr, which most likely reflects a shift from principal sales to a platform/franchise-fee model rather than a collapse in activity — this needs verification before use. Book net worth fell c.34.65% in FY24. | G14: $1bn valuation (emerging gem). | H14: M&M/parent c.54.5%; funds c.32%

Sheet Revenue
A1: Growth Gems — revenue
A2: Black = reported actual (source named). Blue = our estimate. Grey n/l = not disclosed anywhere located.
A4: Gem (Rs cr) | B4: FY21A | C4: FY22A | D4: FY23A | E4: FY24A | F4: FY25A | G4: FY26A | H4: FY27E | I4: FY28E | J4: FY29E | K4: FY30E | L4: CAGR FY26-30E | M4: Source / basis
A5: Mahindra Last Mile Mobility | B5: n/l | C5: n/l | D5: n/l | E5: 2367 | F5: 3880 | G5: 4798 | H5: 6000 | I5: 7500 | J5: 9200 | K5: 11000 | L5: =(K5/G5)^(1/4)-1 -> 0.23050423 | M5: Mint/TradingView (2026), Tracxn. Entity incorporated 29-May-23; commercial ops from Sep-23, so no FY21-FY23 standalone.
A6: Mahindra Trucks & Buses (MTBD + SML) | B6: n/l | C6: n/l | D6: n/l | E6: 2196 | F6: n/l | G6: 5827 | H6: 7000 | I6: 8500 | J6: 10300 | K6: 12100 | L6: =(K6/G6)^(1/4)-1 -> 0.20042516 | M6: FY26 = MTBD Rs 2,989cr + SML Rs 2,838cr (Reuters/Zerodha, Jul-26). FY24 = SML only (M&M release, 26-Apr-25). MTBD sat inside M&M standalone historically.
A7: Mahindra Susten | B7: n/l | C7: n/l | D7: n/l | E7: 195 | F7: 509 | G7: n/l | H7: 1200 | I7: 2000 | J7: 3000 | K7: 4200 | L7: n/l | M7: FY24 Board's Report (mahindrasusten.com); FY25 Tracxn. FY26 total income not located — mine AOC-1.
A8: Mahindra Logistics (MAHLOG IN) | B8: 3264 | C8: n/l | D8: n/l | E8: 5506 | F8: 6105 | G8: 6999 | H8: 8050 | I8: 9250 | J8: 10600 | K8: 12100 | L8: =(K8/G8)^(1/4)-1 -> 0.14666708 | M8: MLL press releases Q4 FY25 (21-Apr-25) and Q4 FY26 (23-Apr-26). FY22/FY23 not located in sources used.
A9: Mahindra Holidays / Club Mahindra (MHRIL IN) | B9: n/l | C9: n/l | D9: n/l | E9: 2700 | F9: 2910 | G9: 3116 | H9: 3450 | I9: 3850 | J9: 4300 | K9: 4800 | L9: =(K9/G9)^(1/4)-1 -> 0.11406607 | M9: MHRIL results/press releases; ICICIdirect; tradebrains. FY24/FY25 are approximations from secondary sources — verify against the audited AR.
A10: Mahindra Lifespace Developers (MAHLIFE IN) | B10: n/l | C10: n/l | D10: n/l | E10: 279 | F10: 464 | G10: 4118 | H10: 4600 | I10: 5800 | J10: 7200 | K10: 8800 | L10: =(K10/G10)^(1/4)-1 -> 0.20906342 | M10: MLDL results; Business Standard; Whalesbook. WARNING: the FY26 Rs 4,118cr is reported as 'consolidated sales' (sales value) — this is NOT directly comparable to the FY24/FY25 Ind-AS revenue line. See Data Quality Log.
A11: Mahindra Accelo | B11: n/l | C11: n/l | D11: 4188 | E11: 4600 | F11: n/l | G11: n/l | H11: 5600 | I11: 6400 | J11: 7300 | K11: 8300 | L11: n/l | M11: FY23 entity data; FY24 'highest ever' c.Rs 4,600cr per M&M FY24 Integrated AR. FY25/FY26 not located — mine AOC-1. Scope (consolidated vs standalone) unconfirmed.
A12: Mahindra Aerostructures | B12: n/l | C12: n/l | D12: n/l | E12: 235 | F12: 258 | G12: n/l | H12: 340 | I12: 470 | J12: 650 | K12: 900 | L12: n/l | M12: CARE Ratings press release, 12-Jun-25 (FY25 revenue Rs 258cr, +10% YoY, implying FY24 c.Rs 235cr). FY26 not located — mine AOC-1.
A13: Classic Legends (Jawa / Yezdi / BSA) | B13: n/l | C13: n/l | D13: n/l | E13: n/l | F13: 600 | G13: 900 | H13: 1250 | I13: 1700 | J13: 2100 | K13: 2550 | L13: =(K13/G13)^(1/4)-1 -> 0.29740157 | M13: ESTIMATE throughout. Tracxn gives only a Rs 500-1,000cr band for FY25. FY25/FY26 derived from retail units x c.Rs 1.8-2.0L ASP. Treat as indicative only.
A14: Car&Bike / Mahindra First Choice Wheels | B14: n/l | C14: n/l | D14: n/l | E14: 500 | F14: 313 | G14: n/l | H14: 380 | I14: 470 | J14: 580 | K14: 720 | L14: n/l | M14: Tracxn (FY24 >Rs 500cr; FY25 Rs 313cr). The c.59% FY25 drop likely reflects a revenue-recognition shift to platform/franchise fees, not a business collapse — verify before use.
A15: Total (populated cells only) | B15: =SUM(B5:B14) -> 3264 | C15: =SUM(C5:C14) -> 0 | D15: =SUM(D5:D14) -> 4188 | E15: =SUM(E5:E14) -> 18578 | F15: =SUM(F5:F14) -> 15039 | G15: =SUM(G5:G14) -> 25758 | H15: =SUM(H5:H14) -> 37870 | I15: =SUM(I5:I14) -> 45940 | ... K15: =SUM(K5:K14) -> 65470 | M15: NOT a like-for-like portfolio total — historic columns are incomplete because several gems are not disclosed. Use for the FY27E-FY30E columns only.
A17: FORECAST BASIS: LMM c.23% CAGR (management's 'c.2x industry' and 1m-EVs-by-2031 framing). T&B ramped toward the stated Rs 15,000cr FY31 ambition, with FY30E deliberately below it on a back-ended synergy ramp. Susten tied to the 1.5-to-7 GW roadmap (revenue is lumpy on EPC-vs-IPP mix). Logistics c.15% CAGR. Club Mahindra tied to the 10,000-room roadmap plus premiumisation. Lifespaces anchored to explicit FY27 pre-sales guidance and the FY30 Rs 10,000cr ambition. Accelo c.14%. Aerostructures c.25-30% off the c.$1bn order book. Classic Legends off unit trajectory. Car&Bike low-confidence given the model shift.

Sheet EBITDA
A1: Growth Gems — EBITDA
A2: Sparsely disclosed for the unlisted gems. Where absent, we have NOT back-solved a number.
A4: Gem (Rs cr) | B4: FY21A | C4: FY22A | D4: FY23A | E4: FY24A | F4: FY25A | G4: FY26A | H4: FY27E | I4: FY28E | J4: FY29E | K4: FY30E | L4: CAGR FY26-30E | M4: Source / basis
A5: Mahindra Last Mile Mobility | B5: n/l | C5: n/l | D5: n/l | E5: n/l | F5: n/l | G5: n/l | H5: 480 | I5: 675 | J5: 920 | K5: 1100 | L5: n/l | M5: Not disclosed. FY26 margin c.7-8% is an estimate.
A6: Mahindra Trucks & Buses (MTBD + SML) | B6: n/l | C6: n/l | D6: n/l | E6: 179 | F6: n/l | G6: n/l | H6: 490 | I6: 680 | J6: 900 | K6: 1090 | L6: n/l | M6: FY24 = SML only (Rs 179cr, M&M acquisition release 26-Apr-25). Combined EBITDA not disclosed.
A7: Mahindra Susten | B7: n/l | C7: n/l | D7: n/l | E7: n/l | F7: n/l | G7: n/l | H7: 300 | I7: 540 | J7: 840 | K7: 1220 | L7: n/l | M7: Not disclosed.
A8: Mahindra Logistics (MAHLOG IN) | B8: 190 | C8: n/l | D8: n/l | E8: 229 | F8: 284 | G8: 376 | H8: 470 | I8: 590 | J8: 730 | K8: 880 | L8: =(K8/G8)^(1/4)-1 -> 0.23686901 | M8: MLL press releases. FY21 approximate.
A9: Mahindra Holidays / Club Mahindra (MHRIL IN) | B9: n/l | C9: n/l | D9: n/l | E9: 629 | F9: 708 | G9: n/l | H9: 820 | I9: 960 | J9: 1120 | K9: 1300 | L9: n/l | M9: FY24 Rs 628.9cr, FY25 Rs 707.8cr. FY26 consolidated EBITDA not located; FY26 standalone EBITDA was Rs 592.67cr.
A10: Mahindra Lifespace Developers (MAHLIFE IN) | B10: n/l | C10: n/l | D10: n/l | E10: n/l | F10: n/l | G10: n/l | H10: 560 | I10: 780 | J10: 1010 | K10: 1320 | L10: n/l | M10: Not disclosed on a comparable basis; real-estate EBITDA is distorted by JV equity accounting.
A11: Mahindra Accelo | B11: n/l | C11: n/l | D11: n/l | E11: n/l | F11: 333 | G11: n/l | H11: 420 | I11: 500 | J11: 590 | K11: 690 | L11: n/l | M11: FY25 Rs 332.77cr per the Mahindra Accelo FY25 Integrated Annual Report.
A12: Mahindra Aerostructures | B12: n/l | C12: n/l | D12: n/l | E12: 19 | F12: 22 | G12: n/l | H12: 31 | I12: 47 | J12: 72 | K12: 108 | L12: n/l | M12: Derived from CARE's 8.62% FY25 operating margin on Rs 258cr revenue; FY24 derived on c.8%.
A13: Classic Legends (Jawa / Yezdi / BSA) | B13: n/l | C13: n/l | D13: n/l | E13: n/l | F13: n/l | G13: n/l | H13: 100 | I13: 160 | J13: 215 | K13: 280 | L13: n/l | M13: Not disclosed.
A14: Car&Bike / Mahindra First Choice Wheels | B14: n/l | C14: n/l | D14: n/l | E14: n/l | F14: n/l | G14: n/l | H14: -15 | I14: 10 | J14: 40 | K14: 80 | L14: n/l | M14: Not disclosed.
A15: Total (populated cells only) | B15: =SUM(B5:B14) -> 190 | C15: =SUM(C5:C14) -> 0 | D15: =SUM(D5:D14) -> 0 | E15: =SUM(E5:E14) -> 1056 | F15: =SUM(F5:F14) -> 1347 | G15: =SUM(G5:G14) -> 376 | H15: =SUM(H5:H14) -> 3656 | I15: =SUM(I5:I14) -> 4942 | ... K15: =SUM(K5:K14) -> 8068 | M15: NOT a like-for-like portfolio total — historic columns are incomplete because several gems are not disclosed. Use for the FY27E-FY30E columns only.
A18: EBITDA MARGIN (%) — calculated; blank where either input is not disclosed
A19: Gem | B19: FY21A | C19: FY22A | D19: FY23A | E19: FY24A | F19: FY25A | G19: FY26A | H19: FY27E | I19: FY28E | J19: FY29E | K19: FY30E | M19: Comment
A20: Mahindra Last Mile Mobility | B20: =IF(OR(NOT(ISNUMBER(B5)),NOT(ISNUMBER(Revenue!B5))),"",B5/Revenue!B5) | C20: =IF(OR(NOT(ISNUMBER(C5)),NOT(ISNUMBER(Revenue!C5))),"",C5/Revenue!C5) | D20: =IF(OR(NOT(ISNUMBER(D5)),NOT(ISNUMBER(Revenue!D5))),"",D5/Revenue!D5) | E20: =IF(OR(NOT(ISNUMBER(E5)),NOT(ISNUMBER(Revenue!E5))),"",E5/Revenue!E5) | F20: =IF(OR(NOT(ISNUMBER(F5)),NOT(ISNUMBER(Revenue!F5))),"",F5/Revenue!F5) | G20: =IF(OR(NOT(ISNUMBER(G5)),NOT(ISNUMBER(Revenue!G5))),"",G5/Revenue!G5) | H20: =IF(OR(NOT(ISNUMBER(H5)),NOT(ISNUMBER(Revenue!H5))),"",H5/Revenue!H5) -> 0.08 | I20: =IF(OR(NOT(ISNUMBER(I5)),NOT(ISNUMBER(Revenue!I5))),"",I5/Revenue!I5) -> 0.09 | ... K20: =IF(OR(NOT(ISNUMBER(K5)),NOT(ISNUMBER(Revenue!K5))),"",K5/Revenue!K5) -> 0.1
A21: Mahindra Trucks & Buses (MTBD + SML) | B21: =IF(OR(NOT(ISNUMBER(B6)),NOT(ISNUMBER(Revenue!B6))),"",B6/Revenue!B6) | C21: =IF(OR(NOT(ISNUMBER(C6)),NOT(ISNUMBER(Revenue!C6))),"",C6/Revenue!C6) | D21: =IF(OR(NOT(ISNUMBER(D6)),NOT(ISNUMBER(Revenue!D6))),"",D6/Revenue!D6) | E21: =IF(OR(NOT(ISNUMBER(E6)),NOT(ISNUMBER(Revenue!E6))),"",E6/Revenue!E6) -> 0.08151184 | F21: =IF(OR(NOT(ISNUMBER(F6)),NOT(ISNUMBER(Revenue!F6))),"",F6/Revenue!F6) | G21: =IF(OR(NOT(ISNUMBER(G6)),NOT(ISNUMBER(Revenue!G6))),"",G6/Revenue!G6) | H21: =IF(OR(NOT(ISNUMBER(H6)),NOT(ISNUMBER(Revenue!H6))),"",H6/Revenue!H6) -> 0.07 | I21: =IF(OR(NOT(ISNUMBER(I6)),NOT(ISNUMBER(Revenue!I6))),"",I6/Revenue!I6) -> 0.08 | ... K21: =IF(OR(NOT(ISNUMBER(K6)),NOT(ISNUMBER(Revenue!K6))),"",K6/Revenue!K6) -> 0.090082645
A22: Mahindra Susten | B22: =IF(OR(NOT(ISNUMBER(B7)),NOT(ISNUMBER(Revenue!B7))),"",B7/Revenue!B7) | C22: =IF(OR(NOT(ISNUMBER(C7)),NOT(ISNUMBER(Revenue!C7))),"",C7/Revenue!C7) | D22: =IF(OR(NOT(ISNUMBER(D7)),NOT(ISNUMBER(Revenue!D7))),"",D7/Revenue!D7) | E22: =IF(OR(NOT(ISNUMBER(E7)),NOT(ISNUMBER(Revenue!E7))),"",E7/Revenue!E7) | F22: =IF(OR(NOT(ISNUMBER(F7)),NOT(ISNUMBER(Revenue!F7))),"",F7/Revenue!F7) | G22: =IF(OR(NOT(ISNUMBER(G7)),NOT(ISNUMBER(Revenue!G7))),"",G7/Revenue!G7) | H22: =IF(OR(NOT(ISNUMBER(H7)),NOT(ISNUMBER(Revenue!H7))),"",H7/Revenue!H7) -> 0.25 | I22: =IF(OR(NOT(ISNUMBER(I7)),NOT(ISNUMBER(Revenue!I7))),"",I7/Revenue!I7) -> 0.27 | ... K22: =IF(OR(NOT(ISNUMBER(K7)),NOT(ISNUMBER(Revenue!K7))),"",K7/Revenue!K7) -> 0.29047619
A23: Mahindra Logistics (MAHLOG IN) | B23: =IF(OR(NOT(ISNUMBER(B8)),NOT(ISNUMBER(Revenue!B8))),"",B8/Revenue!B8) -> 0.058210784 | C23: =IF(OR(NOT(ISNUMBER(C8)),NOT(ISNUMBER(Revenue!C8))),"",C8/Revenue!C8) | D23: =IF(OR(NOT(ISNUMBER(D8)),NOT(ISNUMBER(Revenue!D8))),"",D8/Revenue!D8) | E23: =IF(OR(NOT(ISNUMBER(E8)),NOT(ISNUMBER(Revenue!E8))),"",E8/Revenue!E8) -> 0.041590992 | F23: =IF(OR(NOT(ISNUMBER(F8)),NOT(ISNUMBER(Revenue!F8))),"",F8/Revenue!F8) -> 0.046519247 | G23: =IF(OR(NOT(ISNUMBER(G8)),NOT(ISNUMBER(Revenue!G8))),"",G8/Revenue!G8) -> 0.05372196 | H23: =IF(OR(NOT(ISNUMBER(H8)),NOT(ISNUMBER(Revenue!H8))),"",H8/Revenue!H8) -> 0.058385093 | I23: =IF(OR(NOT(ISNUMBER(I8)),NOT(ISNUMBER(Revenue!I8))),"",I8/Revenue!I8) -> 0.063783784 | ... K23: =IF(OR(NOT(ISNUMBER(K8)),NOT(ISNUMBER(Revenue!K8))),"",K8/Revenue!K8) -> 0.072727273
A24: Mahindra Holidays / Club Mahindra (MHRIL IN) | B24: =IF(OR(NOT(ISNUMBER(B9)),NOT(ISNUMBER(Revenue!B9))),"",B9/Revenue!B9) | C24: =IF(OR(NOT(ISNUMBER(C9)),NOT(ISNUMBER(Revenue!C9))),"",C9/Revenue!C9) | D24: =IF(OR(NOT(ISNUMBER(D9)),NOT(ISNUMBER(Revenue!D9))),"",D9/Revenue!D9) | E24: =IF(OR(NOT(ISNUMBER(E9)),NOT(ISNUMBER(Revenue!E9))),"",E9/Revenue!E9) -> 0.23296296 | F24: =IF(OR(NOT(ISNUMBER(F9)),NOT(ISNUMBER(Revenue!F9))),"",F9/Revenue!F9) -> 0.24329897 | G24: =IF(OR(NOT(ISNUMBER(G9)),NOT(ISNUMBER(Revenue!G9))),"",G9/Revenue!G9) | H24: =IF(OR(NOT(ISNUMBER(H9)),NOT(ISNUMBER(Revenue!H9))),"",H9/Revenue!H9) -> 0.23768116 | I24: =IF(OR(NOT(ISNUMBER(I9)),NOT(ISNUMBER(Revenue!I9))),"",I9/Revenue!I9) -> 0.24935065 | ... K24: =IF(OR(NOT(ISNUMBER(K9)),NOT(ISNUMBER(Revenue!K9))),"",K9/Revenue!K9) -> 0.27083333
A25: Mahindra Lifespace Developers (MAHLIFE IN) | B25: =IF(OR(NOT(ISNUMBER(B10)),NOT(ISNUMBER(Revenue!B10))),"",B10/Revenue!B10) | C25: =IF(OR(NOT(ISNUMBER(C10)),NOT(ISNUMBER(Revenue!C10))),"",C10/Revenue!C10) | D25: =IF(OR(NOT(ISNUMBER(D10)),NOT(ISNUMBER(Revenue!D10))),"",D10/Revenue!D10) | E25: =IF(OR(NOT(ISNUMBER(E10)),NOT(ISNUMBER(Revenue!E10))),"",E10/Revenue!E10) | F25: =IF(OR(NOT(ISNUMBER(F10)),NOT(ISNUMBER(Revenue!F10))),"",F10/Revenue!F10) | G25: =IF(OR(NOT(ISNUMBER(G10)),NOT(ISNUMBER(Revenue!G10))),"",G10/Revenue!G10) | H25: =IF(OR(NOT(ISNUMBER(H10)),NOT(ISNUMBER(Revenue!H10))),"",H10/Revenue!H10) -> 0.12173913 | I25: =IF(OR(NOT(ISNUMBER(I10)),NOT(ISNUMBER(Revenue!I10))),"",I10/Revenue!I10) -> 0.13448276 | ... K25: =IF(OR(NOT(ISNUMBER(K10)),NOT(ISNUMBER(Revenue!K10))),"",K10/Revenue!K10) -> 0.15
A26: Mahindra Accelo | B26: =IF(OR(NOT(ISNUMBER(B11)),NOT(ISNUMBER(Revenue!B11))),"",B11/Revenue!B11) | C26: =IF(OR(NOT(ISNUMBER(C11)),NOT(ISNUMBER(Revenue!C11))),"",C11/Revenue!C11) | D26: =IF(OR(NOT(ISNUMBER(D11)),NOT(ISNUMBER(Revenue!D11))),"",D11/Revenue!D11) | E26: =IF(OR(NOT(ISNUMBER(E11)),NOT(ISNUMBER(Revenue!E11))),"",E11/Revenue!E11) | F26: =IF(OR(NOT(ISNUMBER(F11)),NOT(ISNUMBER(Revenue!F11))),"",F11/Revenue!F11) | G26: =IF(OR(NOT(ISNUMBER(G11)),NOT(ISNUMBER(Revenue!G11))),"",G11/Revenue!G11) | H26: =IF(OR(NOT(ISNUMBER(H11)),NOT(ISNUMBER(Revenue!H11))),"",H11/Revenue!H11) -> 0.075 | I26: =IF(OR(NOT(ISNUMBER(I11)),NOT(ISNUMBER(Revenue!I11))),"",I11/Revenue!I11) -> 0.078125 | ... K26: =IF(OR(NOT(ISNUMBER(K11)),NOT(ISNUMBER(Revenue!K11))),"",K11/Revenue!K11) -> 0.08313253
A27: Mahindra Aerostructures | B27: =IF(OR(NOT(ISNUMBER(B12)),NOT(ISNUMBER(Revenue!B12))),"",B12/Revenue!B12) | C27: =IF(OR(NOT(ISNUMBER(C12)),NOT(ISNUMBER(Revenue!C12))),"",C12/Revenue!C12) | D27: =IF(OR(NOT(ISNUMBER(D12)),NOT(ISNUMBER(Revenue!D12))),"",D12/Revenue!D12) | E27: =IF(OR(NOT(ISNUMBER(E12)),NOT(ISNUMBER(Revenue!E12))),"",E12/Revenue!E12) -> 0.080851064 | F27: =IF(OR(NOT(ISNUMBER(F12)),NOT(ISNUMBER(Revenue!F12))),"",F12/Revenue!F12) -> 0.085271318 | G27: =IF(OR(NOT(ISNUMBER(G12)),NOT(ISNUMBER(Revenue!G12))),"",G12/Revenue!G12) | H27: =IF(OR(NOT(ISNUMBER(H12)),NOT(ISNUMBER(Revenue!H12))),"",H12/Revenue!H12) -> 0.091176471 | I27: =IF(OR(NOT(ISNUMBER(I12)),NOT(ISNUMBER(Revenue!I12))),"",I12/Revenue!I12) -> 0.1 | ... K27: =IF(OR(NOT(ISNUMBER(K12)),NOT(ISNUMBER(Revenue!K12))),"",K12/Revenue!K12) -> 0.12
A28: Classic Legends (Jawa / Yezdi / BSA) | B28: =IF(OR(NOT(ISNUMBER(B13)),NOT(ISNUMBER(Revenue!B13))),"",B13/Revenue!B13) | C28: =IF(OR(NOT(ISNUMBER(C13)),NOT(ISNUMBER(Revenue!C13))),"",C13/Revenue!C13) | D28: =IF(OR(NOT(ISNUMBER(D13)),NOT(ISNUMBER(Revenue!D13))),"",D13/Revenue!D13) | E28: =IF(OR(NOT(ISNUMBER(E13)),NOT(ISNUMBER(Revenue!E13))),"",E13/Revenue!E13) | F28: =IF(OR(NOT(ISNUMBER(F13)),NOT(ISNUMBER(Revenue!F13))),"",F13/Revenue!F13) | G28: =IF(OR(NOT(ISNUMBER(G13)),NOT(ISNUMBER(Revenue!G13))),"",G13/Revenue!G13) | H28: =IF(OR(NOT(ISNUMBER(H13)),NOT(ISNUMBER(Revenue!H13))),"",H13/Revenue!H13) -> 0.08 | I28: =IF(OR(NOT(ISNUMBER(I13)),NOT(ISNUMBER(Revenue!I13))),"",I13/Revenue!I13) -> 0.094117647 | ... K28: =IF(OR(NOT(ISNUMBER(K13)),NOT(ISNUMBER(Revenue!K13))),"",K13/Revenue!K13) -> 0.10980392
A29: Car&Bike / Mahindra First Choice Wheels | B29: =IF(OR(NOT(ISNUMBER(B14)),NOT(ISNUMBER(Revenue!B14))),"",B14/Revenue!B14) | C29: =IF(OR(NOT(ISNUMBER(C14)),NOT(ISNUMBER(Revenue!C14))),"",C14/Revenue!C14) | D29: =IF(OR(NOT(ISNUMBER(D14)),NOT(ISNUMBER(Revenue!D14))),"",D14/Revenue!D14) | E29: =IF(OR(NOT(ISNUMBER(E14)),NOT(ISNUMBER(Revenue!E14))),"",E14/Revenue!E14) | F29: =IF(OR(NOT(ISNUMBER(F14)),NOT(ISNUMBER(Revenue!F14))),"",F14/Revenue!F14) | G29: =IF(OR(NOT(ISNUMBER(G14)),NOT(ISNUMBER(Revenue!G14))),"",G14/Revenue!G14) | H29: =IF(OR(NOT(ISNUMBER(H14)),NOT(ISNUMBER(Revenue!H14))),"",H14/Revenue!H14) -> -0.039473684 | I29: =IF(OR(NOT(ISNUMBER(I14)),NOT(ISNUMBER(Revenue!I14))),"",I14/Revenue!I14) -> 0.021276596 | ... K29: =IF(OR(NOT(ISNUMBER(K14)),NOT(ISNUMBER(Revenue!K14))),"",K14/Revenue!K14) -> 0.11111111
A31: Margins are computed against the Revenue tab. A blank means at least one of revenue or EBITDA is not disclosed for that year — it does not mean zero.

Sheet PAT
A1: Growth Gems — profit after tax
A2: Note the one-offs: Susten FY24 and Club Mahindra FY26 are both distorted. Read the Source column.
A4: Gem (Rs cr) | B4: FY21A | C4: FY22A | D4: FY23A | E4: FY24A | F4: FY25A | G4: FY26A | H4: FY27E | I4: FY28E | J4: FY29E | K4: FY30E | L4: CAGR FY26-30E | M4: Source / basis
A5: Mahindra Last Mile Mobility | B5: n/l | C5: n/l | D5: n/l | E5: 26 | F5: n/l | G5: 185 | H5: 260 | I5: 360 | J5: 480 | K5: 600 | L5: =(K5/G5)^(1/4)-1 -> 0.34197641 | M5: FY24 Rs 26cr, FY26 Rs 185cr (Mint/TradingView 2026, Tracxn). FY25 not located.
A6: Mahindra Trucks & Buses (MTBD + SML) | B6: n/l | C6: n/l | D6: n/l | E6: n/l | F6: n/l | G6: n/l | H6: 180 | I6: 300 | J6: 440 | K6: 590 | L6: n/l | M6: Not disclosed on a combined basis. SML is separately listed — pull SML's own P&L for the listed portion.
A7: Mahindra Susten | B7: n/l | C7: n/l | D7: n/l | E7: 852 | F7: n/l | G7: n/l | H7: 150 | I7: 260 | J7: 400 | K7: 560 | L7: n/l | M7: FY24 Rs 852cr INCLUDES large exceptional gains from the InvIT monetisation — NOT a clean operating number. Do not use as a run-rate.
A8: Mahindra Logistics (MAHLOG IN) | B8: 47 | C8: n/l | D8: n/l | E8: 8 | F8: -36 | G8: 2 | H8: 60 | I8: 130 | J8: 210 | K8: 300 | L8: =(K8/G8)^(1/4)-1 -> 2.4996355 | M8: MLL press releases. FY26 reported PAT Rs 2.3cr (operational Rs 8.2cr); FY25 was an operational loss. FY21 approximate.
A9: Mahindra Holidays / Club Mahindra (MHRIL IN) | B9: n/l | C9: n/l | D9: n/l | E9: 116 | F9: 126 | G9: 67 | H9: 150 | I9: 200 | J9: 260 | K9: 330 | L9: =(K9/G9)^(1/4)-1 -> 0.48973762 | M9: FY26 consolidated PAT Rs 67cr is depressed by a c.Rs 234cr HCRO/Mauritius impairment; ex-one-off c.Rs 136.3cr.
A10: Mahindra Lifespace Developers (MAHLIFE IN) | B10: n/l | C10: n/l | D10: n/l | E10: 98 | F10: 61 | G10: 298 | H10: 420 | I10: 620 | J10: 850 | K10: 1100 | L10: =(K10/G10)^(1/4)-1 -> 0.38609854 | M10: FY26 consolidated PAT Rs 298.17cr vs Rs 61.35cr in FY25 (+386%). MLDL results / BRSR filed 30-Jun-26.
A11: Mahindra Accelo | B11: n/l | C11: 181 | D11: 147 | E11: n/l | F11: n/l | G11: n/l | H11: 220 | I11: 280 | J11: 350 | K11: 430 | L11: n/l | M11: FY22 Rs 180.5cr, FY23 Rs 146.6cr (-19% YoY). FY24-FY26 not located — mine AOC-1.
A12: Mahindra Aerostructures | B12: n/l | C12: n/l | D12: n/l | E12: 1 | F12: -8 | G12: n/l | H12: 5 | I12: 20 | J12: 45 | K12: 80 | L12: n/l | M12: FY25 net loss c.Rs 7.8cr per CARE Ratings (12-Jun-25). FY24 approximate.
A13: Classic Legends (Jawa / Yezdi / BSA) | B13: n/l | C13: n/l | D13: n/l | E13: n/l | F13: n/l | G13: n/l | H13: 40 | I13: 90 | J13: 150 | K13: 220 | L13: n/l | M13: Loss-making every year from 2018 until FY26, which was the first profitable year (co-founder Anupam Thareja to Autocar Professional). Quantum not disclosed.
A14: Car&Bike / Mahindra First Choice Wheels | B14: n/l | C14: n/l | D14: n/l | E14: n/l | F14: n/l | G14: n/l | H14: -20 | I14: 5 | J14: 30 | K14: 60 | L14: n/l | M14: Not disclosed. Book net worth fell c.34.65% in FY24.
A15: Total (populated cells only) | B15: =SUM(B5:B14) -> 47 | C15: =SUM(C5:C14) -> 181 | D15: =SUM(D5:D14) -> 147 | E15: =SUM(E5:E14) -> 1101 | F15: =SUM(F5:F14) -> 143 | G15: =SUM(G5:G14) -> 552 | H15: =SUM(H5:H14) -> 1465 | I15: =SUM(I5:I14) -> 2265 | ... K15: =SUM(K5:K14) -> 4270 | M15: NOT a like-for-like portfolio total — historic columns are incomplete because several gems are not disclosed. Use for the FY27E-FY30E columns only.
A18: PAT MARGIN (%) — calculated; blank where either input is not disclosed
A19: Gem | B19: FY21A | C19: FY22A | D19: FY23A | E19: FY24A | F19: FY25A | G19: FY26A | H19: FY27E | I19: FY28E | J19: FY29E | K19: FY30E | M19: Comment
A20: Mahindra Last Mile Mobility | B20: =IF(OR(NOT(ISNUMBER(B5)),NOT(ISNUMBER(Revenue!B5))),"",B5/Revenue!B5) | C20: =IF(OR(NOT(ISNUMBER(C5)),NOT(ISNUMBER(Revenue!C5))),"",C5/Revenue!C5) | D20: =IF(OR(NOT(ISNUMBER(D5)),NOT(ISNUMBER(Revenue!D5))),"",D5/Revenue!D5) | E20: =IF(OR(NOT(ISNUMBER(E5)),NOT(ISNUMBER(Revenue!E5))),"",E5/Revenue!E5) -> 0.010984368 | F20: =IF(OR(NOT(ISNUMBER(F5)),NOT(ISNUMBER(Revenue!F5))),"",F5/Revenue!F5) | G20: =IF(OR(NOT(ISNUMBER(G5)),NOT(ISNUMBER(Revenue!G5))),"",G5/Revenue!G5) -> 0.038557732 | H20: =IF(OR(NOT(ISNUMBER(H5)),NOT(ISNUMBER(Revenue!H5))),"",H5/Revenue!H5) -> 0.043333333 | I20: =IF(OR(NOT(ISNUMBER(I5)),NOT(ISNUMBER(Revenue!I5))),"",I5/Revenue!I5) -> 0.048 | ... K20: =IF(OR(NOT(ISNUMBER(K5)),NOT(ISNUMBER(Revenue!K5))),"",K5/Revenue!K5) -> 0.054545455
A21: Mahindra Trucks & Buses (MTBD + SML) | B21: =IF(OR(NOT(ISNUMBER(B6)),NOT(ISNUMBER(Revenue!B6))),"",B6/Revenue!B6) | C21: =IF(OR(NOT(ISNUMBER(C6)),NOT(ISNUMBER(Revenue!C6))),"",C6/Revenue!C6) | D21: =IF(OR(NOT(ISNUMBER(D6)),NOT(ISNUMBER(Revenue!D6))),"",D6/Revenue!D6) | E21: =IF(OR(NOT(ISNUMBER(E6)),NOT(ISNUMBER(Revenue!E6))),"",E6/Revenue!E6) | F21: =IF(OR(NOT(ISNUMBER(F6)),NOT(ISNUMBER(Revenue!F6))),"",F6/Revenue!F6) | G21: =IF(OR(NOT(ISNUMBER(G6)),NOT(ISNUMBER(Revenue!G6))),"",G6/Revenue!G6) | H21: =IF(OR(NOT(ISNUMBER(H6)),NOT(ISNUMBER(Revenue!H6))),"",H6/Revenue!H6) -> 0.025714286 | I21: =IF(OR(NOT(ISNUMBER(I6)),NOT(ISNUMBER(Revenue!I6))),"",I6/Revenue!I6) -> 0.035294118 | ... K21: =IF(OR(NOT(ISNUMBER(K6)),NOT(ISNUMBER(Revenue!K6))),"",K6/Revenue!K6) -> 0.048760331
A22: Mahindra Susten | B22: =IF(OR(NOT(ISNUMBER(B7)),NOT(ISNUMBER(Revenue!B7))),"",B7/Revenue!B7) | C22: =IF(OR(NOT(ISNUMBER(C7)),NOT(ISNUMBER(Revenue!C7))),"",C7/Revenue!C7) | D22: =IF(OR(NOT(ISNUMBER(D7)),NOT(ISNUMBER(Revenue!D7))),"",D7/Revenue!D7) | E22: =IF(OR(NOT(ISNUMBER(E7)),NOT(ISNUMBER(Revenue!E7))),"",E7/Revenue!E7) -> 4.3692308 | F22: =IF(OR(NOT(ISNUMBER(F7)),NOT(ISNUMBER(Revenue!F7))),"",F7/Revenue!F7) | G22: =IF(OR(NOT(ISNUMBER(G7)),NOT(ISNUMBER(Revenue!G7))),"",G7/Revenue!G7) | H22: =IF(OR(NOT(ISNUMBER(H7)),NOT(ISNUMBER(Revenue!H7))),"",H7/Revenue!H7) -> 0.125 | I22: =IF(OR(NOT(ISNUMBER(I7)),NOT(ISNUMBER(Revenue!I7))),"",I7/Revenue!I7) -> 0.13 | ... K22: =IF(OR(NOT(ISNUMBER(K7)),NOT(ISNUMBER(Revenue!K7))),"",K7/Revenue!K7) -> 0.13333333
A23: Mahindra Logistics (MAHLOG IN) | B23: =IF(OR(NOT(ISNUMBER(B8)),NOT(ISNUMBER(Revenue!B8))),"",B8/Revenue!B8) -> 0.01439951 | C23: =IF(OR(NOT(ISNUMBER(C8)),NOT(ISNUMBER(Revenue!C8))),"",C8/Revenue!C8) | D23: =IF(OR(NOT(ISNUMBER(D8)),NOT(ISNUMBER(Revenue!D8))),"",D8/Revenue!D8) | E23: =IF(OR(NOT(ISNUMBER(E8)),NOT(ISNUMBER(Revenue!E8))),"",E8/Revenue!E8) -> 0.0014529604 | F23: =IF(OR(NOT(ISNUMBER(F8)),NOT(ISNUMBER(Revenue!F8))),"",F8/Revenue!F8) -> -0.0058968059 | G23: =IF(OR(NOT(ISNUMBER(G8)),NOT(ISNUMBER(Revenue!G8))),"",G8/Revenue!G8) -> 0.00028575511 | H23: =IF(OR(NOT(ISNUMBER(H8)),NOT(ISNUMBER(Revenue!H8))),"",H8/Revenue!H8) -> 0.0074534161 | I23: =IF(OR(NOT(ISNUMBER(I8)),NOT(ISNUMBER(Revenue!I8))),"",I8/Revenue!I8) -> 0.014054054 | ... K23: =IF(OR(NOT(ISNUMBER(K8)),NOT(ISNUMBER(Revenue!K8))),"",K8/Revenue!K8) -> 0.024793388
A24: Mahindra Holidays / Club Mahindra (MHRIL IN) | B24: =IF(OR(NOT(ISNUMBER(B9)),NOT(ISNUMBER(Revenue!B9))),"",B9/Revenue!B9) | C24: =IF(OR(NOT(ISNUMBER(C9)),NOT(ISNUMBER(Revenue!C9))),"",C9/Revenue!C9) | D24: =IF(OR(NOT(ISNUMBER(D9)),NOT(ISNUMBER(Revenue!D9))),"",D9/Revenue!D9) | E24: =IF(OR(NOT(ISNUMBER(E9)),NOT(ISNUMBER(Revenue!E9))),"",E9/Revenue!E9) -> 0.042962963 | F24: =IF(OR(NOT(ISNUMBER(F9)),NOT(ISNUMBER(Revenue!F9))),"",F9/Revenue!F9) -> 0.043298969 | G24: =IF(OR(NOT(ISNUMBER(G9)),NOT(ISNUMBER(Revenue!G9))),"",G9/Revenue!G9) -> 0.021501926 | H24: =IF(OR(NOT(ISNUMBER(H9)),NOT(ISNUMBER(Revenue!H9))),"",H9/Revenue!H9) -> 0.043478261 | I24: =IF(OR(NOT(ISNUMBER(I9)),NOT(ISNUMBER(Revenue!I9))),"",I9/Revenue!I9) -> 0.051948052 | ... K24: =IF(OR(NOT(ISNUMBER(K9)),NOT(ISNUMBER(Revenue!K9))),"",K9/Revenue!K9) -> 0.06875
A25: Mahindra Lifespace Developers (MAHLIFE IN) | B25: =IF(OR(NOT(ISNUMBER(B10)),NOT(ISNUMBER(Revenue!B10))),"",B10/Revenue!B10) | C25: =IF(OR(NOT(ISNUMBER(C10)),NOT(ISNUMBER(Revenue!C10))),"",C10/Revenue!C10) | D25: =IF(OR(NOT(ISNUMBER(D10)),NOT(ISNUMBER(Revenue!D10))),"",D10/Revenue!D10) | E25: =IF(OR(NOT(ISNUMBER(E10)),NOT(ISNUMBER(Revenue!E10))),"",E10/Revenue!E10) -> 0.35125448 | F25: =IF(OR(NOT(ISNUMBER(F10)),NOT(ISNUMBER(Revenue!F10))),"",F10/Revenue!F10) -> 0.13146552 | G25: =IF(OR(NOT(ISNUMBER(G10)),NOT(ISNUMBER(Revenue!G10))),"",G10/Revenue!G10) -> 0.072365226 | H25: =IF(OR(NOT(ISNUMBER(H10)),NOT(ISNUMBER(Revenue!H10))),"",H10/Revenue!H10) -> 0.091304348 | I25: =IF(OR(NOT(ISNUMBER(I10)),NOT(ISNUMBER(Revenue!I10))),"",I10/Revenue!I10) -> 0.10689655 | ... K25: =IF(OR(NOT(ISNUMBER(K10)),NOT(ISNUMBER(Revenue!K10))),"",K10/Revenue!K10) -> 0.125
A26: Mahindra Accelo | B26: =IF(OR(NOT(ISNUMBER(B11)),NOT(ISNUMBER(Revenue!B11))),"",B11/Revenue!B11) | C26: =IF(OR(NOT(ISNUMBER(C11)),NOT(ISNUMBER(Revenue!C11))),"",C11/Revenue!C11) | D26: =IF(OR(NOT(ISNUMBER(D11)),NOT(ISNUMBER(Revenue!D11))),"",D11/Revenue!D11) -> 0.035100287 | E26: =IF(OR(NOT(ISNUMBER(E11)),NOT(ISNUMBER(Revenue!E11))),"",E11/Revenue!E11) | F26: =IF(OR(NOT(ISNUMBER(F11)),NOT(ISNUMBER(Revenue!F11))),"",F11/Revenue!F11) | G26: =IF(OR(NOT(ISNUMBER(G11)),NOT(ISNUMBER(Revenue!G11))),"",G11/Revenue!G11) | H26: =IF(OR(NOT(ISNUMBER(H11)),NOT(ISNUMBER(Revenue!H11))),"",H11/Revenue!H11) -> 0.039285714 | I26: =IF(OR(NOT(ISNUMBER(I11)),NOT(ISNUMBER(Revenue!I11))),"",I11/Revenue!I11) -> 0.04375 | ... K26: =IF(OR(NOT(ISNUMBER(K11)),NOT(ISNUMBER(Revenue!K11))),"",K11/Revenue!K11) -> 0.051807229
A27: Mahindra Aerostructures | B27: =IF(OR(NOT(ISNUMBER(B12)),NOT(ISNUMBER(Revenue!B12))),"",B12/Revenue!B12) | C27: =IF(OR(NOT(ISNUMBER(C12)),NOT(ISNUMBER(Revenue!C12))),"",C12/Revenue!C12) | D27: =IF(OR(NOT(ISNUMBER(D12)),NOT(ISNUMBER(Revenue!D12))),"",D12/Revenue!D12) | E27: =IF(OR(NOT(ISNUMBER(E12)),NOT(ISNUMBER(Revenue!E12))),"",E12/Revenue!E12) -> 0.0042553191 | F27: =IF(OR(NOT(ISNUMBER(F12)),NOT(ISNUMBER(Revenue!F12))),"",F12/Revenue!F12) -> -0.031007752 | G27: =IF(OR(NOT(ISNUMBER(G12)),NOT(ISNUMBER(Revenue!G12))),"",G12/Revenue!G12) | H27: =IF(OR(NOT(ISNUMBER(H12)),NOT(ISNUMBER(Revenue!H12))),"",H12/Revenue!H12) -> 0.014705882 | I27: =IF(OR(NOT(ISNUMBER(I12)),NOT(ISNUMBER(Revenue!I12))),"",I12/Revenue!I12) -> 0.042553191 | ... K27: =IF(OR(NOT(ISNUMBER(K12)),NOT(ISNUMBER(Revenue!K12))),"",K12/Revenue!K12) -> 0.088888889
A28: Classic Legends (Jawa / Yezdi / BSA) | B28: =IF(OR(NOT(ISNUMBER(B13)),NOT(ISNUMBER(Revenue!B13))),"",B13/Revenue!B13) | C28: =IF(OR(NOT(ISNUMBER(C13)),NOT(ISNUMBER(Revenue!C13))),"",C13/Revenue!C13) | D28: =IF(OR(NOT(ISNUMBER(D13)),NOT(ISNUMBER(Revenue!D13))),"",D13/Revenue!D13) | E28: =IF(OR(NOT(ISNUMBER(E13)),NOT(ISNUMBER(Revenue!E13))),"",E13/Revenue!E13) | F28: =IF(OR(NOT(ISNUMBER(F13)),NOT(ISNUMBER(Revenue!F13))),"",F13/Revenue!F13) | G28: =IF(OR(NOT(ISNUMBER(G13)),NOT(ISNUMBER(Revenue!G13))),"",G13/Revenue!G13) | H28: =IF(OR(NOT(ISNUMBER(H13)),NOT(ISNUMBER(Revenue!H13))),"",H13/Revenue!H13) -> 0.032 | I28: =IF(OR(NOT(ISNUMBER(I13)),NOT(ISNUMBER(Revenue!I13))),"",I13/Revenue!I13) -> 0.052941176 | ... K28: =IF(OR(NOT(ISNUMBER(K13)),NOT(ISNUMBER(Revenue!K13))),"",K13/Revenue!K13) -> 0.08627451
A29: Car&Bike / Mahindra First Choice Wheels | B29: =IF(OR(NOT(ISNUMBER(B14)),NOT(ISNUMBER(Revenue!B14))),"",B14/Revenue!B14) | C29: =IF(OR(NOT(ISNUMBER(C14)),NOT(ISNUMBER(Revenue!C14))),"",C14/Revenue!C14) | D29: =IF(OR(NOT(ISNUMBER(D14)),NOT(ISNUMBER(Revenue!D14))),"",D14/Revenue!D14) | E29: =IF(OR(NOT(ISNUMBER(E14)),NOT(ISNUMBER(Revenue!E14))),"",E14/Revenue!E14) | F29: =IF(OR(NOT(ISNUMBER(F14)),NOT(ISNUMBER(Revenue!F14))),"",F14/Revenue!F14) | G29: =IF(OR(NOT(ISNUMBER(G14)),NOT(ISNUMBER(Revenue!G14))),"",G14/Revenue!G14) | H29: =IF(OR(NOT(ISNUMBER(H14)),NOT(ISNUMBER(Revenue!H14))),"",H14/Revenue!H14) -> -0.052631579 | I29: =IF(OR(NOT(ISNUMBER(I14)),NOT(ISNUMBER(Revenue!I14))),"",I14/Revenue!I14) -> 0.010638298 | ... K29: =IF(OR(NOT(ISNUMBER(K14)),NOT(ISNUMBER(Revenue!K14))),"",K14/Revenue!K14) -> 0.083333333
A31: Susten FY24 margin is meaningless (exceptional InvIT gain on a small revenue base). Club Mahindra FY26 is depressed by the c.Rs 234cr impairment.

Sheet Group Contribution
A1: Growth Gems — contribution to M&M group earnings
A2: M&M share of gem PAT = gem PAT x M&M stake. Compared against M&M consolidated PAT.
A4: Gem — M&M share of PAT (Rs cr) | B4: M&M stake | C4: FY21A | D4: FY22A | E4: FY23A | F4: FY24A | G4: FY25A | H4: FY26A | I4: FY27E | J4: FY28E | K4: FY29E | L4: FY30E | M4: Note
A5: Mahindra Last Mile Mobility | B5: 0.7579 | C5: =IF(NOT(ISNUMBER(PAT!B5)),"",PAT!B5*$B5) | D5: =IF(NOT(ISNUMBER(PAT!C5)),"",PAT!C5*$B5) | E5: =IF(NOT(ISNUMBER(PAT!D5)),"",PAT!D5*$B5) | F5: =IF(NOT(ISNUMBER(PAT!E5)),"",PAT!E5*$B5) -> 19.7054 | G5: =IF(NOT(ISNUMBER(PAT!F5)),"",PAT!F5*$B5) | H5: =IF(NOT(ISNUMBER(PAT!G5)),"",PAT!G5*$B5) -> 140.2115 | I5: =IF(NOT(ISNUMBER(PAT!H5)),"",PAT!H5*$B5) -> 197.054 | J5: =IF(NOT(ISNUMBER(PAT!I5)),"",PAT!I5*$B5) -> 272.844 | ... L5: =IF(NOT(ISNUMBER(PAT!K5)),"",PAT!K5*$B5) -> 454.74 | M5: Post Lightrock round, 30-Jul-26 (was 78.11%)
A6: Mahindra Trucks & Buses (MTBD + SML) | B6: 0.5896 | C6: =IF(NOT(ISNUMBER(PAT!B6)),"",PAT!B6*$B6) | D6: =IF(NOT(ISNUMBER(PAT!C6)),"",PAT!C6*$B6) | E6: =IF(NOT(ISNUMBER(PAT!D6)),"",PAT!D6*$B6) | F6: =IF(NOT(ISNUMBER(PAT!E6)),"",PAT!E6*$B6) | G6: =IF(NOT(ISNUMBER(PAT!F6)),"",PAT!F6*$B6) | H6: =IF(NOT(ISNUMBER(PAT!G6)),"",PAT!G6*$B6) | I6: =IF(NOT(ISNUMBER(PAT!H6)),"",PAT!H6*$B6) -> 106.128 | J6: =IF(NOT(ISNUMBER(PAT!I6)),"",PAT!I6*$B6) -> 176.88 | ... L6: =IF(NOT(ISNUMBER(PAT!K6)),"",PAT!K6*$B6) -> 347.864 | M6: SML Mahindra 58.96%; MTBD 100% (inside M&M standalone until the Jan-27 transfer)
A7: Mahindra Susten | B7: 0.7 | C7: =IF(NOT(ISNUMBER(PAT!B7)),"",PAT!B7*$B7) | D7: =IF(NOT(ISNUMBER(PAT!C7)),"",PAT!C7*$B7) | E7: =IF(NOT(ISNUMBER(PAT!D7)),"",PAT!D7*$B7) | F7: =IF(NOT(ISNUMBER(PAT!E7)),"",PAT!E7*$B7) -> 596.4 | G7: =IF(NOT(ISNUMBER(PAT!F7)),"",PAT!F7*$B7) | H7: =IF(NOT(ISNUMBER(PAT!G7)),"",PAT!G7*$B7) | I7: =IF(NOT(ISNUMBER(PAT!H7)),"",PAT!H7*$B7) -> 105 | J7: =IF(NOT(ISNUMBER(PAT!I7)),"",PAT!I7*$B7) -> 182 | ... L7: =IF(NOT(ISNUMBER(PAT!K7)),"",PAT!K7*$B7) -> 392 | M7: ESTIMATE. OTPP holds 30% (Sep-22) with an option for a further 9.99% — confirm via AOC-1
A8: Mahindra Logistics (MAHLOG IN) | B8: 0.58 | C8: =IF(NOT(ISNUMBER(PAT!B8)),"",PAT!B8*$B8) -> 27.26 | D8: =IF(NOT(ISNUMBER(PAT!C8)),"",PAT!C8*$B8) | E8: =IF(NOT(ISNUMBER(PAT!D8)),"",PAT!D8*$B8) | F8: =IF(NOT(ISNUMBER(PAT!E8)),"",PAT!E8*$B8) -> 4.64 | G8: =IF(NOT(ISNUMBER(PAT!F8)),"",PAT!F8*$B8) -> -20.88 | H8: =IF(NOT(ISNUMBER(PAT!G8)),"",PAT!G8*$B8) -> 1.16 | I8: =IF(NOT(ISNUMBER(PAT!H8)),"",PAT!H8*$B8) -> 34.8 | J8: =IF(NOT(ISNUMBER(PAT!I8)),"",PAT!I8*$B8) -> 75.4 | ... L8: =IF(NOT(ISNUMBER(PAT!K8)),"",PAT!K8*$B8) -> 174 | M8: Listed
A9: Mahindra Holidays / Club Mahindra (MHRIL IN) | B9: 0.67 | C9: =IF(NOT(ISNUMBER(PAT!B9)),"",PAT!B9*$B9) | D9: =IF(NOT(ISNUMBER(PAT!C9)),"",PAT!C9*$B9) | E9: =IF(NOT(ISNUMBER(PAT!D9)),"",PAT!D9*$B9) | F9: =IF(NOT(ISNUMBER(PAT!E9)),"",PAT!E9*$B9) -> 77.72 | G9: =IF(NOT(ISNUMBER(PAT!F9)),"",PAT!F9*$B9) -> 84.42 | H9: =IF(NOT(ISNUMBER(PAT!G9)),"",PAT!G9*$B9) -> 44.89 | I9: =IF(NOT(ISNUMBER(PAT!H9)),"",PAT!H9*$B9) -> 100.5 | J9: =IF(NOT(ISNUMBER(PAT!I9)),"",PAT!I9*$B9) -> 134 | ... L9: =IF(NOT(ISNUMBER(PAT!K9)),"",PAT!K9*$B9) -> 221.1 | M9: Listed
A10: Mahindra Lifespace Developers (MAHLIFE IN) | B10: 0.51 | C10: =IF(NOT(ISNUMBER(PAT!B10)),"",PAT!B10*$B10) | D10: =IF(NOT(ISNUMBER(PAT!C10)),"",PAT!C10*$B10) | E10: =IF(NOT(ISNUMBER(PAT!D10)),"",PAT!D10*$B10) | F10: =IF(NOT(ISNUMBER(PAT!E10)),"",PAT!E10*$B10) -> 49.98 | G10: =IF(NOT(ISNUMBER(PAT!F10)),"",PAT!F10*$B10) -> 31.11 | H10: =IF(NOT(ISNUMBER(PAT!G10)),"",PAT!G10*$B10) -> 151.98 | I10: =IF(NOT(ISNUMBER(PAT!H10)),"",PAT!H10*$B10) -> 214.2 | J10: =IF(NOT(ISNUMBER(PAT!I10)),"",PAT!I10*$B10) -> 316.2 | ... L10: =IF(NOT(ISNUMBER(PAT!K10)),"",PAT!K10*$B10) -> 561 | M10: Listed
A11: Mahindra Accelo | B11: 1 | C11: =IF(NOT(ISNUMBER(PAT!B11)),"",PAT!B11*$B11) | D11: =IF(NOT(ISNUMBER(PAT!C11)),"",PAT!C11*$B11) -> 181 | E11: =IF(NOT(ISNUMBER(PAT!D11)),"",PAT!D11*$B11) -> 147 | F11: =IF(NOT(ISNUMBER(PAT!E11)),"",PAT!E11*$B11) | G11: =IF(NOT(ISNUMBER(PAT!F11)),"",PAT!F11*$B11) | H11: =IF(NOT(ISNUMBER(PAT!G11)),"",PAT!G11*$B11) | I11: =IF(NOT(ISNUMBER(PAT!H11)),"",PAT!H11*$B11) -> 220 | J11: =IF(NOT(ISNUMBER(PAT!I11)),"",PAT!I11*$B11) -> 280 | ... L11: =IF(NOT(ISNUMBER(PAT!K11)),"",PAT!K11*$B11) -> 430 | M11: ESTIMATE — confirm via AOC-1
A12: Mahindra Aerostructures | B12: 1 | C12: =IF(NOT(ISNUMBER(PAT!B12)),"",PAT!B12*$B12) | D12: =IF(NOT(ISNUMBER(PAT!C12)),"",PAT!C12*$B12) | E12: =IF(NOT(ISNUMBER(PAT!D12)),"",PAT!D12*$B12) | F12: =IF(NOT(ISNUMBER(PAT!E12)),"",PAT!E12*$B12) -> 1 | G12: =IF(NOT(ISNUMBER(PAT!F12)),"",PAT!F12*$B12) -> -8 | H12: =IF(NOT(ISNUMBER(PAT!G12)),"",PAT!G12*$B12) | I12: =IF(NOT(ISNUMBER(PAT!H12)),"",PAT!H12*$B12) -> 5 | J12: =IF(NOT(ISNUMBER(PAT!I12)),"",PAT!I12*$B12) -> 20 | ... L12: =IF(NOT(ISNUMBER(PAT!K12)),"",PAT!K12*$B12) -> 80 | M12: 100% indirect via Mahindra Aerospace
A13: Classic Legends (Jawa / Yezdi / BSA) | B13: 0.6 | C13: =IF(NOT(ISNUMBER(PAT!B13)),"",PAT!B13*$B13) | D13: =IF(NOT(ISNUMBER(PAT!C13)),"",PAT!C13*$B13) | E13: =IF(NOT(ISNUMBER(PAT!D13)),"",PAT!D13*$B13) | F13: =IF(NOT(ISNUMBER(PAT!E13)),"",PAT!E13*$B13) | G13: =IF(NOT(ISNUMBER(PAT!F13)),"",PAT!F13*$B13) | H13: =IF(NOT(ISNUMBER(PAT!G13)),"",PAT!G13*$B13) | I13: =IF(NOT(ISNUMBER(PAT!H13)),"",PAT!H13*$B13) -> 24 | J13: =IF(NOT(ISNUMBER(PAT!I13)),"",PAT!I13*$B13) -> 54 | ... L13: =IF(NOT(ISNUMBER(PAT!K13)),"",PAT!K13*$B13) -> 132 | M13: ESTIMATE — confirm via AOC-1
A14: Car&Bike / Mahindra First Choice Wheels | B14: 0.545 | C14: =IF(NOT(ISNUMBER(PAT!B14)),"",PAT!B14*$B14) | D14: =IF(NOT(ISNUMBER(PAT!C14)),"",PAT!C14*$B14) | E14: =IF(NOT(ISNUMBER(PAT!D14)),"",PAT!D14*$B14) | F14: =IF(NOT(ISNUMBER(PAT!E14)),"",PAT!E14*$B14) | G14: =IF(NOT(ISNUMBER(PAT!F14)),"",PAT!F14*$B14) | H14: =IF(NOT(ISNUMBER(PAT!G14)),"",PAT!G14*$B14) | I14: =IF(NOT(ISNUMBER(PAT!H14)),"",PAT!H14*$B14) -> -10.9 | J14: =IF(NOT(ISNUMBER(PAT!I14)),"",PAT!I14*$B14) -> 2.725 | ... L14: =IF(NOT(ISNUMBER(PAT!K14)),"",PAT!K14*$B14) -> 32.7 | M14: M&M/parent c.54.5%; funds c.32%
A15: Aggregate M&M share of gem PAT | C15: =SUM(C5:C14) -> 27.26 | D15: =SUM(D5:D14) -> 181 | E15: =SUM(E5:E14) -> 147 | F15: =SUM(F5:F14) -> 749.4454 | G15: =SUM(G5:G14) -> 86.65 | H15: =SUM(H5:H14) -> 338.2415 | I15: =SUM(I5:I14) -> 995.782 | J15: =SUM(J5:J14) -> 1514.049 | ... L15: =SUM(L5:L14) -> 2825.404
A16: M&M consolidated PAT (reported) | C16: 1512 | D16: 6577 | E16: 10282 | F16: 11269 | G16: 12929 | H16: 17099 | I16: n/l | J16: n/l | K16: n/l | L16: n/l | M16: M&M press-release basis. See Data Quality Log for the conflict with Screener's net-profit line. Group forecasts are out of scope of this pack.
A17: Gems as % of group PAT (populated cells only) | C17: =IF(NOT(ISNUMBER(C16)),"",C15/C16) -> 0.018029101 | D17: =IF(NOT(ISNUMBER(D16)),"",D15/D16) -> 0.027520146 | E17: =IF(NOT(ISNUMBER(E16)),"",E15/E16) -> 0.014296829 | F17: =IF(NOT(ISNUMBER(F16)),"",F15/F16) -> 0.066505049 | G17: =IF(NOT(ISNUMBER(G16)),"",G15/G16) -> 0.0067019878 | H17: =IF(NOT(ISNUMBER(H16)),"",H15/H16) -> 0.019781361 | M17: UNDERSTATED — several gems have no disclosed PAT, so the numerator is incomplete. Treat as a floor, not a measure.
A20: COMPANY-DISCLOSED CROSS-CHECK: M&M's FY26 results press release (5 May 2026) states that the Growth Gems delivered PAT growth of 50%, footnoted as 'M&M share of PAT', led by Real Estate, Logistics and Accelo. That is the only aggregate the company publishes — it does not disclose the absolute rupee figure. Our aggregate above is built bottom-up from the gems where PAT is disclosed and is therefore incomplete; do not present it as the company's number.
A22: VALUE-CREATION CROSS-CHECK: per Autocar Professional's Investor Day coverage (Nov 2025), the gems' share of group market capitalisation grew sevenfold between March 2020 and November 2025, reaching Rs 56,000cr. The '5x Challenge' targets a c.5x value increase over FY25-FY30. Group ROE was 20.1% in FY26, above the 18% hurdle.

Sheet Balance Sheet & CF
A1: Growth Gems — balance sheet and cash flow metrics
A2: Deliberately sparse. The unlisted gems do not publish these; AOC-1 will close most of the gaps.
A4: Gem | B4: Net worth / equity | C4: Borrowings / gearing | D4: Capital intensity & capex | E4: Cash flow / self-funding | F4: Capital infused by M&M | G4: What is disclosed, and what is not
A5: Mahindra Last Mile Mobility | B5: n/l — mine AOC-1 | C5: n/l | D5: Capacity build ahead of demand; new Telangana plant | E5: Improving; external capital funds the ramp | F5: c.Rs 1,300cr of external capital raised (IFC Rs 600cr, India-Japan Fund Rs 400cr, Lightrock-led Rs 322cr) rather than M&M equity | G5: Entity-level balance sheet not published. AOC-1 in the FY25/FY26 annual report will give share capital, reserves, total assets and total liabilities.
A6: Mahindra Trucks & Buses (MTBD + SML) | B6: SML: available in SML Mahindra's own filings | C6: SML: available in SML filings | D6: Manufacturing-heavy; SML plant utilisation is the lever | E6: SML profitable and largely self-funding | F6: Rs 555cr for the 58.96% SML stake (Apr-25) plus Rs 525cr for the MTBD division transfer (announced Jul-26) | G6: SML is separately listed — pull its audited balance sheet directly. MTBD has no standalone balance sheet because it sits inside M&M standalone until the Jan-27 transfer.
A7: Mahindra Susten | B7: n/l — mine AOC-1 | C7: Project-level debt: Rs 1,025cr (Mar-26, 300 MW Rajasthan) and Rs 1,448cr (Dec-24, 560 MW) | D7: Highly capital-intensive; GW build-out | E7: Capital recycling via the InvIT (ROFO to the Trust) is the funding model | F7: Rs 1,799.61cr rights issue (Aug-25) at Rs 60.40/share; OTPP equity of c.$300m for 30% (Sep-22) | G7: Project financing is disclosed via news flow; the entity balance sheet is not. The InvIT's own filings are a useful proxy for the monetised assets.
A8: Mahindra Logistics (MAHLOG IN) | B8: Listed — audited BS available | C8: Listed — audited; asset-right model, modest gearing | D8: Asset-light 3PL; leases dominate | E8: Returned to positive operating profitability in FY26 | F8: Rights issue completed FY26 | G8: Fully disclosed. Pull the audited annual report for the complete FY21-FY26 series.
A9: Mahindra Holidays / Club Mahindra (MHRIL IN) | B9: Listed — audited BS available | C9: Listed — audited; net cash | D9: Resort development is capex-heavy; c.900 keys added in FY26 | E9: Strongly cash-generative; deferred revenue of c.Rs 5,700cr+ funds the build | F9: None recently — self-funding | G9: Fully disclosed. Note the c.Rs 234cr HCRO/Mauritius impairment in FY26 and the NFRA directive on vacation-ownership revenue recognition flagged in the FY26 audit.
A10: Mahindra Lifespace Developers (MAHLIFE IN) | B10: Listed — audited BS available | C10: Net debt/equity -0.27 at FY26 (net cash) | D10: Land and development capex; Rs 18,060cr of GDV added in FY26 | E10: Self-funding; rights issue completed FY26 | F10: Rights issue completed FY26 | G10: Fully disclosed. GDV pipeline c.Rs 50,000cr. Revenue recognition is completion-method under Ind-AS 115, so the P&L lags pre-sales materially.
A11: Mahindra Accelo | B11: n/l — mine AOC-1 | C11: Net debt/equity 0.10 at FY25 (Accelo FY25 Integrated Annual Report) | D11: Steel service centres and RVSF recycling infrastructure | E11: Largely self-funding | F11: n/l | G11: Publishes its own Integrated Annual Report with selected ratios, but not a full comparable series. FY25 EBITDA Rs 332.77cr, 5-year revenue CAGR 30.85%, PAT CAGR 49.21%.
A12: Mahindra Aerostructures | B12: Rs 159.5cr at FY25 (CARE Ratings, 12-Jun-25) | C12: Gearing 1.31x at FY25; no external bank debt | D12: Industrialisation capex ahead of the order-book ramp | E12: NOT self-funding — dependent on M&M support | F12: c.Rs 100cr of inter-corporate deposits from M&M in FY25; paid-up capital Rs 577.84cr | G12: CARE's rating rationale is the best available source. The funding structure (ICDs rather than bank debt) is the key point: this gem still consumes group capital.
A13: Classic Legends (Jawa / Yezdi / BSA) | B13: Accumulated losses since 2018 — quantum n/l | C13: n/l | D13: Very low — the plant was acquired from Mahindra at no cost, so there is no depreciation or interest burden (co-founder cites 'infinite' ROCE) | E13: First profitable year in FY26 | F13: Rs 350cr invested in product development across 12 products; paid-up capital c.Rs 754.66cr (FY23) | G13: The zero-cost plant is the single most important structural fact about this gem's economics and is not obvious from any financial statement.
A14: Car&Bike / Mahindra First Choice Wheels | B14: Book net worth fell c.34.65% in FY24 | C14: n/l | D14: Asset-light platform | E14: NOT self-funding | F14: n/l | G14: Thinly disclosed. The FY25 revenue drop needs to be diagnosed before any forecast is relied on.
A16: Roughly half of this tab is genuinely unavailable. That is a disclosure fact about M&M's unlisted subsidiaries, not a gap in the work. Form AOC-1 in the FY25 and FY26 Integrated Annual Reports (s.129(3)) discloses share capital, reserves & surplus, total assets, total liabilities, investments, turnover, PBT, tax, PAT and % shareholding for every subsidiary — that single schedule closes most of these cells.

Sheet Growth Drivers
A1: Growth Gems — what is actually driving the numbers
A2: The qualitative layer behind the forecasts: revenue drivers, margin drivers, the FY30 view, and what breaks it
A4: Gem | B4: What is driving revenue right now | C4: What drives the margin, and where it goes | D4: What drives growth through FY30 | E4: What breaks the thesis | F4: Capital intensity / self-funding
A5: Mahindra Last Mile Mobility | B5: Structural L5 electrification — electric 3W penetration went from 12% to 40% in two years. Policy support (FAME/PM E-DRIVE-type schemes), urban last-mile e-commerce demand, and product-band expansion from 3W into small 4W cargo. 136,855 units in FY26 with 100,000+ electric. | C5: Scale, localisation and battery-cost deflation. Margin is thin today (we estimate c.7-8% EBITDA in FY26) and should creep toward c.10% by FY30 as volume and the higher-value L5/4W mix build. | D5: The 1m-EVs-by-2031 and 50%-electrification-by-FY30 targets. Exports to 10+ markets. The H2 FY27 IPO would fund capacity and put a public mark on the business. | E5: Subsidy or policy withdrawal is the biggest single risk on a sub-10% margin. Battery-metal cost spikes. New entrants and legacy OEMs compressing the c.40% L5 share. | F5: Improving. Funded by external capital (c.Rs 1,300cr across IFC, India-Japan Fund and Lightrock) rather than M&M equity — which is itself a signal of confidence.
A6: Mahindra Trucks & Buses (MTBD + SML) | B6: SML integration — combined share went from c.3% to 6.0% of >3.5T CV in FY26. Nov-25 combined volumes +57% YoY with SML +102%. GST 2.0 replacement demand and infrastructure/e-commerce freight. | C6: Platform consolidation, shared sourcing and network, and plant-utilisation leverage off SML's frugal manufacturing base. The Jan-27 MTBD transfer into SML is what unlocks the synergy. | D6: The stated Rs 15,000cr-by-FY31 ambition, 10-12% CV share by FY31 and 20%+ by FY36, against a CV market going from c.Rs 1,50,000cr to c.Rs 2,00,000cr. | E6: A CV-cycle downturn — this is the most cyclical gem in the portfolio. Integration missteps on the MTBD transfer. HCV competitive intensity from Tata and Ashok Leyland, where M&M has never had scale. | F6: Rs 555cr acquisition plus Rs 525cr division transfer. SML is profitable and largely self-funding.
A7: Mahindra Susten | B7: India's solar build-out — c.6.4 GWp of connectivity secured, 560 MWp commissioned in FY26. Project wins and the hybrid/BESS extension (15 MWh at Modhera). | C7: The mix shift from lumpy EPC toward annuity IPP improves earnings quality but lowers headline revenue recognition. Read revenue and margin together here, never separately. | D7: The 1.5-to-7 GW roadmap and the 5x-by-2030 target, funded through the InvIT capital-recycling model. | E7: Module-price volatility, tariff aggression in auctions, and execution risk on land and grid connectivity. Also note FY24 PAT was inflated by an exceptional InvIT gain — the underlying earnings base is much smaller. | F7: Highly capital-intensive. Part-funded by OTPP equity and the InvIT recycling model with a ROFO to the Trust.
A8: Mahindra Logistics (MAHLOG IN) | B8: The turnaround itself. Express reached a positive gross margin (1.3% in FY26), white space was cut from 1.6m to 0.7m sq ft, freight-forwarding EBITDA rose 48% and mobility revenue 22%. 400+ corporate clients. | C8: Operating leverage on a fixed warehousing base plus mix shift toward higher-margin freight forwarding and mobility. From 5.4% in FY26 toward c.7% by FY30 on our numbers. | D8: Warehousing formalisation post-GST, e-commerce and 3PL outsourcing penetration, and continued white-space reduction. | E8: 3PL price competition is brutal and margins are structurally thin — a 100bp miss is most of the PAT. Captive-mix concentration with M&M. Cyclical freight rates. | F8: Asset-right model; largely self-funding post-turnaround. Rights issue completed FY26.
A9: Mahindra Holidays / Club Mahindra (MHRIL IN) | B9: Inventory addition — a record c.900 gross keys in FY26 taking the estate to 6,228 — plus premiumisation, with AUR up c.83% in Q4 FY26, and the new Keystone membership product. | C9: Premiumisation and occupancy on a largely fixed resort cost base. Note that consolidated margins are dragged by the European HCRO arm, which took a c.Rs 234cr impairment in FY26. | D9: The 10,000-rooms-by-FY30 roadmap and the '3x keys, 3x revenue, 4x PAT this decade' framing. Deferred revenue of c.Rs 5,700cr+ underpins the visibility. | E9: Member additions slowing — this is a subscription business and gross adds are the leading indicator. The HCRO European drag. Regulatory scrutiny of vacation-ownership revenue recognition (NFRA directive flagged in the FY26 audit) is a genuine accounting risk. | F9: Resort development is capex-heavy but funded from deferred revenue and c.Rs 1,500cr+ of cash. Self-funding.
A10: Mahindra Lifespace Developers (MAHLIFE IN) | B10: Pre-sales momentum — Rs 3,405cr in FY26, +21% — and a step-change in project additions: Rs 18,060cr of GDV added, taking the pipeline to c.Rs 50,000cr. Kandivali added Rs 5,600cr of GDV. | C10: Project mix and the completion-method recognition cycle. FY26 PAT rose 386% as earlier pre-sales converted to revenue — expect continued but lumpy operating leverage. | D10: The FY27 guidance of Rs 4,500-5,000cr of pre-sales with Rs 10,000cr of launches, building toward Rs 8,000-10,000cr of annual pre-sales and 5x scale by FY30. Bhandup (Rs 12,400cr GDV) and Mahalaxmi are the near-term launches. IC&IC adds Rs 400-500cr revenue and Rs 100-150cr PAT annually. | E10: A housing-cycle downturn. Launch and approval delays — real-estate timelines slip routinely. Premium mix compressing margins. And note the P&L is lumpy by construction, so a weak year is not necessarily a weak business. | F10: Self-funding with a net-cash balance sheet (net debt/equity -0.27 at FY26). Rights issue completed FY26.
A11: Mahindra Accelo | B11: Steel processing volumes tracking M&M's own UV growth (it is partly a captive service centre), plus electrical-steel and EV-component demand and the recycling network build-out (7 RVSFs, 42 collection centres). | C11: Spread over steel input costs plus the mix shift toward higher-value electrical steel and recycling, which carries better margins than commodity processing. | D11: Vehicle-scrappage mandates driving organised recycling toward the c.25%-share-by-FY28 target; EV component localisation under PLI; electrical steel for renewables. | E11: Steel-price and spread volatility, which flows straight through. Slow scrappage-policy rollout — the recycling thesis is entirely policy-dependent. And the captive linkage means M&M volume weakness hits twice. | F11: Largely self-funding; net debt/equity 0.10 at FY25.
A12: Mahindra Aerostructures | B12: The order-book inflection. c.$1bn of orders in just over a year against c.$150m accumulated over the preceding fifteen years, anchored by the Jun-25 Aernnova contract of c.$300m for Airbus/Embraer work. | C12: Industrialisation and learning-curve effects on new programmes. FY25 operating margin was 8.62% with a small net loss; margin should build as programmes mature, but slowly. | D12: The c.12x-revenue-this-decade ambition and the top-10-global-supplier goal, plus the new Novavayu Aerospace entity for aircraft and defence manufacturing. | E12: Client concentration on Boeing and Airbus. Order deferrals — an order book is not revenue, and aerospace lead times are long. Ramp and industrialisation delays. Note this gem still loses money and consumes group capital. | F12: NOT self-funding. M&M provided c.Rs 100cr of inter-corporate deposits in FY25; gearing 1.31x with no external bank debt.
A13: Classic Legends (Jawa / Yezdi / BSA) | B13: Volume recovery — 45,409 retails in FY26, +40%, with H2 up 100% YoY after two years of decline (FY24 36,680, FY25 32,482). New launches, dealer expansion and GST 2.0. | C13: The structural point: the plant was acquired from Mahindra at no cost, so there is no depreciation or interest burden. That is why FY26 turned profitable at only c.45k units, and why incremental volume drops through hard. | D13: The 2028 IPO ambition, global expansion (BSA into Western markets, Jawa into Eastern Europe and South America), dealer network from c.350 to 500+, and new scramblers. | E13: Royal Enfield at 80%+ share, with Triumph and Harley now in the segment. Quality and distribution execution — this business has stumbled before. US tariff and customs disruption (c.5,000 units held at US Customs in Aug-25) is a live export risk. | F13: Very low capital intensity given the zero-cost plant. Rs 350cr invested in product development.
A14: Car&Bike / Mahindra First Choice Wheels | B14: Formalisation of the organised used-car market and monetisation of the platform and data assets (AutoInspekt inspections, eDiig auctions, YMS). | C14: The FY25 revenue drop of c.59% most likely reflects a shift from principal sales to platform and franchise fees — which would mean lower revenue at a much higher margin. This must be verified before any margin forecast is used. | D14: Used-car market formalisation and platform/data monetisation. | E14: Intense competition from Cars24, Spinny and CarTrade, all better capitalised in the consumer-facing layer. The path to profitability is unproven. This is the weakest gem in the portfolio on disclosed evidence. | F14: NOT self-funding. Book net worth fell c.34.65% in FY24.

Sheet Group Financials
A1: M&M group financials — FY21 to FY26 (reported actuals)
A2: Context for the gems' contribution. Note the consolidated-PAT source conflict, shown in full.
A4: Rs cr unless stated | B4: FY21A | C4: FY22A | D4: FY23A | E4: FY24A | F4: FY25A | G4: FY26A | I4: Source / note
A5: Consolidated revenue | B5: 74278 | C5: 90171 | D5: 121269 | E5: 139078 | F5: 159211 | G5: 198639 | I5: M&M press releases FY22-FY26; FY25 & FY26 Integrated Annual Reports.
A6: Consolidated PAT — M&M press-release basis | B6: 1512 | C6: 6577 | D6: 10282 | E6: 11269 | F6: 12929 | G6: 17099 | I6: M&M's own KPI framing, after non-controlling interest. FY21 is ambiguous: Rs 1,512cr includes discontinued SsangYong operations; Business Today (28-May-21) reports Rs 3,702cr on a continuing-operations basis.
A7: Consolidated PAT — Screener 'Net Profit' basis | B7: 1512 | C7: 7253 | D7: 11374 | E7: 12270 | F7: 14073 | G7: 18622 | I7: screener.in/company/M&M/consolidated. Consistently HIGHER than M&M's press-release PAT (different consolidation and exceptional-item scope). Both shown deliberately — pick one basis and state it.
A8: Consolidated EPS (Rs) | B8: 14.58 | C8: 52.9 | D8: 82.7 | E8: 100.7 | F8: 115.1 | G8: 152.2 | I8: M&M basis. FY22 and FY23 are derived and approximate.
A9: Consolidated ROE (%) | B9: 0.066 | C9: 0.13 | D9: 0.199 | E9: 0.184 | F9: 0.181 | G9: 0.201 | I9: FY21 and FY22 approximate. M&M runs a minimum 18% consolidated ROE hurdle — cleared in FY23, FY24, FY25 and FY26.
A10: Standalone revenue | B10: 44574 | C10: 57787 | D10: 84960 | E10: 101219 | F10: 118625 | G10: 147765 | I10: FY21 approximate. Minor restatement: standalone FY23 revenue was Rs 84,960cr in the FY23 release vs Rs 86,645cr in the FY24 comparative.
A11: Standalone PAT | B11: n/l | C11: 4870 | D11: 6549 | E11: 10718 | F11: 11855 | G11: 15639 | I11: FY21 not located.
A13: CAPITAL ALLOCATION — the credibility anchor
A14: M&M runs a minimum 18% consolidated ROE hurdle with a turn-around-or-exit discipline. Delivered 19.9% / 18.4% / 18.1% / 20.1% in FY23-FY26.
A15: Under Anish Shah (Group CEO/MD from April 2021), M&M has exited c.15 underperforming businesses: SsangYong (deconsolidated Dec-20), Mahindra First Choice Services workshops (sold to TVS Automobile Solutions, Feb-21), Peugeot Motocycles (control to Mutares, early 2023), GenZe (US e-mobility), the general-aviation aircraft business (wound down 2023), Sampo Rosenlew (Finland, sold FY26), Erkunt Traktor (Turkey, sale announced, completion FY27) and MAM Japan / Mitsubishi Agricultural Machinery (liquidation, wind-down FY27).
A16: The '5x Challenge' targets a c.5x value increase for the gems over FY25-FY30. Per Autocar Professional's Investor Day coverage (Nov 2025), the gems' share of group market capitalisation grew sevenfold between March 2020 and November 2025, reaching Rs 56,000cr; M&M stock rose c.14x from April 2020 to November 2025 against c.3x for the Nifty.

Sheet Milestones
A1: Dated milestones and forward catalysts
A2: Last 24 months of events, then what to watch
A4: Date | B4: Gem | C4: Event
A5: Sep 2022 | B5: Susten | C5: Ontario Teachers' Pension Plan acquires 30% at c.Rs 2,371cr equity value (c.$300m), with an option for a further 9.99%.
A6: Mar 2023 | B6: LMM | C6: IFC commits Rs 600cr at a valuation of up to Rs 6,020cr.
A7: May 2023 | B7: LMM | C7: Mahindra Last Mile Mobility Ltd incorporated (CIN U29102MH2023PLC403752); commercial operations from Sep-23.
A8: Aug 2023 | B8: Susten | C8: India's largest renewables InvIT lists, seeded with c.1.54 GWp.
A9: Jan 2024 | B9: LMM | C9: NIIF's India-Japan Fund invests Rs 400cr.
A10: Oct 2024 | B10: Accelo | C10: Zero Waste to Landfill certification.
A11: Dec 2024 | B11: Susten | C11: Rs 1,448cr project financing for 560 MW.
A12: Jan 2025 | B12: Susten | C12: SBTi approval.
A13: Apr 2025 | B13: T&B | C13: M&M agrees to acquire 58.96% of SML Isuzu for Rs 555cr (Rs 650/share; open offer at Rs 1,554.60/share).
A14: May 2025 | B14: All | C14: Q4 FY25 call (5 May): Anish Shah formalises the Scalable ($2-3bn) vs Emerging ($1bn) gem taxonomy and the 5x Challenge.
A15: Jun 2025 | B15: Aerostructures | C15: Aernnova contract of c.$300m (Rs 2,585cr) for multi-year Airbus/Embraer work.
... A29: Aug 2026 | B29: LMM | C29: Crosses 400,000 cumulative EV sales — India's first CV maker to do so.
A31: FORWARD | C31: Catalysts to track — these are what move the gems from book value to market value
A32: Jan 2027 | B32: T&B | C32: MTBD transfer into SML Mahindra completes — consolidates all >3.5T CV under one listed entity. The CV re-rating trigger.
A33: H2 FY27 | B33: LMM | C33: IPO. The single most important event in the portfolio: it puts a public mark on the largest unlisted gem and validates or breaks the private-mark approach. A delay is the clearest signal to cut gem-value assumptions.
A34: FY27 | B34: Lifespaces | C34: Delivery against the Rs 4,500-5,000cr FY27 pre-sales guidance and Rs 10,000cr of launches (Bhandup, Mahalaxmi).
A35: FY27 | B35: Logistics | C35: Sustaining EBITDA margin above c.6% and keeping reported PAT positive — the turnaround has to hold for more than one year.
A36: FY27 | B36: Classic Legends | C36: Sustaining FY26's first-ever profitability into a second year.
A37: Open | B37: Susten | C37: InvIT asset monetisation — crystallises a yield-based mark and creates a repeatable template for the rest of the portfolio.
A38: 2028 | B38: Classic Legends | C38: Targeted IPO.
A39: FY30 | B39: All | C39: The 5x Challenge scorecard: $2-3bn per scalable gem, $1bn per emerging gem. If two or more scalable gems miss their FY27 milestones, haircut the aggregate.

Sheet Data Quality Log
A1: Data quality log — every conflict, ambiguity and gap
A2: Read this before circulating. Nothing here is hidden in a footnote.
A4: Item | B4: Severity | C4: What the issue is and what to do about it
A5: M&M consolidated PAT | B5: HIGH — conflict | C5: M&M's press-release PAT and Screener's 'Net Profit' line differ every single year (FY25: 12,929 vs 14,073; FY26: 17,099 vs 18,622) because of differing consolidation and exceptional-item scope. Both are shown on the Group Financials tab. Pick one basis, state it explicitly in the client note, and do not mix them.
A6: M&M FY21 consolidated PAT | B6: HIGH — ambiguous | C6: Rs 1,512cr includes discontinued SsangYong operations; Business Today (28-May-21) reports Rs 3,702cr on a continuing-operations basis. FY21 was distorted by the SsangYong deconsolidation (28-Dec-20) and international write-offs. Do not use FY21 as a clean base year for any CAGR.
A7: Lifespaces FY26 revenue | B7: HIGH — not comparable | C7: The Rs 4,118cr FY26 figure is reported as 'consolidated sales' (sales value), which is NOT the same as the Ind-AS revenue line used for FY24 (Rs 279cr) and FY25 (Rs 464cr). The apparent 9x jump is largely a definitional break, not organic growth. Do not compute a revenue CAGR across that break. Pre-sales (Rs 2,328 / 2,804 / 3,405cr) is the consistent operating series — use that.
A8: Susten FY24 PAT | B8: HIGH — one-off | C8: Rs 852cr includes large exceptional gains from the InvIT monetisation on total income of only Rs 195cr. It is not an operating number and implies a nonsensical margin. Never use as a run-rate or a base for growth.
A9: Club Mahindra FY26 PAT | B9: MEDIUM — one-off | C9: Consolidated PAT of Rs 67cr is depressed by a c.Rs 234cr HCRO/Mauritius impairment; ex-one-off is c.Rs 136.3cr. Use the ex-one-off figure for trend analysis and disclose the adjustment.
A10: Car&Bike FY25 revenue | B10: MEDIUM — needs diagnosis | C10: Revenue fell c.59% to Rs 313cr from >Rs 500cr. Most likely a revenue-recognition shift from principal sales to platform and franchise fees, which would imply lower revenue at higher margin. Verify against AOC-1 before using the FY27E-FY30E forecasts, which are low-confidence as a result.
A11: Accelo scope | B11: MEDIUM — scope unclear | C11: Entity-level revenue of c.Rs 4,600cr (FY24) far exceeds the 'Rs 1,000cr+' band some commercial databases show. Confirm whether the figure is consolidated or standalone in AOC-1 before quoting it. Also note Accelo is partly a captive steel service centre for M&M's UV business, so its revenue is not fully third-party.
A12: Classic Legends financials | B12: HIGH — estimated throughout | C12: Tracxn gives only a Rs 500-1,000cr band for FY25. Our FY25 and FY26 revenue figures are derived from retail units multiplied by an assumed c.Rs 1.8-2.0L ASP. They are marked blue and should be treated as indicative only. FY26 profitability is confirmed qualitatively by the co-founder but the quantum is not disclosed.
A13: M&M shareholding percentages | B13: MEDIUM — partly estimated | C13: Firm: LMM 75.79% (post Jul-26), SML 58.96%, Club Mahindra c.67%, Logistics c.58%, Lifespaces c.51%, Aerostructures 100% (indirect). ESTIMATED and needing AOC-1 confirmation: Susten c.70%, Accelo 100%, Classic Legends c.60%. The Group Contribution tab is sensitive to these.
A14: Trucks & Buses entity structure | B14: MEDIUM — structural | C14: MTBD has no standalone historic financials because it sat inside M&M standalone as a division. The FY26 combined figure (Rs 5,827cr) is the first meaningful combined datapoint, and even that is a sum of two separately reported numbers. A clean series only begins after the Jan-27 transfer completes.
A15: Historic coverage gaps | B15: MEDIUM — disclosure fact | C15: FY21-FY23 is largely blank for the unlisted gems. LMM did not exist as an entity before May-23. Logistics FY22 and FY23 were not located in the sources used and should be pulled from its own annual reports. Roughly a third of the historic cells across the pack are genuinely unavailable in public disclosure.
... A17: Aggregate gems PAT | B17: MEDIUM — incomplete | C17: The aggregate on the Group Contribution tab sums only the gems where PAT is disclosed, so it understates the true figure. M&M itself discloses only a growth rate (+50% in FY26, M&M share of PAT), never an absolute. Present ours as a floor, not as the company's number.

Sheet Sources
A1: Master source list
A2: Document, date and location for every reported figure in this pack
A4: Document | B4: Date | C4: Where / note
A5: M&M FY26 results press release | B5: 5 May 2026 | C5: mahindra.com/news-room/press-release/en/m-and-m-results-q4-f26-and-fy26 — group FY26 financials, Growth Gems PAT +50%
A6: M&M FY25 results press release | B6: 5 May 2025 | C6: mahindra.com — group FY25 financials; Anish Shah's Scalable vs Emerging gem taxonomy
A7: M&M FY24 results press release | B7: 16 May 2024 | C7: mahindra.com — group FY24 financials
A8: M&M Integrated Annual Report FY26 | B8: FY2025-26 | C8: mahindra.com/annual-report-FY2026/ — Susten 560 MWp and Rs 443cr; T&B 6.0% share; 'Other Emerging Businesses' grouping. CONTAINS FORM AOC-1.
A9: M&M Integrated Annual Report FY25 | B9: FY2024-25 | C9: mahindra.com/annual-report-FY2025/ — CONTAINS FORM AOC-1 (s.129(3) subsidiary schedule)
A10: Screener.in | B10: ongoing | C10: screener.in/company/M&M/consolidated — alternative consolidated PAT basis
A11: Autocar Professional — Investor Day coverage | B11: 20 Nov 2025 | C11: Gems' market-cap share up sevenfold since Mar-20 to Rs 56,000cr; $2bn+ scalable-gem targets
A12: Autocar Professional — 'Mahindra Bets Big on Growth Gems' | B12: May 2025 | C12: Q4 FY25 call coverage; gem taxonomy
A13: AlphaStreet — M&M Q4 FY25 call highlights | B13: May 2025 | C13: 5x Challenge framing
A14: M&M press release — MLMML achieves Unicorn Status | B14: 30 July 2026 | C14: Rs 322cr Lightrock-led round at Rs 10,822cr; stake 78.11% to 75.79%; IPO H2 FY27; 100,000+ cumulative e-3W in FY26
A15: Business Today / Business Standard — LMM unicorn | B15: 30 July 2026 | C15: Corroborating coverage of the Lightrock round
... A34: Business Today — M&M FY21 results | B34: 28 May 2021 | C34: FY21 continuing-operations PAT Rs 3,702cr
