Workbook

Sheet Read Me
A1: VEHICLE PLATFORM ECONOMICS | Cars vs two-wheelers, ICE vs EV
A2: Investment-research model. India-centred, with global benchmarks. All figures in INR unless stated.
A4: WHAT THIS MODEL DOES
A5: Sizes the one-time cost of creating a vehicle platform, the incremental cost of each model placed on it, and the volume and margin needed to earn that money back. It runs the same logic across four segments - car ICE, car BEV, two-wheeler ICE, two-wheeler BEV - so the four are directly comparable.
A6: Everything is driven off one dropdown on the Control Panel. Twelve headline levers sit beside it; the full assumption library sits on the Assumptions tab, with every line tagged Reported or Estimate.
A8: HOW TO DRIVE IT
A9: 1. Control Panel - pick the segment, then set overrides in the yellow Override column. Blank means 'use the segment default'.
A10: 2. Investment Build - the cost stack: platform engineering, per-model top hats, capacity capex. Development investment and plant capex are deliberately kept apart, because the first is sunk against the platform and the second is fungible across it.
A11: 3. Unit Economics - the per-vehicle P&L at start of production, from net realisation down to fully-loaded programme EBIT.
A12: 4. Programme Returns - a 20-year lifecycle cash flow with break-even volume, payback year, NPV and IRR.
A13: 5. Platform Sharing - the same programme run at one to eight models, showing what sharing is actually worth.
A14: 6. Sensitivities - three grids across model count, volume and margin.
... A39: No PLI or subsidy benefit. Add it as a lever on net realisation if you want it - Ola cites c.INR 40,000-45,000 per vehicle.

Sheet Control Panel
A1: CONTROL PANEL | Vehicle Platform Economics
A2: Pick a segment, then flex the twelve headline levers. Leave an override blank to use the segment default.
A5: SEGMENT
A6: Vehicle type / powertrain | C6: Car - ICE | E6: <-- dropdown. Everything downstream re-prices off this cell.
A8: HEADLINE LEVERS (blank override = segment default)
A9: Lever | B9: Unit | C9: Segment default | D9: Override | E9: In use
A10: Number of models on the platform | B10: # | C10: =Assumptions!$I$29 -> 4 | E10: =Assumptions!$K$29 -> 4
A11: Peak annual volume per model | B11: units | C11: =Assumptions!$I$46 -> 100000 | E11: =Assumptions!$K$46 -> 100000
A12: Platform lifecycle (production years) | B12: years | C12: =Assumptions!$I$47 -> 10 | E12: =Assumptions!$K$47 -> 10
A13: Net realisation per unit (ex-factory) | B13: INR | C13: =Assumptions!$I$36 -> 700000 | E13: =Assumptions!$K$36 -> 700000
A14: Non-battery BOM | B14: % of NR | C14: =Assumptions!$I$37 -> 0.7 | E14: =Assumptions!$K$37 -> 0.7
A15: Fixed manufacturing overhead | B15: INR cr p.a. | C15: =Assumptions!$I$43 -> 450 | E15: =Assumptions!$K$43 -> 450
A16: Platform engineering scaling factor | B16: x | C16: =Assumptions!$I$17 -> 1 | E16: =Assumptions!$K$17 -> 1
A17: Top-hat scaling factor | B17: x | C17: =Assumptions!$I$24 -> 1 | E17: =Assumptions!$K$24 -> 1
A18: Incremental platform re-engineering per added model | B18: % of plat. eng. | C18: =Assumptions!$I$26 -> 0.08 | E18: =Assumptions!$K$26 -> 0.08
A19: Capacity capex attributable to platform | B19: % | C19: =Assumptions!$I$34 -> 0.5 | E19: =Assumptions!$K$34 -> 0.5
A20: Annual change in net realisation | B20: % | C20: =Assumptions!$I$49 -> 0.01 | E20: =Assumptions!$K$49 -> 0.01
A21: WACC | B21: % | C21: =Assumptions!$I$53 -> 0.11 | E21: =Assumptions!$K$53 -> 0.11
A24: PROGRAMME OUTPUT (live)
A25: Total platform-level investment | B25: INR cr | C25: ='Investment Build'!$D$20 -> 1727.568
A26: Total top-hat investment (all models) | B26: INR cr | C26: ='Investment Build'!$D$31 -> 1700
A27: TOTAL DEVELOPMENT INVESTMENT | B27: INR cr | C27: ='Investment Build'!$D$33 -> 3427.568
A28: Capacity capex attributed to platform | B28: INR cr | C28: ='Investment Build'!$D$41 -> 6800
A29: TOTAL INVESTED CAPITAL | B29: INR cr | C29: ='Investment Build'!$D$43 -> 10227.568
A31: Lifetime platform volume | B31: units | C31: ='Programme Returns'!$D$12 -> 3328000
A32: Development investment per unit | B32: INR | C32: ='Investment Build'!$D$46 -> 10299.183
A33: Contribution margin at SOP | B33: % of NR | C33: ='Unit Economics'!$D$22 -> 0.249
A34: Contribution per unit at SOP | B34: INR | C34: ='Unit Economics'!$D$21 -> 174300
A36: Break-even volume - development investment only | B36: cum. units | C36: ='Programme Returns'!$D$15 -> 196647.62
A37: Break-even volume - total invested capital | B37: cum. units | C37: ='Programme Returns'!$D$16 -> 586779.58
A38: Break-even as % of lifetime volume | B38: % | C38: ='Programme Returns'!$D$17 -> 0.17631598
A39: Cash break-even year (from start of development) | B39: year | C39: ='Programme Returns'!$D$18 -> 7
A41: Lifetime revenue | B41: INR cr | C41: ='Programme Returns'!$D$19 -> 243194.6
A42: Lifetime EBITDA | B42: INR cr | C42: ='Programme Returns'!$D$20 -> 56904.677
A43: Lifetime EBIT margin | B43: % | C43: ='Programme Returns'!$D$21 -> 0.20125355
A44: Programme NPV | B44: INR cr | C44: ='Programme Returns'!$D$22 -> 9476.2379
A45: Programme IRR | B45: % | C45: ='Programme Returns'!$D$23 -> 0.28992704
A46: Peak cash outflow | B46: INR cr | C46: ='Programme Returns'!$D$24 -> -10227.568
A48: COLOUR LEGEND
A49: Blue text on yellow fill | C49: Input / lever - edit these
A50: Black text | C50: Formula calculated on this sheet
A51: Green text | C51: Link to another sheet

Sheet Assumptions
A1: ASSUMPTIONS | Vehicle Platform Economics
A2: All four segments held side by side. Column K ('In use') is what every other sheet reads. Blue = hardcoded input. Override on the Control Panel, not here, for the twelve headline levers.
A4: Active segment | B4: ='Control Panel'!$C$6 -> Car - ICE | D4: Active column index | E4: =MATCH($B$4,$C$7:$F$7,0) -> 1
A7: Line item | B7: Unit | C7: Car - ICE | D7: Car - BEV | E7: 2W - ICE | F7: 2W - BEV | G7: Basis | H7: Source / cross-check | I7: Segment default | J7: Override | K7: In use
A8: A. PLATFORM DEVELOPMENT INVESTMENT (one-time, INR cr)
A9: Concept, styling & platform design | B9: INR cr | C9: 120 | D9: 130 | E9: 15 | F9: 18 | G9: Estimate | H9: Scaled from disclosed programme totals; no OEM discloses this line separately | I9: =IFERROR(INDEX(C9:F9,$E$4),0) -> 120 | K9: =IF(J9="",I9,J9) -> 120
A10: Body / chassis architecture engineering | B10: INR cr | C10: 250 | D10: 320 | E10: 35 | F10: 40 | G10: Estimate | H10: BEV skateboard carries higher structural content (battery-in-floor) | I10: =IFERROR(INDEX(C10:F10,$E$4),0) -> 250 | K10: =IF(J10="",I10,J10) -> 250
A11: Powertrain development (ICE: engine + transmission family; EV: e-drive, pack, BMS, thermal) | B11: INR cr | C11: 350 | D11: 550 | E11: 90 | F11: 130 | G11: Estimate | H11: Cross-check: Renault CMF-A total EUR400m covered platform + new engine + new gearbox + 300k plant | I11: =IFERROR(INDEX(C11:F11,$E$4),0) -> 350 | K11: =IF(J11="",I11,J11) -> 350
A12: E/E architecture, electronics & software | B12: INR cr | C12: 150 | D12: 400 | E12: 20 | F12: 90 | G12: Estimate | H12: Largest ICE-to-EV step-up. Ola cites ~INR 2,000cr for the whole Gen-3 architecture incl. cell/motor integration | I12: =IFERROR(INDEX(C12:F12,$E$4),0) -> 150 | K12: =IF(J12="",I12,J12) -> 150
A13: Prototyping, testing & validation (crash, durability, NVH) | B13: INR cr | C13: 180 | D13: 220 | E13: 40 | F13: 45 | G13: Estimate | I13: =IFERROR(INDEX(C13:F13,$E$4),0) -> 180 | K13: =IF(J13="",I13,J13) -> 180
A14: Homologation & regulatory certification | B14: INR cr | C14: 40 | D14: 45 | E14: 10 | F14: 10 | G14: Estimate | I14: =IFERROR(INDEX(C14:F14,$E$4),0) -> 40 | K14: =IF(J14="",I14,J14) -> 40
A15: Supplier development & common-part tooling | B15: INR cr | C15: 200 | D15: 280 | E15: 45 | F15: 55 | G15: Estimate | I15: =IFERROR(INDEX(C15:F15,$E$4),0) -> 200 | K15: =IF(J15="",I15,J15) -> 200
A16: Contingency & programme management | B16: % of above | C16: 0.08 | D16: 0.1 | E16: 0.08 | F16: 0.1 | G16: Estimate | I16: =IFERROR(INDEX(C16:F16,$E$4),0) -> 0.08 | K16: =IF(J16="",I16,J16) -> 0.08
A17: Platform engineering scaling factor | B17: x | C17: 1 | D17: 1 | E17: 1 | F17: 1 | G17: LEVER | H17: Control Panel override. Set 1.5x for a global-scalable architecture, 0.7x for a derivative platform | I17: =IFERROR(INDEX(C17:F17,$E$4),0) -> 1 | J17: =IF('Control Panel'!$D$16="","",'Control Panel'!$D$16) | K17: =IF(J17="",I17,J17) -> 1
A18: B. PER-MODEL 'TOP HAT' INVESTMENT (INR cr per model)
A19: Model styling & upper-body engineering | B19: INR cr | C19: 90 | D19: 110 | E19: 12 | F19: 14 | G19: Estimate | I19: =IFERROR(INDEX(C19:F19,$E$4),0) -> 90 | K19: =IF(J19="",I19,J19) -> 90
A20: Model-specific tooling (stamping dies, moulds, jigs) | B20: INR cr | C20: 180 | D20: 200 | E20: 22 | F20: 24 | G20: Estimate | H20: Single biggest top-hat item; scales with body-panel count, not with volume | I20: =IFERROR(INDEX(C20:F20,$E$4),0) -> 180 | K20: =IF(J20="",I20,J20) -> 180
A21: Model-specific validation & homologation | B21: INR cr | C21: 55 | D21: 65 | E21: 8 | F21: 9 | G21: Estimate | I21: =IFERROR(INDEX(C21:F21,$E$4),0) -> 55 | K21: =IF(J21="",I21,J21) -> 55
A22: Launch, marketing & network readiness | B22: INR cr | C22: 60 | D22: 90 | E22: 20 | F22: 26 | G22: Estimate | I22: =IFERROR(INDEX(C22:F22,$E$4),0) -> 60 | K22: =IF(J22="",I22,J22) -> 60
A23: Model-specific line & fixture changes | B23: INR cr | C23: 40 | D23: 50 | E23: 6 | F23: 8 | G23: Estimate | I23: =IFERROR(INDEX(C23:F23,$E$4),0) -> 40 | K23: =IF(J23="",I23,J23) -> 40
A24: Top-hat scaling factor | B24: x | C24: 1 | D24: 1 | E24: 1 | F24: 1 | G24: LEVER | H24: Control Panel override. Cross-check: new Swift (2011) cost INR 550cr incl. supplier spend | I24: =IFERROR(INDEX(C24:F24,$E$4),0) -> 1 | J24: =IF('Control Panel'!$D$17="","",'Control Panel'!$D$17) | K24: =IF(J24="",I24,J24) -> 1
A25: C. PLATFORM SHARING PARAMETERS
A26: Incremental platform re-engineering per added model | B26: % of platform eng. | C26: 0.08 | D26: 0.09 | E26: 0.07 | F26: 0.08 | G26: LEVER | H26: Ola: further Gen-3 products need 'limited incremental R&D' | I26: =IFERROR(INDEX(C26:F26,$E$4),0) -> 0.08 | J26: =IF('Control Panel'!$D$18="","",'Control Panel'!$D$18) | K26: =IF(J26="",I26,J26) -> 0.08
A27: Dedicated architecture cost if the model were built standalone | B27: % of modular platform eng. | C27: 0.8 | D27: 0.82 | E27: 0.78 | F27: 0.8 | G27: Estimate | H27: A standalone architecture is cheaper than a scalable modular one, but only modestly | I27: =IFERROR(INDEX(C27:F27,$E$4),0) -> 0.8 | K27: =IF(J27="",I27,J27) -> 0.8
A28: BOM benefit per doubling of platform component volume | B28: % of BOM | C28: 0.035 | D28: 0.03 | E28: 0.03 | F28: 0.025 | G28: Estimate | H28: VW targeted c.20% component cost saving from MQB; treated here as a per-doubling learning rate | I28: =IFERROR(INDEX(C28:F28,$E$4),0) -> 0.035 | K28: =IF(J28="",I28,J28) -> 0.035
A29: Number of models on platform | B29: # | C29: 4 | D29: 3 | E29: 4 | F29: 3 | G29: LEVER | H29: HEARTECT underpins 8-9 Maruti models; INGLO has 3 launched | I29: =IFERROR(INDEX(C29:F29,$E$4),0) -> 4 | J29: =IF('Control Panel'!$D$10="","",'Control Panel'!$D$10) | K29: =IF(J29="",I29,J29) -> 4
A30: Mid-cycle facelift cost | B30: % of top hat | C30: 0.25 | D30: 0.25 | E30: 0.2 | F30: 0.2 | G30: Estimate | I30: =IFERROR(INDEX(C30:F30,$E$4),0) -> 0.25 | K30: =IF(J30="",I30,J30) -> 0.25
A31: D. CAPACITY / PLANT INVESTMENT
A32: Capacity capex per unit of annual capacity | B32: INR | C32: 340000 | D32: 450000 | E32: 25000 | F32: 30000 | G32: Reported (derived) | H32: Cars: Toyota Bidadi INR 3,300cr/100k; Maruti Khoraj INR 35,000cr/1.0m; Tata-JLR Ranipet INR 9,000cr/250k. 2W: RE Cheyyar INR 958cr/540k; Bajaj CTL Akurdi INR 750cr/500k; RE Andhra (greenfield) INR 2,500cr/450k | I32: =IFERROR(INDEX(C32:F32,$E$4),0) -> 340000 | K32: =IF(J32="",I32,J32) -> 340000
A33: Annual capacity built for this platform | B33: units | C33: 400000 | D33: 150000 | E33: 1200000 | F33: 500000 | G33: Estimate | H33: Defaults are set just above the default model count x peak volume. Cut this below that product and capacity becomes the binding constraint on programme volume - which is exactly what happens in practice | I33: =IFERROR(INDEX(C33:F33,$E$4),0) -> 400000 | K33: =IF(J33="",I33,J33) -> 400000
A34: Share of capacity capex attributable to this platform | B34: % | C34: 0.5 | D34: 0.8 | E34: 0.4 | F34: 0.7 | G34: LEVER | H34: Brownfield / shared lines carry a low attribution; a dedicated BEV plant carries a high one | I34: =IFERROR(INDEX(C34:F34,$E$4),0) -> 0.5 | J34: =IF('Control Panel'!$D$19="","",'Control Panel'!$D$19) | K34: =IF(J34="",I34,J34) -> 0.5
A35: E. PER-UNIT ECONOMICS (at start of production)
A36: Net realisation (ex-factory, ex-GST) | B36: INR/unit | C36: 700000 | D36: 1500000 | E36: 68000 | F36: 105000 | G36: LEVER | I36: =IFERROR(INDEX(C36:F36,$E$4),0) -> 700000 | J36: =IF('Control Panel'!$D$13="","",'Control Panel'!$D$13) | K36: =IF(J36="",I36,J36) -> 700000
A37: Non-battery bill of materials | B37: % of NR | C37: 0.7 | D37: 0.47 | E37: 0.68 | F37: 0.49 | G37: LEVER | I37: =IFERROR(INDEX(C37:F37,$E$4),0) -> 0.7 | J37: =IF('Control Panel'!$D$14="","",'Control Panel'!$D$14) | K37: =IF(J37="",I37,J37) -> 0.7
A38: Battery pack size | B38: kWh | C38: 0 | D38: 50 | E38: 0 | F38: 3 | G38: Estimate | I38: =IFERROR(INDEX(C38:F38,$E$4),0) -> 0 | K38: =IF(J38="",I38,J38) -> 0
A39: Battery pack cost | B39: INR/kWh | C39: 0 | D39: 8700 | E39: 0 | F39: 8700 | G39: Reported (BNEF) | H39: BNEF 2025 survey: BEV packs USD99/kWh; LFP USD81/kWh; China USD84/kWh. Converted at c.INR 88/USD | I39: =IFERROR(INDEX(C39:F39,$E$4),0) -> 0 | K39: =IF(J39="",I39,J39) -> 0
A40: Direct conversion cost (labour, energy, consumables) | B40: % of NR | C40: 0.06 | D40: 0.055 | E40: 0.05 | F40: 0.05 | G40: Estimate | I40: =IFERROR(INDEX(C40:F40,$E$4),0) -> 0.06 | K40: =IF(J40="",I40,J40) -> 0.06
A41: Warranty & after-sales provision | B41: % of NR | C41: 0.015 | D41: 0.02 | E41: 0.01 | F41: 0.02 | G41: Estimate | I41: =IFERROR(INDEX(C41:F41,$E$4),0) -> 0.015 | K41: =IF(J41="",I41,J41) -> 0.015
A42: Freight & variable selling | B42: % of NR | C42: 0.025 | D42: 0.025 | E42: 0.02 | F42: 0.03 | G42: Estimate | I42: =IFERROR(INDEX(C42:F42,$E$4),0) -> 0.025 | K42: =IF(J42="",I42,J42) -> 0.025
A43: Fixed manufacturing overhead | B43: INR cr p.a. | C43: 450 | D43: 300 | E43: 180 | F43: 200 | G43: LEVER | I43: =IFERROR(INDEX(C43:F43,$E$4),0) -> 450 | J43: =IF('Control Panel'!$D$15="","",'Control Panel'!$D$15) | K43: =IF(J43="",I43,J43) -> 450
A44: Corporate SG&A and brand allocated to programme | B44: % of revenue | C44: 0.05 | D44: 0.06 | E44: 0.06 | F44: 0.09 | G44: Estimate | H44: EV 2W carries the highest load: D2C network build plus brand from zero | I44: =IFERROR(INDEX(C44:F44,$E$4),0) -> 0.05 | K44: =IF(J44="",I44,J44) -> 0.05
A45: F. PROGRAMME & VOLUME
A46: Peak annual volume per model | B46: units | C46: 100000 | D46: 45000 | E46: 300000 | F46: 150000 | G46: LEVER | I46: =IFERROR(INDEX(C46:F46,$E$4),0) -> 100000 | J46: =IF('Control Panel'!$D$11="","",'Control Panel'!$D$11) | K46: =IF(J46="",I46,J46) -> 100000
A47: Platform lifecycle (production years) | B47: years | C47: 10 | D47: 8 | E47: 10 | F47: 7 | G47: LEVER | H47: EV lifecycles assumed shorter: faster cell/electronics obsolescence | I47: =IFERROR(INDEX(C47:F47,$E$4),0) -> 10 | J47: =IF('Control Panel'!$D$12="","",'Control Panel'!$D$12) | K47: =IF(J47="",I47,J47) -> 10
A48: Development period before start of production | B48: years | C48: 4 | D48: 3.5 | E48: 2.5 | F48: 2.5 | G48: Estimate | H48: VW MQB took c.4 years; Ather took 4 years to first product | I48: =IFERROR(INDEX(C48:F48,$E$4),0) -> 4 | K48: =IF(J48="",I48,J48) -> 4
A49: Annual change in net realisation | B49: % | C49: 0.01 | D49: -0.015 | E49: 0.015 | F49: -0.01 | G49: LEVER | I49: =IFERROR(INDEX(C49:F49,$E$4),0) -> 0.01 | J49: =IF('Control Panel'!$D$20="","",'Control Panel'!$D$20) | K49: =IF(J49="",I49,J49) -> 0.01
A50: Annual change in non-battery BOM cost | B50: % | C50: -0.01 | D50: -0.02 | E50: -0.01 | F50: -0.015 | G50: Estimate | I50: =IFERROR(INDEX(C50:F50,$E$4),0) -> -0.01 | K50: =IF(J50="",I50,J50) -> -0.01
A51: Annual change in battery pack cost | B51: % | C51: 0 | D51: -0.05 | E51: 0 | F51: -0.05 | G51: Estimate | H51: BNEF: pack prices -8% in 2025; -93% since 2010. -5% p.a. is a deliberately conservative forward rate | I51: =IFERROR(INDEX(C51:F51,$E$4),0) -> 0 | K51: =IF(J51="",I51,J51) -> 0
A52: G. FINANCIAL
A53: WACC (discount rate) | B53: % | C53: 0.11 | D53: 0.125 | E53: 0.11 | F53: 0.14 | G53: LEVER | I53: =IFERROR(INDEX(C53:F53,$E$4),0) -> 0.11 | J53: =IF('Control Panel'!$D$21="","",'Control Panel'!$D$21) | K53: =IF(J53="",I53,J53) -> 0.11
A54: Effective tax rate | B54: % | C54: 0.252 | D54: 0.252 | E54: 0.252 | F54: 0.252 | G54: Reported | H54: India statutory concessional rate | I54: =IFERROR(INDEX(C54:F54,$E$4),0) -> 0.252 | K54: =IF(J54="",I54,J54) -> 0.252
A55: Amortisation life of capitalised development | B55: years | C55: 8 | D55: 7 | E55: 8 | F55: 6 | G55: Estimate | I55: =IFERROR(INDEX(C55:F55,$E$4),0) -> 8 | K55: =IF(J55="",I55,J55) -> 8
A56: Depreciation life of capacity capex | B56: years | C56: 15 | D56: 15 | E56: 15 | F56: 15 | G56: Estimate | I56: =IFERROR(INDEX(C56:F56,$E$4),0) -> 15 | K56: =IF(J56="",I56,J56) -> 15
A57: Working capital as % of revenue | B57: % | C57: -0.03 | D57: -0.01 | E57: -0.04 | F57: 0 | G57: Estimate | H57: Indian OEMs typically run negative working capital | I57: =IFERROR(INDEX(C57:F57,$E$4),0) -> -0.03 | K57: =IF(J57="",I57,J57) -> -0.03
A59: H. VOLUME RAMP PROFILE (% of peak annual volume, by production year)
A60: Production year | C60: 1 | D60: 2 | E60: 3 | F60: 4 | G60: 5 | H60: 6 | I60: 7 | J60: 8 | K60: 9 | L60: 10 | M60: 11 | N60: 12 | O60: 13 | P60: 14 | Q60: 15
A61: % of peak volume | C61: 0.6 | D61: 0.85 | E61: 1 | F61: 1 | G61: 1 | H61: 1 | I61: 0.92 | J61: 0.8 | K61: 0.65 | L61: 0.5 | M61: 0.38 | N61: 0.28 | O61: 0.2 | P61: 0.15 | Q61: 0.1
A62: Sum of ramp factors within lifecycle | K62: =SUMPRODUCT((C60:Q60<=K47)*C61:Q61) -> 8.32
A64: Note: 'Reported' = figure disclosed by a company, regulator or industry survey (see Sources tab). 'Estimate' = Bernstein estimate, triangulated against disclosed programme totals. 'LEVER' = overridable on the Control Panel.

Sheet Investment Build
A1: INVESTMENT BUILD | What it costs to create a platform and put models on it
A2: Development investment is platform-specific and sunk. Capacity capex is fungible across platforms and is shown separately.
A4: Active segment | C4: ='Control Panel'!$C$6 -> Car - ICE
A6: Line item | B6: Unit | D6: Value | E6: % of eng.
A7: A. PLATFORM ENGINEERING (one-time, independent of model count)
A8: Concept, styling & platform design | B8: INR cr | D8: =Assumptions!$K$9 -> 120 | E8: =IFERROR(D8/$D$14,0) -> 0.6
A9: Body / chassis architecture engineering | B9: INR cr | D9: =Assumptions!$K$10 -> 250 | E9: =IFERROR(D9/$D$14,0) -> 1.25
A10: Powertrain development | B10: INR cr | D10: =Assumptions!$K$11 -> 350 | E10: =IFERROR(D10/$D$14,0) -> 1.75
A11: E/E architecture, electronics & software | B11: INR cr | D11: =Assumptions!$K$12 -> 150 | E11: =IFERROR(D11/$D$14,0) -> 0.75
A12: Prototyping, testing & validation | B12: INR cr | D12: =Assumptions!$K$13 -> 180 | E12: =IFERROR(D12/$D$14,0) -> 0.9
A13: Homologation & regulatory certification | B13: INR cr | D13: =Assumptions!$K$14 -> 40 | E13: =IFERROR(D13/$D$14,0) -> 0.2
A14: Supplier development & common-part tooling | B14: INR cr | D14: =Assumptions!$K$15 -> 200 | E14: =IFERROR(D14/$D$14,0) -> 1
A15: Sub-total, core engineering | B15: INR cr | D15: =SUM(D8:D14) -> 1290
A16: Contingency & programme management | B16: % of above | C16: =Assumptions!$K$16 -> 0.08 | D16: =D15*C16 -> 103.2
A17: Platform engineering scaling factor | B17: x | C17: =Assumptions!$K$17 -> 1
A18: PLATFORM ENGINEERING INVESTMENT (base architecture) | B18: INR cr | D18: =(D15+D16)*C17 -> 1393.2
A19: Incremental platform re-engineering for models 2..N | B19: INR cr | C19: =Assumptions!$K$26 -> 0.08 | D19: =D18*C19*MAX(0,Assumptions!$K$29-1) -> 334.368
A20: TOTAL PLATFORM-LEVEL INVESTMENT | B20: INR cr | D20: =D18+D19 -> 1727.568
A22: B. PER-MODEL 'TOP HAT' INVESTMENT
A23: Model styling & upper-body engineering | B23: INR cr / model | D23: =Assumptions!$K$19 -> 90
A24: Model-specific tooling (dies, moulds, jigs) | B24: INR cr / model | D24: =Assumptions!$K$20 -> 180
A25: Model-specific validation & homologation | B25: INR cr / model | D25: =Assumptions!$K$21 -> 55
A26: Launch, marketing & network readiness | B26: INR cr / model | D26: =Assumptions!$K$22 -> 60
A27: Model-specific line & fixture changes | B27: INR cr / model | D27: =Assumptions!$K$23 -> 40
A28: Top-hat scaling factor | B28: x | C28: =Assumptions!$K$24 -> 1
A29: TOP-HAT INVESTMENT PER MODEL | B29: INR cr | D29: =SUM(D23:D27)*C28 -> 425
A30: Number of models on platform | B30: # | D30: =Assumptions!$K$29 -> 4
A31: TOTAL TOP-HAT INVESTMENT (all models) | B31: INR cr | D31: =D29*D30 -> 1700
A32: C. TOTAL DEVELOPMENT INVESTMENT
A33: TOTAL DEVELOPMENT INVESTMENT (platform + all top hats) | B33: INR cr | D33: =D20+D31 -> 3427.568
A34: of which platform-level | D34: =IFERROR(D20/D33,0) -> 0.50402151
A36: D. CAPACITY / PLANT INVESTMENT (shown separately: fungible across platforms)
A37: Capacity capex per unit of annual capacity | B37: INR | D37: =Assumptions!$K$32 -> 340000
A38: Annual capacity built for this platform | B38: units | D38: =Assumptions!$K$33 -> 400000
A39: Gross capacity capex | B39: INR cr | D39: =D37*D38/10000000 -> 13600
A40: Share attributable to this platform | B40: % | D40: =Assumptions!$K$34 -> 0.5
A41: CAPACITY CAPEX ATTRIBUTED TO PLATFORM | B41: INR cr | D41: =D39*D40 -> 6800
A42: E. TOTAL INVESTED CAPITAL
A43: TOTAL INVESTED CAPITAL (development + attributed capacity) | B43: INR cr | D43: =D33+D41 -> 10227.568
A44: F. INVESTMENT PER UNIT OF LIFETIME VOLUME
A45: Lifetime platform volume | B45: units | D45: ='Programme Returns'!$D$12 -> 3328000
A46: Development investment per unit | B46: INR | D46: =IFERROR(D33*10000000/D45,0) -> 10299.183
A47: Total invested capital per unit | B47: INR | D47: =IFERROR(D43*10000000/D45,0) -> 30731.875
A48: Development investment as % of one unit's net realisation | B48: % | D48: =IFERROR(D46/Assumptions!$K$36,0) -> 0.014713118

Sheet Unit Economics
A1: UNIT ECONOMICS | Per-vehicle profit-and-loss at start of production
A2: Contribution margin is what services the platform investment. Everything below the contribution line is fixed or sunk.
A4: Active segment | C4: ='Control Panel'!$C$6 -> Car - ICE
A6: Line item | B6: Unit | C6: % of NR | D6: INR / unit
A7: REVENUE AND VARIABLE COST
A8: Net realisation (ex-factory, ex-GST) | B8: INR/unit | C8: 1 | D8: =Assumptions!$K$36 -> 700000
A9: Non-battery bill of materials | C9: =Assumptions!$K$37 -> 0.7 | D9: =-C9*$D$8 -> -490000
A10: Battery pack (pack size x pack cost) | B10: =Assumptions!$K$38&" kWh @ INR "&TEXT(Assumptions!$K$39,"#,##0")&"/kWh" -> 0 kWh @ INR 0/kWh | C10: =IFERROR(-D10/$D$8,0) -> 0 | D10: =-Assumptions!$K$38*Assumptions!$K$39 -> 0
A11: BOM before platform scale benefit | C11: =IFERROR(-D11/$D$8,0) -> 0.7 | D11: =D9+D10 -> -490000
A12: Platform scale benefit on BOM | B12: ="LOG("&Assumptions!$K$29&",2) doublings x "&TEXT(Assumptions!$K$28,"0.0%") -> LOG(4,2) doublings x 3.5% | C12: =LOG(MAX(Assumptions!$K$29,1),2)*Assumptions!$K$28 -> 0.07 | D12: =-D11*C12 -> 34300
A13: Total bill of materials | C13: =IFERROR(-D13/$D$8,0) -> 0.651 | D13: =D11+D12 -> -455700
A14: Direct conversion cost (labour, energy, consumables) | C14: =Assumptions!$K$40 -> 0.06 | D14: =-C14*$D$8 -> -42000
A15: Warranty & after-sales provision | C15: =Assumptions!$K$41 -> 0.015 | D15: =-C15*$D$8 -> -10500
A16: Freight & variable selling | C16: =Assumptions!$K$42 -> 0.025 | D16: =-C16*$D$8 -> -17500
A17: Total variable cost | C17: =IFERROR(-D17/$D$8,0) -> 0.751 | D17: =D13+D14+D15+D16 -> -525700
A19: Annual programme volume at plateau | B19: units | D19: =MIN(Assumptions!$K$29*Assumptions!$K$46,Assumptions!$K$33) -> 400000
A20: CONTRIBUTION
A21: CONTRIBUTION PER UNIT | B21: INR/unit | D21: =D8+D17 -> 174300
A22: Contribution margin | B22: % of NR | D22: =IFERROR(D21/D8,0) -> 0.249
A24: FIXED AND SUNK COSTS SPREAD OVER THE UNIT
A25: Fixed manufacturing overhead | B25: INR cr p.a. | C25: =IFERROR(-D25/$D$8,0) -> 0.016071429 | D25: =IFERROR(-Assumptions!$K$43*10000000/$D$19,0) -> -11250
A26: Corporate SG&A & brand allocated to programme | C26: =-Assumptions!$K$44 -> -0.05 | D26: =C26*$D$8 -> -35000
A27: Amortisation of development investment | B27: over lifetime volume | C27: =IFERROR(-D27/$D$8,0) -> 0.014713118 | D27: =-'Investment Build'!$D$46 -> -10299.183
A28: Depreciation of attributed capacity capex | B28: over lifetime volume | C28: =IFERROR(-D28/$D$8,0) -> 0.02918956 | D28: =-IFERROR('Investment Build'!$D$41*10000000/'Programme Returns'!$D$12,0) -> -20432.692
A30: PROGRAMME EBIT PER UNIT (fully loaded) | B30: INR/unit | D30: =D21+D25+D26+D27+D28 -> 97318.125
A31: Programme EBIT margin (fully loaded) | B31: % of NR | D31: =IFERROR(D30/D8,0) -> 0.13902589
A33: Memo: development + capacity burden as % of net realisation | D33: =IFERROR(-(D27+D28)/D8,0) -> 0.043902679
A34: Memo: units required to cover one year of fixed manufacturing overhead | D34: =IFERROR(Assumptions!$K$43*10000000/D21,0) -> 25817.556
A35: Memo: BOM saving from running components across all models on the platform | D35: =-D12 -> -34300
A37: The platform scale benefit on row 12 is the third and least-modelled effect of sharing: common components run at N times the volume of a single-model programme, so unit BOM falls. It is applied here at the active model count, and it flows through to the Programme Returns cash flow, so the three sheets tie.

Sheet Programme Returns
A1: PROGRAMME RETURNS | Full-lifecycle cash flow, break-even and IRR
A2: Year 1 is the first year of development spend. Production starts once the development period is complete.
A4: Active segment | C4: ='Control Panel'!$C$6 -> Car - ICE
A6: PROGRAMME SUMMARY
A7: Total development investment | B7: INR cr | D7: ='Investment Build'!$D$33 -> 3427.568
A8: Capacity capex attributed | B8: INR cr | D8: ='Investment Build'!$D$41 -> 6800
A9: Total invested capital | B9: INR cr | D9: ='Investment Build'!$D$43 -> 10227.568
A10: Number of models | B10: # | D10: =Assumptions!$K$29 -> 4
A11: Peak annual programme volume | B11: units | D11: =MAX(C30:V30) -> 400000
A12: Lifetime platform volume | B12: units | D12: =SUM(C30:V30) -> 3328000
A13: Contribution per unit at SOP | B13: INR | D13: ='Unit Economics'!$D$21 -> 174300
A14: Contribution margin at SOP | B14: % | D14: ='Unit Economics'!$D$22 -> 0.249
A15: Break-even volume - development only | B15: cum. units | D15: =IFERROR($D$7*10000000/$D$13,0) -> 196647.62
A16: Break-even volume - total invested capital | B16: cum. units | D16: =IFERROR($D$9*10000000/$D$13,0) -> 586779.58
A17: Break-even as % of lifetime volume | B17: % | D17: =IFERROR($D$16/$D$12,0) -> 0.17631598
A18: Cash break-even year (from start of development) | B18: year | D18: =IF(MIN(C48:V48)>900,0,MIN(C48:V48)) -> 7
A19: Lifetime revenue | B19: INR cr | D19: =SUM(C33:V33) -> 243194.6
A20: Lifetime EBITDA | B20: INR cr | D20: =SUM(C43:V43) -> 56904.677
A21: Lifetime EBIT margin | B21: % | D21: =IFERROR(SUM(C46:V46)/SUM(C33:V33),0) -> 0.20125355
A22: Programme NPV | B22: INR cr | D22: =NPV(Assumptions!$K$53,C53:V53) -> 9476.2379
A23: Programme IRR | B23: % | D23: =IFERROR(IRR(C53:V53),0) -> 0.28992704
A24: Peak cash outflow | B24: INR cr | D24: =MIN(C54:V54) -> -10227.568
A26: LIFECYCLE CASH FLOW (INR cr unless stated)
A27: Year from start of development | C27: 1 | D27: 2 | E27: 3 | F27: 4 | G27: 5 | H27: 6 | I27: 7 | J27: 8 | K27: 9 | L27: 10 | M27: 11 | N27: 12 | O27: 13 | P27: 14 | Q27: 15 | R27: 16 | S27: 17 | T27: 18 | U27: 19 | V27: 20
A28: Development year | B28: # | C28: =IF(C$27<=ROUNDUP(Assumptions!$K$48,0),C$27,0) -> 1 | D28: =IF(D$27<=ROUNDUP(Assumptions!$K$48,0),D$27,0) -> 2 | E28: =IF(E$27<=ROUNDUP(Assumptions!$K$48,0),E$27,0) -> 3 | F28: =IF(F$27<=ROUNDUP(Assumptions!$K$48,0),F$27,0) -> 4 | G28: =IF(G$27<=ROUNDUP(Assumptions!$K$48,0),G$27,0) -> 0 | H28: =IF(H$27<=ROUNDUP(Assumptions!$K$48,0),H$27,0) -> 0 | I28: =IF(I$27<=ROUNDUP(Assumptions!$K$48,0),I$27,0) -> 0 | J28: =IF(J$27<=ROUNDUP(Assumptions!$K$48,0),J$27,0) -> 0 | ... V28: =IF(V$27<=ROUNDUP(Assumptions!$K$48,0),V$27,0) -> 0
A29: Production year | B29: # | C29: =IF(C$27>ROUNDUP(Assumptions!$K$48,0),MIN(C$27-ROUNDUP(Assumptions!$K$48,0),999),0) -> 0 | D29: =IF(D$27>ROUNDUP(Assumptions!$K$48,0),MIN(D$27-ROUNDUP(Assumptions!$K$48,0),999),0) -> 0 | E29: =IF(E$27>ROUNDUP(Assumptions!$K$48,0),MIN(E$27-ROUNDUP(Assumptions!$K$48,0),999),0) -> 0 | F29: =IF(F$27>ROUNDUP(Assumptions!$K$48,0),MIN(F$27-ROUNDUP(Assumptions!$K$48,0),999),0) -> 0 | G29: =IF(G$27>ROUNDUP(Assumptions!$K$48,0),MIN(G$27-ROUNDUP(Assumptions!$K$48,0),999),0) -> 1 | H29: =IF(H$27>ROUNDUP(Assumptions!$K$48,0),MIN(H$27-ROUNDUP(Assumptions!$K$48,0),999),0) -> 2 | I29: =IF(I$27>ROUNDUP(Assumptions!$K$48,0),MIN(I$27-ROUNDUP(Assumptions!$K$48,0),999),0) -> 3 | J29: =IF(J$27>ROUNDUP(Assumptions!$K$48,0),MIN(J$27-ROUNDUP(Assumptions!$K$48,0),999),0) -> 4 | ... V29: =IF(V$27>ROUNDUP(Assumptions!$K$48,0),MIN(V$27-ROUNDUP(Assumptions!$K$48,0),999),0) -> 16
A30: Programme volume | B30: units | C30: =IF(OR(C29=0,C29>Assumptions!$K$47),0,MIN(Assumptions!$K$29*Assumptions!$K$46*INDEX(Assumptions!$C$61:$Q$61,MIN(C29,15)),Assumptions!$K$33)) -> 0 | D30: =IF(OR(D29=0,D29>Assumptions!$K$47),0,MIN(Assumptions!$K$29*Assumptions!$K$46*INDEX(Assumptions!$C$61:$Q$61,MIN(D29,15)),Assumptions!$K$33)) -> 0 | E30: =IF(OR(E29=0,E29>Assumptions!$K$47),0,MIN(Assumptions!$K$29*Assumptions!$K$46*INDEX(Assumptions!$C$61:$Q$61,MIN(E29,15)),Assumptions!$K$33)) -> 0 | F30: =IF(OR(F29=0,F29>Assumptions!$K$47),0,MIN(Assumptions!$K$29*Assumptions!$K$46*INDEX(Assumptions!$C$61:$Q$61,MIN(F29,15)),Assumptions!$K$33)) -> 0 | G30: =IF(OR(G29=0,G29>Assumptions!$K$47),0,MIN(Assumptions!$K$29*Assumptions!$K$46*INDEX(Assumptions!$C$61:$Q$61,MIN(G29,15)),Assumptions!$K$33)) -> 240000 | H30: =IF(OR(H29=0,H29>Assumptions!$K$47),0,MIN(Assumptions!$K$29*Assumptions!$K$46*INDEX(Assumptions!$C$61:$Q$61,MIN(H29,15)),Assumptions!$K$33)) -> 340000 | I30: =IF(OR(I29=0,I29>Assumptions!$K$47),0,MIN(Assumptions!$K$29*Assumptions!$K$46*INDEX(Assumptions!$C$61:$Q$61,MIN(I29,15)),Assumptions!$K$33)) -> 400000 | J30: =IF(OR(J29=0,J29>Assumptions!$K$47),0,MIN(Assumptions!$K$29*Assumptions!$K$46*INDEX(Assumptions!$C$61:$Q$61,MIN(J29,15)),Assumptions!$K$33)) -> 400000 | ... V30: =IF(OR(V29=0,V29>Assumptions!$K$47),0,MIN(Assumptions!$K$29*Assumptions!$K$46*INDEX(Assumptions!$C$61:$Q$61,MIN(V29,15)),Assumptions!$K$33)) -> 0
A31: Cumulative volume | B31: units | C31: =C30 -> 0 | D31: =C31+D30 -> 0 | E31: =D31+E30 -> 0 | F31: =E31+F30 -> 0 | G31: =F31+G30 -> 240000 | H31: =G31+H30 -> 580000 | I31: =H31+I30 -> 980000 | J31: =I31+J30 -> 1380000 | K31: =J31+K30 -> 1780000 | ... V31: =U31+V30 -> 3328000
A32: Net realisation per unit | B32: INR | C32: =IF(C30=0,0,Assumptions!$K$36*(1+Assumptions!$K$49)^(C29-1)) -> 0 | D32: =IF(D30=0,0,Assumptions!$K$36*(1+Assumptions!$K$49)^(D29-1)) -> 0 | E32: =IF(E30=0,0,Assumptions!$K$36*(1+Assumptions!$K$49)^(E29-1)) -> 0 | F32: =IF(F30=0,0,Assumptions!$K$36*(1+Assumptions!$K$49)^(F29-1)) -> 0 | G32: =IF(G30=0,0,Assumptions!$K$36*(1+Assumptions!$K$49)^(G29-1)) -> 700000 | H32: =IF(H30=0,0,Assumptions!$K$36*(1+Assumptions!$K$49)^(H29-1)) -> 707000 | I32: =IF(I30=0,0,Assumptions!$K$36*(1+Assumptions!$K$49)^(I29-1)) -> 714070 | J32: =IF(J30=0,0,Assumptions!$K$36*(1+Assumptions!$K$49)^(J29-1)) -> 721210.7 | ... V32: =IF(V30=0,0,Assumptions!$K$36*(1+Assumptions!$K$49)^(V29-1)) -> 0
A33: Revenue | B33: INR cr | C33: =C30*C32/10000000 -> 0 | D33: =D30*D32/10000000 -> 0 | E33: =E30*E32/10000000 -> 0 | F33: =F30*F32/10000000 -> 0 | G33: =G30*G32/10000000 -> 16800 | H33: =H30*H32/10000000 -> 24038 | I33: =I30*I32/10000000 -> 28562.8 | J33: =J30*J32/10000000 -> 28848.428 | ... V33: =V30*V32/10000000 -> 0
A34: Non-battery BOM per unit (after platform scale benefit) | B34: INR | C34: =IF(C30=0,0,Assumptions!$K$36*Assumptions!$K$37*(1-LOG(MAX(Assumptions!$K$29,1),2)*Assumptions!$K$28)*(1+Assumptions!$K$50)^(C29-1)) -> 0 | D34: =IF(D30=0,0,Assumptions!$K$36*Assumptions!$K$37*(1-LOG(MAX(Assumptions!$K$29,1),2)*Assumptions!$K$28)*(1+Assumptions!$K$50)^(D29-1)) -> 0 | E34: =IF(E30=0,0,Assumptions!$K$36*Assumptions!$K$37*(1-LOG(MAX(Assumptions!$K$29,1),2)*Assumptions!$K$28)*(1+Assumptions!$K$50)^(E29-1)) -> 0 | F34: =IF(F30=0,0,Assumptions!$K$36*Assumptions!$K$37*(1-LOG(MAX(Assumptions!$K$29,1),2)*Assumptions!$K$28)*(1+Assumptions!$K$50)^(F29-1)) -> 0 | G34: =IF(G30=0,0,Assumptions!$K$36*Assumptions!$K$37*(1-LOG(MAX(Assumptions!$K$29,1),2)*Assumptions!$K$28)*(1+Assumptions!$K$50)^(G29-1)) -> 455700 | H34: =IF(H30=0,0,Assumptions!$K$36*Assumptions!$K$37*(1-LOG(MAX(Assumptions!$K$29,1),2)*Assumptions!$K$28)*(1+Assumptions!$K$50)^(H29-1)) -> 451143 | I34: =IF(I30=0,0,Assumptions!$K$36*Assumptions!$K$37*(1-LOG(MAX(Assumptions!$K$29,1),2)*Assumptions!$K$28)*(1+Assumptions!$K$50)^(I29-1)) -> 446631.57 | J34: =IF(J30=0,0,Assumptions!$K$36*Assumptions!$K$37*(1-LOG(MAX(Assumptions!$K$29,1),2)*Assumptions!$K$28)*(1+Assumptions!$K$50)^(J29-1)) -> 442165.25 | ... V34: =IF(V30=0,0,Assumptions!$K$36*Assumptions!$K$37*(1-LOG(MAX(Assumptions!$K$29,1),2)*Assumptions!$K$28)*(1+Assumptions!$K$50)^(V29-1)) -> 0
A35: Battery pack per unit (after platform scale benefit) | B35: INR | C35: =IF(C30=0,0,Assumptions!$K$38*Assumptions!$K$39*(1-LOG(MAX(Assumptions!$K$29,1),2)*Assumptions!$K$28)*(1+Assumptions!$K$51)^(C29-1)) -> 0 | D35: =IF(D30=0,0,Assumptions!$K$38*Assumptions!$K$39*(1-LOG(MAX(Assumptions!$K$29,1),2)*Assumptions!$K$28)*(1+Assumptions!$K$51)^(D29-1)) -> 0 | E35: =IF(E30=0,0,Assumptions!$K$38*Assumptions!$K$39*(1-LOG(MAX(Assumptions!$K$29,1),2)*Assumptions!$K$28)*(1+Assumptions!$K$51)^(E29-1)) -> 0 | F35: =IF(F30=0,0,Assumptions!$K$38*Assumptions!$K$39*(1-LOG(MAX(Assumptions!$K$29,1),2)*Assumptions!$K$28)*(1+Assumptions!$K$51)^(F29-1)) -> 0 | G35: =IF(G30=0,0,Assumptions!$K$38*Assumptions!$K$39*(1-LOG(MAX(Assumptions!$K$29,1),2)*Assumptions!$K$28)*(1+Assumptions!$K$51)^(G29-1)) -> 0 | H35: =IF(H30=0,0,Assumptions!$K$38*Assumptions!$K$39*(1-LOG(MAX(Assumptions!$K$29,1),2)*Assumptions!$K$28)*(1+Assumptions!$K$51)^(H29-1)) -> 0 | I35: =IF(I30=0,0,Assumptions!$K$38*Assumptions!$K$39*(1-LOG(MAX(Assumptions!$K$29,1),2)*Assumptions!$K$28)*(1+Assumptions!$K$51)^(I29-1)) -> 0 | J35: =IF(J30=0,0,Assumptions!$K$38*Assumptions!$K$39*(1-LOG(MAX(Assumptions!$K$29,1),2)*Assumptions!$K$28)*(1+Assumptions!$K$51)^(J29-1)) -> 0 | ... V35: =IF(V30=0,0,Assumptions!$K$38*Assumptions!$K$39*(1-LOG(MAX(Assumptions!$K$29,1),2)*Assumptions!$K$28)*(1+Assumptions!$K$51)^(V29-1)) -> 0
A36: Conversion, warranty & variable selling per unit | B36: INR | C36: =IF(C30=0,0,C32*(Assumptions!$K$40+Assumptions!$K$41+Assumptions!$K$42)) -> 0 | D36: =IF(D30=0,0,D32*(Assumptions!$K$40+Assumptions!$K$41+Assumptions!$K$42)) -> 0 | E36: =IF(E30=0,0,E32*(Assumptions!$K$40+Assumptions!$K$41+Assumptions!$K$42)) -> 0 | F36: =IF(F30=0,0,F32*(Assumptions!$K$40+Assumptions!$K$41+Assumptions!$K$42)) -> 0 | G36: =IF(G30=0,0,G32*(Assumptions!$K$40+Assumptions!$K$41+Assumptions!$K$42)) -> 70000 | H36: =IF(H30=0,0,H32*(Assumptions!$K$40+Assumptions!$K$41+Assumptions!$K$42)) -> 70700 | I36: =IF(I30=0,0,I32*(Assumptions!$K$40+Assumptions!$K$41+Assumptions!$K$42)) -> 71407 | J36: =IF(J30=0,0,J32*(Assumptions!$K$40+Assumptions!$K$41+Assumptions!$K$42)) -> 72121.07 | ... V36: =IF(V30=0,0,V32*(Assumptions!$K$40+Assumptions!$K$41+Assumptions!$K$42)) -> 0
A37: Contribution per unit | B37: INR | C37: =C32-C34-C35-C36 -> 0 | D37: =D32-D34-D35-D36 -> 0 | E37: =E32-E34-E35-E36 -> 0 | F37: =F32-F34-F35-F36 -> 0 | G37: =G32-G34-G35-G36 -> 174300 | H37: =H32-H34-H35-H36 -> 185157 | I37: =I32-I34-I35-I36 -> 196031.43 | J37: =J32-J34-J35-J36 -> 206924.38 | ... V37: =V32-V34-V35-V36 -> 0
A38: Contribution margin | B38: % | C38: =IFERROR(C37/C32,0) -> 0 | D38: =IFERROR(D37/D32,0) -> 0 | E38: =IFERROR(E37/E32,0) -> 0 | F38: =IFERROR(F37/F32,0) -> 0 | G38: =IFERROR(G37/G32,0) -> 0.249 | H38: =IFERROR(H37/H32,0) -> 0.26189109 | I38: =IFERROR(I37/I32,0) -> 0.27452691 | J38: =IFERROR(J37/J32,0) -> 0.28691251 | ... V38: =IFERROR(V37/V32,0) -> 0
A39: Contribution | B39: INR cr | C39: =C30*C37/10000000 -> 0 | D39: =D30*D37/10000000 -> 0 | E39: =E30*E37/10000000 -> 0 | F39: =F30*F37/10000000 -> 0 | G39: =G30*G37/10000000 -> 4183.2 | H39: =H30*H37/10000000 -> 6295.338 | I39: =I30*I37/10000000 -> 7841.2572 | J39: =J30*J37/10000000 -> 8276.975 | ... V39: =V30*V37/10000000 -> 0
A40: Fixed manufacturing overhead | B40: INR cr | C40: =IF(C30=0,0,-Assumptions!$K$43) -> 0 | D40: =IF(D30=0,0,-Assumptions!$K$43) -> 0 | E40: =IF(E30=0,0,-Assumptions!$K$43) -> 0 | F40: =IF(F30=0,0,-Assumptions!$K$43) -> 0 | G40: =IF(G30=0,0,-Assumptions!$K$43) -> -450 | H40: =IF(H30=0,0,-Assumptions!$K$43) -> -450 | I40: =IF(I30=0,0,-Assumptions!$K$43) -> -450 | J40: =IF(J30=0,0,-Assumptions!$K$43) -> -450 | ... V40: =IF(V30=0,0,-Assumptions!$K$43) -> 0
A41: Corporate SG&A allocated | B41: INR cr | C41: =-C33*Assumptions!$K$44 -> 0 | D41: =-D33*Assumptions!$K$44 -> 0 | E41: =-E33*Assumptions!$K$44 -> 0 | F41: =-F33*Assumptions!$K$44 -> 0 | G41: =-G33*Assumptions!$K$44 -> -840 | H41: =-H33*Assumptions!$K$44 -> -1201.9 | I41: =-I33*Assumptions!$K$44 -> -1428.14 | J41: =-J33*Assumptions!$K$44 -> -1442.4214 | ... V41: =-V33*Assumptions!$K$44 -> 0
A43: EBITDA | B43: INR cr | C43: =C39+C40+C41 -> 0 | D43: =D39+D40+D41 -> 0 | E43: =E39+E40+E41 -> 0 | F43: =F39+F40+F41 -> 0 | G43: =G39+G40+G41 -> 2893.2 | H43: =H39+H40+H41 -> 4643.438 | I43: =I39+I40+I41 -> 5963.1172 | J43: =J39+J40+J41 -> 6384.5536 | ... V43: =V39+V40+V41 -> 0
A44: Amortisation of development investment | B44: INR cr | C44: =IF(AND(C29>=1,C29<=Assumptions!$K$55,C29<=Assumptions!$K$47),-$D$7/Assumptions!$K$55,0) -> 0 | D44: =IF(AND(D29>=1,D29<=Assumptions!$K$55,D29<=Assumptions!$K$47),-$D$7/Assumptions!$K$55,0) -> 0 | E44: =IF(AND(E29>=1,E29<=Assumptions!$K$55,E29<=Assumptions!$K$47),-$D$7/Assumptions!$K$55,0) -> 0 | F44: =IF(AND(F29>=1,F29<=Assumptions!$K$55,F29<=Assumptions!$K$47),-$D$7/Assumptions!$K$55,0) -> 0 | G44: =IF(AND(G29>=1,G29<=Assumptions!$K$55,G29<=Assumptions!$K$47),-$D$7/Assumptions!$K$55,0) -> -428.446 | H44: =IF(AND(H29>=1,H29<=Assumptions!$K$55,H29<=Assumptions!$K$47),-$D$7/Assumptions!$K$55,0) -> -428.446 | I44: =IF(AND(I29>=1,I29<=Assumptions!$K$55,I29<=Assumptions!$K$47),-$D$7/Assumptions!$K$55,0) -> -428.446 | J44: =IF(AND(J29>=1,J29<=Assumptions!$K$55,J29<=Assumptions!$K$47),-$D$7/Assumptions!$K$55,0) -> -428.446 | ... V44: =IF(AND(V29>=1,V29<=Assumptions!$K$55,V29<=Assumptions!$K$47),-$D$7/Assumptions!$K$55,0) -> 0
A45: Depreciation of capacity capex | B45: INR cr | C45: =IF(AND(C29>=1,C29<=Assumptions!$K$56,C29<=Assumptions!$K$47),-$D$8/Assumptions!$K$56,0) -> 0 | D45: =IF(AND(D29>=1,D29<=Assumptions!$K$56,D29<=Assumptions!$K$47),-$D$8/Assumptions!$K$56,0) -> 0 | E45: =IF(AND(E29>=1,E29<=Assumptions!$K$56,E29<=Assumptions!$K$47),-$D$8/Assumptions!$K$56,0) -> 0 | F45: =IF(AND(F29>=1,F29<=Assumptions!$K$56,F29<=Assumptions!$K$47),-$D$8/Assumptions!$K$56,0) -> 0 | G45: =IF(AND(G29>=1,G29<=Assumptions!$K$56,G29<=Assumptions!$K$47),-$D$8/Assumptions!$K$56,0) -> -453.33333 | H45: =IF(AND(H29>=1,H29<=Assumptions!$K$56,H29<=Assumptions!$K$47),-$D$8/Assumptions!$K$56,0) -> -453.33333 | I45: =IF(AND(I29>=1,I29<=Assumptions!$K$56,I29<=Assumptions!$K$47),-$D$8/Assumptions!$K$56,0) -> -453.33333 | J45: =IF(AND(J29>=1,J29<=Assumptions!$K$56,J29<=Assumptions!$K$47),-$D$8/Assumptions!$K$56,0) -> -453.33333 | ... V45: =IF(AND(V29>=1,V29<=Assumptions!$K$56,V29<=Assumptions!$K$47),-$D$8/Assumptions!$K$56,0) -> 0
A46: EBIT | B46: INR cr | C46: =C43+C44+C45 -> 0 | D46: =D43+D44+D45 -> 0 | E46: =E43+E44+E45 -> 0 | F46: =F43+F44+F45 -> 0 | G46: =G43+G44+G45 -> 2011.4207 | H46: =H43+H44+H45 -> 3761.6587 | I46: =I43+I44+I45 -> 5081.3379 | J46: =J43+J44+J45 -> 5502.7743 | ... V46: =V43+V44+V45 -> 0
A47: Tax | B47: INR cr | C47: =-MAX(0,C46)*Assumptions!$K$54 -> 0 | D47: =-MAX(0,D46)*Assumptions!$K$54 -> 0 | E47: =-MAX(0,E46)*Assumptions!$K$54 -> 0 | F47: =-MAX(0,F46)*Assumptions!$K$54 -> 0 | G47: =-MAX(0,G46)*Assumptions!$K$54 -> -506.87801 | H47: =-MAX(0,H46)*Assumptions!$K$54 -> -947.93798 | I47: =-MAX(0,I46)*Assumptions!$K$54 -> -1280.4971 | J47: =-MAX(0,J46)*Assumptions!$K$54 -> -1386.6991 | ... V47: =-MAX(0,V46)*Assumptions!$K$54 -> 0
A48: Helper: year if cumulative FCF positive | B48: # | C48: =IF(AND(C54>0,C30>0),C27,999) -> 999 | D48: =IF(AND(D54>0,D30>0),D27,999) -> 999 | E48: =IF(AND(E54>0,E30>0),E27,999) -> 999 | F48: =IF(AND(F54>0,F30>0),F27,999) -> 999 | G48: =IF(AND(G54>0,G30>0),G27,999) -> 999 | H48: =IF(AND(H54>0,H30>0),H27,999) -> 999 | I48: =IF(AND(I54>0,I30>0),I27,999) -> 7 | J48: =IF(AND(J54>0,J30>0),J27,999) -> 8 | ... V48: =IF(AND(V54>0,V30>0),V27,999) -> 999
A49: NOPAT | B49: INR cr | C49: =C46+C47 -> 0 | D49: =D46+D47 -> 0 | E49: =E46+E47 -> 0 | F49: =F46+F47 -> 0 | G49: =G46+G47 -> 1504.5427 | H49: =H46+H47 -> 2813.7207 | I49: =I46+I47 -> 3800.8407 | J49: =J46+J47 -> 4116.0752 | ... V49: =V46+V47 -> 0
A50: Add back D&A | B50: INR cr | C50: =-C44-C45 -> 0 | D50: =-D44-D45 -> 0 | E50: =-E44-E45 -> 0 | F50: =-F44-F45 -> 0 | G50: =-G44-G45 -> 881.77933 | H50: =-H44-H45 -> 881.77933 | I50: =-I44-I45 -> 881.77933 | J50: =-J44-J45 -> 881.77933 | ... V50: =-V44-V45 -> 0
A51: Development capex | B51: INR cr | C51: =IF(C28>0,-$D$7/ROUNDUP(Assumptions!$K$48,0),0) -> -856.892 | D51: =IF(D28>0,-$D$7/ROUNDUP(Assumptions!$K$48,0),0) -> -856.892 | E51: =IF(E28>0,-$D$7/ROUNDUP(Assumptions!$K$48,0),0) -> -856.892 | F51: =IF(F28>0,-$D$7/ROUNDUP(Assumptions!$K$48,0),0) -> -856.892 | G51: =IF(G28>0,-$D$7/ROUNDUP(Assumptions!$K$48,0),0) -> 0 | H51: =IF(H28>0,-$D$7/ROUNDUP(Assumptions!$K$48,0),0) -> 0 | I51: =IF(I28>0,-$D$7/ROUNDUP(Assumptions!$K$48,0),0) -> 0 | J51: =IF(J28>0,-$D$7/ROUNDUP(Assumptions!$K$48,0),0) -> 0 | ... V51: =IF(V28>0,-$D$7/ROUNDUP(Assumptions!$K$48,0),0) -> 0
A52: Capacity capex | B52: INR cr | C52: =IF(AND(C28>0,C28>ROUNDUP(Assumptions!$K$48,0)-MIN(2,ROUNDUP(Assumptions!$K$48,0))),-$D$8/MIN(2,ROUNDUP(Assumptions!$K$48,0)),0) -> 0 | D52: =IF(AND(D28>0,D28>ROUNDUP(Assumptions!$K$48,0)-MIN(2,ROUNDUP(Assumptions!$K$48,0))),-$D$8/MIN(2,ROUNDUP(Assumptions!$K$48,0)),0) -> 0 | E52: =IF(AND(E28>0,E28>ROUNDUP(Assumptions!$K$48,0)-MIN(2,ROUNDUP(Assumptions!$K$48,0))),-$D$8/MIN(2,ROUNDUP(Assumptions!$K$48,0)),0) -> -3400 | F52: =IF(AND(F28>0,F28>ROUNDUP(Assumptions!$K$48,0)-MIN(2,ROUNDUP(Assumptions!$K$48,0))),-$D$8/MIN(2,ROUNDUP(Assumptions!$K$48,0)),0) -> -3400 | G52: =IF(AND(G28>0,G28>ROUNDUP(Assumptions!$K$48,0)-MIN(2,ROUNDUP(Assumptions!$K$48,0))),-$D$8/MIN(2,ROUNDUP(Assumptions!$K$48,0)),0) -> 0 | H52: =IF(AND(H28>0,H28>ROUNDUP(Assumptions!$K$48,0)-MIN(2,ROUNDUP(Assumptions!$K$48,0))),-$D$8/MIN(2,ROUNDUP(Assumptions!$K$48,0)),0) -> 0 | I52: =IF(AND(I28>0,I28>ROUNDUP(Assumptions!$K$48,0)-MIN(2,ROUNDUP(Assumptions!$K$48,0))),-$D$8/MIN(2,ROUNDUP(Assumptions!$K$48,0)),0) -> 0 | J52: =IF(AND(J28>0,J28>ROUNDUP(Assumptions!$K$48,0)-MIN(2,ROUNDUP(Assumptions!$K$48,0))),-$D$8/MIN(2,ROUNDUP(Assumptions!$K$48,0)),0) -> 0 | ... V52: =IF(AND(V28>0,V28>ROUNDUP(Assumptions!$K$48,0)-MIN(2,ROUNDUP(Assumptions!$K$48,0))),-$D$8/MIN(2,ROUNDUP(Assumptions!$K$48,0)),0) -> 0
A53: Free cash flow | B53: INR cr | C53: =C49+C50+C51+C52 -> -856.892 | D53: =D49+D50+D51+D52 -> -856.892 | E53: =E49+E50+E51+E52 -> -4256.892 | F53: =F49+F50+F51+F52 -> -4256.892 | G53: =G49+G50+G51+G52 -> 2386.322 | H53: =H49+H50+H51+H52 -> 3695.5 | I53: =I49+I50+I51+I52 -> 4682.6201 | J53: =J49+J50+J51+J52 -> 4997.8545 | ... V53: =V49+V50+V51+V52 -> 0
A54: Cumulative free cash flow | B54: INR cr | C54: =C53 -> -856.892 | D54: =C54+D53 -> -1713.784 | E54: =D54+E53 -> -5970.676 | F54: =E54+F53 -> -10227.568 | G54: =F54+G53 -> -7841.246 | H54: =G54+H53 -> -4145.746 | I54: =H54+I53 -> 536.87407 | J54: =I54+J53 -> 5534.7286 | K54: =J54+K53 -> 10848.297 | ... V54: =U54+V53 -> 34343.278
A55: Discount factor | B55: x | C55: =1/(1+Assumptions!$K$53)^C27 -> 0.9009009 | D55: =1/(1+Assumptions!$K$53)^D27 -> 0.81162243 | E55: =1/(1+Assumptions!$K$53)^E27 -> 0.73119138 | F55: =1/(1+Assumptions!$K$53)^F27 -> 0.65873097 | G55: =1/(1+Assumptions!$K$53)^G27 -> 0.59345133 | H55: =1/(1+Assumptions!$K$53)^H27 -> 0.53464084 | I55: =1/(1+Assumptions!$K$53)^I27 -> 0.48165841 | J55: =1/(1+Assumptions!$K$53)^J27 -> 0.4339265 | ... V55: =1/(1+Assumptions!$K$53)^V27 -> 0.12403391
A56: PV of free cash flow | B56: INR cr | C56: =C53*C55 -> -771.97477 | D56: =D53*D55 -> -695.47277 | E56: =E53*E55 -> -3112.6027 | F56: =F53*F55 -> -2804.1466 | G56: =G53*G55 -> 1416.166 | H56: =H53*H55 -> 1975.7652 | I56: =I53*I55 -> 2255.4233 | J56: =J53*J55 -> 2168.7015 | ... V56: =V53*V55 -> 0
A58: Note: development capex is spread evenly across the development period; capacity capex across its final two years. Working capital is excluded from the cash flow because Indian OEMs typically run it negative, which would flatter the programme.

Sheet Platform Sharing
A1: PLATFORM SHARING | What changes as you put more models on one architecture
A2: Shared route: one platform, N top hats. Standalone route: N dedicated architectures. Same models, same volumes.
A4: Active segment | C4: ='Control Panel'!$C$6 -> Car - ICE
A6: Number of models on the platform | C6: 1 | D6: 2 | E6: 3 | F6: 4 | G6: 5 | H6: 6 | I6: 7 | J6: 8
A7: Platform engineering (base architecture) | B7: INR cr | C7: ='Investment Build'!$D$18 -> 1393.2 | D7: ='Investment Build'!$D$18 -> 1393.2 | E7: ='Investment Build'!$D$18 -> 1393.2 | F7: ='Investment Build'!$D$18 -> 1393.2 | G7: ='Investment Build'!$D$18 -> 1393.2 | H7: ='Investment Build'!$D$18 -> 1393.2 | I7: ='Investment Build'!$D$18 -> 1393.2 | J7: ='Investment Build'!$D$18 -> 1393.2
A8: Incremental platform re-engineering for models 2..N | B8: INR cr | C8: ='Investment Build'!$D$18*Assumptions!$K$26*0 -> 0 | D8: ='Investment Build'!$D$18*Assumptions!$K$26*1 -> 111.456 | E8: ='Investment Build'!$D$18*Assumptions!$K$26*2 -> 222.912 | F8: ='Investment Build'!$D$18*Assumptions!$K$26*3 -> 334.368 | G8: ='Investment Build'!$D$18*Assumptions!$K$26*4 -> 445.824 | H8: ='Investment Build'!$D$18*Assumptions!$K$26*5 -> 557.28 | I8: ='Investment Build'!$D$18*Assumptions!$K$26*6 -> 668.736 | J8: ='Investment Build'!$D$18*Assumptions!$K$26*7 -> 780.192
A9: Top-hat investment (N models) | B9: INR cr | C9: ='Investment Build'!$D$29*1 -> 425 | D9: ='Investment Build'!$D$29*2 -> 850 | E9: ='Investment Build'!$D$29*3 -> 1275 | F9: ='Investment Build'!$D$29*4 -> 1700 | G9: ='Investment Build'!$D$29*5 -> 2125 | H9: ='Investment Build'!$D$29*6 -> 2550 | I9: ='Investment Build'!$D$29*7 -> 2975 | J9: ='Investment Build'!$D$29*8 -> 3400
A10: SHARED ROUTE - total development investment | B10: INR cr | C10: =C7+C8+C9 -> 1818.2 | D10: =D7+D8+D9 -> 2354.656 | E10: =E7+E8+E9 -> 2891.112 | F10: =F7+F8+F9 -> 3427.568 | G10: =G7+G8+G9 -> 3964.024 | H10: =H7+H8+H9 -> 4500.48 | I10: =I7+I8+I9 -> 5036.936 | J10: =J7+J8+J9 -> 5573.392
A11: STANDALONE ROUTE - N dedicated architectures | B11: INR cr | C11: =(1)*('Investment Build'!$D$18*Assumptions!$K$27+'Investment Build'!$D$29) -> 1539.56 | D11: =(2)*('Investment Build'!$D$18*Assumptions!$K$27+'Investment Build'!$D$29) -> 3079.12 | E11: =(3)*('Investment Build'!$D$18*Assumptions!$K$27+'Investment Build'!$D$29) -> 4618.68 | F11: =(4)*('Investment Build'!$D$18*Assumptions!$K$27+'Investment Build'!$D$29) -> 6158.24 | G11: =(5)*('Investment Build'!$D$18*Assumptions!$K$27+'Investment Build'!$D$29) -> 7697.8 | H11: =(6)*('Investment Build'!$D$18*Assumptions!$K$27+'Investment Build'!$D$29) -> 9237.36 | I11: =(7)*('Investment Build'!$D$18*Assumptions!$K$27+'Investment Build'!$D$29) -> 10776.92 | J11: =(8)*('Investment Build'!$D$18*Assumptions!$K$27+'Investment Build'!$D$29) -> 12316.48
A12: Investment saved by sharing | B12: INR cr | C12: =C11-C10 -> -278.64 | D12: =D11-D10 -> 724.464 | E12: =E11-E10 -> 1727.568 | F12: =F11-F10 -> 2730.672 | G12: =G11-G10 -> 3733.776 | H12: =H11-H10 -> 4736.88 | I12: =I11-I10 -> 5739.984 | J12: =J11-J10 -> 6743.088
A13: Saving as % of standalone | B13: % | C13: =IFERROR(C12/C11,0) -> -0.18098678 | D13: =IFERROR(D12/D11,0) -> 0.23528281 | E13: =IFERROR(E12/E11,0) -> 0.37403934 | F13: =IFERROR(F12/F11,0) -> 0.4434176 | G13: =IFERROR(G12/G11,0) -> 0.48504456 | H13: =IFERROR(H12/H11,0) -> 0.51279586 | I13: =IFERROR(I12/I11,0) -> 0.53261822 | J13: =IFERROR(J12/J11,0) -> 0.547485
A15: Lifetime volume | B15: units | C15: =1*Assumptions!$K$46*Assumptions!$K$62 -> 832000 | D15: =2*Assumptions!$K$46*Assumptions!$K$62 -> 1664000 | E15: =3*Assumptions!$K$46*Assumptions!$K$62 -> 2496000 | F15: =4*Assumptions!$K$46*Assumptions!$K$62 -> 3328000 | G15: =5*Assumptions!$K$46*Assumptions!$K$62 -> 4160000 | H15: =6*Assumptions!$K$46*Assumptions!$K$62 -> 4992000 | I15: =7*Assumptions!$K$46*Assumptions!$K$62 -> 5824000 | J15: =8*Assumptions!$K$46*Assumptions!$K$62 -> 6656000
A16: Development investment per unit - SHARED | B16: INR | C16: =IFERROR(C10*10000000/C15,0) -> 21853.365 | D16: =IFERROR(D10*10000000/D15,0) -> 14150.577 | E16: =IFERROR(E10*10000000/E15,0) -> 11582.981 | F16: =IFERROR(F10*10000000/F15,0) -> 10299.183 | G16: =IFERROR(G10*10000000/G15,0) -> 9528.9038 | H16: =IFERROR(H10*10000000/H15,0) -> 9015.3846 | I16: =IFERROR(I10*10000000/I15,0) -> 8648.5852 | J16: =IFERROR(J10*10000000/J15,0) -> 8373.4856
A17: Development investment per unit - STANDALONE | B17: INR | C17: =IFERROR(C11*10000000/C15,0) -> 18504.327 | D17: =IFERROR(D11*10000000/D15,0) -> 18504.327 | E17: =IFERROR(E11*10000000/E15,0) -> 18504.327 | F17: =IFERROR(F11*10000000/F15,0) -> 18504.327 | G17: =IFERROR(G11*10000000/G15,0) -> 18504.327 | H17: =IFERROR(H11*10000000/H15,0) -> 18504.327 | I17: =IFERROR(I11*10000000/I15,0) -> 18504.327 | J17: =IFERROR(J11*10000000/J15,0) -> 18504.327
A18: Development burden per unit, % of net realisation - SHARED | B18: % | C18: =IFERROR(C16/Assumptions!$K$36,0) -> 0.031219093 | D18: =IFERROR(D16/Assumptions!$K$36,0) -> 0.02021511 | E18: =IFERROR(E16/Assumptions!$K$36,0) -> 0.016547115 | F18: =IFERROR(F16/Assumptions!$K$36,0) -> 0.014713118 | G18: =IFERROR(G16/Assumptions!$K$36,0) -> 0.01361272 | H18: =IFERROR(H16/Assumptions!$K$36,0) -> 0.012879121 | I18: =IFERROR(I16/Assumptions!$K$36,0) -> 0.012355122 | J18: =IFERROR(J16/Assumptions!$K$36,0) -> 0.011962122
A20: Component-volume doublings vs a single-model platform | B20: x | C20: =LOG(1,2) -> 0 | D20: =LOG(2,2) -> 1 | E20: =LOG(3,2) -> 1.5849625 | F20: =LOG(4,2) -> 2 | G20: =LOG(5,2) -> 2.3219281 | H20: =LOG(6,2) -> 2.5849625 | I20: =LOG(7,2) -> 2.8073549 | J20: =LOG(8,2) -> 3
A21: BOM benefit from platform scale | B21: % of BOM | C21: =C20*Assumptions!$K$28 -> 0 | D21: =D20*Assumptions!$K$28 -> 0.035 | E21: =E20*Assumptions!$K$28 -> 0.055473688 | F21: =F20*Assumptions!$K$28 -> 0.07 | G21: =G20*Assumptions!$K$28 -> 0.081267483 | H21: =H20*Assumptions!$K$28 -> 0.090473688 | I21: =I20*Assumptions!$K$28 -> 0.098257422 | J21: =J20*Assumptions!$K$28 -> 0.105
A22: Contribution per unit after scale benefit | B22: INR | C22: =Assumptions!$K$36-(Assumptions!$K$36*Assumptions!$K$37+Assumptions!$K$38*Assumptions!$K$39)*(1-C21)-Assumptions!$K$36*(Assumptions!$K$40+Assumptions!$K$41+Assumptions!$K$42) -> 140000 | D22: =Assumptions!$K$36-(Assumptions!$K$36*Assumptions!$K$37+Assumptions!$K$38*Assumptions!$K$39)*(1-D21)-Assumptions!$K$36*(Assumptions!$K$40+Assumptions!$K$41+Assumptions!$K$42) -> 157150 | E22: =Assumptions!$K$36-(Assumptions!$K$36*Assumptions!$K$37+Assumptions!$K$38*Assumptions!$K$39)*(1-E21)-Assumptions!$K$36*(Assumptions!$K$40+Assumptions!$K$41+Assumptions!$K$42) -> 167182.11 | F22: =Assumptions!$K$36-(Assumptions!$K$36*Assumptions!$K$37+Assumptions!$K$38*Assumptions!$K$39)*(1-F21)-Assumptions!$K$36*(Assumptions!$K$40+Assumptions!$K$41+Assumptions!$K$42) -> 174300 | G22: =Assumptions!$K$36-(Assumptions!$K$36*Assumptions!$K$37+Assumptions!$K$38*Assumptions!$K$39)*(1-G21)-Assumptions!$K$36*(Assumptions!$K$40+Assumptions!$K$41+Assumptions!$K$42) -> 179821.07 | H22: =Assumptions!$K$36-(Assumptions!$K$36*Assumptions!$K$37+Assumptions!$K$38*Assumptions!$K$39)*(1-H21)-Assumptions!$K$36*(Assumptions!$K$40+Assumptions!$K$41+Assumptions!$K$42) -> 184332.11 | I22: =Assumptions!$K$36-(Assumptions!$K$36*Assumptions!$K$37+Assumptions!$K$38*Assumptions!$K$39)*(1-I21)-Assumptions!$K$36*(Assumptions!$K$40+Assumptions!$K$41+Assumptions!$K$42) -> 188146.14 | J22: =Assumptions!$K$36-(Assumptions!$K$36*Assumptions!$K$37+Assumptions!$K$38*Assumptions!$K$39)*(1-J21)-Assumptions!$K$36*(Assumptions!$K$40+Assumptions!$K$41+Assumptions!$K$42) -> 191450
A23: Contribution margin after scale benefit | B23: % | C23: =IFERROR(C22/Assumptions!$K$36,0) -> 0.2 | D23: =IFERROR(D22/Assumptions!$K$36,0) -> 0.2245 | E23: =IFERROR(E22/Assumptions!$K$36,0) -> 0.23883158 | F23: =IFERROR(F22/Assumptions!$K$36,0) -> 0.249 | G23: =IFERROR(G22/Assumptions!$K$36,0) -> 0.25688724 | H23: =IFERROR(H22/Assumptions!$K$36,0) -> 0.26333158 | I23: =IFERROR(I22/Assumptions!$K$36,0) -> 0.2687802 | J23: =IFERROR(J22/Assumptions!$K$36,0) -> 0.2735
A25: Break-even volume on development investment | B25: cum. units | C25: =IFERROR(C10*10000000/C22,0) -> 129871.43 | D25: =IFERROR(D10*10000000/D22,0) -> 149834.93 | E25: =IFERROR(E10*10000000/E22,0) -> 172931.9 | F25: =IFERROR(F10*10000000/F22,0) -> 196647.62 | G25: =IFERROR(G10*10000000/G22,0) -> 220442.69 | H25: =IFERROR(H10*10000000/H22,0) -> 244150.63 | I25: =IFERROR(I10*10000000/I22,0) -> 267714.03 | J25: =IFERROR(J10*10000000/J22,0) -> 291114.76
A26: Break-even (development only) as % of lifetime volume | B26: % | C26: =IFERROR(C25/C15,0) -> 0.15609547 | D26: =IFERROR(D25/D15,0) -> 0.090045033 | E26: =IFERROR(E25/E15,0) -> 0.069283615 | F26: =IFERROR(F25/F15,0) -> 0.059088828 | G26: =IFERROR(G25/G15,0) -> 0.052991032 | H26: =IFERROR(H25/H15,0) -> 0.048908379 | I26: =IFERROR(I25/I15,0) -> 0.045967381 | J26: =IFERROR(J25/J15,0) -> 0.043737193
A27: Fully-loaded EBIT margin at plateau volume | B27: % | C27: =IFERROR((C22-Assumptions!$K$44*Assumptions!$K$36-Assumptions!$K$43*10000000/MIN(1*Assumptions!$K$46,Assumptions!$K$33)-C16)/Assumptions!$K$36,0) -> 0.054495192 | D27: =IFERROR((D22-Assumptions!$K$44*Assumptions!$K$36-Assumptions!$K$43*10000000/MIN(2*Assumptions!$K$46,Assumptions!$K$33)-D16)/Assumptions!$K$36,0) -> 0.12214203 | E27: =IFERROR((E22-Assumptions!$K$44*Assumptions!$K$36-Assumptions!$K$43*10000000/MIN(3*Assumptions!$K$46,Assumptions!$K$33)-E16)/Assumptions!$K$36,0) -> 0.15085589 | F27: =IFERROR((F22-Assumptions!$K$44*Assumptions!$K$36-Assumptions!$K$43*10000000/MIN(4*Assumptions!$K$46,Assumptions!$K$33)-F16)/Assumptions!$K$36,0) -> 0.16821545 | G27: =IFERROR((G22-Assumptions!$K$44*Assumptions!$K$36-Assumptions!$K$43*10000000/MIN(5*Assumptions!$K$46,Assumptions!$K$33)-G16)/Assumptions!$K$36,0) -> 0.17720309 | H27: =IFERROR((H22-Assumptions!$K$44*Assumptions!$K$36-Assumptions!$K$43*10000000/MIN(6*Assumptions!$K$46,Assumptions!$K$33)-H16)/Assumptions!$K$36,0) -> 0.18438103 | I27: =IFERROR((I22-Assumptions!$K$44*Assumptions!$K$36-Assumptions!$K$43*10000000/MIN(7*Assumptions!$K$46,Assumptions!$K$33)-I16)/Assumptions!$K$36,0) -> 0.19035365 | J27: =IFERROR((J22-Assumptions!$K$44*Assumptions!$K$36-Assumptions!$K$43*10000000/MIN(8*Assumptions!$K$46,Assumptions!$K$33)-J16)/Assumptions!$K$36,0) -> 0.19546645
A29: How to read this
A30: Three separate effects compound as model count rises. One: the platform engineering bill is paid once, not N times. Two: that bill is spread over N times the volume, so development cost per unit collapses. Three: common components run at N times the volume, so BOM falls and contribution per unit rises. The third effect is the one most models miss, and it is why break-even volume per model falls faster than investment per model.
A34: The saving at N=1 is negative, and that is not an error. A modular, scalable architecture is deliberately over-engineered for flexibility it does not yet use, so it costs more than a dedicated single-model architecture would. Platform strategy is a bet on model count. Make one model and you have simply paid a premium for optionality; make three or more and the bet pays.

Sheet Sensitivities
A1: SENSITIVITIES | Model count, volume and margin
A2: All grids recompute off the active segment. Row and column headers in blue are editable.
A4: Active segment | C4: ='Control Panel'!$C$6 -> Car - ICE
A6: GRID 1 | Development investment per unit (INR) - rows: models on platform, columns: peak volume per model
A7: Peak volume per model (units) -> | C7: =Assumptions!$K$46*0.25 -> 25000 | D7: =Assumptions!$K$46*0.5 -> 50000 | E7: =Assumptions!$K$46*0.75 -> 75000 | F7: =Assumptions!$K$46*1 -> 100000 | G7: =Assumptions!$K$46*1.5 -> 150000 | H7: =Assumptions!$K$46*2 -> 200000
A8: Models on platform | B8: 1 | C8: =IFERROR(('Investment Build'!$D$18*(1+Assumptions!$K$26*0)+'Investment Build'!$D$29*1)*10000000/(1*C$7*Assumptions!$K$62),0) -> 87413.462 | D8: =IFERROR(('Investment Build'!$D$18*(1+Assumptions!$K$26*0)+'Investment Build'!$D$29*1)*10000000/(1*D$7*Assumptions!$K$62),0) -> 43706.731 | E8: =IFERROR(('Investment Build'!$D$18*(1+Assumptions!$K$26*0)+'Investment Build'!$D$29*1)*10000000/(1*E$7*Assumptions!$K$62),0) -> 29137.821 | F8: =IFERROR(('Investment Build'!$D$18*(1+Assumptions!$K$26*0)+'Investment Build'!$D$29*1)*10000000/(1*F$7*Assumptions!$K$62),0) -> 21853.365 | G8: =IFERROR(('Investment Build'!$D$18*(1+Assumptions!$K$26*0)+'Investment Build'!$D$29*1)*10000000/(1*G$7*Assumptions!$K$62),0) -> 14568.91 | H8: =IFERROR(('Investment Build'!$D$18*(1+Assumptions!$K$26*0)+'Investment Build'!$D$29*1)*10000000/(1*H$7*Assumptions!$K$62),0) -> 10926.683
B9: 2 | C9: =IFERROR(('Investment Build'!$D$18*(1+Assumptions!$K$26*1)+'Investment Build'!$D$29*2)*10000000/(2*C$7*Assumptions!$K$62),0) -> 56602.308 | D9: =IFERROR(('Investment Build'!$D$18*(1+Assumptions!$K$26*1)+'Investment Build'!$D$29*2)*10000000/(2*D$7*Assumptions!$K$62),0) -> 28301.154 | E9: =IFERROR(('Investment Build'!$D$18*(1+Assumptions!$K$26*1)+'Investment Build'!$D$29*2)*10000000/(2*E$7*Assumptions!$K$62),0) -> 18867.436 | F9: =IFERROR(('Investment Build'!$D$18*(1+Assumptions!$K$26*1)+'Investment Build'!$D$29*2)*10000000/(2*F$7*Assumptions!$K$62),0) -> 14150.577 | G9: =IFERROR(('Investment Build'!$D$18*(1+Assumptions!$K$26*1)+'Investment Build'!$D$29*2)*10000000/(2*G$7*Assumptions!$K$62),0) -> 9433.7179 | H9: =IFERROR(('Investment Build'!$D$18*(1+Assumptions!$K$26*1)+'Investment Build'!$D$29*2)*10000000/(2*H$7*Assumptions!$K$62),0) -> 7075.2885
B10: 3 | C10: =IFERROR(('Investment Build'!$D$18*(1+Assumptions!$K$26*2)+'Investment Build'!$D$29*3)*10000000/(3*C$7*Assumptions!$K$62),0) -> 46331.923 | D10: =IFERROR(('Investment Build'!$D$18*(1+Assumptions!$K$26*2)+'Investment Build'!$D$29*3)*10000000/(3*D$7*Assumptions!$K$62),0) -> 23165.962 | E10: =IFERROR(('Investment Build'!$D$18*(1+Assumptions!$K$26*2)+'Investment Build'!$D$29*3)*10000000/(3*E$7*Assumptions!$K$62),0) -> 15443.974 | F10: =IFERROR(('Investment Build'!$D$18*(1+Assumptions!$K$26*2)+'Investment Build'!$D$29*3)*10000000/(3*F$7*Assumptions!$K$62),0) -> 11582.981 | G10: =IFERROR(('Investment Build'!$D$18*(1+Assumptions!$K$26*2)+'Investment Build'!$D$29*3)*10000000/(3*G$7*Assumptions!$K$62),0) -> 7721.9872 | H10: =IFERROR(('Investment Build'!$D$18*(1+Assumptions!$K$26*2)+'Investment Build'!$D$29*3)*10000000/(3*H$7*Assumptions!$K$62),0) -> 5791.4904
B11: 4 | C11: =IFERROR(('Investment Build'!$D$18*(1+Assumptions!$K$26*3)+'Investment Build'!$D$29*4)*10000000/(4*C$7*Assumptions!$K$62),0) -> 41196.731 | D11: =IFERROR(('Investment Build'!$D$18*(1+Assumptions!$K$26*3)+'Investment Build'!$D$29*4)*10000000/(4*D$7*Assumptions!$K$62),0) -> 20598.365 | E11: =IFERROR(('Investment Build'!$D$18*(1+Assumptions!$K$26*3)+'Investment Build'!$D$29*4)*10000000/(4*E$7*Assumptions!$K$62),0) -> 13732.244 | F11: =IFERROR(('Investment Build'!$D$18*(1+Assumptions!$K$26*3)+'Investment Build'!$D$29*4)*10000000/(4*F$7*Assumptions!$K$62),0) -> 10299.183 | G11: =IFERROR(('Investment Build'!$D$18*(1+Assumptions!$K$26*3)+'Investment Build'!$D$29*4)*10000000/(4*G$7*Assumptions!$K$62),0) -> 6866.1218 | H11: =IFERROR(('Investment Build'!$D$18*(1+Assumptions!$K$26*3)+'Investment Build'!$D$29*4)*10000000/(4*H$7*Assumptions!$K$62),0) -> 5149.5913
B12: 5 | C12: =IFERROR(('Investment Build'!$D$18*(1+Assumptions!$K$26*4)+'Investment Build'!$D$29*5)*10000000/(5*C$7*Assumptions!$K$62),0) -> 38115.615 | D12: =IFERROR(('Investment Build'!$D$18*(1+Assumptions!$K$26*4)+'Investment Build'!$D$29*5)*10000000/(5*D$7*Assumptions!$K$62),0) -> 19057.808 | E12: =IFERROR(('Investment Build'!$D$18*(1+Assumptions!$K$26*4)+'Investment Build'!$D$29*5)*10000000/(5*E$7*Assumptions!$K$62),0) -> 12705.205 | F12: =IFERROR(('Investment Build'!$D$18*(1+Assumptions!$K$26*4)+'Investment Build'!$D$29*5)*10000000/(5*F$7*Assumptions!$K$62),0) -> 9528.9038 | G12: =IFERROR(('Investment Build'!$D$18*(1+Assumptions!$K$26*4)+'Investment Build'!$D$29*5)*10000000/(5*G$7*Assumptions!$K$62),0) -> 6352.6026 | H12: =IFERROR(('Investment Build'!$D$18*(1+Assumptions!$K$26*4)+'Investment Build'!$D$29*5)*10000000/(5*H$7*Assumptions!$K$62),0) -> 4764.4519
B13: 6 | C13: =IFERROR(('Investment Build'!$D$18*(1+Assumptions!$K$26*5)+'Investment Build'!$D$29*6)*10000000/(6*C$7*Assumptions!$K$62),0) -> 36061.538 | D13: =IFERROR(('Investment Build'!$D$18*(1+Assumptions!$K$26*5)+'Investment Build'!$D$29*6)*10000000/(6*D$7*Assumptions!$K$62),0) -> 18030.769 | E13: =IFERROR(('Investment Build'!$D$18*(1+Assumptions!$K$26*5)+'Investment Build'!$D$29*6)*10000000/(6*E$7*Assumptions!$K$62),0) -> 12020.513 | F13: =IFERROR(('Investment Build'!$D$18*(1+Assumptions!$K$26*5)+'Investment Build'!$D$29*6)*10000000/(6*F$7*Assumptions!$K$62),0) -> 9015.3846 | G13: =IFERROR(('Investment Build'!$D$18*(1+Assumptions!$K$26*5)+'Investment Build'!$D$29*6)*10000000/(6*G$7*Assumptions!$K$62),0) -> 6010.2564 | H13: =IFERROR(('Investment Build'!$D$18*(1+Assumptions!$K$26*5)+'Investment Build'!$D$29*6)*10000000/(6*H$7*Assumptions!$K$62),0) -> 4507.6923
B14: 7 | C14: =IFERROR(('Investment Build'!$D$18*(1+Assumptions!$K$26*6)+'Investment Build'!$D$29*7)*10000000/(7*C$7*Assumptions!$K$62),0) -> 34594.341 | D14: =IFERROR(('Investment Build'!$D$18*(1+Assumptions!$K$26*6)+'Investment Build'!$D$29*7)*10000000/(7*D$7*Assumptions!$K$62),0) -> 17297.17 | E14: =IFERROR(('Investment Build'!$D$18*(1+Assumptions!$K$26*6)+'Investment Build'!$D$29*7)*10000000/(7*E$7*Assumptions!$K$62),0) -> 11531.447 | F14: =IFERROR(('Investment Build'!$D$18*(1+Assumptions!$K$26*6)+'Investment Build'!$D$29*7)*10000000/(7*F$7*Assumptions!$K$62),0) -> 8648.5852 | G14: =IFERROR(('Investment Build'!$D$18*(1+Assumptions!$K$26*6)+'Investment Build'!$D$29*7)*10000000/(7*G$7*Assumptions!$K$62),0) -> 5765.7234 | H14: =IFERROR(('Investment Build'!$D$18*(1+Assumptions!$K$26*6)+'Investment Build'!$D$29*7)*10000000/(7*H$7*Assumptions!$K$62),0) -> 4324.2926
B15: 8 | C15: =IFERROR(('Investment Build'!$D$18*(1+Assumptions!$K$26*7)+'Investment Build'!$D$29*8)*10000000/(8*C$7*Assumptions!$K$62),0) -> 33493.942 | D15: =IFERROR(('Investment Build'!$D$18*(1+Assumptions!$K$26*7)+'Investment Build'!$D$29*8)*10000000/(8*D$7*Assumptions!$K$62),0) -> 16746.971 | E15: =IFERROR(('Investment Build'!$D$18*(1+Assumptions!$K$26*7)+'Investment Build'!$D$29*8)*10000000/(8*E$7*Assumptions!$K$62),0) -> 11164.647 | F15: =IFERROR(('Investment Build'!$D$18*(1+Assumptions!$K$26*7)+'Investment Build'!$D$29*8)*10000000/(8*F$7*Assumptions!$K$62),0) -> 8373.4856 | G15: =IFERROR(('Investment Build'!$D$18*(1+Assumptions!$K$26*7)+'Investment Build'!$D$29*8)*10000000/(8*G$7*Assumptions!$K$62),0) -> 5582.3237 | H15: =IFERROR(('Investment Build'!$D$18*(1+Assumptions!$K$26*7)+'Investment Build'!$D$29*8)*10000000/(8*H$7*Assumptions!$K$62),0) -> 4186.7428
A16: Grid 1: total development investment (platform + N top hats) divided by lifetime platform volume. Reading down a column shows the return to model count; reading across a row shows the return to volume. The first added model is worth far more than the eighth.
A18: GRID 2 | Break-even volume PER MODEL on development investment (units) - rows: contribution margin, columns: models on platform
A19: Models on platform -> | C19: 1 | D19: 2 | E19: 3 | F19: 4 | G19: 5 | H19: 6
A20: Contribution margin | B20: 0.1 | C20: =IFERROR(('Investment Build'!$D$18*(1+Assumptions!$K$26*0)+'Investment Build'!$D$29*1)*10000000/($B20*Assumptions!$K$36*1),0) -> 259742.86 | D20: =IFERROR(('Investment Build'!$D$18*(1+Assumptions!$K$26*1)+'Investment Build'!$D$29*2)*10000000/($B20*Assumptions!$K$36*2),0) -> 168189.71 | E20: =IFERROR(('Investment Build'!$D$18*(1+Assumptions!$K$26*2)+'Investment Build'!$D$29*3)*10000000/($B20*Assumptions!$K$36*3),0) -> 137672 | F20: =IFERROR(('Investment Build'!$D$18*(1+Assumptions!$K$26*3)+'Investment Build'!$D$29*4)*10000000/($B20*Assumptions!$K$36*4),0) -> 122413.14 | G20: =IFERROR(('Investment Build'!$D$18*(1+Assumptions!$K$26*4)+'Investment Build'!$D$29*5)*10000000/($B20*Assumptions!$K$36*5),0) -> 113257.83 | H20: =IFERROR(('Investment Build'!$D$18*(1+Assumptions!$K$26*5)+'Investment Build'!$D$29*6)*10000000/($B20*Assumptions!$K$36*6),0) -> 107154.29
B21: 0.14 | C21: =IFERROR(('Investment Build'!$D$18*(1+Assumptions!$K$26*0)+'Investment Build'!$D$29*1)*10000000/($B21*Assumptions!$K$36*1),0) -> 185530.61 | D21: =IFERROR(('Investment Build'!$D$18*(1+Assumptions!$K$26*1)+'Investment Build'!$D$29*2)*10000000/($B21*Assumptions!$K$36*2),0) -> 120135.51 | E21: =IFERROR(('Investment Build'!$D$18*(1+Assumptions!$K$26*2)+'Investment Build'!$D$29*3)*10000000/($B21*Assumptions!$K$36*3),0) -> 98337.143 | F21: =IFERROR(('Investment Build'!$D$18*(1+Assumptions!$K$26*3)+'Investment Build'!$D$29*4)*10000000/($B21*Assumptions!$K$36*4),0) -> 87437.959 | G21: =IFERROR(('Investment Build'!$D$18*(1+Assumptions!$K$26*4)+'Investment Build'!$D$29*5)*10000000/($B21*Assumptions!$K$36*5),0) -> 80898.449 | H21: =IFERROR(('Investment Build'!$D$18*(1+Assumptions!$K$26*5)+'Investment Build'!$D$29*6)*10000000/($B21*Assumptions!$K$36*6),0) -> 76538.776
B22: 0.18 | C22: =IFERROR(('Investment Build'!$D$18*(1+Assumptions!$K$26*0)+'Investment Build'!$D$29*1)*10000000/($B22*Assumptions!$K$36*1),0) -> 144301.59 | D22: =IFERROR(('Investment Build'!$D$18*(1+Assumptions!$K$26*1)+'Investment Build'!$D$29*2)*10000000/($B22*Assumptions!$K$36*2),0) -> 93438.73 | E22: =IFERROR(('Investment Build'!$D$18*(1+Assumptions!$K$26*2)+'Investment Build'!$D$29*3)*10000000/($B22*Assumptions!$K$36*3),0) -> 76484.444 | F22: =IFERROR(('Investment Build'!$D$18*(1+Assumptions!$K$26*3)+'Investment Build'!$D$29*4)*10000000/($B22*Assumptions!$K$36*4),0) -> 68007.302 | G22: =IFERROR(('Investment Build'!$D$18*(1+Assumptions!$K$26*4)+'Investment Build'!$D$29*5)*10000000/($B22*Assumptions!$K$36*5),0) -> 62921.016 | H22: =IFERROR(('Investment Build'!$D$18*(1+Assumptions!$K$26*5)+'Investment Build'!$D$29*6)*10000000/($B22*Assumptions!$K$36*6),0) -> 59530.159
B23: 0.22 | C23: =IFERROR(('Investment Build'!$D$18*(1+Assumptions!$K$26*0)+'Investment Build'!$D$29*1)*10000000/($B23*Assumptions!$K$36*1),0) -> 118064.94 | D23: =IFERROR(('Investment Build'!$D$18*(1+Assumptions!$K$26*1)+'Investment Build'!$D$29*2)*10000000/($B23*Assumptions!$K$36*2),0) -> 76449.87 | E23: =IFERROR(('Investment Build'!$D$18*(1+Assumptions!$K$26*2)+'Investment Build'!$D$29*3)*10000000/($B23*Assumptions!$K$36*3),0) -> 62578.182 | F23: =IFERROR(('Investment Build'!$D$18*(1+Assumptions!$K$26*3)+'Investment Build'!$D$29*4)*10000000/($B23*Assumptions!$K$36*4),0) -> 55642.338 | G23: =IFERROR(('Investment Build'!$D$18*(1+Assumptions!$K$26*4)+'Investment Build'!$D$29*5)*10000000/($B23*Assumptions!$K$36*5),0) -> 51480.831 | H23: =IFERROR(('Investment Build'!$D$18*(1+Assumptions!$K$26*5)+'Investment Build'!$D$29*6)*10000000/($B23*Assumptions!$K$36*6),0) -> 48706.494
B24: 0.26 | C24: =IFERROR(('Investment Build'!$D$18*(1+Assumptions!$K$26*0)+'Investment Build'!$D$29*1)*10000000/($B24*Assumptions!$K$36*1),0) -> 99901.099 | D24: =IFERROR(('Investment Build'!$D$18*(1+Assumptions!$K$26*1)+'Investment Build'!$D$29*2)*10000000/($B24*Assumptions!$K$36*2),0) -> 64688.352 | E24: =IFERROR(('Investment Build'!$D$18*(1+Assumptions!$K$26*2)+'Investment Build'!$D$29*3)*10000000/($B24*Assumptions!$K$36*3),0) -> 52950.769 | F24: =IFERROR(('Investment Build'!$D$18*(1+Assumptions!$K$26*3)+'Investment Build'!$D$29*4)*10000000/($B24*Assumptions!$K$36*4),0) -> 47081.978 | G24: =IFERROR(('Investment Build'!$D$18*(1+Assumptions!$K$26*4)+'Investment Build'!$D$29*5)*10000000/($B24*Assumptions!$K$36*5),0) -> 43560.703 | H24: =IFERROR(('Investment Build'!$D$18*(1+Assumptions!$K$26*5)+'Investment Build'!$D$29*6)*10000000/($B24*Assumptions!$K$36*6),0) -> 41213.187
B25: 0.3 | C25: =IFERROR(('Investment Build'!$D$18*(1+Assumptions!$K$26*0)+'Investment Build'!$D$29*1)*10000000/($B25*Assumptions!$K$36*1),0) -> 86580.952 | D25: =IFERROR(('Investment Build'!$D$18*(1+Assumptions!$K$26*1)+'Investment Build'!$D$29*2)*10000000/($B25*Assumptions!$K$36*2),0) -> 56063.238 | E25: =IFERROR(('Investment Build'!$D$18*(1+Assumptions!$K$26*2)+'Investment Build'!$D$29*3)*10000000/($B25*Assumptions!$K$36*3),0) -> 45890.667 | F25: =IFERROR(('Investment Build'!$D$18*(1+Assumptions!$K$26*3)+'Investment Build'!$D$29*4)*10000000/($B25*Assumptions!$K$36*4),0) -> 40804.381 | G25: =IFERROR(('Investment Build'!$D$18*(1+Assumptions!$K$26*4)+'Investment Build'!$D$29*5)*10000000/($B25*Assumptions!$K$36*5),0) -> 37752.61 | H25: =IFERROR(('Investment Build'!$D$18*(1+Assumptions!$K$26*5)+'Investment Build'!$D$29*6)*10000000/($B25*Assumptions!$K$36*6),0) -> 35718.095
A26: Grid 2: units each individual model must sell to repay the whole platform's development bill. It falls with model count because the platform is paid for once, and falls with margin because each unit repays more.
A29: GRID 3 | Fully-loaded programme EBIT margin - rows: models on platform, columns: peak volume per model
A30: Peak volume per model (units) -> | C30: =Assumptions!$K$46*0.25 -> 25000 | D30: =Assumptions!$K$46*0.5 -> 50000 | E30: =Assumptions!$K$46*0.75 -> 75000 | F30: =Assumptions!$K$46*1 -> 100000 | G30: =Assumptions!$K$46*1.5 -> 150000 | H30: =Assumptions!$K$46*2 -> 200000
A31: Models on platform | B31: 1 | C31: =IFERROR(((Assumptions!$K$36-(Assumptions!$K$36*Assumptions!$K$37+Assumptions!$K$38*Assumptions!$K$39)*(1-LOG(1,2)*Assumptions!$K$28)-Assumptions!$K$36*(Assumptions!$K$40+Assumptions!$K$41+Assumptions!$K$42))-(Assumptions!$K$43*10000000/MIN(1*C$30,Assumptions!$K$33))-(Assumptions!$K$44*Assumptions!$K$36)-(('Investment Build'!$D$18*(1+Assumptions!$K$26*0)+'Investment Build'!$D$29*1)*10000000/(1*C$30*Assumptions!$K$62)))/Assumptions!$K$36,0) -> -0.23201923 | D31: =IFERROR(((Assumptions!$K$36-(Assumptions!$K$36*Assumptions!$K$37+Assumptions!$K$38*Assumptions!$K$39)*(1-LOG(1,2)*Assumptions!$K$28)-Assumptions!$K$36*(Assumptions!$K$40+Assumptions!$K$41+Assumptions!$K$42))-(Assumptions!$K$43*10000000/MIN(1*D$30,Assumptions!$K$33))-(Assumptions!$K$44*Assumptions!$K$36)-(('Investment Build'!$D$18*(1+Assumptions!$K$26*0)+'Investment Build'!$D$29*1)*10000000/(1*D$30*Assumptions!$K$62)))/Assumptions!$K$36,0) -> -0.041009615 | E31: =IFERROR(((Assumptions!$K$36-(Assumptions!$K$36*Assumptions!$K$37+Assumptions!$K$38*Assumptions!$K$39)*(1-LOG(1,2)*Assumptions!$K$28)-Assumptions!$K$36*(Assumptions!$K$40+Assumptions!$K$41+Assumptions!$K$42))-(Assumptions!$K$43*10000000/MIN(1*E$30,Assumptions!$K$33))-(Assumptions!$K$44*Assumptions!$K$36)-(('Investment Build'!$D$18*(1+Assumptions!$K$26*0)+'Investment Build'!$D$29*1)*10000000/(1*E$30*Assumptions!$K$62)))/Assumptions!$K$36,0) -> 0.022660256 | F31: =IFERROR(((Assumptions!$K$36-(Assumptions!$K$36*Assumptions!$K$37+Assumptions!$K$38*Assumptions!$K$39)*(1-LOG(1,2)*Assumptions!$K$28)-Assumptions!$K$36*(Assumptions!$K$40+Assumptions!$K$41+Assumptions!$K$42))-(Assumptions!$K$43*10000000/MIN(1*F$30,Assumptions!$K$33))-(Assumptions!$K$44*Assumptions!$K$36)-(('Investment Build'!$D$18*(1+Assumptions!$K$26*0)+'Investment Build'!$D$29*1)*10000000/(1*F$30*Assumptions!$K$62)))/Assumptions!$K$36,0) -> 0.054495192 | G31: =IFERROR(((Assumptions!$K$36-(Assumptions!$K$36*Assumptions!$K$37+Assumptions!$K$38*Assumptions!$K$39)*(1-LOG(1,2)*Assumptions!$K$28)-Assumptions!$K$36*(Assumptions!$K$40+Assumptions!$K$41+Assumptions!$K$42))-(Assumptions!$K$43*10000000/MIN(1*G$30,Assumptions!$K$33))-(Assumptions!$K$44*Assumptions!$K$36)-(('Investment Build'!$D$18*(1+Assumptions!$K$26*0)+'Investment Build'!$D$29*1)*10000000/(1*G$30*Assumptions!$K$62)))/Assumptions!$K$36,0) -> 0.086330128 | H31: =IFERROR(((Assumptions!$K$36-(Assumptions!$K$36*Assumptions!$K$37+Assumptions!$K$38*Assumptions!$K$39)*(1-LOG(1,2)*Assumptions!$K$28)-Assumptions!$K$36*(Assumptions!$K$40+Assumptions!$K$41+Assumptions!$K$42))-(Assumptions!$K$43*10000000/MIN(1*H$30,Assumptions!$K$33))-(Assumptions!$K$44*Assumptions!$K$36)-(('Investment Build'!$D$18*(1+Assumptions!$K$26*0)+'Investment Build'!$D$29*1)*10000000/(1*H$30*Assumptions!$K$62)))/Assumptions!$K$36,0) -> 0.1022476
B32: 2 | C32: =IFERROR(((Assumptions!$K$36-(Assumptions!$K$36*Assumptions!$K$37+Assumptions!$K$38*Assumptions!$K$39)*(1-LOG(2,2)*Assumptions!$K$28)-Assumptions!$K$36*(Assumptions!$K$40+Assumptions!$K$41+Assumptions!$K$42))-(Assumptions!$K$43*10000000/MIN(2*C$30,Assumptions!$K$33))-(Assumptions!$K$44*Assumptions!$K$36)-(('Investment Build'!$D$18*(1+Assumptions!$K$26*1)+'Investment Build'!$D$29*2)*10000000/(2*C$30*Assumptions!$K$62)))/Assumptions!$K$36,0) -> -0.034931868 | D32: =IFERROR(((Assumptions!$K$36-(Assumptions!$K$36*Assumptions!$K$37+Assumptions!$K$38*Assumptions!$K$39)*(1-LOG(2,2)*Assumptions!$K$28)-Assumptions!$K$36*(Assumptions!$K$40+Assumptions!$K$41+Assumptions!$K$42))-(Assumptions!$K$43*10000000/MIN(2*D$30,Assumptions!$K$33))-(Assumptions!$K$44*Assumptions!$K$36)-(('Investment Build'!$D$18*(1+Assumptions!$K$26*1)+'Investment Build'!$D$29*2)*10000000/(2*D$30*Assumptions!$K$62)))/Assumptions!$K$36,0) -> 0.069784066 | E32: =IFERROR(((Assumptions!$K$36-(Assumptions!$K$36*Assumptions!$K$37+Assumptions!$K$38*Assumptions!$K$39)*(1-LOG(2,2)*Assumptions!$K$28)-Assumptions!$K$36*(Assumptions!$K$40+Assumptions!$K$41+Assumptions!$K$42))-(Assumptions!$K$43*10000000/MIN(2*E$30,Assumptions!$K$33))-(Assumptions!$K$44*Assumptions!$K$36)-(('Investment Build'!$D$18*(1+Assumptions!$K$26*1)+'Investment Build'!$D$29*2)*10000000/(2*E$30*Assumptions!$K$62)))/Assumptions!$K$36,0) -> 0.10468938 | F32: =IFERROR(((Assumptions!$K$36-(Assumptions!$K$36*Assumptions!$K$37+Assumptions!$K$38*Assumptions!$K$39)*(1-LOG(2,2)*Assumptions!$K$28)-Assumptions!$K$36*(Assumptions!$K$40+Assumptions!$K$41+Assumptions!$K$42))-(Assumptions!$K$43*10000000/MIN(2*F$30,Assumptions!$K$33))-(Assumptions!$K$44*Assumptions!$K$36)-(('Investment Build'!$D$18*(1+Assumptions!$K$26*1)+'Investment Build'!$D$29*2)*10000000/(2*F$30*Assumptions!$K$62)))/Assumptions!$K$36,0) -> 0.12214203 | G32: =IFERROR(((Assumptions!$K$36-(Assumptions!$K$36*Assumptions!$K$37+Assumptions!$K$38*Assumptions!$K$39)*(1-LOG(2,2)*Assumptions!$K$28)-Assumptions!$K$36*(Assumptions!$K$40+Assumptions!$K$41+Assumptions!$K$42))-(Assumptions!$K$43*10000000/MIN(2*G$30,Assumptions!$K$33))-(Assumptions!$K$44*Assumptions!$K$36)-(('Investment Build'!$D$18*(1+Assumptions!$K$26*1)+'Investment Build'!$D$29*2)*10000000/(2*G$30*Assumptions!$K$62)))/Assumptions!$K$36,0) -> 0.13959469 | H32: =IFERROR(((Assumptions!$K$36-(Assumptions!$K$36*Assumptions!$K$37+Assumptions!$K$38*Assumptions!$K$39)*(1-LOG(2,2)*Assumptions!$K$28)-Assumptions!$K$36*(Assumptions!$K$40+Assumptions!$K$41+Assumptions!$K$42))-(Assumptions!$K$43*10000000/MIN(2*H$30,Assumptions!$K$33))-(Assumptions!$K$44*Assumptions!$K$36)-(('Investment Build'!$D$18*(1+Assumptions!$K$26*1)+'Investment Build'!$D$29*2)*10000000/(2*H$30*Assumptions!$K$62)))/Assumptions!$K$36,0) -> 0.14832102
B33: 3 | C33: =IFERROR(((Assumptions!$K$36-(Assumptions!$K$36*Assumptions!$K$37+Assumptions!$K$38*Assumptions!$K$39)*(1-LOG(3,2)*Assumptions!$K$28)-Assumptions!$K$36*(Assumptions!$K$40+Assumptions!$K$41+Assumptions!$K$42))-(Assumptions!$K$43*10000000/MIN(3*C$30,Assumptions!$K$33))-(Assumptions!$K$44*Assumptions!$K$36)-(('Investment Build'!$D$18*(1+Assumptions!$K$26*2)+'Investment Build'!$D$29*3)*10000000/(3*C$30*Assumptions!$K$62)))/Assumptions!$K$36,0) -> 0.036928834 | D33: =IFERROR(((Assumptions!$K$36-(Assumptions!$K$36*Assumptions!$K$37+Assumptions!$K$38*Assumptions!$K$39)*(1-LOG(3,2)*Assumptions!$K$28)-Assumptions!$K$36*(Assumptions!$K$40+Assumptions!$K$41+Assumptions!$K$42))-(Assumptions!$K$43*10000000/MIN(3*D$30,Assumptions!$K$33))-(Assumptions!$K$44*Assumptions!$K$36)-(('Investment Build'!$D$18*(1+Assumptions!$K$26*2)+'Investment Build'!$D$29*3)*10000000/(3*D$30*Assumptions!$K$62)))/Assumptions!$K$36,0) -> 0.11288021 | E33: =IFERROR(((Assumptions!$K$36-(Assumptions!$K$36*Assumptions!$K$37+Assumptions!$K$38*Assumptions!$K$39)*(1-LOG(3,2)*Assumptions!$K$28)-Assumptions!$K$36*(Assumptions!$K$40+Assumptions!$K$41+Assumptions!$K$42))-(Assumptions!$K$43*10000000/MIN(3*E$30,Assumptions!$K$33))-(Assumptions!$K$44*Assumptions!$K$36)-(('Investment Build'!$D$18*(1+Assumptions!$K$26*2)+'Investment Build'!$D$29*3)*10000000/(3*E$30*Assumptions!$K$62)))/Assumptions!$K$36,0) -> 0.13819733 | F33: =IFERROR(((Assumptions!$K$36-(Assumptions!$K$36*Assumptions!$K$37+Assumptions!$K$38*Assumptions!$K$39)*(1-LOG(3,2)*Assumptions!$K$28)-Assumptions!$K$36*(Assumptions!$K$40+Assumptions!$K$41+Assumptions!$K$42))-(Assumptions!$K$43*10000000/MIN(3*F$30,Assumptions!$K$33))-(Assumptions!$K$44*Assumptions!$K$36)-(('Investment Build'!$D$18*(1+Assumptions!$K$26*2)+'Investment Build'!$D$29*3)*10000000/(3*F$30*Assumptions!$K$62)))/Assumptions!$K$36,0) -> 0.15085589 | G33: =IFERROR(((Assumptions!$K$36-(Assumptions!$K$36*Assumptions!$K$37+Assumptions!$K$38*Assumptions!$K$39)*(1-LOG(3,2)*Assumptions!$K$28)-Assumptions!$K$36*(Assumptions!$K$40+Assumptions!$K$41+Assumptions!$K$42))-(Assumptions!$K$43*10000000/MIN(3*G$30,Assumptions!$K$33))-(Assumptions!$K$44*Assumptions!$K$36)-(('Investment Build'!$D$18*(1+Assumptions!$K$26*2)+'Investment Build'!$D$29*3)*10000000/(3*G$30*Assumptions!$K$62)))/Assumptions!$K$36,0) -> 0.16172874 | H33: =IFERROR(((Assumptions!$K$36-(Assumptions!$K$36*Assumptions!$K$37+Assumptions!$K$38*Assumptions!$K$39)*(1-LOG(3,2)*Assumptions!$K$28)-Assumptions!$K$36*(Assumptions!$K$40+Assumptions!$K$41+Assumptions!$K$42))-(Assumptions!$K$43*10000000/MIN(3*H$30,Assumptions!$K$33))-(Assumptions!$K$44*Assumptions!$K$36)-(('Investment Build'!$D$18*(1+Assumptions!$K$26*2)+'Investment Build'!$D$29*3)*10000000/(3*H$30*Assumptions!$K$62)))/Assumptions!$K$36,0) -> 0.1644866
B34: 4 | C34: =IFERROR(((Assumptions!$K$36-(Assumptions!$K$36*Assumptions!$K$37+Assumptions!$K$38*Assumptions!$K$39)*(1-LOG(4,2)*Assumptions!$K$28)-Assumptions!$K$36*(Assumptions!$K$40+Assumptions!$K$41+Assumptions!$K$42))-(Assumptions!$K$43*10000000/MIN(4*C$30,Assumptions!$K$33))-(Assumptions!$K$44*Assumptions!$K$36)-(('Investment Build'!$D$18*(1+Assumptions!$K$26*3)+'Investment Build'!$D$29*4)*10000000/(4*C$30*Assumptions!$K$62)))/Assumptions!$K$36,0) -> 0.075861813 | D34: =IFERROR(((Assumptions!$K$36-(Assumptions!$K$36*Assumptions!$K$37+Assumptions!$K$38*Assumptions!$K$39)*(1-LOG(4,2)*Assumptions!$K$28)-Assumptions!$K$36*(Assumptions!$K$40+Assumptions!$K$41+Assumptions!$K$42))-(Assumptions!$K$43*10000000/MIN(4*D$30,Assumptions!$K$33))-(Assumptions!$K$44*Assumptions!$K$36)-(('Investment Build'!$D$18*(1+Assumptions!$K$26*3)+'Investment Build'!$D$29*4)*10000000/(4*D$30*Assumptions!$K$62)))/Assumptions!$K$36,0) -> 0.13743091 | E34: =IFERROR(((Assumptions!$K$36-(Assumptions!$K$36*Assumptions!$K$37+Assumptions!$K$38*Assumptions!$K$39)*(1-LOG(4,2)*Assumptions!$K$28)-Assumptions!$K$36*(Assumptions!$K$40+Assumptions!$K$41+Assumptions!$K$42))-(Assumptions!$K$43*10000000/MIN(4*E$30,Assumptions!$K$33))-(Assumptions!$K$44*Assumptions!$K$36)-(('Investment Build'!$D$18*(1+Assumptions!$K$26*3)+'Investment Build'!$D$29*4)*10000000/(4*E$30*Assumptions!$K$62)))/Assumptions!$K$36,0) -> 0.15795394 | F34: =IFERROR(((Assumptions!$K$36-(Assumptions!$K$36*Assumptions!$K$37+Assumptions!$K$38*Assumptions!$K$39)*(1-LOG(4,2)*Assumptions!$K$28)-Assumptions!$K$36*(Assumptions!$K$40+Assumptions!$K$41+Assumptions!$K$42))-(Assumptions!$K$43*10000000/MIN(4*F$30,Assumptions!$K$33))-(Assumptions!$K$44*Assumptions!$K$36)-(('Investment Build'!$D$18*(1+Assumptions!$K$26*3)+'Investment Build'!$D$29*4)*10000000/(4*F$30*Assumptions!$K$62)))/Assumptions!$K$36,0) -> 0.16821545 | G34: =IFERROR(((Assumptions!$K$36-(Assumptions!$K$36*Assumptions!$K$37+Assumptions!$K$38*Assumptions!$K$39)*(1-LOG(4,2)*Assumptions!$K$28)-Assumptions!$K$36*(Assumptions!$K$40+Assumptions!$K$41+Assumptions!$K$42))-(Assumptions!$K$43*10000000/MIN(4*G$30,Assumptions!$K$33))-(Assumptions!$K$44*Assumptions!$K$36)-(('Investment Build'!$D$18*(1+Assumptions!$K$26*3)+'Investment Build'!$D$29*4)*10000000/(4*G$30*Assumptions!$K$62)))/Assumptions!$K$36,0) -> 0.17311983 | H34: =IFERROR(((Assumptions!$K$36-(Assumptions!$K$36*Assumptions!$K$37+Assumptions!$K$38*Assumptions!$K$39)*(1-LOG(4,2)*Assumptions!$K$28)-Assumptions!$K$36*(Assumptions!$K$40+Assumptions!$K$41+Assumptions!$K$42))-(Assumptions!$K$43*10000000/MIN(4*H$30,Assumptions!$K$33))-(Assumptions!$K$44*Assumptions!$K$36)-(('Investment Build'!$D$18*(1+Assumptions!$K$26*3)+'Investment Build'!$D$29*4)*10000000/(4*H$30*Assumptions!$K$62)))/Assumptions!$K$36,0) -> 0.17557201
B35: 5 | C35: =IFERROR(((Assumptions!$K$36-(Assumptions!$K$36*Assumptions!$K$37+Assumptions!$K$38*Assumptions!$K$39)*(1-LOG(5,2)*Assumptions!$K$28)-Assumptions!$K$36*(Assumptions!$K$40+Assumptions!$K$41+Assumptions!$K$42))-(Assumptions!$K$43*10000000/MIN(5*C$30,Assumptions!$K$33))-(Assumptions!$K$44*Assumptions!$K$36)-(('Investment Build'!$D$18*(1+Assumptions!$K$26*4)+'Investment Build'!$D$29*5)*10000000/(5*C$30*Assumptions!$K$62)))/Assumptions!$K$36,0) -> 0.10100779 | D35: =IFERROR(((Assumptions!$K$36-(Assumptions!$K$36*Assumptions!$K$37+Assumptions!$K$38*Assumptions!$K$39)*(1-LOG(5,2)*Assumptions!$K$28)-Assumptions!$K$36*(Assumptions!$K$40+Assumptions!$K$41+Assumptions!$K$42))-(Assumptions!$K$43*10000000/MIN(5*D$30,Assumptions!$K$33))-(Assumptions!$K$44*Assumptions!$K$36)-(('Investment Build'!$D$18*(1+Assumptions!$K$26*4)+'Investment Build'!$D$29*5)*10000000/(5*D$30*Assumptions!$K$62)))/Assumptions!$K$36,0) -> 0.15394751 | E35: =IFERROR(((Assumptions!$K$36-(Assumptions!$K$36*Assumptions!$K$37+Assumptions!$K$38*Assumptions!$K$39)*(1-LOG(5,2)*Assumptions!$K$28)-Assumptions!$K$36*(Assumptions!$K$40+Assumptions!$K$41+Assumptions!$K$42))-(Assumptions!$K$43*10000000/MIN(5*E$30,Assumptions!$K$33))-(Assumptions!$K$44*Assumptions!$K$36)-(('Investment Build'!$D$18*(1+Assumptions!$K$26*4)+'Investment Build'!$D$29*5)*10000000/(5*E$30*Assumptions!$K$62)))/Assumptions!$K$36,0) -> 0.17159409 | F35: =IFERROR(((Assumptions!$K$36-(Assumptions!$K$36*Assumptions!$K$37+Assumptions!$K$38*Assumptions!$K$39)*(1-LOG(5,2)*Assumptions!$K$28)-Assumptions!$K$36*(Assumptions!$K$40+Assumptions!$K$41+Assumptions!$K$42))-(Assumptions!$K$43*10000000/MIN(5*F$30,Assumptions!$K$33))-(Assumptions!$K$44*Assumptions!$K$36)-(('Investment Build'!$D$18*(1+Assumptions!$K$26*4)+'Investment Build'!$D$29*5)*10000000/(5*F$30*Assumptions!$K$62)))/Assumptions!$K$36,0) -> 0.17720309 | G35: =IFERROR(((Assumptions!$K$36-(Assumptions!$K$36*Assumptions!$K$37+Assumptions!$K$38*Assumptions!$K$39)*(1-LOG(5,2)*Assumptions!$K$28)-Assumptions!$K$36*(Assumptions!$K$40+Assumptions!$K$41+Assumptions!$K$42))-(Assumptions!$K$43*10000000/MIN(5*G$30,Assumptions!$K$33))-(Assumptions!$K$44*Assumptions!$K$36)-(('Investment Build'!$D$18*(1+Assumptions!$K$26*4)+'Investment Build'!$D$29*5)*10000000/(5*G$30*Assumptions!$K$62)))/Assumptions!$K$36,0) -> 0.18174066 | H35: =IFERROR(((Assumptions!$K$36-(Assumptions!$K$36*Assumptions!$K$37+Assumptions!$K$38*Assumptions!$K$39)*(1-LOG(5,2)*Assumptions!$K$28)-Assumptions!$K$36*(Assumptions!$K$40+Assumptions!$K$41+Assumptions!$K$42))-(Assumptions!$K$43*10000000/MIN(5*H$30,Assumptions!$K$33))-(Assumptions!$K$44*Assumptions!$K$36)-(('Investment Build'!$D$18*(1+Assumptions!$K$26*4)+'Investment Build'!$D$29*5)*10000000/(5*H$30*Assumptions!$K$62)))/Assumptions!$K$36,0) -> 0.18400945
B36: 6 | C36: =IFERROR(((Assumptions!$K$36-(Assumptions!$K$36*Assumptions!$K$37+Assumptions!$K$38*Assumptions!$K$39)*(1-LOG(6,2)*Assumptions!$K$28)-Assumptions!$K$36*(Assumptions!$K$40+Assumptions!$K$41+Assumptions!$K$42))-(Assumptions!$K$43*10000000/MIN(6*C$30,Assumptions!$K$33))-(Assumptions!$K$44*Assumptions!$K$36)-(('Investment Build'!$D$18*(1+Assumptions!$K$26*5)+'Investment Build'!$D$29*6)*10000000/(6*C$30*Assumptions!$K$62)))/Assumptions!$K$36,0) -> 0.11895795 | D36: =IFERROR(((Assumptions!$K$36-(Assumptions!$K$36*Assumptions!$K$37+Assumptions!$K$38*Assumptions!$K$39)*(1-LOG(6,2)*Assumptions!$K$28)-Assumptions!$K$36*(Assumptions!$K$40+Assumptions!$K$41+Assumptions!$K$42))-(Assumptions!$K$43*10000000/MIN(6*D$30,Assumptions!$K$33))-(Assumptions!$K$44*Assumptions!$K$36)-(('Investment Build'!$D$18*(1+Assumptions!$K$26*5)+'Investment Build'!$D$29*6)*10000000/(6*D$30*Assumptions!$K$62)))/Assumptions!$K$36,0) -> 0.16614477 | E36: =IFERROR(((Assumptions!$K$36-(Assumptions!$K$36*Assumptions!$K$37+Assumptions!$K$38*Assumptions!$K$39)*(1-LOG(6,2)*Assumptions!$K$28)-Assumptions!$K$36*(Assumptions!$K$40+Assumptions!$K$41+Assumptions!$K$42))-(Assumptions!$K$43*10000000/MIN(6*E$30,Assumptions!$K$33))-(Assumptions!$K$44*Assumptions!$K$36)-(('Investment Build'!$D$18*(1+Assumptions!$K$26*5)+'Investment Build'!$D$29*6)*10000000/(6*E$30*Assumptions!$K$62)))/Assumptions!$K$36,0) -> 0.18008799 | F36: =IFERROR(((Assumptions!$K$36-(Assumptions!$K$36*Assumptions!$K$37+Assumptions!$K$38*Assumptions!$K$39)*(1-LOG(6,2)*Assumptions!$K$28)-Assumptions!$K$36*(Assumptions!$K$40+Assumptions!$K$41+Assumptions!$K$42))-(Assumptions!$K$43*10000000/MIN(6*F$30,Assumptions!$K$33))-(Assumptions!$K$44*Assumptions!$K$36)-(('Investment Build'!$D$18*(1+Assumptions!$K$26*5)+'Investment Build'!$D$29*6)*10000000/(6*F$30*Assumptions!$K$62)))/Assumptions!$K$36,0) -> 0.18438103 | G36: =IFERROR(((Assumptions!$K$36-(Assumptions!$K$36*Assumptions!$K$37+Assumptions!$K$38*Assumptions!$K$39)*(1-LOG(6,2)*Assumptions!$K$28)-Assumptions!$K$36*(Assumptions!$K$40+Assumptions!$K$41+Assumptions!$K$42))-(Assumptions!$K$43*10000000/MIN(6*G$30,Assumptions!$K$33))-(Assumptions!$K$44*Assumptions!$K$36)-(('Investment Build'!$D$18*(1+Assumptions!$K$26*5)+'Investment Build'!$D$29*6)*10000000/(6*G$30*Assumptions!$K$62)))/Assumptions!$K$36,0) -> 0.18867407 | H36: =IFERROR(((Assumptions!$K$36-(Assumptions!$K$36*Assumptions!$K$37+Assumptions!$K$38*Assumptions!$K$39)*(1-LOG(6,2)*Assumptions!$K$28)-Assumptions!$K$36*(Assumptions!$K$40+Assumptions!$K$41+Assumptions!$K$42))-(Assumptions!$K$43*10000000/MIN(6*H$30,Assumptions!$K$33))-(Assumptions!$K$44*Assumptions!$K$36)-(('Investment Build'!$D$18*(1+Assumptions!$K$26*5)+'Investment Build'!$D$29*6)*10000000/(6*H$30*Assumptions!$K$62)))/Assumptions!$K$36,0) -> 0.19082059
B37: 7 | C37: =IFERROR(((Assumptions!$K$36-(Assumptions!$K$36*Assumptions!$K$37+Assumptions!$K$38*Assumptions!$K$39)*(1-LOG(7,2)*Assumptions!$K$28)-Assumptions!$K$36*(Assumptions!$K$40+Assumptions!$K$41+Assumptions!$K$42))-(Assumptions!$K$43*10000000/MIN(7*C$30,Assumptions!$K$33))-(Assumptions!$K$44*Assumptions!$K$36)-(('Investment Build'!$D$18*(1+Assumptions!$K$26*6)+'Investment Build'!$D$29*7)*10000000/(7*C$30*Assumptions!$K$62)))/Assumptions!$K$36,0) -> 0.13262502 | D37: =IFERROR(((Assumptions!$K$36-(Assumptions!$K$36*Assumptions!$K$37+Assumptions!$K$38*Assumptions!$K$39)*(1-LOG(7,2)*Assumptions!$K$28)-Assumptions!$K$36*(Assumptions!$K$40+Assumptions!$K$41+Assumptions!$K$42))-(Assumptions!$K$43*10000000/MIN(7*D$30,Assumptions!$K$33))-(Assumptions!$K$44*Assumptions!$K$36)-(('Investment Build'!$D$18*(1+Assumptions!$K$26*6)+'Investment Build'!$D$29*7)*10000000/(7*D$30*Assumptions!$K$62)))/Assumptions!$K$36,0) -> 0.17570261 | E37: =IFERROR(((Assumptions!$K$36-(Assumptions!$K$36*Assumptions!$K$37+Assumptions!$K$38*Assumptions!$K$39)*(1-LOG(7,2)*Assumptions!$K$28)-Assumptions!$K$36*(Assumptions!$K$40+Assumptions!$K$41+Assumptions!$K$42))-(Assumptions!$K$43*10000000/MIN(7*E$30,Assumptions!$K$33))-(Assumptions!$K$44*Assumptions!$K$36)-(('Investment Build'!$D$18*(1+Assumptions!$K$26*6)+'Investment Build'!$D$29*7)*10000000/(7*E$30*Assumptions!$K$62)))/Assumptions!$K$36,0) -> 0.18623527 | F37: =IFERROR(((Assumptions!$K$36-(Assumptions!$K$36*Assumptions!$K$37+Assumptions!$K$38*Assumptions!$K$39)*(1-LOG(7,2)*Assumptions!$K$28)-Assumptions!$K$36*(Assumptions!$K$40+Assumptions!$K$41+Assumptions!$K$42))-(Assumptions!$K$43*10000000/MIN(7*F$30,Assumptions!$K$33))-(Assumptions!$K$44*Assumptions!$K$36)-(('Investment Build'!$D$18*(1+Assumptions!$K$26*6)+'Investment Build'!$D$29*7)*10000000/(7*F$30*Assumptions!$K$62)))/Assumptions!$K$36,0) -> 0.19035365 | G37: =IFERROR(((Assumptions!$K$36-(Assumptions!$K$36*Assumptions!$K$37+Assumptions!$K$38*Assumptions!$K$39)*(1-LOG(7,2)*Assumptions!$K$28)-Assumptions!$K$36*(Assumptions!$K$40+Assumptions!$K$41+Assumptions!$K$42))-(Assumptions!$K$43*10000000/MIN(7*G$30,Assumptions!$K$33))-(Assumptions!$K$44*Assumptions!$K$36)-(('Investment Build'!$D$18*(1+Assumptions!$K$26*6)+'Investment Build'!$D$29*7)*10000000/(7*G$30*Assumptions!$K$62)))/Assumptions!$K$36,0) -> 0.19447202 | H37: =IFERROR(((Assumptions!$K$36-(Assumptions!$K$36*Assumptions!$K$37+Assumptions!$K$38*Assumptions!$K$39)*(1-LOG(7,2)*Assumptions!$K$28)-Assumptions!$K$36*(Assumptions!$K$40+Assumptions!$K$41+Assumptions!$K$42))-(Assumptions!$K$43*10000000/MIN(7*H$30,Assumptions!$K$33))-(Assumptions!$K$44*Assumptions!$K$36)-(('Investment Build'!$D$18*(1+Assumptions!$K$26*6)+'Investment Build'!$D$29*7)*10000000/(7*H$30*Assumptions!$K$62)))/Assumptions!$K$36,0) -> 0.19653121
B38: 8 | C38: =IFERROR(((Assumptions!$K$36-(Assumptions!$K$36*Assumptions!$K$37+Assumptions!$K$38*Assumptions!$K$39)*(1-LOG(8,2)*Assumptions!$K$28)-Assumptions!$K$36*(Assumptions!$K$40+Assumptions!$K$41+Assumptions!$K$42))-(Assumptions!$K$43*10000000/MIN(8*C$30,Assumptions!$K$33))-(Assumptions!$K$44*Assumptions!$K$36)-(('Investment Build'!$D$18*(1+Assumptions!$K$26*7)+'Investment Build'!$D$29*8)*10000000/(8*C$30*Assumptions!$K$62)))/Assumptions!$K$36,0) -> 0.14350865 | D38: =IFERROR(((Assumptions!$K$36-(Assumptions!$K$36*Assumptions!$K$37+Assumptions!$K$38*Assumptions!$K$39)*(1-LOG(8,2)*Assumptions!$K$28)-Assumptions!$K$36*(Assumptions!$K$40+Assumptions!$K$41+Assumptions!$K$42))-(Assumptions!$K$43*10000000/MIN(8*D$30,Assumptions!$K$33))-(Assumptions!$K$44*Assumptions!$K$36)-(('Investment Build'!$D$18*(1+Assumptions!$K$26*7)+'Investment Build'!$D$29*8)*10000000/(8*D$30*Assumptions!$K$62)))/Assumptions!$K$36,0) -> 0.18350433 | E38: =IFERROR(((Assumptions!$K$36-(Assumptions!$K$36*Assumptions!$K$37+Assumptions!$K$38*Assumptions!$K$39)*(1-LOG(8,2)*Assumptions!$K$28)-Assumptions!$K$36*(Assumptions!$K$40+Assumptions!$K$41+Assumptions!$K$42))-(Assumptions!$K$43*10000000/MIN(8*E$30,Assumptions!$K$33))-(Assumptions!$K$44*Assumptions!$K$36)-(('Investment Build'!$D$18*(1+Assumptions!$K$26*7)+'Investment Build'!$D$29*8)*10000000/(8*E$30*Assumptions!$K$62)))/Assumptions!$K$36,0) -> 0.19147908 | F38: =IFERROR(((Assumptions!$K$36-(Assumptions!$K$36*Assumptions!$K$37+Assumptions!$K$38*Assumptions!$K$39)*(1-LOG(8,2)*Assumptions!$K$28)-Assumptions!$K$36*(Assumptions!$K$40+Assumptions!$K$41+Assumptions!$K$42))-(Assumptions!$K$43*10000000/MIN(8*F$30,Assumptions!$K$33))-(Assumptions!$K$44*Assumptions!$K$36)-(('Investment Build'!$D$18*(1+Assumptions!$K$26*7)+'Investment Build'!$D$29*8)*10000000/(8*F$30*Assumptions!$K$62)))/Assumptions!$K$36,0) -> 0.19546645 | G38: =IFERROR(((Assumptions!$K$36-(Assumptions!$K$36*Assumptions!$K$37+Assumptions!$K$38*Assumptions!$K$39)*(1-LOG(8,2)*Assumptions!$K$28)-Assumptions!$K$36*(Assumptions!$K$40+Assumptions!$K$41+Assumptions!$K$42))-(Assumptions!$K$43*10000000/MIN(8*G$30,Assumptions!$K$33))-(Assumptions!$K$44*Assumptions!$K$36)-(('Investment Build'!$D$18*(1+Assumptions!$K$26*7)+'Investment Build'!$D$29*8)*10000000/(8*G$30*Assumptions!$K$62)))/Assumptions!$K$36,0) -> 0.19945382 | H38: =IFERROR(((Assumptions!$K$36-(Assumptions!$K$36*Assumptions!$K$37+Assumptions!$K$38*Assumptions!$K$39)*(1-LOG(8,2)*Assumptions!$K$28)-Assumptions!$K$36*(Assumptions!$K$40+Assumptions!$K$41+Assumptions!$K$42))-(Assumptions!$K$43*10000000/MIN(8*H$30,Assumptions!$K$33))-(Assumptions!$K$44*Assumptions!$K$36)-(('Investment Build'!$D$18*(1+Assumptions!$K$26*7)+'Investment Build'!$D$29*8)*10000000/(8*H$30*Assumptions!$K$62)))/Assumptions!$K$36,0) -> 0.20144751
A40: Grid 3 excludes capacity depreciation, so it measures the return on the platform decision itself rather than on the plant. Negative cells are programmes that never earn back their engineering at that volume. Note the shape: below roughly 50,000 units per model, adding models rescues the economics far more than adding volume does.

Sheet Real-World Platforms
A1: REAL-WORLD PLATFORMS | Disclosed and derived figures for actual architectures
A2: Green 'Reported' rows are company or survey disclosures. Grey 'Derived' figures are arithmetic on reported numbers. No estimates are introduced on this sheet.
A5: OEM | B5: Platform / programme | C5: Region | D5: Type | E5: Disclosed investment | F5: What the figure covers | G5: Models on platform | H5: Volume reference | I5: Basis
A6: --- PASSENGER CARS: GLOBAL ---
A7: Volkswagen Group | B7: MQB (Modularer Querbaukasten) | C7: Global | D7: ICE / multi-energy | E7: c.USD 8bn (platform + cars); c.EUR 50bn cited for the wider modular toolkit incl. plant conversion | F7: The gap between the two figures is the point: architecture engineering vs total capital deployed to make plants MQB-capable | G7: Golf, A3, Leon, Octavia, Tiguan, Passat and 30+ others | H7: 45m+ vehicles produced to 2023 | I7: Reported
A8: Volkswagen Group | B8: MQB - claimed benefit | C8: Global | D8: ICE | E8: Morgan Stanley estimated up to USD 19bn p.a. of savings by 2019 | F8: VW targeted c.20% component cost saving and c.20% production time reduction | G8: n/a | H8: n/a | I8: Reported (third-party)
A9: Renault-Nissan Alliance | B9: CMF-A (Kwid / redi-GO) | C9: India | D9: ICE | E9: EUR 400m (c.USD 450m) total | F9: Programme chief G. Detourbet: covered a wholly new modular platform, a new engine, a new gearbox AND a 300,000 unit/yr plant | G9: Kwid, redi-GO, Triber, Magnite (CMF-A+) | H9: c.319k units global output forecast 2019 | I9: Reported
A10: Renault-Nissan Alliance | B10: Kwid - India programme | C10: India | D10: ICE | E10: INR 2,000-3,000cr cited for design, development and manufacturing | F10: Wide public range; the EUR 400m figure above is the more precise disclosure | G10: Kwid family | H10: 98% localisation at launch | I10: Reported
A11: Ford | B11: Universal EV Platform | C11: US | D11: BEV | E11: USD 5bn | F11: Covers the platform AND the Universal EV Production System | G11: Affordable EV family | H11: n/a | I11: Reported
A12: Renault-Nissan-Mitsubishi | B12: 5 common EV platforms | C12: Global | D12: BEV | E12: EUR 23bn over 5 years | F12: Whole EV and connected-vehicle roadmap, not one platform | G12: 35 new EVs by 2030; 90% on 5 platforms | H12: CMF-EV targeted 1.5m units p.a.; CMF-BEV c.250k p.a. | I12: Reported
A13: Hyundai Motor Group | B13: E-GMP | C13: Global | D13: BEV | E13: Not separately disclosed | F13: Group announced KRW 109.4tn (c.USD 85bn) over 10 years to 2032, incl. the IMA successor to E-GMP | G13: Ioniq 5, Ioniq 6, EV6, EV9 and others | H13: n/a | I13: Reported (group level)
A14: --- PASSENGER CARS: INDIA ---
A15: Mahindra & Mahindra | B15: INGLO | C15: India | D15: BEV | E15: INR 4,500cr | F15: Company disclosure: powertrain development, TWO product top hats, software and tech, AND manufacturing capacity. Part of the INR 16,000cr F22-F27 cycle | G15: BE 6, XEV 9e, XEV 9S | H15: Capacity target 120k units p.a. by FY26 on INR 6,500cr | I15: Reported
A16: Mahindra & Mahindra | B16: Dedicated BEV plant, Pune | C16: India | D16: BEV | E16: INR 10,000cr over 7-8 years | F16: Plant only | G16: Born Electric range | H16: 200,000 EV units p.a. design capacity | I16: Reported
A17: Tata Motors | B17: ALFA / OMEGA / acti.ev | C17: India | D17: ICE + BEV | E17: INR 35,000cr over 5 years (PV + EV, all-in) | F17: Not platform-specific. Company is consolidating c.6 platforms to 2-3. Avinya uses JLR EMA under licence rather than in-house build | G17: Altroz, Punch, Nexon (ALFA); Harrier, Safari (OMEGA) | H17: n/a | I17: Reported
A18: Tata Motors / JLR | B18: Ranipet plant (EMA + Tata EVs) | C18: India | D18: BEV | E18: INR 9,000cr | F18: Greenfield plant; MoU to first vehicle in 17 months | G18: EMA-based JLR and Tata EVs | H18: 250,000 units p.a. at full capacity | I18: Reported
A19: Maruti Suzuki | B19: HEARTECT | C19: India | D19: ICE | E19: Not disclosed | F19: The clearest Indian example of platform leverage: one architecture, 8-9 nameplates | G19: Swift, Dzire, Baleno, WagonR, Ignis, S-Presso, Ertiga, XL6, Fronx | H19: India's highest-volume car architecture | I19: Reported (model count)
A20: Maruti Suzuki | B20: Swift (2011 generation) | C20: India | D20: ICE | E20: INR 550cr | F20: Management disclosure: invested by Maruti AND its suppliers to develop the new car, at 95% localisation. A useful anchor for what a single India top hat costs | G20: One nameplate | H20: n/a | I20: Reported
A21: Maruti Suzuki | B21: Khoraj plant, Gujarat | C21: India | D21: ICE + BEV | E21: c.INR 35,000cr | F21: Four units of 250k each; production from FY29 | G21: n/a | H21: 1,000,000 units p.a. | I21: Reported
A22: Toyota Kirloskar | B22: Bidadi third plant | C22: India | D22: ICE / hybrid | E22: INR 3,300cr | F22: Plant only | G22: n/a | H22: 100,000 units p.a. added | I22: Reported
A23: JSW MG Motor | B23: Capacity expansion | C23: India | D23: BEV + hybrid | E23: USD 330-440m (INR 3,000-4,000cr) | F23: Plant only | G23: n/a | H23: to c.300,000 units p.a. | I23: Reported
A24: --- TWO-WHEELERS: INDIA ---
A25: Ola Electric | B25: Gen 3 architecture | C25: India | D25: BEV | E25: c.INR 2,000cr | F25: Company disclosure: the platform R&D bill, now 'stabilised into a mature Gen3 architecture'. Management states further products on it require 'limited incremental R&D' - the sharing argument in the company's own words | G25: S1 X, S1 X+, S1 Pro, S1 Pro+, Roadster X, Roadster X+ | H25: Gen 3 delivered c.11% cost reduction vs Gen 2 | I25: Reported
A26: Ola Electric | B26: Auto segment break-even | C26: India | D26: BEV | E26: n/a | F26: At a steady-state opex of c.INR 250-300cr per quarter, management guides EBITDA break-even at c.15,000 units per month (down from an earlier c.25,000 and c.50,000) | G26: n/a | H26: c.180,000 units p.a. break-even run-rate | I26: Reported
A27: Ather Energy | B27: 450 and Rizta platforms | C27: India | D27: BEV | E27: R&D: INR 101cr FY22, INR 192cr FY23, INR 237cr FY24, INR 340-350cr FY25, INR 210cr H1FY26 | F27: Cumulative R&D of roughly INR 1,100cr has funded two scooter platforms plus the Atherstack software and Ather Grid. R&D was 15% of revenue in 9M FY25; 46% of headcount sits in R&D | G27: Ather 450 line, Rizta line | H27: 303 patents filed, 201 designs registered | I27: Reported
A28: Bajaj Auto | B28: Chetak Technology, Akurdi | C28: India | D28: BEV | E28: c.INR 750cr including vendor partners | F28: Dedicated EV plant co-located with an R&D centre | G28: Chetak family | H28: 500,000 units p.a. capacity | I28: Reported
A29: Royal Enfield (Eicher) | B29: FY27 capex plan | C29: India | D29: ICE + BEV | E29: INR 2,200cr for FY27 | F29: c.INR 1,000cr to capacity, the remaining c.INR 1,200cr to new product development and EV programmes. Useful as an annual product-development run-rate for a c.1.2m unit premium 2W business | G29: J-platform (Classic, Meteor, Hunter, Bullet); 650 twins | H29: 12.27 lakh motorcycles sold FY26 | I29: Reported
A30: Royal Enfield (Eicher) | B30: Cheyyar brownfield expansion | C30: India | D30: ICE | E30: INR 958cr | F30: Brownfield capacity only: 14.6 lakh to 20 lakh units p.a. | G30: n/a | H30: +540,000 units p.a. | I30: Reported
A31: Royal Enfield (Eicher) | B31: Tada greenfield plant, Andhra Pradesh | C31: India | D31: ICE | E31: INR 2,500cr (INR 1,225cr phase 1) | F31: Greenfield plant - note the per-unit cost is c.3x the brownfield figure above | G31: n/a | H31: +450,000 units p.a. by FY30 | I31: Reported
A32: Hero MotoCorp | B32: Harley-Davidson X440 platform | C32: India | D32: ICE | E32: Not disclosed | F32: Sharing across brands: the Hero Mavrick 440 is built on the Harley-Davidson X440 platform, and a larger XPulse is being developed on it | G32: X440, Mavrick 440, XPulse (in development) | H32: n/a | I32: Reported (product fact)
A33: Bajaj Auto | B33: In-house electric motorcycle platform | C33: India | D33: BEV | E33: Not disclosed | F33: Announced Q2 FY26: an all-new in-house platform spanning entry commuter to high-performance, leveraging Chetak Technology | G33: Pipeline | H33: n/a | I33: Reported (announcement)
A34: --- DERIVED BENCHMARKS ---
A35: Cars, India | B35: Capacity capex per unit of annual capacity | C35: India | D35: Both | E35: INR 330,000 - 360,000 per unit | F35: Toyota Bidadi INR 3,300cr / 100k = INR 330,000. Maruti Khoraj INR 35,000cr / 1.0m = INR 350,000. Tata-JLR Ranipet INR 9,000cr / 250k = INR 360,000 | G35: n/a | H35: n/a | I35: Derived
A36: 2W, India | B36: Capacity capex per unit of annual capacity | C36: India | D36: Both | E36: INR 15,000 - 56,000 per unit | F36: Bajaj CTL Akurdi INR 750cr / 500k = INR 15,000. RE Cheyyar (brownfield) INR 958cr / 540k = INR 17,700. RE Tada (greenfield) INR 2,500cr / 450k = INR 55,600 | G36: n/a | H36: n/a | I36: Derived
A37: Cars vs 2W | B37: Capacity intensity ratio | C37: India | D37: Both | E37: c.13x | F37: A car plant costs roughly thirteen times a two-wheeler plant per unit of annual capacity. The ASP ratio is closer to 10x, so cars are the more capital-intensive of the two even after adjusting for price | G37: n/a | H37: n/a | I37: Derived
A38: Global benchmark | B38: New vehicle programme cost | C38: Global | D38: ICE | E38: From c.USD 1bn | F38: IHS: a new model programme starts around USD 1bn in developed markets; a new plant can add another USD 1-2bn. The CMF-A figure above shows what an India-led, cost-targeted programme achieves against that benchmark | G38: n/a | H38: n/a | I38: Reported (third-party)
A39: Global benchmark | B39: BEV battery pack price | C39: Global | D39: BEV | E39: USD 99/kWh (BEV packs, 2025) | F39: BNEF 2025 survey. All-segment average USD 108/kWh, -8% y/y. LFP packs USD 81/kWh. China USD 84/kWh; North America +44% and Europe +56% versus China | G39: n/a | H39: n/a | I39: Reported (BNEF)
A40: Global benchmark | B40: EV vs ICE production cost | C40: Global | D40: Both | E40: EVs c.45% more expensive to build | F40: Oliver Wyman: for a C-segment car, ICE total build cost c.EUR 13,900. EVs save on assembly and drivetrain but the powertrain + e-drive + battery cluster is c.EUR 1,500 more, and E/E is c.EUR 2,000 more | G40: n/a | H40: n/a | I40: Reported (third-party)

Sheet Sources
A1: SOURCES | Every reported figure used in this model
A4: # | B4: Data point | C4: Figure as reported | D4: Publisher / source | E4: URL
A5: 1 | B5: VW MQB development cost | C5: c.USD 8bn spent developing the platform and the cars using it | D5: HandWiki / Jalopnik summary | E5: https://handwiki.org/wiki/Engineering:Volkswagen_Group_MQB_platform
A6: 2 | B6: VW modular toolkit total outlay | C6: c.EUR 50bn cited by M. Winterkorn across four years, incl. plant preparation | D6: Autocar UK | E6: https://www.autocar.co.uk/car-news/industry/vw-could-sell-50bn-mqb-platform
A7: 3 | B7: MQB savings estimate | C7: Morgan Stanley: up to USD 19bn p.a. of savings by 2019; c.20% component cost target | D7: Automotive Manufacturing Solutions | E7: https://www.automotivemanufacturingsolutions.com/strategy/vws-platforms-to-perform/541419
A8: 4 | B8: MQB cumulative output | C8: 45m+ vehicles produced on MQB to 2023 | D8: Grokipedia (compiled) | E8: https://grokipedia.com/page/Volkswagen_Group_MQB_platform
A9: 5 | B9: CMF-A programme cost | C9: EUR 400m total for a new modular platform, new engine, new gearbox and a 300k unit/yr plant (G. Detourbet) | D9: Forbes | E9: https://www.forbes.com/sites/bertelschmitt/2017/05/22/how-can-a-4100-renault-kwid-make-a-profit-the-answer-is-here/
A10: 6 | B10: Kwid India investment | C10: c.INR 2,000cr development investment cited at unveiling | D10: Business Today | E10: https://www.businesstoday.in/sectors/auto/renault-unveils-kwid-in-india-priced-up-to-rs-four-lakh/story/219575.html
A11: 7 | B11: Renault-Nissan India capacity cost | C11: INR 15-20bn to add 300,000 units of annual capacity | D11: S&P Global AutoTechInsight | E11: https://autotechinsight.spglobal.com/news/20252/renault-nissan-plans-to-add-300000-units-of-capacity-in-india-for-new-entry-level-cars-
A12: 8 | B12: Alliance EV roadmap | C12: EUR 23bn over five years; 35 EVs by 2030; 90% on five common platforms | D12: S&P Global AutoTechInsight | E12: https://autotechinsight.spglobal.com/news/5264233/renault-nissan-mitsubishi-announce-a-shared-2030-roadmap-plan-to-invest-usd2571-billion
A13: 9 | B13: Hyundai Motor Group investment | C13: KRW 109.4tn (USD 85bn+) over ten years to 2032, incl. the IMA successor to E-GMP | D13: S&P Global AutoTechInsight | E13: https://autotechinsight.spglobal.com/news/5271176/hyundai-motor-group-to-invest-over-85-billion-on-new-technologies-by-2032
A14: 10 | B14: Ford Universal EV Platform | C14: USD 5bn for the platform and the Universal EV Production System | D14: Engineer Live | E14: https://www.engineerlive.com/content/global-race-reinvent-electric-vehicle-powertrain-technologies
A15: 11 | B15: M&M INGLO investment | C15: INR 4,500cr covering powertrain development, two product top hats, software and tech, and manufacturing capacity; part of the INR 16,000cr F22-F27 cycle | D15: Mahindra press release | E15: https://www.mahindra.com/news-room/press-release/en/Mahindra-launches-BE-6e-and-XEV-9e
A16: 12 | B16: M&M EV capacity plan | C16: INR 6,500cr investment; capacity to 120,000 units p.a. by FY26 (XEV 9S launch) | D16: ScanX / company disclosure | E16: https://scanx.trade/stock-market-news/stocks/mahindra-unveils-xev9s-india-s-first-electric-7-seater-suv-starting-at-19-95-lakh/25764461
... A40: 36 | B40: India auto PLI | C40: Auto PLI allocation doubled to INR 5,940cr in Union Budget 2026-27; INR 1,350cr disbursed Dec-2025 | D40: IBEF | E40: https://www.ibef.org/industry/india-automobiles
